Workbook

Sheet Conciliacao
A1: Data | B1: Extrato Zig (Saques) | C1: Faturam Dinheiro | D1: Receitas Extraord | E1: Eventos | F1: Entradas Mútuos | G1: Desbloqueios Judiciais | H1: Extrato Bancário (Crédito) | I1: Diferenças (Contas a Receber) | J1: Custos Sem Parcelamento | K1: Custos Com Parcelamento | L1: Saídas Mútuos | M1: Bloqueios Judiciais | N1: Extrato Bancário (Débito) | O1: Diferenças (Contas a Pagar) | P1: Ajustes Conciliação | Q1: Conciliação | BE1: Coluna Auxiliar Data | BF1: Coluna Auxiliar Data 2 | BG1: Coluna Auxiliar Data 3 | BH1: Coluna Auxiliar Data 4
A2: 45658 | B2: =-SUMIFS(df_extrato_zig!G:G,df_extrato_zig!E:E,Conciliacao!A2,df_extrato_zig!D:D,"Saque")-SUMIFS(df_extrato_zig!G:G,df_extrato_zig!E:E,Conciliacao!A2,df_extrato_zig!D:D,"Antecipação") | C2: =SUMIFS(df_extrato_zig!E:E,df_extrato_zig!L:L,Conciliacao!A2,df_extrato_zig!F:F,"DINHEIRO") | D2: =SUMIFS(view_parc_agrup!H:H,view_parc_agrup!G:G,Conciliacao!A2) | E2: =SUMIFS(df_eventos!F:F,df_eventos!H:H,Conciliacao!A2) | F2: =SUMIFS(df_mutuos!M:M,df_mutuos!B:B,Conciliacao!A2) | G2: =SUMIFS(df_bloqueios_judiciais!G:G,df_bloqueios_judiciais!D:D,Conciliacao!A2,df_bloqueios_judiciais!G:G,">0") | H2: =SUMIFS(df_extratos!I:I,df_extratos!F:F,Conciliacao!BE2,df_extratos!G:G,"CREDITO")+SUMIFS(df_extratos!I:I,df_extratos!F:F,Conciliacao!A2,df_extratos!G:G,"CREDITO")+SUMIFS(df_extratos!I:I,df_extratos!F:F,Conciliacao!BF2,df_extratos!G:G,"CREDITO")+SUMIFS(df_extratos!I:I,df_extratos!F:F,Conciliacao!BG2,df_extratos!G:G,"CREDITO")+SUMIFS(df_extratos!I:I,df_extratos!F:F,Conciliacao!BH2,df_extratos!G:G,"CREDITO") | I2: =H2-SUM(B2:G2) | J2: =SUMIFS(df_blueme_sem_parcelamento!E:E,df_blueme_sem_parcelamento!H:H,Conciliacao!A2)*(-1) | K2: =SUMIFS(df_blueme_com_parcelamento!J:J,df_blueme_com_parcelamento!M:M,Conciliacao!A2)*(-1) | L2: =SUMIFS(df_mutuos!N:N,df_mutuos!B:B,Conciliacao!A2)*(-1) | M2: =SUMIFS(df_bloqueios_judiciais!E:E,df_bloqueios_judiciais!D:D,Conciliacao!A2,df_bloqueios_judiciais!E:E,"<0") | N2: =SUMIFS(df_extratos!I:I,df_extratos!F:F,Conciliacao!BE2,df_extratos!G:G,"DEBITO")+SUMIFS(df_extratos!I:I,df_extratos!F:F,Conciliacao!A2,df_extratos!G:G,"DEBITO")+SUMIFS(df_extratos!I:I,df_extratos!F:F,Conciliacao!BF2,df_extratos!G:G,"DEBITO")+SUMIFS(df_extratos!I:I,df_extratos!F:F,Conciliacao!BG2,df_extratos!G:G,"DEBITO")+SUMIFS(df_extratos!I:I,df_extratos!F:F,Conciliacao!BH2,df_extratos!G:G,"DEBITO") | O2: =N2-SUM(J2:M2) | P2: =SUMIFS(df_ajustes_conciliaco!D:D,df_ajustes_conciliaco!C:C,Conciliacao!A2) | Q2: =O2+I2-P2 | BE2: 45658.5 | BF2: 45658.125 | BG2: 45658.542 | BH2: 45658.625
A3: =A2+1 | B3: =-SUMIFS(df_extrato_zig!G:G,df_extrato_zig!E:E,Conciliacao!A3,df_extrato_zig!D:D,"Saque")-SUMIFS(df_extrato_zig!G:G,df_extrato_zig!E:E,Conciliacao!A3,df_extrato_zig!D:D,"Antecipação") | C3: =SUMIFS(df_extrato_zig!E:E,df_extrato_zig!L:L,Conciliacao!A3,df_extrato_zig!F:F,"DINHEIRO") | D3: =SUMIFS(view_parc_agrup!H:H,view_parc_agrup!G:G,Conciliacao!A3) | E3: =SUMIFS(df_eventos!F:F,df_eventos!H:H,Conciliacao!A3) | F3: =SUMIFS(df_mutuos!M:M,df_mutuos!B:B,Conciliacao!A3) | G3: =SUMIFS(df_bloqueios_judiciais!G:G,df_bloqueios_judiciais!D:D,Conciliacao!A3,df_bloqueios_judiciais!G:G,">0") | H3: =SUMIFS(df_extratos!I:I,df_extratos!F:F,Conciliacao!BE3,df_extratos!G:G,"CREDITO")+SUMIFS(df_extratos!I:I,df_extratos!F:F,Conciliacao!A3,df_extratos!G:G,"CREDITO")+SUMIFS(df_extratos!I:I,df_extratos!F:F,Conciliacao!BF3,df_extratos!G:G,"CREDITO")+SUMIFS(df_extratos!I:I,df_extratos!F:F,Conciliacao!BG3,df_extratos!G:G,"CREDITO")+SUMIFS(df_extratos!I:I,df_extratos!F:F,Conciliacao!BH3,df_extratos!G:G,"CREDITO") | I3: =H3-SUM(B3:G3) | J3: =SUMIFS(df_blueme_sem_parcelamento!E:E,df_blueme_sem_parcelamento!H:H,Conciliacao!A3)*(-1) | K3: =SUMIFS(df_blueme_com_parcelamento!J:J,df_blueme_com_parcelamento!M:M,Conciliacao!A3)*(-1) | L3: =SUMIFS(df_mutuos!N:N,df_mutuos!B:B,Conciliacao!A3)*(-1) | M3: =SUMIFS(df_bloqueios_judiciais!E:E,df_bloqueios_judiciais!D:D,Conciliacao!A3,df_bloqueios_judiciais!E:E,"<0") | N3: =SUMIFS(df_extratos!I:I,df_extratos!F:F,Conciliacao!BE3,df_extratos!G:G,"DEBITO")+SUMIFS(df_extratos!I:I,df_extratos!F:F,Conciliacao!A3,df_extratos!G:G,"DEBITO")+SUMIFS(df_extratos!I:I,df_extratos!F:F,Conciliacao!BF3,df_extratos!G:G,"DEBITO")+SUMIFS(df_extratos!I:I,df_extratos!F:F,Conciliacao!BG3,df_extratos!G:G,"DEBITO")+SUMIFS(df_extratos!I:I,df_extratos!F:F,Conciliacao!BH3,df_extratos!G:G,"DEBITO") | O3: =N3-SUM(J3:M3) | P3: =SUMIFS(df_ajustes_conciliaco!D:D,df_ajustes_conciliaco!C:C,Conciliacao!A3) | Q3: =O3+I3-P3 | BE3: 45659.5 | BF3: 45659.125 | BG3: 45659.542 | BH3: 45659.625
A4: =A3+1 | B4: =-SUMIFS(df_extrato_zig!G:G,df_extrato_zig!E:E,Conciliacao!A4,df_extrato_zig!D:D,"Saque")-SUMIFS(df_extrato_zig!G:G,df_extrato_zig!E:E,Conciliacao!A4,df_extrato_zig!D:D,"Antecipação") | C4: =SUMIFS(df_extrato_zig!E:E,df_extrato_zig!L:L,Conciliacao!A4,df_extrato_zig!F:F,"DINHEIRO") | D4: =SUMIFS(view_parc_agrup!H:H,view_parc_agrup!G:G,Conciliacao!A4) | E4: =SUMIFS(df_eventos!F:F,df_eventos!H:H,Conciliacao!A4) | F4: =SUMIFS(df_mutuos!M:M,df_mutuos!B:B,Conciliacao!A4) | G4: =SUMIFS(df_bloqueios_judiciais!G:G,df_bloqueios_judiciais!D:D,Conciliacao!A4,df_bloqueios_judiciais!G:G,">0") | H4: =SUMIFS(df_extratos!I:I,df_extratos!F:F,Conciliacao!BE4,df_extratos!G:G,"CREDITO")+SUMIFS(df_extratos!I:I,df_extratos!F:F,Conciliacao!A4,df_extratos!G:G,"CREDITO")+SUMIFS(df_extratos!I:I,df_extratos!F:F,Conciliacao!BF4,df_extratos!G:G,"CREDITO")+SUMIFS(df_extratos!I:I,df_extratos!F:F,Conciliacao!BG4,df_extratos!G:G,"CREDITO")+SUMIFS(df_extratos!I:I,df_extratos!F:F,Conciliacao!BH4,df_extratos!G:G,"CREDITO") | I4: =H4-SUM(B4:G4) | J4: =SUMIFS(df_blueme_sem_parcelamento!E:E,df_blueme_sem_parcelamento!H:H,Conciliacao!A4)*(-1) | K4: =SUMIFS(df_blueme_com_parcelamento!J:J,df_blueme_com_parcelamento!M:M,Conciliacao!A4)*(-1) | L4: =SUMIFS(df_mutuos!N:N,df_mutuos!B:B,Conciliacao!A4)*(-1) | M4: =SUMIFS(df_bloqueios_judiciais!E:E,df_bloqueios_judiciais!D:D,Conciliacao!A4,df_bloqueios_judiciais!E:E,"<0") | N4: =SUMIFS(df_extratos!I:I,df_extratos!F:F,Conciliacao!BE4,df_extratos!G:G,"DEBITO")+SUMIFS(df_extratos!I:I,df_extratos!F:F,Conciliacao!A4,df_extratos!G:G,"DEBITO")+SUMIFS(df_extratos!I:I,df_extratos!F:F,Conciliacao!BF4,df_extratos!G:G,"DEBITO")+SUMIFS(df_extratos!I:I,df_extratos!F:F,Conciliacao!BG4,df_extratos!G:G,"DEBITO")+SUMIFS(df_extratos!I:I,df_extratos!F:F,Conciliacao!BH4,df_extratos!G:G,"DEBITO") | O4: =N4-SUM(J4:M4) | P4: =SUMIFS(df_ajustes_conciliaco!D:D,df_ajustes_conciliaco!C:C,Conciliacao!A4) | Q4: =O4+I4-P4 | BE4: 45660.5 | BF4: 45660.125 | BG4: 45660.542 | BH4: 45660.625
A5: =A4+1 | B5: =-SUMIFS(df_extrato_zig!G:G,df_extrato_zig!E:E,Conciliacao!A5,df_extrato_zig!D:D,"Saque")-SUMIFS(df_extrato_zig!G:G,df_extrato_zig!E:E,Conciliacao!A5,df_extrato_zig!D:D,"Antecipação") | C5: =SUMIFS(df_extrato_zig!E:E,df_extrato_zig!L:L,Conciliacao!A5,df_extrato_zig!F:F,"DINHEIRO") | D5: =SUMIFS(view_parc_agrup!H:H,view_parc_agrup!G:G,Conciliacao!A5) | E5: =SUMIFS(df_eventos!F:F,df_eventos!H:H,Conciliacao!A5) | F5: =SUMIFS(df_mutuos!M:M,df_mutuos!B:B,Conciliacao!A5) | G5: =SUMIFS(df_bloqueios_judiciais!G:G,df_bloqueios_judiciais!D:D,Conciliacao!A5,df_bloqueios_judiciais!G:G,">0") | H5: =SUMIFS(df_extratos!I:I,df_extratos!F:F,Conciliacao!BE5,df_extratos!G:G,"CREDITO")+SUMIFS(df_extratos!I:I,df_extratos!F:F,Conciliacao!A5,df_extratos!G:G,"CREDITO")+SUMIFS(df_extratos!I:I,df_extratos!F:F,Conciliacao!BF5,df_extratos!G:G,"CREDITO")+SUMIFS(df_extratos!I:I,df_extratos!F:F,Conciliacao!BG5,df_extratos!G:G,"CREDITO")+SUMIFS(df_extratos!I:I,df_extratos!F:F,Conciliacao!BH5,df_extratos!G:G,"CREDITO") | I5: =H5-SUM(B5:G5) | J5: =SUMIFS(df_blueme_sem_parcelamento!E:E,df_blueme_sem_parcelamento!H:H,Conciliacao!A5)*(-1) | K5: =SUMIFS(df_blueme_com_parcelamento!J:J,df_blueme_com_parcelamento!M:M,Conciliacao!A5)*(-1) | L5: =SUMIFS(df_mutuos!N:N,df_mutuos!B:B,Conciliacao!A5)*(-1) | M5: =SUMIFS(df_bloqueios_judiciais!E:E,df_bloqueios_judiciais!D:D,Conciliacao!A5,df_bloqueios_judiciais!E:E,"<0") | N5: =SUMIFS(df_extratos!I:I,df_extratos!F:F,Conciliacao!BE5,df_extratos!G:G,"DEBITO")+SUMIFS(df_extratos!I:I,df_extratos!F:F,Conciliacao!A5,df_extratos!G:G,"DEBITO")+SUMIFS(df_extratos!I:I,df_extratos!F:F,Conciliacao!BF5,df_extratos!G:G,"DEBITO")+SUMIFS(df_extratos!I:I,df_extratos!F:F,Conciliacao!BG5,df_extratos!G:G,"DEBITO")+SUMIFS(df_extratos!I:I,df_extratos!F:F,Conciliacao!BH5,df_extratos!G:G,"DEBITO") | O5: =N5-SUM(J5:M5) | P5: =SUMIFS(df_ajustes_conciliaco!D:D,df_ajustes_conciliaco!C:C,Conciliacao!A5) | Q5: =O5+I5-P5 | BE5: 45661.5 | BF5: 45661.125 | BG5: 45661.542 | BH5: 45661.625
A6: =A5+1 | B6: =-SUMIFS(df_extrato_zig!G:G,df_extrato_zig!E:E,Conciliacao!A6,df_extrato_zig!D:D,"Saque")-SUMIFS(df_extrato_zig!G:G,df_extrato_zig!E:E,Conciliacao!A6,df_extrato_zig!D:D,"Antecipação") | C6: =SUMIFS(df_extrato_zig!E:E,df_extrato_zig!L:L,Conciliacao!A6,df_extrato_zig!F:F,"DINHEIRO") | D6: =SUMIFS(view_parc_agrup!H:H,view_parc_agrup!G:G,Conciliacao!A6) | E6: =SUMIFS(df_eventos!F:F,df_eventos!H:H,Conciliacao!A6) | F6: =SUMIFS(df_mutuos!M:M,df_mutuos!B:B,Conciliacao!A6) | G6: =SUMIFS(df_bloqueios_judiciais!G:G,df_bloqueios_judiciais!D:D,Conciliacao!A6,df_bloqueios_judiciais!G:G,">0") | H6: =SUMIFS(df_extratos!I:I,df_extratos!F:F,Conciliacao!BE6,df_extratos!G:G,"CREDITO")+SUMIFS(df_extratos!I:I,df_extratos!F:F,Conciliacao!A6,df_extratos!G:G,"CREDITO")+SUMIFS(df_extratos!I:I,df_extratos!F:F,Conciliacao!BF6,df_extratos!G:G,"CREDITO")+SUMIFS(df_extratos!I:I,df_extratos!F:F,Conciliacao!BG6,df_extratos!G:G,"CREDITO")+SUMIFS(df_extratos!I:I,df_extratos!F:F,Conciliacao!BH6,df_extratos!G:G,"CREDITO") | I6: =H6-SUM(B6:G6) | J6: =SUMIFS(df_blueme_sem_parcelamento!E:E,df_blueme_sem_parcelamento!H:H,Conciliacao!A6)*(-1) | K6: =SUMIFS(df_blueme_com_parcelamento!J:J,df_blueme_com_parcelamento!M:M,Conciliacao!A6)*(-1) | L6: =SUMIFS(df_mutuos!N:N,df_mutuos!B:B,Conciliacao!A6)*(-1) | M6: =SUMIFS(df_bloqueios_judiciais!E:E,df_bloqueios_judiciais!D:D,Conciliacao!A6,df_bloqueios_judiciais!E:E,"<0") | N6: =SUMIFS(df_extratos!I:I,df_extratos!F:F,Conciliacao!BE6,df_extratos!G:G,"DEBITO")+SUMIFS(df_extratos!I:I,df_extratos!F:F,Conciliacao!A6,df_extratos!G:G,"DEBITO")+SUMIFS(df_extratos!I:I,df_extratos!F:F,Conciliacao!BF6,df_extratos!G:G,"DEBITO")+SUMIFS(df_extratos!I:I,df_extratos!F:F,Conciliacao!BG6,df_extratos!G:G,"DEBITO")+SUMIFS(df_extratos!I:I,df_extratos!F:F,Conciliacao!BH6,df_extratos!G:G,"DEBITO") | O6: =N6-SUM(J6:M6) | P6: =SUMIFS(df_ajustes_conciliaco!D:D,df_ajustes_conciliaco!C:C,Conciliacao!A6) | Q6: =O6+I6-P6 | BE6: 45662.5 | BF6: 45662.125 | BG6: 45662.542 | BH6: 45662.625
A7: =A6+1 | B7: =-SUMIFS(df_extrato_zig!G:G,df_extrato_zig!E:E,Conciliacao!A7,df_extrato_zig!D:D,"Saque")-SUMIFS(df_extrato_zig!G:G,df_extrato_zig!E:E,Conciliacao!A7,df_extrato_zig!D:D,"Antecipação") | C7: =SUMIFS(df_extrato_zig!E:E,df_extrato_zig!L:L,Conciliacao!A7,df_extrato_zig!F:F,"DINHEIRO") | D7: =SUMIFS(view_parc_agrup!H:H,view_parc_agrup!G:G,Conciliacao!A7) | E7: =SUMIFS(df_eventos!F:F,df_eventos!H:H,Conciliacao!A7) | F7: =SUMIFS(df_mutuos!M:M,df_mutuos!B:B,Conciliacao!A7) | G7: =SUMIFS(df_bloqueios_judiciais!G:G,df_bloqueios_judiciais!D:D,Conciliacao!A7,df_bloqueios_judiciais!G:G,">0") | H7: =SUMIFS(df_extratos!I:I,df_extratos!F:F,Conciliacao!BE7,df_extratos!G:G,"CREDITO")+SUMIFS(df_extratos!I:I,df_extratos!F:F,Conciliacao!A7,df_extratos!G:G,"CREDITO")+SUMIFS(df_extratos!I:I,df_extratos!F:F,Conciliacao!BF7,df_extratos!G:G,"CREDITO")+SUMIFS(df_extratos!I:I,df_extratos!F:F,Conciliacao!BG7,df_extratos!G:G,"CREDITO")+SUMIFS(df_extratos!I:I,df_extratos!F:F,Conciliacao!BH7,df_extratos!G:G,"CREDITO") | I7: =H7-SUM(B7:G7) | J7: =SUMIFS(df_blueme_sem_parcelamento!E:E,df_blueme_sem_parcelamento!H:H,Conciliacao!A7)*(-1) | K7: =SUMIFS(df_blueme_com_parcelamento!J:J,df_blueme_com_parcelamento!M:M,Conciliacao!A7)*(-1) | L7: =SUMIFS(df_mutuos!N:N,df_mutuos!B:B,Conciliacao!A7)*(-1) | M7: =SUMIFS(df_bloqueios_judiciais!E:E,df_bloqueios_judiciais!D:D,Conciliacao!A7,df_bloqueios_judiciais!E:E,"<0") | N7: =SUMIFS(df_extratos!I:I,df_extratos!F:F,Conciliacao!BE7,df_extratos!G:G,"DEBITO")+SUMIFS(df_extratos!I:I,df_extratos!F:F,Conciliacao!A7,df_extratos!G:G,"DEBITO")+SUMIFS(df_extratos!I:I,df_extratos!F:F,Conciliacao!BF7,df_extratos!G:G,"DEBITO")+SUMIFS(df_extratos!I:I,df_extratos!F:F,Conciliacao!BG7,df_extratos!G:G,"DEBITO")+SUMIFS(df_extratos!I:I,df_extratos!F:F,Conciliacao!BH7,df_extratos!G:G,"DEBITO") | O7: =N7-SUM(J7:M7) | P7: =SUMIFS(df_ajustes_conciliaco!D:D,df_ajustes_conciliaco!C:C,Conciliacao!A7) | Q7: =O7+I7-P7 | BE7: 45663.5 | BF7: 45663.125 | BG7: 45663.542 | BH7: 45663.625
A8: =A7+1 | B8: =-SUMIFS(df_extrato_zig!G:G,df_extrato_zig!E:E,Conciliacao!A8,df_extrato_zig!D:D,"Saque")-SUMIFS(df_extrato_zig!G:G,df_extrato_zig!E:E,Conciliacao!A8,df_extrato_zig!D:D,"Antecipação") | C8: =SUMIFS(df_extrato_zig!E:E,df_extrato_zig!L:L,Conciliacao!A8,df_extrato_zig!F:F,"DINHEIRO") | D8: =SUMIFS(view_parc_agrup!H:H,view_parc_agrup!G:G,Conciliacao!A8) | E8: =SUMIFS(df_eventos!F:F,df_eventos!H:H,Conciliacao!A8) | F8: =SUMIFS(df_mutuos!M:M,df_mutuos!B:B,Conciliacao!A8) | G8: =SUMIFS(df_bloqueios_judiciais!G:G,df_bloqueios_judiciais!D:D,Conciliacao!A8,df_bloqueios_judiciais!G:G,">0") | H8: =SUMIFS(df_extratos!I:I,df_extratos!F:F,Conciliacao!BE8,df_extratos!G:G,"CREDITO")+SUMIFS(df_extratos!I:I,df_extratos!F:F,Conciliacao!A8,df_extratos!G:G,"CREDITO")+SUMIFS(df_extratos!I:I,df_extratos!F:F,Conciliacao!BF8,df_extratos!G:G,"CREDITO")+SUMIFS(df_extratos!I:I,df_extratos!F:F,Conciliacao!BG8,df_extratos!G:G,"CREDITO")+SUMIFS(df_extratos!I:I,df_extratos!F:F,Conciliacao!BH8,df_extratos!G:G,"CREDITO") | I8: =H8-SUM(B8:G8) | J8: =SUMIFS(df_blueme_sem_parcelamento!E:E,df_blueme_sem_parcelamento!H:H,Conciliacao!A8)*(-1) | K8: =SUMIFS(df_blueme_com_parcelamento!J:J,df_blueme_com_parcelamento!M:M,Conciliacao!A8)*(-1) | L8: =SUMIFS(df_mutuos!N:N,df_mutuos!B:B,Conciliacao!A8)*(-1) | M8: =SUMIFS(df_bloqueios_judiciais!E:E,df_bloqueios_judiciais!D:D,Conciliacao!A8,df_bloqueios_judiciais!E:E,"<0") | N8: =SUMIFS(df_extratos!I:I,df_extratos!F:F,Conciliacao!BE8,df_extratos!G:G,"DEBITO")+SUMIFS(df_extratos!I:I,df_extratos!F:F,Conciliacao!A8,df_extratos!G:G,"DEBITO")+SUMIFS(df_extratos!I:I,df_extratos!F:F,Conciliacao!BF8,df_extratos!G:G,"DEBITO")+SUMIFS(df_extratos!I:I,df_extratos!F:F,Conciliacao!BG8,df_extratos!G:G,"DEBITO")+SUMIFS(df_extratos!I:I,df_extratos!F:F,Conciliacao!BH8,df_extratos!G:G,"DEBITO") | O8: =N8-SUM(J8:M8) | P8: =SUMIFS(df_ajustes_conciliaco!D:D,df_ajustes_conciliaco!C:C,Conciliacao!A8) | Q8: =O8+I8-P8 | BE8: 45664.5 | BF8: 45664.125 | BG8: 45664.542 | BH8: 45664.625
A9: =A8+1 | B9: =-SUMIFS(df_extrato_zig!G:G,df_extrato_zig!E:E,Conciliacao!A9,df_extrato_zig!D:D,"Saque")-SUMIFS(df_extrato_zig!G:G,df_extrato_zig!E:E,Conciliacao!A9,df_extrato_zig!D:D,"Antecipação") | C9: =SUMIFS(df_extrato_zig!E:E,df_extrato_zig!L:L,Conciliacao!A9,df_extrato_zig!F:F,"DINHEIRO") | D9: =SUMIFS(view_parc_agrup!H:H,view_parc_agrup!G:G,Conciliacao!A9) | E9: =SUMIFS(df_eventos!F:F,df_eventos!H:H,Conciliacao!A9) | F9: =SUMIFS(df_mutuos!M:M,df_mutuos!B:B,Conciliacao!A9) | G9: =SUMIFS(df_bloqueios_judiciais!G:G,df_bloqueios_judiciais!D:D,Conciliacao!A9,df_bloqueios_judiciais!G:G,">0") | H9: =SUMIFS(df_extratos!I:I,df_extratos!F:F,Conciliacao!BE9,df_extratos!G:G,"CREDITO")+SUMIFS(df_extratos!I:I,df_extratos!F:F,Conciliacao!A9,df_extratos!G:G,"CREDITO")+SUMIFS(df_extratos!I:I,df_extratos!F:F,Conciliacao!BF9,df_extratos!G:G,"CREDITO")+SUMIFS(df_extratos!I:I,df_extratos!F:F,Conciliacao!BG9,df_extratos!G:G,"CREDITO")+SUMIFS(df_extratos!I:I,df_extratos!F:F,Conciliacao!BH9,df_extratos!G:G,"CREDITO") | I9: =H9-SUM(B9:G9) | J9: =SUMIFS(df_blueme_sem_parcelamento!E:E,df_blueme_sem_parcelamento!H:H,Conciliacao!A9)*(-1) | K9: =SUMIFS(df_blueme_com_parcelamento!J:J,df_blueme_com_parcelamento!M:M,Conciliacao!A9)*(-1) | L9: =SUMIFS(df_mutuos!N:N,df_mutuos!B:B,Conciliacao!A9)*(-1) | M9: =SUMIFS(df_bloqueios_judiciais!E:E,df_bloqueios_judiciais!D:D,Conciliacao!A9,df_bloqueios_judiciais!E:E,"<0") | N9: =SUMIFS(df_extratos!I:I,df_extratos!F:F,Conciliacao!BE9,df_extratos!G:G,"DEBITO")+SUMIFS(df_extratos!I:I,df_extratos!F:F,Conciliacao!A9,df_extratos!G:G,"DEBITO")+SUMIFS(df_extratos!I:I,df_extratos!F:F,Conciliacao!BF9,df_extratos!G:G,"DEBITO")+SUMIFS(df_extratos!I:I,df_extratos!F:F,Conciliacao!BG9,df_extratos!G:G,"DEBITO")+SUMIFS(df_extratos!I:I,df_extratos!F:F,Conciliacao!BH9,df_extratos!G:G,"DEBITO") | O9: =N9-SUM(J9:M9) | P9: =SUMIFS(df_ajustes_conciliaco!D:D,df_ajustes_conciliaco!C:C,Conciliacao!A9) | Q9: =O9+I9-P9 | BE9: 45665.5 | BF9: 45665.125 | BG9: 45665.542 | BH9: 45665.625
A10: =A9+1 | B10: =-SUMIFS(df_extrato_zig!G:G,df_extrato_zig!E:E,Conciliacao!A10,df_extrato_zig!D:D,"Saque")-SUMIFS(df_extrato_zig!G:G,df_extrato_zig!E:E,Conciliacao!A10,df_extrato_zig!D:D,"Antecipação") | C10: =SUMIFS(df_extrato_zig!E:E,df_extrato_zig!L:L,Conciliacao!A10,df_extrato_zig!F:F,"DINHEIRO") | D10: =SUMIFS(view_parc_agrup!H:H,view_parc_agrup!G:G,Conciliacao!A10) | E10: =SUMIFS(df_eventos!F:F,df_eventos!H:H,Conciliacao!A10) | F10: =SUMIFS(df_mutuos!M:M,df_mutuos!B:B,Conciliacao!A10) | G10: =SUMIFS(df_bloqueios_judiciais!G:G,df_bloqueios_judiciais!D:D,Conciliacao!A10,df_bloqueios_judiciais!G:G,">0") | H10: =SUMIFS(df_extratos!I:I,df_extratos!F:F,Conciliacao!BE10,df_extratos!G:G,"CREDITO")+SUMIFS(df_extratos!I:I,df_extratos!F:F,Conciliacao!A10,df_extratos!G:G,"CREDITO")+SUMIFS(df_extratos!I:I,df_extratos!F:F,Conciliacao!BF10,df_extratos!G:G,"CREDITO")+SUMIFS(df_extratos!I:I,df_extratos!F:F,Conciliacao!BG10,df_extratos!G:G,"CREDITO")+SUMIFS(df_extratos!I:I,df_extratos!F:F,Conciliacao!BH10,df_extratos!G:G,"CREDITO") | I10: =H10-SUM(B10:G10) | J10: =SUMIFS(df_blueme_sem_parcelamento!E:E,df_blueme_sem_parcelamento!H:H,Conciliacao!A10)*(-1) | K10: =SUMIFS(df_blueme_com_parcelamento!J:J,df_blueme_com_parcelamento!M:M,Conciliacao!A10)*(-1) | L10: =SUMIFS(df_mutuos!N:N,df_mutuos!B:B,Conciliacao!A10)*(-1) | M10: =SUMIFS(df_bloqueios_judiciais!E:E,df_bloqueios_judiciais!D:D,Conciliacao!A10,df_bloqueios_judiciais!E:E,"<0") | N10: =SUMIFS(df_extratos!I:I,df_extratos!F:F,Conciliacao!BE10,df_extratos!G:G,"DEBITO")+SUMIFS(df_extratos!I:I,df_extratos!F:F,Conciliacao!A10,df_extratos!G:G,"DEBITO")+SUMIFS(df_extratos!I:I,df_extratos!F:F,Conciliacao!BF10,df_extratos!G:G,"DEBITO")+SUMIFS(df_extratos!I:I,df_extratos!F:F,Conciliacao!BG10,df_extratos!G:G,"DEBITO")+SUMIFS(df_extratos!I:I,df_extratos!F:F,Conciliacao!BH10,df_extratos!G:G,"DEBITO") | O10: =N10-SUM(J10:M10) | P10: =SUMIFS(df_ajustes_conciliaco!D:D,df_ajustes_conciliaco!C:C,Conciliacao!A10) | Q10: =O10+I10-P10 | BE10: 45666.5 | BF10: 45666.125 | BG10: 45666.542 | BH10: 45666.625
A11: =A10+1 | B11: =-SUMIFS(df_extrato_zig!G:G,df_extrato_zig!E:E,Conciliacao!A11,df_extrato_zig!D:D,"Saque")-SUMIFS(df_extrato_zig!G:G,df_extrato_zig!E:E,Conciliacao!A11,df_extrato_zig!D:D,"Antecipação") | C11: =SUMIFS(df_extrato_zig!E:E,df_extrato_zig!L:L,Conciliacao!A11,df_extrato_zig!F:F,"DINHEIRO") | D11: =SUMIFS(view_parc_agrup!H:H,view_parc_agrup!G:G,Conciliacao!A11) | E11: =SUMIFS(df_eventos!F:F,df_eventos!H:H,Conciliacao!A11) | F11: =SUMIFS(df_mutuos!M:M,df_mutuos!B:B,Conciliacao!A11) | G11: =SUMIFS(df_bloqueios_judiciais!G:G,df_bloqueios_judiciais!D:D,Conciliacao!A11,df_bloqueios_judiciais!G:G,">0") | H11: =SUMIFS(df_extratos!I:I,df_extratos!F:F,Conciliacao!BE11,df_extratos!G:G,"CREDITO")+SUMIFS(df_extratos!I:I,df_extratos!F:F,Conciliacao!A11,df_extratos!G:G,"CREDITO")+SUMIFS(df_extratos!I:I,df_extratos!F:F,Conciliacao!BF11,df_extratos!G:G,"CREDITO")+SUMIFS(df_extratos!I:I,df_extratos!F:F,Conciliacao!BG11,df_extratos!G:G,"CREDITO")+SUMIFS(df_extratos!I:I,df_extratos!F:F,Conciliacao!BH11,df_extratos!G:G,"CREDITO") | I11: =H11-SUM(B11:G11) | J11: =SUMIFS(df_blueme_sem_parcelamento!E:E,df_blueme_sem_parcelamento!H:H,Conciliacao!A11)*(-1) | K11: =SUMIFS(df_blueme_com_parcelamento!J:J,df_blueme_com_parcelamento!M:M,Conciliacao!A11)*(-1) | L11: =SUMIFS(df_mutuos!N:N,df_mutuos!B:B,Conciliacao!A11)*(-1) | M11: =SUMIFS(df_bloqueios_judiciais!E:E,df_bloqueios_judiciais!D:D,Conciliacao!A11,df_bloqueios_judiciais!E:E,"<0") | N11: =SUMIFS(df_extratos!I:I,df_extratos!F:F,Conciliacao!BE11,df_extratos!G:G,"DEBITO")+SUMIFS(df_extratos!I:I,df_extratos!F:F,Conciliacao!A11,df_extratos!G:G,"DEBITO")+SUMIFS(df_extratos!I:I,df_extratos!F:F,Conciliacao!BF11,df_extratos!G:G,"DEBITO")+SUMIFS(df_extratos!I:I,df_extratos!F:F,Conciliacao!BG11,df_extratos!G:G,"DEBITO")+SUMIFS(df_extratos!I:I,df_extratos!F:F,Conciliacao!BH11,df_extratos!G:G,"DEBITO") | O11: =N11-SUM(J11:M11) | P11: =SUMIFS(df_ajustes_conciliaco!D:D,df_ajustes_conciliaco!C:C,Conciliacao!A11) | Q11: =O11+I11-P11 | BE11: 45667.5 | BF11: 45667.125 | BG11: 45667.542 | BH11: 45667.625
A12: =A11+1 | B12: =-SUMIFS(df_extrato_zig!G:G,df_extrato_zig!E:E,Conciliacao!A12,df_extrato_zig!D:D,"Saque")-SUMIFS(df_extrato_zig!G:G,df_extrato_zig!E:E,Conciliacao!A12,df_extrato_zig!D:D,"Antecipação") | C12: =SUMIFS(df_extrato_zig!E:E,df_extrato_zig!L:L,Conciliacao!A12,df_extrato_zig!F:F,"DINHEIRO") | D12: =SUMIFS(view_parc_agrup!H:H,view_parc_agrup!G:G,Conciliacao!A12) | E12: =SUMIFS(df_eventos!F:F,df_eventos!H:H,Conciliacao!A12) | F12: =SUMIFS(df_mutuos!M:M,df_mutuos!B:B,Conciliacao!A12) | G12: =SUMIFS(df_bloqueios_judiciais!G:G,df_bloqueios_judiciais!D:D,Conciliacao!A12,df_bloqueios_judiciais!G:G,">0") | H12: =SUMIFS(df_extratos!I:I,df_extratos!F:F,Conciliacao!BE12,df_extratos!G:G,"CREDITO")+SUMIFS(df_extratos!I:I,df_extratos!F:F,Conciliacao!A12,df_extratos!G:G,"CREDITO")+SUMIFS(df_extratos!I:I,df_extratos!F:F,Conciliacao!BF12,df_extratos!G:G,"CREDITO")+SUMIFS(df_extratos!I:I,df_extratos!F:F,Conciliacao!BG12,df_extratos!G:G,"CREDITO")+SUMIFS(df_extratos!I:I,df_extratos!F:F,Conciliacao!BH12,df_extratos!G:G,"CREDITO") | I12: =H12-SUM(B12:G12) | J12: =SUMIFS(df_blueme_sem_parcelamento!E:E,df_blueme_sem_parcelamento!H:H,Conciliacao!A12)*(-1) | K12: =SUMIFS(df_blueme_com_parcelamento!J:J,df_blueme_com_parcelamento!M:M,Conciliacao!A12)*(-1) | L12: =SUMIFS(df_mutuos!N:N,df_mutuos!B:B,Conciliacao!A12)*(-1) | M12: =SUMIFS(df_bloqueios_judiciais!E:E,df_bloqueios_judiciais!D:D,Conciliacao!A12,df_bloqueios_judiciais!E:E,"<0") | N12: =SUMIFS(df_extratos!I:I,df_extratos!F:F,Conciliacao!BE12,df_extratos!G:G,"DEBITO")+SUMIFS(df_extratos!I:I,df_extratos!F:F,Conciliacao!A12,df_extratos!G:G,"DEBITO")+SUMIFS(df_extratos!I:I,df_extratos!F:F,Conciliacao!BF12,df_extratos!G:G,"DEBITO")+SUMIFS(df_extratos!I:I,df_extratos!F:F,Conciliacao!BG12,df_extratos!G:G,"DEBITO")+SUMIFS(df_extratos!I:I,df_extratos!F:F,Conciliacao!BH12,df_extratos!G:G,"DEBITO") | O12: =N12-SUM(J12:M12) | P12: =SUMIFS(df_ajustes_conciliaco!D:D,df_ajustes_conciliaco!C:C,Conciliacao!A12) | Q12: =O12+I12-P12 | BE12: 45668.5 | BF12: 45668.125 | BG12: 45668.542 | BH12: 45668.625
A13: =A12+1 | B13: =-SUMIFS(df_extrato_zig!G:G,df_extrato_zig!E:E,Conciliacao!A13,df_extrato_zig!D:D,"Saque")-SUMIFS(df_extrato_zig!G:G,df_extrato_zig!E:E,Conciliacao!A13,df_extrato_zig!D:D,"Antecipação") | C13: =SUMIFS(df_extrato_zig!E:E,df_extrato_zig!L:L,Conciliacao!A13,df_extrato_zig!F:F,"DINHEIRO") | D13: =SUMIFS(view_parc_agrup!H:H,view_parc_agrup!G:G,Conciliacao!A13) | E13: =SUMIFS(df_eventos!F:F,df_eventos!H:H,Conciliacao!A13) | F13: =SUMIFS(df_mutuos!M:M,df_mutuos!B:B,Conciliacao!A13) | G13: =SUMIFS(df_bloqueios_judiciais!G:G,df_bloqueios_judiciais!D:D,Conciliacao!A13,df_bloqueios_judiciais!G:G,">0") | H13: =SUMIFS(df_extratos!I:I,df_extratos!F:F,Conciliacao!BE13,df_extratos!G:G,"CREDITO")+SUMIFS(df_extratos!I:I,df_extratos!F:F,Conciliacao!A13,df_extratos!G:G,"CREDITO")+SUMIFS(df_extratos!I:I,df_extratos!F:F,Conciliacao!BF13,df_extratos!G:G,"CREDITO")+SUMIFS(df_extratos!I:I,df_extratos!F:F,Conciliacao!BG13,df_extratos!G:G,"CREDITO")+SUMIFS(df_extratos!I:I,df_extratos!F:F,Conciliacao!BH13,df_extratos!G:G,"CREDITO") | I13: =H13-SUM(B13:G13) | J13: =SUMIFS(df_blueme_sem_parcelamento!E:E,df_blueme_sem_parcelamento!H:H,Conciliacao!A13)*(-1) | K13: =SUMIFS(df_blueme_com_parcelamento!J:J,df_blueme_com_parcelamento!M:M,Conciliacao!A13)*(-1) | L13: =SUMIFS(df_mutuos!N:N,df_mutuos!B:B,Conciliacao!A13)*(-1) | M13: =SUMIFS(df_bloqueios_judiciais!E:E,df_bloqueios_judiciais!D:D,Conciliacao!A13,df_bloqueios_judiciais!E:E,"<0") | N13: =SUMIFS(df_extratos!I:I,df_extratos!F:F,Conciliacao!BE13,df_extratos!G:G,"DEBITO")+SUMIFS(df_extratos!I:I,df_extratos!F:F,Conciliacao!A13,df_extratos!G:G,"DEBITO")+SUMIFS(df_extratos!I:I,df_extratos!F:F,Conciliacao!BF13,df_extratos!G:G,"DEBITO")+SUMIFS(df_extratos!I:I,df_extratos!F:F,Conciliacao!BG13,df_extratos!G:G,"DEBITO")+SUMIFS(df_extratos!I:I,df_extratos!F:F,Conciliacao!BH13,df_extratos!G:G,"DEBITO") | O13: =N13-SUM(J13:M13) | P13: =SUMIFS(df_ajustes_conciliaco!D:D,df_ajustes_conciliaco!C:C,Conciliacao!A13) | Q13: =O13+I13-P13 | BE13: 45669.5 | BF13: 45669.125 | BG13: 45669.542 | BH13: 45669.625
A14: =A13+1 | B14: =-SUMIFS(df_extrato_zig!G:G,df_extrato_zig!E:E,Conciliacao!A14,df_extrato_zig!D:D,"Saque")-SUMIFS(df_extrato_zig!G:G,df_extrato_zig!E:E,Conciliacao!A14,df_extrato_zig!D:D,"Antecipação") | C14: =SUMIFS(df_extrato_zig!E:E,df_extrato_zig!L:L,Conciliacao!A14,df_extrato_zig!F:F,"DINHEIRO") | D14: =SUMIFS(view_parc_agrup!H:H,view_parc_agrup!G:G,Conciliacao!A14) | E14: =SUMIFS(df_eventos!F:F,df_eventos!H:H,Conciliacao!A14) | F14: =SUMIFS(df_mutuos!M:M,df_mutuos!B:B,Conciliacao!A14) | G14: =SUMIFS(df_bloqueios_judiciais!G:G,df_bloqueios_judiciais!D:D,Conciliacao!A14,df_bloqueios_judiciais!G:G,">0") | H14: =SUMIFS(df_extratos!I:I,df_extratos!F:F,Conciliacao!BE14,df_extratos!G:G,"CREDITO")+SUMIFS(df_extratos!I:I,df_extratos!F:F,Conciliacao!A14,df_extratos!G:G,"CREDITO")+SUMIFS(df_extratos!I:I,df_extratos!F:F,Conciliacao!BF14,df_extratos!G:G,"CREDITO")+SUMIFS(df_extratos!I:I,df_extratos!F:F,Conciliacao!BG14,df_extratos!G:G,"CREDITO")+SUMIFS(df_extratos!I:I,df_extratos!F:F,Conciliacao!BH14,df_extratos!G:G,"CREDITO") | I14: =H14-SUM(B14:G14) | J14: =SUMIFS(df_blueme_sem_parcelamento!E:E,df_blueme_sem_parcelamento!H:H,Conciliacao!A14)*(-1) | K14: =SUMIFS(df_blueme_com_parcelamento!J:J,df_blueme_com_parcelamento!M:M,Conciliacao!A14)*(-1) | L14: =SUMIFS(df_mutuos!N:N,df_mutuos!B:B,Conciliacao!A14)*(-1) | M14: =SUMIFS(df_bloqueios_judiciais!E:E,df_bloqueios_judiciais!D:D,Conciliacao!A14,df_bloqueios_judiciais!E:E,"<0") | N14: =SUMIFS(df_extratos!I:I,df_extratos!F:F,Conciliacao!BE14,df_extratos!G:G,"DEBITO")+SUMIFS(df_extratos!I:I,df_extratos!F:F,Conciliacao!A14,df_extratos!G:G,"DEBITO")+SUMIFS(df_extratos!I:I,df_extratos!F:F,Conciliacao!BF14,df_extratos!G:G,"DEBITO")+SUMIFS(df_extratos!I:I,df_extratos!F:F,Conciliacao!BG14,df_extratos!G:G,"DEBITO")+SUMIFS(df_extratos!I:I,df_extratos!F:F,Conciliacao!BH14,df_extratos!G:G,"DEBITO") | O14: =N14-SUM(J14:M14) | P14: =SUMIFS(df_ajustes_conciliaco!D:D,df_ajustes_conciliaco!C:C,Conciliacao!A14) | Q14: =O14+I14-P14 | BE14: 45670.5 | BF14: 45670.125 | BG14: 45670.542 | BH14: 45670.625
... A34: =A33+1 | B34: =-SUMIFS(df_extrato_zig!G:G,df_extrato_zig!E:E,Conciliacao!A34,df_extrato_zig!D:D,"Saque")-SUMIFS(df_extrato_zig!G:G,df_extrato_zig!E:E,Conciliacao!A34,df_extrato_zig!D:D,"Antecipação") | C34: =SUMIFS(df_extrato_zig!E:E,df_extrato_zig!L:L,Conciliacao!A34,df_extrato_zig!F:F,"DINHEIRO") | D34: =SUMIFS(view_parc_agrup!H:H,view_parc_agrup!G:G,Conciliacao!A34) | E34: =SUMIFS(df_eventos!F:F,df_eventos!H:H,Conciliacao!A34) | F34: =SUMIFS(df_mutuos!M:M,df_mutuos!B:B,Conciliacao!A34) | G34: =SUMIFS(df_bloqueios_judiciais!G:G,df_bloqueios_judiciais!D:D,Conciliacao!A34,df_bloqueios_judiciais!G:G,">0") | H34: =SUMIFS(df_extratos!I:I,df_extratos!F:F,Conciliacao!BE34,df_extratos!G:G,"CREDITO")+SUMIFS(df_extratos!I:I,df_extratos!F:F,Conciliacao!A34,df_extratos!G:G,"CREDITO")+SUMIFS(df_extratos!I:I,df_extratos!F:F,Conciliacao!BF34,df_extratos!G:G,"CREDITO")+SUMIFS(df_extratos!I:I,df_extratos!F:F,Conciliacao!BG34,df_extratos!G:G,"CREDITO")+SUMIFS(df_extratos!I:I,df_extratos!F:F,Conciliacao!BH34,df_extratos!G:G,"CREDITO") | I34: =H34-SUM(B34:G34) | J34: =SUMIFS(df_blueme_sem_parcelamento!E:E,df_blueme_sem_parcelamento!H:H,Conciliacao!A34)*(-1) | K34: =SUMIFS(df_blueme_com_parcelamento!J:J,df_blueme_com_parcelamento!M:M,Conciliacao!A34)*(-1) | L34: =SUMIFS(df_mutuos!N:N,df_mutuos!B:B,Conciliacao!A34)*(-1) | M34: =SUMIFS(df_bloqueios_judiciais!E:E,df_bloqueios_judiciais!D:D,Conciliacao!A34,df_bloqueios_judiciais!E:E,"<0") | N34: =SUMIFS(df_extratos!I:I,df_extratos!F:F,Conciliacao!BE34,df_extratos!G:G,"DEBITO")+SUMIFS(df_extratos!I:I,df_extratos!F:F,Conciliacao!A34,df_extratos!G:G,"DEBITO")+SUMIFS(df_extratos!I:I,df_extratos!F:F,Conciliacao!BF34,df_extratos!G:G,"DEBITO")+SUMIFS(df_extratos!I:I,df_extratos!F:F,Conciliacao!BG34,df_extratos!G:G,"DEBITO")+SUMIFS(df_extratos!I:I,df_extratos!F:F,Conciliacao!BH34,df_extratos!G:G,"DEBITO") | O34: =N34-SUM(J34:M34) | P34: =SUMIFS(df_ajustes_conciliaco!D:D,df_ajustes_conciliaco!C:C,Conciliacao!A34) | Q34: =O34+I34-P34 | BE34: 45690.5 | BF34: 45690.125 | BG34: 45690.542 | BH34: 45690.625
A35: =A34+1 | B35: =-SUMIFS(df_extrato_zig!G:G,df_extrato_zig!E:E,Conciliacao!A35,df_extrato_zig!D:D,"Saque")-SUMIFS(df_extrato_zig!G:G,df_extrato_zig!E:E,Conciliacao!A35,df_extrato_zig!D:D,"Antecipação") | C35: =SUMIFS(df_extrato_zig!E:E,df_extrato_zig!L:L,Conciliacao!A35,df_extrato_zig!F:F,"DINHEIRO") | D35: =SUMIFS(view_parc_agrup!H:H,view_parc_agrup!G:G,Conciliacao!A35) | E35: =SUMIFS(df_eventos!F:F,df_eventos!H:H,Conciliacao!A35) | F35: =SUMIFS(df_mutuos!M:M,df_mutuos!B:B,Conciliacao!A35) | G35: =SUMIFS(df_bloqueios_judiciais!G:G,df_bloqueios_judiciais!D:D,Conciliacao!A35,df_bloqueios_judiciais!G:G,">0") | H35: =SUMIFS(df_extratos!I:I,df_extratos!F:F,Conciliacao!BE35,df_extratos!G:G,"CREDITO")+SUMIFS(df_extratos!I:I,df_extratos!F:F,Conciliacao!A35,df_extratos!G:G,"CREDITO")+SUMIFS(df_extratos!I:I,df_extratos!F:F,Conciliacao!BF35,df_extratos!G:G,"CREDITO")+SUMIFS(df_extratos!I:I,df_extratos!F:F,Conciliacao!BG35,df_extratos!G:G,"CREDITO")+SUMIFS(df_extratos!I:I,df_extratos!F:F,Conciliacao!BH35,df_extratos!G:G,"CREDITO") | I35: =H35-SUM(B35:G35) | J35: =SUMIFS(df_blueme_sem_parcelamento!E:E,df_blueme_sem_parcelamento!H:H,Conciliacao!A35)*(-1) | K35: =SUMIFS(df_blueme_com_parcelamento!J:J,df_blueme_com_parcelamento!M:M,Conciliacao!A35)*(-1) | L35: =SUMIFS(df_mutuos!N:N,df_mutuos!B:B,Conciliacao!A35)*(-1) | M35: =SUMIFS(df_bloqueios_judiciais!G:G,df_bloqueios_judiciais!D:D,Conciliacao!A35,df_bloqueios_judiciais!G:G,"<0") | N35: =SUMIFS(df_extratos!I:I,df_extratos!F:F,Conciliacao!BE35,df_extratos!G:G,"DEBITO")+SUMIFS(df_extratos!I:I,df_extratos!F:F,Conciliacao!A35,df_extratos!G:G,"DEBITO")+SUMIFS(df_extratos!I:I,df_extratos!F:F,Conciliacao!BF35,df_extratos!G:G,"DEBITO")+SUMIFS(df_extratos!I:I,df_extratos!F:F,Conciliacao!BG35,df_extratos!G:G,"DEBITO")+SUMIFS(df_extratos!I:I,df_extratos!F:F,Conciliacao!BH35,df_extratos!G:G,"DEBITO") | O35: =N35-SUM(J35:M35) | P35: =SUMIFS(df_ajustes_conciliaco!D:D,df_ajustes_conciliaco!C:C,Conciliacao!A35) | Q35: =O35+I35-P35 | BE35: 45691.5 | BF35: 45691.125 | BG35: 45691.542 | BH35: 45691.625
A36: =A35+1 | B36: =-SUMIFS(df_extrato_zig!G:G,df_extrato_zig!E:E,Conciliacao!A36,df_extrato_zig!D:D,"Saque")-SUMIFS(df_extrato_zig!G:G,df_extrato_zig!E:E,Conciliacao!A36,df_extrato_zig!D:D,"Antecipação") | C36: =SUMIFS(df_extrato_zig!E:E,df_extrato_zig!L:L,Conciliacao!A36,df_extrato_zig!F:F,"DINHEIRO") | D36: =SUMIFS(view_parc_agrup!H:H,view_parc_agrup!G:G,Conciliacao!A36) | E36: =SUMIFS(df_eventos!F:F,df_eventos!H:H,Conciliacao!A36) | F36: =SUMIFS(df_mutuos!M:M,df_mutuos!B:B,Conciliacao!A36) | G36: =SUMIFS(df_bloqueios_judiciais!G:G,df_bloqueios_judiciais!D:D,Conciliacao!A36,df_bloqueios_judiciais!G:G,">0") | H36: =SUMIFS(df_extratos!I:I,df_extratos!F:F,Conciliacao!BE36,df_extratos!G:G,"CREDITO")+SUMIFS(df_extratos!I:I,df_extratos!F:F,Conciliacao!A36,df_extratos!G:G,"CREDITO")+SUMIFS(df_extratos!I:I,df_extratos!F:F,Conciliacao!BF36,df_extratos!G:G,"CREDITO")+SUMIFS(df_extratos!I:I,df_extratos!F:F,Conciliacao!BG36,df_extratos!G:G,"CREDITO")+SUMIFS(df_extratos!I:I,df_extratos!F:F,Conciliacao!BH36,df_extratos!G:G,"CREDITO") | I36: =H36-SUM(B36:G36) | J36: =SUMIFS(df_blueme_sem_parcelamento!E:E,df_blueme_sem_parcelamento!H:H,Conciliacao!A36)*(-1) | K36: =SUMIFS(df_blueme_com_parcelamento!J:J,df_blueme_com_parcelamento!M:M,Conciliacao!A36)*(-1) | L36: =SUMIFS(df_mutuos!N:N,df_mutuos!B:B,Conciliacao!A36)*(-1) | M36: =SUMIFS(df_bloqueios_judiciais!G:G,df_bloqueios_judiciais!D:D,Conciliacao!A36,df_bloqueios_judiciais!G:G,"<0") | N36: =SUMIFS(df_extratos!I:I,df_extratos!F:F,Conciliacao!BE36,df_extratos!G:G,"DEBITO")+SUMIFS(df_extratos!I:I,df_extratos!F:F,Conciliacao!A36,df_extratos!G:G,"DEBITO")+SUMIFS(df_extratos!I:I,df_extratos!F:F,Conciliacao!BF36,df_extratos!G:G,"DEBITO")+SUMIFS(df_extratos!I:I,df_extratos!F:F,Conciliacao!BG36,df_extratos!G:G,"DEBITO")+SUMIFS(df_extratos!I:I,df_extratos!F:F,Conciliacao!BH36,df_extratos!G:G,"DEBITO") | O36: =N36-SUM(J36:M36) | P36: =SUMIFS(df_ajustes_conciliaco!D:D,df_ajustes_conciliaco!C:C,Conciliacao!A36) | Q36: =O36+I36-P36 | BE36: 45692.5 | BF36: 45692.125 | BG36: 45692.542 | BH36: 45692.625
A37: =A36+1 | B37: =-SUMIFS(df_extrato_zig!G:G,df_extrato_zig!E:E,Conciliacao!A37,df_extrato_zig!D:D,"Saque")-SUMIFS(df_extrato_zig!G:G,df_extrato_zig!E:E,Conciliacao!A37,df_extrato_zig!D:D,"Antecipação") | C37: =SUMIFS(df_extrato_zig!E:E,df_extrato_zig!L:L,Conciliacao!A37,df_extrato_zig!F:F,"DINHEIRO") | D37: =SUMIFS(view_parc_agrup!H:H,view_parc_agrup!G:G,Conciliacao!A37) | E37: =SUMIFS(df_eventos!F:F,df_eventos!H:H,Conciliacao!A37) | F37: =SUMIFS(df_mutuos!M:M,df_mutuos!B:B,Conciliacao!A37) | G37: =SUMIFS(df_bloqueios_judiciais!G:G,df_bloqueios_judiciais!D:D,Conciliacao!A37,df_bloqueios_judiciais!G:G,">0") | H37: =SUMIFS(df_extratos!I:I,df_extratos!F:F,Conciliacao!BE37,df_extratos!G:G,"CREDITO")+SUMIFS(df_extratos!I:I,df_extratos!F:F,Conciliacao!A37,df_extratos!G:G,"CREDITO")+SUMIFS(df_extratos!I:I,df_extratos!F:F,Conciliacao!BF37,df_extratos!G:G,"CREDITO")+SUMIFS(df_extratos!I:I,df_extratos!F:F,Conciliacao!BG37,df_extratos!G:G,"CREDITO")+SUMIFS(df_extratos!I:I,df_extratos!F:F,Conciliacao!BH37,df_extratos!G:G,"CREDITO") | I37: =H37-SUM(B37:G37) | J37: =SUMIFS(df_blueme_sem_parcelamento!E:E,df_blueme_sem_parcelamento!H:H,Conciliacao!A37)*(-1) | K37: =SUMIFS(df_blueme_com_parcelamento!J:J,df_blueme_com_parcelamento!M:M,Conciliacao!A37)*(-1) | L37: =SUMIFS(df_mutuos!N:N,df_mutuos!B:B,Conciliacao!A37)*(-1) | M37: =SUMIFS(df_bloqueios_judiciais!G:G,df_bloqueios_judiciais!D:D,Conciliacao!A37,df_bloqueios_judiciais!G:G,"<0") | N37: =SUMIFS(df_extratos!I:I,df_extratos!F:F,Conciliacao!BE37,df_extratos!G:G,"DEBITO")+SUMIFS(df_extratos!I:I,df_extratos!F:F,Conciliacao!A37,df_extratos!G:G,"DEBITO")+SUMIFS(df_extratos!I:I,df_extratos!F:F,Conciliacao!BF37,df_extratos!G:G,"DEBITO")+SUMIFS(df_extratos!I:I,df_extratos!F:F,Conciliacao!BG37,df_extratos!G:G,"DEBITO")+SUMIFS(df_extratos!I:I,df_extratos!F:F,Conciliacao!BH37,df_extratos!G:G,"DEBITO") | O37: =N37-SUM(J37:M37) | P37: =SUMIFS(df_ajustes_conciliaco!D:D,df_ajustes_conciliaco!C:C,Conciliacao!A37) | Q37: =O37+I37-P37 | BE37: 45693.5 | BF37: 45693.125 | BG37: 45693.542 | BH37: 45693.625
A38: =A37+1 | B38: =-SUMIFS(df_extrato_zig!G:G,df_extrato_zig!E:E,Conciliacao!A38,df_extrato_zig!D:D,"Saque")-SUMIFS(df_extrato_zig!G:G,df_extrato_zig!E:E,Conciliacao!A38,df_extrato_zig!D:D,"Antecipação") | C38: =SUMIFS(df_extrato_zig!E:E,df_extrato_zig!L:L,Conciliacao!A38,df_extrato_zig!F:F,"DINHEIRO") | D38: =SUMIFS(view_parc_agrup!H:H,view_parc_agrup!G:G,Conciliacao!A38) | E38: =SUMIFS(df_eventos!F:F,df_eventos!H:H,Conciliacao!A38) | F38: =SUMIFS(df_mutuos!M:M,df_mutuos!B:B,Conciliacao!A38) | G38: =SUMIFS(df_bloqueios_judiciais!G:G,df_bloqueios_judiciais!D:D,Conciliacao!A38,df_bloqueios_judiciais!G:G,">0") | H38: =SUMIFS(df_extratos!I:I,df_extratos!F:F,Conciliacao!BE38,df_extratos!G:G,"CREDITO")+SUMIFS(df_extratos!I:I,df_extratos!F:F,Conciliacao!A38,df_extratos!G:G,"CREDITO")+SUMIFS(df_extratos!I:I,df_extratos!F:F,Conciliacao!BF38,df_extratos!G:G,"CREDITO")+SUMIFS(df_extratos!I:I,df_extratos!F:F,Conciliacao!BG38,df_extratos!G:G,"CREDITO")+SUMIFS(df_extratos!I:I,df_extratos!F:F,Conciliacao!BH38,df_extratos!G:G,"CREDITO") | I38: =H38-SUM(B38:G38) | J38: =SUMIFS(df_blueme_sem_parcelamento!E:E,df_blueme_sem_parcelamento!H:H,Conciliacao!A38)*(-1) | K38: =SUMIFS(df_blueme_com_parcelamento!J:J,df_blueme_com_parcelamento!M:M,Conciliacao!A38)*(-1) | L38: =SUMIFS(df_mutuos!N:N,df_mutuos!B:B,Conciliacao!A38)*(-1) | M38: =SUMIFS(df_bloqueios_judiciais!G:G,df_bloqueios_judiciais!D:D,Conciliacao!A38,df_bloqueios_judiciais!G:G,"<0") | N38: =SUMIFS(df_extratos!I:I,df_extratos!F:F,Conciliacao!BE38,df_extratos!G:G,"DEBITO")+SUMIFS(df_extratos!I:I,df_extratos!F:F,Conciliacao!A38,df_extratos!G:G,"DEBITO")+SUMIFS(df_extratos!I:I,df_extratos!F:F,Conciliacao!BF38,df_extratos!G:G,"DEBITO")+SUMIFS(df_extratos!I:I,df_extratos!F:F,Conciliacao!BG38,df_extratos!G:G,"DEBITO")+SUMIFS(df_extratos!I:I,df_extratos!F:F,Conciliacao!BH38,df_extratos!G:G,"DEBITO") | O38: =N38-SUM(J38:M38) | P38: =SUMIFS(df_ajustes_conciliaco!D:D,df_ajustes_conciliaco!C:C,Conciliacao!A38) | Q38: =O38+I38-P38 | BE38: 45694.5 | BF38: 45694.125 | BG38: 45694.542 | BH38: 45694.625
A39: =A38+1 | B39: =-SUMIFS(df_extrato_zig!G:G,df_extrato_zig!E:E,Conciliacao!A39,df_extrato_zig!D:D,"Saque")-SUMIFS(df_extrato_zig!G:G,df_extrato_zig!E:E,Conciliacao!A39,df_extrato_zig!D:D,"Antecipação") | C39: =SUMIFS(df_extrato_zig!E:E,df_extrato_zig!L:L,Conciliacao!A39,df_extrato_zig!F:F,"DINHEIRO") | D39: =SUMIFS(view_parc_agrup!H:H,view_parc_agrup!G:G,Conciliacao!A39) | E39: =SUMIFS(df_eventos!F:F,df_eventos!H:H,Conciliacao!A39) | F39: =SUMIFS(df_mutuos!M:M,df_mutuos!B:B,Conciliacao!A39) | G39: =SUMIFS(df_bloqueios_judiciais!G:G,df_bloqueios_judiciais!D:D,Conciliacao!A39,df_bloqueios_judiciais!G:G,">0") | H39: =SUMIFS(df_extratos!I:I,df_extratos!F:F,Conciliacao!BE39,df_extratos!G:G,"CREDITO")+SUMIFS(df_extratos!I:I,df_extratos!F:F,Conciliacao!A39,df_extratos!G:G,"CREDITO")+SUMIFS(df_extratos!I:I,df_extratos!F:F,Conciliacao!BF39,df_extratos!G:G,"CREDITO")+SUMIFS(df_extratos!I:I,df_extratos!F:F,Conciliacao!BG39,df_extratos!G:G,"CREDITO")+SUMIFS(df_extratos!I:I,df_extratos!F:F,Conciliacao!BH39,df_extratos!G:G,"CREDITO") | I39: =H39-SUM(B39:G39) | J39: =SUMIFS(df_blueme_sem_parcelamento!E:E,df_blueme_sem_parcelamento!H:H,Conciliacao!A39)*(-1) | K39: =SUMIFS(df_blueme_com_parcelamento!J:J,df_blueme_com_parcelamento!M:M,Conciliacao!A39)*(-1) | L39: =SUMIFS(df_mutuos!N:N,df_mutuos!B:B,Conciliacao!A39)*(-1) | M39: =SUMIFS(df_bloqueios_judiciais!G:G,df_bloqueios_judiciais!D:D,Conciliacao!A39,df_bloqueios_judiciais!G:G,"<0") | N39: =SUMIFS(df_extratos!I:I,df_extratos!F:F,Conciliacao!BE39,df_extratos!G:G,"DEBITO")+SUMIFS(df_extratos!I:I,df_extratos!F:F,Conciliacao!A39,df_extratos!G:G,"DEBITO")+SUMIFS(df_extratos!I:I,df_extratos!F:F,Conciliacao!BF39,df_extratos!G:G,"DEBITO")+SUMIFS(df_extratos!I:I,df_extratos!F:F,Conciliacao!BG39,df_extratos!G:G,"DEBITO")+SUMIFS(df_extratos!I:I,df_extratos!F:F,Conciliacao!BH39,df_extratos!G:G,"DEBITO") | O39: =N39-SUM(J39:M39) | P39: =SUMIFS(df_ajustes_conciliaco!D:D,df_ajustes_conciliaco!C:C,Conciliacao!A39) | Q39: =O39+I39-P39 | BE39: 45695.5 | BF39: 45695.125 | BG39: 45695.542 | BH39: 45695.625
A40: =A39+1 | B40: =-SUMIFS(df_extrato_zig!G:G,df_extrato_zig!E:E,Conciliacao!A40,df_extrato_zig!D:D,"Saque")-SUMIFS(df_extrato_zig!G:G,df_extrato_zig!E:E,Conciliacao!A40,df_extrato_zig!D:D,"Antecipação") | C40: =SUMIFS(df_extrato_zig!E:E,df_extrato_zig!L:L,Conciliacao!A40,df_extrato_zig!F:F,"DINHEIRO") | D40: =SUMIFS(view_parc_agrup!H:H,view_parc_agrup!G:G,Conciliacao!A40) | E40: =SUMIFS(df_eventos!F:F,df_eventos!H:H,Conciliacao!A40) | F40: =SUMIFS(df_mutuos!M:M,df_mutuos!B:B,Conciliacao!A40) | G40: =SUMIFS(df_bloqueios_judiciais!G:G,df_bloqueios_judiciais!D:D,Conciliacao!A40,df_bloqueios_judiciais!G:G,">0") | H40: =SUMIFS(df_extratos!I:I,df_extratos!F:F,Conciliacao!BE40,df_extratos!G:G,"CREDITO")+SUMIFS(df_extratos!I:I,df_extratos!F:F,Conciliacao!A40,df_extratos!G:G,"CREDITO")+SUMIFS(df_extratos!I:I,df_extratos!F:F,Conciliacao!BF40,df_extratos!G:G,"CREDITO")+SUMIFS(df_extratos!I:I,df_extratos!F:F,Conciliacao!BG40,df_extratos!G:G,"CREDITO")+SUMIFS(df_extratos!I:I,df_extratos!F:F,Conciliacao!BH40,df_extratos!G:G,"CREDITO") | I40: =H40-SUM(B40:G40) | J40: =SUMIFS(df_blueme_sem_parcelamento!E:E,df_blueme_sem_parcelamento!H:H,Conciliacao!A40)*(-1) | K40: =SUMIFS(df_blueme_com_parcelamento!J:J,df_blueme_com_parcelamento!M:M,Conciliacao!A40)*(-1) | L40: =SUMIFS(df_mutuos!N:N,df_mutuos!B:B,Conciliacao!A40)*(-1) | M40: =SUMIFS(df_bloqueios_judiciais!G:G,df_bloqueios_judiciais!D:D,Conciliacao!A40,df_bloqueios_judiciais!G:G,"<0") | N40: =SUMIFS(df_extratos!I:I,df_extratos!F:F,Conciliacao!BE40,df_extratos!G:G,"DEBITO")+SUMIFS(df_extratos!I:I,df_extratos!F:F,Conciliacao!A40,df_extratos!G:G,"DEBITO")+SUMIFS(df_extratos!I:I,df_extratos!F:F,Conciliacao!BF40,df_extratos!G:G,"DEBITO")+SUMIFS(df_extratos!I:I,df_extratos!F:F,Conciliacao!BG40,df_extratos!G:G,"DEBITO")+SUMIFS(df_extratos!I:I,df_extratos!F:F,Conciliacao!BH40,df_extratos!G:G,"DEBITO") | O40: =N40-SUM(J40:M40) | P40: =SUMIFS(df_ajustes_conciliaco!D:D,df_ajustes_conciliaco!C:C,Conciliacao!A40) | Q40: =O40+I40-P40 | BE40: 45696.5 | BF40: 45696.125 | BG40: 45696.542 | BH40: 45696.625
A41: =A40+1 | B41: =-SUMIFS(df_extrato_zig!G:G,df_extrato_zig!E:E,Conciliacao!A41,df_extrato_zig!D:D,"Saque")-SUMIFS(df_extrato_zig!G:G,df_extrato_zig!E:E,Conciliacao!A41,df_extrato_zig!D:D,"Antecipação") | C41: =SUMIFS(df_extrato_zig!E:E,df_extrato_zig!L:L,Conciliacao!A41,df_extrato_zig!F:F,"DINHEIRO") | D41: =SUMIFS(view_parc_agrup!H:H,view_parc_agrup!G:G,Conciliacao!A41) | E41: =SUMIFS(df_eventos!F:F,df_eventos!H:H,Conciliacao!A41) | F41: =SUMIFS(df_mutuos!M:M,df_mutuos!B:B,Conciliacao!A41) | G41: =SUMIFS(df_bloqueios_judiciais!G:G,df_bloqueios_judiciais!D:D,Conciliacao!A41,df_bloqueios_judiciais!G:G,">0") | H41: =SUMIFS(df_extratos!I:I,df_extratos!F:F,Conciliacao!BE41,df_extratos!G:G,"CREDITO")+SUMIFS(df_extratos!I:I,df_extratos!F:F,Conciliacao!A41,df_extratos!G:G,"CREDITO")+SUMIFS(df_extratos!I:I,df_extratos!F:F,Conciliacao!BF41,df_extratos!G:G,"CREDITO")+SUMIFS(df_extratos!I:I,df_extratos!F:F,Conciliacao!BG41,df_extratos!G:G,"CREDITO")+SUMIFS(df_extratos!I:I,df_extratos!F:F,Conciliacao!BH41,df_extratos!G:G,"CREDITO") | I41: =H41-SUM(B41:G41) | J41: =SUMIFS(df_blueme_sem_parcelamento!E:E,df_blueme_sem_parcelamento!H:H,Conciliacao!A41)*(-1) | K41: =SUMIFS(df_blueme_com_parcelamento!J:J,df_blueme_com_parcelamento!M:M,Conciliacao!A41)*(-1) | L41: =SUMIFS(df_mutuos!N:N,df_mutuos!B:B,Conciliacao!A41)*(-1) | M41: =SUMIFS(df_bloqueios_judiciais!G:G,df_bloqueios_judiciais!D:D,Conciliacao!A41,df_bloqueios_judiciais!G:G,"<0") | N41: =SUMIFS(df_extratos!I:I,df_extratos!F:F,Conciliacao!BE41,df_extratos!G:G,"DEBITO")+SUMIFS(df_extratos!I:I,df_extratos!F:F,Conciliacao!A41,df_extratos!G:G,"DEBITO")+SUMIFS(df_extratos!I:I,df_extratos!F:F,Conciliacao!BF41,df_extratos!G:G,"DEBITO")+SUMIFS(df_extratos!I:I,df_extratos!F:F,Conciliacao!BG41,df_extratos!G:G,"DEBITO")+SUMIFS(df_extratos!I:I,df_extratos!F:F,Conciliacao!BH41,df_extratos!G:G,"DEBITO") | O41: =N41-SUM(J41:M41) | P41: =SUMIFS(df_ajustes_conciliaco!D:D,df_ajustes_conciliaco!C:C,Conciliacao!A41) | Q41: =O41+I41-P41 | BE41: 45697.5 | BF41: 45697.125 | BG41: 45697.542 | BH41: 45697.625
A42: =A41+1 | B42: =-SUMIFS(df_extrato_zig!G:G,df_extrato_zig!E:E,Conciliacao!A42,df_extrato_zig!D:D,"Saque")-SUMIFS(df_extrato_zig!G:G,df_extrato_zig!E:E,Conciliacao!A42,df_extrato_zig!D:D,"Antecipação") | C42: =SUMIFS(df_extrato_zig!E:E,df_extrato_zig!L:L,Conciliacao!A42,df_extrato_zig!F:F,"DINHEIRO") | D42: =SUMIFS(view_parc_agrup!H:H,view_parc_agrup!G:G,Conciliacao!A42) | E42: =SUMIFS(df_eventos!F:F,df_eventos!H:H,Conciliacao!A42) | F42: =SUMIFS(df_mutuos!M:M,df_mutuos!B:B,Conciliacao!A42) | G42: =SUMIFS(df_bloqueios_judiciais!G:G,df_bloqueios_judiciais!D:D,Conciliacao!A42,df_bloqueios_judiciais!G:G,">0") | H42: =SUMIFS(df_extratos!I:I,df_extratos!F:F,Conciliacao!BE42,df_extratos!G:G,"CREDITO")+SUMIFS(df_extratos!I:I,df_extratos!F:F,Conciliacao!A42,df_extratos!G:G,"CREDITO")+SUMIFS(df_extratos!I:I,df_extratos!F:F,Conciliacao!BF42,df_extratos!G:G,"CREDITO")+SUMIFS(df_extratos!I:I,df_extratos!F:F,Conciliacao!BG42,df_extratos!G:G,"CREDITO")+SUMIFS(df_extratos!I:I,df_extratos!F:F,Conciliacao!BH42,df_extratos!G:G,"CREDITO") | I42: =H42-SUM(B42:G42) | J42: =SUMIFS(df_blueme_sem_parcelamento!E:E,df_blueme_sem_parcelamento!H:H,Conciliacao!A42)*(-1) | K42: =SUMIFS(df_blueme_com_parcelamento!J:J,df_blueme_com_parcelamento!M:M,Conciliacao!A42)*(-1) | L42: =SUMIFS(df_mutuos!N:N,df_mutuos!B:B,Conciliacao!A42)*(-1) | M42: =SUMIFS(df_bloqueios_judiciais!G:G,df_bloqueios_judiciais!D:D,Conciliacao!A42,df_bloqueios_judiciais!G:G,"<0") | N42: =SUMIFS(df_extratos!I:I,df_extratos!F:F,Conciliacao!BE42,df_extratos!G:G,"DEBITO")+SUMIFS(df_extratos!I:I,df_extratos!F:F,Conciliacao!A42,df_extratos!G:G,"DEBITO")+SUMIFS(df_extratos!I:I,df_extratos!F:F,Conciliacao!BF42,df_extratos!G:G,"DEBITO")+SUMIFS(df_extratos!I:I,df_extratos!F:F,Conciliacao!BG42,df_extratos!G:G,"DEBITO")+SUMIFS(df_extratos!I:I,df_extratos!F:F,Conciliacao!BH42,df_extratos!G:G,"DEBITO") | O42: =N42-SUM(J42:M42) | P42: =SUMIFS(df_ajustes_conciliaco!D:D,df_ajustes_conciliaco!C:C,Conciliacao!A42) | Q42: =O42+I42-P42 | BE42: 45698.5 | BF42: 45698.125 | BG42: 45698.542 | BH42: 45698.625
A43: =A42+1 | B43: =-SUMIFS(df_extrato_zig!G:G,df_extrato_zig!E:E,Conciliacao!A43,df_extrato_zig!D:D,"Saque")-SUMIFS(df_extrato_zig!G:G,df_extrato_zig!E:E,Conciliacao!A43,df_extrato_zig!D:D,"Antecipação") | C43: =SUMIFS(df_extrato_zig!E:E,df_extrato_zig!L:L,Conciliacao!A43,df_extrato_zig!F:F,"DINHEIRO") | D43: =SUMIFS(view_parc_agrup!H:H,view_parc_agrup!G:G,Conciliacao!A43) | E43: =SUMIFS(df_eventos!F:F,df_eventos!H:H,Conciliacao!A43) | F43: =SUMIFS(df_mutuos!M:M,df_mutuos!B:B,Conciliacao!A43) | G43: =SUMIFS(df_bloqueios_judiciais!G:G,df_bloqueios_judiciais!D:D,Conciliacao!A43,df_bloqueios_judiciais!G:G,">0") | H43: =SUMIFS(df_extratos!I:I,df_extratos!F:F,Conciliacao!BE43,df_extratos!G:G,"CREDITO")+SUMIFS(df_extratos!I:I,df_extratos!F:F,Conciliacao!A43,df_extratos!G:G,"CREDITO")+SUMIFS(df_extratos!I:I,df_extratos!F:F,Conciliacao!BF43,df_extratos!G:G,"CREDITO")+SUMIFS(df_extratos!I:I,df_extratos!F:F,Conciliacao!BG43,df_extratos!G:G,"CREDITO")+SUMIFS(df_extratos!I:I,df_extratos!F:F,Conciliacao!BH43,df_extratos!G:G,"CREDITO") | I43: =H43-SUM(B43:G43) | J43: =SUMIFS(df_blueme_sem_parcelamento!E:E,df_blueme_sem_parcelamento!H:H,Conciliacao!A43)*(-1) | K43: =SUMIFS(df_blueme_com_parcelamento!J:J,df_blueme_com_parcelamento!M:M,Conciliacao!A43)*(-1) | L43: =SUMIFS(df_mutuos!N:N,df_mutuos!B:B,Conciliacao!A43)*(-1) | M43: =SUMIFS(df_bloqueios_judiciais!G:G,df_bloqueios_judiciais!D:D,Conciliacao!A43,df_bloqueios_judiciais!G:G,"<0") | N43: =SUMIFS(df_extratos!I:I,df_extratos!F:F,Conciliacao!BE43,df_extratos!G:G,"DEBITO")+SUMIFS(df_extratos!I:I,df_extratos!F:F,Conciliacao!A43,df_extratos!G:G,"DEBITO")+SUMIFS(df_extratos!I:I,df_extratos!F:F,Conciliacao!BF43,df_extratos!G:G,"DEBITO")+SUMIFS(df_extratos!I:I,df_extratos!F:F,Conciliacao!BG43,df_extratos!G:G,"DEBITO")+SUMIFS(df_extratos!I:I,df_extratos!F:F,Conciliacao!BH43,df_extratos!G:G,"DEBITO") | O43: =N43-SUM(J43:M43) | P43: =SUMIFS(df_ajustes_conciliaco!D:D,df_ajustes_conciliaco!C:C,Conciliacao!A43) | Q43: =O43+I43-P43 | BE43: 45699.5 | BF43: 45699.125 | BG43: 45699.542 | BH43: 45699.625
A44: =A43+1 | B44: =-SUMIFS(df_extrato_zig!G:G,df_extrato_zig!E:E,Conciliacao!A44,df_extrato_zig!D:D,"Saque")-SUMIFS(df_extrato_zig!G:G,df_extrato_zig!E:E,Conciliacao!A44,df_extrato_zig!D:D,"Antecipação") | C44: =SUMIFS(df_extrato_zig!E:E,df_extrato_zig!L:L,Conciliacao!A44,df_extrato_zig!F:F,"DINHEIRO") | D44: =SUMIFS(view_parc_agrup!H:H,view_parc_agrup!G:G,Conciliacao!A44) | E44: =SUMIFS(df_eventos!F:F,df_eventos!H:H,Conciliacao!A44) | F44: =SUMIFS(df_mutuos!M:M,df_mutuos!B:B,Conciliacao!A44) | G44: =SUMIFS(df_bloqueios_judiciais!G:G,df_bloqueios_judiciais!D:D,Conciliacao!A44,df_bloqueios_judiciais!G:G,">0") | H44: =SUMIFS(df_extratos!I:I,df_extratos!F:F,Conciliacao!BE44,df_extratos!G:G,"CREDITO")+SUMIFS(df_extratos!I:I,df_extratos!F:F,Conciliacao!A44,df_extratos!G:G,"CREDITO")+SUMIFS(df_extratos!I:I,df_extratos!F:F,Conciliacao!BF44,df_extratos!G:G,"CREDITO")+SUMIFS(df_extratos!I:I,df_extratos!F:F,Conciliacao!BG44,df_extratos!G:G,"CREDITO")+SUMIFS(df_extratos!I:I,df_extratos!F:F,Conciliacao!BH44,df_extratos!G:G,"CREDITO") | I44: =H44-SUM(B44:G44) | J44: =SUMIFS(df_blueme_sem_parcelamento!E:E,df_blueme_sem_parcelamento!H:H,Conciliacao!A44)*(-1) | K44: =SUMIFS(df_blueme_com_parcelamento!J:J,df_blueme_com_parcelamento!M:M,Conciliacao!A44)*(-1) | L44: =SUMIFS(df_mutuos!N:N,df_mutuos!B:B,Conciliacao!A44)*(-1) | M44: =SUMIFS(df_bloqueios_judiciais!G:G,df_bloqueios_judiciais!D:D,Conciliacao!A44,df_bloqueios_judiciais!G:G,"<0") | N44: =SUMIFS(df_extratos!I:I,df_extratos!F:F,Conciliacao!BE44,df_extratos!G:G,"DEBITO")+SUMIFS(df_extratos!I:I,df_extratos!F:F,Conciliacao!A44,df_extratos!G:G,"DEBITO")+SUMIFS(df_extratos!I:I,df_extratos!F:F,Conciliacao!BF44,df_extratos!G:G,"DEBITO")+SUMIFS(df_extratos!I:I,df_extratos!F:F,Conciliacao!BG44,df_extratos!G:G,"DEBITO")+SUMIFS(df_extratos!I:I,df_extratos!F:F,Conciliacao!BH44,df_extratos!G:G,"DEBITO") | O44: =N44-SUM(J44:M44) | P44: =SUMIFS(df_ajustes_conciliaco!D:D,df_ajustes_conciliaco!C:C,Conciliacao!A44) | Q44: =O44+I44-P44 | BE44: 45700.5 | BF44: 45700.125 | BG44: 45700.542 | BH44: 45700.625
A45: =A44+1 | B45: =-SUMIFS(df_extrato_zig!G:G,df_extrato_zig!E:E,Conciliacao!A45,df_extrato_zig!D:D,"Saque")-SUMIFS(df_extrato_zig!G:G,df_extrato_zig!E:E,Conciliacao!A45,df_extrato_zig!D:D,"Antecipação") | C45: =SUMIFS(df_extrato_zig!E:E,df_extrato_zig!L:L,Conciliacao!A45,df_extrato_zig!F:F,"DINHEIRO") | D45: =SUMIFS(view_parc_agrup!H:H,view_parc_agrup!G:G,Conciliacao!A45) | E45: =SUMIFS(df_eventos!F:F,df_eventos!H:H,Conciliacao!A45) | F45: =SUMIFS(df_mutuos!M:M,df_mutuos!B:B,Conciliacao!A45) | G45: =SUMIFS(df_bloqueios_judiciais!G:G,df_bloqueios_judiciais!D:D,Conciliacao!A45,df_bloqueios_judiciais!G:G,">0") | H45: =SUMIFS(df_extratos!I:I,df_extratos!F:F,Conciliacao!BE45,df_extratos!G:G,"CREDITO")+SUMIFS(df_extratos!I:I,df_extratos!F:F,Conciliacao!A45,df_extratos!G:G,"CREDITO")+SUMIFS(df_extratos!I:I,df_extratos!F:F,Conciliacao!BF45,df_extratos!G:G,"CREDITO")+SUMIFS(df_extratos!I:I,df_extratos!F:F,Conciliacao!BG45,df_extratos!G:G,"CREDITO")+SUMIFS(df_extratos!I:I,df_extratos!F:F,Conciliacao!BH45,df_extratos!G:G,"CREDITO") | I45: =H45-SUM(B45:G45) | J45: =SUMIFS(df_blueme_sem_parcelamento!E:E,df_blueme_sem_parcelamento!H:H,Conciliacao!A45)*(-1) | K45: =SUMIFS(df_blueme_com_parcelamento!J:J,df_blueme_com_parcelamento!M:M,Conciliacao!A45)*(-1) | L45: =SUMIFS(df_mutuos!N:N,df_mutuos!B:B,Conciliacao!A45)*(-1) | M45: =SUMIFS(df_bloqueios_judiciais!G:G,df_bloqueios_judiciais!D:D,Conciliacao!A45,df_bloqueios_judiciais!G:G,"<0") | N45: =SUMIFS(df_extratos!I:I,df_extratos!F:F,Conciliacao!BE45,df_extratos!G:G,"DEBITO")+SUMIFS(df_extratos!I:I,df_extratos!F:F,Conciliacao!A45,df_extratos!G:G,"DEBITO")+SUMIFS(df_extratos!I:I,df_extratos!F:F,Conciliacao!BF45,df_extratos!G:G,"DEBITO")+SUMIFS(df_extratos!I:I,df_extratos!F:F,Conciliacao!BG45,df_extratos!G:G,"DEBITO")+SUMIFS(df_extratos!I:I,df_extratos!F:F,Conciliacao!BH45,df_extratos!G:G,"DEBITO") | O45: =N45-SUM(J45:M45) | P45: =SUMIFS(df_ajustes_conciliaco!D:D,df_ajustes_conciliaco!C:C,Conciliacao!A45) | Q45: =O45+I45-P45 | BE45: 45701.5 | BF45: 45701.125 | BG45: 45701.542 | BH45: 45701.625
A46: =A45+1 | B46: =-SUMIFS(df_extrato_zig!G:G,df_extrato_zig!E:E,Conciliacao!A46,df_extrato_zig!D:D,"Saque")-SUMIFS(df_extrato_zig!G:G,df_extrato_zig!E:E,Conciliacao!A46,df_extrato_zig!D:D,"Antecipação") | C46: =SUMIFS(df_extrato_zig!E:E,df_extrato_zig!L:L,Conciliacao!A46,df_extrato_zig!F:F,"DINHEIRO") | D46: =SUMIFS(view_parc_agrup!H:H,view_parc_agrup!G:G,Conciliacao!A46) | E46: =SUMIFS(df_eventos!F:F,df_eventos!H:H,Conciliacao!A46) | F46: =SUMIFS(df_mutuos!M:M,df_mutuos!B:B,Conciliacao!A46) | G46: =SUMIFS(df_bloqueios_judiciais!G:G,df_bloqueios_judiciais!D:D,Conciliacao!A46,df_bloqueios_judiciais!G:G,">0") | H46: =SUMIFS(df_extratos!I:I,df_extratos!F:F,Conciliacao!BE46,df_extratos!G:G,"CREDITO")+SUMIFS(df_extratos!I:I,df_extratos!F:F,Conciliacao!A46,df_extratos!G:G,"CREDITO")+SUMIFS(df_extratos!I:I,df_extratos!F:F,Conciliacao!BF46,df_extratos!G:G,"CREDITO")+SUMIFS(df_extratos!I:I,df_extratos!F:F,Conciliacao!BG46,df_extratos!G:G,"CREDITO")+SUMIFS(df_extratos!I:I,df_extratos!F:F,Conciliacao!BH46,df_extratos!G:G,"CREDITO") | I46: =H46-SUM(B46:G46) | J46: =SUMIFS(df_blueme_sem_parcelamento!E:E,df_blueme_sem_parcelamento!H:H,Conciliacao!A46)*(-1) | K46: =SUMIFS(df_blueme_com_parcelamento!J:J,df_blueme_com_parcelamento!M:M,Conciliacao!A46)*(-1) | L46: =SUMIFS(df_mutuos!N:N,df_mutuos!B:B,Conciliacao!A46)*(-1) | M46: =SUMIFS(df_bloqueios_judiciais!G:G,df_bloqueios_judiciais!D:D,Conciliacao!A46,df_bloqueios_judiciais!G:G,"<0") | N46: =SUMIFS(df_extratos!I:I,df_extratos!F:F,Conciliacao!BE46,df_extratos!G:G,"DEBITO")+SUMIFS(df_extratos!I:I,df_extratos!F:F,Conciliacao!A46,df_extratos!G:G,"DEBITO")+SUMIFS(df_extratos!I:I,df_extratos!F:F,Conciliacao!BF46,df_extratos!G:G,"DEBITO")+SUMIFS(df_extratos!I:I,df_extratos!F:F,Conciliacao!BG46,df_extratos!G:G,"DEBITO")+SUMIFS(df_extratos!I:I,df_extratos!F:F,Conciliacao!BH46,df_extratos!G:G,"DEBITO") | O46: =N46-SUM(J46:M46) | P46: =SUMIFS(df_ajustes_conciliaco!D:D,df_ajustes_conciliaco!C:C,Conciliacao!A46) | Q46: =O46+I46-P46 | BE46: 45702.5 | BF46: 45702.125 | BG46: 45702.542 | BH46: 45702.625
... A731: =A730+1 | B731: =-SUMIFS(df_extrato_zig!G:G,df_extrato_zig!E:E,Conciliacao!A731,df_extrato_zig!D:D,"Saque")-SUMIFS(df_extrato_zig!G:G,df_extrato_zig!E:E,Conciliacao!A731,df_extrato_zig!D:D,"Antecipação") | C731: =SUMIFS(df_extrato_zig!E:E,df_extrato_zig!L:L,Conciliacao!A731,df_extrato_zig!F:F,"DINHEIRO") | D731: =SUMIFS(view_parc_agrup!H:H,view_parc_agrup!G:G,Conciliacao!A731) | E731: =SUMIFS(df_eventos!F:F,df_eventos!H:H,Conciliacao!A731) | F731: =SUMIFS(df_mutuos!M:M,df_mutuos!B:B,Conciliacao!A731) | G731: =SUMIFS(df_bloqueios_judiciais!G:G,df_bloqueios_judiciais!D:D,Conciliacao!A731,df_bloqueios_judiciais!G:G,">0") | H731: =SUMIFS(df_extratos!I:I,df_extratos!F:F,Conciliacao!BE731,df_extratos!G:G,"CREDITO")+SUMIFS(df_extratos!I:I,df_extratos!F:F,Conciliacao!A731,df_extratos!G:G,"CREDITO")+SUMIFS(df_extratos!I:I,df_extratos!F:F,Conciliacao!BF731,df_extratos!G:G,"CREDITO")+SUMIFS(df_extratos!I:I,df_extratos!F:F,Conciliacao!BG731,df_extratos!G:G,"CREDITO")+SUMIFS(df_extratos!I:I,df_extratos!F:F,Conciliacao!BH731,df_extratos!G:G,"CREDITO") | I731: =H731-SUM(B731:G731) | J731: =SUMIFS(df_blueme_sem_parcelamento!E:E,df_blueme_sem_parcelamento!H:H,Conciliacao!A731)*(-1) | K731: =SUMIFS(df_blueme_com_parcelamento!J:J,df_blueme_com_parcelamento!M:M,Conciliacao!A731)*(-1) | L731: =SUMIFS(df_mutuos!N:N,df_mutuos!B:B,Conciliacao!A731)*(-1) | M731: =SUMIFS(df_bloqueios_judiciais!G:G,df_bloqueios_judiciais!D:D,Conciliacao!A731,df_bloqueios_judiciais!G:G,"<0") | N731: =SUMIFS(df_extratos!I:I,df_extratos!F:F,Conciliacao!BE731,df_extratos!G:G,"DEBITO")+SUMIFS(df_extratos!I:I,df_extratos!F:F,Conciliacao!A731,df_extratos!G:G,"DEBITO")+SUMIFS(df_extratos!I:I,df_extratos!F:F,Conciliacao!BF731,df_extratos!G:G,"DEBITO")+SUMIFS(df_extratos!I:I,df_extratos!F:F,Conciliacao!BG731,df_extratos!G:G,"DEBITO")+SUMIFS(df_extratos!I:I,df_extratos!F:F,Conciliacao!BH731,df_extratos!G:G,"DEBITO") | O731: =N731-SUM(J731:M731) | P731: =SUMIFS(df_ajustes_conciliaco!D:D,df_ajustes_conciliaco!C:C,Conciliacao!A731) | Q731: =O731+I731-P731 | BE731: 46387.5 | BF731: 46387.125 | BG731: 46387.542 | BH731: 46029.625

Sheet df_extrato_zig
A1: ID_Extrato | B1: ID_Casa | C1: Casa | D1: Descricao | E1: Data_Liquidacao | F1: Data_Transacao | G1: Valor
A2: 51087 | B2: 176 | C2: The Cavern | D2: Saldo Inicial | E2: 46099 | F2: 46099 | G2: -819046.2
A3: 51088 | B3: 176 | C3: The Cavern | D3: Saque | E3: 46099 | F3: 46099 | G3: -716
A4: 51089 | B4: 176 | C4: The Cavern | D4: Saldo Inicial | E4: 46099 | F4: 46099 | G4: -213926
A5: 51090 | B5: 176 | C5: The Cavern | D5: Saque | E5: 46099 | F5: 46099 | G5: -5175
A6: 51057 | B6: 176 | C6: The Cavern | D6: Saque | E6: 46098 | F6: 46098 | G6: -935
A7: 51056 | B7: 176 | C7: The Cavern | D7: Saldo Inicial | E7: 46098 | F7: 46098 | G7: -212991
A8: 51055 | B8: 176 | C8: The Cavern | D8: Saque | E8: 46098 | F8: 46098 | G8: -491
A9: 51054 | B9: 176 | C9: The Cavern | D9: Saldo Inicial | E9: 46098 | F9: 46098 | G9: -818555.2
A10: 51022 | B10: 176 | C10: The Cavern | D10: Saldo Inicial | E10: 46097 | F10: 46097 | G10: -207672
A11: 51020 | B11: 176 | C11: The Cavern | D11: Saldo Inicial | E11: 46097 | F11: 46097 | G11: -761878.2
A12: 51021 | B12: 176 | C12: The Cavern | D12: Saque | E12: 46097 | F12: 46097 | G12: -56677
A13: 51023 | B13: 176 | C13: The Cavern | D13: Saque | E13: 46097 | F13: 46097 | G13: -5319
... A228: 48771 | B228: 176 | C228: The Cavern | D228: Saldo Inicial | E228: 46023 | F228: 46023 | G228: -326626.42

Sheet df_zig_faturam
A1: ID_Casa | B1: Casa | C1: Data_Venda | D1: Valor | E1: Tipo_Pagamento
A2: 176 | B2: The Cavern | C2: 46099 | D2: 0 | E2: DELIVERY ONLINE
A3: 176 | B3: The Cavern | C3: 46099 | D3: 300.58 | E3: DÉBITO
A4: 176 | B4: The Cavern | C4: 46099 | D4: 0 | E4: DINHEIRO
A5: 176 | B5: The Cavern | C5: 46099 | D5: 0 | E5: APP
A6: 176 | B6: The Cavern | C6: 46099 | D6: 0 | E6: DELIVERY ONLINE
A7: 176 | B7: The Cavern | C7: 46099 | D7: 0 | E7: IFOOD
A8: 176 | B8: The Cavern | C8: 46099 | D8: 0 | E8: PIX
A9: 176 | B9: The Cavern | C9: 46099 | D9: 0 | E9: RAPPI
A10: 176 | B10: The Cavern | C10: 46099 | D10: 0 | E10: UBER
A11: 176 | B11: The Cavern | C11: 46099 | D11: 0 | E11: ANTECIPADO
A12: 176 | B12: The Cavern | C12: 46099 | D12: 0 | E12: VOUCHER
A13: 176 | B13: The Cavern | C13: 46099 | D13: 3120.67 | E13: CRÉDITO
... A2566: 176 | B2566: The Cavern | C2566: 46030 | D2566: 100 | E2566: DINHEIRO

Sheet view_parc_agrup
A1: ID_Receita | B1: ID_Casa | C1: Casa | D1: Cliente | E1: Data_Ocorrencia | F1: Vencimento_Parcela | G1: Recebimento_Parcela | H1: Valor_Parcela | I1: Doc_NF | J1: Classif_Receita | K1: Forma_Pagamento | L1: Status_Pgto | M1: Conta_Bancaria | N1: Observacoes
A2: 11309 | B2: 176 | C2: The Cavern | D2: LIRIUM RECICLAGEM | E2: 46080 | F2: 46101 | G2: 46091 | H2: 351 | J2: Coleta de Óleo | K2: Transferência Bancária ou Pix | L2: Pago | M2: The Cavern - Kamino | N2: COLETA DE OLEO VEGETAL - 130 LITROS - REF. 02/2026
A3: 11225 | B3: 176 | C3: The Cavern | D3: A CAVERNA BAR LTDA | E3: 46083 | F3: 46085 | G3: 46085 | H3: 5000 | J3: Aporte | K3: Transferência Bancária ou Pix | L3: Pago | M3: The Cavern - Kamino | N3: APORTE - 03/2026
A4: 11225 | B4: 176 | C4: The Cavern | D4: A CAVERNA BAR LTDA | E4: 46083 | F4: 46083 | G4: 46083 | H4: 65000 | J4: Aporte | K4: Transferência Bancária ou Pix | L4: Pago | M4: The Cavern - Kamino | N4: APORTE - 03/2026
A5: 11223 | B5: 176 | C5: The Cavern | D5: A CAVERNA BAR LTDA | E5: 46080 | F5: 46080 | G5: 46080 | H5: 25000 | J5: Aporte | K5: Transferência Bancária ou Pix | L5: Pago | M5: The Cavern - Kamino | N5: APORTE - 02/2026
A6: 11163 | B6: 176 | C6: The Cavern | D6: A CAVERNA BAR LTDA | E6: 46078 | F6: 46078 | G6: 46078 | H6: 3300 | J6: Aporte | K6: Transferência Bancária ou Pix | L6: Pago | M6: The Cavern - Kamino | N6: APORTE DOS SOCIOS - 02/2026
A7: 11145 | B7: 176 | C7: The Cavern | D7: A CAVERNA BAR LTDA | E7: 46077 | F7: 46077 | G7: 46077 | H7: 600 | J7: Aporte | K7: Transferência Bancária ou Pix | L7: Pago | M7: The Cavern - Kamino
A8: 11054 | B8: 176 | C8: The Cavern | D8: A CAVERNA BAR LTDA | E8: 46073 | F8: 46076 | G8: 46076 | H8: 7906.15 | J8: Aporte | K8: Transferência Bancária ou Pix | L8: Pago | M8: The Cavern - Kamino | N8: APORTE DOS SOCIOS - 02/2026
A9: 11054 | B9: 176 | C9: The Cavern | D9: A CAVERNA BAR LTDA | E9: 46073 | F9: 46073 | G9: 46073 | H9: 13303.5 | J9: Aporte | K9: Transferência Bancária ou Pix | L9: Pago | M9: The Cavern - Kamino | N9: APORTE DOS SOCIOS - 02/2026
A10: 10899 | B10: 176 | C10: The Cavern | D10: A CAVERNA BAR LTDA | E10: 46062 | F10: 46072 | G10: 46072 | H10: 8000 | J10: Aporte | K10: Transferência Bancária ou Pix | L10: Pago | M10: The Cavern - Kamino | N10: APORTE DOS SOCIOS - 02/2026
A11: 10899 | B11: 176 | C11: The Cavern | D11: A CAVERNA BAR LTDA | E11: 46062 | F11: 46071 | G11: 46071 | H11: 35687.25 | J11: Aporte | K11: Transferência Bancária ou Pix | L11: Pago | M11: The Cavern - Kamino | N11: APORTE DOS SOCIOS - 02/2026
A12: 11362 | B12: 176 | C12: The Cavern | D12: A CAVERNA BAR LTDA | E12: 46066 | F12: 46066 | G12: 46066 | H12: 8500 | J12: Aporte | K12: Transferência Bancária ou Pix | L12: Pago | M12: The Cavern - Kamino | N12: Aporte - 02/2026
A13: 10899 | B13: 176 | C13: The Cavern | D13: A CAVERNA BAR LTDA | E13: 46062 | F13: 46064 | G13: 46064 | H13: 14000 | J13: Aporte | K13: Transferência Bancária ou Pix | L13: Pago | M13: The Cavern - Kamino | N13: APORTE DOS SOCIOS - 02/2026
A14: 10899 | B14: 176 | C14: The Cavern | D14: A CAVERNA BAR LTDA | E14: 46062 | F14: 46063 | G14: 46063 | H14: 3550 | J14: Aporte | K14: Transferência Bancária ou Pix | L14: Pago | M14: The Cavern - Kamino | N14: APORTE DOS SOCIOS - 02/2026
A15: 10899 | B15: 176 | C15: The Cavern | D15: A CAVERNA BAR LTDA | E15: 46062 | F15: 46062 | G15: 46062 | H15: 12435.21 | J15: Aporte | K15: Transferência Bancária ou Pix | L15: Pago | M15: The Cavern - Kamino | N15: APORTE DOS SOCIOS - 02/2026

Sheet df_eventos
A1: ID_Evento | B1: Nome_Evento | C1: ID_Casa | D1: Casa | E1: ID_Parcela | F1: Valor_Parcela | G1: Vencimento_Parcela | H1: Recebimento_Parcela | I1: Status_Pgto | J1: Forma_Pgto | K1: ID_Conta_Bancaria | L1: Conta_Bancaria | M1: Observacoes

Sheet df_blueme_sem_parcelamento
A1: ID_Despesa | B1: ID_Casa | C1: Casa | D1: Fornecedor | E1: Valor | F1: Data_Vencimento | G1: Previsao_Pgto | H1: Realizacao_Pgto | I1: Data_Competencia | J1: Data_Lancamento | K1: Forma_Pagamento | L1: Class_Cont_1 | M1: Class_Cont_2 | N1: Doc_NF | O1: Status_Conf_Document | P1: Status_Aprov_Diret | Q1: Status_Aprov_Caixa | R1: Status_Pgto | S1: ID_Conta_Bancaria | T1: Conta_Bancaria | U1: CNPJ_Loja
A2: 209346 | B2: 176 | C2: The Cavern | D2: MARIO PEDRO FELICIANO - HORTIFRUTI | E2: 193.47 | F2: 46099 | G2: 46099 | H2: 46099 | I2: 46071 | J2: 46072 | K2: Boleto Bancário | L2: Custo Mercadoria Vendida | M2: Insumos - Alimentos | N2: 468095 | O2: Documentação Aprovada | P2: Aprovado Diretoria | Q2: Aprovado Caixa | R2: Pago | S2: 226 | T2: The Cavern - Kamino
A3: 209323 | B3: 176 | C3: The Cavern | D3: HORTIFRUTI DO CHEF LTDA | E3: 118.78 | F3: 46099 | G3: 46099 | H3: 46099 | I3: 46071 | J3: 46072 | K3: Boleto Bancário | L3: Custo Mercadoria Vendida | M3: Insumos - Alimentos | N3: 29184 | O3: Documentação Aprovada | P3: Aprovado Diretoria | Q3: Aprovado Caixa | R3: Pago | S3: 226 | T3: The Cavern - Kamino
A4: 209331 | B4: 176 | C4: The Cavern | D4: CECILIA TSUYACO ARAKI SILVA LTDA | E4: 48.65 | F4: 46099 | G4: 46099 | H4: 46099 | I4: 46071 | J4: 46072 | K4: Boleto Bancário | L4: Custo Mercadoria Vendida | M4: Insumos - Alimentos | N4: 387093 | O4: Documentação Aprovada | P4: Aprovado Diretoria | Q4: Aprovado Caixa | R4: Pago | S4: 226 | T4: The Cavern - Kamino
A5: 212823 | B5: 176 | C5: The Cavern | D5: PROAUTO INDUSTRIA QUIMICA EIRELI | E5: 1377.54 | F5: 46099 | G5: 46099 | H5: 46099 | I5: 46078 | J5: 46083 | K5: Boleto Bancário | L5: Utilidades | M5: Higiene e Limpeza | N5: 152297 | O5: Documentação Aprovada | P5: Aprovado Diretoria | Q5: Aprovado Caixa | R5: Pago | S5: 226 | T5: The Cavern - Kamino
A6: 215853 | B6: 176 | C6: The Cavern | D6: SPON DISTRIBUIDORA DE BEBIDAS LTDA | E6: 167.76 | F6: 46099 | G6: 46099 | H6: 46099 | I6: 46091 | J6: 46092 | K6: Boleto Bancário | L6: Custo Mercadoria Vendida | M6: Insumos - Bebidas | N6: 157622 | O6: Documentação Aprovada | P6: Aprovado Diretoria | Q6: Aprovado Caixa | R6: Pago | S6: 226 | T6: The Cavern - Kamino
A7: 215956 | B7: 176 | C7: The Cavern | D7: RCS COMERCIAL DE ALIMENTOS LTDA | E7: 153.5 | F7: 46099 | G7: 46099 | H7: 46099 | I7: 46085 | J7: 46092 | K7: Boleto Bancário | L7: Custo Mercadoria Vendida | M7: Insumos - Alimentos | N7: 11155 | O7: Documentação Aprovada | P7: Aprovado Diretoria | Q7: Aprovado Caixa | R7: Pago | S7: 226 | T7: The Cavern - Kamino
A8: 215829 | B8: 176 | C8: The Cavern | D8: INDUSTRIA DE BEBIDAS IGARASSU LTDA | E8: 4727.23 | F8: 46099 | G8: 46099 | H8: 46099 | I8: 46084 | J8: 46092 | K8: Boleto Bancário | L8: Custo Mercadoria Vendida | M8: Insumos - Bebidas | N8: 70114 | O8: Documentação Aprovada | P8: Aprovado Diretoria | Q8: Aprovado Caixa | R8: Pago | S8: 226 | T8: The Cavern - Kamino
A9: 215618 | B9: 176 | C9: The Cavern | D9: HENRIQUE DE LIMA RAMOS | E9: 575.55 | F9: 46098 | G9: 46098 | H9: 46098 | I9: 46091 | J9: 46091 | K9: Transferência Bancária ou Pix | L9: Mão de Obra - Extra | M9: Mão de Obra Extra | N9: 6517032026 | O9: Documentação Aprovada | P9: Aprovado Diretoria | Q9: Aprovado Caixa | R9: Pago | S9: 226 | T9: The Cavern - Kamino
A10: 215470 | B10: 176 | C10: The Cavern | D10: HNK BR INDUSTRIA DE BEBIDAS | E10: 1635.5 | F10: 46098 | G10: 46098 | H10: 46098 | I10: 46083 | J10: 46091 | K10: Boleto Bancário | L10: Custo Mercadoria Vendida | M10: Insumos - Bebidas | N10: 169110 | O10: Documentação Aprovada | P10: Aprovado Diretoria | Q10: Aprovado Caixa | R10: Pago | S10: 226 | T10: The Cavern - Kamino
A11: 215149 | B11: 176 | C11: The Cavern | D11: PAULO SERGIO LOPES MARTINS DE FREITAS | E11: 6600 | F11: 46091 | G11: 46097 | H11: 46097 | I11: 46054 | J11: 46088 | K11: Transferência Bancária ou Pix | L11: Mão de Obra - PJ | M11: MDO PJ Fixo | N11: 190 | O11: Documentação Aprovada | P11: Aprovado Diretoria | Q11: Aprovado Caixa | R11: Pago | S11: 226 | T11: The Cavern - Kamino
A12: 215795 | B12: 176 | C12: The Cavern | D12: MAR DIRETO POC COMERCIO DE PEIXES LTDA | E12: 1365 | F12: 46097 | G12: 46097 | H12: 46097 | I12: 46086 | J12: 46092 | K12: Boleto Bancário | L12: Custo Mercadoria Vendida | M12: Insumos - Alimentos | N12: 118398 | O12: Documentação Aprovada | P12: Aprovado Diretoria | Q12: Aprovado Caixa | R12: Pago | S12: 226 | T12: The Cavern - Kamino
A13: 209403 | B13: 176 | C13: The Cavern | D13: F & C ASSESSORIA CONTABIL LTDA | E13: 1000 | F13: 46097 | G13: 46097 | H13: 46097 | I13: 46081 | J13: 46072 | K13: Boleto Bancário | L13: Serviços de Terceiros | M13: Assessoria Contabil | N13: 2379116032026 | O13: Documentação Aprovada | P13: Aprovado Diretoria | Q13: Aprovado Caixa | R13: Pago | S13: 226 | T13: The Cavern - Kamino
... A76: 213427 | B76: 176 | C76: The Cavern | D76: VIRTUAL MARKET SERVICOS ELETRONICOS LTDA | E76: 329.9 | F76: 46090 | G76: 46090 | H76: 46090 | I76: 46085 | J76: 46085 | K76: Boleto Bancário | L76: Informática e TI | M76: Sistemas Gerais - Operacionais | N76: 4509009032026 | O76: Documentação Aprovada | P76: Aprovado Diretoria | Q76: Aprovado Caixa | R76: Pago | S76: 226 | T76: The Cavern - Kamino
A77: 214650 | B77: 176 | C77: The Cavern | D77: ALINE CRISTINA DA SILVA | E77: 2092.23 | F77: 46087 | G77: 46087 | H77: 46087 | I77: 46081 | L77: Mão de Obra - Salários | M77: MDO CLT - Salário | O77: Documentação Aprovada | P77: Aprovado Diretoria | Q77: Aprovado Caixa | R77: Pago | S77: 226 | T77: The Cavern - Kamino
A78: 214641 | B78: 176 | C78: The Cavern | D78: ISMAEL SANTOS SILVA | E78: 2105.21 | F78: 46087 | G78: 46087 | H78: 46087 | I78: 46081 | L78: Mão de Obra - Salários | M78: MDO CLT - Salário | O78: Documentação Aprovada | P78: Aprovado Diretoria | Q78: Aprovado Caixa | R78: Pago | S78: 226 | T78: The Cavern - Kamino
A79: 214642 | B79: 176 | C79: The Cavern | D79: VAGNER BRANDAO | E79: 1800.66 | F79: 46087 | G79: 46087 | H79: 46087 | I79: 46081 | L79: Mão de Obra - Salários | M79: MDO CLT - Salário | O79: Documentação Aprovada | P79: Aprovado Diretoria | Q79: Aprovado Caixa | R79: Pago | S79: 226 | T79: The Cavern - Kamino
A80: 214643 | B80: 176 | C80: The Cavern | D80: CARLOS ALBERTO FERREIRA PIMENTEL | E80: 2199.59 | F80: 46087 | G80: 46087 | H80: 46087 | I80: 46081 | L80: Mão de Obra - Salários | M80: MDO CLT - Salário | O80: Documentação Aprovada | P80: Aprovado Diretoria | Q80: Aprovado Caixa | R80: Pago | S80: 226 | T80: The Cavern - Kamino
A81: 214644 | B81: 176 | C81: The Cavern | D81: EMILY RENATA MENDONCA VIEIRA | E81: 1277.87 | F81: 46087 | G81: 46087 | H81: 46087 | I81: 46081 | L81: Mão de Obra - Salários | M81: MDO CLT - Salário | O81: Documentação Aprovada | P81: Aprovado Diretoria | Q81: Aprovado Caixa | R81: Pago | S81: 226 | T81: The Cavern - Kamino
A82: 214645 | B82: 176 | C82: The Cavern | D82: MAIKI SOUZA CHAVES | E82: 2969.58 | F82: 46087 | G82: 46087 | H82: 46087 | I82: 46081 | L82: Mão de Obra - Salários | M82: MDO CLT - Salário | O82: Documentação Aprovada | P82: Aprovado Diretoria | Q82: Aprovado Caixa | R82: Pago | S82: 226 | T82: The Cavern - Kamino
A83: 214646 | B83: 176 | C83: The Cavern | D83: SABRINA MOURA DE SOUSA | E83: 2842.01 | F83: 46087 | G83: 46087 | H83: 46087 | I83: 46081 | L83: Mão de Obra - Salários | M83: MDO CLT - Salário | O83: Documentação Aprovada | P83: Aprovado Diretoria | Q83: Aprovado Caixa | R83: Pago | S83: 226 | T83: The Cavern - Kamino
A84: 214647 | B84: 176 | C84: The Cavern | D84: NICOLE SOUZA VIEIRA | E84: 2725.23 | F84: 46087 | G84: 46087 | H84: 46087 | I84: 46081 | L84: Mão de Obra - Salários | M84: MDO CLT - Salário | O84: Documentação Aprovada | P84: Aprovado Diretoria | Q84: Aprovado Caixa | R84: Pago | S84: 226 | T84: The Cavern - Kamino
A85: 214648 | B85: 176 | C85: The Cavern | D85: WILKIAS HENRIQUE SANTOS DE SOUSA | E85: 2348.14 | F85: 46087 | G85: 46087 | H85: 46087 | I85: 46081 | L85: Mão de Obra - Salários | M85: MDO CLT - Salário | O85: Documentação Aprovada | P85: Aprovado Diretoria | Q85: Aprovado Caixa | R85: Pago | S85: 226 | T85: The Cavern - Kamino
A86: 214649 | B86: 176 | C86: The Cavern | D86: MARCO OCTAVIO BARBOSA DA SILVA | E86: 2366.72 | F86: 46087 | G86: 46087 | H86: 46087 | I86: 46081 | L86: Mão de Obra - Salários | M86: MDO CLT - Salário | O86: Documentação Aprovada | P86: Aprovado Diretoria | Q86: Aprovado Caixa | R86: Pago | S86: 226 | T86: The Cavern - Kamino
A87: 215860 | B87: 176 | C87: The Cavern | D87: WEW IMPORTACAO E EXPORTACAO LTDA | E87: 990 | F87: 46092 | G87: 46092 | H87: 46087 | I87: 46090 | J87: 46092 | K87: Transferência Bancária ou Pix | L87: Custo Mercadoria Vendida | M87: Insumos - Alimentos | N87: 498770 | O87: Análise Pendente | P87: Análise Pendente | Q87: Análise Pendente | R87: Pago | S87: 226 | T87: The Cavern - Kamino
A88: 206316 | B88: 176 | C88: The Cavern | D88: CECILIA TSUYACO ARAKI SILVA LTDA | E88: 461.35 | F88: 46087 | G88: 46087 | H88: 46087 | I88: 46059 | J88: 46064 | K88: Boleto Bancário | L88: Custo Mercadoria Vendida | M88: Insumos - Alimentos | N88: 386443 | O88: Documentação Aprovada | P88: Aprovado Diretoria | Q88: Aprovado Caixa | R88: Pago | S88: 226 | T88: The Cavern - Kamino
A89: 210740 | B89: 176 | C89: The Cavern | D89: SPAL INDUSTRIA BRASILEIRA DE BEBIDAS S A | E89: 584.82 | F89: 46087 | G89: 46087 | H89: 46087 | I89: 46076 | J89: 46077 | K89: Boleto Bancário | L89: Custo Mercadoria Vendida | M89: Insumos - Bebidas | N89: 16454441 | O89: Documentação Aprovada | P89: Aprovado Diretoria | Q89: Aprovado Caixa | R89: Pago | S89: 226 | T89: The Cavern - Kamino
A90: 211140 | B90: 176 | C90: The Cavern | D90: MARCO OCTAVIO BARBOSA DA SILVA | E90: 990.9 | F90: 46087 | G90: 46087 | H90: 46087 | I90: 46078 | J90: 46078 | K90: Transferência Bancária ou Pix | L90: Mão de Obra - Extra | M90: Mão de Obra Extra | N90: 572026 | O90: Documentação Aprovada | P90: Aprovado Diretoria | Q90: Aprovado Caixa | R90: Pago | S90: 226 | T90: The Cavern - Kamino
A91: 211143 | B91: 176 | C91: The Cavern | D91: NICOLE SOUZA VIEIRA | E91: 495.45 | F91: 46087 | G91: 46087 | H91: 46087 | I91: 46078 | J91: 46078 | K91: Transferência Bancária ou Pix | L91: Mão de Obra - Extra | M91: Mão de Obra Extra | N91: 582026 | O91: Documentação Aprovada | P91: Aprovado Diretoria | Q91: Aprovado Caixa | R91: Pago | S91: 226 | T91: The Cavern - Kamino
A92: 211130 | B92: 176 | C92: The Cavern | D92: MAIKI SOUZA CHAVES | E92: 198.18 | F92: 46087 | G92: 46087 | H92: 46087 | I92: 46078 | J92: 46078 | K92: Transferência Bancária ou Pix | L92: Mão de Obra - Extra | M92: Mão de Obra Extra | N92: 562026 | O92: Documentação Aprovada | P92: Aprovado Diretoria | Q92: Aprovado Caixa | R92: Pago | S92: 226 | T92: The Cavern - Kamino
A93: 211154 | B93: 176 | C93: The Cavern | D93: SABRINA MOURA DE SOUSA | E93: 198.18 | F93: 46087 | G93: 46087 | H93: 46087 | I93: 46078 | J93: 46078 | K93: Transferência Bancária ou Pix | L93: Mão de Obra - Extra | M93: Mão de Obra Extra | N93: 592026 | O93: Documentação Aprovada | P93: Aprovado Diretoria | Q93: Aprovado Caixa | R93: Pago | S93: 226 | T93: The Cavern - Kamino
A94: 211189 | B94: 176 | C94: The Cavern | D94: WILKIAS HENRIQUE SANTOS DE SOUSA | E94: 990.9 | F94: 46087 | G94: 46087 | H94: 46087 | I94: 46078 | J94: 46078 | K94: Transferência Bancária ou Pix | L94: Mão de Obra - Extra | M94: Mão de Obra Extra | N94: 602026 | O94: Documentação Aprovada | P94: Aprovado Diretoria | Q94: Aprovado Caixa | R94: Pago | S94: 226 | T94: The Cavern - Kamino
A95: 207805 | B95: 176 | C95: The Cavern | D95: EMPORIO M&L COMERCIO DE ALIM E BEBIDAS LTDA | E95: 599.39 | F95: 46087 | G95: 46087 | H95: 46087 | I95: 46058 | J95: 46066 | K95: Boleto Bancário | L95: Custo Mercadoria Vendida | M95: Insumos - Alimentos | N95: 495238 | O95: Documentação Aprovada | P95: Aprovado Diretoria | Q95: Aprovado Caixa | R95: Pago | S95: 226 | T95: The Cavern - Kamino
A96: 207995 | B96: 176 | C96: The Cavern | D96: FORTE ALIMENTOS COM. IMPORTAÇÃO LTDA | E96: 1036.89 | F96: 46086 | G96: 46086 | H96: 46086 | I96: 46057 | J96: 46069 | K96: Boleto Bancário | L96: Custo Mercadoria Vendida | M96: Insumos - Alimentos | N96: 356851 | O96: Documentação Aprovada | P96: Aprovado Diretoria | Q96: Aprovado Caixa | R96: Pago | S96: 226 | T96: The Cavern - Kamino
A97: 207794 | B97: 176 | C97: The Cavern | D97: MARIO PEDRO FELICIANO - HORTIFRUTI | E97: 178.06 | F97: 46086 | G97: 46086 | H97: 46086 | I97: 46058 | J97: 46066 | K97: Boleto Bancário | L97: Custo Mercadoria Vendida | M97: Insumos - Alimentos | N97: 466908 | O97: Documentação Aprovada | P97: Aprovado Diretoria | Q97: Aprovado Caixa | R97: Pago | S97: 226 | T97: The Cavern - Kamino
A98: 207999 | B98: 176 | C98: The Cavern | D98: AROUMAR DISTRIBUIDORA DE PRODUTOS ALIMENTICIOS LTDA | E98: 486.6 | F98: 46086 | G98: 46086 | H98: 46086 | I98: 46058 | J98: 46069 | K98: Boleto Bancário | L98: Custo Mercadoria Vendida | M98: Insumos - Alimentos | N98: 1039869 | O98: Documentação Aprovada | P98: Aprovado Diretoria | Q98: Aprovado Caixa | R98: Pago | S98: 226 | T98: The Cavern - Kamino
... A124: 195489 | B124: 176 | C124: The Cavern | D124: INSS | E124: 4326.44 | F124: 46073 | G124: 46084 | H124: 46084 | I124: 46023 | J124: 46044 | K124: Boleto Bancário | L124: Mão de Obra - Encargos e Provisões | M124: - INSS Segurados | N124: Jan2026 | O124: Documentação Aprovada | P124: Aprovado Diretoria | Q124: Aprovado Caixa | R124: Pago | S124: 226 | T124: The Cavern - Kamino
A125: 194131 | B125: 176 | C125: The Cavern | D125: ESTAFF SOLUCOES TECNOLOGICAS DE AGENCIAMENTO LTDA | E125: 15345 | F125: 46083 | G125: 46083 | H125: 46083 | I125: 46032 | J125: 46063 | K125: Boleto Bancário | L125: Mão de Obra - Extra | M125: Mão de Obra Extra | N125: 4619102032026 | O125: Documentação Aprovada | P125: Aprovado Diretoria | Q125: Aprovado Caixa | R125: Pago
A126: 203140 | B126: 176 | C126: The Cavern | D126: ESTAFF SOLUCOES TECNOLOGICAS DE AGENCIAMENTO LTDA | E126: 12341.1 | F126: 46083 | G126: 46083 | H126: 46083 | I126: 46055 | J126: 46055 | K126: Boleto Bancário | L126: Mão de Obra - Extra | M126: Mão de Obra Extra | N126: 4619102032026 | O126: Documentação Aprovada | P126: Aprovado Diretoria | Q126: Aprovado Caixa | R126: Pago | S126: 226 | T126: The Cavern - Kamino
A127: 203625 | B127: 176 | C127: The Cavern | D127: HORTIFRUTI DO CHEF LTDA | E127: 263.8 | F127: 46083 | G127: 46083 | H127: 46083 | I127: 46055 | J127: 46057 | K127: Boleto Bancário | L127: Custo Mercadoria Vendida | M127: Insumos - Alimentos | N127: 28855 | O127: Documentação Aprovada | P127: Aprovado Diretoria | Q127: Aprovado Caixa | R127: Pago | S127: 226 | T127: The Cavern - Kamino
A128: 203357 | B128: 176 | C128: The Cavern | D128: MARIO PEDRO FELICIANO - HORTIFRUTI | E128: 283.42 | F128: 46083 | G128: 46083 | H128: 46083 | I128: 46055 | J128: 46056 | K128: Boleto Bancário | L128: Custo Mercadoria Vendida | M128: Insumos - Alimentos | N128: 466553 | O128: Documentação Aprovada | P128: Aprovado Diretoria | Q128: Aprovado Caixa | R128: Pago | S128: 226 | T128: The Cavern - Kamino
A129: 203124 | B129: 176 | C129: The Cavern | D129: FABRICA DE BARES PARTICIPACOES LTDA | E129: 10218.61 | F129: 46063 | G129: 46083 | H129: 46083 | I129: 45993 | J129: 46055 | K129: Transferência Bancária ou Pix | L129: Mão de Obra - Extra | M129: Mão de Obra Extra | N129: 072026 | O129: Documentação Aprovada | P129: Aprovado Diretoria | Q129: Aprovado Caixa | R129: Pago | S129: 226 | T129: The Cavern - Kamino
A130: 203341 | B130: 176 | C130: The Cavern | D130: CECILIA TSUYACO ARAKI SILVA LTDA | E130: 859.35 | F130: 46083 | G130: 46083 | H130: 46083 | I130: 46055 | J130: 46056 | K130: Boleto Bancário | L130: Custo Mercadoria Vendida | M130: Insumos - Alimentos | N130: 386157 | O130: Documentação Aprovada | P130: Aprovado Diretoria | Q130: Aprovado Caixa | R130: Pago | S130: 226 | T130: The Cavern - Kamino
A131: 205946 | B131: 176 | C131: The Cavern | D131: NOVA COMERCIAL PESCADOS LTDA | E131: 1783.08 | F131: 46083 | G131: 46083 | H131: 46083 | I131: 46055 | J131: 46062 | K131: Boleto Bancário | L131: Custo Mercadoria Vendida | M131: Insumos - Alimentos | N131: 31046 | O131: Documentação Aprovada | P131: Aprovado Diretoria | Q131: Aprovado Caixa | R131: Pago | S131: 226 | T131: The Cavern - Kamino
A132: 205878 | B132: 176 | C132: The Cavern | D132: MARCOS SILVA DO NASCIMENTO | E132: 1412.35 | F132: 46081 | G132: 46083 | H132: 46083 | I132: 46056 | J132: 46062 | K132: Boleto Bancário | L132: Custo Mercadoria Vendida | M132: Insumos - Alimentos | N132: 765 | O132: Documentação Aprovada | P132: Aprovado Diretoria | Q132: Aprovado Caixa | R132: Pago | S132: 226 | T132: The Cavern - Kamino
A133: 202106 | B133: 176 | C133: The Cavern | D133: ANDREIA SANTOS FREITAS DUARTE | E133: 236.88 | F133: 46083 | G133: 46083 | H133: 46083 | I133: 46049 | J133: 46051 | K133: Boleto Bancário | L133: Custo Mercadoria Vendida | M133: Insumos - Alimentos | N133: 2532 | O133: Documentação Aprovada | P133: Aprovado Diretoria | Q133: Aprovado Caixa | R133: Pago | S133: 226 | T133: The Cavern - Kamino
A134: 210315 | B134: 176 | C134: The Cavern | D134: KAMINO INSTITUICAO DE PAGAMENTO LTDA | E134: 400 | F134: 46082 | G134: 46083 | H134: 46083 | I134: 46072 | J134: 46076 | K134: Boleto Bancário | L134: Despesas Financeiras | M134: Tarifas Bancárias | N134: 3019001032026 | O134: Documentação Aprovada | P134: Aprovado Diretoria | Q134: Aprovado Caixa | R134: Pago | S134: 226 | T134: The Cavern - Kamino
A135: 210298 | B135: 176 | C135: The Cavern | D135: LALAMOVE TECNOLOGIA (BRASIL) LTDA | E135: 255.09 | F135: 46083 | G135: 46083 | H135: 46083 | I135: 46052 | J135: 46052 | K135: Boleto Bancário | L135: Despesas com Transporte / Hospedagem | M135: Fretes e Carretos | N135: 532026 | O135: Documentação Aprovada | P135: Aprovado Diretoria | Q135: Aprovado Caixa | R135: Pago | S135: 226 | T135: The Cavern - Kamino
A136: 208946 | B136: 176 | C136: The Cavern | D136: ESTAFF SOLUCOES TECNOLOGICAS DE AGENCIAMENTO LTDA | E136: 6809 | F136: 46078 | G136: 46083 | H136: 46083 | I136: 46068 | J136: 46072 | K136: Boleto Bancário | L136: Mão de Obra - Extra | M136: Mão de Obra Extra | N136: 4619125022026 | O136: Documentação Aprovada | P136: Aprovado Diretoria | Q136: Aprovado Caixa | R136: Pago | S136: 226 | T136: The Cavern - Kamino
A137: 206435 | B137: 176 | C137: The Cavern | D137: ANALUISA SCALON DE OLIVEIRA GONCALVES | E137: 386.73 | F137: 46078 | G137: 46083 | H137: 46083 | I137: 46063 | J137: 46064 | K137: Transferência Bancária ou Pix | L137: Mão de Obra - Benefícios | M137: - Vale-transporte | N137: 046-2026 | O137: Documentação Aprovada | P137: Aprovado Diretoria | Q137: Aprovado Caixa | R137: Pago | S137: 226 | T137: The Cavern - Kamino
A138: 215754 | B138: 176 | C138: The Cavern | D138: ZIGPAY LTDAS -ME | E138: 2234.72 | F138: 46081 | H138: 46081 | I138: 46081 | K138: Debito Automático | L138: Deduções sobre Venda | M138: Meios de pagamento | O138: Documentação Aprovada | P138: Aprovado Diretoria | Q138: Aprovado Caixa | R138: Pago | S138: 220 | T138: The Cavern - Zigpay
A139: 213377 | B139: 176 | C139: The Cavern | D139: KAMINO INSTITUICAO DE PAGAMENTO LTDA | E139: 1 | F139: 46080 | H139: 46080 | I139: 46080 | K139: Debito Automático | L139: Despesas Financeiras | M139: Tarifas Bancárias | O139: Documentação Aprovada | P139: Aprovado Diretoria | Q139: Aprovado Caixa | R139: Pago | S139: 226 | T139: The Cavern - Kamino
A140: 208077 | B140: 176 | C140: The Cavern | D140: MS FRANGOS LTDA | E140: 337.23 | F140: 46080 | G140: 46080 | H140: 46080 | I140: 46065 | J140: 46069 | K140: Boleto Bancário | L140: Custo Mercadoria Vendida | M140: Insumos - Alimentos | N140: 45497 | O140: Documentação Aprovada | P140: Aprovado Diretoria | Q140: Aprovado Caixa | R140: Pago | S140: 226 | T140: The Cavern - Kamino
A141: 208148 | B141: 176 | C141: The Cavern | D141: PAULO SERGIO LOPES MARTINS DE FREITAS | E141: 7415.6 | F141: 46076 | G141: 46080 | H141: 46080 | I141: 46069 | J141: 46069 | K141: Transferência Bancária ou Pix | L141: Gorjeta | M141: - Comissões e Gorjeta | N141: 0472026 | O141: Documentação Aprovada | P141: Aprovado Diretoria | Q141: Aprovado Caixa | R141: Pago | S141: 226 | T141: The Cavern - Kamino
A142: 209752 | B142: 176 | C142: The Cavern | D142: ANALUISA SCALON DE OLIVEIRA GONCALVES | E142: 688.75 | F142: 46076 | G142: 46080 | H142: 46080 | I142: 46073 | J142: 46073 | K142: Transferência Bancária ou Pix | L142: Utilidades | M142: Material de Escritorio | N142: 512026 | O142: Documentação Aprovada | P142: Aprovado Diretoria | Q142: Aprovado Caixa | R142: Pago | S142: 226 | T142: The Cavern - Kamino
A143: 209756 | B143: 176 | C143: The Cavern | D143: MAR DIRETO POC COMERCIO DE PEIXES LTDA | E143: 1309.75 | F143: 46080 | G143: 46080 | H143: 46080 | I143: 46073 | J143: 46073 | K143: Boleto Bancário | L143: Custo Mercadoria Vendida | M143: Insumos - Alimentos | N143: 117471 | O143: Documentação Aprovada | P143: Aprovado Diretoria | Q143: Aprovado Caixa | R143: Pago | S143: 226 | T143: The Cavern - Kamino
A144: 208578 | B144: 176 | C144: The Cavern | D144: PSSS LTDA | E144: 723.2 | F144: 46080 | G144: 46080 | H144: 46080 | I144: 46063 | J144: 46071 | K144: Boleto Bancário | L144: Utilidades | M144: Higiene e Limpeza | N144: 3120 | O144: Documentação Aprovada | P144: Aprovado Diretoria | Q144: Aprovado Caixa | R144: Pago | S144: 226 | T144: The Cavern - Kamino
A145: 208594 | B145: 176 | C145: The Cavern | D145: PSSS LTDA | E145: 59 | F145: 46080 | G145: 46080 | H145: 46080 | I145: 46063 | J145: 46071 | K145: Boleto Bancário | L145: Utilidades | M145: Higiene e Limpeza | N145: 3128 | O145: Documentação Aprovada | P145: Aprovado Diretoria | Q145: Aprovado Caixa | R145: Pago | S145: 226 | T145: The Cavern - Kamino
A146: 203697 | B146: 176 | C146: The Cavern | D146: HORTIFRUTI DO CHEF LTDA | E146: 536.7 | F146: 46080 | G146: 46080 | H146: 46080 | I146: 46052 | J146: 46057 | K146: Boleto Bancário | L146: Custo Mercadoria Vendida | M146: Insumos - Alimentos | N146: 28802 | O146: Documentação Aprovada | P146: Aprovado Diretoria | Q146: Aprovado Caixa | R146: Pago | S146: 226 | T146: The Cavern - Kamino
A147: 203649 | B147: 176 | C147: The Cavern | D147: CECILIA TSUYACO ARAKI SILVA LTDA | E147: 1292.5 | F147: 46080 | G147: 46080 | H147: 46080 | I147: 46052 | J147: 46057 | K147: Boleto Bancário | L147: Custo Mercadoria Vendida | M147: Insumos - Alimentos | N147: 386005 | O147: Documentação Aprovada | P147: Aprovado Diretoria | Q147: Aprovado Caixa | R147: Pago | S147: 226 | T147: The Cavern - Kamino
A148: 203669 | B148: 176 | C148: The Cavern | D148: MARIO PEDRO FELICIANO - HORTIFRUTI | E148: 422.83 | F148: 46080 | G148: 46080 | H148: 46080 | I148: 46052 | J148: 46057 | K148: Boleto Bancário | L148: Custo Mercadoria Vendida | M148: Insumos - Alimentos | N148: 466325 | O148: Documentação Aprovada | P148: Aprovado Diretoria | Q148: Aprovado Caixa | R148: Pago | S148: 226 | T148: The Cavern - Kamino
A149: 205696 | B149: 176 | C149: The Cavern | D149: VALE TRANSPORTE | E149: 3151.14 | F149: 46080 | G149: 46083 | H149: 46080 | I149: 46082 | J149: 46082 | K149: Boleto Bancário | L149: Mão de Obra - Benefícios | M149: - Vale-transporte | N149: 315114 032026 | O149: Documentação Aprovada | P149: Aprovado Diretoria | Q149: Aprovado Caixa | R149: Pago | S149: 226 | T149: The Cavern - Kamino
A150: 205862 | B150: 176 | C150: The Cavern | D150: CG FOOD´S DISTRIBUIDORA DE ALIMENTOS LTDA | E150: 414.7 | F150: 46080 | G150: 46080 | H150: 46080 | I150: 46059 | J150: 46062 | K150: Boleto Bancário | L150: Custo Mercadoria Vendida | M150: Insumos - Bebidas | N150: 178798 | O150: Documentação Aprovada | P150: Aprovado Diretoria | Q150: Aprovado Caixa | R150: Pago | S150: 226 | T150: The Cavern - Kamino
A151: 203034 | B151: 176 | C151: The Cavern | D151: DTK COMERCIO DE ALIMENTOS LTDA | E151: 372.09 | F151: 46080 | G151: 46080 | H151: 46080 | I151: 46052 | J151: 46055 | K151: Boleto Bancário | L151: Custo Mercadoria Vendida | M151: Insumos - Alimentos | N151: 63148 | O151: Documentação Aprovada | P151: Aprovado Diretoria | Q151: Aprovado Caixa | R151: Pago | S151: 226 | T151: The Cavern - Kamino
... A162: 209502 | B162: 176 | C162: The Cavern | D162: VALE TRANSPORTE | E162: 326.36 | F162: 46078 | G162: 46078 | H162: 46078 | I162: 46072 | J162: 46072 | K162: Boleto Bancário | L162: Mão de Obra - Benefícios | M162: - Vale-transporte | N162: 232872874 | O162: Documentação Aprovada | P162: Aprovado Diretoria | Q162: Aprovado Caixa | R162: Pago | S162: 226 | T162: The Cavern - Kamino
A163: 211832 | B163: 176 | C163: The Cavern | D163: KAMINO INSTITUICAO DE PAGAMENTO LTDA | E163: 2 | F163: 46078 | H163: 46078 | I163: 46078 | K163: Debito Automático | L163: Despesas Financeiras | M163: Tarifas Bancárias | O163: Documentação Aprovada | P163: Aprovado Diretoria | Q163: Aprovado Caixa | R163: Pago | S163: 226 | T163: The Cavern - Kamino
A164: 202069 | B164: 176 | C164: The Cavern | D164: B.B DISTRIBUIDORA DE CARNES LTDA | E164: 1500.04 | F164: 46078 | G164: 46078 | H164: 46078 | I164: 46050 | J164: 46051 | K164: Boleto Bancário | L164: Custo Mercadoria Vendida | M164: Insumos - Alimentos | N164: 413088 | O164: Documentação Aprovada | P164: Aprovado Diretoria | Q164: Aprovado Caixa | R164: Pago | S164: 226 | T164: The Cavern - Kamino
A165: 201841 | B165: 176 | C165: The Cavern | D165: FRONT BEBIDAS LTDA | E165: 1065.3 | F165: 46078 | G165: 46078 | H165: 46078 | I165: 46050 | J165: 46051 | K165: Boleto Bancário | L165: Custo Mercadoria Vendida | M165: Insumos - Bebidas | N165: 789487 | O165: Documentação Aprovada | P165: Aprovado Diretoria | Q165: Aprovado Caixa | R165: Pago | S165: 226 | T165: The Cavern - Kamino
A166: 201750 | B166: 176 | C166: The Cavern | D166: MARCOS SILVA DO NASCIMENTO | E166: 731.71 | F166: 46078 | G166: 46078 | H166: 46078 | I166: 46050 | J166: 46051 | K166: Boleto Bancário | L166: Custo Mercadoria Vendida | M166: Insumos - Alimentos | N166: 754 | O166: Documentação Aprovada | P166: Aprovado Diretoria | Q166: Aprovado Caixa | R166: Pago | S166: 226 | T166: The Cavern - Kamino
A167: 196817 | B167: 176 | C167: The Cavern | D167: EAU - DISTRIBUIDORA DE AGUA MINERAL LTDA | E167: 257.5 | F167: 46078 | G167: 46078 | H167: 46078 | I167: 46043 | J167: 46045 | K167: Boleto Bancário | L167: Custo Mercadoria Vendida | M167: Insumos - Bebidas | N167: 287870 | O167: Documentação Aprovada | P167: Aprovado Diretoria | Q167: Aprovado Caixa | R167: Pago | S167: 226 | T167: The Cavern - Kamino
A168: 199052 | B168: 176 | C168: The Cavern | D168: WPP COMERCIO DE CARNES LTDA | E168: 209.5 | F168: 46078 | G168: 46078 | H168: 46078 | I168: 46050 | J168: 46050 | K168: Boleto Bancário | L168: Custo Mercadoria Vendida | M168: Insumos - Alimentos | N168: 77000 | O168: Documentação Aprovada | P168: Aprovado Diretoria | Q168: Aprovado Caixa | R168: Pago | S168: 226 | T168: The Cavern - Kamino
A169: 199045 | B169: 176 | C169: The Cavern | D169: EMPORIO M&L COMERCIO DE ALIM E BEBIDAS LTDA | E169: 419.3 | F169: 46077 | G169: 46077 | H169: 46077 | I169: 46049 | J169: 46050 | K169: Boleto Bancário | L169: Custo Mercadoria Vendida | M169: Insumos - Alimentos | N169: 493704 | O169: Documentação Aprovada | P169: Aprovado Diretoria | Q169: Aprovado Caixa | R169: Pago | S169: 226 | T169: The Cavern - Kamino
A170: 199049 | B170: 176 | C170: The Cavern | D170: WPP COMERCIO DE CARNES LTDA | E170: 2558.56 | F170: 46077 | G170: 46077 | H170: 46077 | I170: 46049 | J170: 46050 | K170: Boleto Bancário | L170: Custo Mercadoria Vendida | M170: Insumos - Alimentos | N170: 76968 | O170: Documentação Aprovada | P170: Aprovado Diretoria | Q170: Aprovado Caixa | R170: Pago | S170: 226 | T170: The Cavern - Kamino
A171: 195451 | B171: 176 | C171: The Cavern | D171: ANDREIA SANTOS FREITAS DUARTE | E171: 201.89 | F171: 46077 | G171: 46077 | H171: 46077 | I171: 46042 | J171: 46044 | K171: Boleto Bancário | L171: Custo Mercadoria Vendida | M171: Insumos - Alimentos | N171: 2487 | O171: Documentação Aprovada | P171: Aprovado Diretoria | Q171: Aprovado Caixa | R171: Pago | S171: 226 | T171: The Cavern - Kamino
A172: 198376 | B172: 176 | C172: The Cavern | D172: FORTE ALIMENTOS COM. IMPORTAÇÃO LTDA | E172: 119.5 | F172: 46077 | G172: 46077 | H172: 46077 | I172: 46048 | J172: 46049 | K172: Boleto Bancário | L172: Custo Mercadoria Vendida | M172: Insumos - Alimentos | N172: 355104 | O172: Documentação Aprovada | P172: Aprovado Diretoria | Q172: Aprovado Caixa | R172: Pago | S172: 226 | T172: The Cavern - Kamino
A173: 202914 | B173: 176 | C173: The Cavern | D173: FORTE ALIMENTOS COM. IMPORTAÇÃO LTDA | E173: 525 | F173: 46077 | G173: 46077 | H173: 46077 | I173: 46048 | J173: 46053 | K173: Boleto Bancário | L173: Custo Mercadoria Vendida | M173: Insumos - Alimentos | N173: 355043 | O173: Documentação Aprovada | P173: Aprovado Diretoria | Q173: Aprovado Caixa | R173: Pago | S173: 226 | T173: The Cavern - Kamino
A174: 203638 | B174: 176 | C174: The Cavern | D174: ALLIMENTARI COMERCIO DE PRODUTOS ALIMENTICIOS E SERVICOS LTDA | E174: 635.34 | F174: 46077 | G174: 46077 | H174: 46077 | I174: 46049 | J174: 46057 | K174: Boleto Bancário | L174: Custo Mercadoria Vendida | M174: Insumos - Alimentos | N174: 35425 | O174: Documentação Aprovada | P174: Aprovado Diretoria | Q174: Aprovado Caixa | R174: Pago | S174: 226 | T174: The Cavern - Kamino
A175: 205884 | B175: 176 | C175: The Cavern | D175: PROAUTO INDUSTRIA QUIMICA EIRELI | E175: 1185.71 | F175: 46077 | G175: 46077 | H175: 46077 | I175: 46056 | J175: 46062 | K175: Boleto Bancário | L175: Utilidades | M175: Higiene e Limpeza | N175: 151225 | O175: Documentação Aprovada | P175: Aprovado Diretoria | Q175: Aprovado Caixa | R175: Pago | S175: 226 | T175: The Cavern - Kamino
... A178: 207980 | B178: 176 | C178: The Cavern | D178: LPQBR RESTAURANTES E PADARIAS LTDA | E178: 273.6 | F178: 46077 | G178: 46077 | H178: 46077 | I178: 46049 | J178: 46069 | K178: Transferência Bancária ou Pix | L178: Custo Mercadoria Vendida | M178: Insumos - Alimentos | N178: 87891 | O178: Documentação Aprovada | P178: Aprovado Diretoria | Q178: Aprovado Caixa | R178: Pago | S178: 226 | T178: The Cavern - Kamino
A179: 211632 | B179: 176 | C179: The Cavern | D179: KAMINO INSTITUICAO DE PAGAMENTO LTDA | E179: 0.5 | F179: 46077 | H179: 46077 | I179: 46077 | K179: Debito Automático | L179: Despesas Financeiras | M179: Tarifas Bancárias | O179: Documentação Aprovada | P179: Aprovado Diretoria | Q179: Aprovado Caixa | R179: Pago | S179: 226 | T179: The Cavern - Kamino
A180: 208810 | B180: 176 | C180: The Cavern | D180: 28.811.338 GABRIELLA ABBUD PASSARO - ME | E180: 2536.08 | F180: 46076 | G180: 46076 | H180: 46076 | I180: 46057 | J180: 46071 | K180: Transferência Bancária ou Pix | L180: Custo Mercadoria Vendida | M180: Insumos - Bebidas | N180: 15 | O180: Documentação Aprovada | P180: Aprovado Diretoria | Q180: Aprovado Caixa | R180: Pago | S180: 226 | T180: The Cavern - Kamino
A181: 208573 | B181: 176 | C181: The Cavern | D181: SPAL INDUSTRIA BRASILEIRA DE BEBIDAS S A | E181: 464.95 | F181: 46076 | G181: 46076 | H181: 46076 | I181: 46064 | J181: 46071 | K181: Boleto Bancário | L181: Custo Mercadoria Vendida | M181: Insumos - Bebidas | N181: 16431502 | O181: Documentação Aprovada | P181: Aprovado Diretoria | Q181: Aprovado Caixa | R181: Pago | S181: 226 | T181: The Cavern - Kamino
A182: 210781 | B182: 176 | C182: The Cavern | D182: KAMINO INSTITUICAO DE PAGAMENTO LTDA | E182: 1 | F182: 46076 | H182: 46076 | I182: 46076 | K182: Debito Automático | L182: Despesas Financeiras | M182: Tarifas Bancárias | O182: Documentação Aprovada | P182: Aprovado Diretoria | Q182: Aprovado Caixa | R182: Pago | S182: 226 | T182: The Cavern - Kamino
A183: 206264 | B183: 176 | C183: The Cavern | D183: DISTRIBUIDORA DE CARNES CANTAREIRA | E183: 130.9 | F183: 46076 | G183: 46076 | H183: 46076 | I183: 46062 | J183: 46063 | K183: Boleto Bancário | L183: Custo Mercadoria Vendida | M183: Insumos - Alimentos | N183: 49904 | O183: Documentação Aprovada | P183: Aprovado Diretoria | Q183: Aprovado Caixa | R183: Pago | S183: 226 | T183: The Cavern - Kamino
A184: 209357 | B184: 176 | C184: The Cavern | D184: F & C ASSESSORIA CONTABIL LTDA | E184: 2000 | F184: 46076 | G184: 46076 | H184: 46076 | I184: 46053 | J184: 46072 | K184: Transferência Bancária ou Pix | L184: Serviços de Terceiros | M184: Assessoria Contabil | N184: 492026 | O184: Documentação Aprovada | P184: Aprovado Diretoria | Q184: Aprovado Caixa | R184: Pago | S184: 226 | T184: The Cavern - Kamino
A185: 203280 | B185: 176 | C185: The Cavern | D185: HORTIFRUTI DO CHEF LTDA | E185: 927.9 | F185: 46076 | G185: 46076 | H185: 46076 | I185: 46048 | J185: 46056 | K185: Boleto Bancário | L185: Custo Mercadoria Vendida | M185: Insumos - Alimentos | N185: 28680 | O185: Documentação Aprovada | P185: Aprovado Diretoria | Q185: Aprovado Caixa | R185: Pago | S185: 226 | T185: The Cavern - Kamino
A186: 198279 | B186: 176 | C186: The Cavern | D186: CECILIA TSUYACO ARAKI SILVA LTDA | E186: 1331.8 | F186: 46076 | G186: 46076 | H186: 46076 | I186: 46048 | J186: 46049 | K186: Boleto Bancário | L186: Custo Mercadoria Vendida | M186: Insumos - Alimentos | N186: 385725 | O186: Documentação Aprovada | P186: Aprovado Diretoria | Q186: Aprovado Caixa | R186: Pago | S186: 226 | T186: The Cavern - Kamino
A187: 198757 | B187: 176 | C187: The Cavern | D187: ARENA VIP DISTRIBUIDORA DE BEBIDAS LTDA | E187: 810.5 | F187: 46076 | G187: 46076 | H187: 46076 | I187: 46048 | J187: 46050 | K187: Boleto Bancário | L187: Custo Mercadoria Vendida | M187: Insumos - Bebidas | N187: 26467 | O187: Documentação Aprovada | P187: Aprovado Diretoria | Q187: Aprovado Caixa | R187: Pago | S187: 226 | T187: The Cavern - Kamino
A188: 198760 | B188: 176 | C188: The Cavern | D188: DTK COMERCIO DE ALIMENTOS LTDA | E188: 1717.47 | F188: 46076 | G188: 46076 | H188: 46076 | I188: 46048 | J188: 46050 | K188: Boleto Bancário | L188: Custo Mercadoria Vendida | M188: Insumos - Alimentos | N188: 62280 | O188: Documentação Aprovada | P188: Aprovado Diretoria | Q188: Aprovado Caixa | R188: Pago | S188: 226 | T188: The Cavern - Kamino
A189: 195463 | B189: 176 | C189: The Cavern | D189: ANDREIA SANTOS FREITAS DUARTE | E189: 417.3 | F189: 46076 | G189: 46076 | H189: 46076 | I189: 46041 | J189: 46044 | K189: Boleto Bancário | L189: Custo Mercadoria Vendida | M189: Insumos - Alimentos | N189: 2477 | O189: Documentação Aprovada | P189: Aprovado Diretoria | Q189: Aprovado Caixa | R189: Pago | S189: 226 | T189: The Cavern - Kamino
A190: 195503 | B190: 176 | C190: The Cavern | D190: FGTS | E190: 673.07 | F190: 46073 | G190: 46073 | H190: 46073 | I190: 46023 | J190: 46044 | K190: Transferência Bancária ou Pix | L190: Mão de Obra - Encargos e Provisões | M190: - FGTS | N190: JAN2026 | O190: Documentação Aprovada | P190: Aprovado Diretoria | Q190: Aprovado Caixa | R190: Pago | S190: 226 | T190: The Cavern - Kamino
A191: 196995 | B191: 176 | C191: The Cavern | D191: WPP COMERCIO DE CARNES LTDA | E191: 1209.52 | F191: 46073 | G191: 46073 | H191: 46073 | I191: 46045 | J191: 46045 | K191: Boleto Bancário | L191: Custo Mercadoria Vendida | M191: Insumos - Alimentos | N191: 76908 | O191: Documentação Aprovada | P191: Aprovado Diretoria | Q191: Aprovado Caixa | R191: Pago | S191: 226 | T191: The Cavern - Kamino
A192: 197709 | B192: 176 | C192: The Cavern | D192: NOVA COMERCIAL PESCADOS LTDA | E192: 1120 | F192: 46073 | G192: 46073 | H192: 46073 | I192: 46045 | J192: 46048 | K192: Boleto Bancário | L192: Custo Mercadoria Vendida | M192: Insumos - Alimentos | N192: 30815 | O192: Documentação Aprovada | P192: Aprovado Diretoria | Q192: Aprovado Caixa | R192: Pago | S192: 226 | T192: The Cavern - Kamino
A193: 197710 | B193: 176 | C193: The Cavern | D193: DTK COMERCIO DE ALIMENTOS LTDA | E193: 591.75 | F193: 46073 | G193: 46073 | H193: 46073 | I193: 46045 | J193: 46048 | K193: Boleto Bancário | L193: Custo Mercadoria Vendida | M193: Insumos - Alimentos | N193: 62151 | O193: Documentação Aprovada | P193: Aprovado Diretoria | Q193: Aprovado Caixa | R193: Pago | S193: 226 | T193: The Cavern - Kamino
A194: 203661 | B194: 176 | C194: The Cavern | D194: DTK COMERCIO DE ALIMENTOS LTDA | E194: 115.15 | F194: 46073 | G194: 46073 | H194: 46073 | I194: 46052 | J194: 46057 | K194: Boleto Bancário | L194: Custo Mercadoria Vendida | M194: Insumos - Alimentos | N194: 63188 | O194: Documentação Aprovada | P194: Aprovado Diretoria | Q194: Aprovado Caixa | R194: Pago | S194: 226 | T194: The Cavern - Kamino
A195: 209456 | B195: 176 | C195: The Cavern | D195: FUNCIONARIO EXTRA | E195: 3946.43 | F195: 46073 | G195: 46073 | H195: 46073 | I195: 46072 | J195: 46072 | K195: Transferência Bancária ou Pix | L195: Mão de Obra - Extra | M195: Mão de Obra Extra | N195: 502026 | O195: Documentação Aprovada | P195: Aprovado Diretoria | Q195: Aprovado Caixa | R195: Pago | S195: 226 | T195: The Cavern - Kamino
A196: 209491 | B196: 176 | C196: The Cavern | D196: VAGNER BRANDAO | E196: 944.02 | F196: 46073 | G196: 46073 | H196: 46073 | I196: 46068 | L196: Mão de Obra - Salários | M196: MDO CLT - Salário | O196: Documentação Aprovada | P196: Aprovado Diretoria | Q196: Aprovado Caixa | R196: Pago | S196: 226 | T196: The Cavern - Kamino
A197: 209490 | B197: 176 | C197: The Cavern | D197: ISMAEL SANTOS SILVA | E197: 1027.6 | F197: 46073 | G197: 46073 | H197: 46073 | I197: 46068 | L197: Mão de Obra - Salários | M197: MDO CLT - Salário | O197: Documentação Aprovada | P197: Aprovado Diretoria | Q197: Aprovado Caixa | R197: Pago | S197: 226 | T197: The Cavern - Kamino
A198: 209489 | B198: 176 | C198: The Cavern | D198: EMILY RENATA MENDONCA VIEIRA | E198: 1000 | F198: 46073 | G198: 46073 | H198: 46073 | I198: 46068 | L198: Mão de Obra - Salários | M198: MDO CLT - Salário | O198: Documentação Aprovada | P198: Aprovado Diretoria | Q198: Aprovado Caixa | R198: Pago | S198: 226 | T198: The Cavern - Kamino
A199: 209488 | B199: 176 | C199: The Cavern | D199: CARLOS ALBERTO FERREIRA PIMENTEL | E199: 1309.9 | F199: 46073 | G199: 46073 | H199: 46073 | I199: 46068 | L199: Mão de Obra - Salários | M199: MDO CLT - Salário | O199: Documentação Aprovada | P199: Aprovado Diretoria | Q199: Aprovado Caixa | R199: Pago | S199: 226 | T199: The Cavern - Kamino
...

Sheet df_blueme_com_parcelamento
A1: ID_Parcela | B1: ID_Despesa | C1: ID_Casa | D1: Casa | E1: CNPJ_Loja | F1: Fornecedor | G1: Parcelamento | H1: Qtd_Parcelas | I1: Num_Parcela | J1: Valor_Parcela | K1: Vencimento_Parcela | L1: Previsao_Parcela | M1: Realiz_Parcela | N1: Valor_Original | O1: Valor_Liquido | P1: Data_Lancamento | Q1: Forma_Pagamento | R1: Doc_NF | S1: Class_Cont_1 | T1: Class_Cont_2 | U1: Status_Conf_Document | V1: Status_Aprov_Diret | W1: Status_Aprov_Caixa | X1: Status_Pgto | Y1: ID_Conta_Bancaria | Z1: Conta_Bancaria
A2: 12903 | B2: 193694 | C2: 176 | D2: The Cavern | F2: ZAHIL IMPORTADORA LTDA | G2: True | H2: 5 | I2: 5 | J2: 10970.69 | K2: 46098 | L2: 46099 | M2: 46098 | N2: 54853.37 | O2: 54853.37 | P2: 46038 | Q2: Boleto Bancário | R2: 260242 | S2: Custo Mercadoria Vendida | T2: Insumos - Bebidas | U2: Documentação Aprovada | V2: Aprovado Diretoria | W2: Aprovado Caixa | X2: Parcela_Paga | Y2: 226 | Z2: The Cavern - Kamino
A3: 12943 | B3: 195592 | C3: 176 | D3: The Cavern | F3: CALEBE EQUIPAMENTOS INDUSTRIAIS EIRELI | G3: True | H3: 6 | I3: 2 | J3: 4000 | K3: 46097 | L3: 46098 | M3: 46097 | N3: 24000 | O3: 24000 | P3: 46044 | Q3: Boleto Bancário | R3: 12472 | S3: Utilidades | T3: Utensilios | U3: Documentação Aprovada | V3: Aprovado Diretoria | W3: Aprovado Caixa | X3: Parcela_Paga | Y3: 226 | Z3: The Cavern - Kamino
A4: 12965 | B4: 196844 | C4: 176 | D4: The Cavern | F4: REBAL COMERCIAL LTDA | G4: True | H4: 3 | I4: 2 | J4: 1782.27 | K4: 46096 | L4: 46098 | M4: 46097 | N4: 5346.8 | O4: 5346.8 | P4: 46045 | Q4: Boleto Bancário | R4: 292320 | S4: Utilidades | T4: Utensilios | U4: Documentação Aprovada | V4: Aprovado Diretoria | W4: Aprovado Caixa | X4: Parcela_Paga | Y4: 226 | Z4: The Cavern - Kamino
A5: 13237 | B5: 208948 | C5: 176 | D5: The Cavern | F5: ZAHIL IMPORTADORA LTDA | G5: True | H5: 3 | I5: 2 | J5: 1705.17 | K5: 46097 | L5: 46098 | M5: 46097 | N5: 4794.4 | O5: 5115.51 | P5: 46072 | Q5: Boleto Bancário | R5: 264084 | S5: Custo Mercadoria Vendida | T5: Insumos - Bebidas | U5: Documentação Aprovada | V5: Aprovado Diretoria | W5: Aprovado Caixa | X5: Parcela_Paga | Y5: 226 | Z5: The Cavern - Kamino
A6: 13248 | B6: 209321 | C6: 176 | D6: The Cavern | F6: ZAHIL IMPORTADORA LTDA | G6: True | H6: 2 | I6: 2 | J6: 722.71 | K6: 46086 | L6: 46087 | M6: 46086 | N6: 1357.2 | O6: 1445.42 | P6: 46072 | Q6: Boleto Bancário | R6: 263527 | S6: Custo Mercadoria Vendida | T6: Insumos - Bebidas | U6: Documentação Aprovada | V6: Aprovado Diretoria | W6: Aprovado Caixa | X6: Parcela_Paga | Y6: 226 | Z6: The Cavern - Kamino
A7: 13223 | B7: 208864 | C7: 176 | D7: The Cavern | F7: ZAHIL IMPORTADORA LTDA | G7: True | H7: 5 | I7: 1 | J7: 1895.66 | K7: 46086 | L7: 46087 | M7: 46086 | N7: 8899.8 | O7: 9478.29 | P7: 46071 | Q7: Boleto Bancário | R7: 264335 | S7: Custo Mercadoria Vendida | T7: Insumos - Bebidas | U7: Documentação Aprovada | V7: Aprovado Diretoria | W7: Aprovado Caixa | X7: Parcela_Paga | Y7: 226 | Z7: The Cavern - Kamino
A8: 12902 | B8: 193694 | C8: 176 | D8: The Cavern | F8: ZAHIL IMPORTADORA LTDA | G8: True | H8: 5 | I8: 4 | J8: 10970.67 | K8: 46084 | L8: 46085 | M8: 46084 | N8: 54853.37 | O8: 54853.37 | P8: 46038 | Q8: Boleto Bancário | R8: 260242 | S8: Custo Mercadoria Vendida | T8: Insumos - Bebidas | U8: Documentação Aprovada | V8: Aprovado Diretoria | W8: Aprovado Caixa | X8: Parcela_Paga | Y8: 226 | Z8: The Cavern - Kamino
A9: 12901 | B9: 193694 | C9: 176 | D9: The Cavern | F9: ZAHIL IMPORTADORA LTDA | G9: True | H9: 5 | I9: 3 | J9: 10970.67 | K9: 46073 | L9: 46084 | M9: 46083 | N9: 54853.37 | O9: 54853.37 | P9: 46038 | Q9: Boleto Bancário | R9: 260242 | S9: Custo Mercadoria Vendida | T9: Insumos - Bebidas | U9: Documentação Aprovada | V9: Aprovado Diretoria | W9: Aprovado Caixa | X9: Parcela_Paga | Y9: 226 | Z9: The Cavern - Kamino
A10: 12899 | B10: 193694 | C10: 176 | D10: The Cavern | F10: ZAHIL IMPORTADORA LTDA | G10: True | H10: 5 | I10: 1 | J10: 10970.67 | K10: 46045 | L10: 46038 | M10: 46083 | N10: 54853.37 | O10: 54853.37 | P10: 46038 | Q10: Boleto Bancário | R10: 260242 | S10: Custo Mercadoria Vendida | T10: Insumos - Bebidas | U10: Documentação Aprovada | V10: Aprovado Diretoria | W10: Aprovado Caixa | X10: Parcela_Paga | Y10: 226 | Z10: The Cavern - Kamino
A11: 13236 | B11: 208948 | C11: 176 | D11: The Cavern | F11: ZAHIL IMPORTADORA LTDA | G11: True | H11: 3 | I11: 1 | J11: 1705.17 | K11: 46080 | L11: 46083 | M11: 46080 | N11: 4794.4 | O11: 5115.51 | P11: 46072 | Q11: Boleto Bancário | R11: 264084 | S11: Custo Mercadoria Vendida | T11: Insumos - Bebidas | U11: Documentação Aprovada | V11: Aprovado Diretoria | W11: Aprovado Caixa | X11: Parcela_Paga | Y11: 226 | Z11: The Cavern - Kamino
A12: 12109 | B12: 176848 | C12: 176 | D12: The Cavern | F12: CALEBE EQUIPAMENTOS INDUSTRIAIS EIRELI | G12: True | H12: 3 | I12: 1 | J12: 2300 | K12: 46010 | L12: 46010 | M12: 46080 | N12: 6900 | O12: 6900 | P12: 45980 | Q12: Boleto Bancário | R12: 1513 | S12: Utilidades | T12: Utensilios | U12: Documentação Aprovada | V12: Aprovado Diretoria | W12: Aprovado Caixa | X12: Parcela_Paga | Y12: 226 | Z12: The Cavern - Kamino
A13: 12110 | B13: 176848 | C13: 176 | D13: The Cavern | F13: CALEBE EQUIPAMENTOS INDUSTRIAIS EIRELI | G13: True | H13: 3 | I13: 2 | J13: 2300 | K13: 46041 | L13: 46041 | M13: 46080 | N13: 6900 | O13: 6900 | P13: 45980 | Q13: Boleto Bancário | R13: 1513 | S13: Utilidades | T13: Utensilios | U13: Documentação Aprovada | V13: Aprovado Diretoria | W13: Aprovado Caixa | X13: Parcela_Paga
A14: 12111 | B14: 176848 | C14: 176 | D14: The Cavern | F14: CALEBE EQUIPAMENTOS INDUSTRIAIS EIRELI | G14: True | H14: 3 | I14: 3 | J14: 2353.66 | K14: 46070 | L14: 46083 | M14: 46080 | N14: 6900 | O14: 6900 | P14: 45980 | Q14: Boleto Bancário | R14: 1513 | S14: Utilidades | T14: Utensilios | U14: Documentação Aprovada | V14: Aprovado Diretoria | W14: Aprovado Caixa | X14: Parcela_Paga | Y14: 226 | Z14: The Cavern - Kamino
A15: 13247 | B15: 209321 | C15: 176 | D15: The Cavern | F15: ZAHIL IMPORTADORA LTDA | G15: True | H15: 2 | I15: 1 | J15: 722.71 | K15: 46076 | L15: 46076 | M15: 46076 | N15: 1357.2 | O15: 1445.42 | P15: 46072 | Q15: Boleto Bancário | R15: 263527 | S15: Custo Mercadoria Vendida | T15: Insumos - Bebidas | U15: Documentação Aprovada | V15: Aprovado Diretoria | W15: Aprovado Caixa | X15: Parcela_Paga | Y15: 226 | Z15: The Cavern - Kamino
A16: 12942 | B16: 195592 | C16: 176 | D16: The Cavern | F16: CALEBE EQUIPAMENTOS INDUSTRIAIS EIRELI | G16: True | H16: 6 | I16: 1 | J16: 4000 | K16: 46069 | L16: 46071 | M16: 46071 | N16: 24000 | O16: 24000 | P16: 46044 | Q16: Boleto Bancário | R16: 12472 | S16: Utilidades | T16: Utensilios | U16: Documentação Aprovada | V16: Aprovado Diretoria | W16: Aprovado Caixa | X16: Parcela_Paga | Y16: 226 | Z16: The Cavern - Kamino
A17: 12964 | B17: 196844 | C17: 176 | D17: The Cavern | F17: REBAL COMERCIAL LTDA | G17: True | H17: 3 | I17: 1 | J17: 1782.26 | K17: 46066 | L17: 46071 | M17: 46066 | N17: 5346.8 | O17: 5346.8 | P17: 46045 | Q17: Boleto Bancário | R17: 292320 | S17: Utilidades | T17: Utensilios | U17: Documentação Aprovada | V17: Aprovado Diretoria | W17: Aprovado Caixa | X17: Parcela_Paga | Y17: 226 | Z17: The Cavern - Kamino
A18: 12900 | B18: 193694 | C18: 176 | D18: The Cavern | F18: ZAHIL IMPORTADORA LTDA | G18: True | H18: 5 | I18: 2 | J18: 10970.67 | K18: 46059 | L18: 46045 | M18: 46059 | N18: 54853.37 | O18: 54853.37 | P18: 46038 | Q18: Boleto Bancário | R18: 260242 | S18: Custo Mercadoria Vendida | T18: Insumos - Bebidas | U18: Documentação Aprovada | V18: Aprovado Diretoria | W18: Aprovado Caixa | X18: Parcela_Paga

Sheet df_extratos
A1: ID_Extrato_Bancario | B1: ID_Conta_Bancaria | C1: Nome_Conta_Bancaria | D1: ID_Casa | E1: Casa | F1: Data_Transacao | G1: Tipo_Credito_Debito | H1: Descricao_Transacao | I1: Valor
A2: 261472 | B2: 226 | C2: The Cavern - Kamino | D2: 176 | E2: The Cavern | F2: 46080 | G2: DEBITO | H2: Sptrans | I2: -3151.14
A3: 261461 | B3: 226 | C3: The Cavern - Kamino | D3: 176 | E3: The Cavern | F3: 46080 | G3: DEBITO | H3: Cia do Whisky | I3: -432.44
A4: 261459 | B4: 226 | C4: The Cavern - Kamino | D4: 176 | E4: The Cavern | F4: 46080 | G4: DEBITO | H4: Zahil | I4: -1705.17
A5: 261458 | B5: 226 | C5: The Cavern - Kamino | D5: 176 | E5: The Cavern | F5: 46080 | G5: DEBITO | H5: Fg7 Comercio D B Eireli Epp | I5: -453.9
A6: 261457 | B6: 226 | C6: The Cavern - Kamino | D6: 176 | E6: The Cavern | F6: 46080 | G6: DEBITO | H6: Cecilia Tsuyaco Araki Silva Ltda | I6: -1292.5
A7: 261456 | B7: 226 | C7: The Cavern - Kamino | D7: 176 | E7: The Cavern | F7: 46080 | G7: DEBITO | H7: Analuisa Scalon de Oliveira Goncalves | I7: -688.75
A8: 261455 | B8: 226 | C8: The Cavern - Kamino | D8: 176 | E8: The Cavern | F8: 46080 | G8: DEBITO | H8: Paulo Sergio Lopes Martins de Freitas | I8: -7415.6
A9: 261454 | B9: 226 | C9: The Cavern - Kamino | D9: 176 | E9: The Cavern | F9: 46080 | G9: DEBITO | H9: Mar Direto Poc Comercio de Pei | I9: -1309.75
A10: 261453 | B10: 226 | C10: The Cavern - Kamino | D10: 176 | E10: The Cavern | F10: 46080 | G10: DEBITO | H10: Tarifa Pix Enviado-PJ | I10: -0.5
A11: 261452 | B11: 226 | C11: The Cavern - Kamino | D11: 176 | E11: The Cavern | F11: 46080 | G11: CREDITO | H11: A CAVERNA BAR LTDA | I11: 1000
A12: 261451 | B12: 226 | C12: The Cavern - Kamino | D12: 176 | E12: The Cavern | F12: 46080 | G12: CREDITO | H12: A CAVERNA BAR LTDA | I12: 24000
A13: 261450 | B13: 226 | C13: The Cavern - Kamino | D13: 176 | E13: The Cavern | F13: 46080 | G13: CREDITO | H13: Zig Tecnologia S.A. | I13: 5144
... A247: 256718 | B247: 226 | C247: The Cavern - Kamino | D247: 176 | E247: The Cavern | F247: 46059 | G247: DEBITO | H247: Potencial Servicos Tecnicos | I247: -9500

Sheet df_mutuos
A1: Mutuo_ID | B1: Data_Mutuo | C1: ID_Casa_Saida | D1: Casa_Saida | E1: ID_Conta_Saida | F1: Conta_Saida | G1: ID_Casa_Entrada | H1: Casa_Entrada | I1: ID_Conta_Entrada | J1: Conta_Entrada | K1: Tag_Faturam_Zig | L1: Observacoes | M1: Valor_Entrada | N1: Valor_Saida

Sheet df_tesouraria_trans
A1: ID_Transacao_Tesouraria | B1: ID_Casa | C1: Casa | D1: ID_Empresa_Tesouraria | E1: Empresa_Tesouraria | F1: Data_Transacao | G1: Valor | H1: Descricao

Sheet df_ajustes_conciliaco
A1: ID_Casa | B1: Casa | C1: Data_Ajuste | D1: Valor | E1: Categoria | F1: Descrição
A2: 176 | B2: The Cavern | C2: 46081 | D2: -3769.3 | E2: RESG/VENCTO CDB | F2: SAQUE ZIG QUE ENTROU NO ITAU
A3: 176 | B3: The Cavern | C3: 46080 | D3: 4600 | E3: RESG/VENCTO CDB | F3: DESPESAS PAGA PELO ROMULO NO ITAU ID 12.109 - 12.110 PARCELADO
A4: 176 | B4: The Cavern | C4: 46079 | D4: -2335.41 | E4: RESG/VENCTO CDB | F4: SAQUE ZIG QUE ENTROU NO ITAU
A5: 176 | B5: The Cavern | C5: 46076 | D5: -292.61 | E5: RESG/VENCTO CDB | F5: SAQUE ZIG QUE ENTROU NO ITAU
A6: 176 | B6: The Cavern | C6: 46075 | D6: -3110.6 | E6: RESG/VENCTO CDB | F6: SAQUE ZIG QUE ENTROU NO ITAU
A7: 176 | B7: The Cavern | C7: 46074 | D7: -3653.93 | E7: RESG/VENCTO CDB | F7: SAQUE ZIG QUE ENTROU NO ITAU
A8: 176 | B8: The Cavern | C8: 46073 | D8: -108.57 | E8: RESG/VENCTO CDB | F8: SAQUE ZIG QUE ENTROU NO ITAU
A9: 176 | B9: The Cavern | C9: 46072 | D9: -152.87 | E9: RESG/VENCTO CDB | F9: SAQUE ZIG QUE ENTROU NO ITAU
A10: 176 | B10: The Cavern | C10: 46071 | D10: -817.22 | E10: RESG/VENCTO CDB | F10: SAQUE ZIG QUE ENTROU NO ITAU
A11: 176 | B11: The Cavern | C11: 46070 | D11: -448.48 | E11: RESG/VENCTO CDB | F11: SAQUE ZIG QUE ENTROU NO ITAU
A12: 176 | B12: The Cavern | C12: 46069 | D12: -9619.6 | E12: RESG/VENCTO CDB | F12: SAQUE ZIG QUE ENTROU NO ITAU
A13: 176 | B13: The Cavern | C13: 46068 | D13: -6094.92 | E13: RESG/VENCTO CDB | F13: SAQUE ZIG QUE ENTROU NO ITAU
... A26: 176 | B26: The Cavern | C26: 46054 | D26: -14591.9 | E26: RESG/VENCTO CDB | F26: SAQUE ZIG QUE ENTROU NO ITAU

Sheet df_bloqueios_judiciais
A1: ID_Bloqueio | B1: ID_Casa | C1: Casa | D1: Data_Transacao | E1: ID_Conta_Bancaria | F1: Nome da Conta | G1: Valor | H1: Observacao
