Workbook

Sheet DRE
A3: BAR BRAHMA PAULISTA | H3: =IFERROR(J8/H8,0) -> 0 | J3: =IFERROR(J8/I8,0) -> 0 | K3: =IFERROR(M8/K8,0) -> 0 | M3: =IFERROR(M8/L8,0) -> 0 | N3: =IFERROR(P8/N8,0) -> 0 | P3: =IFERROR(P8/O8,0) -> 0 | Q3: =IFERROR(S8/Q8,0) -> 0 | S3: =IFERROR(S8/R8,0) -> 0 | T3: =IFERROR(V8/T8,0) -> 0 | V3: =IFERROR(V8/U8,0) -> 0 | W3: =IFERROR(Y8/W8,0) -> 0 | Y3: =IFERROR(Y8/X8,0) -> 0 | Z3: =IFERROR(AB8/Z8,0) -> 0 | AB3: =IFERROR(AB8/AA8,0) -> 0 | AC3: =IFERROR(AE8/AC8,0) -> 0 | AE3: =IFERROR(AE8/AD8,0) -> 0 | AF3: =IFERROR(AH8/AF8,0) -> 0 | AH3: =IFERROR(AH8/AG8,0) -> 0 | AI3: =IFERROR(AK8/AI8,0) -> 0 | AK3: =IFERROR(AK8/AJ8,0) -> 0 | AL3: =IFERROR(AN8/AL8,0) -> 0 | AN3: =IFERROR(AN8/AM8,0) -> 0 | AO3: =IFERROR(AQ8/AO8,0) -> 0 | AQ3: =IFERROR(AQ8/AP8,0) -> 0 | AR3: =IFERROR(AT8/AR8,0) -> 0 | AT3: =IFERROR(AT8/AS8,0) -> 0.071124714 | AU3: =IFERROR(AW8/AU8,0) -> 0 | AW3: =IFERROR(AW8/AV8,0) -> 0.014003695 | AX3: =IFERROR(AZ8/AX8,0) -> 0 | AZ3: =IFERROR(AZ8/AY8,0) -> 0 | BA3: =IFERROR(BC8/BA8,0) -> 0 | BC3: =IFERROR(BC8/BB8,0) -> 0 | BD3: =IFERROR(BF8/BD8,0) -> 0 | BF3: =IFERROR(BF8/BE8,0) -> 0.036125354 | BG3: =IFERROR(BI8/BG8,0) -> 0 | BI3: =IFERROR(BI8/BH8,0) -> 0
H4: 46023 | K4: 46054 | N4: 46082 | Q4: 46113 | T4: 46143 | W4: 46174 | Z4: 46204 | AC4: 46235 | AF4: 46266 | AI4: 46296 | AL4: 46327 | AO4: 46357 | AR4: Acumulado | AU4: ANO | AX4: 1º TRIMESTRE | BA4: 2º TRIMESTRE | BD4: 3º TRIMESTRE | BG4: 4º TRIMESTRE
H5: 1 | I5: 1 | J5: =MONTH(H4) -> 1 | K5: 2 | L5: 2 | M5: =MONTH(K4) -> 2 | N5: 3 | O5: 3 | P5: =MONTH(N4) -> 3 | Q5: 4 | R5: 4 | S5: =MONTH(Q4) -> 4 | T5: 5 | U5: 5 | V5: =MONTH(T4) -> 5 | W5: 6 | X5: 6 | Y5: =MONTH(W4) -> 6 | Z5: 7 | AA5: 7 | AB5: =MONTH(Z4) -> 7 | AC5: 8 | AD5: 8 | AE5: =MONTH(AC4) -> 8 | AF5: 9 | AG5: 9 | AH5: =MONTH(AF4) -> 9 | AI5: 10 | AJ5: 10 | AK5: =MONTH(AI4) -> 10 | AL5: 11 | AM5: 11 | AN5: =MONTH(AL4) -> 11 | AO5: 12 | AP5: 12 | AQ5: =MONTH(AO4) -> 12
H6: REAL 25 | I6: ORÇADO | J6: REAL 26 | K6: REAL 25 | L6: ORÇADO | M6: REAL 26 | N6: REAL 25 | O6: ORÇADO | P6: REAL 26 | Q6: REAL 25 | R6: ORÇADO | S6: REAL 26 | T6: REAL 25 | U6: ORÇADO | V6: REAL 26 | W6: REAL 25 | X6: ORÇADO | Y6: REAL 26 | Z6: REAL 25 | AA6: ORÇADO | AB6: REAL 26 | AC6: REAL 25 | AD6: ORÇADO | AE6: REAL 26 | AF6: REAL 25 | AG6: ORÇADO | AH6: REAL 26 | AI6: REAL 25 | AJ6: ORÇADO | AK6: REAL 26 | AL6: REAL 25 | AM6: ORÇADO | AN6: REAL 26 | AO6: REAL 25 | AP6: ORÇADO | AQ6: REAL 26 | AR6: 2025 | AS6: ORÇADO | AT6: REAL 2026 | AU6: 2025 | AV6: ORÇADO | AW6: REAL 2026 | AX6: REAL 25 | AY6: ORÇADO | AZ6: REAL 26 | BA6: REAL 25 | BB6: ORÇADO | BC6: REAL 26 | BD6: REAL 25 | BE6: ORÇADO | BF6: REAL 26 | BG6: REAL 25 | BH6: ORÇADO | BI6: REAL 26
H7: 45658 | I7: 46023 | K7: 45689 | L7: 46054 | N7: 45717 | Q7: 45748 | T7: 45778 | W7: 45809 | Z7: 45839 | AC7: 45870 | AF7: 45901 | AI7: 45931 | AL7: 45962 | AO7: 45992
A8: FATURAMENTO BRUTO | C8: PARÂMETROS UTILIZADOS | I8: =SUM(I9:I19) -> 0 | J8: =SUM(J9:J19)+SUMIFS(Aut_Ajustes_Manuais!$G:$G,Aut_Ajustes_Manuais!$I:$I,DRE!H$4,Aut_Ajustes_Manuais!$F:$F,"FATURAMENTO BRUTO") -> 0 | L8: =SUM(L9:L19) -> 0 | M8: =SUM(M9:M19)+SUMIFS(Aut_Ajustes_Manuais!$G:$G,Aut_Ajustes_Manuais!$I:$I,DRE!K$4,Aut_Ajustes_Manuais!$F:$F,"FATURAMENTO BRUTO") -> 0 | O8: =SUM(O9:O19) -> 0 | P8: =SUM(P9:P19)+SUMIFS(Aut_Ajustes_Manuais!$G:$G,Aut_Ajustes_Manuais!$I:$I,DRE!N$4,Aut_Ajustes_Manuais!$F:$F,"FATURAMENTO BRUTO") -> 0 | R8: =SUM(R9:R19) -> 0 | S8: =SUM(S9:S19)+SUMIFS(Aut_Ajustes_Manuais!$G:$G,Aut_Ajustes_Manuais!$I:$I,DRE!Q$4,Aut_Ajustes_Manuais!$F:$F,"FATURAMENTO BRUTO") -> 0 | U8: =SUM(U9:U19) -> 0 | V8: =SUM(V9:V19)+SUMIFS(Aut_Ajustes_Manuais!$G:$G,Aut_Ajustes_Manuais!$I:$I,DRE!T$4,Aut_Ajustes_Manuais!$F:$F,"FATURAMENTO BRUTO") -> 0 | X8: =SUM(X9:X19) -> 0 | Y8: =SUM(Y9:Y19)+SUMIFS(Aut_Ajustes_Manuais!$G:$G,Aut_Ajustes_Manuais!$I:$I,DRE!W$4,Aut_Ajustes_Manuais!$F:$F,"FATURAMENTO BRUTO") -> 0 | AA8: =SUM(AA9:AA19) -> 0 | AB8: =SUM(AB9:AB19)+SUMIFS(Aut_Ajustes_Manuais!$G:$G,Aut_Ajustes_Manuais!$I:$I,DRE!Z$4,Aut_Ajustes_Manuais!$F:$F,"FATURAMENTO BRUTO") -> 340656.42 | AD8: =SUM(AD9:AD19) -> 4789564.7 | AE8: =SUM(AE9:AE19)+SUMIFS(Aut_Ajustes_Manuais!$G:$G,Aut_Ajustes_Manuais!$I:$I,DRE!AC$4,Aut_Ajustes_Manuais!$F:$F,"FATURAMENTO BRUTO") -> 0 | AG8: =SUM(AG9:AG19) -> 4640278.5 | AH8: =SUM(AH9:AH19)+SUMIFS(Aut_Ajustes_Manuais!$G:$G,Aut_Ajustes_Manuais!$I:$I,DRE!AF$4,Aut_Ajustes_Manuais!$F:$F,"FATURAMENTO BRUTO") -> 0 | AJ8: =SUM(AJ9:AJ19) -> 5093050.1 | AK8: =SUM(AK9:AK19)+SUMIFS(Aut_Ajustes_Manuais!$G:$G,Aut_Ajustes_Manuais!$I:$I,DRE!AI$4,Aut_Ajustes_Manuais!$F:$F,"FATURAMENTO BRUTO") -> 0 | AM8: =SUM(AM9:AM19) -> 4691760.9 | AN8: =SUM(AN9:AN19)+SUMIFS(Aut_Ajustes_Manuais!$G:$G,Aut_Ajustes_Manuais!$I:$I,DRE!AL$4,Aut_Ajustes_Manuais!$F:$F,"FATURAMENTO BRUTO") -> 0 | AP8: =SUM(AP9:AP19) -> 5111526.5 | AQ8: =SUM(AQ9:AQ19)+SUMIFS(Aut_Ajustes_Manuais!$G:$G,Aut_Ajustes_Manuais!$I:$I,DRE!AO$4,Aut_Ajustes_Manuais!$F:$F,"FATURAMENTO BRUTO") -> 0 | AR8: =SUM(AR9:AR19) -> 0 | AS8: =SUM(AS9:AS19) -> 4789564.7 | AT8: =SUM(AT9:AT19) -> 340656.42 | AU8: =SUM(AU9:AU19) -> 0 | AV8: =SUM(AV9:AV19) -> 24326181 | AW8: =SUM(AW9:AW19) -> 340656.42 | AX8: =SUM(AX9:AX19) -> 0 | AY8: =SUM(AY9:AY19) -> 0 | ... BI8: =SUM(BI9:BI19) -> 0
A9: Alimentação | C9: Estim. Mensal | D9: Preencher base de Faturamento A&B&C | I9: =SUMIFS(T_ORCAMENTOS!$E:$E,T_ORCAMENTOS!$C:$C,"Alimentação",T_ORCAMENTOS!$H:$H,"1/2026") -> 0 | J9: =SUMIFS(Aut_Faturamento_Zig!$F:$F,Aut_Faturamento_Zig!$E:$E,"Alimentos",Aut_Faturamento_Zig!$D:$D,DRE!H$4)-SUMIFS(Aut_Promocoes_Utilizadas!$G:$G,Aut_Promocoes_Utilizadas!$J:$J,DRE!H$4,Aut_Promocoes_Utilizadas!$H:$H,"A",Aut_Promocoes_Utilizadas!$I:$I,"Eventos")-SUMIFS(Aut_Descontos!$I:$I,Aut_Descontos!$L:$L,DRE!H$4)-(SUMIFS(BD_Eventos_Novo!$J:$J,BD_Eventos_Novo!$AB:$AB,DRE!H$4,BD_Eventos_Novo!$G:$G,"Consumação Mínima")*50%)-(SUMIFS(BD_Eventos_Novo!$K:$K,BD_Eventos_Novo!$AB:$AB,DRE!H$4,BD_Eventos_Novo!$G:$G,"Consumação Mínima")*50%)-(SUMIFS(BD_Eventos_Novo!$J:$J,BD_Eventos_Novo!$AB:$AB,DRE!H$4,BD_Eventos_Novo!$G:$G,"Comanda Aberta / Couvert Antecipado")*50%)-(SUMIFS(BD_Eventos_Novo!$K:$K,BD_Eventos_Novo!$AB:$AB,DRE!H$4,BD_Eventos_Novo!$G:$G,"Comanda Aberta / Couvert Antecipado")*50%)+SUMIFS(Aut_Ajustes_Manuais!$G:$G,Aut_Ajustes_Manuais!$I:$I,DRE!H$4,Aut_Ajustes_Manuais!$F:$F,"Alimentação") -> 0 | L9: =SUMIFS(T_ORCAMENTOS!$E:$E,T_ORCAMENTOS!$C:$C,"Alimentação",T_ORCAMENTOS!$H:$H,"2/2026") -> 0 | M9: =SUMIFS(Aut_Faturamento_Zig!$F:$F,Aut_Faturamento_Zig!$E:$E,"Alimentos",Aut_Faturamento_Zig!$D:$D,DRE!K$4)-SUMIFS(Aut_Promocoes_Utilizadas!$G:$G,Aut_Promocoes_Utilizadas!$J:$J,DRE!K$4,Aut_Promocoes_Utilizadas!$H:$H,"A",Aut_Promocoes_Utilizadas!$I:$I,"Eventos")-SUMIFS(Aut_Descontos!$I:$I,Aut_Descontos!$L:$L,DRE!K$4)-(SUMIFS(BD_Eventos_Novo!$J:$J,BD_Eventos_Novo!$AB:$AB,DRE!K$4,BD_Eventos_Novo!$G:$G,"Consumação Mínima")*50%)-(SUMIFS(BD_Eventos_Novo!$K:$K,BD_Eventos_Novo!$AB:$AB,DRE!K$4,BD_Eventos_Novo!$G:$G,"Consumação Mínima")*50%)-(SUMIFS(BD_Eventos_Novo!$J:$J,BD_Eventos_Novo!$AB:$AB,DRE!K$4,BD_Eventos_Novo!$G:$G,"Comanda Aberta / Couvert Antecipado")*50%)-(SUMIFS(BD_Eventos_Novo!$K:$K,BD_Eventos_Novo!$AB:$AB,DRE!K$4,BD_Eventos_Novo!$G:$G,"Comanda Aberta / Couvert Antecipado")*50%)+SUMIFS(Aut_Ajustes_Manuais!$G:$G,Aut_Ajustes_Manuais!$I:$I,DRE!K$4,Aut_Ajustes_Manuais!$F:$F,"Alimentação") -> 0 | O9: =SUMIFS(T_ORCAMENTOS!$E:$E,T_ORCAMENTOS!$C:$C,"Alimentação",T_ORCAMENTOS!$H:$H,"3/2026") -> 0 | P9: =SUMIFS(Aut_Faturamento_Zig!$F:$F,Aut_Faturamento_Zig!$E:$E,"Alimentos",Aut_Faturamento_Zig!$D:$D,DRE!N$4)-SUMIFS(Aut_Promocoes_Utilizadas!$G:$G,Aut_Promocoes_Utilizadas!$J:$J,DRE!N$4,Aut_Promocoes_Utilizadas!$H:$H,"A",Aut_Promocoes_Utilizadas!$I:$I,"Eventos")-SUMIFS(Aut_Descontos!$I:$I,Aut_Descontos!$L:$L,DRE!N$4)-(SUMIFS(BD_Eventos_Novo!$J:$J,BD_Eventos_Novo!$AB:$AB,DRE!N$4,BD_Eventos_Novo!$G:$G,"Consumação Mínima")*50%)-(SUMIFS(BD_Eventos_Novo!$K:$K,BD_Eventos_Novo!$AB:$AB,DRE!N$4,BD_Eventos_Novo!$G:$G,"Consumação Mínima")*50%)-(SUMIFS(BD_Eventos_Novo!$J:$J,BD_Eventos_Novo!$AB:$AB,DRE!N$4,BD_Eventos_Novo!$G:$G,"Comanda Aberta / Couvert Antecipado")*50%)-(SUMIFS(BD_Eventos_Novo!$K:$K,BD_Eventos_Novo!$AB:$AB,DRE!N$4,BD_Eventos_Novo!$G:$G,"Comanda Aberta / Couvert Antecipado")*50%)+SUMIFS(Aut_Ajustes_Manuais!$G:$G,Aut_Ajustes_Manuais!$I:$I,DRE!N$4,Aut_Ajustes_Manuais!$F:$F,"Alimentação") -> 0 | R9: =SUMIFS(T_ORCAMENTOS!$E:$E,T_ORCAMENTOS!$C:$C,"Alimentação",T_ORCAMENTOS!$H:$H,"4/2026") -> 0 | S9: =SUMIFS(Aut_Faturamento_Zig!$F:$F,Aut_Faturamento_Zig!$E:$E,"Alimentos",Aut_Faturamento_Zig!$D:$D,DRE!Q$4)-SUMIFS(Aut_Promocoes_Utilizadas!$G:$G,Aut_Promocoes_Utilizadas!$J:$J,DRE!Q$4,Aut_Promocoes_Utilizadas!$H:$H,"A",Aut_Promocoes_Utilizadas!$I:$I,"Eventos")-SUMIFS(Aut_Descontos!$I:$I,Aut_Descontos!$L:$L,DRE!Q$4)-(SUMIFS(BD_Eventos_Novo!$J:$J,BD_Eventos_Novo!$AB:$AB,DRE!Q$4,BD_Eventos_Novo!$G:$G,"Consumação Mínima")*50%)-(SUMIFS(BD_Eventos_Novo!$K:$K,BD_Eventos_Novo!$AB:$AB,DRE!Q$4,BD_Eventos_Novo!$G:$G,"Consumação Mínima")*50%)-(SUMIFS(BD_Eventos_Novo!$J:$J,BD_Eventos_Novo!$AB:$AB,DRE!Q$4,BD_Eventos_Novo!$G:$G,"Comanda Aberta / Couvert Antecipado")*50%)-(SUMIFS(BD_Eventos_Novo!$K:$K,BD_Eventos_Novo!$AB:$AB,DRE!Q$4,BD_Eventos_Novo!$G:$G,"Comanda Aberta / Couvert Antecipado")*50%)+SUMIFS(Aut_Ajustes_Manuais!$G:$G,Aut_Ajustes_Manuais!$I:$I,DRE!Q$4,Aut_Ajustes_Manuais!$F:$F,"Alimentação") -> 0 | U9: =SUMIFS(T_ORCAMENTOS!$E:$E,T_ORCAMENTOS!$C:$C,"Alimentação",T_ORCAMENTOS!$H:$H,"5/2026") -> 0 | V9: =SUMIFS(Aut_Faturamento_Zig!$F:$F,Aut_Faturamento_Zig!$E:$E,"Alimentos",Aut_Faturamento_Zig!$D:$D,DRE!T$4)-SUMIFS(Aut_Promocoes_Utilizadas!$G:$G,Aut_Promocoes_Utilizadas!$J:$J,DRE!T$4,Aut_Promocoes_Utilizadas!$H:$H,"A",Aut_Promocoes_Utilizadas!$I:$I,"Eventos")-SUMIFS(Aut_Descontos!$I:$I,Aut_Descontos!$L:$L,DRE!T$4)-(SUMIFS(BD_Eventos_Novo!$J:$J,BD_Eventos_Novo!$AB:$AB,DRE!T$4,BD_Eventos_Novo!$G:$G,"Consumação Mínima")*50%)-(SUMIFS(BD_Eventos_Novo!$K:$K,BD_Eventos_Novo!$AB:$AB,DRE!T$4,BD_Eventos_Novo!$G:$G,"Consumação Mínima")*50%)-(SUMIFS(BD_Eventos_Novo!$J:$J,BD_Eventos_Novo!$AB:$AB,DRE!T$4,BD_Eventos_Novo!$G:$G,"Comanda Aberta / Couvert Antecipado")*50%)-(SUMIFS(BD_Eventos_Novo!$K:$K,BD_Eventos_Novo!$AB:$AB,DRE!T$4,BD_Eventos_Novo!$G:$G,"Comanda Aberta / Couvert Antecipado")*50%)+SUMIFS(Aut_Ajustes_Manuais!$G:$G,Aut_Ajustes_Manuais!$I:$I,DRE!T$4,Aut_Ajustes_Manuais!$F:$F,"Alimentação") -> 0 | X9: =SUMIFS(T_ORCAMENTOS!$E:$E,T_ORCAMENTOS!$C:$C,"Alimentação",T_ORCAMENTOS!$H:$H,"6/2026") -> 0 | Y9: =SUMIFS(Aut_Faturamento_Zig!$F:$F,Aut_Faturamento_Zig!$E:$E,"Alimentos",Aut_Faturamento_Zig!$D:$D,DRE!W$4)-SUMIFS(Aut_Promocoes_Utilizadas!$G:$G,Aut_Promocoes_Utilizadas!$J:$J,DRE!W$4,Aut_Promocoes_Utilizadas!$H:$H,"A",Aut_Promocoes_Utilizadas!$I:$I,"Eventos")-SUMIFS(Aut_Descontos!$I:$I,Aut_Descontos!$L:$L,DRE!W$4)-(SUMIFS(BD_Eventos_Novo!$J:$J,BD_Eventos_Novo!$AB:$AB,DRE!W$4,BD_Eventos_Novo!$G:$G,"Consumação Mínima")*50%)-(SUMIFS(BD_Eventos_Novo!$K:$K,BD_Eventos_Novo!$AB:$AB,DRE!W$4,BD_Eventos_Novo!$G:$G,"Consumação Mínima")*50%)-(SUMIFS(BD_Eventos_Novo!$J:$J,BD_Eventos_Novo!$AB:$AB,DRE!W$4,BD_Eventos_Novo!$G:$G,"Comanda Aberta / Couvert Antecipado")*50%)-(SUMIFS(BD_Eventos_Novo!$K:$K,BD_Eventos_Novo!$AB:$AB,DRE!W$4,BD_Eventos_Novo!$G:$G,"Comanda Aberta / Couvert Antecipado")*50%)+SUMIFS(Aut_Ajustes_Manuais!$G:$G,Aut_Ajustes_Manuais!$I:$I,DRE!W$4,Aut_Ajustes_Manuais!$F:$F,"Alimentação") -> 0 | AA9: =SUMIFS(T_ORCAMENTOS!$E:$E,T_ORCAMENTOS!$C:$C,"Alimentação",T_ORCAMENTOS!$H:$H,"7/2026") -> 0 | AB9: =SUMIFS(Aut_Faturamento_Zig!$F:$F,Aut_Faturamento_Zig!$E:$E,"Alimentos",Aut_Faturamento_Zig!$D:$D,DRE!Z$4)-SUMIFS(Aut_Promocoes_Utilizadas!$G:$G,Aut_Promocoes_Utilizadas!$J:$J,DRE!Z$4,Aut_Promocoes_Utilizadas!$H:$H,"A",Aut_Promocoes_Utilizadas!$I:$I,"Eventos")-SUMIFS(Aut_Descontos!$I:$I,Aut_Descontos!$L:$L,DRE!Z$4)-(SUMIFS(BD_Eventos_Novo!$J:$J,BD_Eventos_Novo!$AB:$AB,DRE!Z$4,BD_Eventos_Novo!$G:$G,"Consumação Mínima")*50%)-(SUMIFS(BD_Eventos_Novo!$K:$K,BD_Eventos_Novo!$AB:$AB,DRE!Z$4,BD_Eventos_Novo!$G:$G,"Consumação Mínima")*50%)-(SUMIFS(BD_Eventos_Novo!$J:$J,BD_Eventos_Novo!$AB:$AB,DRE!Z$4,BD_Eventos_Novo!$G:$G,"Comanda Aberta / Couvert Antecipado")*50%)-(SUMIFS(BD_Eventos_Novo!$K:$K,BD_Eventos_Novo!$AB:$AB,DRE!Z$4,BD_Eventos_Novo!$G:$G,"Comanda Aberta / Couvert Antecipado")*50%)+SUMIFS(Aut_Ajustes_Manuais!$G:$G,Aut_Ajustes_Manuais!$I:$I,DRE!Z$4,Aut_Ajustes_Manuais!$F:$F,"Alimentação") -> 120768 | AD9: =SUMIFS(T_ORCAMENTOS!$E:$E,T_ORCAMENTOS!$C:$C,"Alimentação",T_ORCAMENTOS!$H:$H,"8/2026") -> 1936227.6 | AE9: =SUMIFS(Aut_Faturamento_Zig!$F:$F,Aut_Faturamento_Zig!$E:$E,"Alimentos",Aut_Faturamento_Zig!$D:$D,DRE!AC$4)-SUMIFS(Aut_Promocoes_Utilizadas!$G:$G,Aut_Promocoes_Utilizadas!$J:$J,DRE!AC$4,Aut_Promocoes_Utilizadas!$H:$H,"A",Aut_Promocoes_Utilizadas!$I:$I,"Eventos")-SUMIFS(Aut_Descontos!$I:$I,Aut_Descontos!$L:$L,DRE!AC$4)-(SUMIFS(BD_Eventos_Novo!$J:$J,BD_Eventos_Novo!$AB:$AB,DRE!AC$4,BD_Eventos_Novo!$G:$G,"Consumação Mínima")*50%)-(SUMIFS(BD_Eventos_Novo!$K:$K,BD_Eventos_Novo!$AB:$AB,DRE!AC$4,BD_Eventos_Novo!$G:$G,"Consumação Mínima")*50%)-(SUMIFS(BD_Eventos_Novo!$J:$J,BD_Eventos_Novo!$AB:$AB,DRE!AC$4,BD_Eventos_Novo!$G:$G,"Comanda Aberta / Couvert Antecipado")*50%)-(SUMIFS(BD_Eventos_Novo!$K:$K,BD_Eventos_Novo!$AB:$AB,DRE!AC$4,BD_Eventos_Novo!$G:$G,"Comanda Aberta / Couvert Antecipado")*50%)+SUMIFS(Aut_Ajustes_Manuais!$G:$G,Aut_Ajustes_Manuais!$I:$I,DRE!AC$4,Aut_Ajustes_Manuais!$F:$F,"Alimentação") -> 0 | AG9: =SUMIFS(T_ORCAMENTOS!$E:$E,T_ORCAMENTOS!$C:$C,"Alimentação",T_ORCAMENTOS!$H:$H,"9/2026") -> 1845573.6 | AH9: =SUMIFS(Aut_Faturamento_Zig!$F:$F,Aut_Faturamento_Zig!$E:$E,"Alimentos",Aut_Faturamento_Zig!$D:$D,DRE!AF$4)-SUMIFS(Aut_Promocoes_Utilizadas!$G:$G,Aut_Promocoes_Utilizadas!$J:$J,DRE!AF$4,Aut_Promocoes_Utilizadas!$H:$H,"A",Aut_Promocoes_Utilizadas!$I:$I,"Eventos")-SUMIFS(Aut_Descontos!$I:$I,Aut_Descontos!$L:$L,DRE!AF$4)-(SUMIFS(BD_Eventos_Novo!$J:$J,BD_Eventos_Novo!$AB:$AB,DRE!AF$4,BD_Eventos_Novo!$G:$G,"Consumação Mínima")*50%)-(SUMIFS(BD_Eventos_Novo!$K:$K,BD_Eventos_Novo!$AB:$AB,DRE!AF$4,BD_Eventos_Novo!$G:$G,"Consumação Mínima")*50%)-(SUMIFS(BD_Eventos_Novo!$J:$J,BD_Eventos_Novo!$AB:$AB,DRE!AF$4,BD_Eventos_Novo!$G:$G,"Comanda Aberta / Couvert Antecipado")*50%)-(SUMIFS(BD_Eventos_Novo!$K:$K,BD_Eventos_Novo!$AB:$AB,DRE!AF$4,BD_Eventos_Novo!$G:$G,"Comanda Aberta / Couvert Antecipado")*50%)+SUMIFS(Aut_Ajustes_Manuais!$G:$G,Aut_Ajustes_Manuais!$I:$I,DRE!AF$4,Aut_Ajustes_Manuais!$F:$F,"Alimentação") -> 0 | AJ9: =SUMIFS(T_ORCAMENTOS!$E:$E,T_ORCAMENTOS!$C:$C,"Alimentação",T_ORCAMENTOS!$H:$H,"10/2026") -> 1996644.3 | AK9: =SUMIFS(Aut_Faturamento_Zig!$F:$F,Aut_Faturamento_Zig!$E:$E,"Alimentos",Aut_Faturamento_Zig!$D:$D,DRE!AI$4)-SUMIFS(Aut_Promocoes_Utilizadas!$G:$G,Aut_Promocoes_Utilizadas!$J:$J,DRE!AI$4,Aut_Promocoes_Utilizadas!$H:$H,"A",Aut_Promocoes_Utilizadas!$I:$I,"Eventos")-SUMIFS(Aut_Descontos!$I:$I,Aut_Descontos!$L:$L,DRE!AI$4)-(SUMIFS(BD_Eventos_Novo!$J:$J,BD_Eventos_Novo!$AB:$AB,DRE!AI$4,BD_Eventos_Novo!$G:$G,"Consumação Mínima")*50%)-(SUMIFS(BD_Eventos_Novo!$K:$K,BD_Eventos_Novo!$AB:$AB,DRE!AI$4,BD_Eventos_Novo!$G:$G,"Consumação Mínima")*50%)-(SUMIFS(BD_Eventos_Novo!$J:$J,BD_Eventos_Novo!$AB:$AB,DRE!AI$4,BD_Eventos_Novo!$G:$G,"Comanda Aberta / Couvert Antecipado")*50%)-(SUMIFS(BD_Eventos_Novo!$K:$K,BD_Eventos_Novo!$AB:$AB,DRE!AI$4,BD_Eventos_Novo!$G:$G,"Comanda Aberta / Couvert Antecipado")*50%)+SUMIFS(Aut_Ajustes_Manuais!$G:$G,Aut_Ajustes_Manuais!$I:$I,DRE!AI$4,Aut_Ajustes_Manuais!$F:$F,"Alimentação") -> 0 | AM9: =SUMIFS(T_ORCAMENTOS!$E:$E,T_ORCAMENTOS!$C:$C,"Alimentação",T_ORCAMENTOS!$H:$H,"11/2026") -> 1821943.2 | AN9: =SUMIFS(Aut_Faturamento_Zig!$F:$F,Aut_Faturamento_Zig!$E:$E,"Alimentos",Aut_Faturamento_Zig!$D:$D,DRE!AL$4)-SUMIFS(Aut_Promocoes_Utilizadas!$G:$G,Aut_Promocoes_Utilizadas!$J:$J,DRE!AL$4,Aut_Promocoes_Utilizadas!$H:$H,"A",Aut_Promocoes_Utilizadas!$I:$I,"Eventos")-SUMIFS(Aut_Descontos!$I:$I,Aut_Descontos!$L:$L,DRE!AL$4)-(SUMIFS(BD_Eventos_Novo!$J:$J,BD_Eventos_Novo!$AB:$AB,DRE!AL$4,BD_Eventos_Novo!$G:$G,"Consumação Mínima")*50%)-(SUMIFS(BD_Eventos_Novo!$K:$K,BD_Eventos_Novo!$AB:$AB,DRE!AL$4,BD_Eventos_Novo!$G:$G,"Consumação Mínima")*50%)-(SUMIFS(BD_Eventos_Novo!$J:$J,BD_Eventos_Novo!$AB:$AB,DRE!AL$4,BD_Eventos_Novo!$G:$G,"Comanda Aberta / Couvert Antecipado")*50%)-(SUMIFS(BD_Eventos_Novo!$K:$K,BD_Eventos_Novo!$AB:$AB,DRE!AL$4,BD_Eventos_Novo!$G:$G,"Comanda Aberta / Couvert Antecipado")*50%)+SUMIFS(Aut_Ajustes_Manuais!$G:$G,Aut_Ajustes_Manuais!$I:$I,DRE!AL$4,Aut_Ajustes_Manuais!$F:$F,"Alimentação") -> 0 | AP9: =SUMIFS(T_ORCAMENTOS!$E:$E,T_ORCAMENTOS!$C:$C,"Alimentação",T_ORCAMENTOS!$H:$H,"12/2026") -> 1819938 | AQ9: =SUMIFS(Aut_Faturamento_Zig!$F:$F,Aut_Faturamento_Zig!$E:$E,"Alimentos",Aut_Faturamento_Zig!$D:$D,DRE!AO$4)-SUMIFS(Aut_Promocoes_Utilizadas!$G:$G,Aut_Promocoes_Utilizadas!$J:$J,DRE!AO$4,Aut_Promocoes_Utilizadas!$H:$H,"A",Aut_Promocoes_Utilizadas!$I:$I,"Eventos")-SUMIFS(Aut_Descontos!$I:$I,Aut_Descontos!$L:$L,DRE!AO$4)-(SUMIFS(BD_Eventos_Novo!$J:$J,BD_Eventos_Novo!$AB:$AB,DRE!AO$4,BD_Eventos_Novo!$G:$G,"Consumação Mínima")*50%)-(SUMIFS(BD_Eventos_Novo!$K:$K,BD_Eventos_Novo!$AB:$AB,DRE!AO$4,BD_Eventos_Novo!$G:$G,"Consumação Mínima")*50%)-(SUMIFS(BD_Eventos_Novo!$J:$J,BD_Eventos_Novo!$AB:$AB,DRE!AO$4,BD_Eventos_Novo!$G:$G,"Comanda Aberta / Couvert Antecipado")*50%)-(SUMIFS(BD_Eventos_Novo!$K:$K,BD_Eventos_Novo!$AB:$AB,DRE!AO$4,BD_Eventos_Novo!$G:$G,"Comanda Aberta / Couvert Antecipado")*50%)+SUMIFS(Aut_Ajustes_Manuais!$G:$G,Aut_Ajustes_Manuais!$I:$I,DRE!AO$4,Aut_Ajustes_Manuais!$F:$F,"Alimentação") -> 0 | AR9: =SUMIFS($H9:$AO9,$H$5:$AO$5,"<"&MONTH(TODAY()),$H$6:$AO$6,"REAL 25") -> 0 | AS9: =SUMIFS($I9:$AP9,$I$5:$AP$5,"<"&MONTH(TODAY()),$I$6:$AP$6,"ORÇADO ") -> 1936227.6 | AT9: =SUMIFS($J9:$AQ9,$J$5:$AQ$5,"<"&MONTH(TODAY()),$J$6:$AQ$6,"REAL 26") -> 120768 | AU9: =SUM(H9,K9,N9,Q9,T9,W9,Z9,AC9,AF9,AI9,AL9,AO9) -> 0 | AV9: =SUM(I9,L9,O9,R9,U9,X9,AA9,AD9,AG9,AJ9,AM9,AP9) -> 9420326.6 | AW9: =SUM(J9,M9,P9,S9,V9,Y9,AB9,AE9,AH9,AK9,AN9,AQ9) -> 120768 | AX9: =SUM(H9,K9,N9) -> 0 | AY9: =SUM(I9,L9,O9) -> 0 | AZ9: =SUM(J9,M9,P9) -> 0 | BA9: =SUM(Q9,T9,W9) -> 0 | BB9: =SUM(R9,U9,X9) -> 0 | BC9: =SUM(S9,V9,Y9) -> 0 | BD9: =SUM(Z9,AC9,AF9) -> 0 | BE9: =SUM(AA9,AD9,AG9) -> 3781801.2 | BF9: =SUM(AB9,AE9,AH9) -> 120768 | BG9: =SUM(AI9,AL9,AO9) -> 0 | BH9: =SUM(AJ9,AM9,AP9) -> 5638525.4 | BI9: =SUM(AK9,AN9,AQ9) -> 0
A10: Bebida | C10: Estim. Mensal | D10: Preencher base de Faturamento A&B&C | I10: =SUMIFS(T_ORCAMENTOS!$E:$E,T_ORCAMENTOS!$C:$C,"Bebida",T_ORCAMENTOS!$H:$H,"1/2026") -> 0 | J10: =SUMIFS(Aut_Faturamento_Zig!$F:$F,Aut_Faturamento_Zig!$E:$E,"Bebidas",Aut_Faturamento_Zig!$D:$D,DRE!H$4)-SUMIFS(Aut_Promocoes_Utilizadas!$G:$G,Aut_Promocoes_Utilizadas!$J:$J,DRE!H$4,Aut_Promocoes_Utilizadas!$H:$H,"B",Aut_Promocoes_Utilizadas!$I:$I,"Eventos")-SUMIFS(Aut_Descontos!$J:$J,Aut_Descontos!$L:$L,DRE!H$4)-(SUMIFS(BD_Eventos_Novo!$J:$J,BD_Eventos_Novo!$AB:$AB,DRE!H$4,BD_Eventos_Novo!$G:$G,"Consumação Mínima")*50%)-(SUMIFS(BD_Eventos_Novo!$K:$K,BD_Eventos_Novo!$AB:$AB,DRE!H$4,BD_Eventos_Novo!$G:$G,"Consumação Mínima")*50%)-(SUMIFS(BD_Eventos_Novo!$J:$J,BD_Eventos_Novo!$AB:$AB,DRE!H$4,BD_Eventos_Novo!$G:$G,"Comanda Aberta / Couvert Antecipado")*50%)-(SUMIFS(BD_Eventos_Novo!$K:$K,BD_Eventos_Novo!$AB:$AB,DRE!H$4,BD_Eventos_Novo!$G:$G,"Comanda Aberta / Couvert Antecipado")*50%)+SUMIFS(Aut_Ajustes_Manuais!$G:$G,Aut_Ajustes_Manuais!$I:$I,DRE!H$4,Aut_Ajustes_Manuais!$F:$F,"Bebida") -> 0 | L10: =SUMIFS(T_ORCAMENTOS!$E:$E,T_ORCAMENTOS!$C:$C,"Bebida",T_ORCAMENTOS!$H:$H,"2/2026") -> 0 | M10: =SUMIFS(Aut_Faturamento_Zig!$F:$F,Aut_Faturamento_Zig!$E:$E,"Bebidas",Aut_Faturamento_Zig!$D:$D,DRE!K$4)-SUMIFS(Aut_Promocoes_Utilizadas!$G:$G,Aut_Promocoes_Utilizadas!$J:$J,DRE!K$4,Aut_Promocoes_Utilizadas!$H:$H,"B",Aut_Promocoes_Utilizadas!$I:$I,"Eventos")-SUMIFS(Aut_Descontos!$J:$J,Aut_Descontos!$L:$L,DRE!K$4)-(SUMIFS(BD_Eventos_Novo!$J:$J,BD_Eventos_Novo!$AB:$AB,DRE!K$4,BD_Eventos_Novo!$G:$G,"Consumação Mínima")*50%)-(SUMIFS(BD_Eventos_Novo!$K:$K,BD_Eventos_Novo!$AB:$AB,DRE!K$4,BD_Eventos_Novo!$G:$G,"Consumação Mínima")*50%)-(SUMIFS(BD_Eventos_Novo!$J:$J,BD_Eventos_Novo!$AB:$AB,DRE!K$4,BD_Eventos_Novo!$G:$G,"Comanda Aberta / Couvert Antecipado")*50%)-(SUMIFS(BD_Eventos_Novo!$K:$K,BD_Eventos_Novo!$AB:$AB,DRE!K$4,BD_Eventos_Novo!$G:$G,"Comanda Aberta / Couvert Antecipado")*50%)+SUMIFS(Aut_Ajustes_Manuais!$G:$G,Aut_Ajustes_Manuais!$I:$I,DRE!K$4,Aut_Ajustes_Manuais!$F:$F,"Bebida") -> 0 | O10: =SUMIFS(T_ORCAMENTOS!$E:$E,T_ORCAMENTOS!$C:$C,"Bebida",T_ORCAMENTOS!$H:$H,"3/2026") -> 0 | P10: =SUMIFS(Aut_Faturamento_Zig!$F:$F,Aut_Faturamento_Zig!$E:$E,"Bebidas",Aut_Faturamento_Zig!$D:$D,DRE!N$4)-SUMIFS(Aut_Promocoes_Utilizadas!$G:$G,Aut_Promocoes_Utilizadas!$J:$J,DRE!N$4,Aut_Promocoes_Utilizadas!$H:$H,"B",Aut_Promocoes_Utilizadas!$I:$I,"Eventos")-SUMIFS(Aut_Descontos!$J:$J,Aut_Descontos!$L:$L,DRE!N$4)-(SUMIFS(BD_Eventos_Novo!$J:$J,BD_Eventos_Novo!$AB:$AB,DRE!N$4,BD_Eventos_Novo!$G:$G,"Consumação Mínima")*50%)-(SUMIFS(BD_Eventos_Novo!$K:$K,BD_Eventos_Novo!$AB:$AB,DRE!N$4,BD_Eventos_Novo!$G:$G,"Consumação Mínima")*50%)-(SUMIFS(BD_Eventos_Novo!$J:$J,BD_Eventos_Novo!$AB:$AB,DRE!N$4,BD_Eventos_Novo!$G:$G,"Comanda Aberta / Couvert Antecipado")*50%)-(SUMIFS(BD_Eventos_Novo!$K:$K,BD_Eventos_Novo!$AB:$AB,DRE!N$4,BD_Eventos_Novo!$G:$G,"Comanda Aberta / Couvert Antecipado")*50%)+SUMIFS(Aut_Ajustes_Manuais!$G:$G,Aut_Ajustes_Manuais!$I:$I,DRE!N$4,Aut_Ajustes_Manuais!$F:$F,"Bebida") -> 0 | R10: =SUMIFS(T_ORCAMENTOS!$E:$E,T_ORCAMENTOS!$C:$C,"Bebida",T_ORCAMENTOS!$H:$H,"4/2026") -> 0 | S10: =SUMIFS(Aut_Faturamento_Zig!$F:$F,Aut_Faturamento_Zig!$E:$E,"Bebidas",Aut_Faturamento_Zig!$D:$D,DRE!Q$4)-SUMIFS(Aut_Promocoes_Utilizadas!$G:$G,Aut_Promocoes_Utilizadas!$J:$J,DRE!Q$4,Aut_Promocoes_Utilizadas!$H:$H,"B",Aut_Promocoes_Utilizadas!$I:$I,"Eventos")-SUMIFS(Aut_Descontos!$J:$J,Aut_Descontos!$L:$L,DRE!Q$4)-(SUMIFS(BD_Eventos_Novo!$J:$J,BD_Eventos_Novo!$AB:$AB,DRE!Q$4,BD_Eventos_Novo!$G:$G,"Consumação Mínima")*50%)-(SUMIFS(BD_Eventos_Novo!$K:$K,BD_Eventos_Novo!$AB:$AB,DRE!Q$4,BD_Eventos_Novo!$G:$G,"Consumação Mínima")*50%)-(SUMIFS(BD_Eventos_Novo!$J:$J,BD_Eventos_Novo!$AB:$AB,DRE!Q$4,BD_Eventos_Novo!$G:$G,"Comanda Aberta / Couvert Antecipado")*50%)-(SUMIFS(BD_Eventos_Novo!$K:$K,BD_Eventos_Novo!$AB:$AB,DRE!Q$4,BD_Eventos_Novo!$G:$G,"Comanda Aberta / Couvert Antecipado")*50%)+SUMIFS(Aut_Ajustes_Manuais!$G:$G,Aut_Ajustes_Manuais!$I:$I,DRE!Q$4,Aut_Ajustes_Manuais!$F:$F,"Bebida") -> 0 | U10: =SUMIFS(T_ORCAMENTOS!$E:$E,T_ORCAMENTOS!$C:$C,"Bebida",T_ORCAMENTOS!$H:$H,"5/2026") -> 0 | V10: =SUMIFS(Aut_Faturamento_Zig!$F:$F,Aut_Faturamento_Zig!$E:$E,"Bebidas",Aut_Faturamento_Zig!$D:$D,DRE!T$4)-SUMIFS(Aut_Promocoes_Utilizadas!$G:$G,Aut_Promocoes_Utilizadas!$J:$J,DRE!T$4,Aut_Promocoes_Utilizadas!$H:$H,"B",Aut_Promocoes_Utilizadas!$I:$I,"Eventos")-SUMIFS(Aut_Descontos!$J:$J,Aut_Descontos!$L:$L,DRE!T$4)-(SUMIFS(BD_Eventos_Novo!$J:$J,BD_Eventos_Novo!$AB:$AB,DRE!T$4,BD_Eventos_Novo!$G:$G,"Consumação Mínima")*50%)-(SUMIFS(BD_Eventos_Novo!$K:$K,BD_Eventos_Novo!$AB:$AB,DRE!T$4,BD_Eventos_Novo!$G:$G,"Consumação Mínima")*50%)-(SUMIFS(BD_Eventos_Novo!$J:$J,BD_Eventos_Novo!$AB:$AB,DRE!T$4,BD_Eventos_Novo!$G:$G,"Comanda Aberta / Couvert Antecipado")*50%)-(SUMIFS(BD_Eventos_Novo!$K:$K,BD_Eventos_Novo!$AB:$AB,DRE!T$4,BD_Eventos_Novo!$G:$G,"Comanda Aberta / Couvert Antecipado")*50%)+SUMIFS(Aut_Ajustes_Manuais!$G:$G,Aut_Ajustes_Manuais!$I:$I,DRE!T$4,Aut_Ajustes_Manuais!$F:$F,"Bebida") -> 0 | X10: =SUMIFS(T_ORCAMENTOS!$E:$E,T_ORCAMENTOS!$C:$C,"Bebida",T_ORCAMENTOS!$H:$H,"6/2026") -> 0 | Y10: =SUMIFS(Aut_Faturamento_Zig!$F:$F,Aut_Faturamento_Zig!$E:$E,"Bebidas",Aut_Faturamento_Zig!$D:$D,DRE!W$4)-SUMIFS(Aut_Promocoes_Utilizadas!$G:$G,Aut_Promocoes_Utilizadas!$J:$J,DRE!W$4,Aut_Promocoes_Utilizadas!$H:$H,"B",Aut_Promocoes_Utilizadas!$I:$I,"Eventos")-SUMIFS(Aut_Descontos!$J:$J,Aut_Descontos!$L:$L,DRE!W$4)-(SUMIFS(BD_Eventos_Novo!$J:$J,BD_Eventos_Novo!$AB:$AB,DRE!W$4,BD_Eventos_Novo!$G:$G,"Consumação Mínima")*50%)-(SUMIFS(BD_Eventos_Novo!$K:$K,BD_Eventos_Novo!$AB:$AB,DRE!W$4,BD_Eventos_Novo!$G:$G,"Consumação Mínima")*50%)-(SUMIFS(BD_Eventos_Novo!$J:$J,BD_Eventos_Novo!$AB:$AB,DRE!W$4,BD_Eventos_Novo!$G:$G,"Comanda Aberta / Couvert Antecipado")*50%)-(SUMIFS(BD_Eventos_Novo!$K:$K,BD_Eventos_Novo!$AB:$AB,DRE!W$4,BD_Eventos_Novo!$G:$G,"Comanda Aberta / Couvert Antecipado")*50%)+SUMIFS(Aut_Ajustes_Manuais!$G:$G,Aut_Ajustes_Manuais!$I:$I,DRE!W$4,Aut_Ajustes_Manuais!$F:$F,"Bebida") -> 0 | AA10: =SUMIFS(T_ORCAMENTOS!$E:$E,T_ORCAMENTOS!$C:$C,"Bebida",T_ORCAMENTOS!$H:$H,"7/2026") -> 0 | AB10: =SUMIFS(Aut_Faturamento_Zig!$F:$F,Aut_Faturamento_Zig!$E:$E,"Bebidas",Aut_Faturamento_Zig!$D:$D,DRE!Z$4)-SUMIFS(Aut_Promocoes_Utilizadas!$G:$G,Aut_Promocoes_Utilizadas!$J:$J,DRE!Z$4,Aut_Promocoes_Utilizadas!$H:$H,"B",Aut_Promocoes_Utilizadas!$I:$I,"Eventos")-SUMIFS(Aut_Descontos!$J:$J,Aut_Descontos!$L:$L,DRE!Z$4)-(SUMIFS(BD_Eventos_Novo!$J:$J,BD_Eventos_Novo!$AB:$AB,DRE!Z$4,BD_Eventos_Novo!$G:$G,"Consumação Mínima")*50%)-(SUMIFS(BD_Eventos_Novo!$K:$K,BD_Eventos_Novo!$AB:$AB,DRE!Z$4,BD_Eventos_Novo!$G:$G,"Consumação Mínima")*50%)-(SUMIFS(BD_Eventos_Novo!$J:$J,BD_Eventos_Novo!$AB:$AB,DRE!Z$4,BD_Eventos_Novo!$G:$G,"Comanda Aberta / Couvert Antecipado")*50%)-(SUMIFS(BD_Eventos_Novo!$K:$K,BD_Eventos_Novo!$AB:$AB,DRE!Z$4,BD_Eventos_Novo!$G:$G,"Comanda Aberta / Couvert Antecipado")*50%)+SUMIFS(Aut_Ajustes_Manuais!$G:$G,Aut_Ajustes_Manuais!$I:$I,DRE!Z$4,Aut_Ajustes_Manuais!$F:$F,"Bebida") -> 137627.7 | AD10: =SUMIFS(T_ORCAMENTOS!$E:$E,T_ORCAMENTOS!$C:$C,"Bebida",T_ORCAMENTOS!$H:$H,"8/2026") -> 1483067.9 | AE10: =SUMIFS(Aut_Faturamento_Zig!$F:$F,Aut_Faturamento_Zig!$E:$E,"Bebidas",Aut_Faturamento_Zig!$D:$D,DRE!AC$4)-SUMIFS(Aut_Promocoes_Utilizadas!$G:$G,Aut_Promocoes_Utilizadas!$J:$J,DRE!AC$4,Aut_Promocoes_Utilizadas!$H:$H,"B",Aut_Promocoes_Utilizadas!$I:$I,"Eventos")-SUMIFS(Aut_Descontos!$J:$J,Aut_Descontos!$L:$L,DRE!AC$4)-(SUMIFS(BD_Eventos_Novo!$J:$J,BD_Eventos_Novo!$AB:$AB,DRE!AC$4,BD_Eventos_Novo!$G:$G,"Consumação Mínima")*50%)-(SUMIFS(BD_Eventos_Novo!$K:$K,BD_Eventos_Novo!$AB:$AB,DRE!AC$4,BD_Eventos_Novo!$G:$G,"Consumação Mínima")*50%)-(SUMIFS(BD_Eventos_Novo!$J:$J,BD_Eventos_Novo!$AB:$AB,DRE!AC$4,BD_Eventos_Novo!$G:$G,"Comanda Aberta / Couvert Antecipado")*50%)-(SUMIFS(BD_Eventos_Novo!$K:$K,BD_Eventos_Novo!$AB:$AB,DRE!AC$4,BD_Eventos_Novo!$G:$G,"Comanda Aberta / Couvert Antecipado")*50%)+SUMIFS(Aut_Ajustes_Manuais!$G:$G,Aut_Ajustes_Manuais!$I:$I,DRE!AC$4,Aut_Ajustes_Manuais!$F:$F,"Bebida") -> 0 | AG10: =SUMIFS(T_ORCAMENTOS!$E:$E,T_ORCAMENTOS!$C:$C,"Bebida",T_ORCAMENTOS!$H:$H,"9/2026") -> 1413630.9 | AH10: =SUMIFS(Aut_Faturamento_Zig!$F:$F,Aut_Faturamento_Zig!$E:$E,"Bebidas",Aut_Faturamento_Zig!$D:$D,DRE!AF$4)-SUMIFS(Aut_Promocoes_Utilizadas!$G:$G,Aut_Promocoes_Utilizadas!$J:$J,DRE!AF$4,Aut_Promocoes_Utilizadas!$H:$H,"B",Aut_Promocoes_Utilizadas!$I:$I,"Eventos")-SUMIFS(Aut_Descontos!$J:$J,Aut_Descontos!$L:$L,DRE!AF$4)-(SUMIFS(BD_Eventos_Novo!$J:$J,BD_Eventos_Novo!$AB:$AB,DRE!AF$4,BD_Eventos_Novo!$G:$G,"Consumação Mínima")*50%)-(SUMIFS(BD_Eventos_Novo!$K:$K,BD_Eventos_Novo!$AB:$AB,DRE!AF$4,BD_Eventos_Novo!$G:$G,"Consumação Mínima")*50%)-(SUMIFS(BD_Eventos_Novo!$J:$J,BD_Eventos_Novo!$AB:$AB,DRE!AF$4,BD_Eventos_Novo!$G:$G,"Comanda Aberta / Couvert Antecipado")*50%)-(SUMIFS(BD_Eventos_Novo!$K:$K,BD_Eventos_Novo!$AB:$AB,DRE!AF$4,BD_Eventos_Novo!$G:$G,"Comanda Aberta / Couvert Antecipado")*50%)+SUMIFS(Aut_Ajustes_Manuais!$G:$G,Aut_Ajustes_Manuais!$I:$I,DRE!AF$4,Aut_Ajustes_Manuais!$F:$F,"Bebida") -> 0 | AJ10: =SUMIFS(T_ORCAMENTOS!$E:$E,T_ORCAMENTOS!$C:$C,"Bebida",T_ORCAMENTOS!$H:$H,"10/2026") -> 1529344.6 | AK10: =SUMIFS(Aut_Faturamento_Zig!$F:$F,Aut_Faturamento_Zig!$E:$E,"Bebidas",Aut_Faturamento_Zig!$D:$D,DRE!AI$4)-SUMIFS(Aut_Promocoes_Utilizadas!$G:$G,Aut_Promocoes_Utilizadas!$J:$J,DRE!AI$4,Aut_Promocoes_Utilizadas!$H:$H,"B",Aut_Promocoes_Utilizadas!$I:$I,"Eventos")-SUMIFS(Aut_Descontos!$J:$J,Aut_Descontos!$L:$L,DRE!AI$4)-(SUMIFS(BD_Eventos_Novo!$J:$J,BD_Eventos_Novo!$AB:$AB,DRE!AI$4,BD_Eventos_Novo!$G:$G,"Consumação Mínima")*50%)-(SUMIFS(BD_Eventos_Novo!$K:$K,BD_Eventos_Novo!$AB:$AB,DRE!AI$4,BD_Eventos_Novo!$G:$G,"Consumação Mínima")*50%)-(SUMIFS(BD_Eventos_Novo!$J:$J,BD_Eventos_Novo!$AB:$AB,DRE!AI$4,BD_Eventos_Novo!$G:$G,"Comanda Aberta / Couvert Antecipado")*50%)-(SUMIFS(BD_Eventos_Novo!$K:$K,BD_Eventos_Novo!$AB:$AB,DRE!AI$4,BD_Eventos_Novo!$G:$G,"Comanda Aberta / Couvert Antecipado")*50%)+SUMIFS(Aut_Ajustes_Manuais!$G:$G,Aut_Ajustes_Manuais!$I:$I,DRE!AI$4,Aut_Ajustes_Manuais!$F:$F,"Bebida") -> 0 | AM10: =SUMIFS(T_ORCAMENTOS!$E:$E,T_ORCAMENTOS!$C:$C,"Bebida",T_ORCAMENTOS!$H:$H,"11/2026") -> 1395531 | AN10: =SUMIFS(Aut_Faturamento_Zig!$F:$F,Aut_Faturamento_Zig!$E:$E,"Bebidas",Aut_Faturamento_Zig!$D:$D,DRE!AL$4)-SUMIFS(Aut_Promocoes_Utilizadas!$G:$G,Aut_Promocoes_Utilizadas!$J:$J,DRE!AL$4,Aut_Promocoes_Utilizadas!$H:$H,"B",Aut_Promocoes_Utilizadas!$I:$I,"Eventos")-SUMIFS(Aut_Descontos!$J:$J,Aut_Descontos!$L:$L,DRE!AL$4)-(SUMIFS(BD_Eventos_Novo!$J:$J,BD_Eventos_Novo!$AB:$AB,DRE!AL$4,BD_Eventos_Novo!$G:$G,"Consumação Mínima")*50%)-(SUMIFS(BD_Eventos_Novo!$K:$K,BD_Eventos_Novo!$AB:$AB,DRE!AL$4,BD_Eventos_Novo!$G:$G,"Consumação Mínima")*50%)-(SUMIFS(BD_Eventos_Novo!$J:$J,BD_Eventos_Novo!$AB:$AB,DRE!AL$4,BD_Eventos_Novo!$G:$G,"Comanda Aberta / Couvert Antecipado")*50%)-(SUMIFS(BD_Eventos_Novo!$K:$K,BD_Eventos_Novo!$AB:$AB,DRE!AL$4,BD_Eventos_Novo!$G:$G,"Comanda Aberta / Couvert Antecipado")*50%)+SUMIFS(Aut_Ajustes_Manuais!$G:$G,Aut_Ajustes_Manuais!$I:$I,DRE!AL$4,Aut_Ajustes_Manuais!$F:$F,"Bebida") -> 0 | AP10: =SUMIFS(T_ORCAMENTOS!$E:$E,T_ORCAMENTOS!$C:$C,"Bebida",T_ORCAMENTOS!$H:$H,"12/2026") -> 1393995 | AQ10: =SUMIFS(Aut_Faturamento_Zig!$F:$F,Aut_Faturamento_Zig!$E:$E,"Bebidas",Aut_Faturamento_Zig!$D:$D,DRE!AO$4)-SUMIFS(Aut_Promocoes_Utilizadas!$G:$G,Aut_Promocoes_Utilizadas!$J:$J,DRE!AO$4,Aut_Promocoes_Utilizadas!$H:$H,"B",Aut_Promocoes_Utilizadas!$I:$I,"Eventos")-SUMIFS(Aut_Descontos!$J:$J,Aut_Descontos!$L:$L,DRE!AO$4)-(SUMIFS(BD_Eventos_Novo!$J:$J,BD_Eventos_Novo!$AB:$AB,DRE!AO$4,BD_Eventos_Novo!$G:$G,"Consumação Mínima")*50%)-(SUMIFS(BD_Eventos_Novo!$K:$K,BD_Eventos_Novo!$AB:$AB,DRE!AO$4,BD_Eventos_Novo!$G:$G,"Consumação Mínima")*50%)-(SUMIFS(BD_Eventos_Novo!$J:$J,BD_Eventos_Novo!$AB:$AB,DRE!AO$4,BD_Eventos_Novo!$G:$G,"Comanda Aberta / Couvert Antecipado")*50%)-(SUMIFS(BD_Eventos_Novo!$K:$K,BD_Eventos_Novo!$AB:$AB,DRE!AO$4,BD_Eventos_Novo!$G:$G,"Comanda Aberta / Couvert Antecipado")*50%)+SUMIFS(Aut_Ajustes_Manuais!$G:$G,Aut_Ajustes_Manuais!$I:$I,DRE!AO$4,Aut_Ajustes_Manuais!$F:$F,"Bebida") -> 0 | AR10: =SUMIFS($H10:$AO10,$H$5:$AO$5,"<"&MONTH(TODAY()),$H$6:$AO$6,"REAL 25") -> 0 | AS10: =SUMIFS($I10:$AP10,$I$5:$AP$5,"<"&MONTH(TODAY()),$I$6:$AP$6,"ORÇADO ") -> 1483067.9 | AT10: =SUMIFS($J10:$AQ10,$J$5:$AQ$5,"<"&MONTH(TODAY()),$J$6:$AQ$6,"REAL 26") -> 137627.7 | AU10: =SUM(H10,K10,N10,Q10,T10,W10,Z10,AC10,AF10,AI10,AL10,AO10) -> 0 | AV10: =SUM(I10,L10,O10,R10,U10,X10,AA10,AD10,AG10,AJ10,AM10,AP10) -> 7215569.3 | AW10: =SUM(J10,M10,P10,S10,V10,Y10,AB10,AE10,AH10,AK10,AN10,AQ10) -> 137627.7 | AX10: =SUM(H10,K10,N10) -> 0 | AY10: =SUM(I10,L10,O10) -> 0 | AZ10: =SUM(J10,M10,P10) -> 0 | BA10: =SUM(Q10,T10,W10) -> 0 | BB10: =SUM(R10,U10,X10) -> 0 | BC10: =SUM(S10,V10,Y10) -> 0 | BD10: =SUM(Z10,AC10,AF10) -> 0 | BE10: =SUM(AA10,AD10,AG10) -> 2896698.8 | BF10: =SUM(AB10,AE10,AH10) -> 137627.7 | BG10: =SUM(AI10,AL10,AO10) -> 0 | BH10: =SUM(AJ10,AM10,AP10) -> 4318870.5 | BI10: =SUM(AK10,AN10,AQ10) -> 0
A11: Artístico (couvert/shows) | C11: Estim. Mensal | D11: Preencher base de Faturamento A&B&C | I11: =SUMIFS(T_ORCAMENTOS!$E:$E,T_ORCAMENTOS!$C:$C,"Artístico (couvert/shows)",T_ORCAMENTOS!$H:$H,"1/2026") -> 0 | J11: =SUMIFS(Aut_Faturamento_Zig!$F:$F,Aut_Faturamento_Zig!$E:$E,"Couvert",Aut_Faturamento_Zig!$D:$D,DRE!H$4)+SUMIFS(Aut_Ajustes_Manuais!$G:$G,Aut_Ajustes_Manuais!$I:$I,DRE!H$4,Aut_Ajustes_Manuais!$F:$F,"Artístico (couvert/shows)") -> 0 | L11: =SUMIFS(T_ORCAMENTOS!$E:$E,T_ORCAMENTOS!$C:$C,"Artístico (couvert/shows)",T_ORCAMENTOS!$H:$H,"2/2026") -> 0 | M11: =SUMIFS(Aut_Faturamento_Zig!$F:$F,Aut_Faturamento_Zig!$E:$E,"Couvert",Aut_Faturamento_Zig!$D:$D,DRE!K$4)+SUMIFS(Aut_Ajustes_Manuais!$G:$G,Aut_Ajustes_Manuais!$I:$I,DRE!K$4,Aut_Ajustes_Manuais!$F:$F,"Artístico (couvert/shows)") -> 0 | O11: =SUMIFS(T_ORCAMENTOS!$E:$E,T_ORCAMENTOS!$C:$C,"Artístico (couvert/shows)",T_ORCAMENTOS!$H:$H,"3/2026") -> 0 | P11: =SUMIFS(Aut_Faturamento_Zig!$F:$F,Aut_Faturamento_Zig!$E:$E,"Couvert",Aut_Faturamento_Zig!$D:$D,DRE!N$4)+SUMIFS(Aut_Ajustes_Manuais!$G:$G,Aut_Ajustes_Manuais!$I:$I,DRE!N$4,Aut_Ajustes_Manuais!$F:$F,"Artístico (couvert/shows)") -> 0 | R11: =SUMIFS(T_ORCAMENTOS!$E:$E,T_ORCAMENTOS!$C:$C,"Artístico (couvert/shows)",T_ORCAMENTOS!$H:$H,"4/2026") -> 0 | S11: =SUMIFS(Aut_Faturamento_Zig!$F:$F,Aut_Faturamento_Zig!$E:$E,"Couvert",Aut_Faturamento_Zig!$D:$D,DRE!Q$4)+SUMIFS(Aut_Ajustes_Manuais!$G:$G,Aut_Ajustes_Manuais!$I:$I,DRE!Q$4,Aut_Ajustes_Manuais!$F:$F,"Artístico (couvert/shows)") -> 0 | U11: =SUMIFS(T_ORCAMENTOS!$E:$E,T_ORCAMENTOS!$C:$C,"Artístico (couvert/shows)",T_ORCAMENTOS!$H:$H,"5/2026") -> 0 | V11: =SUMIFS(Aut_Faturamento_Zig!$F:$F,Aut_Faturamento_Zig!$E:$E,"Couvert",Aut_Faturamento_Zig!$D:$D,DRE!T$4)+SUMIFS(Aut_Ajustes_Manuais!$G:$G,Aut_Ajustes_Manuais!$I:$I,DRE!T$4,Aut_Ajustes_Manuais!$F:$F,"Artístico (couvert/shows)") -> 0 | X11: =SUMIFS(T_ORCAMENTOS!$E:$E,T_ORCAMENTOS!$C:$C,"Artístico (couvert/shows)",T_ORCAMENTOS!$H:$H,"6/2026") -> 0 | Y11: =SUMIFS(Aut_Faturamento_Zig!$F:$F,Aut_Faturamento_Zig!$E:$E,"Couvert",Aut_Faturamento_Zig!$D:$D,DRE!W$4)+SUMIFS(Aut_Ajustes_Manuais!$G:$G,Aut_Ajustes_Manuais!$I:$I,DRE!W$4,Aut_Ajustes_Manuais!$F:$F,"Artístico (couvert/shows)") -> 0 | AA11: =SUMIFS(T_ORCAMENTOS!$E:$E,T_ORCAMENTOS!$C:$C,"Artístico (couvert/shows)",T_ORCAMENTOS!$H:$H,"7/2026") -> 0 | AB11: =SUMIFS(Aut_Faturamento_Zig!$F:$F,Aut_Faturamento_Zig!$E:$E,"Couvert",Aut_Faturamento_Zig!$D:$D,DRE!Z$4)+SUMIFS(Aut_Ajustes_Manuais!$G:$G,Aut_Ajustes_Manuais!$I:$I,DRE!Z$4,Aut_Ajustes_Manuais!$F:$F,"Artístico (couvert/shows)") -> 12520 | AD11: =SUMIFS(T_ORCAMENTOS!$E:$E,T_ORCAMENTOS!$C:$C,"Artístico (couvert/shows)",T_ORCAMENTOS!$H:$H,"8/2026") -> 862555.9 | AE11: =SUMIFS(Aut_Faturamento_Zig!$F:$F,Aut_Faturamento_Zig!$E:$E,"Couvert",Aut_Faturamento_Zig!$D:$D,DRE!AC$4)+SUMIFS(Aut_Ajustes_Manuais!$G:$G,Aut_Ajustes_Manuais!$I:$I,DRE!AC$4,Aut_Ajustes_Manuais!$F:$F,"Artístico (couvert/shows)") -> 0 | AG11: =SUMIFS(T_ORCAMENTOS!$E:$E,T_ORCAMENTOS!$C:$C,"Artístico (couvert/shows)",T_ORCAMENTOS!$H:$H,"9/2026") -> 817648.72 | AH11: =SUMIFS(Aut_Faturamento_Zig!$F:$F,Aut_Faturamento_Zig!$E:$E,"Couvert",Aut_Faturamento_Zig!$D:$D,DRE!AF$4)+SUMIFS(Aut_Ajustes_Manuais!$G:$G,Aut_Ajustes_Manuais!$I:$I,DRE!AF$4,Aut_Ajustes_Manuais!$F:$F,"Artístico (couvert/shows)") -> 0 | AJ11: =SUMIFS(T_ORCAMENTOS!$E:$E,T_ORCAMENTOS!$C:$C,"Artístico (couvert/shows)",T_ORCAMENTOS!$H:$H,"10/2026") -> 896493.38 | AK11: =SUMIFS(Aut_Faturamento_Zig!$F:$F,Aut_Faturamento_Zig!$E:$E,"Couvert",Aut_Faturamento_Zig!$D:$D,DRE!AI$4)+SUMIFS(Aut_Ajustes_Manuais!$G:$G,Aut_Ajustes_Manuais!$I:$I,DRE!AI$4,Aut_Ajustes_Manuais!$F:$F,"Artístico (couvert/shows)") -> 0 | AM11: =SUMIFS(T_ORCAMENTOS!$E:$E,T_ORCAMENTOS!$C:$C,"Artístico (couvert/shows)",T_ORCAMENTOS!$H:$H,"11/2026") -> 810889.24 | AN11: =SUMIFS(Aut_Faturamento_Zig!$F:$F,Aut_Faturamento_Zig!$E:$E,"Couvert",Aut_Faturamento_Zig!$D:$D,DRE!AL$4)+SUMIFS(Aut_Ajustes_Manuais!$G:$G,Aut_Ajustes_Manuais!$I:$I,DRE!AL$4,Aut_Ajustes_Manuais!$F:$F,"Artístico (couvert/shows)") -> 0 | AP11: =SUMIFS(T_ORCAMENTOS!$E:$E,T_ORCAMENTOS!$C:$C,"Artístico (couvert/shows)",T_ORCAMENTOS!$H:$H,"12/2026") -> 797122.72 | AQ11: =SUMIFS(Aut_Faturamento_Zig!$F:$F,Aut_Faturamento_Zig!$E:$E,"Couvert",Aut_Faturamento_Zig!$D:$D,DRE!AO$4)+SUMIFS(Aut_Ajustes_Manuais!$G:$G,Aut_Ajustes_Manuais!$I:$I,DRE!AO$4,Aut_Ajustes_Manuais!$F:$F,"Artístico (couvert/shows)") -> 0 | AR11: =SUMIFS($H11:$AO11,$H$5:$AO$5,"<"&MONTH(TODAY()),$H$6:$AO$6,"REAL 25") -> 0 | AS11: =SUMIFS($I11:$AP11,$I$5:$AP$5,"<"&MONTH(TODAY()),$I$6:$AP$6,"ORÇADO ") -> 862555.9 | AT11: =SUMIFS($J11:$AQ11,$J$5:$AQ$5,"<"&MONTH(TODAY()),$J$6:$AQ$6,"REAL 26") -> 12520 | AU11: =SUM(H11,K11,N11,Q11,T11,W11,Z11,AC11,AF11,AI11,AL11,AO11) -> 0 | AV11: =SUM(I11,L11,O11,R11,U11,X11,AA11,AD11,AG11,AJ11,AM11,AP11) -> 4184710 | AW11: =SUM(J11,M11,P11,S11,V11,Y11,AB11,AE11,AH11,AK11,AN11,AQ11) -> 12520 | AX11: =SUM(H11,K11,N11) -> 0 | AY11: =SUM(I11,L11,O11) -> 0 | AZ11: =SUM(J11,M11,P11) -> 0 | BA11: =SUM(Q11,T11,W11) -> 0 | BB11: =SUM(R11,U11,X11) -> 0 | BC11: =SUM(S11,V11,Y11) -> 0 | BD11: =SUM(Z11,AC11,AF11) -> 0 | BE11: =SUM(AA11,AD11,AG11) -> 1680204.6 | BF11: =SUM(AB11,AE11,AH11) -> 12520 | BG11: =SUM(AI11,AL11,AO11) -> 0 | BH11: =SUM(AJ11,AM11,AP11) -> 2504505.3 | BI11: =SUM(AK11,AN11,AQ11) -> 0
A12: Gifts | C12: Estim. Mensal | D12: Vendas Lojinha | I12: =SUMIFS(T_ORCAMENTOS!$E:$E,T_ORCAMENTOS!$C:$C,"Gifts",T_ORCAMENTOS!$H:$H,"1/2026") -> 0 | J12: =SUMIFS(Aut_Faturamento_Zig!$F:$F,Aut_Faturamento_Zig!$E:$E,"Gifts",Aut_Faturamento_Zig!$D:$D,DRE!H$4)+SUMIFS(Aut_Ajustes_Manuais!$G:$G,Aut_Ajustes_Manuais!$I:$I,DRE!H$4,Aut_Ajustes_Manuais!$F:$F,"Gifts") -> 0 | L12: =SUMIFS(T_ORCAMENTOS!$E:$E,T_ORCAMENTOS!$C:$C,"Gifts",T_ORCAMENTOS!$H:$H,"2/2026") -> 0 | M12: =SUMIFS(Aut_Faturamento_Zig!$F:$F,Aut_Faturamento_Zig!$E:$E,"Gifts",Aut_Faturamento_Zig!$D:$D,DRE!K$4)+SUMIFS(Aut_Ajustes_Manuais!$G:$G,Aut_Ajustes_Manuais!$I:$I,DRE!K$4,Aut_Ajustes_Manuais!$F:$F,"Gifts") -> 0 | O12: =SUMIFS(T_ORCAMENTOS!$E:$E,T_ORCAMENTOS!$C:$C,"Gifts",T_ORCAMENTOS!$H:$H,"3/2026") -> 0 | P12: =SUMIFS(Aut_Faturamento_Zig!$F:$F,Aut_Faturamento_Zig!$E:$E,"Gifts",Aut_Faturamento_Zig!$D:$D,DRE!N$4)+SUMIFS(Aut_Ajustes_Manuais!$G:$G,Aut_Ajustes_Manuais!$I:$I,DRE!N$4,Aut_Ajustes_Manuais!$F:$F,"Gifts") -> 0 | R12: =SUMIFS(T_ORCAMENTOS!$E:$E,T_ORCAMENTOS!$C:$C,"Gifts",T_ORCAMENTOS!$H:$H,"4/2026") -> 0 | S12: =SUMIFS(Aut_Faturamento_Zig!$F:$F,Aut_Faturamento_Zig!$E:$E,"Gifts",Aut_Faturamento_Zig!$D:$D,DRE!Q$4)+SUMIFS(Aut_Ajustes_Manuais!$G:$G,Aut_Ajustes_Manuais!$I:$I,DRE!Q$4,Aut_Ajustes_Manuais!$F:$F,"Gifts") -> 0 | U12: =SUMIFS(T_ORCAMENTOS!$E:$E,T_ORCAMENTOS!$C:$C,"Gifts",T_ORCAMENTOS!$H:$H,"5/2026") -> 0 | V12: =SUMIFS(Aut_Faturamento_Zig!$F:$F,Aut_Faturamento_Zig!$E:$E,"Gifts",Aut_Faturamento_Zig!$D:$D,DRE!T$4)+SUMIFS(Aut_Ajustes_Manuais!$G:$G,Aut_Ajustes_Manuais!$I:$I,DRE!T$4,Aut_Ajustes_Manuais!$F:$F,"Gifts") -> 0 | X12: =SUMIFS(T_ORCAMENTOS!$E:$E,T_ORCAMENTOS!$C:$C,"Gifts",T_ORCAMENTOS!$H:$H,"6/2026") -> 0 | Y12: =SUMIFS(Aut_Faturamento_Zig!$F:$F,Aut_Faturamento_Zig!$E:$E,"Gifts",Aut_Faturamento_Zig!$D:$D,DRE!W$4)+SUMIFS(Aut_Ajustes_Manuais!$G:$G,Aut_Ajustes_Manuais!$I:$I,DRE!W$4,Aut_Ajustes_Manuais!$F:$F,"Gifts") -> 0 | AA12: =SUMIFS(T_ORCAMENTOS!$E:$E,T_ORCAMENTOS!$C:$C,"Gifts",T_ORCAMENTOS!$H:$H,"7/2026") -> 0 | AB12: =SUMIFS(Aut_Faturamento_Zig!$F:$F,Aut_Faturamento_Zig!$E:$E,"Gifts",Aut_Faturamento_Zig!$D:$D,DRE!Z$4)+SUMIFS(Aut_Ajustes_Manuais!$G:$G,Aut_Ajustes_Manuais!$I:$I,DRE!Z$4,Aut_Ajustes_Manuais!$F:$F,"Gifts") -> 0 | AD12: =SUMIFS(T_ORCAMENTOS!$E:$E,T_ORCAMENTOS!$C:$C,"Gifts",T_ORCAMENTOS!$H:$H,"8/2026") -> 20000 | AE12: =SUMIFS(Aut_Faturamento_Zig!$F:$F,Aut_Faturamento_Zig!$E:$E,"Gifts",Aut_Faturamento_Zig!$D:$D,DRE!AC$4)+SUMIFS(Aut_Ajustes_Manuais!$G:$G,Aut_Ajustes_Manuais!$I:$I,DRE!AC$4,Aut_Ajustes_Manuais!$F:$F,"Gifts") -> 0 | AG12: =SUMIFS(T_ORCAMENTOS!$E:$E,T_ORCAMENTOS!$C:$C,"Gifts",T_ORCAMENTOS!$H:$H,"9/2026") -> 20000 | AH12: =SUMIFS(Aut_Faturamento_Zig!$F:$F,Aut_Faturamento_Zig!$E:$E,"Gifts",Aut_Faturamento_Zig!$D:$D,DRE!AF$4)+SUMIFS(Aut_Ajustes_Manuais!$G:$G,Aut_Ajustes_Manuais!$I:$I,DRE!AF$4,Aut_Ajustes_Manuais!$F:$F,"Gifts") -> 0 | AJ12: =SUMIFS(T_ORCAMENTOS!$E:$E,T_ORCAMENTOS!$C:$C,"Gifts",T_ORCAMENTOS!$H:$H,"10/2026") -> 20000 | AK12: =SUMIFS(Aut_Faturamento_Zig!$F:$F,Aut_Faturamento_Zig!$E:$E,"Gifts",Aut_Faturamento_Zig!$D:$D,DRE!AI$4)+SUMIFS(Aut_Ajustes_Manuais!$G:$G,Aut_Ajustes_Manuais!$I:$I,DRE!AI$4,Aut_Ajustes_Manuais!$F:$F,"Gifts") -> 0 | AM12: =SUMIFS(T_ORCAMENTOS!$E:$E,T_ORCAMENTOS!$C:$C,"Gifts",T_ORCAMENTOS!$H:$H,"11/2026") -> 20000 | AN12: =SUMIFS(Aut_Faturamento_Zig!$F:$F,Aut_Faturamento_Zig!$E:$E,"Gifts",Aut_Faturamento_Zig!$D:$D,DRE!AL$4)+SUMIFS(Aut_Ajustes_Manuais!$G:$G,Aut_Ajustes_Manuais!$I:$I,DRE!AL$4,Aut_Ajustes_Manuais!$F:$F,"Gifts") -> 0 | AP12: =SUMIFS(T_ORCAMENTOS!$E:$E,T_ORCAMENTOS!$C:$C,"Gifts",T_ORCAMENTOS!$H:$H,"12/2026") -> 20000 | AQ12: =SUMIFS(Aut_Faturamento_Zig!$F:$F,Aut_Faturamento_Zig!$E:$E,"Gifts",Aut_Faturamento_Zig!$D:$D,DRE!AO$4)+SUMIFS(Aut_Ajustes_Manuais!$G:$G,Aut_Ajustes_Manuais!$I:$I,DRE!AO$4,Aut_Ajustes_Manuais!$F:$F,"Gifts") -> 0 | AR12: =SUMIFS($H12:$AO12,$H$5:$AO$5,"<"&MONTH(TODAY()),$H$6:$AO$6,"REAL 25") -> 0 | AS12: =SUMIFS($I12:$AP12,$I$5:$AP$5,"<"&MONTH(TODAY()),$I$6:$AP$6,"ORÇADO ") -> 20000 | AT12: =SUMIFS($J12:$AQ12,$J$5:$AQ$5,"<"&MONTH(TODAY()),$J$6:$AQ$6,"REAL 26") -> 0 | AU12: =SUM(H12,K12,N12,Q12,T12,W12,Z12,AC12,AF12,AI12,AL12,AO12) -> 0 | AV12: =SUM(I12,L12,O12,R12,U12,X12,AA12,AD12,AG12,AJ12,AM12,AP12) -> 100000 | AW12: =SUM(J12,M12,P12,S12,V12,Y12,AB12,AE12,AH12,AK12,AN12,AQ12) -> 0 | AX12: =SUM(H12,K12,N12) -> 0 | AY12: =SUM(I12,L12,O12) -> 0 | AZ12: =SUM(J12,M12,P12) -> 0 | BA12: =SUM(Q12,T12,W12) -> 0 | BB12: =SUM(R12,U12,X12) -> 0 | BC12: =SUM(S12,V12,Y12) -> 0 | BD12: =SUM(Z12,AC12,AF12) -> 0 | BE12: =SUM(AA12,AD12,AG12) -> 40000 | BF12: =SUM(AB12,AE12,AH12) -> 0 | BG12: =SUM(AI12,AL12,AO12) -> 0 | BH12: =SUM(AJ12,AM12,AP12) -> 60000 | BI12: =SUM(AK12,AN12,AQ12) -> 0
A13: Serviço | C13: Estim. Mensal | D13: Gorjeta Fórmula | E13: 13% sobre A&B&C | I13: =SUMIFS(T_ORCAMENTOS!$E:$E,T_ORCAMENTOS!$C:$C,"Serviço",T_ORCAMENTOS!$H:$H,"1/2026") -> 0 | J13: =SUMIFS(Aut_Faturamento_Zig!$F:$F,Aut_Faturamento_Zig!$E:$E,"Serviço",Aut_Faturamento_Zig!$D:$D,DRE!H$4)+SUMIFS(Aut_Ajustes_Manuais!$G:$G,Aut_Ajustes_Manuais!$I:$I,DRE!H$4,Aut_Ajustes_Manuais!$F:$F,"Serviço") -> 0 | L13: =SUMIFS(T_ORCAMENTOS!$E:$E,T_ORCAMENTOS!$C:$C,"Serviço",T_ORCAMENTOS!$H:$H,"2/2026") -> 0 | M13: =SUMIFS(Aut_Faturamento_Zig!$F:$F,Aut_Faturamento_Zig!$E:$E,"Serviço",Aut_Faturamento_Zig!$D:$D,DRE!K$4)+SUMIFS(Aut_Ajustes_Manuais!$G:$G,Aut_Ajustes_Manuais!$I:$I,DRE!K$4,Aut_Ajustes_Manuais!$F:$F,"Serviço") -> 0 | O13: =SUMIFS(T_ORCAMENTOS!$E:$E,T_ORCAMENTOS!$C:$C,"Serviço",T_ORCAMENTOS!$H:$H,"3/2026") -> 0 | P13: =SUMIFS(Aut_Faturamento_Zig!$F:$F,Aut_Faturamento_Zig!$E:$E,"Serviço",Aut_Faturamento_Zig!$D:$D,DRE!N$4)+SUMIFS(Aut_Ajustes_Manuais!$G:$G,Aut_Ajustes_Manuais!$I:$I,DRE!N$4,Aut_Ajustes_Manuais!$F:$F,"Serviço") -> 0 | R13: =SUMIFS(T_ORCAMENTOS!$E:$E,T_ORCAMENTOS!$C:$C,"Serviço",T_ORCAMENTOS!$H:$H,"4/2026") -> 0 | S13: =SUMIFS(Aut_Faturamento_Zig!$F:$F,Aut_Faturamento_Zig!$E:$E,"Serviço",Aut_Faturamento_Zig!$D:$D,DRE!Q$4)+SUMIFS(Aut_Ajustes_Manuais!$G:$G,Aut_Ajustes_Manuais!$I:$I,DRE!Q$4,Aut_Ajustes_Manuais!$F:$F,"Serviço") -> 0 | U13: =SUMIFS(T_ORCAMENTOS!$E:$E,T_ORCAMENTOS!$C:$C,"Serviço",T_ORCAMENTOS!$H:$H,"5/2026") -> 0 | V13: =SUMIFS(Aut_Faturamento_Zig!$F:$F,Aut_Faturamento_Zig!$E:$E,"Serviço",Aut_Faturamento_Zig!$D:$D,DRE!T$4)+SUMIFS(Aut_Ajustes_Manuais!$G:$G,Aut_Ajustes_Manuais!$I:$I,DRE!T$4,Aut_Ajustes_Manuais!$F:$F,"Serviço") -> 0 | X13: =SUMIFS(T_ORCAMENTOS!$E:$E,T_ORCAMENTOS!$C:$C,"Serviço",T_ORCAMENTOS!$H:$H,"6/2026") -> 0 | Y13: =SUMIFS(Aut_Faturamento_Zig!$F:$F,Aut_Faturamento_Zig!$E:$E,"Serviço",Aut_Faturamento_Zig!$D:$D,DRE!W$4)+SUMIFS(Aut_Ajustes_Manuais!$G:$G,Aut_Ajustes_Manuais!$I:$I,DRE!W$4,Aut_Ajustes_Manuais!$F:$F,"Serviço") -> 0 | AA13: =SUMIFS(T_ORCAMENTOS!$E:$E,T_ORCAMENTOS!$C:$C,"Serviço",T_ORCAMENTOS!$H:$H,"7/2026") -> 0 | AB13: =SUMIFS(Aut_Faturamento_Zig!$F:$F,Aut_Faturamento_Zig!$E:$E,"Serviço",Aut_Faturamento_Zig!$D:$D,DRE!Z$4)+SUMIFS(Aut_Ajustes_Manuais!$G:$G,Aut_Ajustes_Manuais!$I:$I,DRE!Z$4,Aut_Ajustes_Manuais!$F:$F,"Serviço") -> 29390.72 | AD13: =SUMIFS(T_ORCAMENTOS!$E:$E,T_ORCAMENTOS!$C:$C,"Serviço",T_ORCAMENTOS!$H:$H,"8/2026") -> 411963.31 | AE13: =SUMIFS(Aut_Faturamento_Zig!$F:$F,Aut_Faturamento_Zig!$E:$E,"Serviço",Aut_Faturamento_Zig!$D:$D,DRE!AC$4)+SUMIFS(Aut_Ajustes_Manuais!$G:$G,Aut_Ajustes_Manuais!$I:$I,DRE!AC$4,Aut_Ajustes_Manuais!$F:$F,"Serviço") -> 0 | AG13: =SUMIFS(T_ORCAMENTOS!$E:$E,T_ORCAMENTOS!$C:$C,"Serviço",T_ORCAMENTOS!$H:$H,"9/2026") -> 392675.24 | AH13: =SUMIFS(Aut_Faturamento_Zig!$F:$F,Aut_Faturamento_Zig!$E:$E,"Serviço",Aut_Faturamento_Zig!$D:$D,DRE!AF$4)+SUMIFS(Aut_Ajustes_Manuais!$G:$G,Aut_Ajustes_Manuais!$I:$I,DRE!AF$4,Aut_Ajustes_Manuais!$F:$F,"Serviço") -> 0 | AJ13: =SUMIFS(T_ORCAMENTOS!$E:$E,T_ORCAMENTOS!$C:$C,"Serviço",T_ORCAMENTOS!$H:$H,"10/2026") -> 424817.93 | AK13: =SUMIFS(Aut_Faturamento_Zig!$F:$F,Aut_Faturamento_Zig!$E:$E,"Serviço",Aut_Faturamento_Zig!$D:$D,DRE!AI$4)+SUMIFS(Aut_Ajustes_Manuais!$G:$G,Aut_Ajustes_Manuais!$I:$I,DRE!AI$4,Aut_Ajustes_Manuais!$F:$F,"Serviço") -> 0 | AM13: =SUMIFS(T_ORCAMENTOS!$E:$E,T_ORCAMENTOS!$C:$C,"Serviço",T_ORCAMENTOS!$H:$H,"11/2026") -> 387647.49 | AN13: =SUMIFS(Aut_Faturamento_Zig!$F:$F,Aut_Faturamento_Zig!$E:$E,"Serviço",Aut_Faturamento_Zig!$D:$D,DRE!AL$4)+SUMIFS(Aut_Ajustes_Manuais!$G:$G,Aut_Ajustes_Manuais!$I:$I,DRE!AL$4,Aut_Ajustes_Manuais!$F:$F,"Serviço") -> 0 | AP13: =SUMIFS(T_ORCAMENTOS!$E:$E,T_ORCAMENTOS!$C:$C,"Serviço",T_ORCAMENTOS!$H:$H,"12/2026") -> 387220.84 | AQ13: =SUMIFS(Aut_Faturamento_Zig!$F:$F,Aut_Faturamento_Zig!$E:$E,"Serviço",Aut_Faturamento_Zig!$D:$D,DRE!AO$4)+SUMIFS(Aut_Ajustes_Manuais!$G:$G,Aut_Ajustes_Manuais!$I:$I,DRE!AO$4,Aut_Ajustes_Manuais!$F:$F,"Serviço") -> 0 | AR13: =SUMIFS($H13:$AO13,$H$5:$AO$5,"<"&MONTH(TODAY()),$H$6:$AO$6,"REAL 25") -> 0 | AS13: =SUMIFS($I13:$AP13,$I$5:$AP$5,"<"&MONTH(TODAY()),$I$6:$AP$6,"ORÇADO ") -> 411963.31 | AT13: =SUMIFS($J13:$AQ13,$J$5:$AQ$5,"<"&MONTH(TODAY()),$J$6:$AQ$6,"REAL 26") -> 29390.72 | AU13: =SUM(H13,K13,N13,Q13,T13,W13,Z13,AC13,AF13,AI13,AL13,AO13) -> 0 | AV13: =SUM(I13,L13,O13,R13,U13,X13,AA13,AD13,AG13,AJ13,AM13,AP13) -> 2004324.8 | AW13: =SUM(J13,M13,P13,S13,V13,Y13,AB13,AE13,AH13,AK13,AN13,AQ13) -> 29390.72 | AX13: =SUM(H13,K13,N13) -> 0 | AY13: =SUM(I13,L13,O13) -> 0 | AZ13: =SUM(J13,M13,P13) -> 0 | BA13: =SUM(Q13,T13,W13) -> 0 | BB13: =SUM(R13,U13,X13) -> 0 | BC13: =SUM(S13,V13,Y13) -> 0 | BD13: =SUM(Z13,AC13,AF13) -> 0 | BE13: =SUM(AA13,AD13,AG13) -> 804638.55 | BF13: =SUM(AB13,AE13,AH13) -> 29390.72 | BG13: =SUM(AI13,AL13,AO13) -> 0 | BH13: =SUM(AJ13,AM13,AP13) -> 1199686.3 | BI13: =SUM(AK13,AN13,AQ13) -> 0
A14: Eventos A&B | C14: Estim. Mensal | D14: Preencher base de Eventos | I14: =SUMIFS(T_ORCAMENTOS!$E:$E,T_ORCAMENTOS!$C:$C,"Eventos A&B",T_ORCAMENTOS!$H:$H,"1/2026") -> 0 | J14: =SUMIFS(BD_Eventos_Novo!$J:$J,BD_Eventos_Novo!$AB:$AB,DRE!H$4)+SUMIFS(BD_Eventos_Novo!$K:$K,BD_Eventos_Novo!$AB:$AB,DRE!H$4)+SUMIFS(Aut_Ajustes_Manuais!$G:$G,Aut_Ajustes_Manuais!$I:$I,DRE!H$4,Aut_Ajustes_Manuais!$F:$F,"Eventos A&B") -> 0 | L14: =SUMIFS(T_ORCAMENTOS!$E:$E,T_ORCAMENTOS!$C:$C,"Eventos A&B",T_ORCAMENTOS!$H:$H,"2/2026") -> 0 | M14: =SUMIFS(BD_Eventos_Novo!$J:$J,BD_Eventos_Novo!$AB:$AB,DRE!K$4)+SUMIFS(BD_Eventos_Novo!$K:$K,BD_Eventos_Novo!$AB:$AB,DRE!K$4)+SUMIFS(Aut_Ajustes_Manuais!$G:$G,Aut_Ajustes_Manuais!$I:$I,DRE!K$4,Aut_Ajustes_Manuais!$F:$F,"Eventos A&B") -> 0 | O14: =SUMIFS(T_ORCAMENTOS!$E:$E,T_ORCAMENTOS!$C:$C,"Eventos A&B",T_ORCAMENTOS!$H:$H,"3/2026") -> 0 | P14: =SUMIFS(BD_Eventos_Novo!$J:$J,BD_Eventos_Novo!$AB:$AB,DRE!N$4)+SUMIFS(BD_Eventos_Novo!$K:$K,BD_Eventos_Novo!$AB:$AB,DRE!N$4)+SUMIFS(Aut_Ajustes_Manuais!$G:$G,Aut_Ajustes_Manuais!$I:$I,DRE!N$4,Aut_Ajustes_Manuais!$F:$F,"Eventos A&B") -> 0 | R14: =SUMIFS(T_ORCAMENTOS!$E:$E,T_ORCAMENTOS!$C:$C,"Eventos A&B",T_ORCAMENTOS!$H:$H,"4/2026") -> 0 | S14: =SUMIFS(BD_Eventos_Novo!$J:$J,BD_Eventos_Novo!$AB:$AB,DRE!Q$4)+SUMIFS(BD_Eventos_Novo!$K:$K,BD_Eventos_Novo!$AB:$AB,DRE!Q$4)+SUMIFS(Aut_Ajustes_Manuais!$G:$G,Aut_Ajustes_Manuais!$I:$I,DRE!Q$4,Aut_Ajustes_Manuais!$F:$F,"Eventos A&B") -> 0 | U14: =SUMIFS(T_ORCAMENTOS!$E:$E,T_ORCAMENTOS!$C:$C,"Eventos A&B",T_ORCAMENTOS!$H:$H,"5/2026") -> 0 | V14: =SUMIFS(BD_Eventos_Novo!$J:$J,BD_Eventos_Novo!$AB:$AB,DRE!T$4)+SUMIFS(BD_Eventos_Novo!$K:$K,BD_Eventos_Novo!$AB:$AB,DRE!T$4)+SUMIFS(Aut_Ajustes_Manuais!$G:$G,Aut_Ajustes_Manuais!$I:$I,DRE!T$4,Aut_Ajustes_Manuais!$F:$F,"Eventos A&B") -> 0 | X14: =SUMIFS(T_ORCAMENTOS!$E:$E,T_ORCAMENTOS!$C:$C,"Eventos A&B",T_ORCAMENTOS!$H:$H,"6/2026") -> 0 | Y14: =SUMIFS(BD_Eventos_Novo!$J:$J,BD_Eventos_Novo!$AB:$AB,DRE!W$4)+SUMIFS(BD_Eventos_Novo!$K:$K,BD_Eventos_Novo!$AB:$AB,DRE!W$4)+SUMIFS(Aut_Ajustes_Manuais!$G:$G,Aut_Ajustes_Manuais!$I:$I,DRE!W$4,Aut_Ajustes_Manuais!$F:$F,"Eventos A&B") -> 0 | AA14: =SUMIFS(T_ORCAMENTOS!$E:$E,T_ORCAMENTOS!$C:$C,"Eventos A&B",T_ORCAMENTOS!$H:$H,"7/2026") -> 0 | AB14: =SUMIFS(BD_Eventos_Novo!$J:$J,BD_Eventos_Novo!$AB:$AB,DRE!Z$4)+SUMIFS(BD_Eventos_Novo!$K:$K,BD_Eventos_Novo!$AB:$AB,DRE!Z$4)+SUMIFS(Aut_Ajustes_Manuais!$G:$G,Aut_Ajustes_Manuais!$I:$I,DRE!Z$4,Aut_Ajustes_Manuais!$F:$F,"Eventos A&B") -> 26850 | AD14: =SUMIFS(T_ORCAMENTOS!$E:$E,T_ORCAMENTOS!$C:$C,"Eventos A&B",T_ORCAMENTOS!$H:$H,"8/2026") -> 48750 | AE14: =SUMIFS(BD_Eventos_Novo!$J:$J,BD_Eventos_Novo!$AB:$AB,DRE!AC$4)+SUMIFS(BD_Eventos_Novo!$K:$K,BD_Eventos_Novo!$AB:$AB,DRE!AC$4)+SUMIFS(Aut_Ajustes_Manuais!$G:$G,Aut_Ajustes_Manuais!$I:$I,DRE!AC$4,Aut_Ajustes_Manuais!$F:$F,"Eventos A&B") -> 0 | AG14: =SUMIFS(T_ORCAMENTOS!$E:$E,T_ORCAMENTOS!$C:$C,"Eventos A&B",T_ORCAMENTOS!$H:$H,"9/2026") -> 97500 | AH14: =SUMIFS(BD_Eventos_Novo!$J:$J,BD_Eventos_Novo!$AB:$AB,DRE!AF$4)+SUMIFS(BD_Eventos_Novo!$K:$K,BD_Eventos_Novo!$AB:$AB,DRE!AF$4)+SUMIFS(Aut_Ajustes_Manuais!$G:$G,Aut_Ajustes_Manuais!$I:$I,DRE!AF$4,Aut_Ajustes_Manuais!$F:$F,"Eventos A&B") -> 0 | AJ14: =SUMIFS(T_ORCAMENTOS!$E:$E,T_ORCAMENTOS!$C:$C,"Eventos A&B",T_ORCAMENTOS!$H:$H,"10/2026") -> 146250 | AK14: =SUMIFS(BD_Eventos_Novo!$J:$J,BD_Eventos_Novo!$AB:$AB,DRE!AI$4)+SUMIFS(BD_Eventos_Novo!$K:$K,BD_Eventos_Novo!$AB:$AB,DRE!AI$4)+SUMIFS(Aut_Ajustes_Manuais!$G:$G,Aut_Ajustes_Manuais!$I:$I,DRE!AI$4,Aut_Ajustes_Manuais!$F:$F,"Eventos A&B") -> 0 | AM14: =SUMIFS(T_ORCAMENTOS!$E:$E,T_ORCAMENTOS!$C:$C,"Eventos A&B",T_ORCAMENTOS!$H:$H,"11/2026") -> 165750 | AN14: =SUMIFS(BD_Eventos_Novo!$J:$J,BD_Eventos_Novo!$AB:$AB,DRE!AL$4)+SUMIFS(BD_Eventos_Novo!$K:$K,BD_Eventos_Novo!$AB:$AB,DRE!AL$4)+SUMIFS(Aut_Ajustes_Manuais!$G:$G,Aut_Ajustes_Manuais!$I:$I,DRE!AL$4,Aut_Ajustes_Manuais!$F:$F,"Eventos A&B") -> 0 | AP14: =SUMIFS(T_ORCAMENTOS!$E:$E,T_ORCAMENTOS!$C:$C,"Eventos A&B",T_ORCAMENTOS!$H:$H,"12/2026") -> 450125 | AQ14: =SUMIFS(BD_Eventos_Novo!$J:$J,BD_Eventos_Novo!$AB:$AB,DRE!AO$4)+SUMIFS(BD_Eventos_Novo!$K:$K,BD_Eventos_Novo!$AB:$AB,DRE!AO$4)+SUMIFS(Aut_Ajustes_Manuais!$G:$G,Aut_Ajustes_Manuais!$I:$I,DRE!AO$4,Aut_Ajustes_Manuais!$F:$F,"Eventos A&B") -> 0 | AR14: =SUMIFS($H14:$AO14,$H$5:$AO$5,"<"&MONTH(TODAY()),$H$6:$AO$6,"REAL 25") -> 0 | AS14: =SUMIFS($I14:$AP14,$I$5:$AP$5,"<"&MONTH(TODAY()),$I$6:$AP$6,"ORÇADO ") -> 48750 | AT14: =SUMIFS($J14:$AQ14,$J$5:$AQ$5,"<"&MONTH(TODAY()),$J$6:$AQ$6,"REAL 26") -> 26850 | AU14: =SUM(H14,K14,N14,Q14,T14,W14,Z14,AC14,AF14,AI14,AL14,AO14) -> 0 | AV14: =SUM(I14,L14,O14,R14,U14,X14,AA14,AD14,AG14,AJ14,AM14,AP14) -> 908375 | AW14: =SUM(J14,M14,P14,S14,V14,Y14,AB14,AE14,AH14,AK14,AN14,AQ14) -> 26850 | AX14: =SUM(H14,K14,N14) -> 0 | AY14: =SUM(I14,L14,O14) -> 0 | AZ14: =SUM(J14,M14,P14) -> 0 | BA14: =SUM(Q14,T14,W14) -> 0 | BB14: =SUM(R14,U14,X14) -> 0 | BC14: =SUM(S14,V14,Y14) -> 0 | BD14: =SUM(Z14,AC14,AF14) -> 0 | BE14: =SUM(AA14,AD14,AG14) -> 146250 | BF14: =SUM(AB14,AE14,AH14) -> 26850 | BG14: =SUM(AI14,AL14,AO14) -> 0 | BH14: =SUM(AJ14,AM14,AP14) -> 762125 | BI14: =SUM(AK14,AN14,AQ14) -> 0
A15: Eventos Couvert | C15: Estim. Mensal | D15: Preencher base de Eventos | I15: =SUMIFS(T_ORCAMENTOS!$E:$E,T_ORCAMENTOS!$C:$C,"Eventos Couvert",T_ORCAMENTOS!$H:$H,"1/2026") -> 0 | J15: =SUMIFS(BD_Eventos_Novo!$M:$M,BD_Eventos_Novo!$AB:$AB,DRE!H$4)+SUMIFS(BD_Eventos_Novo!$N:$N,BD_Eventos_Novo!$AB:$AB,DRE!H$4)+SUMIFS(BD_Eventos_Novo!$O:$O,BD_Eventos_Novo!$AB:$AB,DRE!H$4)+SUMIFS(Aut_Ajustes_Manuais!$G:$G,Aut_Ajustes_Manuais!$I:$I,DRE!H$4,Aut_Ajustes_Manuais!$F:$F,"Eventos Couvert") -> 0 | L15: =SUMIFS(T_ORCAMENTOS!$E:$E,T_ORCAMENTOS!$C:$C,"Eventos Couvert",T_ORCAMENTOS!$H:$H,"2/2026") -> 0 | M15: =SUMIFS(BD_Eventos_Novo!$M:$M,BD_Eventos_Novo!$AB:$AB,DRE!K$4)+SUMIFS(BD_Eventos_Novo!$N:$N,BD_Eventos_Novo!$AB:$AB,DRE!K$4)+SUMIFS(BD_Eventos_Novo!$O:$O,BD_Eventos_Novo!$AB:$AB,DRE!K$4)+SUMIFS(Aut_Ajustes_Manuais!$G:$G,Aut_Ajustes_Manuais!$I:$I,DRE!K$4,Aut_Ajustes_Manuais!$F:$F,"Eventos Couvert") -> 0 | O15: =SUMIFS(T_ORCAMENTOS!$E:$E,T_ORCAMENTOS!$C:$C,"Eventos Couvert",T_ORCAMENTOS!$H:$H,"3/2026") -> 0 | P15: =SUMIFS(BD_Eventos_Novo!$M:$M,BD_Eventos_Novo!$AB:$AB,DRE!N$4)+SUMIFS(BD_Eventos_Novo!$N:$N,BD_Eventos_Novo!$AB:$AB,DRE!N$4)+SUMIFS(BD_Eventos_Novo!$O:$O,BD_Eventos_Novo!$AB:$AB,DRE!N$4)+SUMIFS(Aut_Ajustes_Manuais!$G:$G,Aut_Ajustes_Manuais!$I:$I,DRE!N$4,Aut_Ajustes_Manuais!$F:$F,"Eventos Couvert") -> 0 | R15: =SUMIFS(T_ORCAMENTOS!$E:$E,T_ORCAMENTOS!$C:$C,"Eventos Couvert",T_ORCAMENTOS!$H:$H,"4/2026") -> 0 | S15: =SUMIFS(BD_Eventos_Novo!$M:$M,BD_Eventos_Novo!$AB:$AB,DRE!Q$4)+SUMIFS(BD_Eventos_Novo!$N:$N,BD_Eventos_Novo!$AB:$AB,DRE!Q$4)+SUMIFS(BD_Eventos_Novo!$O:$O,BD_Eventos_Novo!$AB:$AB,DRE!Q$4)+SUMIFS(Aut_Ajustes_Manuais!$G:$G,Aut_Ajustes_Manuais!$I:$I,DRE!Q$4,Aut_Ajustes_Manuais!$F:$F,"Eventos Couvert") -> 0 | U15: =SUMIFS(T_ORCAMENTOS!$E:$E,T_ORCAMENTOS!$C:$C,"Eventos Couvert",T_ORCAMENTOS!$H:$H,"5/2026") -> 0 | V15: =SUMIFS(BD_Eventos_Novo!$M:$M,BD_Eventos_Novo!$AB:$AB,DRE!T$4)+SUMIFS(BD_Eventos_Novo!$N:$N,BD_Eventos_Novo!$AB:$AB,DRE!T$4)+SUMIFS(BD_Eventos_Novo!$O:$O,BD_Eventos_Novo!$AB:$AB,DRE!T$4)+SUMIFS(Aut_Ajustes_Manuais!$G:$G,Aut_Ajustes_Manuais!$I:$I,DRE!T$4,Aut_Ajustes_Manuais!$F:$F,"Eventos Couvert") -> 0 | X15: =SUMIFS(T_ORCAMENTOS!$E:$E,T_ORCAMENTOS!$C:$C,"Eventos Couvert",T_ORCAMENTOS!$H:$H,"6/2026") -> 0 | Y15: =SUMIFS(BD_Eventos_Novo!$M:$M,BD_Eventos_Novo!$AB:$AB,DRE!W$4)+SUMIFS(BD_Eventos_Novo!$N:$N,BD_Eventos_Novo!$AB:$AB,DRE!W$4)+SUMIFS(BD_Eventos_Novo!$O:$O,BD_Eventos_Novo!$AB:$AB,DRE!W$4)+SUMIFS(Aut_Ajustes_Manuais!$G:$G,Aut_Ajustes_Manuais!$I:$I,DRE!W$4,Aut_Ajustes_Manuais!$F:$F,"Eventos Couvert") -> 0 | AA15: =SUMIFS(T_ORCAMENTOS!$E:$E,T_ORCAMENTOS!$C:$C,"Eventos Couvert",T_ORCAMENTOS!$H:$H,"7/2026") -> 0 | AB15: =SUMIFS(BD_Eventos_Novo!$M:$M,BD_Eventos_Novo!$AB:$AB,DRE!Z$4)+SUMIFS(BD_Eventos_Novo!$N:$N,BD_Eventos_Novo!$AB:$AB,DRE!Z$4)+SUMIFS(BD_Eventos_Novo!$O:$O,BD_Eventos_Novo!$AB:$AB,DRE!Z$4)+SUMIFS(Aut_Ajustes_Manuais!$G:$G,Aut_Ajustes_Manuais!$I:$I,DRE!Z$4,Aut_Ajustes_Manuais!$F:$F,"Eventos Couvert") -> 13500 | AD15: =SUMIFS(T_ORCAMENTOS!$E:$E,T_ORCAMENTOS!$C:$C,"Eventos Couvert",T_ORCAMENTOS!$H:$H,"8/2026") -> 11250 | AE15: =SUMIFS(BD_Eventos_Novo!$M:$M,BD_Eventos_Novo!$AB:$AB,DRE!AC$4)+SUMIFS(BD_Eventos_Novo!$N:$N,BD_Eventos_Novo!$AB:$AB,DRE!AC$4)+SUMIFS(BD_Eventos_Novo!$O:$O,BD_Eventos_Novo!$AB:$AB,DRE!AC$4)+SUMIFS(Aut_Ajustes_Manuais!$G:$G,Aut_Ajustes_Manuais!$I:$I,DRE!AC$4,Aut_Ajustes_Manuais!$F:$F,"Eventos Couvert") -> 0 | AG15: =SUMIFS(T_ORCAMENTOS!$E:$E,T_ORCAMENTOS!$C:$C,"Eventos Couvert",T_ORCAMENTOS!$H:$H,"9/2026") -> 22500 | AH15: =SUMIFS(BD_Eventos_Novo!$M:$M,BD_Eventos_Novo!$AB:$AB,DRE!AF$4)+SUMIFS(BD_Eventos_Novo!$N:$N,BD_Eventos_Novo!$AB:$AB,DRE!AF$4)+SUMIFS(BD_Eventos_Novo!$O:$O,BD_Eventos_Novo!$AB:$AB,DRE!AF$4)+SUMIFS(Aut_Ajustes_Manuais!$G:$G,Aut_Ajustes_Manuais!$I:$I,DRE!AF$4,Aut_Ajustes_Manuais!$F:$F,"Eventos Couvert") -> 0 | AJ15: =SUMIFS(T_ORCAMENTOS!$E:$E,T_ORCAMENTOS!$C:$C,"Eventos Couvert",T_ORCAMENTOS!$H:$H,"10/2026") -> 33750 | AK15: =SUMIFS(BD_Eventos_Novo!$M:$M,BD_Eventos_Novo!$AB:$AB,DRE!AI$4)+SUMIFS(BD_Eventos_Novo!$N:$N,BD_Eventos_Novo!$AB:$AB,DRE!AI$4)+SUMIFS(BD_Eventos_Novo!$O:$O,BD_Eventos_Novo!$AB:$AB,DRE!AI$4)+SUMIFS(Aut_Ajustes_Manuais!$G:$G,Aut_Ajustes_Manuais!$I:$I,DRE!AI$4,Aut_Ajustes_Manuais!$F:$F,"Eventos Couvert") -> 0 | AM15: =SUMIFS(T_ORCAMENTOS!$E:$E,T_ORCAMENTOS!$C:$C,"Eventos Couvert",T_ORCAMENTOS!$H:$H,"11/2026") -> 38250 | AN15: =SUMIFS(BD_Eventos_Novo!$M:$M,BD_Eventos_Novo!$AB:$AB,DRE!AL$4)+SUMIFS(BD_Eventos_Novo!$N:$N,BD_Eventos_Novo!$AB:$AB,DRE!AL$4)+SUMIFS(BD_Eventos_Novo!$O:$O,BD_Eventos_Novo!$AB:$AB,DRE!AL$4)+SUMIFS(Aut_Ajustes_Manuais!$G:$G,Aut_Ajustes_Manuais!$I:$I,DRE!AL$4,Aut_Ajustes_Manuais!$F:$F,"Eventos Couvert") -> 0 | AP15: =SUMIFS(T_ORCAMENTOS!$E:$E,T_ORCAMENTOS!$C:$C,"Eventos Couvert",T_ORCAMENTOS!$H:$H,"12/2026") -> 103875 | AQ15: =SUMIFS(BD_Eventos_Novo!$M:$M,BD_Eventos_Novo!$AB:$AB,DRE!AO$4)+SUMIFS(BD_Eventos_Novo!$N:$N,BD_Eventos_Novo!$AB:$AB,DRE!AO$4)+SUMIFS(BD_Eventos_Novo!$O:$O,BD_Eventos_Novo!$AB:$AB,DRE!AO$4)+SUMIFS(Aut_Ajustes_Manuais!$G:$G,Aut_Ajustes_Manuais!$I:$I,DRE!AO$4,Aut_Ajustes_Manuais!$F:$F,"Eventos Couvert") -> 0 | AR15: =SUMIFS($H15:$AO15,$H$5:$AO$5,"<"&MONTH(TODAY()),$H$6:$AO$6,"REAL 25") -> 0 | AS15: =SUMIFS($I15:$AP15,$I$5:$AP$5,"<"&MONTH(TODAY()),$I$6:$AP$6,"ORÇADO ") -> 11250 | AT15: =SUMIFS($J15:$AQ15,$J$5:$AQ$5,"<"&MONTH(TODAY()),$J$6:$AQ$6,"REAL 26") -> 13500 | AU15: =SUM(H15,K15,N15,Q15,T15,W15,Z15,AC15,AF15,AI15,AL15,AO15) -> 0 | AV15: =SUM(I15,L15,O15,R15,U15,X15,AA15,AD15,AG15,AJ15,AM15,AP15) -> 209625 | AW15: =SUM(J15,M15,P15,S15,V15,Y15,AB15,AE15,AH15,AK15,AN15,AQ15) -> 13500 | AX15: =SUM(H15,K15,N15) -> 0 | AY15: =SUM(I15,L15,O15) -> 0 | AZ15: =SUM(J15,M15,P15) -> 0 | BA15: =SUM(Q15,T15,W15) -> 0 | BB15: =SUM(R15,U15,X15) -> 0 | BC15: =SUM(S15,V15,Y15) -> 0 | BD15: =SUM(Z15,AC15,AF15) -> 0 | BE15: =SUM(AA15,AD15,AG15) -> 33750 | BF15: =SUM(AB15,AE15,AH15) -> 13500 | BG15: =SUM(AI15,AL15,AO15) -> 0 | BH15: =SUM(AJ15,AM15,AP15) -> 175875 | BI15: =SUM(AK15,AN15,AQ15) -> 0
A16: Eventos Locações | C16: Estim. Mensal | D16: Preencher base de Eventos | I16: =SUMIFS(T_ORCAMENTOS!$E:$E,T_ORCAMENTOS!$C:$C,"Eventos Locações",T_ORCAMENTOS!$H:$H,"1/2026") -> 0 | J16: =SUMIFS(BD_Eventos_Novo!$L:$L,BD_Eventos_Novo!$AB:$AB,DRE!H$4)+SUMIFS(BD_Eventos_Novo!$P:$P,BD_Eventos_Novo!$AB:$AB,DRE!H$4)+SUMIFS(BD_Eventos_Novo!$Q:$Q,BD_Eventos_Novo!$AB:$AB,DRE!H$4)+SUMIFS(BD_Eventos_Novo!$R:$R,BD_Eventos_Novo!$AB:$AB,DRE!H$4)+SUMIFS(BD_Eventos_Novo!$S:$S,BD_Eventos_Novo!$AB:$AB,DRE!H$4)+SUMIFS(BD_Eventos_Novo!$T:$T,BD_Eventos_Novo!$AB:$AB,DRE!H$4)+SUMIFS(BD_Eventos_Novo!$U:$U,BD_Eventos_Novo!$AB:$AB,DRE!H$4)+SUMIFS(BD_Eventos_Novo!$V:$V,BD_Eventos_Novo!$AB:$AB,DRE!H$4)+SUMIFS(BD_Eventos_Novo!$W:$W,BD_Eventos_Novo!$AB:$AB,DRE!H$4)+SUMIFS(BD_Eventos_Novo!$X:$X,BD_Eventos_Novo!$AB:$AB,DRE!H$4)+SUMIFS(Aut_Ajustes_Manuais!$G:$G,Aut_Ajustes_Manuais!$I:$I,DRE!H$4,Aut_Ajustes_Manuais!$F:$F,"Eventos Locações") -> 0 | L16: =SUMIFS(T_ORCAMENTOS!$E:$E,T_ORCAMENTOS!$C:$C,"Eventos Locações",T_ORCAMENTOS!$H:$H,"2/2026") -> 0 | M16: =SUMIFS(BD_Eventos_Novo!$L:$L,BD_Eventos_Novo!$AB:$AB,DRE!K$4)+SUMIFS(BD_Eventos_Novo!$P:$P,BD_Eventos_Novo!$AB:$AB,DRE!K$4)+SUMIFS(BD_Eventos_Novo!$Q:$Q,BD_Eventos_Novo!$AB:$AB,DRE!K$4)+SUMIFS(BD_Eventos_Novo!$R:$R,BD_Eventos_Novo!$AB:$AB,DRE!K$4)+SUMIFS(BD_Eventos_Novo!$S:$S,BD_Eventos_Novo!$AB:$AB,DRE!K$4)+SUMIFS(BD_Eventos_Novo!$T:$T,BD_Eventos_Novo!$AB:$AB,DRE!K$4)+SUMIFS(BD_Eventos_Novo!$U:$U,BD_Eventos_Novo!$AB:$AB,DRE!K$4)+SUMIFS(BD_Eventos_Novo!$V:$V,BD_Eventos_Novo!$AB:$AB,DRE!K$4)+SUMIFS(BD_Eventos_Novo!$W:$W,BD_Eventos_Novo!$AB:$AB,DRE!K$4)+SUMIFS(BD_Eventos_Novo!$X:$X,BD_Eventos_Novo!$AB:$AB,DRE!K$4)+SUMIFS(Aut_Ajustes_Manuais!$G:$G,Aut_Ajustes_Manuais!$I:$I,DRE!K$4,Aut_Ajustes_Manuais!$F:$F,"Eventos Locações") -> 0 | O16: =SUMIFS(T_ORCAMENTOS!$E:$E,T_ORCAMENTOS!$C:$C,"Eventos Locações",T_ORCAMENTOS!$H:$H,"3/2026") -> 0 | P16: =SUMIFS(BD_Eventos_Novo!$L:$L,BD_Eventos_Novo!$AB:$AB,DRE!N$4)+SUMIFS(BD_Eventos_Novo!$P:$P,BD_Eventos_Novo!$AB:$AB,DRE!N$4)+SUMIFS(BD_Eventos_Novo!$Q:$Q,BD_Eventos_Novo!$AB:$AB,DRE!N$4)+SUMIFS(BD_Eventos_Novo!$R:$R,BD_Eventos_Novo!$AB:$AB,DRE!N$4)+SUMIFS(BD_Eventos_Novo!$S:$S,BD_Eventos_Novo!$AB:$AB,DRE!N$4)+SUMIFS(BD_Eventos_Novo!$T:$T,BD_Eventos_Novo!$AB:$AB,DRE!N$4)+SUMIFS(BD_Eventos_Novo!$U:$U,BD_Eventos_Novo!$AB:$AB,DRE!N$4)+SUMIFS(BD_Eventos_Novo!$V:$V,BD_Eventos_Novo!$AB:$AB,DRE!N$4)+SUMIFS(BD_Eventos_Novo!$W:$W,BD_Eventos_Novo!$AB:$AB,DRE!N$4)+SUMIFS(BD_Eventos_Novo!$X:$X,BD_Eventos_Novo!$AB:$AB,DRE!N$4)+SUMIFS(Aut_Ajustes_Manuais!$G:$G,Aut_Ajustes_Manuais!$I:$I,DRE!N$4,Aut_Ajustes_Manuais!$F:$F,"Eventos Locações") -> 0 | R16: =SUMIFS(T_ORCAMENTOS!$E:$E,T_ORCAMENTOS!$C:$C,"Eventos Locações",T_ORCAMENTOS!$H:$H,"4/2026") -> 0 | S16: =SUMIFS(BD_Eventos_Novo!$L:$L,BD_Eventos_Novo!$AB:$AB,DRE!Q$4)+SUMIFS(BD_Eventos_Novo!$P:$P,BD_Eventos_Novo!$AB:$AB,DRE!Q$4)+SUMIFS(BD_Eventos_Novo!$Q:$Q,BD_Eventos_Novo!$AB:$AB,DRE!Q$4)+SUMIFS(BD_Eventos_Novo!$R:$R,BD_Eventos_Novo!$AB:$AB,DRE!Q$4)+SUMIFS(BD_Eventos_Novo!$S:$S,BD_Eventos_Novo!$AB:$AB,DRE!Q$4)+SUMIFS(BD_Eventos_Novo!$T:$T,BD_Eventos_Novo!$AB:$AB,DRE!Q$4)+SUMIFS(BD_Eventos_Novo!$U:$U,BD_Eventos_Novo!$AB:$AB,DRE!Q$4)+SUMIFS(BD_Eventos_Novo!$V:$V,BD_Eventos_Novo!$AB:$AB,DRE!Q$4)+SUMIFS(BD_Eventos_Novo!$W:$W,BD_Eventos_Novo!$AB:$AB,DRE!Q$4)+SUMIFS(BD_Eventos_Novo!$X:$X,BD_Eventos_Novo!$AB:$AB,DRE!Q$4)+SUMIFS(Aut_Ajustes_Manuais!$G:$G,Aut_Ajustes_Manuais!$I:$I,DRE!Q$4,Aut_Ajustes_Manuais!$F:$F,"Eventos Locações") -> 0 | U16: =SUMIFS(T_ORCAMENTOS!$E:$E,T_ORCAMENTOS!$C:$C,"Eventos Locações",T_ORCAMENTOS!$H:$H,"5/2026") -> 0 | V16: =SUMIFS(BD_Eventos_Novo!$L:$L,BD_Eventos_Novo!$AB:$AB,DRE!T$4)+SUMIFS(BD_Eventos_Novo!$P:$P,BD_Eventos_Novo!$AB:$AB,DRE!T$4)+SUMIFS(BD_Eventos_Novo!$Q:$Q,BD_Eventos_Novo!$AB:$AB,DRE!T$4)+SUMIFS(BD_Eventos_Novo!$R:$R,BD_Eventos_Novo!$AB:$AB,DRE!T$4)+SUMIFS(BD_Eventos_Novo!$S:$S,BD_Eventos_Novo!$AB:$AB,DRE!T$4)+SUMIFS(BD_Eventos_Novo!$T:$T,BD_Eventos_Novo!$AB:$AB,DRE!T$4)+SUMIFS(BD_Eventos_Novo!$U:$U,BD_Eventos_Novo!$AB:$AB,DRE!T$4)+SUMIFS(BD_Eventos_Novo!$V:$V,BD_Eventos_Novo!$AB:$AB,DRE!T$4)+SUMIFS(BD_Eventos_Novo!$W:$W,BD_Eventos_Novo!$AB:$AB,DRE!T$4)+SUMIFS(BD_Eventos_Novo!$X:$X,BD_Eventos_Novo!$AB:$AB,DRE!T$4)+SUMIFS(Aut_Ajustes_Manuais!$G:$G,Aut_Ajustes_Manuais!$I:$I,DRE!T$4,Aut_Ajustes_Manuais!$F:$F,"Eventos Locações") -> 0 | X16: =SUMIFS(T_ORCAMENTOS!$E:$E,T_ORCAMENTOS!$C:$C,"Eventos Locações",T_ORCAMENTOS!$H:$H,"6/2026") -> 0 | Y16: =SUMIFS(BD_Eventos_Novo!$L:$L,BD_Eventos_Novo!$AB:$AB,DRE!W$4)+SUMIFS(BD_Eventos_Novo!$P:$P,BD_Eventos_Novo!$AB:$AB,DRE!W$4)+SUMIFS(BD_Eventos_Novo!$Q:$Q,BD_Eventos_Novo!$AB:$AB,DRE!W$4)+SUMIFS(BD_Eventos_Novo!$R:$R,BD_Eventos_Novo!$AB:$AB,DRE!W$4)+SUMIFS(BD_Eventos_Novo!$S:$S,BD_Eventos_Novo!$AB:$AB,DRE!W$4)+SUMIFS(BD_Eventos_Novo!$T:$T,BD_Eventos_Novo!$AB:$AB,DRE!W$4)+SUMIFS(BD_Eventos_Novo!$U:$U,BD_Eventos_Novo!$AB:$AB,DRE!W$4)+SUMIFS(BD_Eventos_Novo!$V:$V,BD_Eventos_Novo!$AB:$AB,DRE!W$4)+SUMIFS(BD_Eventos_Novo!$W:$W,BD_Eventos_Novo!$AB:$AB,DRE!W$4)+SUMIFS(BD_Eventos_Novo!$X:$X,BD_Eventos_Novo!$AB:$AB,DRE!W$4)+SUMIFS(Aut_Ajustes_Manuais!$G:$G,Aut_Ajustes_Manuais!$I:$I,DRE!W$4,Aut_Ajustes_Manuais!$F:$F,"Eventos Locações") -> 0 | AA16: =SUMIFS(T_ORCAMENTOS!$E:$E,T_ORCAMENTOS!$C:$C,"Eventos Locações",T_ORCAMENTOS!$H:$H,"7/2026") -> 0 | AB16: =SUMIFS(BD_Eventos_Novo!$L:$L,BD_Eventos_Novo!$AB:$AB,DRE!Z$4)+SUMIFS(BD_Eventos_Novo!$P:$P,BD_Eventos_Novo!$AB:$AB,DRE!Z$4)+SUMIFS(BD_Eventos_Novo!$Q:$Q,BD_Eventos_Novo!$AB:$AB,DRE!Z$4)+SUMIFS(BD_Eventos_Novo!$R:$R,BD_Eventos_Novo!$AB:$AB,DRE!Z$4)+SUMIFS(BD_Eventos_Novo!$S:$S,BD_Eventos_Novo!$AB:$AB,DRE!Z$4)+SUMIFS(BD_Eventos_Novo!$T:$T,BD_Eventos_Novo!$AB:$AB,DRE!Z$4)+SUMIFS(BD_Eventos_Novo!$U:$U,BD_Eventos_Novo!$AB:$AB,DRE!Z$4)+SUMIFS(BD_Eventos_Novo!$V:$V,BD_Eventos_Novo!$AB:$AB,DRE!Z$4)+SUMIFS(BD_Eventos_Novo!$W:$W,BD_Eventos_Novo!$AB:$AB,DRE!Z$4)+SUMIFS(BD_Eventos_Novo!$X:$X,BD_Eventos_Novo!$AB:$AB,DRE!Z$4)+SUMIFS(Aut_Ajustes_Manuais!$G:$G,Aut_Ajustes_Manuais!$I:$I,DRE!Z$4,Aut_Ajustes_Manuais!$F:$F,"Eventos Locações") -> 0 | AD16: =SUMIFS(T_ORCAMENTOS!$E:$E,T_ORCAMENTOS!$C:$C,"Eventos Locações",T_ORCAMENTOS!$H:$H,"8/2026") -> 15000 | AE16: =SUMIFS(BD_Eventos_Novo!$L:$L,BD_Eventos_Novo!$AB:$AB,DRE!AC$4)+SUMIFS(BD_Eventos_Novo!$P:$P,BD_Eventos_Novo!$AB:$AB,DRE!AC$4)+SUMIFS(BD_Eventos_Novo!$Q:$Q,BD_Eventos_Novo!$AB:$AB,DRE!AC$4)+SUMIFS(BD_Eventos_Novo!$R:$R,BD_Eventos_Novo!$AB:$AB,DRE!AC$4)+SUMIFS(BD_Eventos_Novo!$S:$S,BD_Eventos_Novo!$AB:$AB,DRE!AC$4)+SUMIFS(BD_Eventos_Novo!$T:$T,BD_Eventos_Novo!$AB:$AB,DRE!AC$4)+SUMIFS(BD_Eventos_Novo!$U:$U,BD_Eventos_Novo!$AB:$AB,DRE!AC$4)+SUMIFS(BD_Eventos_Novo!$V:$V,BD_Eventos_Novo!$AB:$AB,DRE!AC$4)+SUMIFS(BD_Eventos_Novo!$W:$W,BD_Eventos_Novo!$AB:$AB,DRE!AC$4)+SUMIFS(BD_Eventos_Novo!$X:$X,BD_Eventos_Novo!$AB:$AB,DRE!AC$4)+SUMIFS(Aut_Ajustes_Manuais!$G:$G,Aut_Ajustes_Manuais!$I:$I,DRE!AC$4,Aut_Ajustes_Manuais!$F:$F,"Eventos Locações") -> 0 | AG16: =SUMIFS(T_ORCAMENTOS!$E:$E,T_ORCAMENTOS!$C:$C,"Eventos Locações",T_ORCAMENTOS!$H:$H,"9/2026") -> 30000 | AH16: =SUMIFS(BD_Eventos_Novo!$L:$L,BD_Eventos_Novo!$AB:$AB,DRE!AF$4)+SUMIFS(BD_Eventos_Novo!$P:$P,BD_Eventos_Novo!$AB:$AB,DRE!AF$4)+SUMIFS(BD_Eventos_Novo!$Q:$Q,BD_Eventos_Novo!$AB:$AB,DRE!AF$4)+SUMIFS(BD_Eventos_Novo!$R:$R,BD_Eventos_Novo!$AB:$AB,DRE!AF$4)+SUMIFS(BD_Eventos_Novo!$S:$S,BD_Eventos_Novo!$AB:$AB,DRE!AF$4)+SUMIFS(BD_Eventos_Novo!$T:$T,BD_Eventos_Novo!$AB:$AB,DRE!AF$4)+SUMIFS(BD_Eventos_Novo!$U:$U,BD_Eventos_Novo!$AB:$AB,DRE!AF$4)+SUMIFS(BD_Eventos_Novo!$V:$V,BD_Eventos_Novo!$AB:$AB,DRE!AF$4)+SUMIFS(BD_Eventos_Novo!$W:$W,BD_Eventos_Novo!$AB:$AB,DRE!AF$4)+SUMIFS(BD_Eventos_Novo!$X:$X,BD_Eventos_Novo!$AB:$AB,DRE!AF$4)+SUMIFS(Aut_Ajustes_Manuais!$G:$G,Aut_Ajustes_Manuais!$I:$I,DRE!AF$4,Aut_Ajustes_Manuais!$F:$F,"Eventos Locações") -> 0 | AJ16: =SUMIFS(T_ORCAMENTOS!$E:$E,T_ORCAMENTOS!$C:$C,"Eventos Locações",T_ORCAMENTOS!$H:$H,"10/2026") -> 45000 | AK16: =SUMIFS(BD_Eventos_Novo!$L:$L,BD_Eventos_Novo!$AB:$AB,DRE!AI$4)+SUMIFS(BD_Eventos_Novo!$P:$P,BD_Eventos_Novo!$AB:$AB,DRE!AI$4)+SUMIFS(BD_Eventos_Novo!$Q:$Q,BD_Eventos_Novo!$AB:$AB,DRE!AI$4)+SUMIFS(BD_Eventos_Novo!$R:$R,BD_Eventos_Novo!$AB:$AB,DRE!AI$4)+SUMIFS(BD_Eventos_Novo!$S:$S,BD_Eventos_Novo!$AB:$AB,DRE!AI$4)+SUMIFS(BD_Eventos_Novo!$T:$T,BD_Eventos_Novo!$AB:$AB,DRE!AI$4)+SUMIFS(BD_Eventos_Novo!$U:$U,BD_Eventos_Novo!$AB:$AB,DRE!AI$4)+SUMIFS(BD_Eventos_Novo!$V:$V,BD_Eventos_Novo!$AB:$AB,DRE!AI$4)+SUMIFS(BD_Eventos_Novo!$W:$W,BD_Eventos_Novo!$AB:$AB,DRE!AI$4)+SUMIFS(BD_Eventos_Novo!$X:$X,BD_Eventos_Novo!$AB:$AB,DRE!AI$4)+SUMIFS(Aut_Ajustes_Manuais!$G:$G,Aut_Ajustes_Manuais!$I:$I,DRE!AI$4,Aut_Ajustes_Manuais!$F:$F,"Eventos Locações") -> 0 | AM16: =SUMIFS(T_ORCAMENTOS!$E:$E,T_ORCAMENTOS!$C:$C,"Eventos Locações",T_ORCAMENTOS!$H:$H,"11/2026") -> 51000 | AN16: =SUMIFS(BD_Eventos_Novo!$L:$L,BD_Eventos_Novo!$AB:$AB,DRE!AL$4)+SUMIFS(BD_Eventos_Novo!$P:$P,BD_Eventos_Novo!$AB:$AB,DRE!AL$4)+SUMIFS(BD_Eventos_Novo!$Q:$Q,BD_Eventos_Novo!$AB:$AB,DRE!AL$4)+SUMIFS(BD_Eventos_Novo!$R:$R,BD_Eventos_Novo!$AB:$AB,DRE!AL$4)+SUMIFS(BD_Eventos_Novo!$S:$S,BD_Eventos_Novo!$AB:$AB,DRE!AL$4)+SUMIFS(BD_Eventos_Novo!$T:$T,BD_Eventos_Novo!$AB:$AB,DRE!AL$4)+SUMIFS(BD_Eventos_Novo!$U:$U,BD_Eventos_Novo!$AB:$AB,DRE!AL$4)+SUMIFS(BD_Eventos_Novo!$V:$V,BD_Eventos_Novo!$AB:$AB,DRE!AL$4)+SUMIFS(BD_Eventos_Novo!$W:$W,BD_Eventos_Novo!$AB:$AB,DRE!AL$4)+SUMIFS(BD_Eventos_Novo!$X:$X,BD_Eventos_Novo!$AB:$AB,DRE!AL$4)+SUMIFS(Aut_Ajustes_Manuais!$G:$G,Aut_Ajustes_Manuais!$I:$I,DRE!AL$4,Aut_Ajustes_Manuais!$F:$F,"Eventos Locações") -> 0 | AP16: =SUMIFS(T_ORCAMENTOS!$E:$E,T_ORCAMENTOS!$C:$C,"Eventos Locações",T_ORCAMENTOS!$H:$H,"12/2026") -> 138500 | AQ16: =SUMIFS(BD_Eventos_Novo!$L:$L,BD_Eventos_Novo!$AB:$AB,DRE!AO$4)+SUMIFS(BD_Eventos_Novo!$P:$P,BD_Eventos_Novo!$AB:$AB,DRE!AO$4)+SUMIFS(BD_Eventos_Novo!$Q:$Q,BD_Eventos_Novo!$AB:$AB,DRE!AO$4)+SUMIFS(BD_Eventos_Novo!$R:$R,BD_Eventos_Novo!$AB:$AB,DRE!AO$4)+SUMIFS(BD_Eventos_Novo!$S:$S,BD_Eventos_Novo!$AB:$AB,DRE!AO$4)+SUMIFS(BD_Eventos_Novo!$T:$T,BD_Eventos_Novo!$AB:$AB,DRE!AO$4)+SUMIFS(BD_Eventos_Novo!$U:$U,BD_Eventos_Novo!$AB:$AB,DRE!AO$4)+SUMIFS(BD_Eventos_Novo!$V:$V,BD_Eventos_Novo!$AB:$AB,DRE!AO$4)+SUMIFS(BD_Eventos_Novo!$W:$W,BD_Eventos_Novo!$AB:$AB,DRE!AO$4)+SUMIFS(BD_Eventos_Novo!$X:$X,BD_Eventos_Novo!$AB:$AB,DRE!AO$4)+SUMIFS(Aut_Ajustes_Manuais!$G:$G,Aut_Ajustes_Manuais!$I:$I,DRE!AO$4,Aut_Ajustes_Manuais!$F:$F,"Eventos Locações") -> 0 | AR16: =SUMIFS($H16:$AO16,$H$5:$AO$5,"<"&MONTH(TODAY()),$H$6:$AO$6,"REAL 25") -> 0 | AS16: =SUMIFS($I16:$AP16,$I$5:$AP$5,"<"&MONTH(TODAY()),$I$6:$AP$6,"ORÇADO ") -> 15000 | AT16: =SUMIFS($J16:$AQ16,$J$5:$AQ$5,"<"&MONTH(TODAY()),$J$6:$AQ$6,"REAL 26") -> 0 | AU16: =SUM(H16,K16,N16,Q16,T16,W16,Z16,AC16,AF16,AI16,AL16,AO16) -> 0 | AV16: =SUM(I16,L16,O16,R16,U16,X16,AA16,AD16,AG16,AJ16,AM16,AP16) -> 279500 | AW16: =SUM(J16,M16,P16,S16,V16,Y16,AB16,AE16,AH16,AK16,AN16,AQ16) -> 0 | AX16: =SUM(H16,K16,N16) -> 0 | AY16: =SUM(I16,L16,O16) -> 0 | AZ16: =SUM(J16,M16,P16) -> 0 | BA16: =SUM(Q16,T16,W16) -> 0 | BB16: =SUM(R16,U16,X16) -> 0 | BC16: =SUM(S16,V16,Y16) -> 0 | BD16: =SUM(Z16,AC16,AF16) -> 0 | BE16: =SUM(AA16,AD16,AG16) -> 45000 | BF16: =SUM(AB16,AE16,AH16) -> 0 | BG16: =SUM(AI16,AL16,AO16) -> 0 | BH16: =SUM(AJ16,AM16,AP16) -> 234500 | BI16: =SUM(AK16,AN16,AQ16) -> 0
A17: Eventos Rebate Fornecedores | C17: Estim. Mensal | D17: Comissão sobre venda dos fornecedores homologados | I17: =SUMIFS(T_ORCAMENTOS!$E:$E,T_ORCAMENTOS!$C:$C,"Eventos Rebate Fornecedores",T_ORCAMENTOS!$H:$H,"1/2026") -> 0 | J17: 0 | L17: =SUMIFS(T_ORCAMENTOS!$E:$E,T_ORCAMENTOS!$C:$C,"Eventos Rebate Fornecedores",T_ORCAMENTOS!$H:$H,"2/2026") -> 0 | M17: 0 | O17: =SUMIFS(T_ORCAMENTOS!$E:$E,T_ORCAMENTOS!$C:$C,"Eventos Rebate Fornecedores",T_ORCAMENTOS!$H:$H,"3/2026") -> 0 | P17: 0 | R17: =SUMIFS(T_ORCAMENTOS!$E:$E,T_ORCAMENTOS!$C:$C,"Eventos Rebate Fornecedores",T_ORCAMENTOS!$H:$H,"4/2026") -> 0 | S17: 0 | U17: =SUMIFS(T_ORCAMENTOS!$E:$E,T_ORCAMENTOS!$C:$C,"Eventos Rebate Fornecedores",T_ORCAMENTOS!$H:$H,"5/2026") -> 0 | V17: 0 | X17: =SUMIFS(T_ORCAMENTOS!$E:$E,T_ORCAMENTOS!$C:$C,"Eventos Rebate Fornecedores",T_ORCAMENTOS!$H:$H,"6/2026") -> 0 | Y17: 0 | AA17: =SUMIFS(T_ORCAMENTOS!$E:$E,T_ORCAMENTOS!$C:$C,"Eventos Rebate Fornecedores",T_ORCAMENTOS!$H:$H,"7/2026") -> 0 | AB17: 0 | AD17: =SUMIFS(T_ORCAMENTOS!$E:$E,T_ORCAMENTOS!$C:$C,"Eventos Rebate Fornecedores",T_ORCAMENTOS!$H:$H,"8/2026") -> 0 | AE17: 0 | AG17: =SUMIFS(T_ORCAMENTOS!$E:$E,T_ORCAMENTOS!$C:$C,"Eventos Rebate Fornecedores",T_ORCAMENTOS!$H:$H,"9/2026") -> 0 | AH17: 0 | AJ17: =SUMIFS(T_ORCAMENTOS!$E:$E,T_ORCAMENTOS!$C:$C,"Eventos Rebate Fornecedores",T_ORCAMENTOS!$H:$H,"10/2026") -> 0 | AK17: 0 | AM17: =SUMIFS(T_ORCAMENTOS!$E:$E,T_ORCAMENTOS!$C:$C,"Eventos Rebate Fornecedores",T_ORCAMENTOS!$H:$H,"11/2026") -> 0 | AN17: 0 | AP17: =SUMIFS(T_ORCAMENTOS!$E:$E,T_ORCAMENTOS!$C:$C,"Eventos Rebate Fornecedores",T_ORCAMENTOS!$H:$H,"12/2026") -> 0 | AQ17: 0 | AR17: =SUMIFS($H17:$AO17,$H$5:$AO$5,"<"&MONTH(TODAY()),$H$6:$AO$6,"REAL 25") -> 0 | AS17: =SUMIFS($I17:$AP17,$I$5:$AP$5,"<"&MONTH(TODAY()),$I$6:$AP$6,"ORÇADO ") -> 0 | AT17: =SUMIFS($J17:$AQ17,$J$5:$AQ$5,"<"&MONTH(TODAY()),$J$6:$AQ$6,"REAL 26") -> 0 | AU17: =SUM(H17,K17,N17,Q17,T17,W17,Z17,AC17,AF17,AI17,AL17,AO17) -> 0 | AV17: =SUM(I17,L17,O17,R17,U17,X17,AA17,AD17,AG17,AJ17,AM17,AP17) -> 0 | AW17: =SUM(J17,M17,P17,S17,V17,Y17,AB17,AE17,AH17,AK17,AN17,AQ17) -> 0 | AX17: =SUM(H17,K17,N17) -> 0 | AY17: =SUM(I17,L17,O17) -> 0 | AZ17: =SUM(J17,M17,P17) -> 0 | BA17: =SUM(Q17,T17,W17) -> 0 | BB17: =SUM(R17,U17,X17) -> 0 | BC17: =SUM(S17,V17,Y17) -> 0 | BD17: =SUM(Z17,AC17,AF17) -> 0 | BE17: =SUM(AA17,AD17,AG17) -> 0 | BF17: =SUM(AB17,AE17,AH17) -> 0 | BG17: =SUM(AI17,AL17,AO17) -> 0 | BH17: =SUM(AJ17,AM17,AP17) -> 0 | BI17: =SUM(AK17,AN17,AQ17) -> 0
A18: Delivery | C18: Estim. Mensal | D18: Preencher base de Delivery | I18: =SUMIFS(T_ORCAMENTOS!$E:$E,T_ORCAMENTOS!$C:$C,"Delivery",T_ORCAMENTOS!$H:$H,"1/2026") -> 0 | J18: =SUMIFS(Aut_Faturamento_Zig_Delivery!$F:$F,Aut_Faturamento_Zig_Delivery!$D:$D,DRE!H$4)+SUMIFS(Aut_Ajustes_Manuais!$G:$G,Aut_Ajustes_Manuais!$I:$I,DRE!H$4,Aut_Ajustes_Manuais!$F:$F,"Delivery") -> 0 | L18: =SUMIFS(T_ORCAMENTOS!$E:$E,T_ORCAMENTOS!$C:$C,"Delivery",T_ORCAMENTOS!$H:$H,"2/2026") -> 0 | M18: =SUMIFS(Aut_Faturamento_Zig_Delivery!$F:$F,Aut_Faturamento_Zig_Delivery!$D:$D,DRE!K$4)+SUMIFS(Aut_Ajustes_Manuais!$G:$G,Aut_Ajustes_Manuais!$I:$I,DRE!K$4,Aut_Ajustes_Manuais!$F:$F,"Delivery") -> 0 | O18: =SUMIFS(T_ORCAMENTOS!$E:$E,T_ORCAMENTOS!$C:$C,"Delivery",T_ORCAMENTOS!$H:$H,"3/2026") -> 0 | P18: =SUMIFS(Aut_Faturamento_Zig_Delivery!$F:$F,Aut_Faturamento_Zig_Delivery!$D:$D,DRE!N$4)+SUMIFS(Aut_Ajustes_Manuais!$G:$G,Aut_Ajustes_Manuais!$I:$I,DRE!N$4,Aut_Ajustes_Manuais!$F:$F,"Delivery") -> 0 | R18: =SUMIFS(T_ORCAMENTOS!$E:$E,T_ORCAMENTOS!$C:$C,"Delivery",T_ORCAMENTOS!$H:$H,"4/2026") -> 0 | S18: =SUMIFS(Aut_Faturamento_Zig_Delivery!$F:$F,Aut_Faturamento_Zig_Delivery!$D:$D,DRE!Q$4)+SUMIFS(Aut_Ajustes_Manuais!$G:$G,Aut_Ajustes_Manuais!$I:$I,DRE!Q$4,Aut_Ajustes_Manuais!$F:$F,"Delivery") -> 0 | U18: =SUMIFS(T_ORCAMENTOS!$E:$E,T_ORCAMENTOS!$C:$C,"Delivery",T_ORCAMENTOS!$H:$H,"5/2026") -> 0 | V18: =SUMIFS(Aut_Faturamento_Zig_Delivery!$F:$F,Aut_Faturamento_Zig_Delivery!$D:$D,DRE!T$4)+SUMIFS(Aut_Ajustes_Manuais!$G:$G,Aut_Ajustes_Manuais!$I:$I,DRE!T$4,Aut_Ajustes_Manuais!$F:$F,"Delivery") -> 0 | X18: =SUMIFS(T_ORCAMENTOS!$E:$E,T_ORCAMENTOS!$C:$C,"Delivery",T_ORCAMENTOS!$H:$H,"6/2026") -> 0 | Y18: =SUMIFS(Aut_Faturamento_Zig_Delivery!$F:$F,Aut_Faturamento_Zig_Delivery!$D:$D,DRE!W$4)+SUMIFS(Aut_Ajustes_Manuais!$G:$G,Aut_Ajustes_Manuais!$I:$I,DRE!W$4,Aut_Ajustes_Manuais!$F:$F,"Delivery") -> 0 | AA18: =SUMIFS(T_ORCAMENTOS!$E:$E,T_ORCAMENTOS!$C:$C,"Delivery",T_ORCAMENTOS!$H:$H,"7/2026") -> 0 | AB18: =SUMIFS(Aut_Faturamento_Zig_Delivery!$F:$F,Aut_Faturamento_Zig_Delivery!$D:$D,DRE!Z$4)+SUMIFS(Aut_Ajustes_Manuais!$G:$G,Aut_Ajustes_Manuais!$I:$I,DRE!Z$4,Aut_Ajustes_Manuais!$F:$F,"Delivery") -> 0 | AD18: =SUMIFS(T_ORCAMENTOS!$E:$E,T_ORCAMENTOS!$C:$C,"Delivery",T_ORCAMENTOS!$H:$H,"8/2026") -> 0 | AE18: =SUMIFS(Aut_Faturamento_Zig_Delivery!$F:$F,Aut_Faturamento_Zig_Delivery!$D:$D,DRE!AC$4)+SUMIFS(Aut_Ajustes_Manuais!$G:$G,Aut_Ajustes_Manuais!$I:$I,DRE!AC$4,Aut_Ajustes_Manuais!$F:$F,"Delivery") -> 0 | AG18: =SUMIFS(T_ORCAMENTOS!$E:$E,T_ORCAMENTOS!$C:$C,"Delivery",T_ORCAMENTOS!$H:$H,"9/2026") -> 0 | AH18: =SUMIFS(Aut_Faturamento_Zig_Delivery!$F:$F,Aut_Faturamento_Zig_Delivery!$D:$D,DRE!AF$4)+SUMIFS(Aut_Ajustes_Manuais!$G:$G,Aut_Ajustes_Manuais!$I:$I,DRE!AF$4,Aut_Ajustes_Manuais!$F:$F,"Delivery") -> 0 | AJ18: =SUMIFS(T_ORCAMENTOS!$E:$E,T_ORCAMENTOS!$C:$C,"Delivery",T_ORCAMENTOS!$H:$H,"10/2026") -> 0 | AK18: =SUMIFS(Aut_Faturamento_Zig_Delivery!$F:$F,Aut_Faturamento_Zig_Delivery!$D:$D,DRE!AI$4)+SUMIFS(Aut_Ajustes_Manuais!$G:$G,Aut_Ajustes_Manuais!$I:$I,DRE!AI$4,Aut_Ajustes_Manuais!$F:$F,"Delivery") -> 0 | AM18: =SUMIFS(T_ORCAMENTOS!$E:$E,T_ORCAMENTOS!$C:$C,"Delivery",T_ORCAMENTOS!$H:$H,"11/2026") -> 0 | AN18: =SUMIFS(Aut_Faturamento_Zig_Delivery!$F:$F,Aut_Faturamento_Zig_Delivery!$D:$D,DRE!AL$4)+SUMIFS(Aut_Ajustes_Manuais!$G:$G,Aut_Ajustes_Manuais!$I:$I,DRE!AL$4,Aut_Ajustes_Manuais!$F:$F,"Delivery") -> 0 | AP18: =SUMIFS(T_ORCAMENTOS!$E:$E,T_ORCAMENTOS!$C:$C,"Delivery",T_ORCAMENTOS!$H:$H,"12/2026") -> 0 | AQ18: =SUMIFS(Aut_Faturamento_Zig_Delivery!$F:$F,Aut_Faturamento_Zig_Delivery!$D:$D,DRE!AO$4)+SUMIFS(Aut_Ajustes_Manuais!$G:$G,Aut_Ajustes_Manuais!$I:$I,DRE!AO$4,Aut_Ajustes_Manuais!$F:$F,"Delivery") -> 0 | AR18: =SUMIFS($H18:$AO18,$H$5:$AO$5,"<"&MONTH(TODAY()),$H$6:$AO$6,"REAL 25") -> 0 | AS18: =SUMIFS($I18:$AP18,$I$5:$AP$5,"<"&MONTH(TODAY()),$I$6:$AP$6,"ORÇADO ") -> 0 | AT18: =SUMIFS($J18:$AQ18,$J$5:$AQ$5,"<"&MONTH(TODAY()),$J$6:$AQ$6,"REAL 26") -> 0 | AU18: =SUM(H18,K18,N18,Q18,T18,W18,Z18,AC18,AF18,AI18,AL18,AO18) -> 0 | AV18: =SUM(I18,L18,O18,R18,U18,X18,AA18,AD18,AG18,AJ18,AM18,AP18) -> 0 | AW18: =SUM(J18,M18,P18,S18,V18,Y18,AB18,AE18,AH18,AK18,AN18,AQ18) -> 0 | AX18: =SUM(H18,K18,N18) -> 0 | AY18: =SUM(I18,L18,O18) -> 0 | AZ18: =SUM(J18,M18,P18) -> 0 | BA18: =SUM(Q18,T18,W18) -> 0 | BB18: =SUM(R18,U18,X18) -> 0 | BC18: =SUM(S18,V18,Y18) -> 0 | BD18: =SUM(Z18,AC18,AF18) -> 0 | BE18: =SUM(AA18,AD18,AG18) -> 0 | BF18: =SUM(AB18,AE18,AH18) -> 0 | BG18: =SUM(AI18,AL18,AO18) -> 0 | BH18: =SUM(AJ18,AM18,AP18) -> 0 | BI18: =SUM(AK18,AN18,AQ18) -> 0
A19: Outras Receitas | C19: Estim. Mensal | D19: Coleta de Oleo e etc | I19: =SUMIFS(T_ORCAMENTOS!$E:$E,T_ORCAMENTOS!$C:$C,"Outras Receitas",T_ORCAMENTOS!$H:$H,"1/2026") -> 0 | J19: =SUMIFS(Aut_Receitas_Extraord!$L:$L,Aut_Receitas_Extraord!$U:$U,DRE!H4,Aut_Receitas_Extraord!$D:$D,"Coleta de Óleo")+SUMIFS(Aut_Ajustes_Manuais!$G:$G,Aut_Ajustes_Manuais!$I:$I,DRE!H$4,Aut_Ajustes_Manuais!$F:$F,"Outras Receitas") -> 0 | L19: =SUMIFS(T_ORCAMENTOS!$E:$E,T_ORCAMENTOS!$C:$C,"Outras Receitas",T_ORCAMENTOS!$H:$H,"2/2026") -> 0 | M19: =SUMIFS(Aut_Receitas_Extraord!$L:$L,Aut_Receitas_Extraord!$U:$U,DRE!K4,Aut_Receitas_Extraord!$D:$D,"Coleta de Óleo")+SUMIFS(Aut_Ajustes_Manuais!$G:$G,Aut_Ajustes_Manuais!$I:$I,DRE!K$4,Aut_Ajustes_Manuais!$F:$F,"Outras Receitas") -> 0 | O19: =SUMIFS(T_ORCAMENTOS!$E:$E,T_ORCAMENTOS!$C:$C,"Outras Receitas",T_ORCAMENTOS!$H:$H,"3/2026") -> 0 | P19: =SUMIFS(Aut_Receitas_Extraord!$L:$L,Aut_Receitas_Extraord!$U:$U,DRE!N4,Aut_Receitas_Extraord!$D:$D,"Coleta de Óleo")+SUMIFS(Aut_Ajustes_Manuais!$G:$G,Aut_Ajustes_Manuais!$I:$I,DRE!N$4,Aut_Ajustes_Manuais!$F:$F,"Outras Receitas") -> 0 | R19: =SUMIFS(T_ORCAMENTOS!$E:$E,T_ORCAMENTOS!$C:$C,"Outras Receitas",T_ORCAMENTOS!$H:$H,"4/2026") -> 0 | S19: =SUMIFS(Aut_Receitas_Extraord!$L:$L,Aut_Receitas_Extraord!$U:$U,DRE!Q4,Aut_Receitas_Extraord!$D:$D,"Coleta de Óleo")+SUMIFS(Aut_Ajustes_Manuais!$G:$G,Aut_Ajustes_Manuais!$I:$I,DRE!Q$4,Aut_Ajustes_Manuais!$F:$F,"Outras Receitas") -> 0 | U19: =SUMIFS(T_ORCAMENTOS!$E:$E,T_ORCAMENTOS!$C:$C,"Outras Receitas",T_ORCAMENTOS!$H:$H,"5/2026") -> 0 | V19: =SUMIFS(Aut_Receitas_Extraord!$L:$L,Aut_Receitas_Extraord!$U:$U,DRE!T4,Aut_Receitas_Extraord!$D:$D,"Coleta de Óleo")+SUMIFS(Aut_Ajustes_Manuais!$G:$G,Aut_Ajustes_Manuais!$I:$I,DRE!T$4,Aut_Ajustes_Manuais!$F:$F,"Outras Receitas") -> 0 | X19: =SUMIFS(T_ORCAMENTOS!$E:$E,T_ORCAMENTOS!$C:$C,"Outras Receitas",T_ORCAMENTOS!$H:$H,"6/2026") -> 0 | Y19: =SUMIFS(Aut_Receitas_Extraord!$L:$L,Aut_Receitas_Extraord!$U:$U,DRE!W4,Aut_Receitas_Extraord!$D:$D,"Coleta de Óleo")+SUMIFS(Aut_Ajustes_Manuais!$G:$G,Aut_Ajustes_Manuais!$I:$I,DRE!W$4,Aut_Ajustes_Manuais!$F:$F,"Outras Receitas") -> 0 | AA19: =SUMIFS(T_ORCAMENTOS!$E:$E,T_ORCAMENTOS!$C:$C,"Outras Receitas",T_ORCAMENTOS!$H:$H,"7/2026") -> 0 | AB19: =SUMIFS(Aut_Receitas_Extraord!$L:$L,Aut_Receitas_Extraord!$U:$U,DRE!Z4,Aut_Receitas_Extraord!$D:$D,"Coleta de Óleo")+SUMIFS(Aut_Ajustes_Manuais!$G:$G,Aut_Ajustes_Manuais!$I:$I,DRE!Z$4,Aut_Ajustes_Manuais!$F:$F,"Outras Receitas") -> 0 | AD19: =SUMIFS(T_ORCAMENTOS!$E:$E,T_ORCAMENTOS!$C:$C,"Outras Receitas",T_ORCAMENTOS!$H:$H,"8/2026") -> 750 | AE19: =SUMIFS(Aut_Receitas_Extraord!$L:$L,Aut_Receitas_Extraord!$U:$U,DRE!AC4,Aut_Receitas_Extraord!$D:$D,"Coleta de Óleo")+SUMIFS(Aut_Ajustes_Manuais!$G:$G,Aut_Ajustes_Manuais!$I:$I,DRE!AC$4,Aut_Ajustes_Manuais!$F:$F,"Outras Receitas") -> 0 | AG19: =SUMIFS(T_ORCAMENTOS!$E:$E,T_ORCAMENTOS!$C:$C,"Outras Receitas",T_ORCAMENTOS!$H:$H,"9/2026") -> 750 | AH19: =SUMIFS(Aut_Receitas_Extraord!$L:$L,Aut_Receitas_Extraord!$U:$U,DRE!AF4,Aut_Receitas_Extraord!$D:$D,"Coleta de Óleo")+SUMIFS(Aut_Ajustes_Manuais!$G:$G,Aut_Ajustes_Manuais!$I:$I,DRE!AF$4,Aut_Ajustes_Manuais!$F:$F,"Outras Receitas") -> 0 | AJ19: =SUMIFS(T_ORCAMENTOS!$E:$E,T_ORCAMENTOS!$C:$C,"Outras Receitas",T_ORCAMENTOS!$H:$H,"10/2026") -> 750 | AK19: =SUMIFS(Aut_Receitas_Extraord!$L:$L,Aut_Receitas_Extraord!$U:$U,DRE!AI4,Aut_Receitas_Extraord!$D:$D,"Coleta de Óleo")+SUMIFS(Aut_Ajustes_Manuais!$G:$G,Aut_Ajustes_Manuais!$I:$I,DRE!AI$4,Aut_Ajustes_Manuais!$F:$F,"Outras Receitas") -> 0 | AM19: =SUMIFS(T_ORCAMENTOS!$E:$E,T_ORCAMENTOS!$C:$C,"Outras Receitas",T_ORCAMENTOS!$H:$H,"11/2026") -> 750 | AN19: =SUMIFS(Aut_Receitas_Extraord!$L:$L,Aut_Receitas_Extraord!$U:$U,DRE!AL4,Aut_Receitas_Extraord!$D:$D,"Coleta de Óleo")+SUMIFS(Aut_Ajustes_Manuais!$G:$G,Aut_Ajustes_Manuais!$I:$I,DRE!AL$4,Aut_Ajustes_Manuais!$F:$F,"Outras Receitas") -> 0 | AP19: =SUMIFS(T_ORCAMENTOS!$E:$E,T_ORCAMENTOS!$C:$C,"Outras Receitas",T_ORCAMENTOS!$H:$H,"12/2026") -> 750 | AQ19: =SUMIFS(Aut_Receitas_Extraord!$L:$L,Aut_Receitas_Extraord!$U:$U,DRE!AO4,Aut_Receitas_Extraord!$D:$D,"Coleta de Óleo")+SUMIFS(Aut_Ajustes_Manuais!$G:$G,Aut_Ajustes_Manuais!$I:$I,DRE!AO$4,Aut_Ajustes_Manuais!$F:$F,"Outras Receitas") -> 0 | AR19: =SUMIFS($H19:$AO19,$H$5:$AO$5,"<"&MONTH(TODAY()),$H$6:$AO$6,"REAL 25") -> 0 | AS19: =SUMIFS($I19:$AP19,$I$5:$AP$5,"<"&MONTH(TODAY()),$I$6:$AP$6,"ORÇADO ") -> 750 | AT19: =SUMIFS($J19:$AQ19,$J$5:$AQ$5,"<"&MONTH(TODAY()),$J$6:$AQ$6,"REAL 26") -> 0 | AU19: =SUM(H19,K19,N19,Q19,T19,W19,Z19,AC19,AF19,AI19,AL19,AO19) -> 0 | AV19: =SUM(I19,L19,O19,R19,U19,X19,AA19,AD19,AG19,AJ19,AM19,AP19) -> 3750 | AW19: =SUM(J19,M19,P19,S19,V19,Y19,AB19,AE19,AH19,AK19,AN19,AQ19) -> 0 | AX19: =SUM(H19,K19,N19) -> 0 | AY19: =SUM(I19,L19,O19) -> 0 | AZ19: =SUM(J19,M19,P19) -> 0 | BA19: =SUM(Q19,T19,W19) -> 0 | BB19: =SUM(R19,U19,X19) -> 0 | BC19: =SUM(S19,V19,Y19) -> 0 | BD19: =SUM(Z19,AC19,AF19) -> 0 | BE19: =SUM(AA19,AD19,AG19) -> 1500 | BF19: =SUM(AB19,AE19,AH19) -> 0 | BG19: =SUM(AI19,AL19,AO19) -> 0 | BH19: =SUM(AJ19,AM19,AP19) -> 2250 | BI19: =SUM(AK19,AN19,AQ19) -> 0
A20: Eventos | H20: 0 | I20: =SUM(I14:I17) -> 0 | J20: =SUM(J14:J17)+SUMIFS(Aut_Ajustes_Manuais!$G:$G,Aut_Ajustes_Manuais!$I:$I,DRE!H$4,Aut_Ajustes_Manuais!$F:$F,"Eventos") -> 0 | L20: =SUM(L14:L17) -> 0 | M20: =SUM(M14:M17)+SUMIFS(Aut_Ajustes_Manuais!$G:$G,Aut_Ajustes_Manuais!$I:$I,DRE!K$4,Aut_Ajustes_Manuais!$F:$F,"Eventos") -> 0 | O20: =SUM(O14:O17) -> 0 | P20: =SUM(P14:P17)+SUMIFS(Aut_Ajustes_Manuais!$G:$G,Aut_Ajustes_Manuais!$I:$I,DRE!N$4,Aut_Ajustes_Manuais!$F:$F,"Eventos") -> 0 | R20: =SUM(R14:R17) -> 0 | S20: =SUM(S14:S17)+SUMIFS(Aut_Ajustes_Manuais!$G:$G,Aut_Ajustes_Manuais!$I:$I,DRE!Q$4,Aut_Ajustes_Manuais!$F:$F,"Eventos") -> 0 | U20: =SUM(U14:U17) -> 0 | V20: =SUM(V14:V17)+SUMIFS(Aut_Ajustes_Manuais!$G:$G,Aut_Ajustes_Manuais!$I:$I,DRE!T$4,Aut_Ajustes_Manuais!$F:$F,"Eventos") -> 0 | X20: =SUM(X14:X17) -> 0 | Y20: =SUM(Y14:Y17)+SUMIFS(Aut_Ajustes_Manuais!$G:$G,Aut_Ajustes_Manuais!$I:$I,DRE!W$4,Aut_Ajustes_Manuais!$F:$F,"Eventos") -> 0 | AA20: =SUM(AA14:AA17) -> 0 | AB20: =SUM(AB14:AB17)+SUMIFS(Aut_Ajustes_Manuais!$G:$G,Aut_Ajustes_Manuais!$I:$I,DRE!Z$4,Aut_Ajustes_Manuais!$F:$F,"Eventos") -> 40350 | AD20: =SUM(AD14:AD17) -> 75000 | AE20: =SUM(AE14:AE17)+SUMIFS(Aut_Ajustes_Manuais!$G:$G,Aut_Ajustes_Manuais!$I:$I,DRE!AC$4,Aut_Ajustes_Manuais!$F:$F,"Eventos") -> 0 | AG20: =SUM(AG14:AG17) -> 150000 | AH20: =SUM(AH14:AH17)+SUMIFS(Aut_Ajustes_Manuais!$G:$G,Aut_Ajustes_Manuais!$I:$I,DRE!AF$4,Aut_Ajustes_Manuais!$F:$F,"Eventos") -> 0 | AJ20: =SUM(AJ14:AJ17) -> 225000 | AK20: =SUM(AK14:AK17)+SUMIFS(Aut_Ajustes_Manuais!$G:$G,Aut_Ajustes_Manuais!$I:$I,DRE!AI$4,Aut_Ajustes_Manuais!$F:$F,"Eventos") -> 0 | AM20: =SUM(AM14:AM17) -> 255000 | AN20: =SUM(AN14:AN17)+SUMIFS(Aut_Ajustes_Manuais!$G:$G,Aut_Ajustes_Manuais!$I:$I,DRE!AL$4,Aut_Ajustes_Manuais!$F:$F,"Eventos") -> 0 | AP20: =SUM(AP14:AP17) -> 692500 | AQ20: =SUM(AQ14:AQ17)+SUMIFS(Aut_Ajustes_Manuais!$G:$G,Aut_Ajustes_Manuais!$I:$I,DRE!AO$4,Aut_Ajustes_Manuais!$F:$F,"Eventos") -> 0 | AR20: =SUMIFS($H20:$AO20,$H$5:$AO$5,"<"&MONTH(TODAY()),$H$6:$AO$6,"REAL 25") -> 0 | AS20: =SUMIFS($I20:$AP20,$I$5:$AP$5,"<"&MONTH(TODAY()),$I$6:$AP$6,"ORÇADO ") -> 75000 | AT20: =SUMIFS($J20:$AQ20,$J$5:$AQ$5,"<"&MONTH(TODAY()),$J$6:$AQ$6,"REAL 26") -> 40350 | AU20: =SUM(AU14:AU17) -> 0 | AV20: =SUM(AV14:AV17) -> 1397500 | AW20: =SUM(AW14:AW17) -> 40350 | AX20: =SUM(AX14:AX17) -> 0 | AY20: =SUM(AY14:AY17) -> 0 | AZ20: =SUM(AZ14:AZ17) -> 0 | BA20: =SUM(BA14:BA17) -> 0 | BB20: =SUM(BB14:BB17) -> 0 | ... BI20: =SUM(BI14:BI17) -> 0
A21: (-) Desconto sobre Venda | C21: Premissas | D21: Valores | E21: % Incid | I21: =SUM(I22:I24) -> 0 | J21: =SUM(J22:J24)+SUMIFS(Aut_Ajustes_Manuais!$G:$G,Aut_Ajustes_Manuais!$I:$I,DRE!H$4,Aut_Ajustes_Manuais!$F:$F,"(-) Desconto sobre Venda") -> 0 | L21: =SUM(L22:L24) -> 0 | M21: =SUM(M22:M24)+SUMIFS(Aut_Ajustes_Manuais!$G:$G,Aut_Ajustes_Manuais!$I:$I,DRE!K$4,Aut_Ajustes_Manuais!$F:$F,"(-) Desconto sobre Venda") -> 0 | O21: =SUM(O22:O24) -> 0 | P21: =SUM(P22:P24)+SUMIFS(Aut_Ajustes_Manuais!$G:$G,Aut_Ajustes_Manuais!$I:$I,DRE!N$4,Aut_Ajustes_Manuais!$F:$F,"(-) Desconto sobre Venda") -> 0 | R21: =SUM(R22:R24) -> 0 | S21: =SUM(S22:S24)+SUMIFS(Aut_Ajustes_Manuais!$G:$G,Aut_Ajustes_Manuais!$I:$I,DRE!Q$4,Aut_Ajustes_Manuais!$F:$F,"(-) Desconto sobre Venda") -> 0 | U21: =SUM(U22:U24) -> 0 | V21: =SUM(V22:V24)+SUMIFS(Aut_Ajustes_Manuais!$G:$G,Aut_Ajustes_Manuais!$I:$I,DRE!T$4,Aut_Ajustes_Manuais!$F:$F,"(-) Desconto sobre Venda") -> 0 | X21: =SUM(X22:X24) -> 0 | Y21: =SUM(Y22:Y24)+SUMIFS(Aut_Ajustes_Manuais!$G:$G,Aut_Ajustes_Manuais!$I:$I,DRE!W$4,Aut_Ajustes_Manuais!$F:$F,"(-) Desconto sobre Venda") -> 0 | AA21: =SUM(AA22:AA24) -> 0 | AB21: =SUM(AB22:AB24)+SUMIFS(Aut_Ajustes_Manuais!$G:$G,Aut_Ajustes_Manuais!$I:$I,DRE!Z$4,Aut_Ajustes_Manuais!$F:$F,"(-) Desconto sobre Venda") -> 0 | AD21: =SUM(AD22:AD24) -> -125534.28 | AE21: =SUM(AE22:AE24)+SUMIFS(Aut_Ajustes_Manuais!$G:$G,Aut_Ajustes_Manuais!$I:$I,DRE!AC$4,Aut_Ajustes_Manuais!$F:$F,"(-) Desconto sobre Venda") -> 0 | AG21: =SUM(AG22:AG24) -> -119690.96 | AH21: =SUM(AH22:AH24)+SUMIFS(Aut_Ajustes_Manuais!$G:$G,Aut_Ajustes_Manuais!$I:$I,DRE!AF$4,Aut_Ajustes_Manuais!$F:$F,"(-) Desconto sobre Venda") -> 0 | AJ21: =SUM(AJ22:AJ24) -> -129428.6 | AK21: =SUM(AK22:AK24)+SUMIFS(Aut_Ajustes_Manuais!$G:$G,Aut_Ajustes_Manuais!$I:$I,DRE!AI$4,Aut_Ajustes_Manuais!$F:$F,"(-) Desconto sobre Venda") -> 0 | AM21: =SUM(AM22:AM24) -> -118167.81 | AN21: =SUM(AN22:AN24)+SUMIFS(Aut_Ajustes_Manuais!$G:$G,Aut_Ajustes_Manuais!$I:$I,DRE!AL$4,Aut_Ajustes_Manuais!$F:$F,"(-) Desconto sobre Venda") -> 0 | AP21: =SUM(AP22:AP24) -> -118038.56 | AQ21: =SUM(AQ22:AQ24)+SUMIFS(Aut_Ajustes_Manuais!$G:$G,Aut_Ajustes_Manuais!$I:$I,DRE!AO$4,Aut_Ajustes_Manuais!$F:$F,"(-) Desconto sobre Venda") -> 0 | AR21: =SUM(AR22:AR24) -> 0 | AS21: =SUM(AS22:AS24) -> -125534.28 | AT21: =SUM(AT22:AT24) -> 0 | AU21: =SUM(AU22:AU24) -> 0 | AV21: =SUM(AV22:AV24) -> -610860.21 | AW21: =SUM(AW22:AW24) -> 0 | AX21: =SUM(AX22:AX24) -> 0 | AY21: =SUM(AY22:AY24) -> 0 | ... BI21: =SUM(BI22:BI24) -> 0
A22: Descontos - Operação | C22: Estim. Mensal | D22: Alimentação OP/ Correção de Problemas | E22: 0.025 | I22: =-SUMIFS(T_ORCAMENTOS!$E:$E,T_ORCAMENTOS!$C:$C,"Descontos - Operação",T_ORCAMENTOS!$H:$H,"1/2026") -> 0 | J22: =-SUMIFS(Aut_Descontos!$F:$F,Aut_Descontos!$L:$L,DRE!H$4,Aut_Descontos!$K:$K,DRE!$A22)+SUMIFS(Aut_Ajustes_Manuais!$G:$G,Aut_Ajustes_Manuais!$I:$I,DRE!H$4,Aut_Ajustes_Manuais!$F:$F,"Descontos - Operação") -> 0 | L22: =-SUMIFS(T_ORCAMENTOS!$E:$E,T_ORCAMENTOS!$C:$C,"Descontos - Operação",T_ORCAMENTOS!$H:$H,"2/2026") -> 0 | M22: =-SUMIFS(Aut_Descontos!$F:$F,Aut_Descontos!$L:$L,DRE!K$4,Aut_Descontos!$K:$K,DRE!$A22)+SUMIFS(Aut_Ajustes_Manuais!$G:$G,Aut_Ajustes_Manuais!$I:$I,DRE!K$4,Aut_Ajustes_Manuais!$F:$F,"Descontos - Operação") -> 0 | O22: =-SUMIFS(T_ORCAMENTOS!$E:$E,T_ORCAMENTOS!$C:$C,"Descontos - Operação",T_ORCAMENTOS!$H:$H,"3/2026") -> 0 | P22: =-SUMIFS(Aut_Descontos!$F:$F,Aut_Descontos!$L:$L,DRE!N$4,Aut_Descontos!$K:$K,DRE!$A22)+SUMIFS(Aut_Ajustes_Manuais!$G:$G,Aut_Ajustes_Manuais!$I:$I,DRE!N$4,Aut_Ajustes_Manuais!$F:$F,"Descontos - Operação") -> 0 | R22: =-SUMIFS(T_ORCAMENTOS!$E:$E,T_ORCAMENTOS!$C:$C,"Descontos - Operação",T_ORCAMENTOS!$H:$H,"4/2026") -> 0 | S22: =-SUMIFS(Aut_Descontos!$F:$F,Aut_Descontos!$L:$L,DRE!Q$4,Aut_Descontos!$K:$K,DRE!$A22)+SUMIFS(Aut_Ajustes_Manuais!$G:$G,Aut_Ajustes_Manuais!$I:$I,DRE!Q$4,Aut_Ajustes_Manuais!$F:$F,"Descontos - Operação") -> 0 | U22: =-SUMIFS(T_ORCAMENTOS!$E:$E,T_ORCAMENTOS!$C:$C,"Descontos - Operação",T_ORCAMENTOS!$H:$H,"5/2026") -> 0 | V22: =-SUMIFS(Aut_Descontos!$F:$F,Aut_Descontos!$L:$L,DRE!T$4,Aut_Descontos!$K:$K,DRE!$A22)+SUMIFS(Aut_Ajustes_Manuais!$G:$G,Aut_Ajustes_Manuais!$I:$I,DRE!T$4,Aut_Ajustes_Manuais!$F:$F,"Descontos - Operação") -> 0 | X22: =-SUMIFS(T_ORCAMENTOS!$E:$E,T_ORCAMENTOS!$C:$C,"Descontos - Operação",T_ORCAMENTOS!$H:$H,"6/2026") -> 0 | Y22: =-SUMIFS(Aut_Descontos!$F:$F,Aut_Descontos!$L:$L,DRE!W$4,Aut_Descontos!$K:$K,DRE!$A22)+SUMIFS(Aut_Ajustes_Manuais!$G:$G,Aut_Ajustes_Manuais!$I:$I,DRE!W$4,Aut_Ajustes_Manuais!$F:$F,"Descontos - Operação") -> 0 | AA22: =-SUMIFS(T_ORCAMENTOS!$E:$E,T_ORCAMENTOS!$C:$C,"Descontos - Operação",T_ORCAMENTOS!$H:$H,"7/2026") -> 0 | AB22: =-SUMIFS(Aut_Descontos!$F:$F,Aut_Descontos!$L:$L,DRE!Z$4,Aut_Descontos!$K:$K,DRE!$A22)+SUMIFS(Aut_Ajustes_Manuais!$G:$G,Aut_Ajustes_Manuais!$I:$I,DRE!Z$4,Aut_Ajustes_Manuais!$F:$F,"Descontos - Operação") -> 0 | AD22: =-SUMIFS(T_ORCAMENTOS!$E:$E,T_ORCAMENTOS!$C:$C,"Descontos - Operação",T_ORCAMENTOS!$H:$H,"8/2026") -> -72225.2 | AE22: =-SUMIFS(Aut_Descontos!$F:$F,Aut_Descontos!$L:$L,DRE!AC$4,Aut_Descontos!$K:$K,DRE!$A22)+SUMIFS(Aut_Ajustes_Manuais!$G:$G,Aut_Ajustes_Manuais!$I:$I,DRE!AC$4,Aut_Ajustes_Manuais!$F:$F,"Descontos - Operação") -> 0 | AG22: =-SUMIFS(T_ORCAMENTOS!$E:$E,T_ORCAMENTOS!$C:$C,"Descontos - Operação",T_ORCAMENTOS!$H:$H,"9/2026") -> -68863.29 | AH22: =-SUMIFS(Aut_Descontos!$F:$F,Aut_Descontos!$L:$L,DRE!AF$4,Aut_Descontos!$K:$K,DRE!$A22)+SUMIFS(Aut_Ajustes_Manuais!$G:$G,Aut_Ajustes_Manuais!$I:$I,DRE!AF$4,Aut_Ajustes_Manuais!$F:$F,"Descontos - Operação") -> 0 | AJ22: =-SUMIFS(T_ORCAMENTOS!$E:$E,T_ORCAMENTOS!$C:$C,"Descontos - Operação",T_ORCAMENTOS!$H:$H,"10/2026") -> -74465.77 | AK22: =-SUMIFS(Aut_Descontos!$F:$F,Aut_Descontos!$L:$L,DRE!AI$4,Aut_Descontos!$K:$K,DRE!$A22)+SUMIFS(Aut_Ajustes_Manuais!$G:$G,Aut_Ajustes_Manuais!$I:$I,DRE!AI$4,Aut_Ajustes_Manuais!$F:$F,"Descontos - Operação") -> 0 | AM22: =-SUMIFS(T_ORCAMENTOS!$E:$E,T_ORCAMENTOS!$C:$C,"Descontos - Operação",T_ORCAMENTOS!$H:$H,"11/2026") -> -67986.96 | AN22: =-SUMIFS(Aut_Descontos!$F:$F,Aut_Descontos!$L:$L,DRE!AL$4,Aut_Descontos!$K:$K,DRE!$A22)+SUMIFS(Aut_Ajustes_Manuais!$G:$G,Aut_Ajustes_Manuais!$I:$I,DRE!AL$4,Aut_Ajustes_Manuais!$F:$F,"Descontos - Operação") -> 0 | AP22: =-SUMIFS(T_ORCAMENTOS!$E:$E,T_ORCAMENTOS!$C:$C,"Descontos - Operação",T_ORCAMENTOS!$H:$H,"12/2026") -> -67912.59 | AQ22: =-SUMIFS(Aut_Descontos!$F:$F,Aut_Descontos!$L:$L,DRE!AO$4,Aut_Descontos!$K:$K,DRE!$A22)+SUMIFS(Aut_Ajustes_Manuais!$G:$G,Aut_Ajustes_Manuais!$I:$I,DRE!AO$4,Aut_Ajustes_Manuais!$F:$F,"Descontos - Operação") -> 0 | AR22: =SUMIFS($H22:$AO22,$H$5:$AO$5,"<"&MONTH(TODAY()),$H$6:$AO$6,"REAL 25") -> 0 | AS22: =SUMIFS($I22:$AP22,$I$5:$AP$5,"<"&MONTH(TODAY()),$I$6:$AP$6,"ORÇADO ") -> -72225.2 | AT22: =SUMIFS($J22:$AQ22,$J$5:$AQ$5,"<"&MONTH(TODAY()),$J$6:$AQ$6,"REAL 26") -> 0 | AU22: =SUM(H22,K22,N22,Q22,T22,W22,Z22,AC22,AF22,AI22,AL22,AO22) -> 0 | AV22: =SUM(I22,L22,O22,R22,U22,X22,AA22,AD22,AG22,AJ22,AM22,AP22) -> -351453.81 | AW22: =SUM(J22,M22,P22,S22,V22,Y22,AB22,AE22,AH22,AK22,AN22,AQ22) -> 0 | AX22: =SUM(H22,K22,N22) -> 0 | AY22: =SUM(I22,L22,O22) -> 0 | AZ22: =SUM(J22,M22,P22) -> 0 | BA22: =SUM(Q22,T22,W22) -> 0 | BB22: =SUM(R22,U22,X22) -> 0 | BC22: =SUM(S22,V22,Y22) -> 0 | BD22: =SUM(Z22,AC22,AF22) -> 0 | BE22: =SUM(AA22,AD22,AG22) -> -141088.49 | BF22: =SUM(AB22,AE22,AH22) -> 0 | BG22: =SUM(AI22,AL22,AO22) -> 0 | BH22: =SUM(AJ22,AM22,AP22) -> -210365.32 | BI22: =SUM(AK22,AN22,AQ22) -> 0
A23: Desconto - Alimentação Escritório | C23: Estim. Mensal | D23: Cartão FB / Alimentação Escritório | E23: 0.0198 | I23: =-SUMIFS(T_ORCAMENTOS!$E:$E,T_ORCAMENTOS!$C:$C,"Desconto - Alimentação Escritório",T_ORCAMENTOS!$H:$H,"1/2026") -> 0 | J23: =-SUMIFS(Aut_Descontos!$F:$F,Aut_Descontos!$L:$L,DRE!H$4,Aut_Descontos!$K:$K,DRE!$A23)+SUMIFS(Aut_Ajustes_Manuais!$G:$G,Aut_Ajustes_Manuais!$I:$I,DRE!H$4,Aut_Ajustes_Manuais!$F:$F,"Desconto - Alimentação Escritório") -> 0 | L23: =-SUMIFS(T_ORCAMENTOS!$E:$E,T_ORCAMENTOS!$C:$C,"Desconto - Alimentação Escritório",T_ORCAMENTOS!$H:$H,"2/2026") -> 0 | M23: =-SUMIFS(Aut_Descontos!$F:$F,Aut_Descontos!$L:$L,DRE!K$4,Aut_Descontos!$K:$K,DRE!$A23)+SUMIFS(Aut_Ajustes_Manuais!$G:$G,Aut_Ajustes_Manuais!$I:$I,DRE!K$4,Aut_Ajustes_Manuais!$F:$F,"Desconto - Alimentação Escritório") -> 0 | O23: =-SUMIFS(T_ORCAMENTOS!$E:$E,T_ORCAMENTOS!$C:$C,"Desconto - Alimentação Escritório",T_ORCAMENTOS!$H:$H,"3/2026") -> 0 | P23: =-SUMIFS(Aut_Descontos!$F:$F,Aut_Descontos!$L:$L,DRE!N$4,Aut_Descontos!$K:$K,DRE!$A23)+SUMIFS(Aut_Ajustes_Manuais!$G:$G,Aut_Ajustes_Manuais!$I:$I,DRE!N$4,Aut_Ajustes_Manuais!$F:$F,"Desconto - Alimentação Escritório") -> 0 | R23: =-SUMIFS(T_ORCAMENTOS!$E:$E,T_ORCAMENTOS!$C:$C,"Desconto - Alimentação Escritório",T_ORCAMENTOS!$H:$H,"4/2026") -> 0 | S23: =-SUMIFS(Aut_Descontos!$F:$F,Aut_Descontos!$L:$L,DRE!Q$4,Aut_Descontos!$K:$K,DRE!$A23)+SUMIFS(Aut_Ajustes_Manuais!$G:$G,Aut_Ajustes_Manuais!$I:$I,DRE!Q$4,Aut_Ajustes_Manuais!$F:$F,"Desconto - Alimentação Escritório") -> 0 | U23: =-SUMIFS(T_ORCAMENTOS!$E:$E,T_ORCAMENTOS!$C:$C,"Desconto - Alimentação Escritório",T_ORCAMENTOS!$H:$H,"5/2026") -> 0 | V23: =-SUMIFS(Aut_Descontos!$F:$F,Aut_Descontos!$L:$L,DRE!T$4,Aut_Descontos!$K:$K,DRE!$A23)+SUMIFS(Aut_Ajustes_Manuais!$G:$G,Aut_Ajustes_Manuais!$I:$I,DRE!T$4,Aut_Ajustes_Manuais!$F:$F,"Desconto - Alimentação Escritório") -> 0 | X23: =-SUMIFS(T_ORCAMENTOS!$E:$E,T_ORCAMENTOS!$C:$C,"Desconto - Alimentação Escritório",T_ORCAMENTOS!$H:$H,"6/2026") -> 0 | Y23: =-SUMIFS(Aut_Descontos!$F:$F,Aut_Descontos!$L:$L,DRE!W$4,Aut_Descontos!$K:$K,DRE!$A23)+SUMIFS(Aut_Ajustes_Manuais!$G:$G,Aut_Ajustes_Manuais!$I:$I,DRE!W$4,Aut_Ajustes_Manuais!$F:$F,"Desconto - Alimentação Escritório") -> 0 | AA23: =-SUMIFS(T_ORCAMENTOS!$E:$E,T_ORCAMENTOS!$C:$C,"Desconto - Alimentação Escritório",T_ORCAMENTOS!$H:$H,"7/2026") -> 0 | AB23: =-SUMIFS(Aut_Descontos!$F:$F,Aut_Descontos!$L:$L,DRE!Z$4,Aut_Descontos!$K:$K,DRE!$A23)+SUMIFS(Aut_Ajustes_Manuais!$G:$G,Aut_Ajustes_Manuais!$I:$I,DRE!Z$4,Aut_Ajustes_Manuais!$F:$F,"Desconto - Alimentação Escritório") -> 0 | AD23: =-SUMIFS(T_ORCAMENTOS!$E:$E,T_ORCAMENTOS!$C:$C,"Desconto - Alimentação Escritório",T_ORCAMENTOS!$H:$H,"8/2026") -> -46430.49 | AE23: =-SUMIFS(Aut_Descontos!$F:$F,Aut_Descontos!$L:$L,DRE!AC$4,Aut_Descontos!$K:$K,DRE!$A23)+SUMIFS(Aut_Ajustes_Manuais!$G:$G,Aut_Ajustes_Manuais!$I:$I,DRE!AC$4,Aut_Ajustes_Manuais!$F:$F,"Desconto - Alimentação Escritório") -> 0 | AG23: =-SUMIFS(T_ORCAMENTOS!$E:$E,T_ORCAMENTOS!$C:$C,"Desconto - Alimentação Escritório",T_ORCAMENTOS!$H:$H,"9/2026") -> -44269.26 | AH23: =-SUMIFS(Aut_Descontos!$F:$F,Aut_Descontos!$L:$L,DRE!AF$4,Aut_Descontos!$K:$K,DRE!$A23)+SUMIFS(Aut_Ajustes_Manuais!$G:$G,Aut_Ajustes_Manuais!$I:$I,DRE!AF$4,Aut_Ajustes_Manuais!$F:$F,"Desconto - Alimentação Escritório") -> 0 | AJ23: =-SUMIFS(T_ORCAMENTOS!$E:$E,T_ORCAMENTOS!$C:$C,"Desconto - Alimentação Escritório",T_ORCAMENTOS!$H:$H,"10/2026") -> -47870.85 | AK23: =-SUMIFS(Aut_Descontos!$F:$F,Aut_Descontos!$L:$L,DRE!AI$4,Aut_Descontos!$K:$K,DRE!$A23)+SUMIFS(Aut_Ajustes_Manuais!$G:$G,Aut_Ajustes_Manuais!$I:$I,DRE!AI$4,Aut_Ajustes_Manuais!$F:$F,"Desconto - Alimentação Escritório") -> 0 | AM23: =-SUMIFS(T_ORCAMENTOS!$E:$E,T_ORCAMENTOS!$C:$C,"Desconto - Alimentação Escritório",T_ORCAMENTOS!$H:$H,"11/2026") -> -43705.9 | AN23: =-SUMIFS(Aut_Descontos!$F:$F,Aut_Descontos!$L:$L,DRE!AL$4,Aut_Descontos!$K:$K,DRE!$A23)+SUMIFS(Aut_Ajustes_Manuais!$G:$G,Aut_Ajustes_Manuais!$I:$I,DRE!AL$4,Aut_Ajustes_Manuais!$F:$F,"Desconto - Alimentação Escritório") -> 0 | AP23: =-SUMIFS(T_ORCAMENTOS!$E:$E,T_ORCAMENTOS!$C:$C,"Desconto - Alimentação Escritório",T_ORCAMENTOS!$H:$H,"12/2026") -> -43658.1 | AQ23: =-SUMIFS(Aut_Descontos!$F:$F,Aut_Descontos!$L:$L,DRE!AO$4,Aut_Descontos!$K:$K,DRE!$A23)+SUMIFS(Aut_Ajustes_Manuais!$G:$G,Aut_Ajustes_Manuais!$I:$I,DRE!AO$4,Aut_Ajustes_Manuais!$F:$F,"Desconto - Alimentação Escritório") -> 0 | AR23: =SUMIFS($H23:$AO23,$H$5:$AO$5,"<"&MONTH(TODAY()),$H$6:$AO$6,"REAL 25") -> 0 | AS23: =SUMIFS($I23:$AP23,$I$5:$AP$5,"<"&MONTH(TODAY()),$I$6:$AP$6,"ORÇADO ") -> -46430.49 | AT23: =SUMIFS($J23:$AQ23,$J$5:$AQ$5,"<"&MONTH(TODAY()),$J$6:$AQ$6,"REAL 26") -> 0 | AU23: =SUM(H23,K23,N23,Q23,T23,W23,Z23,AC23,AF23,AI23,AL23,AO23) -> 0 | AV23: =SUM(I23,L23,O23,R23,U23,X23,AA23,AD23,AG23,AJ23,AM23,AP23) -> -225934.6 | AW23: =SUM(J23,M23,P23,S23,V23,Y23,AB23,AE23,AH23,AK23,AN23,AQ23) -> 0 | AX23: =SUM(H23,K23,N23) -> 0 | AY23: =SUM(I23,L23,O23) -> 0 | AZ23: =SUM(J23,M23,P23) -> 0 | BA23: =SUM(Q23,T23,W23) -> 0 | BB23: =SUM(R23,U23,X23) -> 0 | BC23: =SUM(S23,V23,Y23) -> 0 | BD23: =SUM(Z23,AC23,AF23) -> 0 | BE23: =SUM(AA23,AD23,AG23) -> -90699.75 | BF23: =SUM(AB23,AE23,AH23) -> 0 | BG23: =SUM(AI23,AL23,AO23) -> 0 | BH23: =SUM(AJ23,AM23,AP23) -> -135234.85 | BI23: =SUM(AK23,AN23,AQ23) -> 0
A24: Descontos - Marketing | C24: Estim. Mensal | D24: Permutas e Ações Gerais | E24: 0.0025 | I24: =-SUMIFS(T_ORCAMENTOS!$E:$E,T_ORCAMENTOS!$C:$C,"Descontos - Marketing",T_ORCAMENTOS!$H:$H,"1/2026") -> 0 | J24: =-SUMIFS(Aut_Descontos!$F:$F,Aut_Descontos!$L:$L,DRE!H$4,Aut_Descontos!$K:$K,DRE!$A24)+SUMIFS(Aut_Ajustes_Manuais!$G:$G,Aut_Ajustes_Manuais!$I:$I,DRE!H$4,Aut_Ajustes_Manuais!$F:$F,"Descontos - Marketing") -> 0 | L24: =-SUMIFS(T_ORCAMENTOS!$E:$E,T_ORCAMENTOS!$C:$C,"Descontos - Marketing",T_ORCAMENTOS!$H:$H,"2/2026") -> 0 | M24: =-SUMIFS(Aut_Descontos!$F:$F,Aut_Descontos!$L:$L,DRE!K$4,Aut_Descontos!$K:$K,DRE!$A24)+SUMIFS(Aut_Ajustes_Manuais!$G:$G,Aut_Ajustes_Manuais!$I:$I,DRE!K$4,Aut_Ajustes_Manuais!$F:$F,"Descontos - Marketing") -> 0 | O24: =-SUMIFS(T_ORCAMENTOS!$E:$E,T_ORCAMENTOS!$C:$C,"Descontos - Marketing",T_ORCAMENTOS!$H:$H,"3/2026") -> 0 | P24: =-SUMIFS(Aut_Descontos!$F:$F,Aut_Descontos!$L:$L,DRE!N$4,Aut_Descontos!$K:$K,DRE!$A24)+SUMIFS(Aut_Ajustes_Manuais!$G:$G,Aut_Ajustes_Manuais!$I:$I,DRE!N$4,Aut_Ajustes_Manuais!$F:$F,"Descontos - Marketing") -> 0 | R24: =-SUMIFS(T_ORCAMENTOS!$E:$E,T_ORCAMENTOS!$C:$C,"Descontos - Marketing",T_ORCAMENTOS!$H:$H,"4/2026") -> 0 | S24: =-SUMIFS(Aut_Descontos!$F:$F,Aut_Descontos!$L:$L,DRE!Q$4,Aut_Descontos!$K:$K,DRE!$A24)+SUMIFS(Aut_Ajustes_Manuais!$G:$G,Aut_Ajustes_Manuais!$I:$I,DRE!Q$4,Aut_Ajustes_Manuais!$F:$F,"Descontos - Marketing") -> 0 | U24: =-SUMIFS(T_ORCAMENTOS!$E:$E,T_ORCAMENTOS!$C:$C,"Descontos - Marketing",T_ORCAMENTOS!$H:$H,"5/2026") -> 0 | V24: =-SUMIFS(Aut_Descontos!$F:$F,Aut_Descontos!$L:$L,DRE!T$4,Aut_Descontos!$K:$K,DRE!$A24)+SUMIFS(Aut_Ajustes_Manuais!$G:$G,Aut_Ajustes_Manuais!$I:$I,DRE!T$4,Aut_Ajustes_Manuais!$F:$F,"Descontos - Marketing") -> 0 | X24: =-SUMIFS(T_ORCAMENTOS!$E:$E,T_ORCAMENTOS!$C:$C,"Descontos - Marketing",T_ORCAMENTOS!$H:$H,"6/2026") -> 0 | Y24: =-SUMIFS(Aut_Descontos!$F:$F,Aut_Descontos!$L:$L,DRE!W$4,Aut_Descontos!$K:$K,DRE!$A24)+SUMIFS(Aut_Ajustes_Manuais!$G:$G,Aut_Ajustes_Manuais!$I:$I,DRE!W$4,Aut_Ajustes_Manuais!$F:$F,"Descontos - Marketing") -> 0 | AA24: =-SUMIFS(T_ORCAMENTOS!$E:$E,T_ORCAMENTOS!$C:$C,"Descontos - Marketing",T_ORCAMENTOS!$H:$H,"7/2026") -> 0 | AB24: =-SUMIFS(Aut_Descontos!$F:$F,Aut_Descontos!$L:$L,DRE!Z$4,Aut_Descontos!$K:$K,DRE!$A24)+SUMIFS(Aut_Ajustes_Manuais!$G:$G,Aut_Ajustes_Manuais!$I:$I,DRE!Z$4,Aut_Ajustes_Manuais!$F:$F,"Descontos - Marketing") -> 0 | AD24: =-SUMIFS(T_ORCAMENTOS!$E:$E,T_ORCAMENTOS!$C:$C,"Descontos - Marketing",T_ORCAMENTOS!$H:$H,"8/2026") -> -6878.59 | AE24: =-SUMIFS(Aut_Descontos!$F:$F,Aut_Descontos!$L:$L,DRE!AC$4,Aut_Descontos!$K:$K,DRE!$A24)+SUMIFS(Aut_Ajustes_Manuais!$G:$G,Aut_Ajustes_Manuais!$I:$I,DRE!AC$4,Aut_Ajustes_Manuais!$F:$F,"Descontos - Marketing") -> 0 | AG24: =-SUMIFS(T_ORCAMENTOS!$E:$E,T_ORCAMENTOS!$C:$C,"Descontos - Marketing",T_ORCAMENTOS!$H:$H,"9/2026") -> -6558.41 | AH24: =-SUMIFS(Aut_Descontos!$F:$F,Aut_Descontos!$L:$L,DRE!AF$4,Aut_Descontos!$K:$K,DRE!$A24)+SUMIFS(Aut_Ajustes_Manuais!$G:$G,Aut_Ajustes_Manuais!$I:$I,DRE!AF$4,Aut_Ajustes_Manuais!$F:$F,"Descontos - Marketing") -> 0 | AJ24: =-SUMIFS(T_ORCAMENTOS!$E:$E,T_ORCAMENTOS!$C:$C,"Descontos - Marketing",T_ORCAMENTOS!$H:$H,"10/2026") -> -7091.98 | AK24: =-SUMIFS(Aut_Descontos!$F:$F,Aut_Descontos!$L:$L,DRE!AI$4,Aut_Descontos!$K:$K,DRE!$A24)+SUMIFS(Aut_Ajustes_Manuais!$G:$G,Aut_Ajustes_Manuais!$I:$I,DRE!AI$4,Aut_Ajustes_Manuais!$F:$F,"Descontos - Marketing") -> 0 | AM24: =-SUMIFS(T_ORCAMENTOS!$E:$E,T_ORCAMENTOS!$C:$C,"Descontos - Marketing",T_ORCAMENTOS!$H:$H,"11/2026") -> -6474.95 | AN24: =-SUMIFS(Aut_Descontos!$F:$F,Aut_Descontos!$L:$L,DRE!AL$4,Aut_Descontos!$K:$K,DRE!$A24)+SUMIFS(Aut_Ajustes_Manuais!$G:$G,Aut_Ajustes_Manuais!$I:$I,DRE!AL$4,Aut_Ajustes_Manuais!$F:$F,"Descontos - Marketing") -> 0 | AP24: =-SUMIFS(T_ORCAMENTOS!$E:$E,T_ORCAMENTOS!$C:$C,"Descontos - Marketing",T_ORCAMENTOS!$H:$H,"12/2026") -> -6467.87 | AQ24: =-SUMIFS(Aut_Descontos!$F:$F,Aut_Descontos!$L:$L,DRE!AO$4,Aut_Descontos!$K:$K,DRE!$A24)+SUMIFS(Aut_Ajustes_Manuais!$G:$G,Aut_Ajustes_Manuais!$I:$I,DRE!AO$4,Aut_Ajustes_Manuais!$F:$F,"Descontos - Marketing") -> 0 | AR24: =SUMIFS($H24:$AO24,$H$5:$AO$5,"<"&MONTH(TODAY()),$H$6:$AO$6,"REAL 25") -> 0 | AS24: =SUMIFS($I24:$AP24,$I$5:$AP$5,"<"&MONTH(TODAY()),$I$6:$AP$6,"ORÇADO ") -> -6878.59 | AT24: =SUMIFS($J24:$AQ24,$J$5:$AQ$5,"<"&MONTH(TODAY()),$J$6:$AQ$6,"REAL 26") -> 0 | AU24: =SUM(H24,K24,N24,Q24,T24,W24,Z24,AC24,AF24,AI24,AL24,AO24) -> 0 | AV24: =SUM(I24,L24,O24,R24,U24,X24,AA24,AD24,AG24,AJ24,AM24,AP24) -> -33471.8 | AW24: =SUM(J24,M24,P24,S24,V24,Y24,AB24,AE24,AH24,AK24,AN24,AQ24) -> 0 | AX24: =SUM(H24,K24,N24) -> 0 | AY24: =SUM(I24,L24,O24) -> 0 | AZ24: =SUM(J24,M24,P24) -> 0 | BA24: =SUM(Q24,T24,W24) -> 0 | BB24: =SUM(R24,U24,X24) -> 0 | BC24: =SUM(S24,V24,Y24) -> 0 | BD24: =SUM(Z24,AC24,AF24) -> 0 | BE24: =SUM(AA24,AD24,AG24) -> -13437 | BF24: =SUM(AB24,AE24,AH24) -> 0 | BG24: =SUM(AI24,AL24,AO24) -> 0 | BH24: =SUM(AJ24,AM24,AP24) -> -20034.8 | BI24: =SUM(AK24,AN24,AQ24) -> 0
A25: % sobre Receita Bruta | I25: =IFERROR(I21/I8,0) -> 0 | J25: =IFERROR(J21/J8,0)+SUMIFS(Aut_Ajustes_Manuais!$G:$G,Aut_Ajustes_Manuais!$I:$I,DRE!H$4,Aut_Ajustes_Manuais!$F:$F,"% sobre Receita Bruta") -> 0 | L25: =IFERROR(L21/L8,0) -> 0 | M25: =IFERROR(M21/M8,0)+SUMIFS(Aut_Ajustes_Manuais!$G:$G,Aut_Ajustes_Manuais!$I:$I,DRE!K$4,Aut_Ajustes_Manuais!$F:$F,"% sobre Receita Bruta") -> 0 | O25: =IFERROR(O21/O8,0) -> 0 | P25: =IFERROR(P21/P8,0)+SUMIFS(Aut_Ajustes_Manuais!$G:$G,Aut_Ajustes_Manuais!$I:$I,DRE!N$4,Aut_Ajustes_Manuais!$F:$F,"% sobre Receita Bruta") -> 0 | R25: =IFERROR(R21/R8,0) -> 0 | S25: =IFERROR(S21/S8,0)+SUMIFS(Aut_Ajustes_Manuais!$G:$G,Aut_Ajustes_Manuais!$I:$I,DRE!Q$4,Aut_Ajustes_Manuais!$F:$F,"% sobre Receita Bruta") -> 0 | U25: =IFERROR(U21/U8,0) -> 0 | V25: =IFERROR(V21/V8,0)+SUMIFS(Aut_Ajustes_Manuais!$G:$G,Aut_Ajustes_Manuais!$I:$I,DRE!T$4,Aut_Ajustes_Manuais!$F:$F,"% sobre Receita Bruta") -> 0 | X25: =IFERROR(X21/X8,0) -> 0 | Y25: =IFERROR(Y21/Y8,0)+SUMIFS(Aut_Ajustes_Manuais!$G:$G,Aut_Ajustes_Manuais!$I:$I,DRE!W$4,Aut_Ajustes_Manuais!$F:$F,"% sobre Receita Bruta") -> 0 | AA25: =IFERROR(AA21/AA8,0) -> 0 | AB25: =IFERROR(AB21/AB8,0)+SUMIFS(Aut_Ajustes_Manuais!$G:$G,Aut_Ajustes_Manuais!$I:$I,DRE!Z$4,Aut_Ajustes_Manuais!$F:$F,"% sobre Receita Bruta") -> 0 | AD25: =IFERROR(AD21/AD8,0) -> -0.026209956 | AE25: =IFERROR(AE21/AE8,0)+SUMIFS(Aut_Ajustes_Manuais!$G:$G,Aut_Ajustes_Manuais!$I:$I,DRE!AC$4,Aut_Ajustes_Manuais!$F:$F,"% sobre Receita Bruta") -> 0 | AG25: =IFERROR(AG21/AG8,0) -> -0.025793917 | AH25: =IFERROR(AH21/AH8,0)+SUMIFS(Aut_Ajustes_Manuais!$G:$G,Aut_Ajustes_Manuais!$I:$I,DRE!AF$4,Aut_Ajustes_Manuais!$F:$F,"% sobre Receita Bruta") -> 0 | AJ25: =IFERROR(AJ21/AJ8,0) -> -0.025412787 | AK25: =IFERROR(AK21/AK8,0)+SUMIFS(Aut_Ajustes_Manuais!$G:$G,Aut_Ajustes_Manuais!$I:$I,DRE!AI$4,Aut_Ajustes_Manuais!$F:$F,"% sobre Receita Bruta") -> 0 | AM25: =IFERROR(AM21/AM8,0) -> -0.025186239 | AN25: =IFERROR(AN21/AN8,0)+SUMIFS(Aut_Ajustes_Manuais!$G:$G,Aut_Ajustes_Manuais!$I:$I,DRE!AL$4,Aut_Ajustes_Manuais!$F:$F,"% sobre Receita Bruta") -> 0 | AP25: =IFERROR(AP21/AP8,0) -> -0.023092624 | AQ25: =IFERROR(AQ21/AQ8,0)+SUMIFS(Aut_Ajustes_Manuais!$G:$G,Aut_Ajustes_Manuais!$I:$I,DRE!AO$4,Aut_Ajustes_Manuais!$F:$F,"% sobre Receita Bruta") -> 0 | AR25: =IFERROR(AR21/AR8,0) -> 0 | AS25: =IFERROR(AS21/AS8,0) -> -0.026209956 | AT25: =IFERROR(AT21/AT8,0) -> 0 | AU25: =IFERROR(AU21/AU8,0) -> 0 | AV25: =IFERROR(AV21/AV8,0) -> -0.025111225 | AW25: =IFERROR(AW21/AW8,0) -> 0 | AX25: =IFERROR(AX21/AX8,0) -> 0 | AY25: =IFERROR(AY21/AY8,0) -> 0 | ... BI25: =IFERROR(BI21/BI8,0) -> 0
A27: (-) Impostos sobre Venda | C27: Premissas | D27: Valores | E27: % Incid | I27: =SUM(I28:I30) -> 0 | J27: =SUM(J28:J30)+SUMIFS(Aut_Ajustes_Manuais!$G:$G,Aut_Ajustes_Manuais!$I:$I,DRE!H$4,Aut_Ajustes_Manuais!$F:$F,"(-) Impostos sobre Venda") -> 0 | L27: =SUM(L28:L30) -> 0 | M27: =SUM(M28:M30)+SUMIFS(Aut_Ajustes_Manuais!$G:$G,Aut_Ajustes_Manuais!$I:$I,DRE!K$4,Aut_Ajustes_Manuais!$F:$F,"(-) Impostos sobre Venda") -> 0 | O27: =SUM(O28:O30) -> 0 | P27: =SUM(P28:P30)+SUMIFS(Aut_Ajustes_Manuais!$G:$G,Aut_Ajustes_Manuais!$I:$I,DRE!N$4,Aut_Ajustes_Manuais!$F:$F,"(-) Impostos sobre Venda") -> 0 | R27: =SUM(R28:R30) -> 0 | S27: =SUM(S28:S30)+SUMIFS(Aut_Ajustes_Manuais!$G:$G,Aut_Ajustes_Manuais!$I:$I,DRE!Q$4,Aut_Ajustes_Manuais!$F:$F,"(-) Impostos sobre Venda") -> 0 | U27: =SUM(U28:U30) -> 0 | V27: =SUM(V28:V30)+SUMIFS(Aut_Ajustes_Manuais!$G:$G,Aut_Ajustes_Manuais!$I:$I,DRE!T$4,Aut_Ajustes_Manuais!$F:$F,"(-) Impostos sobre Venda") -> 0 | X27: =SUM(X28:X30) -> 0 | Y27: =SUM(Y28:Y30)+SUMIFS(Aut_Ajustes_Manuais!$G:$G,Aut_Ajustes_Manuais!$I:$I,DRE!W$4,Aut_Ajustes_Manuais!$F:$F,"(-) Impostos sobre Venda") -> 0 | AA27: =SUM(AA28:AA30) -> 0 | AB27: =SUM(AB28:AB30)+SUMIFS(Aut_Ajustes_Manuais!$G:$G,Aut_Ajustes_Manuais!$I:$I,DRE!Z$4,Aut_Ajustes_Manuais!$F:$F,"(-) Impostos sobre Venda") -> -23512.088 | AD27: =SUM(AD28:AD30) -> -328968.95 | AE27: =SUM(AE28:AE30)+SUMIFS(Aut_Ajustes_Manuais!$G:$G,Aut_Ajustes_Manuais!$I:$I,DRE!AC$4,Aut_Ajustes_Manuais!$F:$F,"(-) Impostos sobre Venda") -> 0 | AG27: =SUM(AG28:AG30) -> -319514.72 | AH27: =SUM(AH28:AH30)+SUMIFS(Aut_Ajustes_Manuais!$G:$G,Aut_Ajustes_Manuais!$I:$I,DRE!AF$4,Aut_Ajustes_Manuais!$F:$F,"(-) Impostos sobre Venda") -> 0 | AJ27: =SUM(AJ28:AJ30) -> -351379.54 | AK27: =SUM(AK28:AK30)+SUMIFS(Aut_Ajustes_Manuais!$G:$G,Aut_Ajustes_Manuais!$I:$I,DRE!AI$4,Aut_Ajustes_Manuais!$F:$F,"(-) Impostos sobre Venda") -> 0 | AM27: =SUM(AM28:AM30) -> -324176.4 | AN27: =SUM(AN28:AN30)+SUMIFS(Aut_Ajustes_Manuais!$G:$G,Aut_Ajustes_Manuais!$I:$I,DRE!AL$4,Aut_Ajustes_Manuais!$F:$F,"(-) Impostos sobre Venda") -> 0 | AP27: =SUM(AP28:AP30) -> -357462.44 | AQ27: =SUM(AQ28:AQ30)+SUMIFS(Aut_Ajustes_Manuais!$G:$G,Aut_Ajustes_Manuais!$I:$I,DRE!AO$4,Aut_Ajustes_Manuais!$F:$F,"(-) Impostos sobre Venda") -> 0 | AR27: =SUM(AR28:AR30) -> 0 | AS27: =SUM(AS28:AS30) -> -328968.95 | AT27: =SUM(AT28:AT30) -> -23512.088 | AU27: =SUM(AU28:AU30) -> 0 | AV27: =SUM(AV28:AV30) -> -1681502 | AW27: =SUM(AW28:AW30) -> -23512.088 | AX27: =SUM(AX28:AX30) -> 0 | AY27: =SUM(AY28:AY30) -> 0 | ... BI27: =SUM(BI28:BI30) -> 0
A28: PIS / COFINS | C28: Base Fiscal | E28: 0.0365 | I28: =-SUMIFS(T_ORCAMENTOS!$E:$E,T_ORCAMENTOS!$C:$C,"PIS / COFINS",T_ORCAMENTOS!$H:$H,"1/2026") -> 0 | J28: =-Fiscal!D21-Fiscal!D22+SUMIFS(Aut_Ajustes_Manuais!$G:$G,Aut_Ajustes_Manuais!$I:$I,DRE!H$4,Aut_Ajustes_Manuais!$F:$F,"PIS / COFINS") -> 0 | L28: =-SUMIFS(T_ORCAMENTOS!$E:$E,T_ORCAMENTOS!$C:$C,"PIS / COFINS",T_ORCAMENTOS!$H:$H,"2/2026") -> 0 | M28: =-Fiscal!E21-Fiscal!E22+SUMIFS(Aut_Ajustes_Manuais!$G:$G,Aut_Ajustes_Manuais!$I:$I,DRE!K$4,Aut_Ajustes_Manuais!$F:$F,"PIS / COFINS") -> 0 | O28: =-SUMIFS(T_ORCAMENTOS!$E:$E,T_ORCAMENTOS!$C:$C,"PIS / COFINS",T_ORCAMENTOS!$H:$H,"3/2026") -> 0 | P28: =-Fiscal!F21-Fiscal!F22+SUMIFS(Aut_Ajustes_Manuais!$G:$G,Aut_Ajustes_Manuais!$I:$I,DRE!N$4,Aut_Ajustes_Manuais!$F:$F,"PIS / COFINS") -> 0 | R28: =-SUMIFS(T_ORCAMENTOS!$E:$E,T_ORCAMENTOS!$C:$C,"PIS / COFINS",T_ORCAMENTOS!$H:$H,"4/2026") -> 0 | S28: =-Fiscal!H21-Fiscal!H22+SUMIFS(Aut_Ajustes_Manuais!$G:$G,Aut_Ajustes_Manuais!$I:$I,DRE!Q$4,Aut_Ajustes_Manuais!$F:$F,"PIS / COFINS") -> 0 | U28: =-SUMIFS(T_ORCAMENTOS!$E:$E,T_ORCAMENTOS!$C:$C,"PIS / COFINS",T_ORCAMENTOS!$H:$H,"5/2026") -> 0 | V28: =-Fiscal!I21-Fiscal!I22+SUMIFS(Aut_Ajustes_Manuais!$G:$G,Aut_Ajustes_Manuais!$I:$I,DRE!T$4,Aut_Ajustes_Manuais!$F:$F,"PIS / COFINS") -> 0 | X28: =-SUMIFS(T_ORCAMENTOS!$E:$E,T_ORCAMENTOS!$C:$C,"PIS / COFINS",T_ORCAMENTOS!$H:$H,"6/2026") -> 0 | Y28: =-Fiscal!J21-Fiscal!J22+SUMIFS(Aut_Ajustes_Manuais!$G:$G,Aut_Ajustes_Manuais!$I:$I,DRE!W$4,Aut_Ajustes_Manuais!$F:$F,"PIS / COFINS") -> 0 | AA28: =-SUMIFS(T_ORCAMENTOS!$E:$E,T_ORCAMENTOS!$C:$C,"PIS / COFINS",T_ORCAMENTOS!$H:$H,"7/2026") -> 0 | AB28: =-Fiscal!L21-Fiscal!L22+SUMIFS(Aut_Ajustes_Manuais!$G:$G,Aut_Ajustes_Manuais!$I:$I,DRE!Z$4,Aut_Ajustes_Manuais!$F:$F,"PIS / COFINS") -> -10926.46 | AD28: =-SUMIFS(T_ORCAMENTOS!$E:$E,T_ORCAMENTOS!$C:$C,"PIS / COFINS",T_ORCAMENTOS!$H:$H,"8/2026") -> -153432.4 | AE28: =-Fiscal!M21-Fiscal!M22+SUMIFS(Aut_Ajustes_Manuais!$G:$G,Aut_Ajustes_Manuais!$I:$I,DRE!AC$4,Aut_Ajustes_Manuais!$F:$F,"PIS / COFINS") -> 0 | AG28: =-SUMIFS(T_ORCAMENTOS!$E:$E,T_ORCAMENTOS!$C:$C,"PIS / COFINS",T_ORCAMENTOS!$H:$H,"9/2026") -> -148915.59 | AH28: =-Fiscal!N21-Fiscal!N22+SUMIFS(Aut_Ajustes_Manuais!$G:$G,Aut_Ajustes_Manuais!$I:$I,DRE!AF$4,Aut_Ajustes_Manuais!$F:$F,"PIS / COFINS") -> 0 | AJ28: =-SUMIFS(T_ORCAMENTOS!$E:$E,T_ORCAMENTOS!$C:$C,"PIS / COFINS",T_ORCAMENTOS!$H:$H,"10/2026") -> -163692.75 | AK28: =-Fiscal!P21-Fiscal!P22+SUMIFS(Aut_Ajustes_Manuais!$G:$G,Aut_Ajustes_Manuais!$I:$I,DRE!AI$4,Aut_Ajustes_Manuais!$F:$F,"PIS / COFINS") -> 0 | AM28: =-SUMIFS(T_ORCAMENTOS!$E:$E,T_ORCAMENTOS!$C:$C,"PIS / COFINS",T_ORCAMENTOS!$H:$H,"11/2026") -> -150949.36 | AN28: =-Fiscal!Q21-Fiscal!Q22+SUMIFS(Aut_Ajustes_Manuais!$G:$G,Aut_Ajustes_Manuais!$I:$I,DRE!AL$4,Aut_Ajustes_Manuais!$F:$F,"PIS / COFINS") -> 0 | AP28: =-SUMIFS(T_ORCAMENTOS!$E:$E,T_ORCAMENTOS!$C:$C,"PIS / COFINS",T_ORCAMENTOS!$H:$H,"12/2026") -> -165896.46 | AQ28: =-Fiscal!R21-Fiscal!R22+SUMIFS(Aut_Ajustes_Manuais!$G:$G,Aut_Ajustes_Manuais!$I:$I,DRE!AO$4,Aut_Ajustes_Manuais!$F:$F,"PIS / COFINS") -> 0 | AR28: =SUMIFS($H28:$AO28,$H$5:$AO$5,"<"&MONTH(TODAY()),$H$6:$AO$6,"REAL 25") -> 0 | AS28: =SUMIFS($I28:$AP28,$I$5:$AP$5,"<"&MONTH(TODAY()),$I$6:$AP$6,"ORÇADO ") -> -153432.4 | AT28: =SUMIFS($J28:$AQ28,$J$5:$AQ$5,"<"&MONTH(TODAY()),$J$6:$AQ$6,"REAL 26") -> -10926.46 | AU28: =SUM(H28,K28,N28,Q28,T28,W28,Z28,AC28,AF28,AI28,AL28,AO28) -> 0 | AV28: =SUM(I28,L28,O28,R28,U28,X28,AA28,AD28,AG28,AJ28,AM28,AP28) -> -782886.56 | AW28: =SUM(J28,M28,P28,S28,V28,Y28,AB28,AE28,AH28,AK28,AN28,AQ28) -> -10926.46 | AX28: =SUM(H28,K28,N28) -> 0 | AY28: =SUM(I28,L28,O28) -> 0 | AZ28: =SUM(J28,M28,P28) -> 0 | BA28: =SUM(Q28,T28,W28) -> 0 | BB28: =SUM(R28,U28,X28) -> 0 | BC28: =SUM(S28,V28,Y28) -> 0 | BD28: =SUM(Z28,AC28,AF28) -> 0 | BE28: =SUM(AA28,AD28,AG28) -> -302347.99 | BF28: =SUM(AB28,AE28,AH28) -> -10926.46 | BG28: =SUM(AI28,AL28,AO28) -> 0 | BH28: =SUM(AJ28,AM28,AP28) -> -480538.57 | BI28: =SUM(AK28,AN28,AQ28) -> 0
A29: ICMS | C29: Base Fiscal | E29: 0.04 | I29: =-SUMIFS(T_ORCAMENTOS!$E:$E,T_ORCAMENTOS!$C:$C,"ICMS",T_ORCAMENTOS!$H:$H,"1/2026") -> 0 | J29: =-Fiscal!D23+SUMIFS(Aut_Ajustes_Manuais!$G:$G,Aut_Ajustes_Manuais!$I:$I,DRE!H$4,Aut_Ajustes_Manuais!$F:$F,"ICMS") -> 0 | L29: =-SUMIFS(T_ORCAMENTOS!$E:$E,T_ORCAMENTOS!$C:$C,"ICMS",T_ORCAMENTOS!$H:$H,"2/2026") -> 0 | M29: =-Fiscal!E23+SUMIFS(Aut_Ajustes_Manuais!$G:$G,Aut_Ajustes_Manuais!$I:$I,DRE!K$4,Aut_Ajustes_Manuais!$F:$F,"ICMS") -> 0 | O29: =-SUMIFS(T_ORCAMENTOS!$E:$E,T_ORCAMENTOS!$C:$C,"ICMS",T_ORCAMENTOS!$H:$H,"3/2026") -> 0 | P29: =-Fiscal!F23+SUMIFS(Aut_Ajustes_Manuais!$G:$G,Aut_Ajustes_Manuais!$I:$I,DRE!N$4,Aut_Ajustes_Manuais!$F:$F,"ICMS") -> 0 | R29: =-SUMIFS(T_ORCAMENTOS!$E:$E,T_ORCAMENTOS!$C:$C,"ICMS",T_ORCAMENTOS!$H:$H,"4/2026") -> 0 | S29: =-Fiscal!H23+SUMIFS(Aut_Ajustes_Manuais!$G:$G,Aut_Ajustes_Manuais!$I:$I,DRE!Q$4,Aut_Ajustes_Manuais!$F:$F,"ICMS") -> 0 | U29: =-SUMIFS(T_ORCAMENTOS!$E:$E,T_ORCAMENTOS!$C:$C,"ICMS",T_ORCAMENTOS!$H:$H,"5/2026") -> 0 | V29: =-Fiscal!I23+SUMIFS(Aut_Ajustes_Manuais!$G:$G,Aut_Ajustes_Manuais!$I:$I,DRE!T$4,Aut_Ajustes_Manuais!$F:$F,"ICMS") -> 0 | X29: =-SUMIFS(T_ORCAMENTOS!$E:$E,T_ORCAMENTOS!$C:$C,"ICMS",T_ORCAMENTOS!$H:$H,"6/2026") -> 0 | Y29: =-Fiscal!J23+SUMIFS(Aut_Ajustes_Manuais!$G:$G,Aut_Ajustes_Manuais!$I:$I,DRE!W$4,Aut_Ajustes_Manuais!$F:$F,"ICMS") -> 0 | AA29: =-SUMIFS(T_ORCAMENTOS!$E:$E,T_ORCAMENTOS!$C:$C,"ICMS",T_ORCAMENTOS!$H:$H,"7/2026") -> 0 | AB29: =-Fiscal!L23+SUMIFS(Aut_Ajustes_Manuais!$G:$G,Aut_Ajustes_Manuais!$I:$I,DRE!Z$4,Aut_Ajustes_Manuais!$F:$F,"ICMS") -> -11910.628 | AD29: =-SUMIFS(T_ORCAMENTOS!$E:$E,T_ORCAMENTOS!$C:$C,"ICMS",T_ORCAMENTOS!$H:$H,"8/2026") -> -173224.05 | AE29: =-Fiscal!M23+SUMIFS(Aut_Ajustes_Manuais!$G:$G,Aut_Ajustes_Manuais!$I:$I,DRE!AC$4,Aut_Ajustes_Manuais!$F:$F,"ICMS") -> 0 | AG29: =-SUMIFS(T_ORCAMENTOS!$E:$E,T_ORCAMENTOS!$C:$C,"ICMS",T_ORCAMENTOS!$H:$H,"9/2026") -> -166974.13 | AH29: =-Fiscal!N23+SUMIFS(Aut_Ajustes_Manuais!$G:$G,Aut_Ajustes_Manuais!$I:$I,DRE!AF$4,Aut_Ajustes_Manuais!$F:$F,"ICMS") -> 0 | AJ29: =-SUMIFS(T_ORCAMENTOS!$E:$E,T_ORCAMENTOS!$C:$C,"ICMS",T_ORCAMENTOS!$H:$H,"10/2026") -> -182749.29 | AK29: =-Fiscal!P23+SUMIFS(Aut_Ajustes_Manuais!$G:$G,Aut_Ajustes_Manuais!$I:$I,DRE!AI$4,Aut_Ajustes_Manuais!$F:$F,"ICMS") -> 0 | AM29: =-SUMIFS(T_ORCAMENTOS!$E:$E,T_ORCAMENTOS!$C:$C,"ICMS",T_ORCAMENTOS!$H:$H,"11/2026") -> -167764.54 | AN29: =-Fiscal!Q23+SUMIFS(Aut_Ajustes_Manuais!$G:$G,Aut_Ajustes_Manuais!$I:$I,DRE!AL$4,Aut_Ajustes_Manuais!$F:$F,"ICMS") -> 0 | AP29: =-SUMIFS(T_ORCAMENTOS!$E:$E,T_ORCAMENTOS!$C:$C,"ICMS",T_ORCAMENTOS!$H:$H,"12/2026") -> -178447.23 | AQ29: =-Fiscal!R23+SUMIFS(Aut_Ajustes_Manuais!$G:$G,Aut_Ajustes_Manuais!$I:$I,DRE!AO$4,Aut_Ajustes_Manuais!$F:$F,"ICMS") -> 0 | AR29: =SUMIFS($H29:$AO29,$H$5:$AO$5,"<"&MONTH(TODAY()),$H$6:$AO$6,"REAL 25") -> 0 | AS29: =SUMIFS($I29:$AP29,$I$5:$AP$5,"<"&MONTH(TODAY()),$I$6:$AP$6,"ORÇADO ") -> -173224.05 | AT29: =SUMIFS($J29:$AQ29,$J$5:$AQ$5,"<"&MONTH(TODAY()),$J$6:$AQ$6,"REAL 26") -> -11910.628 | AU29: =SUM(H29,K29,N29,Q29,T29,W29,Z29,AC29,AF29,AI29,AL29,AO29) -> 0 | AV29: =SUM(I29,L29,O29,R29,U29,X29,AA29,AD29,AG29,AJ29,AM29,AP29) -> -869159.24 | AW29: =SUM(J29,M29,P29,S29,V29,Y29,AB29,AE29,AH29,AK29,AN29,AQ29) -> -11910.628 | AX29: =SUM(H29,K29,N29) -> 0 | AY29: =SUM(I29,L29,O29) -> 0 | AZ29: =SUM(J29,M29,P29) -> 0 | BA29: =SUM(Q29,T29,W29) -> 0 | BB29: =SUM(R29,U29,X29) -> 0 | BC29: =SUM(S29,V29,Y29) -> 0 | BD29: =SUM(Z29,AC29,AF29) -> 0 | BE29: =SUM(AA29,AD29,AG29) -> -340198.18 | BF29: =SUM(AB29,AE29,AH29) -> -11910.628 | BG29: =SUM(AI29,AL29,AO29) -> 0 | BH29: =SUM(AJ29,AM29,AP29) -> -528961.06 | BI29: =SUM(AK29,AN29,AQ29) -> 0
A30: ISS | C30: Base Fiscal | E30: 0.05 | I30: =-SUMIFS(T_ORCAMENTOS!$E:$E,T_ORCAMENTOS!$C:$C,"ISS",T_ORCAMENTOS!$H:$H,"1/2026") -> 0 | J30: =-Fiscal!D20+SUMIFS(Aut_Ajustes_Manuais!$G:$G,Aut_Ajustes_Manuais!$I:$I,DRE!H$4,Aut_Ajustes_Manuais!$F:$F,"ISS") -> 0 | L30: =-SUMIFS(T_ORCAMENTOS!$E:$E,T_ORCAMENTOS!$C:$C,"ISS",T_ORCAMENTOS!$H:$H,"2/2026") -> 0 | M30: =-Fiscal!E20+SUMIFS(Aut_Ajustes_Manuais!$G:$G,Aut_Ajustes_Manuais!$I:$I,DRE!K$4,Aut_Ajustes_Manuais!$F:$F,"ISS") -> 0 | O30: =-SUMIFS(T_ORCAMENTOS!$E:$E,T_ORCAMENTOS!$C:$C,"ISS",T_ORCAMENTOS!$H:$H,"3/2026") -> 0 | P30: =-Fiscal!F20+SUMIFS(Aut_Ajustes_Manuais!$G:$G,Aut_Ajustes_Manuais!$I:$I,DRE!N$4,Aut_Ajustes_Manuais!$F:$F,"ISS") -> 0 | R30: =-SUMIFS(T_ORCAMENTOS!$E:$E,T_ORCAMENTOS!$C:$C,"ISS",T_ORCAMENTOS!$H:$H,"4/2026") -> 0 | S30: =-Fiscal!H20+SUMIFS(Aut_Ajustes_Manuais!$G:$G,Aut_Ajustes_Manuais!$I:$I,DRE!Q$4,Aut_Ajustes_Manuais!$F:$F,"ISS") -> 0 | U30: =-SUMIFS(T_ORCAMENTOS!$E:$E,T_ORCAMENTOS!$C:$C,"ISS",T_ORCAMENTOS!$H:$H,"5/2026") -> 0 | V30: =-Fiscal!I20+SUMIFS(Aut_Ajustes_Manuais!$G:$G,Aut_Ajustes_Manuais!$I:$I,DRE!T$4,Aut_Ajustes_Manuais!$F:$F,"ISS") -> 0 | X30: =-SUMIFS(T_ORCAMENTOS!$E:$E,T_ORCAMENTOS!$C:$C,"ISS",T_ORCAMENTOS!$H:$H,"6/2026") -> 0 | Y30: =-Fiscal!J20+SUMIFS(Aut_Ajustes_Manuais!$G:$G,Aut_Ajustes_Manuais!$I:$I,DRE!W$4,Aut_Ajustes_Manuais!$F:$F,"ISS") -> 0 | AA30: =-SUMIFS(T_ORCAMENTOS!$E:$E,T_ORCAMENTOS!$C:$C,"ISS",T_ORCAMENTOS!$H:$H,"7/2026") -> 0 | AB30: =-Fiscal!L20+SUMIFS(Aut_Ajustes_Manuais!$G:$G,Aut_Ajustes_Manuais!$I:$I,DRE!Z$4,Aut_Ajustes_Manuais!$F:$F,"ISS") -> -675 | AD30: =-SUMIFS(T_ORCAMENTOS!$E:$E,T_ORCAMENTOS!$C:$C,"ISS",T_ORCAMENTOS!$H:$H,"8/2026") -> -2312.5 | AE30: =-Fiscal!M20+SUMIFS(Aut_Ajustes_Manuais!$G:$G,Aut_Ajustes_Manuais!$I:$I,DRE!AC$4,Aut_Ajustes_Manuais!$F:$F,"ISS") -> 0 | AG30: =-SUMIFS(T_ORCAMENTOS!$E:$E,T_ORCAMENTOS!$C:$C,"ISS",T_ORCAMENTOS!$H:$H,"9/2026") -> -3625 | AH30: =-Fiscal!N20+SUMIFS(Aut_Ajustes_Manuais!$G:$G,Aut_Ajustes_Manuais!$I:$I,DRE!AF$4,Aut_Ajustes_Manuais!$F:$F,"ISS") -> 0 | AJ30: =-SUMIFS(T_ORCAMENTOS!$E:$E,T_ORCAMENTOS!$C:$C,"ISS",T_ORCAMENTOS!$H:$H,"10/2026") -> -4937.5 | AK30: =-Fiscal!P20+SUMIFS(Aut_Ajustes_Manuais!$G:$G,Aut_Ajustes_Manuais!$I:$I,DRE!AI$4,Aut_Ajustes_Manuais!$F:$F,"ISS") -> 0 | AM30: =-SUMIFS(T_ORCAMENTOS!$E:$E,T_ORCAMENTOS!$C:$C,"ISS",T_ORCAMENTOS!$H:$H,"11/2026") -> -5462.5 | AN30: =-Fiscal!Q20+SUMIFS(Aut_Ajustes_Manuais!$G:$G,Aut_Ajustes_Manuais!$I:$I,DRE!AL$4,Aut_Ajustes_Manuais!$F:$F,"ISS") -> 0 | AP30: =-SUMIFS(T_ORCAMENTOS!$E:$E,T_ORCAMENTOS!$C:$C,"ISS",T_ORCAMENTOS!$H:$H,"12/2026") -> -13118.75 | AQ30: =-Fiscal!R20+SUMIFS(Aut_Ajustes_Manuais!$G:$G,Aut_Ajustes_Manuais!$I:$I,DRE!AO$4,Aut_Ajustes_Manuais!$F:$F,"ISS") -> 0 | AR30: =SUMIFS($H30:$AO30,$H$5:$AO$5,"<"&MONTH(TODAY()),$H$6:$AO$6,"REAL 25") -> 0 | AS30: =SUMIFS($I30:$AP30,$I$5:$AP$5,"<"&MONTH(TODAY()),$I$6:$AP$6,"ORÇADO ") -> -2312.5 | AT30: =SUMIFS($J30:$AQ30,$J$5:$AQ$5,"<"&MONTH(TODAY()),$J$6:$AQ$6,"REAL 26") -> -675 | AU30: =SUM(H30,K30,N30,Q30,T30,W30,Z30,AC30,AF30,AI30,AL30,AO30) -> 0 | AV30: =SUM(I30,L30,O30,R30,U30,X30,AA30,AD30,AG30,AJ30,AM30,AP30) -> -29456.25 | AW30: =SUM(J30,M30,P30,S30,V30,Y30,AB30,AE30,AH30,AK30,AN30,AQ30) -> -675 | AX30: =SUM(H30,K30,N30) -> 0 | AY30: =SUM(I30,L30,O30) -> 0 | AZ30: =SUM(J30,M30,P30) -> 0 | BA30: =SUM(Q30,T30,W30) -> 0 | BB30: =SUM(R30,U30,X30) -> 0 | BC30: =SUM(S30,V30,Y30) -> 0 | BD30: =SUM(Z30,AC30,AF30) -> 0 | BE30: =SUM(AA30,AD30,AG30) -> -5937.5 | BF30: =SUM(AB30,AE30,AH30) -> -675 | BG30: =SUM(AI30,AL30,AO30) -> 0 | BH30: =SUM(AJ30,AM30,AP30) -> -23518.75 | BI30: =SUM(AK30,AN30,AQ30) -> 0
J31: =J27/J8 -> #DIV/0! | M31: =M27/M8 -> #DIV/0! | P31: =P27/P8 -> #DIV/0!
A32: RECEITA LÍQUIDA | H32: 999539.66 | I32: =SUM(I27,I21,I8) -> 0 | J32: =SUM(J27,J21,J8)+SUMIFS(Aut_Ajustes_Manuais!$G:$G,Aut_Ajustes_Manuais!$I:$I,DRE!H$4,Aut_Ajustes_Manuais!$F:$F,"RECEITA LÍQUIDA") -> 0 | K32: 1081289.2 | L32: =SUM(L27,L21,L8) -> 0 | M32: =SUM(M27,M21,M8)+SUMIFS(Aut_Ajustes_Manuais!$G:$G,Aut_Ajustes_Manuais!$I:$I,DRE!K$4,Aut_Ajustes_Manuais!$F:$F,"RECEITA LÍQUIDA") -> 0 | N32: 1408179.8 | O32: =SUM(O27,O21,O8) -> 0 | P32: =SUM(P27,P21,P8)+SUMIFS(Aut_Ajustes_Manuais!$G:$G,Aut_Ajustes_Manuais!$I:$I,DRE!N$4,Aut_Ajustes_Manuais!$F:$F,"RECEITA LÍQUIDA") -> 0 | Q32: 1253526.4 | R32: =SUM(R27,R21,R8) -> 0 | S32: =SUM(S27,S21,S8)+SUMIFS(Aut_Ajustes_Manuais!$G:$G,Aut_Ajustes_Manuais!$I:$I,DRE!Q$4,Aut_Ajustes_Manuais!$F:$F,"RECEITA LÍQUIDA") -> 0 | T32: 1350286.2 | U32: =SUM(U27,U21,U8) -> 0 | V32: =SUM(V27,V21,V8)+SUMIFS(Aut_Ajustes_Manuais!$G:$G,Aut_Ajustes_Manuais!$I:$I,DRE!T$4,Aut_Ajustes_Manuais!$F:$F,"RECEITA LÍQUIDA") -> 0 | W32: 1374166.1 | X32: =SUM(X27,X21,X8) -> 0 | Y32: =SUM(Y27,Y21,Y8)+SUMIFS(Aut_Ajustes_Manuais!$G:$G,Aut_Ajustes_Manuais!$I:$I,DRE!W$4,Aut_Ajustes_Manuais!$F:$F,"RECEITA LÍQUIDA") -> 0 | Z32: 1311850.3 | AA32: =SUM(AA27,AA21,AA8) -> 0 | AB32: =SUM(AB27,AB21,AB8)+SUMIFS(Aut_Ajustes_Manuais!$G:$G,Aut_Ajustes_Manuais!$I:$I,DRE!Z$4,Aut_Ajustes_Manuais!$F:$F,"RECEITA LÍQUIDA") -> 317144.33 | AC32: 1537451.6 | AD32: =SUM(AD27,AD21,AD8) -> 4335061.5 | AE32: =SUM(AE27,AE21,AE8)+SUMIFS(Aut_Ajustes_Manuais!$G:$G,Aut_Ajustes_Manuais!$I:$I,DRE!AC$4,Aut_Ajustes_Manuais!$F:$F,"RECEITA LÍQUIDA") -> 0 | AF32: 1386509.1 | AG32: =SUM(AG27,AG21,AG8) -> 4201072.8 | AH32: =SUM(AH27,AH21,AH8)+SUMIFS(Aut_Ajustes_Manuais!$G:$G,Aut_Ajustes_Manuais!$I:$I,DRE!AF$4,Aut_Ajustes_Manuais!$F:$F,"RECEITA LÍQUIDA") -> 0 | AI32: 1277890.5 | AJ32: =SUM(AJ27,AJ21,AJ8) -> 4612242 | AK32: =SUM(AK27,AK21,AK8)+SUMIFS(Aut_Ajustes_Manuais!$G:$G,Aut_Ajustes_Manuais!$I:$I,DRE!AI$4,Aut_Ajustes_Manuais!$F:$F,"RECEITA LÍQUIDA") -> 0 | AL32: 1635507.4 | AM32: =SUM(AM27,AM21,AM8) -> 4249416.7 | AN32: =SUM(AN27,AN21,AN8)+SUMIFS(Aut_Ajustes_Manuais!$G:$G,Aut_Ajustes_Manuais!$I:$I,DRE!AL$4,Aut_Ajustes_Manuais!$F:$F,"RECEITA LÍQUIDA") -> 0 | AO32: 1597437.6 | AP32: =SUM(AP27,AP21,AP8) -> 4636025.5 | AQ32: =SUM(AQ27,AQ21,AQ8)+SUMIFS(Aut_Ajustes_Manuais!$G:$G,Aut_Ajustes_Manuais!$I:$I,DRE!AO$4,Aut_Ajustes_Manuais!$F:$F,"RECEITA LÍQUIDA") -> 0 | AR32: =SUM(AR27,AR21,AR8) -> 0 | AS32: =SUM(AS27,AS21,AS8) -> 4335061.5 | AT32: =SUM(AT27,AT21,AT8) -> 317144.33 | AU32: =SUM(AU27,AU21,AU8) -> 0 | AV32: =SUM(AV27,AV21,AV8) -> 22033818 | AW32: =SUM(AW27,AW21,AW8) -> 317144.33 | AX32: =SUM(AX27,AX21,AX8) -> 0 | AY32: =SUM(AY27,AY21,AY8) -> 0 | ... BI32: =SUM(BI27,BI21,BI8) -> 0
A34: (-) Custo Mercadoria Vendida | C34: Premissas | D34: Valores | E34: % Incid | I34: =SUM(I35:I38) -> 0 | J34: =SUM(J35:J38)+SUMIFS(Aut_Ajustes_Manuais!$G:$G,Aut_Ajustes_Manuais!$I:$I,DRE!H$4,Aut_Ajustes_Manuais!$F:$F,"(-) Custo Mercadoria Vendida") -> 0 | L34: =SUM(L35:L38) -> 0 | M34: =SUM(M35:M38)+SUMIFS(Aut_Ajustes_Manuais!$G:$G,Aut_Ajustes_Manuais!$I:$I,DRE!K$4,Aut_Ajustes_Manuais!$F:$F,"(-) Custo Mercadoria Vendida") -> 0 | O34: =SUM(O35:O38) -> 0 | P34: =SUM(P35:P38)+SUMIFS(Aut_Ajustes_Manuais!$G:$G,Aut_Ajustes_Manuais!$I:$I,DRE!N$4,Aut_Ajustes_Manuais!$F:$F,"(-) Custo Mercadoria Vendida") -> 0 | R34: =SUM(R35:R38) -> 0 | S34: =SUM(S35:S38)+SUMIFS(Aut_Ajustes_Manuais!$G:$G,Aut_Ajustes_Manuais!$I:$I,DRE!Q$4,Aut_Ajustes_Manuais!$F:$F,"(-) Custo Mercadoria Vendida") -> -2834.92 | U34: =SUM(U35:U38) -> 0 | V34: =SUM(V35:V38)+SUMIFS(Aut_Ajustes_Manuais!$G:$G,Aut_Ajustes_Manuais!$I:$I,DRE!T$4,Aut_Ajustes_Manuais!$F:$F,"(-) Custo Mercadoria Vendida") -> -1279.09 | X34: =SUM(X35:X38) -> 0 | Y34: =SUM(Y35:Y38)+SUMIFS(Aut_Ajustes_Manuais!$G:$G,Aut_Ajustes_Manuais!$I:$I,DRE!W$4,Aut_Ajustes_Manuais!$F:$F,"(-) Custo Mercadoria Vendida") -> -103238.05 | AA34: =SUM(AA35:AA38) -> 0 | AB34: =SUM(AB35:AB38)+SUMIFS(Aut_Ajustes_Manuais!$G:$G,Aut_Ajustes_Manuais!$I:$I,DRE!Z$4,Aut_Ajustes_Manuais!$F:$F,"(-) Custo Mercadoria Vendida") -> -267871.24 | AD34: =SUM(AD35:AD38) -> -976411.74 | AE34: =SUM(AE35:AE38)+SUMIFS(Aut_Ajustes_Manuais!$G:$G,Aut_Ajustes_Manuais!$I:$I,DRE!AC$4,Aut_Ajustes_Manuais!$F:$F,"(-) Custo Mercadoria Vendida") -> 0 | AG34: =SUM(AG35:AG38) -> -879784.57 | AH34: =SUM(AH35:AH38)+SUMIFS(Aut_Ajustes_Manuais!$G:$G,Aut_Ajustes_Manuais!$I:$I,DRE!AF$4,Aut_Ajustes_Manuais!$F:$F,"(-) Custo Mercadoria Vendida") -> 0 | AJ34: =SUM(AJ35:AJ38) -> -964030.64 | AK34: =SUM(AK35:AK38)+SUMIFS(Aut_Ajustes_Manuais!$G:$G,Aut_Ajustes_Manuais!$I:$I,DRE!AI$4,Aut_Ajustes_Manuais!$F:$F,"(-) Custo Mercadoria Vendida") -> 0 | AM34: =SUM(AM35:AM38) -> -889369.46 | AN34: =SUM(AN35:AN38)+SUMIFS(Aut_Ajustes_Manuais!$G:$G,Aut_Ajustes_Manuais!$I:$I,DRE!AL$4,Aut_Ajustes_Manuais!$F:$F,"(-) Custo Mercadoria Vendida") -> 0 | AP34: =SUM(AP35:AP38) -> -951057.22 | AQ34: =SUM(AQ35:AQ38)+SUMIFS(Aut_Ajustes_Manuais!$G:$G,Aut_Ajustes_Manuais!$I:$I,DRE!AO$4,Aut_Ajustes_Manuais!$F:$F,"(-) Custo Mercadoria Vendida") -> 0 | AR34: =SUM(AR35:AR38) -> 0 | AS34: =SUM(AS35:AS38) -> -976411.74 | AT34: =SUM(AT35:AT38) -> -375223.3 | AU34: =SUM(AU35:AU38) -> 0 | AV34: =SUM(AV35:AV38) -> -4660653.6 | AW34: =SUM(AW35:AW38) -> -375223.3 | AX34: =SUM(AX35:AX38) -> 0 | AY34: =SUM(AY35:AY38) -> 0 | ... BI34: =SUM(BI35:BI38) -> 0
A35: Alimentação D | C35: Estim. Mensal | E35: 0.33 | I35: =-SUMIFS(T_ORCAMENTOS!$E:$E,T_ORCAMENTOS!$C:$C,"Insumos - Alimentos",T_ORCAMENTOS!$H:$H,"1/2026") -> 0 | J35: =-CMV_Manual!D22+SUMIFS(Aut_Ajustes_Manuais!$G:$G,Aut_Ajustes_Manuais!$I:$I,DRE!H$4,Aut_Ajustes_Manuais!$F:$F,"Insumos - Alimentos") -> 0 | L35: =-SUMIFS(T_ORCAMENTOS!$E:$E,T_ORCAMENTOS!$C:$C,"Insumos - Alimentos",T_ORCAMENTOS!$H:$H,"2/2026") -> 0 | M35: =-CMV_Manual!E22+SUMIFS(Aut_Ajustes_Manuais!$G:$G,Aut_Ajustes_Manuais!$I:$I,DRE!K$4,Aut_Ajustes_Manuais!$F:$F,"Insumos - Alimentos") -> 0 | O35: =-SUMIFS(T_ORCAMENTOS!$E:$E,T_ORCAMENTOS!$C:$C,"Insumos - Alimentos",T_ORCAMENTOS!$H:$H,"3/2026") -> 0 | P35: =-CMV_Manual!F22+SUMIFS(Aut_Ajustes_Manuais!$G:$G,Aut_Ajustes_Manuais!$I:$I,DRE!N$4,Aut_Ajustes_Manuais!$F:$F,"Insumos - Alimentos") -> 0 | R35: =-SUMIFS(T_ORCAMENTOS!$E:$E,T_ORCAMENTOS!$C:$C,"Insumos - Alimentos",T_ORCAMENTOS!$H:$H,"4/2026") -> 0 | S35: =-CMV_Manual!G22+SUMIFS(Aut_Ajustes_Manuais!$G:$G,Aut_Ajustes_Manuais!$I:$I,DRE!Q$4,Aut_Ajustes_Manuais!$F:$F,"Insumos - Alimentos") -> 0 | U35: =-SUMIFS(T_ORCAMENTOS!$E:$E,T_ORCAMENTOS!$C:$C,"Insumos - Alimentos",T_ORCAMENTOS!$H:$H,"5/2026") -> 0 | V35: =-CMV_Manual!H22+SUMIFS(Aut_Ajustes_Manuais!$G:$G,Aut_Ajustes_Manuais!$I:$I,DRE!T$4,Aut_Ajustes_Manuais!$F:$F,"Insumos - Alimentos") -> -957.09 | X35: =-SUMIFS(T_ORCAMENTOS!$E:$E,T_ORCAMENTOS!$C:$C,"Insumos - Alimentos",T_ORCAMENTOS!$H:$H,"6/2026") -> 0 | Y35: =-CMV_Manual!I22+SUMIFS(Aut_Ajustes_Manuais!$G:$G,Aut_Ajustes_Manuais!$I:$I,DRE!W$4,Aut_Ajustes_Manuais!$F:$F,"Insumos - Alimentos") -> -60914.37 | AA35: =-SUMIFS(T_ORCAMENTOS!$E:$E,T_ORCAMENTOS!$C:$C,"Insumos - Alimentos",T_ORCAMENTOS!$H:$H,"7/2026") -> 0 | AB35: =-CMV_Manual!J22+SUMIFS(Aut_Ajustes_Manuais!$G:$G,Aut_Ajustes_Manuais!$I:$I,DRE!Z$4,Aut_Ajustes_Manuais!$F:$F,"Insumos - Alimentos") -> -145024.06 | AD35: =-SUMIFS(T_ORCAMENTOS!$E:$E,T_ORCAMENTOS!$C:$C,"Insumos - Alimentos",T_ORCAMENTOS!$H:$H,"8/2026") -> -664967.48 | AE35: =-CMV_Manual!K22+SUMIFS(Aut_Ajustes_Manuais!$G:$G,Aut_Ajustes_Manuais!$I:$I,DRE!AC$4,Aut_Ajustes_Manuais!$F:$F,"Insumos - Alimentos") -> 0 | AG35: =-SUMIFS(T_ORCAMENTOS!$E:$E,T_ORCAMENTOS!$C:$C,"Insumos - Alimentos",T_ORCAMENTOS!$H:$H,"9/2026") -> -582922.09 | AH35: =-CMV_Manual!L22+SUMIFS(Aut_Ajustes_Manuais!$G:$G,Aut_Ajustes_Manuais!$I:$I,DRE!AF$4,Aut_Ajustes_Manuais!$F:$F,"Insumos - Alimentos") -> 0 | AJ35: =-SUMIFS(T_ORCAMENTOS!$E:$E,T_ORCAMENTOS!$C:$C,"Insumos - Alimentos",T_ORCAMENTOS!$H:$H,"10/2026") -> -642868.28 | AK35: =-CMV_Manual!M22+SUMIFS(Aut_Ajustes_Manuais!$G:$G,Aut_Ajustes_Manuais!$I:$I,DRE!AI$4,Aut_Ajustes_Manuais!$F:$F,"Insumos - Alimentos") -> 0 | AM35: =-SUMIFS(T_ORCAMENTOS!$E:$E,T_ORCAMENTOS!$C:$C,"Insumos - Alimentos",T_ORCAMENTOS!$H:$H,"11/2026") -> -596307.96 | AN35: =-CMV_Manual!N22+SUMIFS(Aut_Ajustes_Manuais!$G:$G,Aut_Ajustes_Manuais!$I:$I,DRE!AL$4,Aut_Ajustes_Manuais!$F:$F,"Insumos - Alimentos") -> 0 | AP35: =-SUMIFS(T_ORCAMENTOS!$E:$E,T_ORCAMENTOS!$C:$C,"Insumos - Alimentos",T_ORCAMENTOS!$H:$H,"12/2026") -> -658318.26 | AQ35: =-CMV_Manual!O22+SUMIFS(Aut_Ajustes_Manuais!$G:$G,Aut_Ajustes_Manuais!$I:$I,DRE!AO$4,Aut_Ajustes_Manuais!$F:$F,"Insumos - Alimentos") -> 0 | AR35: =SUMIFS($H35:$AO35,$H$5:$AO$5,"<"&MONTH(TODAY()),$H$6:$AO$6,"REAL 25") -> 0 | AS35: =SUMIFS($I35:$AP35,$I$5:$AP$5,"<"&MONTH(TODAY()),$I$6:$AP$6,"ORÇADO ") -> -664967.48 | AT35: =SUMIFS($J35:$AQ35,$J$5:$AQ$5,"<"&MONTH(TODAY()),$J$6:$AQ$6,"REAL 26") -> -206895.52 | AU35: =SUM(H35,K35,N35,Q35,T35,W35,Z35,AC35,AF35,AI35,AL35,AO35) -> 0 | AV35: =SUM(I35,L35,O35,R35,U35,X35,AA35,AD35,AG35,AJ35,AM35,AP35) -> -3145384.1 | AW35: =SUM(J35,M35,P35,S35,V35,Y35,AB35,AE35,AH35,AK35,AN35,AQ35) -> -206895.52 | AX35: =SUM(H35,K35,N35) -> 0 | AY35: =SUM(I35,L35,O35) -> 0 | AZ35: =SUM(J35,M35,P35) -> 0 | BA35: =SUM(Q35,T35,W35) -> 0 | BB35: =SUM(R35,U35,X35) -> 0 | BC35: =SUM(S35,V35,Y35) -> -61871.46 | BD35: =SUM(Z35,AC35,AF35) -> 0 | BE35: =SUM(AA35,AD35,AG35) -> -1247889.6 | BF35: =SUM(AB35,AE35,AH35) -> -145024.06 | BG35: =SUM(AI35,AL35,AO35) -> 0 | BH35: =SUM(AJ35,AM35,AP35) -> -1897494.5 | BI35: =SUM(AK35,AN35,AQ35) -> 0
A36: Bebida D | C36: Estim. Mensal | E36: 0.18 | I36: =-SUMIFS(T_ORCAMENTOS!$E:$E,T_ORCAMENTOS!$C:$C,"Insumos - Bebidas",T_ORCAMENTOS!$H:$H,"1/2026") -> 0 | J36: =-CMV_Manual!D23+SUMIFS(Aut_Ajustes_Manuais!$G:$G,Aut_Ajustes_Manuais!$I:$I,DRE!H$4,Aut_Ajustes_Manuais!$F:$F,"Insumos - Bebidas") -> 0 | L36: =-SUMIFS(T_ORCAMENTOS!$E:$E,T_ORCAMENTOS!$C:$C,"Insumos - Bebidas",T_ORCAMENTOS!$H:$H,"2/2026") -> 0 | M36: =-CMV_Manual!E23+SUMIFS(Aut_Ajustes_Manuais!$G:$G,Aut_Ajustes_Manuais!$I:$I,DRE!K$4,Aut_Ajustes_Manuais!$F:$F,"Insumos - Bebidas") -> 0 | O36: =-SUMIFS(T_ORCAMENTOS!$E:$E,T_ORCAMENTOS!$C:$C,"Insumos - Bebidas",T_ORCAMENTOS!$H:$H,"3/2026") -> 0 | P36: =-CMV_Manual!F23+SUMIFS(Aut_Ajustes_Manuais!$G:$G,Aut_Ajustes_Manuais!$I:$I,DRE!N$4,Aut_Ajustes_Manuais!$F:$F,"Insumos - Bebidas") -> 0 | R36: =-SUMIFS(T_ORCAMENTOS!$E:$E,T_ORCAMENTOS!$C:$C,"Insumos - Bebidas",T_ORCAMENTOS!$H:$H,"4/2026") -> 0 | S36: =-CMV_Manual!G23+SUMIFS(Aut_Ajustes_Manuais!$G:$G,Aut_Ajustes_Manuais!$I:$I,DRE!Q$4,Aut_Ajustes_Manuais!$F:$F,"Insumos - Bebidas") -> -2834.92 | U36: =-SUMIFS(T_ORCAMENTOS!$E:$E,T_ORCAMENTOS!$C:$C,"Insumos - Bebidas",T_ORCAMENTOS!$H:$H,"5/2026") -> 0 | V36: =-CMV_Manual!H23+SUMIFS(Aut_Ajustes_Manuais!$G:$G,Aut_Ajustes_Manuais!$I:$I,DRE!T$4,Aut_Ajustes_Manuais!$F:$F,"Insumos - Bebidas") -> -322 | X36: =-SUMIFS(T_ORCAMENTOS!$E:$E,T_ORCAMENTOS!$C:$C,"Insumos - Bebidas",T_ORCAMENTOS!$H:$H,"6/2026") -> 0 | Y36: =-CMV_Manual!I23+SUMIFS(Aut_Ajustes_Manuais!$G:$G,Aut_Ajustes_Manuais!$I:$I,DRE!W$4,Aut_Ajustes_Manuais!$F:$F,"Insumos - Bebidas") -> -42323.68 | AA36: =-SUMIFS(T_ORCAMENTOS!$E:$E,T_ORCAMENTOS!$C:$C,"Insumos - Bebidas",T_ORCAMENTOS!$H:$H,"7/2026") -> 0 | AB36: =-CMV_Manual!J23+SUMIFS(Aut_Ajustes_Manuais!$G:$G,Aut_Ajustes_Manuais!$I:$I,DRE!Z$4,Aut_Ajustes_Manuais!$F:$F,"Insumos - Bebidas") -> -122847.18 | AD36: =-SUMIFS(T_ORCAMENTOS!$E:$E,T_ORCAMENTOS!$C:$C,"Insumos - Bebidas",T_ORCAMENTOS!$H:$H,"8/2026") -> -311444.26 | AE36: =-CMV_Manual!K23+SUMIFS(Aut_Ajustes_Manuais!$G:$G,Aut_Ajustes_Manuais!$I:$I,DRE!AC$4,Aut_Ajustes_Manuais!$F:$F,"Insumos - Bebidas") -> 0 | AG36: =-SUMIFS(T_ORCAMENTOS!$E:$E,T_ORCAMENTOS!$C:$C,"Insumos - Bebidas",T_ORCAMENTOS!$H:$H,"9/2026") -> -296862.48 | AH36: =-CMV_Manual!L23+SUMIFS(Aut_Ajustes_Manuais!$G:$G,Aut_Ajustes_Manuais!$I:$I,DRE!AF$4,Aut_Ajustes_Manuais!$F:$F,"Insumos - Bebidas") -> 0 | AJ36: =-SUMIFS(T_ORCAMENTOS!$E:$E,T_ORCAMENTOS!$C:$C,"Insumos - Bebidas",T_ORCAMENTOS!$H:$H,"10/2026") -> -321162.36 | AK36: =-CMV_Manual!M23+SUMIFS(Aut_Ajustes_Manuais!$G:$G,Aut_Ajustes_Manuais!$I:$I,DRE!AI$4,Aut_Ajustes_Manuais!$F:$F,"Insumos - Bebidas") -> 0 | AM36: =-SUMIFS(T_ORCAMENTOS!$E:$E,T_ORCAMENTOS!$C:$C,"Insumos - Bebidas",T_ORCAMENTOS!$H:$H,"11/2026") -> -293061.5 | AN36: =-CMV_Manual!N23+SUMIFS(Aut_Ajustes_Manuais!$G:$G,Aut_Ajustes_Manuais!$I:$I,DRE!AL$4,Aut_Ajustes_Manuais!$F:$F,"Insumos - Bebidas") -> 0 | AP36: =-SUMIFS(T_ORCAMENTOS!$E:$E,T_ORCAMENTOS!$C:$C,"Insumos - Bebidas",T_ORCAMENTOS!$H:$H,"12/2026") -> -292738.96 | AQ36: =-CMV_Manual!O23+SUMIFS(Aut_Ajustes_Manuais!$G:$G,Aut_Ajustes_Manuais!$I:$I,DRE!AO$4,Aut_Ajustes_Manuais!$F:$F,"Insumos - Bebidas") -> 0 | AR36: =SUMIFS($H36:$AO36,$H$5:$AO$5,"<"&MONTH(TODAY()),$H$6:$AO$6,"REAL 25") -> 0 | AS36: =SUMIFS($I36:$AP36,$I$5:$AP$5,"<"&MONTH(TODAY()),$I$6:$AP$6,"ORÇADO ") -> -311444.26 | AT36: =SUMIFS($J36:$AQ36,$J$5:$AQ$5,"<"&MONTH(TODAY()),$J$6:$AQ$6,"REAL 26") -> -168327.78 | AU36: =SUM(H36,K36,N36,Q36,T36,W36,Z36,AC36,AF36,AI36,AL36,AO36) -> 0 | AV36: =SUM(I36,L36,O36,R36,U36,X36,AA36,AD36,AG36,AJ36,AM36,AP36) -> -1515269.6 | AW36: =SUM(J36,M36,P36,S36,V36,Y36,AB36,AE36,AH36,AK36,AN36,AQ36) -> -168327.78 | AX36: =SUM(H36,K36,N36) -> 0 | AY36: =SUM(I36,L36,O36) -> 0 | AZ36: =SUM(J36,M36,P36) -> 0 | BA36: =SUM(Q36,T36,W36) -> 0 | BB36: =SUM(R36,U36,X36) -> 0 | BC36: =SUM(S36,V36,Y36) -> -45480.6 | BD36: =SUM(Z36,AC36,AF36) -> 0 | BE36: =SUM(AA36,AD36,AG36) -> -608306.74 | BF36: =SUM(AB36,AE36,AH36) -> -122847.18 | BG36: =SUM(AI36,AL36,AO36) -> 0 | BH36: =SUM(AJ36,AM36,AP36) -> -906962.82 | BI36: =SUM(AK36,AN36,AQ36) -> 0
A37: Embalagens | C37: Estim. Mensal | I37: =-SUMIFS(T_ORCAMENTOS!$E:$E,T_ORCAMENTOS!$C:$C,"Insumos - Embalagens",T_ORCAMENTOS!$H:$H,"1/2026") -> 0 | J37: =SUMIFS(Aut_BlueMe_Sem_Pedido!$J:$J,Aut_BlueMe_Sem_Pedido!$Q:$Q,DRE!H$4,Aut_BlueMe_Sem_Pedido!$H:$H,DRE!$A37)+SUMIFS(Aut_Ajustes_Manuais!$G:$G,Aut_Ajustes_Manuais!$I:$I,DRE!H$4,Aut_Ajustes_Manuais!$F:$F,"Insumos - Embalagens") -> 0 | L37: =-SUMIFS(T_ORCAMENTOS!$E:$E,T_ORCAMENTOS!$C:$C,"Insumos - Embalagens",T_ORCAMENTOS!$H:$H,"2/2026") -> 0 | M37: =SUMIFS(Aut_BlueMe_Sem_Pedido!$J:$J,Aut_BlueMe_Sem_Pedido!$Q:$Q,DRE!K$4,Aut_BlueMe_Sem_Pedido!$H:$H,DRE!$A37)+SUMIFS(Aut_Ajustes_Manuais!$G:$G,Aut_Ajustes_Manuais!$I:$I,DRE!K$4,Aut_Ajustes_Manuais!$F:$F,"Insumos - Embalagens") -> 0 | O37: =-SUMIFS(T_ORCAMENTOS!$E:$E,T_ORCAMENTOS!$C:$C,"Insumos - Embalagens",T_ORCAMENTOS!$H:$H,"3/2026") -> 0 | P37: =SUMIFS(Aut_BlueMe_Sem_Pedido!$J:$J,Aut_BlueMe_Sem_Pedido!$Q:$Q,DRE!N$4,Aut_BlueMe_Sem_Pedido!$H:$H,DRE!$A37)+SUMIFS(Aut_Ajustes_Manuais!$G:$G,Aut_Ajustes_Manuais!$I:$I,DRE!N$4,Aut_Ajustes_Manuais!$F:$F,"Insumos - Embalagens") -> 0 | R37: =-SUMIFS(T_ORCAMENTOS!$E:$E,T_ORCAMENTOS!$C:$C,"Insumos - Embalagens",T_ORCAMENTOS!$H:$H,"4/2026") -> 0 | S37: =SUMIFS(Aut_BlueMe_Sem_Pedido!$J:$J,Aut_BlueMe_Sem_Pedido!$Q:$Q,DRE!Q$4,Aut_BlueMe_Sem_Pedido!$H:$H,DRE!$A37)+SUMIFS(Aut_Ajustes_Manuais!$G:$G,Aut_Ajustes_Manuais!$I:$I,DRE!Q$4,Aut_Ajustes_Manuais!$F:$F,"Insumos - Embalagens") -> 0 | U37: =-SUMIFS(T_ORCAMENTOS!$E:$E,T_ORCAMENTOS!$C:$C,"Insumos - Embalagens",T_ORCAMENTOS!$H:$H,"5/2026") -> 0 | V37: =SUMIFS(Aut_Ajustes_Manuais!$G:$G,Aut_Ajustes_Manuais!$I:$I,DRE!T$4,Aut_Ajustes_Manuais!$F:$F,"Insumos - Embalagens") -> 0 | X37: =-SUMIFS(T_ORCAMENTOS!$E:$E,T_ORCAMENTOS!$C:$C,"Insumos - Embalagens",T_ORCAMENTOS!$H:$H,"6/2026") -> 0 | Y37: =SUMIFS(Aut_BlueMe_Sem_Pedido!$J:$J,Aut_BlueMe_Sem_Pedido!$Q:$Q,DRE!W$4,Aut_BlueMe_Sem_Pedido!$H:$H,DRE!$A37)+SUMIFS(Aut_Ajustes_Manuais!$G:$G,Aut_Ajustes_Manuais!$I:$I,DRE!W$4,Aut_Ajustes_Manuais!$F:$F,"Insumos - Embalagens") -> 0 | AA37: =-SUMIFS(T_ORCAMENTOS!$E:$E,T_ORCAMENTOS!$C:$C,"Insumos - Embalagens",T_ORCAMENTOS!$H:$H,"7/2026") -> 0 | AB37: =SUMIFS(Aut_BlueMe_Sem_Pedido!$J:$J,Aut_BlueMe_Sem_Pedido!$Q:$Q,DRE!Z$4,Aut_BlueMe_Sem_Pedido!$H:$H,DRE!$A37)+SUMIFS(Aut_Ajustes_Manuais!$G:$G,Aut_Ajustes_Manuais!$I:$I,DRE!Z$4,Aut_Ajustes_Manuais!$F:$F,"Insumos - Embalagens") -> 0 | AD37: =-SUMIFS(T_ORCAMENTOS!$E:$E,T_ORCAMENTOS!$C:$C,"Insumos - Embalagens",T_ORCAMENTOS!$H:$H,"8/2026") -> 0 | AE37: =SUMIFS(Aut_BlueMe_Sem_Pedido!$J:$J,Aut_BlueMe_Sem_Pedido!$Q:$Q,DRE!AC$4,Aut_BlueMe_Sem_Pedido!$H:$H,DRE!$A37)+SUMIFS(Aut_Ajustes_Manuais!$G:$G,Aut_Ajustes_Manuais!$I:$I,DRE!AC$4,Aut_Ajustes_Manuais!$F:$F,"Insumos - Embalagens") -> 0 | AG37: =-SUMIFS(T_ORCAMENTOS!$E:$E,T_ORCAMENTOS!$C:$C,"Insumos - Embalagens",T_ORCAMENTOS!$H:$H,"9/2026") -> 0 | AH37: =SUMIFS(Aut_BlueMe_Sem_Pedido!$J:$J,Aut_BlueMe_Sem_Pedido!$Q:$Q,DRE!AF$4,Aut_BlueMe_Sem_Pedido!$H:$H,DRE!$A37)+SUMIFS(Aut_Ajustes_Manuais!$G:$G,Aut_Ajustes_Manuais!$I:$I,DRE!AF$4,Aut_Ajustes_Manuais!$F:$F,"Insumos - Embalagens") -> 0 | AJ37: =-SUMIFS(T_ORCAMENTOS!$E:$E,T_ORCAMENTOS!$C:$C,"Insumos - Embalagens",T_ORCAMENTOS!$H:$H,"10/2026") -> 0 | AK37: =SUMIFS(Aut_BlueMe_Sem_Pedido!$J:$J,Aut_BlueMe_Sem_Pedido!$Q:$Q,DRE!AI$4,Aut_BlueMe_Sem_Pedido!$H:$H,DRE!$A37)+SUMIFS(Aut_Ajustes_Manuais!$G:$G,Aut_Ajustes_Manuais!$I:$I,DRE!AI$4,Aut_Ajustes_Manuais!$F:$F,"Insumos - Embalagens") -> 0 | AM37: =-SUMIFS(T_ORCAMENTOS!$E:$E,T_ORCAMENTOS!$C:$C,"Insumos - Embalagens",T_ORCAMENTOS!$H:$H,"11/2026") -> 0 | AN37: =SUMIFS(Aut_BlueMe_Sem_Pedido!$J:$J,Aut_BlueMe_Sem_Pedido!$Q:$Q,DRE!AL$4,Aut_BlueMe_Sem_Pedido!$H:$H,DRE!$A37)+SUMIFS(Aut_Ajustes_Manuais!$G:$G,Aut_Ajustes_Manuais!$I:$I,DRE!AL$4,Aut_Ajustes_Manuais!$F:$F,"Insumos - Embalagens") -> 0 | AP37: =-SUMIFS(T_ORCAMENTOS!$E:$E,T_ORCAMENTOS!$C:$C,"Insumos - Embalagens",T_ORCAMENTOS!$H:$H,"12/2026") -> 0 | AQ37: =SUMIFS(Aut_BlueMe_Sem_Pedido!$J:$J,Aut_BlueMe_Sem_Pedido!$Q:$Q,DRE!AO$4,Aut_BlueMe_Sem_Pedido!$H:$H,DRE!$A37)+SUMIFS(Aut_Ajustes_Manuais!$G:$G,Aut_Ajustes_Manuais!$I:$I,DRE!AO$4,Aut_Ajustes_Manuais!$F:$F,"Insumos - Embalagens") -> 0 | AR37: =SUMIFS($H37:$AO37,$H$5:$AO$5,"<"&MONTH(TODAY()),$H$6:$AO$6,"REAL 25") -> 0 | AS37: =SUMIFS($I37:$AP37,$I$5:$AP$5,"<"&MONTH(TODAY()),$I$6:$AP$6,"ORÇADO ") -> 0 | AT37: =SUMIFS($J37:$AQ37,$J$5:$AQ$5,"<"&MONTH(TODAY()),$J$6:$AQ$6,"REAL 26") -> 0 | AU37: =SUM(H37,K37,N37,Q37,T37,W37,Z37,AC37,AF37,AI37,AL37,AO37) -> 0 | AV37: =SUM(I37,L37,O37,R37,U37,X37,AA37,AD37,AG37,AJ37,AM37,AP37) -> 0 | AW37: =SUM(J37,M37,P37,S37,V37,Y37,AB37,AE37,AH37,AK37,AN37,AQ37) -> 0 | AX37: =SUM(H37,K37,N37) -> 0 | AY37: =SUM(I37,L37,O37) -> 0 | AZ37: =SUM(J37,M37,P37) -> 0 | BA37: =SUM(Q37,T37,W37) -> 0 | BB37: =SUM(R37,U37,X37) -> 0 | BC37: =SUM(S37,V37,Y37) -> 0 | BD37: =SUM(Z37,AC37,AF37) -> 0 | BE37: =SUM(AA37,AD37,AG37) -> 0 | BF37: =SUM(AB37,AE37,AH37) -> 0 | BG37: =SUM(AI37,AL37,AO37) -> 0 | BH37: =SUM(AJ37,AM37,AP37) -> 0 | BI37: =SUM(AK37,AN37,AQ37) -> 0
A38: Eventos A&B | C38: Estim. Mensal | I38: =-SUMIFS(T_ORCAMENTOS!$E:$E,T_ORCAMENTOS!$C:$C,"Insumos - Eventos A&B",T_ORCAMENTOS!$H:$H,"1/2026") -> 0 | L38: =-SUMIFS(T_ORCAMENTOS!$E:$E,T_ORCAMENTOS!$C:$C,"Insumos - Eventos A&B",T_ORCAMENTOS!$H:$H,"2/2026") -> 0 | O38: =-SUMIFS(T_ORCAMENTOS!$E:$E,T_ORCAMENTOS!$C:$C,"Insumos - Eventos A&B",T_ORCAMENTOS!$H:$H,"3/2026") -> 0 | R38: =-SUMIFS(T_ORCAMENTOS!$E:$E,T_ORCAMENTOS!$C:$C,"Insumos - Eventos A&B",T_ORCAMENTOS!$H:$H,"4/2026") -> 0 | U38: =-SUMIFS(T_ORCAMENTOS!$E:$E,T_ORCAMENTOS!$C:$C,"Insumos - Eventos A&B",T_ORCAMENTOS!$H:$H,"5/2026") -> 0 | X38: =-SUMIFS(T_ORCAMENTOS!$E:$E,T_ORCAMENTOS!$C:$C,"Insumos - Eventos A&B",T_ORCAMENTOS!$H:$H,"6/2026") -> 0 | AA38: =-SUMIFS(T_ORCAMENTOS!$E:$E,T_ORCAMENTOS!$C:$C,"Insumos - Eventos A&B",T_ORCAMENTOS!$H:$H,"7/2026") -> 0 | AD38: =-SUMIFS(T_ORCAMENTOS!$E:$E,T_ORCAMENTOS!$C:$C,"Insumos - Eventos A&B",T_ORCAMENTOS!$H:$H,"8/2026") -> 0 | AG38: =-SUMIFS(T_ORCAMENTOS!$E:$E,T_ORCAMENTOS!$C:$C,"Insumos - Eventos A&B",T_ORCAMENTOS!$H:$H,"9/2026") -> 0 | AJ38: =-SUMIFS(T_ORCAMENTOS!$E:$E,T_ORCAMENTOS!$C:$C,"Insumos - Eventos A&B",T_ORCAMENTOS!$H:$H,"10/2026") -> 0 | AM38: =-SUMIFS(T_ORCAMENTOS!$E:$E,T_ORCAMENTOS!$C:$C,"Insumos - Eventos A&B",T_ORCAMENTOS!$H:$H,"11/2026") -> 0 | AP38: =-SUMIFS(T_ORCAMENTOS!$E:$E,T_ORCAMENTOS!$C:$C,"Insumos - Eventos A&B",T_ORCAMENTOS!$H:$H,"12/2026") -> 0 | AR38: =SUMIFS($H38:$AO38,$H$5:$AO$5,"<"&MONTH(TODAY()),$H$6:$AO$6,"REAL 25") -> 0 | AS38: =SUMIFS($I38:$AP38,$I$5:$AP$5,"<"&MONTH(TODAY()),$I$6:$AP$6,"ORÇADO ") -> 0 | AT38: =SUMIFS($J38:$AQ38,$J$5:$AQ$5,"<"&MONTH(TODAY()),$J$6:$AQ$6,"REAL 26") -> 0 | AU38: =SUM(H38,K38,N38,Q38,T38,W38,Z38,AC38,AF38,AI38,AL38,AO38) -> 0 | AV38: =SUM(I38,L38,O38,R38,U38,X38,AA38,AD38,AG38,AJ38,AM38,AP38) -> 0 | AW38: =SUM(J38,M38,P38,S38,V38,Y38,AB38,AE38,AH38,AK38,AN38,AQ38) -> 0 | AX38: =SUM(H38,K38,N38) -> 0 | AY38: =SUM(I38,L38,O38) -> 0 | AZ38: =SUM(J38,M38,P38) -> 0 | BA38: =SUM(Q38,T38,W38) -> 0 | BB38: =SUM(R38,U38,X38) -> 0 | BC38: =SUM(S38,V38,Y38) -> 0 | BD38: =SUM(Z38,AC38,AF38) -> 0 | BE38: =SUM(AA38,AD38,AG38) -> 0 | BF38: =SUM(AB38,AE38,AH38) -> 0 | BG38: =SUM(AI38,AL38,AO38) -> 0 | BH38: =SUM(AJ38,AM38,AP38) -> 0 | BI38: =SUM(AK38,AN38,AQ38) -> 0
A39: % sobre Receita Bruta | I39: =IFERROR(I34/(I9+I10+I14+I18),0) -> 0 | J39: =IFERROR(J34/(J9+J10+J14+J18),0)+SUMIFS(Aut_Ajustes_Manuais!$G:$G,Aut_Ajustes_Manuais!$I:$I,DRE!H$4,Aut_Ajustes_Manuais!$F:$F,"% sobre Receita Bruta") -> 0 | L39: =IFERROR(L34/(L9+L10+L14+L18),0) -> 0 | M39: =IFERROR(M34/(M9+M10+M14+M18),0)+SUMIFS(Aut_Ajustes_Manuais!$G:$G,Aut_Ajustes_Manuais!$I:$I,DRE!K$4,Aut_Ajustes_Manuais!$F:$F,"% sobre Receita Bruta") -> 0 | O39: =IFERROR(O34/(O9+O10+O14+O18),0) -> 0 | P39: =IFERROR(P34/(P9+P10+P14+P18),0)+SUMIFS(Aut_Ajustes_Manuais!$G:$G,Aut_Ajustes_Manuais!$I:$I,DRE!N$4,Aut_Ajustes_Manuais!$F:$F,"% sobre Receita Bruta") -> 0 | R39: =IFERROR(R34/(R9+R10+R14+R18),0) -> 0 | S39: =IFERROR(S34/(S9+S10+S14+S18),0)+SUMIFS(Aut_Ajustes_Manuais!$G:$G,Aut_Ajustes_Manuais!$I:$I,DRE!Q$4,Aut_Ajustes_Manuais!$F:$F,"% sobre Receita Bruta") -> 0 | U39: =IFERROR(U34/(U9+U10+U14+U18),0) -> 0 | V39: =IFERROR(V34/(V9+V10+V14+V18),0)+SUMIFS(Aut_Ajustes_Manuais!$G:$G,Aut_Ajustes_Manuais!$I:$I,DRE!T$4,Aut_Ajustes_Manuais!$F:$F,"% sobre Receita Bruta") -> 0 | X39: =IFERROR(X34/(X9+X10+X14+X18),0) -> 0 | Y39: =IFERROR(Y34/(Y9+Y10+Y14+Y18),0)+SUMIFS(Aut_Ajustes_Manuais!$G:$G,Aut_Ajustes_Manuais!$I:$I,DRE!W$4,Aut_Ajustes_Manuais!$F:$F,"% sobre Receita Bruta") -> 0 | AA39: =IFERROR(AA34/(AA9+AA10+AA14+AA18),0) -> 0 | AB39: =IFERROR(AB34/(AB9+AB10+AB14+AB18),0)+SUMIFS(Aut_Ajustes_Manuais!$G:$G,Aut_Ajustes_Manuais!$I:$I,DRE!Z$4,Aut_Ajustes_Manuais!$F:$F,"% sobre Receita Bruta") -> -0.93908949 | AD39: =IFERROR(AD34/(AD9+AD10+AD14+AD18),0) -> -0.28154525 | AE39: =IFERROR(AE34/(AE9+AE10+AE14+AE18),0)+SUMIFS(Aut_Ajustes_Manuais!$G:$G,Aut_Ajustes_Manuais!$I:$I,DRE!AC$4,Aut_Ajustes_Manuais!$F:$F,"% sobre Receita Bruta") -> 0 | AG39: =IFERROR(AG34/(AG9+AG10+AG14+AG18),0) -> -0.26209771 | AH39: =IFERROR(AH34/(AH9+AH10+AH14+AH18),0)+SUMIFS(Aut_Ajustes_Manuais!$G:$G,Aut_Ajustes_Manuais!$I:$I,DRE!AF$4,Aut_Ajustes_Manuais!$F:$F,"% sobre Receita Bruta") -> 0 | AJ39: =IFERROR(AJ34/(AJ9+AJ10+AJ14+AJ18),0) -> -0.2625185 | AK39: =IFERROR(AK34/(AK9+AK10+AK14+AK18),0)+SUMIFS(Aut_Ajustes_Manuais!$G:$G,Aut_Ajustes_Manuais!$I:$I,DRE!AI$4,Aut_Ajustes_Manuais!$F:$F,"% sobre Receita Bruta") -> 0 | AM39: =IFERROR(AM34/(AM9+AM10+AM14+AM18),0) -> -0.2628763 | AN39: =IFERROR(AN34/(AN9+AN10+AN14+AN18),0)+SUMIFS(Aut_Ajustes_Manuais!$G:$G,Aut_Ajustes_Manuais!$I:$I,DRE!AL$4,Aut_Ajustes_Manuais!$F:$F,"% sobre Receita Bruta") -> 0 | AP39: =IFERROR(AP34/(AP9+AP10+AP14+AP18),0) -> -0.25956391 | AQ39: =IFERROR(AQ34/(AQ9+AQ10+AQ14+AQ18),0)+SUMIFS(Aut_Ajustes_Manuais!$G:$G,Aut_Ajustes_Manuais!$I:$I,DRE!AO$4,Aut_Ajustes_Manuais!$F:$F,"% sobre Receita Bruta") -> 0 | AR39: =IFERROR(AR34/(AR9+AR10+AR14+AR18),0) -> 0 | AS39: =IFERROR(AS34/(AS9+AS10+AS14+AS18),0) -> -0.28154525 | AT39: =IFERROR(AT34/(AT9+AT10+AT14+AT18),0) -> -1.3154389 | AU39: =IFERROR(AU34/(AU9+AU10+AU14+AU18),0) -> 0 | AV39: =IFERROR(AV34/(AV9+AV10+AV14+AV18),0) -> -0.26565103 | AW39: =IFERROR(AW34/(AW9+AW10+AW14+AW18),0) -> -1.3154389 | AX39: =IFERROR(AX34/(AX9+AX10+AX14+AX18),0) -> 0 | AY39: =IFERROR(AY34/(AY9+AY10+AY14+AY18),0) -> 0 | ... BI39: =IFERROR(BI34/(BI9+BI10+BI14+BI18),0) -> 0
A40: % sobre Receita Líquida | I40: =IFERROR(I34/I32,0) -> 0 | J40: =IFERROR(J34/J32,0)+SUMIFS(Aut_Ajustes_Manuais!$G:$G,Aut_Ajustes_Manuais!$I:$I,DRE!H$4,Aut_Ajustes_Manuais!$F:$F,"% sobre Receita Líquida") -> 0 | L40: =IFERROR(L34/L32,0) -> 0 | M40: =IFERROR(M34/M32,0)+SUMIFS(Aut_Ajustes_Manuais!$G:$G,Aut_Ajustes_Manuais!$I:$I,DRE!K$4,Aut_Ajustes_Manuais!$F:$F,"% sobre Receita Líquida") -> 0 | O40: =IFERROR(O34/O32,0) -> 0 | P40: =IFERROR(P34/P32,0)+SUMIFS(Aut_Ajustes_Manuais!$G:$G,Aut_Ajustes_Manuais!$I:$I,DRE!N$4,Aut_Ajustes_Manuais!$F:$F,"% sobre Receita Líquida") -> 0 | R40: =IFERROR(R34/R32,0) -> 0 | S40: =IFERROR(S34/S32,0)+SUMIFS(Aut_Ajustes_Manuais!$G:$G,Aut_Ajustes_Manuais!$I:$I,DRE!Q$4,Aut_Ajustes_Manuais!$F:$F,"% sobre Receita Líquida") -> 0 | U40: =IFERROR(U34/U32,0) -> 0 | V40: =IFERROR(V34/V32,0)+SUMIFS(Aut_Ajustes_Manuais!$G:$G,Aut_Ajustes_Manuais!$I:$I,DRE!T$4,Aut_Ajustes_Manuais!$F:$F,"% sobre Receita Líquida") -> 0 | X40: =IFERROR(X34/X32,0) -> 0 | Y40: =IFERROR(Y34/Y32,0)+SUMIFS(Aut_Ajustes_Manuais!$G:$G,Aut_Ajustes_Manuais!$I:$I,DRE!W$4,Aut_Ajustes_Manuais!$F:$F,"% sobre Receita Líquida") -> 0 | AA40: =IFERROR(AA34/AA32,0) -> 0 | AB40: =IFERROR(AB34/AB32,0)+SUMIFS(Aut_Ajustes_Manuais!$G:$G,Aut_Ajustes_Manuais!$I:$I,DRE!Z$4,Aut_Ajustes_Manuais!$F:$F,"% sobre Receita Líquida") -> -0.84463512 | AD40: =IFERROR(AD34/AD32,0) -> -0.22523596 | AE40: =IFERROR(AE34/AE32,0)+SUMIFS(Aut_Ajustes_Manuais!$G:$G,Aut_Ajustes_Manuais!$I:$I,DRE!AC$4,Aut_Ajustes_Manuais!$F:$F,"% sobre Receita Líquida") -> 0 | AG40: =IFERROR(AG34/AG32,0) -> -0.20941903 | AH40: =IFERROR(AH34/AH32,0)+SUMIFS(Aut_Ajustes_Manuais!$G:$G,Aut_Ajustes_Manuais!$I:$I,DRE!AF$4,Aut_Ajustes_Manuais!$F:$F,"% sobre Receita Líquida") -> 0 | AJ40: =IFERROR(AJ34/AJ32,0) -> -0.20901562 | AK40: =IFERROR(AK34/AK32,0)+SUMIFS(Aut_Ajustes_Manuais!$G:$G,Aut_Ajustes_Manuais!$I:$I,DRE!AI$4,Aut_Ajustes_Manuais!$F:$F,"% sobre Receita Líquida") -> 0 | AM40: =IFERROR(AM34/AM32,0) -> -0.20929213 | AN40: =IFERROR(AN34/AN32,0)+SUMIFS(Aut_Ajustes_Manuais!$G:$G,Aut_Ajustes_Manuais!$I:$I,DRE!AL$4,Aut_Ajustes_Manuais!$F:$F,"% sobre Receita Líquida") -> 0 | AP40: =IFERROR(AP34/AP32,0) -> -0.20514495 | AQ40: =IFERROR(AQ34/AQ32,0)+SUMIFS(Aut_Ajustes_Manuais!$G:$G,Aut_Ajustes_Manuais!$I:$I,DRE!AO$4,Aut_Ajustes_Manuais!$F:$F,"% sobre Receita Líquida") -> 0 | AR40: =IFERROR(AR34/AR32,0) -> 0 | AS40: =IFERROR(AS34/AS32,0) -> -0.22523596 | AT40: =IFERROR(AT34/AT32,0) -> -1.183131 | AU40: =IFERROR(AU34/AU32,0) -> 0 | AV40: =IFERROR(AV34/AV32,0) -> -0.21152274 | AW40: =IFERROR(AW34/AW32,0) -> -1.183131 | AX40: =IFERROR(AX34/AX32,0) -> 0 | AY40: =IFERROR(AY34/AY32,0) -> 0 | ... BI40: =IFERROR(BI34/BI32,0) -> 0
A42: (-) Custos Artístico Geral | C42: Premissas | D42: Valores | E42: % Incid | H42: 0 | I42: =SUM(I43,I49) -> 0 | J42: =SUM(J43,J49)+SUMIFS(Aut_Ajustes_Manuais!$G:$G,Aut_Ajustes_Manuais!$I:$I,DRE!H$4,Aut_Ajustes_Manuais!$F:$F,"(-) Custos Artístico Geral") -> 0 | K42: 0 | L42: =SUM(L43,L49) -> 0 | M42: =SUM(M43,M49)+SUMIFS(Aut_Ajustes_Manuais!$G:$G,Aut_Ajustes_Manuais!$I:$I,DRE!K$4,Aut_Ajustes_Manuais!$F:$F,"(-) Custos Artístico Geral") -> 0 | O42: =SUM(O43,O49) -> 0 | P42: =SUM(P43,P49)+SUMIFS(Aut_Ajustes_Manuais!$G:$G,Aut_Ajustes_Manuais!$I:$I,DRE!N$4,Aut_Ajustes_Manuais!$F:$F,"(-) Custos Artístico Geral") -> 0 | R42: =SUM(R43,R49) -> 0 | S42: =SUM(S43,S49)+SUMIFS(Aut_Ajustes_Manuais!$G:$G,Aut_Ajustes_Manuais!$I:$I,DRE!Q$4,Aut_Ajustes_Manuais!$F:$F,"(-) Custos Artístico Geral") -> 0 | U42: =SUM(U43,U49) -> 0 | V42: =SUM(V43,V49)+SUMIFS(Aut_Ajustes_Manuais!$G:$G,Aut_Ajustes_Manuais!$I:$I,DRE!T$4,Aut_Ajustes_Manuais!$F:$F,"(-) Custos Artístico Geral") -> 0 | X42: =SUM(X43,X49) -> 0 | Y42: =SUM(Y43,Y49)+SUMIFS(Aut_Ajustes_Manuais!$G:$G,Aut_Ajustes_Manuais!$I:$I,DRE!W$4,Aut_Ajustes_Manuais!$F:$F,"(-) Custos Artístico Geral") -> 0 | AA42: =SUM(AA43,AA49) -> 0 | AB42: =SUM(AB43,AB49)+SUMIFS(Aut_Ajustes_Manuais!$G:$G,Aut_Ajustes_Manuais!$I:$I,DRE!Z$4,Aut_Ajustes_Manuais!$F:$F,"(-) Custos Artístico Geral") -> 0 | AD42: =SUM(AD43,AD49) -> -762578.47 | AE42: =SUM(AE43,AE49)+SUMIFS(Aut_Ajustes_Manuais!$G:$G,Aut_Ajustes_Manuais!$I:$I,DRE!AC$4,Aut_Ajustes_Manuais!$F:$F,"(-) Custos Artístico Geral") -> 0 | AG42: =SUM(AG43,AG49) -> -759794.22 | AH42: =SUM(AH43,AH49)+SUMIFS(Aut_Ajustes_Manuais!$G:$G,Aut_Ajustes_Manuais!$I:$I,DRE!AF$4,Aut_Ajustes_Manuais!$F:$F,"(-) Custos Artístico Geral") -> 0 | AJ42: =SUM(AJ43,AJ49) -> -764682.59 | AK42: =SUM(AK43,AK49)+SUMIFS(Aut_Ajustes_Manuais!$G:$G,Aut_Ajustes_Manuais!$I:$I,DRE!AI$4,Aut_Ajustes_Manuais!$F:$F,"(-) Custos Artístico Geral") -> 0 | AM42: =SUM(AM43,AM49) -> -759375.13 | AN42: =SUM(AN43,AN49)+SUMIFS(Aut_Ajustes_Manuais!$G:$G,Aut_Ajustes_Manuais!$I:$I,DRE!AL$4,Aut_Ajustes_Manuais!$F:$F,"(-) Custos Artístico Geral") -> 0 | AP42: =SUM(AP43,AP49) -> -758521.61 | AQ42: =SUM(AQ43,AQ49)+SUMIFS(Aut_Ajustes_Manuais!$G:$G,Aut_Ajustes_Manuais!$I:$I,DRE!AO$4,Aut_Ajustes_Manuais!$F:$F,"(-) Custos Artístico Geral") -> 0 | AR42: =SUM(AR43,AR49) -> 0 | AS42: =SUM(AS43,AS49) -> -762578.47 | AT42: =SUM(AT43,AT49) -> 0 | AU42: =SUM(AU43,AU49) -> 0 | AV42: =SUM(AV43,AV49) -> -3804952 | AW42: =SUM(AW43,AW49) -> 0 | AX42: =SUM(AX43,AX49) -> 0 | AY42: =SUM(AY43,AY49) -> 0 | ... BI42: =SUM(BI43,BI49) -> 0
A43: Custos Artístico | H43: 0 | I43: =SUM(I44:I48) -> 0 | J43: =SUM(J44:J48)+SUMIFS(Aut_Ajustes_Manuais!$G:$G,Aut_Ajustes_Manuais!$I:$I,DRE!H$4,Aut_Ajustes_Manuais!$F:$F,"Custos Artístico") -> 0 | K43: 0 | L43: =SUM(L44:L48) -> 0 | M43: =SUM(M44:M48)+SUMIFS(Aut_Ajustes_Manuais!$G:$G,Aut_Ajustes_Manuais!$I:$I,DRE!K$4,Aut_Ajustes_Manuais!$F:$F,"Custos Artístico") -> 0 | O43: =SUM(O44:O48) -> 0 | P43: =SUM(P44:P48)+SUMIFS(Aut_Ajustes_Manuais!$G:$G,Aut_Ajustes_Manuais!$I:$I,DRE!N$4,Aut_Ajustes_Manuais!$F:$F,"Custos Artístico") -> 0 | Q43: 0 | R43: =SUM(R44:R48) -> 0 | S43: =SUM(S44:S48)+SUMIFS(Aut_Ajustes_Manuais!$G:$G,Aut_Ajustes_Manuais!$I:$I,DRE!Q$4,Aut_Ajustes_Manuais!$F:$F,"Custos Artístico") -> 0 | T43: 0 | U43: =SUM(U44:U48) -> 0 | V43: =SUM(V44:V48)+SUMIFS(Aut_Ajustes_Manuais!$G:$G,Aut_Ajustes_Manuais!$I:$I,DRE!T$4,Aut_Ajustes_Manuais!$F:$F,"Custos Artístico") -> 0 | W43: 0 | X43: =SUM(X44:X48) -> 0 | Y43: =SUM(Y44:Y48)+SUMIFS(Aut_Ajustes_Manuais!$G:$G,Aut_Ajustes_Manuais!$I:$I,DRE!W$4,Aut_Ajustes_Manuais!$F:$F,"Custos Artístico") -> 0 | Z43: 0 | AA43: =SUM(AA44:AA48) -> 0 | AB43: =SUM(AB44:AB48)+SUMIFS(Aut_Ajustes_Manuais!$G:$G,Aut_Ajustes_Manuais!$I:$I,DRE!Z$4,Aut_Ajustes_Manuais!$F:$F,"Custos Artístico") -> 0 | AC43: 0 | AD43: =SUM(AD44:AD48) -> -738078.47 | AE43: =SUM(AE44:AE48)+SUMIFS(Aut_Ajustes_Manuais!$G:$G,Aut_Ajustes_Manuais!$I:$I,DRE!AC$4,Aut_Ajustes_Manuais!$F:$F,"Custos Artístico") -> 0 | AF43: 0 | AG43: =SUM(AG44:AG48) -> -735294.22 | AH43: =SUM(AH44:AH48)+SUMIFS(Aut_Ajustes_Manuais!$G:$G,Aut_Ajustes_Manuais!$I:$I,DRE!AF$4,Aut_Ajustes_Manuais!$F:$F,"Custos Artístico") -> 0 | AI43: 0 | AJ43: =SUM(AJ44:AJ48) -> -740182.59 | AK43: =SUM(AK44:AK48)+SUMIFS(Aut_Ajustes_Manuais!$G:$G,Aut_Ajustes_Manuais!$I:$I,DRE!AI$4,Aut_Ajustes_Manuais!$F:$F,"Custos Artístico") -> 0 | AL43: 0 | AM43: =SUM(AM44:AM48) -> -734875.13 | AN43: =SUM(AN44:AN48)+SUMIFS(Aut_Ajustes_Manuais!$G:$G,Aut_Ajustes_Manuais!$I:$I,DRE!AL$4,Aut_Ajustes_Manuais!$F:$F,"Custos Artístico") -> 0 | AO43: 0 | AP43: =SUM(AP44:AP48) -> -734021.61 | AQ43: =SUM(AQ44:AQ48)+SUMIFS(Aut_Ajustes_Manuais!$G:$G,Aut_Ajustes_Manuais!$I:$I,DRE!AO$4,Aut_Ajustes_Manuais!$F:$F,"Custos Artístico") -> 0 | AR43: =SUMIFS($H43:$AO43,$H$5:$AO$5,"<"&MONTH(TODAY()),$H$6:$AO$6,"REAL 25") -> 0 | AS43: =SUMIFS($I43:$AP43,$I$5:$AP$5,"<"&MONTH(TODAY()),$I$6:$AP$6,"ORÇADO ") -> -738078.47 | AT43: =SUMIFS($J43:$AQ43,$J$5:$AQ$5,"<"&MONTH(TODAY()),$J$6:$AQ$6,"REAL 26") -> 0 | AU43: =SUM(AU44:AU48) -> 0 | AV43: =SUM(AV44:AV48) -> -3682452 | AW43: =SUM(AW44:AW48) -> 0 | AX43: =SUM(AX44:AX48) -> 0 | AY43: =SUM(AY44:AY48) -> 0 | AZ43: =SUM(AZ44:AZ48) -> 0 | BA43: =SUM(BA44:BA48) -> 0 | BB43: =SUM(BB44:BB48) -> 0 | ... BI43: =SUM(BI44:BI48) -> 0
A44: Cachê de Músicos e Artistas | C44: Estim. Mensal | E44: 0.0067 | H44: 0 | I44: =-SUMIFS(T_ORCAMENTOS!$E:$E,T_ORCAMENTOS!$C:$C,"Cachê de Músicos e Artistas",T_ORCAMENTOS!$H:$H,"1/2026") -> 0 | J44: =SUMIFS(Aut_BlueMe_Sem_Pedido!$J:$J,Aut_BlueMe_Sem_Pedido!$Q:$Q,DRE!H$4,Aut_BlueMe_Sem_Pedido!$H:$H,DRE!$A44)+SUMIFS(Aut_Ajustes_Manuais!$G:$G,Aut_Ajustes_Manuais!$I:$I,DRE!H$4,Aut_Ajustes_Manuais!$F:$F,"Cachê de Músicos e Artistas") -> 0 | K44: 0 | L44: =-SUMIFS(T_ORCAMENTOS!$E:$E,T_ORCAMENTOS!$C:$C,"Cachê de Músicos e Artistas",T_ORCAMENTOS!$H:$H,"2/2026") -> 0 | M44: =SUMIFS(Aut_BlueMe_Sem_Pedido!$J:$J,Aut_BlueMe_Sem_Pedido!$Q:$Q,DRE!K$4,Aut_BlueMe_Sem_Pedido!$H:$H,DRE!$A44)+SUMIFS(Aut_Ajustes_Manuais!$G:$G,Aut_Ajustes_Manuais!$I:$I,DRE!K$4,Aut_Ajustes_Manuais!$F:$F,"Cachê de Músicos e Artistas") -> 0 | O44: =-SUMIFS(T_ORCAMENTOS!$E:$E,T_ORCAMENTOS!$C:$C,"Cachê de Músicos e Artistas",T_ORCAMENTOS!$H:$H,"3/2026") -> 0 | P44: =SUMIFS(Aut_BlueMe_Sem_Pedido!$J:$J,Aut_BlueMe_Sem_Pedido!$Q:$Q,DRE!N$4,Aut_BlueMe_Sem_Pedido!$H:$H,DRE!$A44)+SUMIFS(Aut_Ajustes_Manuais!$G:$G,Aut_Ajustes_Manuais!$I:$I,DRE!N$4,Aut_Ajustes_Manuais!$F:$F,"Cachê de Músicos e Artistas") -> 0 | Q44: 0 | R44: =-SUMIFS(T_ORCAMENTOS!$E:$E,T_ORCAMENTOS!$C:$C,"Cachê de Músicos e Artistas",T_ORCAMENTOS!$H:$H,"4/2026") -> 0 | S44: =SUMIFS(Aut_BlueMe_Sem_Pedido!$J:$J,Aut_BlueMe_Sem_Pedido!$Q:$Q,DRE!Q$4,Aut_BlueMe_Sem_Pedido!$H:$H,DRE!$A44)+SUMIFS(Aut_Ajustes_Manuais!$G:$G,Aut_Ajustes_Manuais!$I:$I,DRE!Q$4,Aut_Ajustes_Manuais!$F:$F,"Cachê de Músicos e Artistas") -> 0 | T44: 0 | U44: =-SUMIFS(T_ORCAMENTOS!$E:$E,T_ORCAMENTOS!$C:$C,"Cachê de Músicos e Artistas",T_ORCAMENTOS!$H:$H,"5/2026") -> 0 | V44: =SUMIFS(Aut_BlueMe_Sem_Pedido!$J:$J,Aut_BlueMe_Sem_Pedido!$Q:$Q,DRE!T$4,Aut_BlueMe_Sem_Pedido!$H:$H,DRE!$A44)+SUMIFS(Aut_Ajustes_Manuais!$G:$G,Aut_Ajustes_Manuais!$I:$I,DRE!T$4,Aut_Ajustes_Manuais!$F:$F,"Cachê de Músicos e Artistas") -> 0 | W44: 0 | X44: =-SUMIFS(T_ORCAMENTOS!$E:$E,T_ORCAMENTOS!$C:$C,"Cachê de Músicos e Artistas",T_ORCAMENTOS!$H:$H,"6/2026") -> 0 | Y44: =SUMIFS(Aut_BlueMe_Sem_Pedido!$J:$J,Aut_BlueMe_Sem_Pedido!$Q:$Q,DRE!W$4,Aut_BlueMe_Sem_Pedido!$H:$H,DRE!$A44)+SUMIFS(Aut_Ajustes_Manuais!$G:$G,Aut_Ajustes_Manuais!$I:$I,DRE!W$4,Aut_Ajustes_Manuais!$F:$F,"Cachê de Músicos e Artistas") -> 0 | Z44: 0 | AA44: =-SUMIFS(T_ORCAMENTOS!$E:$E,T_ORCAMENTOS!$C:$C,"Cachê de Músicos e Artistas",T_ORCAMENTOS!$H:$H,"7/2026") -> 0 | AB44: =SUMIFS(Aut_BlueMe_Sem_Pedido!$J:$J,Aut_BlueMe_Sem_Pedido!$Q:$Q,DRE!Z$4,Aut_BlueMe_Sem_Pedido!$H:$H,DRE!$A44)+SUMIFS(Aut_Ajustes_Manuais!$G:$G,Aut_Ajustes_Manuais!$I:$I,DRE!Z$4,Aut_Ajustes_Manuais!$F:$F,"Cachê de Músicos e Artistas") -> 0 | AC44: 0 | AD44: =-SUMIFS(T_ORCAMENTOS!$E:$E,T_ORCAMENTOS!$C:$C,"Cachê de Músicos e Artistas",T_ORCAMENTOS!$H:$H,"8/2026") -> -684600 | AE44: =SUMIFS(Aut_BlueMe_Sem_Pedido!$J:$J,Aut_BlueMe_Sem_Pedido!$Q:$Q,DRE!AC$4,Aut_BlueMe_Sem_Pedido!$H:$H,DRE!$A44)+SUMIFS(Aut_Ajustes_Manuais!$G:$G,Aut_Ajustes_Manuais!$I:$I,DRE!AC$4,Aut_Ajustes_Manuais!$F:$F,"Cachê de Músicos e Artistas") -> 0 | AF44: 0 | AG44: =-SUMIFS(T_ORCAMENTOS!$E:$E,T_ORCAMENTOS!$C:$C,"Cachê de Músicos e Artistas",T_ORCAMENTOS!$H:$H,"9/2026") -> -684600 | AH44: =SUMIFS(Aut_BlueMe_Sem_Pedido!$J:$J,Aut_BlueMe_Sem_Pedido!$Q:$Q,DRE!AF$4,Aut_BlueMe_Sem_Pedido!$H:$H,DRE!$A44)+SUMIFS(Aut_Ajustes_Manuais!$G:$G,Aut_Ajustes_Manuais!$I:$I,DRE!AF$4,Aut_Ajustes_Manuais!$F:$F,"Cachê de Músicos e Artistas") -> 0 | AI44: 0 | AJ44: =-SUMIFS(T_ORCAMENTOS!$E:$E,T_ORCAMENTOS!$C:$C,"Cachê de Músicos e Artistas",T_ORCAMENTOS!$H:$H,"10/2026") -> -684600 | AK44: =SUMIFS(Aut_BlueMe_Sem_Pedido!$J:$J,Aut_BlueMe_Sem_Pedido!$Q:$Q,DRE!AI$4,Aut_BlueMe_Sem_Pedido!$H:$H,DRE!$A44)+SUMIFS(Aut_Ajustes_Manuais!$G:$G,Aut_Ajustes_Manuais!$I:$I,DRE!AI$4,Aut_Ajustes_Manuais!$F:$F,"Cachê de Músicos e Artistas") -> 0 | AL44: 0 | AM44: =-SUMIFS(T_ORCAMENTOS!$E:$E,T_ORCAMENTOS!$C:$C,"Cachê de Músicos e Artistas",T_ORCAMENTOS!$H:$H,"11/2026") -> -684600 | AN44: =SUMIFS(Aut_BlueMe_Sem_Pedido!$J:$J,Aut_BlueMe_Sem_Pedido!$Q:$Q,DRE!AL$4,Aut_BlueMe_Sem_Pedido!$H:$H,DRE!$A44)+SUMIFS(Aut_Ajustes_Manuais!$G:$G,Aut_Ajustes_Manuais!$I:$I,DRE!AL$4,Aut_Ajustes_Manuais!$F:$F,"Cachê de Músicos e Artistas") -> 0 | AO44: 0 | AP44: =-SUMIFS(T_ORCAMENTOS!$E:$E,T_ORCAMENTOS!$C:$C,"Cachê de Músicos e Artistas",T_ORCAMENTOS!$H:$H,"12/2026") -> -684600 | AQ44: =SUMIFS(Aut_BlueMe_Sem_Pedido!$J:$J,Aut_BlueMe_Sem_Pedido!$Q:$Q,DRE!AO$4,Aut_BlueMe_Sem_Pedido!$H:$H,DRE!$A44)+SUMIFS(Aut_Ajustes_Manuais!$G:$G,Aut_Ajustes_Manuais!$I:$I,DRE!AO$4,Aut_Ajustes_Manuais!$F:$F,"Cachê de Músicos e Artistas") -> 0 | AR44: =SUMIFS($H44:$AO44,$H$5:$AO$5,"<"&MONTH(TODAY()),$H$6:$AO$6,"REAL 25") -> 0 | AS44: =SUMIFS($I44:$AP44,$I$5:$AP$5,"<"&MONTH(TODAY()),$I$6:$AP$6,"ORÇADO ") -> -684600 | AT44: =SUMIFS($J44:$AQ44,$J$5:$AQ$5,"<"&MONTH(TODAY()),$J$6:$AQ$6,"REAL 26") -> 0 | AU44: =SUM(H44,K44,N44,Q44,T44,W44,Z44,AC44,AF44,AI44,AL44,AO44) -> 0 | AV44: =SUM(I44,L44,O44,R44,U44,X44,AA44,AD44,AG44,AJ44,AM44,AP44) -> -3423000 | AW44: =SUM(J44,M44,P44,S44,V44,Y44,AB44,AE44,AH44,AK44,AN44,AQ44) -> 0 | AX44: =SUM(H44,K44,N44) -> 0 | AY44: =SUM(I44,L44,O44) -> 0 | AZ44: =SUM(J44,M44,P44) -> 0 | BA44: =SUM(Q44,T44,W44) -> 0 | BB44: =SUM(R44,U44,X44) -> 0 | BC44: =SUM(S44,V44,Y44) -> 0 | BD44: =SUM(Z44,AC44,AF44) -> 0 | BE44: =SUM(AA44,AD44,AG44) -> -1369200 | BF44: =SUM(AB44,AE44,AH44) -> 0 | BG44: =SUM(AI44,AL44,AO44) -> 0 | BH44: =SUM(AJ44,AM44,AP44) -> -2053800 | BI44: =SUM(AK44,AN44,AQ44) -> 0
A45: Alimentação e Transporte | C45: Estim. Mensal | E45: 0.0067 | H45: 0 | I45: =-SUMIFS(T_ORCAMENTOS!$E:$E,T_ORCAMENTOS!$C:$C,"Alimentação e Transporte",T_ORCAMENTOS!$H:$H,"1/2026") -> 0 | J45: =SUMIFS(Aut_BlueMe_Sem_Pedido!$J:$J,Aut_BlueMe_Sem_Pedido!$Q:$Q,DRE!H$4,Aut_BlueMe_Sem_Pedido!$H:$H,DRE!$A45)-SUMIFS(Aut_Descontos!$G:$G,Aut_Descontos!$H:$H,DRE!$A45,Aut_Descontos!$L:$L,DRE!H$4)+SUMIFS(Aut_Ajustes_Manuais!$G:$G,Aut_Ajustes_Manuais!$I:$I,DRE!H$4,Aut_Ajustes_Manuais!$F:$F,"Alimentação e Transporte") -> 0 | K45: 0 | L45: =-SUMIFS(T_ORCAMENTOS!$E:$E,T_ORCAMENTOS!$C:$C,"Alimentação e Transporte",T_ORCAMENTOS!$H:$H,"2/2026") -> 0 | M45: =SUMIFS(Aut_BlueMe_Sem_Pedido!$J:$J,Aut_BlueMe_Sem_Pedido!$Q:$Q,DRE!K$4,Aut_BlueMe_Sem_Pedido!$H:$H,DRE!$A45)-SUMIFS(Aut_Descontos!$G:$G,Aut_Descontos!$H:$H,DRE!$A45,Aut_Descontos!$L:$L,DRE!K$4)+SUMIFS(Aut_Ajustes_Manuais!$G:$G,Aut_Ajustes_Manuais!$I:$I,DRE!K$4,Aut_Ajustes_Manuais!$F:$F,"Alimentação e Transporte") -> 0 | N45: 0 | O45: =-SUMIFS(T_ORCAMENTOS!$E:$E,T_ORCAMENTOS!$C:$C,"Alimentação e Transporte",T_ORCAMENTOS!$H:$H,"3/2026") -> 0 | P45: =SUMIFS(Aut_BlueMe_Sem_Pedido!$J:$J,Aut_BlueMe_Sem_Pedido!$Q:$Q,DRE!N$4,Aut_BlueMe_Sem_Pedido!$H:$H,DRE!$A45)-SUMIFS(Aut_Descontos!$G:$G,Aut_Descontos!$H:$H,DRE!$A45,Aut_Descontos!$L:$L,DRE!N$4)+SUMIFS(Aut_Ajustes_Manuais!$G:$G,Aut_Ajustes_Manuais!$I:$I,DRE!N$4,Aut_Ajustes_Manuais!$F:$F,"Alimentação e Transporte") -> 0 | Q45: 0 | R45: =-SUMIFS(T_ORCAMENTOS!$E:$E,T_ORCAMENTOS!$C:$C,"Alimentação e Transporte",T_ORCAMENTOS!$H:$H,"4/2026") -> 0 | S45: =SUMIFS(Aut_BlueMe_Sem_Pedido!$J:$J,Aut_BlueMe_Sem_Pedido!$Q:$Q,DRE!Q$4,Aut_BlueMe_Sem_Pedido!$H:$H,DRE!$A45)-SUMIFS(Aut_Descontos!$G:$G,Aut_Descontos!$H:$H,DRE!$A45,Aut_Descontos!$L:$L,DRE!Q$4)+SUMIFS(Aut_Ajustes_Manuais!$G:$G,Aut_Ajustes_Manuais!$I:$I,DRE!Q$4,Aut_Ajustes_Manuais!$F:$F,"Alimentação e Transporte") -> 0 | T45: 0 | U45: =-SUMIFS(T_ORCAMENTOS!$E:$E,T_ORCAMENTOS!$C:$C,"Alimentação e Transporte",T_ORCAMENTOS!$H:$H,"5/2026") -> 0 | V45: =SUMIFS(Aut_BlueMe_Sem_Pedido!$J:$J,Aut_BlueMe_Sem_Pedido!$Q:$Q,DRE!T$4,Aut_BlueMe_Sem_Pedido!$H:$H,DRE!$A45)-SUMIFS(Aut_Descontos!$G:$G,Aut_Descontos!$H:$H,DRE!$A45,Aut_Descontos!$L:$L,DRE!T$4)+SUMIFS(Aut_Ajustes_Manuais!$G:$G,Aut_Ajustes_Manuais!$I:$I,DRE!T$4,Aut_Ajustes_Manuais!$F:$F,"Alimentação e Transporte") -> 0 | W45: 0 | X45: =-SUMIFS(T_ORCAMENTOS!$E:$E,T_ORCAMENTOS!$C:$C,"Alimentação e Transporte",T_ORCAMENTOS!$H:$H,"6/2026") -> 0 | Y45: =SUMIFS(Aut_BlueMe_Sem_Pedido!$J:$J,Aut_BlueMe_Sem_Pedido!$Q:$Q,DRE!W$4,Aut_BlueMe_Sem_Pedido!$H:$H,DRE!$A45)-SUMIFS(Aut_Descontos!$G:$G,Aut_Descontos!$H:$H,DRE!$A45,Aut_Descontos!$L:$L,DRE!W$4)+SUMIFS(Aut_Ajustes_Manuais!$G:$G,Aut_Ajustes_Manuais!$I:$I,DRE!W$4,Aut_Ajustes_Manuais!$F:$F,"Alimentação e Transporte") -> 0 | Z45: 0 | AA45: =-SUMIFS(T_ORCAMENTOS!$E:$E,T_ORCAMENTOS!$C:$C,"Alimentação e Transporte",T_ORCAMENTOS!$H:$H,"7/2026") -> 0 | AB45: =SUMIFS(Aut_BlueMe_Sem_Pedido!$J:$J,Aut_BlueMe_Sem_Pedido!$Q:$Q,DRE!Z$4,Aut_BlueMe_Sem_Pedido!$H:$H,DRE!$A45)-SUMIFS(Aut_Descontos!$G:$G,Aut_Descontos!$H:$H,DRE!$A45,Aut_Descontos!$L:$L,DRE!Z$4)+SUMIFS(Aut_Ajustes_Manuais!$G:$G,Aut_Ajustes_Manuais!$I:$I,DRE!Z$4,Aut_Ajustes_Manuais!$F:$F,"Alimentação e Transporte") -> 0 | AC45: 0 | AD45: =-SUMIFS(T_ORCAMENTOS!$E:$E,T_ORCAMENTOS!$C:$C,"Alimentação e Transporte",T_ORCAMENTOS!$H:$H,"8/2026") -> -53478.47 | AE45: =SUMIFS(Aut_BlueMe_Sem_Pedido!$J:$J,Aut_BlueMe_Sem_Pedido!$Q:$Q,DRE!AC$4,Aut_BlueMe_Sem_Pedido!$H:$H,DRE!$A45)-SUMIFS(Aut_Descontos!$G:$G,Aut_Descontos!$H:$H,DRE!$A45,Aut_Descontos!$L:$L,DRE!AC$4)+SUMIFS(Aut_Ajustes_Manuais!$G:$G,Aut_Ajustes_Manuais!$I:$I,DRE!AC$4,Aut_Ajustes_Manuais!$F:$F,"Alimentação e Transporte") -> 0 | AF45: 0 | AG45: =-SUMIFS(T_ORCAMENTOS!$E:$E,T_ORCAMENTOS!$C:$C,"Alimentação e Transporte",T_ORCAMENTOS!$H:$H,"9/2026") -> -50694.22 | AH45: =SUMIFS(Aut_BlueMe_Sem_Pedido!$J:$J,Aut_BlueMe_Sem_Pedido!$Q:$Q,DRE!AF$4,Aut_BlueMe_Sem_Pedido!$H:$H,DRE!$A45)-SUMIFS(Aut_Descontos!$G:$G,Aut_Descontos!$H:$H,DRE!$A45,Aut_Descontos!$L:$L,DRE!AF$4)+SUMIFS(Aut_Ajustes_Manuais!$G:$G,Aut_Ajustes_Manuais!$I:$I,DRE!AF$4,Aut_Ajustes_Manuais!$F:$F,"Alimentação e Transporte") -> 0 | AI45: 0 | AJ45: =-SUMIFS(T_ORCAMENTOS!$E:$E,T_ORCAMENTOS!$C:$C,"Alimentação e Transporte",T_ORCAMENTOS!$H:$H,"10/2026") -> -55582.59 | AK45: =SUMIFS(Aut_BlueMe_Sem_Pedido!$J:$J,Aut_BlueMe_Sem_Pedido!$Q:$Q,DRE!AI$4,Aut_BlueMe_Sem_Pedido!$H:$H,DRE!$A45)-SUMIFS(Aut_Descontos!$G:$G,Aut_Descontos!$H:$H,DRE!$A45,Aut_Descontos!$L:$L,DRE!AI$4)+SUMIFS(Aut_Ajustes_Manuais!$G:$G,Aut_Ajustes_Manuais!$I:$I,DRE!AI$4,Aut_Ajustes_Manuais!$F:$F,"Alimentação e Transporte") -> 0 | AL45: 0 | AM45: =-SUMIFS(T_ORCAMENTOS!$E:$E,T_ORCAMENTOS!$C:$C,"Alimentação e Transporte",T_ORCAMENTOS!$H:$H,"11/2026") -> -50275.13 | AN45: =SUMIFS(Aut_BlueMe_Sem_Pedido!$J:$J,Aut_BlueMe_Sem_Pedido!$Q:$Q,DRE!AL$4,Aut_BlueMe_Sem_Pedido!$H:$H,DRE!$A45)-SUMIFS(Aut_Descontos!$G:$G,Aut_Descontos!$H:$H,DRE!$A45,Aut_Descontos!$L:$L,DRE!AL$4)+SUMIFS(Aut_Ajustes_Manuais!$G:$G,Aut_Ajustes_Manuais!$I:$I,DRE!AL$4,Aut_Ajustes_Manuais!$F:$F,"Alimentação e Transporte") -> 0 | AO45: 0 | AP45: =-SUMIFS(T_ORCAMENTOS!$E:$E,T_ORCAMENTOS!$C:$C,"Alimentação e Transporte",T_ORCAMENTOS!$H:$H,"12/2026") -> -49421.61 | AQ45: =SUMIFS(Aut_BlueMe_Sem_Pedido!$J:$J,Aut_BlueMe_Sem_Pedido!$Q:$Q,DRE!AO$4,Aut_BlueMe_Sem_Pedido!$H:$H,DRE!$A45)-SUMIFS(Aut_Descontos!$G:$G,Aut_Descontos!$H:$H,DRE!$A45,Aut_Descontos!$L:$L,DRE!AO$4)+SUMIFS(Aut_Ajustes_Manuais!$G:$G,Aut_Ajustes_Manuais!$I:$I,DRE!AO$4,Aut_Ajustes_Manuais!$F:$F,"Alimentação e Transporte") -> 0 | AR45: =SUMIFS($H45:$AO45,$H$5:$AO$5,"<"&MONTH(TODAY()),$H$6:$AO$6,"REAL 25") -> 0 | AS45: =SUMIFS($I45:$AP45,$I$5:$AP$5,"<"&MONTH(TODAY()),$I$6:$AP$6,"ORÇADO ") -> -53478.47 | AT45: =SUMIFS($J45:$AQ45,$J$5:$AQ$5,"<"&MONTH(TODAY()),$J$6:$AQ$6,"REAL 26") -> 0 | AU45: =SUM(H45,K45,N45,Q45,T45,W45,Z45,AC45,AF45,AI45,AL45,AO45) -> 0 | AV45: =SUM(I45,L45,O45,R45,U45,X45,AA45,AD45,AG45,AJ45,AM45,AP45) -> -259452.02 | AW45: =SUM(J45,M45,P45,S45,V45,Y45,AB45,AE45,AH45,AK45,AN45,AQ45) -> 0 | AX45: =SUM(H45,K45,N45) -> 0 | AY45: =SUM(I45,L45,O45) -> 0 | AZ45: =SUM(J45,M45,P45) -> 0 | BA45: =SUM(Q45,T45,W45) -> 0 | BB45: =SUM(R45,U45,X45) -> 0 | BC45: =SUM(S45,V45,Y45) -> 0 | BD45: =SUM(Z45,AC45,AF45) -> 0 | BE45: =SUM(AA45,AD45,AG45) -> -104172.69 | BF45: =SUM(AB45,AE45,AH45) -> 0 | BG45: =SUM(AI45,AL45,AO45) -> 0 | BH45: =SUM(AJ45,AM45,AP45) -> -155279.33 | BI45: =SUM(AK45,AN45,AQ45) -> 0
A46: Viagens e Estadias | C46: Estim. Mensal | H46: 0 | I46: 0 | J46: =SUMIFS(Aut_BlueMe_Sem_Pedido!$J:$J,Aut_BlueMe_Sem_Pedido!$Q:$Q,DRE!H$4,Aut_BlueMe_Sem_Pedido!$H:$H,DRE!$A46)+SUMIFS(Aut_Ajustes_Manuais!$G:$G,Aut_Ajustes_Manuais!$I:$I,DRE!H$4,Aut_Ajustes_Manuais!$F:$F,"Viagens e Estadias") -> 0 | K46: 0 | L46: 0 | M46: =SUMIFS(Aut_BlueMe_Sem_Pedido!$J:$J,Aut_BlueMe_Sem_Pedido!$Q:$Q,DRE!K$4,Aut_BlueMe_Sem_Pedido!$H:$H,DRE!$A46)+SUMIFS(Aut_Ajustes_Manuais!$G:$G,Aut_Ajustes_Manuais!$I:$I,DRE!K$4,Aut_Ajustes_Manuais!$F:$F,"Viagens e Estadias") -> 0 | N46: 0 | O46: 0 | P46: =SUMIFS(Aut_BlueMe_Sem_Pedido!$J:$J,Aut_BlueMe_Sem_Pedido!$Q:$Q,DRE!N$4,Aut_BlueMe_Sem_Pedido!$H:$H,DRE!$A46)+SUMIFS(Aut_Ajustes_Manuais!$G:$G,Aut_Ajustes_Manuais!$I:$I,DRE!N$4,Aut_Ajustes_Manuais!$F:$F,"Viagens e Estadias") -> 0 | Q46: 0 | R46: 0 | S46: =SUMIFS(Aut_BlueMe_Sem_Pedido!$J:$J,Aut_BlueMe_Sem_Pedido!$Q:$Q,DRE!Q$4,Aut_BlueMe_Sem_Pedido!$H:$H,DRE!$A46)+SUMIFS(Aut_Ajustes_Manuais!$G:$G,Aut_Ajustes_Manuais!$I:$I,DRE!Q$4,Aut_Ajustes_Manuais!$F:$F,"Viagens e Estadias") -> 0 | T46: 0 | U46: 0 | V46: =SUMIFS(Aut_BlueMe_Sem_Pedido!$J:$J,Aut_BlueMe_Sem_Pedido!$Q:$Q,DRE!T$4,Aut_BlueMe_Sem_Pedido!$H:$H,DRE!$A46)+SUMIFS(Aut_Ajustes_Manuais!$G:$G,Aut_Ajustes_Manuais!$I:$I,DRE!T$4,Aut_Ajustes_Manuais!$F:$F,"Viagens e Estadias") -> 0 | W46: 0 | X46: 0 | Y46: =SUMIFS(Aut_BlueMe_Sem_Pedido!$J:$J,Aut_BlueMe_Sem_Pedido!$Q:$Q,DRE!W$4,Aut_BlueMe_Sem_Pedido!$H:$H,DRE!$A46)+SUMIFS(Aut_Ajustes_Manuais!$G:$G,Aut_Ajustes_Manuais!$I:$I,DRE!W$4,Aut_Ajustes_Manuais!$F:$F,"Viagens e Estadias") -> 0 | Z46: 0 | AA46: 0 | AB46: =SUMIFS(Aut_BlueMe_Sem_Pedido!$J:$J,Aut_BlueMe_Sem_Pedido!$Q:$Q,DRE!Z$4,Aut_BlueMe_Sem_Pedido!$H:$H,DRE!$A46)+SUMIFS(Aut_Ajustes_Manuais!$G:$G,Aut_Ajustes_Manuais!$I:$I,DRE!Z$4,Aut_Ajustes_Manuais!$F:$F,"Viagens e Estadias") -> 0 | AC46: 0 | AD46: 0 | AE46: =SUMIFS(Aut_BlueMe_Sem_Pedido!$J:$J,Aut_BlueMe_Sem_Pedido!$Q:$Q,DRE!AC$4,Aut_BlueMe_Sem_Pedido!$H:$H,DRE!$A46)+SUMIFS(Aut_Ajustes_Manuais!$G:$G,Aut_Ajustes_Manuais!$I:$I,DRE!AC$4,Aut_Ajustes_Manuais!$F:$F,"Viagens e Estadias") -> 0 | AF46: 0 | AG46: 0 | AH46: =SUMIFS(Aut_BlueMe_Sem_Pedido!$J:$J,Aut_BlueMe_Sem_Pedido!$Q:$Q,DRE!AF$4,Aut_BlueMe_Sem_Pedido!$H:$H,DRE!$A46)+SUMIFS(Aut_Ajustes_Manuais!$G:$G,Aut_Ajustes_Manuais!$I:$I,DRE!AF$4,Aut_Ajustes_Manuais!$F:$F,"Viagens e Estadias") -> 0 | AI46: 0 | AJ46: 0 | AK46: =SUMIFS(Aut_BlueMe_Sem_Pedido!$J:$J,Aut_BlueMe_Sem_Pedido!$Q:$Q,DRE!AI$4,Aut_BlueMe_Sem_Pedido!$H:$H,DRE!$A46)+SUMIFS(Aut_Ajustes_Manuais!$G:$G,Aut_Ajustes_Manuais!$I:$I,DRE!AI$4,Aut_Ajustes_Manuais!$F:$F,"Viagens e Estadias") -> 0 | AL46: 0 | AM46: 0 | AN46: =SUMIFS(Aut_BlueMe_Sem_Pedido!$J:$J,Aut_BlueMe_Sem_Pedido!$Q:$Q,DRE!AL$4,Aut_BlueMe_Sem_Pedido!$H:$H,DRE!$A46)+SUMIFS(Aut_Ajustes_Manuais!$G:$G,Aut_Ajustes_Manuais!$I:$I,DRE!AL$4,Aut_Ajustes_Manuais!$F:$F,"Viagens e Estadias") -> 0 | AO46: 0 | AP46: 0 | AQ46: =SUMIFS(Aut_BlueMe_Sem_Pedido!$J:$J,Aut_BlueMe_Sem_Pedido!$Q:$Q,DRE!AO$4,Aut_BlueMe_Sem_Pedido!$H:$H,DRE!$A46)+SUMIFS(Aut_Ajustes_Manuais!$G:$G,Aut_Ajustes_Manuais!$I:$I,DRE!AO$4,Aut_Ajustes_Manuais!$F:$F,"Viagens e Estadias") -> 0 | AR46: =SUMIFS($H46:$AO46,$H$5:$AO$5,"<"&MONTH(TODAY()),$H$6:$AO$6,"REAL 25") -> 0 | AS46: =SUMIFS($I46:$AP46,$I$5:$AP$5,"<"&MONTH(TODAY()),$I$6:$AP$6,"ORÇADO ") -> 0 | AT46: =SUMIFS($J46:$AQ46,$J$5:$AQ$5,"<"&MONTH(TODAY()),$J$6:$AQ$6,"REAL 26") -> 0 | AU46: =SUM(H46,K46,N46,Q46,T46,W46,Z46,AC46,AF46,AI46,AL46,AO46) -> 0 | AV46: =SUM(I46,L46,O46,R46,U46,X46,AA46,AD46,AG46,AJ46,AM46,AP46) -> 0 | AW46: =SUM(J46,M46,P46,S46,V46,Y46,AB46,AE46,AH46,AK46,AN46,AQ46) -> 0 | AX46: =SUM(H46,K46,N46) -> 0 | AY46: =SUM(I46,L46,O46) -> 0 | AZ46: =SUM(J46,M46,P46) -> 0 | BA46: =SUM(Q46,T46,W46) -> 0 | BB46: =SUM(R46,U46,X46) -> 0 | BC46: =SUM(S46,V46,Y46) -> 0 | BD46: =SUM(Z46,AC46,AF46) -> 0 | BE46: =SUM(AA46,AD46,AG46) -> 0 | BF46: =SUM(AB46,AE46,AH46) -> 0 | BG46: =SUM(AI46,AL46,AO46) -> 0 | BH46: =SUM(AJ46,AM46,AP46) -> 0 | BI46: =SUM(AK46,AN46,AQ46) -> 0
A47: Taxas e Licenças - Artístico | C47: Contr/Prov - ECAD Valor Mensal | H47: 0 | I47: =-SUMIFS(T_ORCAMENTOS!$E:$E,T_ORCAMENTOS!$C:$C,"Taxas e Licenças - Artístico",T_ORCAMENTOS!$H:$H,"1/2026") -> 0 | J47: =SUMIFS(Aut_BlueMe_Sem_Pedido!$J:$J,Aut_BlueMe_Sem_Pedido!$Q:$Q,DRE!H$4,Aut_BlueMe_Sem_Pedido!$H:$H,DRE!$A47)+SUMIFS(Aut_Ajustes_Manuais!$G:$G,Aut_Ajustes_Manuais!$I:$I,DRE!H$4,Aut_Ajustes_Manuais!$F:$F,"Taxas e Licenças - Artístico") -> 0 | K47: 0 | L47: =-SUMIFS(T_ORCAMENTOS!$E:$E,T_ORCAMENTOS!$C:$C,"Taxas e Licenças - Artístico",T_ORCAMENTOS!$H:$H,"2/2026") -> 0 | M47: =SUMIFS(Aut_BlueMe_Sem_Pedido!$J:$J,Aut_BlueMe_Sem_Pedido!$Q:$Q,DRE!K$4,Aut_BlueMe_Sem_Pedido!$H:$H,DRE!$A47)+SUMIFS(Aut_Ajustes_Manuais!$G:$G,Aut_Ajustes_Manuais!$I:$I,DRE!K$4,Aut_Ajustes_Manuais!$F:$F,"Taxas e Licenças - Artístico") -> 0 | N47: 0 | O47: =-SUMIFS(T_ORCAMENTOS!$E:$E,T_ORCAMENTOS!$C:$C,"Taxas e Licenças - Artístico",T_ORCAMENTOS!$H:$H,"3/2026") -> 0 | P47: =SUMIFS(Aut_BlueMe_Sem_Pedido!$J:$J,Aut_BlueMe_Sem_Pedido!$Q:$Q,DRE!N$4,Aut_BlueMe_Sem_Pedido!$H:$H,DRE!$A47)+SUMIFS(Aut_Ajustes_Manuais!$G:$G,Aut_Ajustes_Manuais!$I:$I,DRE!N$4,Aut_Ajustes_Manuais!$F:$F,"Taxas e Licenças - Artístico") -> 0 | Q47: 0 | R47: =-SUMIFS(T_ORCAMENTOS!$E:$E,T_ORCAMENTOS!$C:$C,"Taxas e Licenças - Artístico",T_ORCAMENTOS!$H:$H,"4/2026") -> 0 | S47: =SUMIFS(Aut_BlueMe_Sem_Pedido!$J:$J,Aut_BlueMe_Sem_Pedido!$Q:$Q,DRE!Q$4,Aut_BlueMe_Sem_Pedido!$H:$H,DRE!$A47)+SUMIFS(Aut_Ajustes_Manuais!$G:$G,Aut_Ajustes_Manuais!$I:$I,DRE!Q$4,Aut_Ajustes_Manuais!$F:$F,"Taxas e Licenças - Artístico") -> 0 | T47: 0 | U47: =-SUMIFS(T_ORCAMENTOS!$E:$E,T_ORCAMENTOS!$C:$C,"Taxas e Licenças - Artístico",T_ORCAMENTOS!$H:$H,"5/2026") -> 0 | V47: =SUMIFS(Aut_BlueMe_Sem_Pedido!$J:$J,Aut_BlueMe_Sem_Pedido!$Q:$Q,DRE!T$4,Aut_BlueMe_Sem_Pedido!$H:$H,DRE!$A47)+SUMIFS(Aut_Ajustes_Manuais!$G:$G,Aut_Ajustes_Manuais!$I:$I,DRE!T$4,Aut_Ajustes_Manuais!$F:$F,"Taxas e Licenças - Artístico") -> 0 | W47: 0 | X47: =-SUMIFS(T_ORCAMENTOS!$E:$E,T_ORCAMENTOS!$C:$C,"Taxas e Licenças - Artístico",T_ORCAMENTOS!$H:$H,"6/2026") -> 0 | Y47: =SUMIFS(Aut_BlueMe_Sem_Pedido!$J:$J,Aut_BlueMe_Sem_Pedido!$Q:$Q,DRE!W$4,Aut_BlueMe_Sem_Pedido!$H:$H,DRE!$A47)+SUMIFS(Aut_Ajustes_Manuais!$G:$G,Aut_Ajustes_Manuais!$I:$I,DRE!W$4,Aut_Ajustes_Manuais!$F:$F,"Taxas e Licenças - Artístico") -> 0 | Z47: 0 | AA47: =-SUMIFS(T_ORCAMENTOS!$E:$E,T_ORCAMENTOS!$C:$C,"Taxas e Licenças - Artístico",T_ORCAMENTOS!$H:$H,"7/2026") -> 0 | AB47: =SUMIFS(Aut_BlueMe_Sem_Pedido!$J:$J,Aut_BlueMe_Sem_Pedido!$Q:$Q,DRE!Z$4,Aut_BlueMe_Sem_Pedido!$H:$H,DRE!$A47)+SUMIFS(Aut_Ajustes_Manuais!$G:$G,Aut_Ajustes_Manuais!$I:$I,DRE!Z$4,Aut_Ajustes_Manuais!$F:$F,"Taxas e Licenças - Artístico") -> 0 | AC47: 0 | AD47: =-SUMIFS(T_ORCAMENTOS!$E:$E,T_ORCAMENTOS!$C:$C,"Taxas e Licenças - Artístico",T_ORCAMENTOS!$H:$H,"8/2026") -> 0 | AE47: =SUMIFS(Aut_BlueMe_Sem_Pedido!$J:$J,Aut_BlueMe_Sem_Pedido!$Q:$Q,DRE!AC$4,Aut_BlueMe_Sem_Pedido!$H:$H,DRE!$A47)+SUMIFS(Aut_Ajustes_Manuais!$G:$G,Aut_Ajustes_Manuais!$I:$I,DRE!AC$4,Aut_Ajustes_Manuais!$F:$F,"Taxas e Licenças - Artístico") -> 0 | AF47: 0 | AG47: =-SUMIFS(T_ORCAMENTOS!$E:$E,T_ORCAMENTOS!$C:$C,"Taxas e Licenças - Artístico",T_ORCAMENTOS!$H:$H,"9/2026") -> 0 | AH47: =SUMIFS(Aut_BlueMe_Sem_Pedido!$J:$J,Aut_BlueMe_Sem_Pedido!$Q:$Q,DRE!AF$4,Aut_BlueMe_Sem_Pedido!$H:$H,DRE!$A47)+SUMIFS(Aut_Ajustes_Manuais!$G:$G,Aut_Ajustes_Manuais!$I:$I,DRE!AF$4,Aut_Ajustes_Manuais!$F:$F,"Taxas e Licenças - Artístico") -> 0 | AI47: 0 | AJ47: =-SUMIFS(T_ORCAMENTOS!$E:$E,T_ORCAMENTOS!$C:$C,"Taxas e Licenças - Artístico",T_ORCAMENTOS!$H:$H,"10/2026") -> 0 | AK47: =SUMIFS(Aut_BlueMe_Sem_Pedido!$J:$J,Aut_BlueMe_Sem_Pedido!$Q:$Q,DRE!AI$4,Aut_BlueMe_Sem_Pedido!$H:$H,DRE!$A47)+SUMIFS(Aut_Ajustes_Manuais!$G:$G,Aut_Ajustes_Manuais!$I:$I,DRE!AI$4,Aut_Ajustes_Manuais!$F:$F,"Taxas e Licenças - Artístico") -> 0 | AL47: 0 | AM47: =-SUMIFS(T_ORCAMENTOS!$E:$E,T_ORCAMENTOS!$C:$C,"Taxas e Licenças - Artístico",T_ORCAMENTOS!$H:$H,"11/2026") -> 0 | AN47: =SUMIFS(Aut_BlueMe_Sem_Pedido!$J:$J,Aut_BlueMe_Sem_Pedido!$Q:$Q,DRE!AL$4,Aut_BlueMe_Sem_Pedido!$H:$H,DRE!$A47)+SUMIFS(Aut_Ajustes_Manuais!$G:$G,Aut_Ajustes_Manuais!$I:$I,DRE!AL$4,Aut_Ajustes_Manuais!$F:$F,"Taxas e Licenças - Artístico") -> 0 | AO47: 0 | AP47: =-SUMIFS(T_ORCAMENTOS!$E:$E,T_ORCAMENTOS!$C:$C,"Taxas e Licenças - Artístico",T_ORCAMENTOS!$H:$H,"12/2026") -> 0 | AQ47: =SUMIFS(Aut_BlueMe_Sem_Pedido!$J:$J,Aut_BlueMe_Sem_Pedido!$Q:$Q,DRE!AO$4,Aut_BlueMe_Sem_Pedido!$H:$H,DRE!$A47)+SUMIFS(Aut_Ajustes_Manuais!$G:$G,Aut_Ajustes_Manuais!$I:$I,DRE!AO$4,Aut_Ajustes_Manuais!$F:$F,"Taxas e Licenças - Artístico") -> 0 | AR47: =SUMIFS($H47:$AO47,$H$5:$AO$5,"<"&MONTH(TODAY()),$H$6:$AO$6,"REAL 25") -> 0 | AS47: =SUMIFS($I47:$AP47,$I$5:$AP$5,"<"&MONTH(TODAY()),$I$6:$AP$6,"ORÇADO ") -> 0 | AT47: =SUMIFS($J47:$AQ47,$J$5:$AQ$5,"<"&MONTH(TODAY()),$J$6:$AQ$6,"REAL 26") -> 0 | AU47: =SUM(H47,K47,N47,Q47,T47,W47,Z47,AC47,AF47,AI47,AL47,AO47) -> 0 | AV47: =SUM(I47,L47,O47,R47,U47,X47,AA47,AD47,AG47,AJ47,AM47,AP47) -> 0 | AW47: =SUM(J47,M47,P47,S47,V47,Y47,AB47,AE47,AH47,AK47,AN47,AQ47) -> 0 | AX47: =SUM(H47,K47,N47) -> 0 | AY47: =SUM(I47,L47,O47) -> 0 | AZ47: =SUM(J47,M47,P47) -> 0 | BA47: =SUM(Q47,T47,W47) -> 0 | BB47: =SUM(R47,U47,X47) -> 0 | BC47: =SUM(S47,V47,Y47) -> 0 | BD47: =SUM(Z47,AC47,AF47) -> 0 | BE47: =SUM(AA47,AD47,AG47) -> 0 | BF47: =SUM(AB47,AE47,AH47) -> 0 | BG47: =SUM(AI47,AL47,AO47) -> 0 | BH47: =SUM(AJ47,AM47,AP47) -> 0 | BI47: =SUM(AK47,AN47,AQ47) -> 0
A48: MDO Terceirizada - Artístico | H48: 0 | I48: =-SUMIFS(T_ORCAMENTOS!$E:$E,T_ORCAMENTOS!$C:$C,"MDO Terceirizada - Artístico",T_ORCAMENTOS!$H:$H,"1/2026") -> 0 | J48: =SUMIFS(Aut_BlueMe_Sem_Pedido!$J:$J,Aut_BlueMe_Sem_Pedido!$Q:$Q,DRE!H$4,Aut_BlueMe_Sem_Pedido!$H:$H,DRE!$A48)+SUMIFS(Aut_Ajustes_Manuais!$G:$G,Aut_Ajustes_Manuais!$I:$I,DRE!H$4,Aut_Ajustes_Manuais!$F:$F,"MDO Terceirizada - Artístico") -> 0 | K48: 0 | L48: =-SUMIFS(T_ORCAMENTOS!$E:$E,T_ORCAMENTOS!$C:$C,"MDO Terceirizada - Artístico",T_ORCAMENTOS!$H:$H,"2/2026") -> 0 | M48: =SUMIFS(Aut_BlueMe_Sem_Pedido!$J:$J,Aut_BlueMe_Sem_Pedido!$Q:$Q,DRE!K$4,Aut_BlueMe_Sem_Pedido!$H:$H,DRE!$A48)+SUMIFS(Aut_Ajustes_Manuais!$G:$G,Aut_Ajustes_Manuais!$I:$I,DRE!K$4,Aut_Ajustes_Manuais!$F:$F,"MDO Terceirizada - Artístico") -> 0 | N48: 0 | O48: =-SUMIFS(T_ORCAMENTOS!$E:$E,T_ORCAMENTOS!$C:$C,"MDO Terceirizada - Artístico",T_ORCAMENTOS!$H:$H,"3/2026") -> 0 | P48: =SUMIFS(Aut_BlueMe_Sem_Pedido!$J:$J,Aut_BlueMe_Sem_Pedido!$Q:$Q,DRE!N$4,Aut_BlueMe_Sem_Pedido!$H:$H,DRE!$A48)+SUMIFS(Aut_Ajustes_Manuais!$G:$G,Aut_Ajustes_Manuais!$I:$I,DRE!N$4,Aut_Ajustes_Manuais!$F:$F,"MDO Terceirizada - Artístico") -> 0 | Q48: 0 | R48: =-SUMIFS(T_ORCAMENTOS!$E:$E,T_ORCAMENTOS!$C:$C,"MDO Terceirizada - Artístico",T_ORCAMENTOS!$H:$H,"4/2026") -> 0 | S48: =SUMIFS(Aut_BlueMe_Sem_Pedido!$J:$J,Aut_BlueMe_Sem_Pedido!$Q:$Q,DRE!Q$4,Aut_BlueMe_Sem_Pedido!$H:$H,DRE!$A48)+SUMIFS(Aut_Ajustes_Manuais!$G:$G,Aut_Ajustes_Manuais!$I:$I,DRE!Q$4,Aut_Ajustes_Manuais!$F:$F,"MDO Terceirizada - Artístico") -> 0 | T48: 0 | U48: =-SUMIFS(T_ORCAMENTOS!$E:$E,T_ORCAMENTOS!$C:$C,"MDO Terceirizada - Artístico",T_ORCAMENTOS!$H:$H,"5/2026") -> 0 | V48: =SUMIFS(Aut_BlueMe_Sem_Pedido!$J:$J,Aut_BlueMe_Sem_Pedido!$Q:$Q,DRE!T$4,Aut_BlueMe_Sem_Pedido!$H:$H,DRE!$A48)+SUMIFS(Aut_Ajustes_Manuais!$G:$G,Aut_Ajustes_Manuais!$I:$I,DRE!T$4,Aut_Ajustes_Manuais!$F:$F,"MDO Terceirizada - Artístico") -> 0 | W48: 0 | X48: =-SUMIFS(T_ORCAMENTOS!$E:$E,T_ORCAMENTOS!$C:$C,"MDO Terceirizada - Artístico",T_ORCAMENTOS!$H:$H,"6/2026") -> 0 | Y48: =SUMIFS(Aut_BlueMe_Sem_Pedido!$J:$J,Aut_BlueMe_Sem_Pedido!$Q:$Q,DRE!W$4,Aut_BlueMe_Sem_Pedido!$H:$H,DRE!$A48)+SUMIFS(Aut_Ajustes_Manuais!$G:$G,Aut_Ajustes_Manuais!$I:$I,DRE!W$4,Aut_Ajustes_Manuais!$F:$F,"MDO Terceirizada - Artístico") -> 0 | Z48: 0 | AA48: =-SUMIFS(T_ORCAMENTOS!$E:$E,T_ORCAMENTOS!$C:$C,"MDO Terceirizada - Artístico",T_ORCAMENTOS!$H:$H,"7/2026") -> 0 | AB48: =SUMIFS(Aut_BlueMe_Sem_Pedido!$J:$J,Aut_BlueMe_Sem_Pedido!$Q:$Q,DRE!Z$4,Aut_BlueMe_Sem_Pedido!$H:$H,DRE!$A48)+SUMIFS(Aut_Ajustes_Manuais!$G:$G,Aut_Ajustes_Manuais!$I:$I,DRE!Z$4,Aut_Ajustes_Manuais!$F:$F,"MDO Terceirizada - Artístico") -> 0 | AC48: 0 | AD48: =-SUMIFS(T_ORCAMENTOS!$E:$E,T_ORCAMENTOS!$C:$C,"MDO Terceirizada - Artístico",T_ORCAMENTOS!$H:$H,"8/2026") -> 0 | AE48: =SUMIFS(Aut_BlueMe_Sem_Pedido!$J:$J,Aut_BlueMe_Sem_Pedido!$Q:$Q,DRE!AC$4,Aut_BlueMe_Sem_Pedido!$H:$H,DRE!$A48)+SUMIFS(Aut_Ajustes_Manuais!$G:$G,Aut_Ajustes_Manuais!$I:$I,DRE!AC$4,Aut_Ajustes_Manuais!$F:$F,"MDO Terceirizada - Artístico") -> 0 | AF48: 0 | AG48: =-SUMIFS(T_ORCAMENTOS!$E:$E,T_ORCAMENTOS!$C:$C,"MDO Terceirizada - Artístico",T_ORCAMENTOS!$H:$H,"9/2026") -> 0 | AH48: =SUMIFS(Aut_BlueMe_Sem_Pedido!$J:$J,Aut_BlueMe_Sem_Pedido!$Q:$Q,DRE!AF$4,Aut_BlueMe_Sem_Pedido!$H:$H,DRE!$A48)+SUMIFS(Aut_Ajustes_Manuais!$G:$G,Aut_Ajustes_Manuais!$I:$I,DRE!AF$4,Aut_Ajustes_Manuais!$F:$F,"MDO Terceirizada - Artístico") -> 0 | AI48: 0 | AJ48: =-SUMIFS(T_ORCAMENTOS!$E:$E,T_ORCAMENTOS!$C:$C,"MDO Terceirizada - Artístico",T_ORCAMENTOS!$H:$H,"10/2026") -> 0 | AK48: =SUMIFS(Aut_BlueMe_Sem_Pedido!$J:$J,Aut_BlueMe_Sem_Pedido!$Q:$Q,DRE!AI$4,Aut_BlueMe_Sem_Pedido!$H:$H,DRE!$A48)+SUMIFS(Aut_Ajustes_Manuais!$G:$G,Aut_Ajustes_Manuais!$I:$I,DRE!AI$4,Aut_Ajustes_Manuais!$F:$F,"MDO Terceirizada - Artístico") -> 0 | AL48: 0 | AM48: =-SUMIFS(T_ORCAMENTOS!$E:$E,T_ORCAMENTOS!$C:$C,"MDO Terceirizada - Artístico",T_ORCAMENTOS!$H:$H,"11/2026") -> 0 | AN48: =SUMIFS(Aut_BlueMe_Sem_Pedido!$J:$J,Aut_BlueMe_Sem_Pedido!$Q:$Q,DRE!AL$4,Aut_BlueMe_Sem_Pedido!$H:$H,DRE!$A48)+SUMIFS(Aut_Ajustes_Manuais!$G:$G,Aut_Ajustes_Manuais!$I:$I,DRE!AL$4,Aut_Ajustes_Manuais!$F:$F,"MDO Terceirizada - Artístico") -> 0 | AO48: 0 | AP48: =-SUMIFS(T_ORCAMENTOS!$E:$E,T_ORCAMENTOS!$C:$C,"MDO Terceirizada - Artístico",T_ORCAMENTOS!$H:$H,"12/2026") -> 0 | AQ48: =SUMIFS(Aut_BlueMe_Sem_Pedido!$J:$J,Aut_BlueMe_Sem_Pedido!$Q:$Q,DRE!AO$4,Aut_BlueMe_Sem_Pedido!$H:$H,DRE!$A48)+SUMIFS(Aut_Ajustes_Manuais!$G:$G,Aut_Ajustes_Manuais!$I:$I,DRE!AO$4,Aut_Ajustes_Manuais!$F:$F,"MDO Terceirizada - Artístico") -> 0 | AR48: =SUMIFS($H48:$AO48,$H$5:$AO$5,"<"&MONTH(TODAY()),$H$6:$AO$6,"REAL 25") -> 0 | AS48: =SUMIFS($I48:$AP48,$I$5:$AP$5,"<"&MONTH(TODAY()),$I$6:$AP$6,"ORÇADO ") -> 0 | AT48: =SUMIFS($J48:$AQ48,$J$5:$AQ$5,"<"&MONTH(TODAY()),$J$6:$AQ$6,"REAL 26") -> 0 | AU48: =SUM(H48,K48,N48,Q48,T48,W48,Z48,AC48,AF48,AI48,AL48,AO48) -> 0 | AV48: =SUM(I48,L48,O48,R48,U48,X48,AA48,AD48,AG48,AJ48,AM48,AP48) -> 0 | AW48: =SUM(J48,M48,P48,S48,V48,Y48,AB48,AE48,AH48,AK48,AN48,AQ48) -> 0 | AX48: =SUM(H48,K48,N48) -> 0 | AY48: =SUM(I48,L48,O48) -> 0 | AZ48: =SUM(J48,M48,P48) -> 0 | BA48: =SUM(Q48,T48,W48) -> 0 | BB48: =SUM(R48,U48,X48) -> 0 | BC48: =SUM(S48,V48,Y48) -> 0 | BD48: =SUM(Z48,AC48,AF48) -> 0 | BE48: =SUM(AA48,AD48,AG48) -> 0 | BF48: =SUM(AB48,AE48,AH48) -> 0 | BG48: =SUM(AI48,AL48,AO48) -> 0 | BH48: =SUM(AJ48,AM48,AP48) -> 0 | BI48: =SUM(AK48,AN48,AQ48) -> 0
A49: Custos Ténico de Som | H49: 0 | I49: =SUM(I50:I52) -> 0 | J49: =SUM(J50:J52)+SUMIFS(Aut_Ajustes_Manuais!$G:$G,Aut_Ajustes_Manuais!$I:$I,DRE!H$4,Aut_Ajustes_Manuais!$F:$F,"Custos Ténico de Som") -> 0 | K49: 0 | L49: =SUM(L50:L52) -> 0 | M49: =SUM(M50:M52)+SUMIFS(Aut_Ajustes_Manuais!$G:$G,Aut_Ajustes_Manuais!$I:$I,DRE!K$4,Aut_Ajustes_Manuais!$F:$F,"Custos Ténico de Som") -> 0 | N49: 0 | O49: =SUM(O50:O52) -> 0 | P49: =SUM(P50:P52)+SUMIFS(Aut_Ajustes_Manuais!$G:$G,Aut_Ajustes_Manuais!$I:$I,DRE!N$4,Aut_Ajustes_Manuais!$F:$F,"Custos Ténico de Som") -> 0 | R49: =SUM(R50:R52) -> 0 | S49: =SUM(S50:S52)+SUMIFS(Aut_Ajustes_Manuais!$G:$G,Aut_Ajustes_Manuais!$I:$I,DRE!Q$4,Aut_Ajustes_Manuais!$F:$F,"Custos Ténico de Som") -> 0 | U49: =SUM(U50:U52) -> 0 | V49: =SUM(V50:V52)+SUMIFS(Aut_Ajustes_Manuais!$G:$G,Aut_Ajustes_Manuais!$I:$I,DRE!T$4,Aut_Ajustes_Manuais!$F:$F,"Custos Ténico de Som") -> 0 | X49: =SUM(X50:X52) -> 0 | Y49: =SUM(Y50:Y52)+SUMIFS(Aut_Ajustes_Manuais!$G:$G,Aut_Ajustes_Manuais!$I:$I,DRE!W$4,Aut_Ajustes_Manuais!$F:$F,"Custos Ténico de Som") -> 0 | AA49: =SUM(AA50:AA52) -> 0 | AB49: =SUM(AB50:AB52)+SUMIFS(Aut_Ajustes_Manuais!$G:$G,Aut_Ajustes_Manuais!$I:$I,DRE!Z$4,Aut_Ajustes_Manuais!$F:$F,"Custos Ténico de Som") -> 0 | AD49: =SUM(AD50:AD52) -> -24500 | AE49: =SUM(AE50:AE52)+SUMIFS(Aut_Ajustes_Manuais!$G:$G,Aut_Ajustes_Manuais!$I:$I,DRE!AC$4,Aut_Ajustes_Manuais!$F:$F,"Custos Ténico de Som") -> 0 | AG49: =SUM(AG50:AG52) -> -24500 | AH49: =SUM(AH50:AH52)+SUMIFS(Aut_Ajustes_Manuais!$G:$G,Aut_Ajustes_Manuais!$I:$I,DRE!AF$4,Aut_Ajustes_Manuais!$F:$F,"Custos Ténico de Som") -> 0 | AJ49: =SUM(AJ50:AJ52) -> -24500 | AK49: =SUM(AK50:AK52)+SUMIFS(Aut_Ajustes_Manuais!$G:$G,Aut_Ajustes_Manuais!$I:$I,DRE!AI$4,Aut_Ajustes_Manuais!$F:$F,"Custos Ténico de Som") -> 0 | AM49: =SUM(AM50:AM52) -> -24500 | AN49: =SUM(AN50:AN52)+SUMIFS(Aut_Ajustes_Manuais!$G:$G,Aut_Ajustes_Manuais!$I:$I,DRE!AL$4,Aut_Ajustes_Manuais!$F:$F,"Custos Ténico de Som") -> 0 | AP49: =SUM(AP50:AP52) -> -24500 | AQ49: =SUM(AQ50:AQ52)+SUMIFS(Aut_Ajustes_Manuais!$G:$G,Aut_Ajustes_Manuais!$I:$I,DRE!AO$4,Aut_Ajustes_Manuais!$F:$F,"Custos Ténico de Som") -> 0 | AR49: =SUMIFS($H49:$AO49,$H$5:$AO$5,"<"&MONTH(TODAY()),$H$6:$AO$6,"REAL 25") -> 0 | AS49: =SUMIFS($I49:$AP49,$I$5:$AP$5,"<"&MONTH(TODAY()),$I$6:$AP$6,"ORÇADO ") -> -24500 | AT49: =SUMIFS($J49:$AQ49,$J$5:$AQ$5,"<"&MONTH(TODAY()),$J$6:$AQ$6,"REAL 26") -> 0 | AU49: =SUM(AU50:AU52) -> 0 | AV49: =SUM(AV50:AV52) -> -122500 | AW49: =SUM(AW50:AW52) -> 0 | AX49: =SUM(AX50:AX52) -> 0 | AY49: =SUM(AY50:AY52) -> 0 | AZ49: =SUM(AZ50:AZ52) -> 0 | BA49: =SUM(BA50:BA52) -> 0 | BB49: =SUM(BB50:BB52) -> 0 | ... BI49: =SUM(BI50:BI52) -> 0
A50: Técnico de Som / Luz | C50: Contr/Prov | H50: 0 | I50: =-SUMIFS(T_ORCAMENTOS!$E:$E,T_ORCAMENTOS!$C:$C,"Técnico de Som / Luz",T_ORCAMENTOS!$H:$H,"1/2026") -> 0 | J50: =SUMIFS(Aut_BlueMe_Sem_Pedido!$J:$J,Aut_BlueMe_Sem_Pedido!$Q:$Q,DRE!H$4,Aut_BlueMe_Sem_Pedido!$H:$H,DRE!$A50)+SUMIFS(Aut_Ajustes_Manuais!$G:$G,Aut_Ajustes_Manuais!$I:$I,DRE!H$4,Aut_Ajustes_Manuais!$F:$F,"Técnico de Som / Luz") -> 0 | K50: 0 | L50: =-SUMIFS(T_ORCAMENTOS!$E:$E,T_ORCAMENTOS!$C:$C,"Técnico de Som / Luz",T_ORCAMENTOS!$H:$H,"2/2026") -> 0 | M50: =SUMIFS(Aut_BlueMe_Sem_Pedido!$J:$J,Aut_BlueMe_Sem_Pedido!$Q:$Q,DRE!K$4,Aut_BlueMe_Sem_Pedido!$H:$H,DRE!$A50)+SUMIFS(Aut_Ajustes_Manuais!$G:$G,Aut_Ajustes_Manuais!$I:$I,DRE!K$4,Aut_Ajustes_Manuais!$F:$F,"Técnico de Som / Luz") -> 0 | N50: 0 | O50: =-SUMIFS(T_ORCAMENTOS!$E:$E,T_ORCAMENTOS!$C:$C,"Técnico de Som / Luz",T_ORCAMENTOS!$H:$H,"3/2026") -> 0 | P50: =SUMIFS(Aut_BlueMe_Sem_Pedido!$J:$J,Aut_BlueMe_Sem_Pedido!$Q:$Q,DRE!N$4,Aut_BlueMe_Sem_Pedido!$H:$H,DRE!$A50)+SUMIFS(Aut_Ajustes_Manuais!$G:$G,Aut_Ajustes_Manuais!$I:$I,DRE!N$4,Aut_Ajustes_Manuais!$F:$F,"Técnico de Som / Luz") -> 0 | R50: =-SUMIFS(T_ORCAMENTOS!$E:$E,T_ORCAMENTOS!$C:$C,"Técnico de Som / Luz",T_ORCAMENTOS!$H:$H,"4/2026") -> 0 | S50: =SUMIFS(Aut_BlueMe_Sem_Pedido!$J:$J,Aut_BlueMe_Sem_Pedido!$Q:$Q,DRE!Q$4,Aut_BlueMe_Sem_Pedido!$H:$H,DRE!$A50)+SUMIFS(Aut_Ajustes_Manuais!$G:$G,Aut_Ajustes_Manuais!$I:$I,DRE!Q$4,Aut_Ajustes_Manuais!$F:$F,"Técnico de Som / Luz") -> 0 | U50: =-SUMIFS(T_ORCAMENTOS!$E:$E,T_ORCAMENTOS!$C:$C,"Técnico de Som / Luz",T_ORCAMENTOS!$H:$H,"5/2026") -> 0 | V50: =SUMIFS(Aut_BlueMe_Sem_Pedido!$J:$J,Aut_BlueMe_Sem_Pedido!$Q:$Q,DRE!T$4,Aut_BlueMe_Sem_Pedido!$H:$H,DRE!$A50)+SUMIFS(Aut_Ajustes_Manuais!$G:$G,Aut_Ajustes_Manuais!$I:$I,DRE!T$4,Aut_Ajustes_Manuais!$F:$F,"Técnico de Som / Luz") -> 0 | X50: =-SUMIFS(T_ORCAMENTOS!$E:$E,T_ORCAMENTOS!$C:$C,"Técnico de Som / Luz",T_ORCAMENTOS!$H:$H,"6/2026") -> 0 | Y50: =SUMIFS(Aut_BlueMe_Sem_Pedido!$J:$J,Aut_BlueMe_Sem_Pedido!$Q:$Q,DRE!W$4,Aut_BlueMe_Sem_Pedido!$H:$H,DRE!$A50)+SUMIFS(Aut_Ajustes_Manuais!$G:$G,Aut_Ajustes_Manuais!$I:$I,DRE!W$4,Aut_Ajustes_Manuais!$F:$F,"Técnico de Som / Luz") -> 0 | AA50: =-SUMIFS(T_ORCAMENTOS!$E:$E,T_ORCAMENTOS!$C:$C,"Técnico de Som / Luz",T_ORCAMENTOS!$H:$H,"7/2026") -> 0 | AB50: =SUMIFS(Aut_BlueMe_Sem_Pedido!$J:$J,Aut_BlueMe_Sem_Pedido!$Q:$Q,DRE!Z$4,Aut_BlueMe_Sem_Pedido!$H:$H,DRE!$A50)+SUMIFS(Aut_Ajustes_Manuais!$G:$G,Aut_Ajustes_Manuais!$I:$I,DRE!Z$4,Aut_Ajustes_Manuais!$F:$F,"Técnico de Som / Luz") -> 0 | AD50: =-SUMIFS(T_ORCAMENTOS!$E:$E,T_ORCAMENTOS!$C:$C,"Técnico de Som / Luz",T_ORCAMENTOS!$H:$H,"8/2026") -> -11500 | AE50: =SUMIFS(Aut_BlueMe_Sem_Pedido!$J:$J,Aut_BlueMe_Sem_Pedido!$Q:$Q,DRE!AC$4,Aut_BlueMe_Sem_Pedido!$H:$H,DRE!$A50)+SUMIFS(Aut_Ajustes_Manuais!$G:$G,Aut_Ajustes_Manuais!$I:$I,DRE!AC$4,Aut_Ajustes_Manuais!$F:$F,"Técnico de Som / Luz") -> 0 | AG50: =-SUMIFS(T_ORCAMENTOS!$E:$E,T_ORCAMENTOS!$C:$C,"Técnico de Som / Luz",T_ORCAMENTOS!$H:$H,"9/2026") -> -11500 | AH50: =SUMIFS(Aut_BlueMe_Sem_Pedido!$J:$J,Aut_BlueMe_Sem_Pedido!$Q:$Q,DRE!AF$4,Aut_BlueMe_Sem_Pedido!$H:$H,DRE!$A50)+SUMIFS(Aut_Ajustes_Manuais!$G:$G,Aut_Ajustes_Manuais!$I:$I,DRE!AF$4,Aut_Ajustes_Manuais!$F:$F,"Técnico de Som / Luz") -> 0 | AJ50: =-SUMIFS(T_ORCAMENTOS!$E:$E,T_ORCAMENTOS!$C:$C,"Técnico de Som / Luz",T_ORCAMENTOS!$H:$H,"10/2026") -> -11500 | AK50: =SUMIFS(Aut_BlueMe_Sem_Pedido!$J:$J,Aut_BlueMe_Sem_Pedido!$Q:$Q,DRE!AI$4,Aut_BlueMe_Sem_Pedido!$H:$H,DRE!$A50)+SUMIFS(Aut_Ajustes_Manuais!$G:$G,Aut_Ajustes_Manuais!$I:$I,DRE!AI$4,Aut_Ajustes_Manuais!$F:$F,"Técnico de Som / Luz") -> 0 | AM50: =-SUMIFS(T_ORCAMENTOS!$E:$E,T_ORCAMENTOS!$C:$C,"Técnico de Som / Luz",T_ORCAMENTOS!$H:$H,"11/2026") -> -11500 | AN50: =SUMIFS(Aut_BlueMe_Sem_Pedido!$J:$J,Aut_BlueMe_Sem_Pedido!$Q:$Q,DRE!AL$4,Aut_BlueMe_Sem_Pedido!$H:$H,DRE!$A50)+SUMIFS(Aut_Ajustes_Manuais!$G:$G,Aut_Ajustes_Manuais!$I:$I,DRE!AL$4,Aut_Ajustes_Manuais!$F:$F,"Técnico de Som / Luz") -> 0 | AP50: =-SUMIFS(T_ORCAMENTOS!$E:$E,T_ORCAMENTOS!$C:$C,"Técnico de Som / Luz",T_ORCAMENTOS!$H:$H,"12/2026") -> -11500 | AQ50: =SUMIFS(Aut_BlueMe_Sem_Pedido!$J:$J,Aut_BlueMe_Sem_Pedido!$Q:$Q,DRE!AO$4,Aut_BlueMe_Sem_Pedido!$H:$H,DRE!$A50)+SUMIFS(Aut_Ajustes_Manuais!$G:$G,Aut_Ajustes_Manuais!$I:$I,DRE!AO$4,Aut_Ajustes_Manuais!$F:$F,"Técnico de Som / Luz") -> 0 | AR50: =SUMIFS($H50:$AO50,$H$5:$AO$5,"<"&MONTH(TODAY()),$H$6:$AO$6,"REAL 25") -> 0 | AS50: =SUMIFS($I50:$AP50,$I$5:$AP$5,"<"&MONTH(TODAY()),$I$6:$AP$6,"ORÇADO ") -> -11500 | AT50: =SUMIFS($J50:$AQ50,$J$5:$AQ$5,"<"&MONTH(TODAY()),$J$6:$AQ$6,"REAL 26") -> 0 | AU50: =SUM(H50,K50,N50,Q50,T50,W50,Z50,AC50,AF50,AI50,AL50,AO50) -> 0 | AV50: =SUM(I50,L50,O50,R50,U50,X50,AA50,AD50,AG50,AJ50,AM50,AP50) -> -57500 | AW50: =SUM(J50,M50,P50,S50,V50,Y50,AB50,AE50,AH50,AK50,AN50,AQ50) -> 0 | AX50: =SUM(H50,K50,N50) -> 0 | AY50: =SUM(I50,L50,O50) -> 0 | AZ50: =SUM(J50,M50,P50) -> 0 | BA50: =SUM(Q50,T50,W50) -> 0 | BB50: =SUM(R50,U50,X50) -> 0 | BC50: =SUM(S50,V50,Y50) -> 0 | BD50: =SUM(Z50,AC50,AF50) -> 0 | BE50: =SUM(AA50,AD50,AG50) -> -23000 | BF50: =SUM(AB50,AE50,AH50) -> 0 | BG50: =SUM(AI50,AL50,AO50) -> 0 | BH50: =SUM(AJ50,AM50,AP50) -> -34500 | BI50: =SUM(AK50,AN50,AQ50) -> 0
A51: Locação de Equipamentos Fixo | C51: Contr/Prov | H51: 0 | I51: =-SUMIFS(T_ORCAMENTOS!$E:$E,T_ORCAMENTOS!$C:$C,"Locação de Equipamentos Fixo",T_ORCAMENTOS!$H:$H,"1/2026") -> 0 | J51: =SUMIFS(Aut_BlueMe_Sem_Pedido!$J:$J,Aut_BlueMe_Sem_Pedido!$Q:$Q,DRE!H$4,Aut_BlueMe_Sem_Pedido!$H:$H,DRE!$A51)+SUMIFS(Aut_Ajustes_Manuais!$G:$G,Aut_Ajustes_Manuais!$I:$I,DRE!H$4,Aut_Ajustes_Manuais!$F:$F,"Locação de Equipamentos Fixo") -> 0 | K51: 0 | L51: =-SUMIFS(T_ORCAMENTOS!$E:$E,T_ORCAMENTOS!$C:$C,"Locação de Equipamentos Fixo",T_ORCAMENTOS!$H:$H,"2/2026") -> 0 | M51: =SUMIFS(Aut_BlueMe_Sem_Pedido!$J:$J,Aut_BlueMe_Sem_Pedido!$Q:$Q,DRE!K$4,Aut_BlueMe_Sem_Pedido!$H:$H,DRE!$A51)+SUMIFS(Aut_Ajustes_Manuais!$G:$G,Aut_Ajustes_Manuais!$I:$I,DRE!K$4,Aut_Ajustes_Manuais!$F:$F,"Locação de Equipamentos Fixo") -> 0 | N51: 0 | O51: =-SUMIFS(T_ORCAMENTOS!$E:$E,T_ORCAMENTOS!$C:$C,"Locação de Equipamentos Fixo",T_ORCAMENTOS!$H:$H,"3/2026") -> 0 | P51: =SUMIFS(Aut_BlueMe_Sem_Pedido!$J:$J,Aut_BlueMe_Sem_Pedido!$Q:$Q,DRE!N$4,Aut_BlueMe_Sem_Pedido!$H:$H,DRE!$A51)+SUMIFS(Aut_Ajustes_Manuais!$G:$G,Aut_Ajustes_Manuais!$I:$I,DRE!N$4,Aut_Ajustes_Manuais!$F:$F,"Locação de Equipamentos Fixo") -> 0 | Q51: 0 | R51: =-SUMIFS(T_ORCAMENTOS!$E:$E,T_ORCAMENTOS!$C:$C,"Locação de Equipamentos Fixo",T_ORCAMENTOS!$H:$H,"4/2026") -> 0 | S51: =SUMIFS(Aut_BlueMe_Sem_Pedido!$J:$J,Aut_BlueMe_Sem_Pedido!$Q:$Q,DRE!Q$4,Aut_BlueMe_Sem_Pedido!$H:$H,DRE!$A51)+SUMIFS(Aut_Ajustes_Manuais!$G:$G,Aut_Ajustes_Manuais!$I:$I,DRE!Q$4,Aut_Ajustes_Manuais!$F:$F,"Locação de Equipamentos Fixo") -> 0 | T51: 0 | U51: =-SUMIFS(T_ORCAMENTOS!$E:$E,T_ORCAMENTOS!$C:$C,"Locação de Equipamentos Fixo",T_ORCAMENTOS!$H:$H,"5/2026") -> 0 | V51: =SUMIFS(Aut_BlueMe_Sem_Pedido!$J:$J,Aut_BlueMe_Sem_Pedido!$Q:$Q,DRE!T$4,Aut_BlueMe_Sem_Pedido!$H:$H,DRE!$A51)+SUMIFS(Aut_Ajustes_Manuais!$G:$G,Aut_Ajustes_Manuais!$I:$I,DRE!T$4,Aut_Ajustes_Manuais!$F:$F,"Locação de Equipamentos Fixo") -> 0 | W51: 0 | X51: =-SUMIFS(T_ORCAMENTOS!$E:$E,T_ORCAMENTOS!$C:$C,"Locação de Equipamentos Fixo",T_ORCAMENTOS!$H:$H,"6/2026") -> 0 | Y51: =SUMIFS(Aut_BlueMe_Sem_Pedido!$J:$J,Aut_BlueMe_Sem_Pedido!$Q:$Q,DRE!W$4,Aut_BlueMe_Sem_Pedido!$H:$H,DRE!$A51)+SUMIFS(Aut_Ajustes_Manuais!$G:$G,Aut_Ajustes_Manuais!$I:$I,DRE!W$4,Aut_Ajustes_Manuais!$F:$F,"Locação de Equipamentos Fixo") -> 0 | AA51: =-SUMIFS(T_ORCAMENTOS!$E:$E,T_ORCAMENTOS!$C:$C,"Locação de Equipamentos Fixo",T_ORCAMENTOS!$H:$H,"7/2026") -> 0 | AB51: =SUMIFS(Aut_BlueMe_Sem_Pedido!$J:$J,Aut_BlueMe_Sem_Pedido!$Q:$Q,DRE!Z$4,Aut_BlueMe_Sem_Pedido!$H:$H,DRE!$A51)+SUMIFS(Aut_Ajustes_Manuais!$G:$G,Aut_Ajustes_Manuais!$I:$I,DRE!Z$4,Aut_Ajustes_Manuais!$F:$F,"Locação de Equipamentos Fixo") -> 0 | AC51: 0 | AD51: =-SUMIFS(T_ORCAMENTOS!$E:$E,T_ORCAMENTOS!$C:$C,"Locação de Equipamentos Fixo",T_ORCAMENTOS!$H:$H,"8/2026") -> -13000 | AE51: =SUMIFS(Aut_BlueMe_Sem_Pedido!$J:$J,Aut_BlueMe_Sem_Pedido!$Q:$Q,DRE!AC$4,Aut_BlueMe_Sem_Pedido!$H:$H,DRE!$A51)+SUMIFS(Aut_Ajustes_Manuais!$G:$G,Aut_Ajustes_Manuais!$I:$I,DRE!AC$4,Aut_Ajustes_Manuais!$F:$F,"Locação de Equipamentos Fixo") -> 0 | AF51: 0 | AG51: =-SUMIFS(T_ORCAMENTOS!$E:$E,T_ORCAMENTOS!$C:$C,"Locação de Equipamentos Fixo",T_ORCAMENTOS!$H:$H,"9/2026") -> -13000 | AH51: =SUMIFS(Aut_BlueMe_Sem_Pedido!$J:$J,Aut_BlueMe_Sem_Pedido!$Q:$Q,DRE!AF$4,Aut_BlueMe_Sem_Pedido!$H:$H,DRE!$A51)+SUMIFS(Aut_Ajustes_Manuais!$G:$G,Aut_Ajustes_Manuais!$I:$I,DRE!AF$4,Aut_Ajustes_Manuais!$F:$F,"Locação de Equipamentos Fixo") -> 0 | AI51: 0 | AJ51: =-SUMIFS(T_ORCAMENTOS!$E:$E,T_ORCAMENTOS!$C:$C,"Locação de Equipamentos Fixo",T_ORCAMENTOS!$H:$H,"10/2026") -> -13000 | AK51: =SUMIFS(Aut_BlueMe_Sem_Pedido!$J:$J,Aut_BlueMe_Sem_Pedido!$Q:$Q,DRE!AI$4,Aut_BlueMe_Sem_Pedido!$H:$H,DRE!$A51)+SUMIFS(Aut_Ajustes_Manuais!$G:$G,Aut_Ajustes_Manuais!$I:$I,DRE!AI$4,Aut_Ajustes_Manuais!$F:$F,"Locação de Equipamentos Fixo") -> 0 | AL51: 0 | AM51: =-SUMIFS(T_ORCAMENTOS!$E:$E,T_ORCAMENTOS!$C:$C,"Locação de Equipamentos Fixo",T_ORCAMENTOS!$H:$H,"11/2026") -> -13000 | AN51: =SUMIFS(Aut_BlueMe_Sem_Pedido!$J:$J,Aut_BlueMe_Sem_Pedido!$Q:$Q,DRE!AL$4,Aut_BlueMe_Sem_Pedido!$H:$H,DRE!$A51)+SUMIFS(Aut_Ajustes_Manuais!$G:$G,Aut_Ajustes_Manuais!$I:$I,DRE!AL$4,Aut_Ajustes_Manuais!$F:$F,"Locação de Equipamentos Fixo") -> 0 | AO51: 0 | AP51: =-SUMIFS(T_ORCAMENTOS!$E:$E,T_ORCAMENTOS!$C:$C,"Locação de Equipamentos Fixo",T_ORCAMENTOS!$H:$H,"12/2026") -> -13000 | AQ51: =SUMIFS(Aut_BlueMe_Sem_Pedido!$J:$J,Aut_BlueMe_Sem_Pedido!$Q:$Q,DRE!AO$4,Aut_BlueMe_Sem_Pedido!$H:$H,DRE!$A51)+SUMIFS(Aut_Ajustes_Manuais!$G:$G,Aut_Ajustes_Manuais!$I:$I,DRE!AO$4,Aut_Ajustes_Manuais!$F:$F,"Locação de Equipamentos Fixo") -> 0 | AR51: =SUMIFS($H51:$AO51,$H$5:$AO$5,"<"&MONTH(TODAY()),$H$6:$AO$6,"REAL 25") -> 0 | AS51: =SUMIFS($I51:$AP51,$I$5:$AP$5,"<"&MONTH(TODAY()),$I$6:$AP$6,"ORÇADO ") -> -13000 | AT51: =SUMIFS($J51:$AQ51,$J$5:$AQ$5,"<"&MONTH(TODAY()),$J$6:$AQ$6,"REAL 26") -> 0 | AU51: =SUM(H51,K51,N51,Q51,T51,W51,Z51,AC51,AF51,AI51,AL51,AO51) -> 0 | AV51: =SUM(I51,L51,O51,R51,U51,X51,AA51,AD51,AG51,AJ51,AM51,AP51) -> -65000 | AW51: =SUM(J51,M51,P51,S51,V51,Y51,AB51,AE51,AH51,AK51,AN51,AQ51) -> 0 | AX51: =SUM(H51,K51,N51) -> 0 | AY51: =SUM(I51,L51,O51) -> 0 | AZ51: =SUM(J51,M51,P51) -> 0 | BA51: =SUM(Q51,T51,W51) -> 0 | BB51: =SUM(R51,U51,X51) -> 0 | BC51: =SUM(S51,V51,Y51) -> 0 | BD51: =SUM(Z51,AC51,AF51) -> 0 | BE51: =SUM(AA51,AD51,AG51) -> -26000 | BF51: =SUM(AB51,AE51,AH51) -> 0 | BG51: =SUM(AI51,AL51,AO51) -> 0 | BH51: =SUM(AJ51,AM51,AP51) -> -39000 | BI51: =SUM(AK51,AN51,AQ51) -> 0
A52: Locação de Equipamentos Variável | C52: Estim. Mensal | E52: 0 | H52: 0 | I52: =-SUMIFS(T_ORCAMENTOS!$E:$E,T_ORCAMENTOS!$C:$C,"Locação de Equipamentos Variável",T_ORCAMENTOS!$H:$H,"1/2026") -> 0 | J52: =SUMIFS(Aut_BlueMe_Sem_Pedido!$J:$J,Aut_BlueMe_Sem_Pedido!$Q:$Q,DRE!H$4,Aut_BlueMe_Sem_Pedido!$H:$H,DRE!$A52)+SUMIFS(Aut_Ajustes_Manuais!$G:$G,Aut_Ajustes_Manuais!$I:$I,DRE!H$4,Aut_Ajustes_Manuais!$F:$F,"Locação de Equipamentos Variável") -> 0 | K52: 0 | L52: =-SUMIFS(T_ORCAMENTOS!$E:$E,T_ORCAMENTOS!$C:$C,"Locação de Equipamentos Variável",T_ORCAMENTOS!$H:$H,"2/2026") -> 0 | M52: =SUMIFS(Aut_BlueMe_Sem_Pedido!$J:$J,Aut_BlueMe_Sem_Pedido!$Q:$Q,DRE!K$4,Aut_BlueMe_Sem_Pedido!$H:$H,DRE!$A52)+SUMIFS(Aut_Ajustes_Manuais!$G:$G,Aut_Ajustes_Manuais!$I:$I,DRE!K$4,Aut_Ajustes_Manuais!$F:$F,"Locação de Equipamentos Variável") -> 0 | N52: 0 | O52: =-SUMIFS(T_ORCAMENTOS!$E:$E,T_ORCAMENTOS!$C:$C,"Locação de Equipamentos Variável",T_ORCAMENTOS!$H:$H,"3/2026") -> 0 | P52: =SUMIFS(Aut_BlueMe_Sem_Pedido!$J:$J,Aut_BlueMe_Sem_Pedido!$Q:$Q,DRE!N$4,Aut_BlueMe_Sem_Pedido!$H:$H,DRE!$A52)+SUMIFS(Aut_Ajustes_Manuais!$G:$G,Aut_Ajustes_Manuais!$I:$I,DRE!N$4,Aut_Ajustes_Manuais!$F:$F,"Locação de Equipamentos Variável") -> 0 | Q52: 0 | R52: =-SUMIFS(T_ORCAMENTOS!$E:$E,T_ORCAMENTOS!$C:$C,"Locação de Equipamentos Variável",T_ORCAMENTOS!$H:$H,"4/2026") -> 0 | S52: =SUMIFS(Aut_BlueMe_Sem_Pedido!$J:$J,Aut_BlueMe_Sem_Pedido!$Q:$Q,DRE!Q$4,Aut_BlueMe_Sem_Pedido!$H:$H,DRE!$A52)+SUMIFS(Aut_Ajustes_Manuais!$G:$G,Aut_Ajustes_Manuais!$I:$I,DRE!Q$4,Aut_Ajustes_Manuais!$F:$F,"Locação de Equipamentos Variável") -> 0 | T52: 0 | U52: =-SUMIFS(T_ORCAMENTOS!$E:$E,T_ORCAMENTOS!$C:$C,"Locação de Equipamentos Variável",T_ORCAMENTOS!$H:$H,"5/2026") -> 0 | V52: =SUMIFS(Aut_BlueMe_Sem_Pedido!$J:$J,Aut_BlueMe_Sem_Pedido!$Q:$Q,DRE!T$4,Aut_BlueMe_Sem_Pedido!$H:$H,DRE!$A52)+SUMIFS(Aut_Ajustes_Manuais!$G:$G,Aut_Ajustes_Manuais!$I:$I,DRE!T$4,Aut_Ajustes_Manuais!$F:$F,"Locação de Equipamentos Variável") -> 0 | W52: 0 | X52: =-SUMIFS(T_ORCAMENTOS!$E:$E,T_ORCAMENTOS!$C:$C,"Locação de Equipamentos Variável",T_ORCAMENTOS!$H:$H,"6/2026") -> 0 | Y52: =SUMIFS(Aut_BlueMe_Sem_Pedido!$J:$J,Aut_BlueMe_Sem_Pedido!$Q:$Q,DRE!W$4,Aut_BlueMe_Sem_Pedido!$H:$H,DRE!$A52)+SUMIFS(Aut_Ajustes_Manuais!$G:$G,Aut_Ajustes_Manuais!$I:$I,DRE!W$4,Aut_Ajustes_Manuais!$F:$F,"Locação de Equipamentos Variável") -> 0 | Z52: 0 | AA52: =-SUMIFS(T_ORCAMENTOS!$E:$E,T_ORCAMENTOS!$C:$C,"Locação de Equipamentos Variável",T_ORCAMENTOS!$H:$H,"7/2026") -> 0 | AB52: =SUMIFS(Aut_BlueMe_Sem_Pedido!$J:$J,Aut_BlueMe_Sem_Pedido!$Q:$Q,DRE!Z$4,Aut_BlueMe_Sem_Pedido!$H:$H,DRE!$A52)+SUMIFS(Aut_Ajustes_Manuais!$G:$G,Aut_Ajustes_Manuais!$I:$I,DRE!Z$4,Aut_Ajustes_Manuais!$F:$F,"Locação de Equipamentos Variável") -> 0 | AC52: 0 | AD52: =-SUMIFS(T_ORCAMENTOS!$E:$E,T_ORCAMENTOS!$C:$C,"Locação de Equipamentos Variável",T_ORCAMENTOS!$H:$H,"8/2026") -> 0 | AE52: =SUMIFS(Aut_BlueMe_Sem_Pedido!$J:$J,Aut_BlueMe_Sem_Pedido!$Q:$Q,DRE!AC$4,Aut_BlueMe_Sem_Pedido!$H:$H,DRE!$A52)+SUMIFS(Aut_Ajustes_Manuais!$G:$G,Aut_Ajustes_Manuais!$I:$I,DRE!AC$4,Aut_Ajustes_Manuais!$F:$F,"Locação de Equipamentos Variável") -> 0 | AF52: 0 | AG52: =-SUMIFS(T_ORCAMENTOS!$E:$E,T_ORCAMENTOS!$C:$C,"Locação de Equipamentos Variável",T_ORCAMENTOS!$H:$H,"9/2026") -> 0 | AH52: =SUMIFS(Aut_BlueMe_Sem_Pedido!$J:$J,Aut_BlueMe_Sem_Pedido!$Q:$Q,DRE!AF$4,Aut_BlueMe_Sem_Pedido!$H:$H,DRE!$A52)+SUMIFS(Aut_Ajustes_Manuais!$G:$G,Aut_Ajustes_Manuais!$I:$I,DRE!AF$4,Aut_Ajustes_Manuais!$F:$F,"Locação de Equipamentos Variável") -> 0 | AI52: 0 | AJ52: =-SUMIFS(T_ORCAMENTOS!$E:$E,T_ORCAMENTOS!$C:$C,"Locação de Equipamentos Variável",T_ORCAMENTOS!$H:$H,"10/2026") -> 0 | AK52: =SUMIFS(Aut_BlueMe_Sem_Pedido!$J:$J,Aut_BlueMe_Sem_Pedido!$Q:$Q,DRE!AI$4,Aut_BlueMe_Sem_Pedido!$H:$H,DRE!$A52)+SUMIFS(Aut_Ajustes_Manuais!$G:$G,Aut_Ajustes_Manuais!$I:$I,DRE!AI$4,Aut_Ajustes_Manuais!$F:$F,"Locação de Equipamentos Variável") -> 0 | AL52: 0 | AM52: =-SUMIFS(T_ORCAMENTOS!$E:$E,T_ORCAMENTOS!$C:$C,"Locação de Equipamentos Variável",T_ORCAMENTOS!$H:$H,"11/2026") -> 0 | AN52: =SUMIFS(Aut_BlueMe_Sem_Pedido!$J:$J,Aut_BlueMe_Sem_Pedido!$Q:$Q,DRE!AL$4,Aut_BlueMe_Sem_Pedido!$H:$H,DRE!$A52)+SUMIFS(Aut_Ajustes_Manuais!$G:$G,Aut_Ajustes_Manuais!$I:$I,DRE!AL$4,Aut_Ajustes_Manuais!$F:$F,"Locação de Equipamentos Variável") -> 0 | AO52: 0 | AP52: =-SUMIFS(T_ORCAMENTOS!$E:$E,T_ORCAMENTOS!$C:$C,"Locação de Equipamentos Variável",T_ORCAMENTOS!$H:$H,"12/2026") -> 0 | AQ52: =SUMIFS(Aut_BlueMe_Sem_Pedido!$J:$J,Aut_BlueMe_Sem_Pedido!$Q:$Q,DRE!AO$4,Aut_BlueMe_Sem_Pedido!$H:$H,DRE!$A52)+SUMIFS(Aut_Ajustes_Manuais!$G:$G,Aut_Ajustes_Manuais!$I:$I,DRE!AO$4,Aut_Ajustes_Manuais!$F:$F,"Locação de Equipamentos Variável") -> 0 | AR52: =SUMIFS($H52:$AO52,$H$5:$AO$5,"<"&MONTH(TODAY()),$H$6:$AO$6,"REAL 25") -> 0 | AS52: =SUMIFS($I52:$AP52,$I$5:$AP$5,"<"&MONTH(TODAY()),$I$6:$AP$6,"ORÇADO ") -> 0 | AT52: =SUMIFS($J52:$AQ52,$J$5:$AQ$5,"<"&MONTH(TODAY()),$J$6:$AQ$6,"REAL 26") -> 0 | AU52: =SUM(H52,K52,N52,Q52,T52,W52,Z52,AC52,AF52,AI52,AL52,AO52) -> 0 | AV52: =SUM(I52,L52,O52,R52,U52,X52,AA52,AD52,AG52,AJ52,AM52,AP52) -> 0 | AW52: =SUM(J52,M52,P52,S52,V52,Y52,AB52,AE52,AH52,AK52,AN52,AQ52) -> 0 | AX52: =SUM(H52,K52,N52) -> 0 | AY52: =SUM(I52,L52,O52) -> 0 | AZ52: =SUM(J52,M52,P52) -> 0 | BA52: =SUM(Q52,T52,W52) -> 0 | BB52: =SUM(R52,U52,X52) -> 0 | BC52: =SUM(S52,V52,Y52) -> 0 | BD52: =SUM(Z52,AC52,AF52) -> 0 | BE52: =SUM(AA52,AD52,AG52) -> 0 | BF52: =SUM(AB52,AE52,AH52) -> 0 | BG52: =SUM(AI52,AL52,AO52) -> 0 | BH52: =SUM(AJ52,AM52,AP52) -> 0 | BI52: =SUM(AK52,AN52,AQ52) -> 0
A53: % sobre Receita Artístico | H53: 0 | I53: =IFERROR(I42/I11,0) -> 0 | J53: =IFERROR(J42/J11,0)+SUMIFS(Aut_Ajustes_Manuais!$G:$G,Aut_Ajustes_Manuais!$I:$I,DRE!H$4,Aut_Ajustes_Manuais!$F:$F,"% sobre Receita Artístico") -> 0 | K53: 0 | L53: =IFERROR(L42/L11,0) -> 0 | M53: =IFERROR(M42/M11,0)+SUMIFS(Aut_Ajustes_Manuais!$G:$G,Aut_Ajustes_Manuais!$I:$I,DRE!K$4,Aut_Ajustes_Manuais!$F:$F,"% sobre Receita Artístico") -> 0 | N53: -3.2703978 | O53: =IFERROR(O42/O11,0) -> 0 | P53: =IFERROR(P42/P11,0)+SUMIFS(Aut_Ajustes_Manuais!$G:$G,Aut_Ajustes_Manuais!$I:$I,DRE!N$4,Aut_Ajustes_Manuais!$F:$F,"% sobre Receita Artístico") -> 0 | Q53: 0 | R53: =IFERROR(R42/R11,0) -> 0 | S53: =IFERROR(S42/S11,0)+SUMIFS(Aut_Ajustes_Manuais!$G:$G,Aut_Ajustes_Manuais!$I:$I,DRE!Q$4,Aut_Ajustes_Manuais!$F:$F,"% sobre Receita Artístico") -> 0 | T53: 0 | U53: =IFERROR(U42/U11,0) -> 0 | V53: =IFERROR(V42/V11,0)+SUMIFS(Aut_Ajustes_Manuais!$G:$G,Aut_Ajustes_Manuais!$I:$I,DRE!T$4,Aut_Ajustes_Manuais!$F:$F,"% sobre Receita Artístico") -> 0 | W53: 0 | X53: =IFERROR(X42/X11,0) -> 0 | Y53: =IFERROR(Y42/Y11,0)+SUMIFS(Aut_Ajustes_Manuais!$G:$G,Aut_Ajustes_Manuais!$I:$I,DRE!W$4,Aut_Ajustes_Manuais!$F:$F,"% sobre Receita Artístico") -> 0 | Z53: 0 | AA53: =IFERROR(AA42/AA11,0) -> 0 | AB53: =IFERROR(AB42/AB11,0)+SUMIFS(Aut_Ajustes_Manuais!$G:$G,Aut_Ajustes_Manuais!$I:$I,DRE!Z$4,Aut_Ajustes_Manuais!$F:$F,"% sobre Receita Artístico") -> 0 | AC53: 0 | AD53: =IFERROR(AD42/AD11,0) -> -0.88409165 | AE53: =IFERROR(AE42/AE11,0)+SUMIFS(Aut_Ajustes_Manuais!$G:$G,Aut_Ajustes_Manuais!$I:$I,DRE!AC$4,Aut_Ajustes_Manuais!$F:$F,"% sobre Receita Artístico") -> 0 | AF53: 0 | AG53: =IFERROR(AG42/AG11,0) -> -0.92924284 | AH53: =IFERROR(AH42/AH11,0)+SUMIFS(Aut_Ajustes_Manuais!$G:$G,Aut_Ajustes_Manuais!$I:$I,DRE!AF$4,Aut_Ajustes_Manuais!$F:$F,"% sobre Receita Artístico") -> 0 | AI53: 0 | AJ53: =IFERROR(AJ42/AJ11,0) -> -0.8529707 | AK53: =IFERROR(AK42/AK11,0)+SUMIFS(Aut_Ajustes_Manuais!$G:$G,Aut_Ajustes_Manuais!$I:$I,DRE!AI$4,Aut_Ajustes_Manuais!$F:$F,"% sobre Receita Artístico") -> 0 | AL53: 0 | AM53: =IFERROR(AM42/AM11,0) -> -0.93647208 | AN53: =IFERROR(AN42/AN11,0)+SUMIFS(Aut_Ajustes_Manuais!$G:$G,Aut_Ajustes_Manuais!$I:$I,DRE!AL$4,Aut_Ajustes_Manuais!$F:$F,"% sobre Receita Artístico") -> 0 | AO53: 0 | AP53: =IFERROR(AP42/AP11,0) -> -0.95157445 | AQ53: =IFERROR(AQ42/AQ11,0)+SUMIFS(Aut_Ajustes_Manuais!$G:$G,Aut_Ajustes_Manuais!$I:$I,DRE!AO$4,Aut_Ajustes_Manuais!$F:$F,"% sobre Receita Artístico") -> 0 | AR53: =IFERROR(AR42/AR11,0) -> 0 | AS53: =IFERROR(AS42/AS11,0) -> -0.88409165 | AT53: =IFERROR(AT42/AT11,0) -> 0 | AU53: =IFERROR(AU42/AU11,0) -> 0 | AV53: =IFERROR(AV42/AV11,0) -> -0.90925107 | AW53: =IFERROR(AW42/AW11,0) -> 0 | AX53: =IFERROR(AX42/AX11,0) -> 0 | AY53: =IFERROR(AY42/AY11,0) -> 0 | ... BI53: =IFERROR(BI42/BI11,0) -> 0
