Workbook

Sheet DRE
A3: BAR LEO | H3: =J8/H8 -> 1.1349048 | J3: =J8/I8 -> 1.0317316 | K3: =M8/K8 -> 1.0260133 | M3: =M8/L8 -> 0.89218552 | N3: =P8/N8 -> 1.0889138 | P3: =P8/O8 -> 1.1836019 | Q3: =S8/Q8 -> 1.1210415 | S3: =S8/R8 -> 1.2456016 | T3: =V8/T8 -> 0.85507486 | V3: =V8/U8 -> 0.77033771 | Y3: =Y8/X8 -> 0.83320363 | AB3: =AB8/AA8 -> 0.18377506 | AE3: =AE8/AD8 -> 0 | AH3: =AH8/AG8 -> 0 | AK3: =AK8/AJ8 -> 0 | AN3: =AN8/AM8 -> 0 | AQ3: =AQ8/AP8 -> 0 | AR3: =AT8/AR8 -> 1.0417289 | AT3: =AT8/AS8 -> 0.96212556
H4: 46023 | K4: 46054 | N4: 46082 | Q4: 46113 | T4: 46143 | W4: 46174 | Z4: 46204 | AC4: 46235 | AF4: 46266 | AI4: 46296 | AL4: 46327 | AO4: 46357 | AR4: Acumulado | AU4: ANO | AX4: 1º TRIMESTRE | BA4: 2º TRIMESTRE | BD4: 3º TRIMESTRE | BG4: 4º TRIMESTRE
H5: 1 | I5: 1 | J5: =MONTH(H4) -> 1 | K5: 2 | L5: 2 | M5: =MONTH(K4) -> 2 | N5: 3 | O5: 3 | P5: =MONTH(N4) -> 3 | Q5: 4 | R5: 4 | S5: =MONTH(Q4) -> 4 | T5: 5 | U5: 5 | V5: =MONTH(T4) -> 5 | W5: 6 | X5: 6 | Y5: =MONTH(W4) -> 6 | Z5: 7 | AA5: 7 | AB5: =MONTH(Z4) -> 7 | AC5: 8 | AD5: 8 | AE5: =MONTH(AC4) -> 8 | AF5: 9 | AG5: 9 | AH5: =MONTH(AF4) -> 9 | AI5: 10 | AJ5: 10 | AK5: =MONTH(AI4) -> 10 | AL5: 11 | AM5: 11 | AN5: =MONTH(AL4) -> 11 | AO5: 12 | AP5: 12 | AQ5: =MONTH(AO4) -> 12
H6: REAL 25 | I6: ORÇADO | J6: REAL 26 | K6: REAL 25 | L6: ORÇADO | M6: REAL 26 | N6: REAL 25 | O6: ORÇADO | P6: REAL 26 | Q6: REAL 25 | R6: ORÇADO | S6: REAL 26 | T6: REAL 25 | U6: ORÇADO | V6: REAL 26 | W6: REAL 25 | X6: ORÇADO | Y6: REAL 26 | Z6: REAL 25 | AA6: ORÇADO | AB6: REAL 26 | AC6: REAL 25 | AD6: ORÇADO | AE6: REAL 26 | AF6: REAL 25 | AG6: ORÇADO | AH6: REAL 26 | AI6: REAL 25 | AJ6: ORÇADO | AK6: REAL 26 | AL6: REAL 25 | AM6: ORÇADO | AN6: REAL 26 | AO6: REAL 25 | AP6: ORÇADO | AQ6: REAL 26 | AR6: 2025 | AS6: ORÇADO | AT6: REAL 2026 | AU6: 2025 | AV6: ORÇADO | AW6: REAL 2026 | AX6: REAL 25 | AY6: ORÇADO | AZ6: REAL 26 | BA6: REAL 25 | BB6: ORÇADO | BC6: REAL 26 | BD6: REAL 25 | BE6: ORÇADO | BF6: REAL 26 | BG6: REAL 25 | BH6: ORÇADO | BI6: REAL 26
H7: 45658 | I7: 46023 | K7: 45689 | L7: 46054 | N7: 45717 | Q7: 45748 | T7: 45778 | W7: 45809 | Z7: 45839 | AC7: 45870 | AF7: 45901 | AI7: 45931 | AL7: 45962 | AO7: 45992 | BK7: Validação orçado | BM7: Validação real
A8: FATURAMENTO BRUTO | C8: PARÂMETROS UTILIZADOS | H8: 340452.79 | I8: 374498.07 | J8: =SUM(J9:J19)+SUMIFS(Aut_Ajustes_Manuais!$G:$G,Aut_Ajustes_Manuais!$I:$I,DRE!H$4,Aut_Ajustes_Manuais!$F:$F,"FATURAMENTO BRUTO") -> 386381.5 | K8: 308971.38 | L8: 355317.09 | M8: =SUM(M9:M19)+SUMIFS(Aut_Ajustes_Manuais!$G:$G,Aut_Ajustes_Manuais!$I:$I,DRE!K$4,Aut_Ajustes_Manuais!$F:$F,"FATURAMENTO BRUTO") -> 317008.76 | N8: 309840.35 | O8: 285053.12 | P8: =SUM(P9:P19)+SUMIFS(Aut_Ajustes_Manuais!$G:$G,Aut_Ajustes_Manuais!$I:$I,DRE!N$4,Aut_Ajustes_Manuais!$F:$F,"FATURAMENTO BRUTO") -> 337389.43 | Q8: 329611.99 | R8: 296650.79 | S8: =SUM(S9:S19)+SUMIFS(Aut_Ajustes_Manuais!$G:$G,Aut_Ajustes_Manuais!$I:$I,DRE!Q$4,Aut_Ajustes_Manuais!$F:$F,"FATURAMENTO BRUTO") -> 369508.71 | T8: 435998.13 | U8: 483957.92 | V8: =SUM(V9:V19)+SUMIFS(Aut_Ajustes_Manuais!$G:$G,Aut_Ajustes_Manuais!$I:$I,DRE!T$4,Aut_Ajustes_Manuais!$F:$F,"FATURAMENTO BRUTO") -> 372811.04 | W8: 331895.17 | X8: 431463.72 | Y8: =SUM(Y9:Y19)+SUMIFS(Aut_Ajustes_Manuais!$G:$G,Aut_Ajustes_Manuais!$I:$I,DRE!W$4,Aut_Ajustes_Manuais!$F:$F,"FATURAMENTO BRUTO") -> 359497.14 | Z8: 356143.63 | AA8: 427372.36 | AB8: =SUM(AB9:AB19)+SUMIFS(Aut_Ajustes_Manuais!$G:$G,Aut_Ajustes_Manuais!$I:$I,DRE!Z$4,Aut_Ajustes_Manuais!$F:$F,"FATURAMENTO BRUTO") -> 78540.38 | AC8: 415517.46 | AD8: 461224.38 | AE8: =SUM(AE9:AE19)+SUMIFS(Aut_Ajustes_Manuais!$G:$G,Aut_Ajustes_Manuais!$I:$I,DRE!AC$4,Aut_Ajustes_Manuais!$F:$F,"FATURAMENTO BRUTO") -> 0 | AF8: 352535.84 | AG8: 401890.86 | AH8: =SUM(AH9:AH19)+SUMIFS(Aut_Ajustes_Manuais!$G:$G,Aut_Ajustes_Manuais!$I:$I,DRE!AF$4,Aut_Ajustes_Manuais!$F:$F,"FATURAMENTO BRUTO") -> 0 | AI8: 362912.76 | AJ8: 404425.97 | AK8: =SUM(AK9:AK19)+SUMIFS(Aut_Ajustes_Manuais!$G:$G,Aut_Ajustes_Manuais!$I:$I,DRE!AI$4,Aut_Ajustes_Manuais!$F:$F,"FATURAMENTO BRUTO") -> 0 | AL8: 429533.42 | AM8: 469333.44 | AN8: =SUM(AN9:AN19)+SUMIFS(Aut_Ajustes_Manuais!$G:$G,Aut_Ajustes_Manuais!$I:$I,DRE!AL$4,Aut_Ajustes_Manuais!$F:$F,"FATURAMENTO BRUTO") -> 0 | AO8: 480232.62 | AP8: 424800 | AQ8: =SUM(AQ9:AQ19)+SUMIFS(Aut_Ajustes_Manuais!$G:$G,Aut_Ajustes_Manuais!$I:$I,DRE!AO$4,Aut_Ajustes_Manuais!$F:$F,"FATURAMENTO BRUTO") -> 0 | AR8: =SUM(AR9:AR19) -> 2056769.8 | AS8: =SUM(AS9:AS19) -> 2226940.7 | AT8: =SUM(AT9:AT19) -> 2142596.6 | AU8: =SUM(AU9:AU19) -> 4453645.5 | AV8: =SUM(AV9:AV19) -> 4815987.7 | AW8: =SUM(AW9:AW19) -> 2221137 | AX8: =SUM(AX9:AX19) -> 959264.52 | AY8: =SUM(AY9:AY19) -> 1014868.3 | ... BI8: =SUM(BI9:BI19) -> 0 | BK8: =SUM(I8,L8,O8,R8,U8,X8,AA8,AD8,AG8,AJ8,AM8,AP8) -> 4815987.7 | BL8: =BK8-AV8 -> 0 | BM8: =SUM(J8,M8,P8,S8,V8) -> 1783099.4 | BN8: =BM8-AT8 -> -359497.14
A9: Alimentação | C9: Estim. Mensal | D9: Preencher base de Faturamento A&B&C | H9: 143346 | I9: 118996.39 | J9: =SUMIFS(Aut_Faturamento_Zig!$F:$F,Aut_Faturamento_Zig!$E:$E,"Alimentos",Aut_Faturamento_Zig!$D:$D,DRE!H$4)-SUMIFS(Aut_Promocoes_Utilizadas!$G:$G,Aut_Promocoes_Utilizadas!$J:$J,DRE!H$4,Aut_Promocoes_Utilizadas!$H:$H,"A",Aut_Promocoes_Utilizadas!$I:$I,"Eventos")-SUMIFS(Aut_Descontos!$I:$I,Aut_Descontos!$L:$L,DRE!H$4)-(SUMIFS(BD_Eventos_Novo!$J:$J,BD_Eventos_Novo!$AB:$AB,DRE!H$4,BD_Eventos_Novo!$G:$G,"Consumação Mínima")*50%)-(SUMIFS(BD_Eventos_Novo!$K:$K,BD_Eventos_Novo!$AB:$AB,DRE!H$4,BD_Eventos_Novo!$G:$G,"Consumação Mínima")*50%)-(SUMIFS(BD_Eventos_Novo!$J:$J,BD_Eventos_Novo!$AB:$AB,DRE!H$4,BD_Eventos_Novo!$G:$G,"Comanda Aberta / Couvert Antecipado")*50%)-(SUMIFS(BD_Eventos_Novo!$K:$K,BD_Eventos_Novo!$AB:$AB,DRE!H$4,BD_Eventos_Novo!$G:$G,"Comanda Aberta / Couvert Antecipado")*50%)+SUMIFS(Aut_Ajustes_Manuais!$G:$G,Aut_Ajustes_Manuais!$I:$I,DRE!H$4,Aut_Ajustes_Manuais!$F:$F,"Alimentação") -> 150801.5 | K9: 132728.5 | L9: 112901.65 | M9: =SUMIFS(Aut_Faturamento_Zig!$F:$F,Aut_Faturamento_Zig!$E:$E,"Alimentos",Aut_Faturamento_Zig!$D:$D,DRE!K$4)-SUMIFS(Aut_Promocoes_Utilizadas!$G:$G,Aut_Promocoes_Utilizadas!$J:$J,DRE!K$4,Aut_Promocoes_Utilizadas!$H:$H,"A",Aut_Promocoes_Utilizadas!$I:$I,"Eventos")-SUMIFS(Aut_Descontos!$I:$I,Aut_Descontos!$L:$L,DRE!K$4)-(SUMIFS(BD_Eventos_Novo!$J:$J,BD_Eventos_Novo!$AB:$AB,DRE!K$4,BD_Eventos_Novo!$G:$G,"Consumação Mínima")*50%)-(SUMIFS(BD_Eventos_Novo!$K:$K,BD_Eventos_Novo!$AB:$AB,DRE!K$4,BD_Eventos_Novo!$G:$G,"Consumação Mínima")*50%)-(SUMIFS(BD_Eventos_Novo!$J:$J,BD_Eventos_Novo!$AB:$AB,DRE!K$4,BD_Eventos_Novo!$G:$G,"Comanda Aberta / Couvert Antecipado")*50%)-(SUMIFS(BD_Eventos_Novo!$K:$K,BD_Eventos_Novo!$AB:$AB,DRE!K$4,BD_Eventos_Novo!$G:$G,"Comanda Aberta / Couvert Antecipado")*50%)+SUMIFS(Aut_Ajustes_Manuais!$G:$G,Aut_Ajustes_Manuais!$I:$I,DRE!K$4,Aut_Ajustes_Manuais!$F:$F,"Alimentação") -> 125404.4 | N9: 131478.5 | O9: 90575.348 | P9: =SUMIFS(Aut_Faturamento_Zig!$F:$F,Aut_Faturamento_Zig!$E:$E,"Alimentos",Aut_Faturamento_Zig!$D:$D,DRE!N$4)-SUMIFS(Aut_Promocoes_Utilizadas!$G:$G,Aut_Promocoes_Utilizadas!$J:$J,DRE!N$4,Aut_Promocoes_Utilizadas!$H:$H,"A",Aut_Promocoes_Utilizadas!$I:$I,"Eventos")-SUMIFS(Aut_Descontos!$I:$I,Aut_Descontos!$L:$L,DRE!N$4)-(SUMIFS(BD_Eventos_Novo!$J:$J,BD_Eventos_Novo!$AB:$AB,DRE!N$4,BD_Eventos_Novo!$G:$G,"Consumação Mínima")*50%)-(SUMIFS(BD_Eventos_Novo!$K:$K,BD_Eventos_Novo!$AB:$AB,DRE!N$4,BD_Eventos_Novo!$G:$G,"Consumação Mínima")*50%)-(SUMIFS(BD_Eventos_Novo!$J:$J,BD_Eventos_Novo!$AB:$AB,DRE!N$4,BD_Eventos_Novo!$G:$G,"Comanda Aberta / Couvert Antecipado")*50%)-(SUMIFS(BD_Eventos_Novo!$K:$K,BD_Eventos_Novo!$AB:$AB,DRE!N$4,BD_Eventos_Novo!$G:$G,"Comanda Aberta / Couvert Antecipado")*50%)+SUMIFS(Aut_Ajustes_Manuais!$G:$G,Aut_Ajustes_Manuais!$I:$I,DRE!N$4,Aut_Ajustes_Manuais!$F:$F,"Alimentação") -> 134559.5 | Q9: 144072 | R9: 94260.496 | S9: =SUMIFS(Aut_Faturamento_Zig!$F:$F,Aut_Faturamento_Zig!$E:$E,"Alimentos",Aut_Faturamento_Zig!$D:$D,DRE!Q$4)-SUMIFS(Aut_Promocoes_Utilizadas!$G:$G,Aut_Promocoes_Utilizadas!$J:$J,DRE!Q$4,Aut_Promocoes_Utilizadas!$H:$H,"A",Aut_Promocoes_Utilizadas!$I:$I,"Eventos")-SUMIFS(Aut_Descontos!$I:$I,Aut_Descontos!$L:$L,DRE!Q$4)-(SUMIFS(BD_Eventos_Novo!$J:$J,BD_Eventos_Novo!$AB:$AB,DRE!Q$4,BD_Eventos_Novo!$G:$G,"Consumação Mínima")*50%)-(SUMIFS(BD_Eventos_Novo!$K:$K,BD_Eventos_Novo!$AB:$AB,DRE!Q$4,BD_Eventos_Novo!$G:$G,"Consumação Mínima")*50%)-(SUMIFS(BD_Eventos_Novo!$J:$J,BD_Eventos_Novo!$AB:$AB,DRE!Q$4,BD_Eventos_Novo!$G:$G,"Comanda Aberta / Couvert Antecipado")*50%)-(SUMIFS(BD_Eventos_Novo!$K:$K,BD_Eventos_Novo!$AB:$AB,DRE!Q$4,BD_Eventos_Novo!$G:$G,"Comanda Aberta / Couvert Antecipado")*50%)+SUMIFS(Aut_Ajustes_Manuais!$G:$G,Aut_Ajustes_Manuais!$I:$I,DRE!Q$4,Aut_Ajustes_Manuais!$F:$F,"Alimentação") -> 147447.9 | T9: 185616.1 | U9: 153777.15 | V9: =SUMIFS(Aut_Faturamento_Zig!$F:$F,Aut_Faturamento_Zig!$E:$E,"Alimentos",Aut_Faturamento_Zig!$D:$D,DRE!T$4)-SUMIFS(Aut_Promocoes_Utilizadas!$G:$G,Aut_Promocoes_Utilizadas!$J:$J,DRE!T$4,Aut_Promocoes_Utilizadas!$H:$H,"A",Aut_Promocoes_Utilizadas!$I:$I,"Eventos")-SUMIFS(Aut_Descontos!$I:$I,Aut_Descontos!$L:$L,DRE!T$4)-(SUMIFS(BD_Eventos_Novo!$J:$J,BD_Eventos_Novo!$AB:$AB,DRE!T$4,BD_Eventos_Novo!$G:$G,"Consumação Mínima")*50%)-(SUMIFS(BD_Eventos_Novo!$K:$K,BD_Eventos_Novo!$AB:$AB,DRE!T$4,BD_Eventos_Novo!$G:$G,"Consumação Mínima")*50%)-(SUMIFS(BD_Eventos_Novo!$J:$J,BD_Eventos_Novo!$AB:$AB,DRE!T$4,BD_Eventos_Novo!$G:$G,"Comanda Aberta / Couvert Antecipado")*50%)-(SUMIFS(BD_Eventos_Novo!$K:$K,BD_Eventos_Novo!$AB:$AB,DRE!T$4,BD_Eventos_Novo!$G:$G,"Comanda Aberta / Couvert Antecipado")*50%)+SUMIFS(Aut_Ajustes_Manuais!$G:$G,Aut_Ajustes_Manuais!$I:$I,DRE!T$4,Aut_Ajustes_Manuais!$F:$F,"Alimentação") -> 154905.5 | W9: 141881.5 | X9: 137097.17 | Y9: =SUMIFS(Aut_Faturamento_Zig!$F:$F,Aut_Faturamento_Zig!$E:$E,"Alimentos",Aut_Faturamento_Zig!$D:$D,DRE!W$4)-SUMIFS(Aut_Promocoes_Utilizadas!$G:$G,Aut_Promocoes_Utilizadas!$J:$J,DRE!W$4,Aut_Promocoes_Utilizadas!$H:$H,"A",Aut_Promocoes_Utilizadas!$I:$I,"Eventos")-SUMIFS(Aut_Descontos!$I:$I,Aut_Descontos!$L:$L,DRE!W$4)-(SUMIFS(BD_Eventos_Novo!$J:$J,BD_Eventos_Novo!$AB:$AB,DRE!W$4,BD_Eventos_Novo!$G:$G,"Consumação Mínima")*50%)-(SUMIFS(BD_Eventos_Novo!$K:$K,BD_Eventos_Novo!$AB:$AB,DRE!W$4,BD_Eventos_Novo!$G:$G,"Consumação Mínima")*50%)-(SUMIFS(BD_Eventos_Novo!$J:$J,BD_Eventos_Novo!$AB:$AB,DRE!W$4,BD_Eventos_Novo!$G:$G,"Comanda Aberta / Couvert Antecipado")*50%)-(SUMIFS(BD_Eventos_Novo!$K:$K,BD_Eventos_Novo!$AB:$AB,DRE!W$4,BD_Eventos_Novo!$G:$G,"Comanda Aberta / Couvert Antecipado")*50%)+SUMIFS(Aut_Ajustes_Manuais!$G:$G,Aut_Ajustes_Manuais!$I:$I,DRE!W$4,Aut_Ajustes_Manuais!$F:$F,"Alimentação") -> 149615.3 | Z9: 160709.8 | AA9: 135797.14 | AB9: =SUMIFS(Aut_Faturamento_Zig!$F:$F,Aut_Faturamento_Zig!$E:$E,"Alimentos",Aut_Faturamento_Zig!$D:$D,DRE!Z$4)-SUMIFS(Aut_Promocoes_Utilizadas!$G:$G,Aut_Promocoes_Utilizadas!$J:$J,DRE!Z$4,Aut_Promocoes_Utilizadas!$H:$H,"A",Aut_Promocoes_Utilizadas!$I:$I,"Eventos")-SUMIFS(Aut_Descontos!$I:$I,Aut_Descontos!$L:$L,DRE!Z$4)-(SUMIFS(BD_Eventos_Novo!$J:$J,BD_Eventos_Novo!$AB:$AB,DRE!Z$4,BD_Eventos_Novo!$G:$G,"Consumação Mínima")*50%)-(SUMIFS(BD_Eventos_Novo!$K:$K,BD_Eventos_Novo!$AB:$AB,DRE!Z$4,BD_Eventos_Novo!$G:$G,"Consumação Mínima")*50%)-(SUMIFS(BD_Eventos_Novo!$J:$J,BD_Eventos_Novo!$AB:$AB,DRE!Z$4,BD_Eventos_Novo!$G:$G,"Comanda Aberta / Couvert Antecipado")*50%)-(SUMIFS(BD_Eventos_Novo!$K:$K,BD_Eventos_Novo!$AB:$AB,DRE!Z$4,BD_Eventos_Novo!$G:$G,"Comanda Aberta / Couvert Antecipado")*50%)+SUMIFS(Aut_Ajustes_Manuais!$G:$G,Aut_Ajustes_Manuais!$I:$I,DRE!Z$4,Aut_Ajustes_Manuais!$F:$F,"Alimentação") -> 32087.5 | AC9: 169931.9 | AD9: 146553.59 | AE9: =SUMIFS(Aut_Faturamento_Zig!$F:$F,Aut_Faturamento_Zig!$E:$E,"Alimentos",Aut_Faturamento_Zig!$D:$D,DRE!AC$4)-SUMIFS(Aut_Promocoes_Utilizadas!$G:$G,Aut_Promocoes_Utilizadas!$J:$J,DRE!AC$4,Aut_Promocoes_Utilizadas!$H:$H,"A",Aut_Promocoes_Utilizadas!$I:$I,"Eventos")-SUMIFS(Aut_Descontos!$I:$I,Aut_Descontos!$L:$L,DRE!AC$4)-(SUMIFS(BD_Eventos_Novo!$J:$J,BD_Eventos_Novo!$AB:$AB,DRE!AC$4,BD_Eventos_Novo!$G:$G,"Consumação Mínima")*50%)-(SUMIFS(BD_Eventos_Novo!$K:$K,BD_Eventos_Novo!$AB:$AB,DRE!AC$4,BD_Eventos_Novo!$G:$G,"Consumação Mínima")*50%)-(SUMIFS(BD_Eventos_Novo!$J:$J,BD_Eventos_Novo!$AB:$AB,DRE!AC$4,BD_Eventos_Novo!$G:$G,"Comanda Aberta / Couvert Antecipado")*50%)-(SUMIFS(BD_Eventos_Novo!$K:$K,BD_Eventos_Novo!$AB:$AB,DRE!AC$4,BD_Eventos_Novo!$G:$G,"Comanda Aberta / Couvert Antecipado")*50%)+SUMIFS(Aut_Ajustes_Manuais!$G:$G,Aut_Ajustes_Manuais!$I:$I,DRE!AC$4,Aut_Ajustes_Manuais!$F:$F,"Alimentação") -> 0 | AF9: 149655 | AG9: 127700.42 | AH9: =SUMIFS(Aut_Faturamento_Zig!$F:$F,Aut_Faturamento_Zig!$E:$E,"Alimentos",Aut_Faturamento_Zig!$D:$D,DRE!AF$4)-SUMIFS(Aut_Promocoes_Utilizadas!$G:$G,Aut_Promocoes_Utilizadas!$J:$J,DRE!AF$4,Aut_Promocoes_Utilizadas!$H:$H,"A",Aut_Promocoes_Utilizadas!$I:$I,"Eventos")-SUMIFS(Aut_Descontos!$I:$I,Aut_Descontos!$L:$L,DRE!AF$4)-(SUMIFS(BD_Eventos_Novo!$J:$J,BD_Eventos_Novo!$AB:$AB,DRE!AF$4,BD_Eventos_Novo!$G:$G,"Consumação Mínima")*50%)-(SUMIFS(BD_Eventos_Novo!$K:$K,BD_Eventos_Novo!$AB:$AB,DRE!AF$4,BD_Eventos_Novo!$G:$G,"Consumação Mínima")*50%)-(SUMIFS(BD_Eventos_Novo!$J:$J,BD_Eventos_Novo!$AB:$AB,DRE!AF$4,BD_Eventos_Novo!$G:$G,"Comanda Aberta / Couvert Antecipado")*50%)-(SUMIFS(BD_Eventos_Novo!$K:$K,BD_Eventos_Novo!$AB:$AB,DRE!AF$4,BD_Eventos_Novo!$G:$G,"Comanda Aberta / Couvert Antecipado")*50%)+SUMIFS(Aut_Ajustes_Manuais!$G:$G,Aut_Ajustes_Manuais!$I:$I,DRE!AF$4,Aut_Ajustes_Manuais!$F:$F,"Alimentação") -> 0 | AI9: 151610.5 | AJ9: 128505.95 | AK9: =SUMIFS(Aut_Faturamento_Zig!$F:$F,Aut_Faturamento_Zig!$E:$E,"Alimentos",Aut_Faturamento_Zig!$D:$D,DRE!AI$4)-SUMIFS(Aut_Promocoes_Utilizadas!$G:$G,Aut_Promocoes_Utilizadas!$J:$J,DRE!AI$4,Aut_Promocoes_Utilizadas!$H:$H,"A",Aut_Promocoes_Utilizadas!$I:$I,"Eventos")-SUMIFS(Aut_Descontos!$I:$I,Aut_Descontos!$L:$L,DRE!AI$4)-(SUMIFS(BD_Eventos_Novo!$J:$J,BD_Eventos_Novo!$AB:$AB,DRE!AI$4,BD_Eventos_Novo!$G:$G,"Consumação Mínima")*50%)-(SUMIFS(BD_Eventos_Novo!$K:$K,BD_Eventos_Novo!$AB:$AB,DRE!AI$4,BD_Eventos_Novo!$G:$G,"Consumação Mínima")*50%)-(SUMIFS(BD_Eventos_Novo!$J:$J,BD_Eventos_Novo!$AB:$AB,DRE!AI$4,BD_Eventos_Novo!$G:$G,"Comanda Aberta / Couvert Antecipado")*50%)-(SUMIFS(BD_Eventos_Novo!$K:$K,BD_Eventos_Novo!$AB:$AB,DRE!AI$4,BD_Eventos_Novo!$G:$G,"Comanda Aberta / Couvert Antecipado")*50%)+SUMIFS(Aut_Ajustes_Manuais!$G:$G,Aut_Ajustes_Manuais!$I:$I,DRE!AI$4,Aut_Ajustes_Manuais!$F:$F,"Alimentação") -> 0 | AL9: 154679 | AM9: 149130.24 | AN9: =SUMIFS(Aut_Faturamento_Zig!$F:$F,Aut_Faturamento_Zig!$E:$E,"Alimentos",Aut_Faturamento_Zig!$D:$D,DRE!AL$4)-SUMIFS(Aut_Promocoes_Utilizadas!$G:$G,Aut_Promocoes_Utilizadas!$J:$J,DRE!AL$4,Aut_Promocoes_Utilizadas!$H:$H,"A",Aut_Promocoes_Utilizadas!$I:$I,"Eventos")-SUMIFS(Aut_Descontos!$I:$I,Aut_Descontos!$L:$L,DRE!AL$4)-(SUMIFS(BD_Eventos_Novo!$J:$J,BD_Eventos_Novo!$AB:$AB,DRE!AL$4,BD_Eventos_Novo!$G:$G,"Consumação Mínima")*50%)-(SUMIFS(BD_Eventos_Novo!$K:$K,BD_Eventos_Novo!$AB:$AB,DRE!AL$4,BD_Eventos_Novo!$G:$G,"Consumação Mínima")*50%)-(SUMIFS(BD_Eventos_Novo!$J:$J,BD_Eventos_Novo!$AB:$AB,DRE!AL$4,BD_Eventos_Novo!$G:$G,"Comanda Aberta / Couvert Antecipado")*50%)-(SUMIFS(BD_Eventos_Novo!$K:$K,BD_Eventos_Novo!$AB:$AB,DRE!AL$4,BD_Eventos_Novo!$G:$G,"Comanda Aberta / Couvert Antecipado")*50%)+SUMIFS(Aut_Ajustes_Manuais!$G:$G,Aut_Ajustes_Manuais!$I:$I,DRE!AL$4,Aut_Ajustes_Manuais!$F:$F,"Alimentação") -> 0 | AO9: 170768.9 | AP9: 134979.78 | AQ9: =SUMIFS(Aut_Faturamento_Zig!$F:$F,Aut_Faturamento_Zig!$E:$E,"Alimentos",Aut_Faturamento_Zig!$D:$D,DRE!AO$4)-SUMIFS(Aut_Promocoes_Utilizadas!$G:$G,Aut_Promocoes_Utilizadas!$J:$J,DRE!AO$4,Aut_Promocoes_Utilizadas!$H:$H,"A",Aut_Promocoes_Utilizadas!$I:$I,"Eventos")-SUMIFS(Aut_Descontos!$I:$I,Aut_Descontos!$L:$L,DRE!AO$4)-(SUMIFS(BD_Eventos_Novo!$J:$J,BD_Eventos_Novo!$AB:$AB,DRE!AO$4,BD_Eventos_Novo!$G:$G,"Consumação Mínima")*50%)-(SUMIFS(BD_Eventos_Novo!$K:$K,BD_Eventos_Novo!$AB:$AB,DRE!AO$4,BD_Eventos_Novo!$G:$G,"Consumação Mínima")*50%)-(SUMIFS(BD_Eventos_Novo!$J:$J,BD_Eventos_Novo!$AB:$AB,DRE!AO$4,BD_Eventos_Novo!$G:$G,"Comanda Aberta / Couvert Antecipado")*50%)-(SUMIFS(BD_Eventos_Novo!$K:$K,BD_Eventos_Novo!$AB:$AB,DRE!AO$4,BD_Eventos_Novo!$G:$G,"Comanda Aberta / Couvert Antecipado")*50%)+SUMIFS(Aut_Ajustes_Manuais!$G:$G,Aut_Ajustes_Manuais!$I:$I,DRE!AO$4,Aut_Ajustes_Manuais!$F:$F,"Alimentação") -> 0 | AR9: =SUMIFS($H9:$AO9,$H$5:$AO$5,"<"&MONTH(TODAY()),$H$6:$AO$6,"REAL 25") -> 879122.6 | AS9: =SUMIFS($I9:$AP9,$I$5:$AP$5,"<"&MONTH(TODAY()),$I$6:$AP$6,"ORÇADO ") -> 707608.21 | AT9: =SUMIFS($J9:$AQ9,$J$5:$AQ$5,"<"&MONTH(TODAY()),$J$6:$AQ$6,"REAL 26") -> 862734.1 | AU9: =SUM(H9,K9,N9,Q9,T9,W9,Z9,AC9,AF9,AI9,AL9,AO9) -> 1836477.7 | AV9: =SUM(I9,L9,O9,R9,U9,X9,AA9,AD9,AG9,AJ9,AM9,AP9) -> 1530275.3 | AW9: =SUM(J9,M9,P9,S9,V9,Y9,AB9,AE9,AH9,AK9,AN9,AQ9) -> 894821.6 | AX9: =SUM(H9,K9,N9) -> 407553 | AY9: =SUM(I9,L9,O9) -> 322473.39 | AZ9: =SUM(J9,M9,P9) -> 410765.4 | BA9: =SUM(Q9,T9,W9) -> 471569.6 | BB9: =SUM(R9,U9,X9) -> 385134.82 | BC9: =SUM(S9,V9,Y9) -> 451968.7 | BD9: =SUM(Z9,AC9,AF9) -> 480296.7 | BE9: =SUM(AA9,AD9,AG9) -> 410051.16 | BF9: =SUM(AB9,AE9,AH9) -> 32087.5 | BG9: =SUM(AI9,AL9,AO9) -> 477058.4 | BH9: =SUM(AJ9,AM9,AP9) -> 412615.97 | BI9: =SUM(AK9,AN9,AQ9) -> 0 | BK9: =SUM(I9,L9,O9,R9,U9,X9,AA9,AD9,AG9,AJ9,AM9,AP9) -> 1530275.3 | BL9: =BK9-AV9 -> 0 | BM9: =SUM(J9,M9,P9,S9,V9) -> 713118.8 | BN9: =BM9-AT9 -> -149615.3
A10: Bebida | C10: Estim. Mensal | D10: Preencher base de Faturamento A&B&C | H10: 155838.7 | I10: 156633.25 | J10: =SUMIFS(Aut_Faturamento_Zig!$F:$F,Aut_Faturamento_Zig!$E:$E,"Bebidas",Aut_Faturamento_Zig!$D:$D,DRE!H$4)-SUMIFS(Aut_Promocoes_Utilizadas!$G:$G,Aut_Promocoes_Utilizadas!$J:$J,DRE!H$4,Aut_Promocoes_Utilizadas!$H:$H,"B",Aut_Promocoes_Utilizadas!$I:$I,"Eventos")-SUMIFS(Aut_Descontos!$J:$J,Aut_Descontos!$L:$L,DRE!H$4)-(SUMIFS(BD_Eventos_Novo!$J:$J,BD_Eventos_Novo!$AB:$AB,DRE!H$4,BD_Eventos_Novo!$G:$G,"Consumação Mínima")*50%)-(SUMIFS(BD_Eventos_Novo!$K:$K,BD_Eventos_Novo!$AB:$AB,DRE!H$4,BD_Eventos_Novo!$G:$G,"Consumação Mínima")*50%)-(SUMIFS(BD_Eventos_Novo!$J:$J,BD_Eventos_Novo!$AB:$AB,DRE!H$4,BD_Eventos_Novo!$G:$G,"Comanda Aberta / Couvert Antecipado")*50%)-(SUMIFS(BD_Eventos_Novo!$K:$K,BD_Eventos_Novo!$AB:$AB,DRE!H$4,BD_Eventos_Novo!$G:$G,"Comanda Aberta / Couvert Antecipado")*50%)+SUMIFS(Aut_Ajustes_Manuais!$G:$G,Aut_Ajustes_Manuais!$I:$I,DRE!H$4,Aut_Ajustes_Manuais!$F:$F,"Bebida") -> 184339 | K10: 138871.7 | L10: 148610.83 | M10: =SUMIFS(Aut_Faturamento_Zig!$F:$F,Aut_Faturamento_Zig!$E:$E,"Bebidas",Aut_Faturamento_Zig!$D:$D,DRE!K$4)-SUMIFS(Aut_Promocoes_Utilizadas!$G:$G,Aut_Promocoes_Utilizadas!$J:$J,DRE!K$4,Aut_Promocoes_Utilizadas!$H:$H,"B",Aut_Promocoes_Utilizadas!$I:$I,"Eventos")-SUMIFS(Aut_Descontos!$J:$J,Aut_Descontos!$L:$L,DRE!K$4)-(SUMIFS(BD_Eventos_Novo!$J:$J,BD_Eventos_Novo!$AB:$AB,DRE!K$4,BD_Eventos_Novo!$G:$G,"Consumação Mínima")*50%)-(SUMIFS(BD_Eventos_Novo!$K:$K,BD_Eventos_Novo!$AB:$AB,DRE!K$4,BD_Eventos_Novo!$G:$G,"Consumação Mínima")*50%)-(SUMIFS(BD_Eventos_Novo!$J:$J,BD_Eventos_Novo!$AB:$AB,DRE!K$4,BD_Eventos_Novo!$G:$G,"Comanda Aberta / Couvert Antecipado")*50%)-(SUMIFS(BD_Eventos_Novo!$K:$K,BD_Eventos_Novo!$AB:$AB,DRE!K$4,BD_Eventos_Novo!$G:$G,"Comanda Aberta / Couvert Antecipado")*50%)+SUMIFS(Aut_Ajustes_Manuais!$G:$G,Aut_Ajustes_Manuais!$I:$I,DRE!K$4,Aut_Ajustes_Manuais!$F:$F,"Bebida") -> 150466.3 | N10: 138641.5 | O10: 119223.03 | P10: =SUMIFS(Aut_Faturamento_Zig!$F:$F,Aut_Faturamento_Zig!$E:$E,"Bebidas",Aut_Faturamento_Zig!$D:$D,DRE!N$4)-SUMIFS(Aut_Promocoes_Utilizadas!$G:$G,Aut_Promocoes_Utilizadas!$J:$J,DRE!N$4,Aut_Promocoes_Utilizadas!$H:$H,"B",Aut_Promocoes_Utilizadas!$I:$I,"Eventos")-SUMIFS(Aut_Descontos!$J:$J,Aut_Descontos!$L:$L,DRE!N$4)-(SUMIFS(BD_Eventos_Novo!$J:$J,BD_Eventos_Novo!$AB:$AB,DRE!N$4,BD_Eventos_Novo!$G:$G,"Consumação Mínima")*50%)-(SUMIFS(BD_Eventos_Novo!$K:$K,BD_Eventos_Novo!$AB:$AB,DRE!N$4,BD_Eventos_Novo!$G:$G,"Consumação Mínima")*50%)-(SUMIFS(BD_Eventos_Novo!$J:$J,BD_Eventos_Novo!$AB:$AB,DRE!N$4,BD_Eventos_Novo!$G:$G,"Comanda Aberta / Couvert Antecipado")*50%)-(SUMIFS(BD_Eventos_Novo!$K:$K,BD_Eventos_Novo!$AB:$AB,DRE!N$4,BD_Eventos_Novo!$G:$G,"Comanda Aberta / Couvert Antecipado")*50%)+SUMIFS(Aut_Ajustes_Manuais!$G:$G,Aut_Ajustes_Manuais!$I:$I,DRE!N$4,Aut_Ajustes_Manuais!$F:$F,"Bebida") -> 155776.2 | Q10: 144963.8 | R10: 124073.74 | S10: =SUMIFS(Aut_Faturamento_Zig!$F:$F,Aut_Faturamento_Zig!$E:$E,"Bebidas",Aut_Faturamento_Zig!$D:$D,DRE!Q$4)-SUMIFS(Aut_Promocoes_Utilizadas!$G:$G,Aut_Promocoes_Utilizadas!$J:$J,DRE!Q$4,Aut_Promocoes_Utilizadas!$H:$H,"B",Aut_Promocoes_Utilizadas!$I:$I,"Eventos")-SUMIFS(Aut_Descontos!$J:$J,Aut_Descontos!$L:$L,DRE!Q$4)-(SUMIFS(BD_Eventos_Novo!$J:$J,BD_Eventos_Novo!$AB:$AB,DRE!Q$4,BD_Eventos_Novo!$G:$G,"Consumação Mínima")*50%)-(SUMIFS(BD_Eventos_Novo!$K:$K,BD_Eventos_Novo!$AB:$AB,DRE!Q$4,BD_Eventos_Novo!$G:$G,"Consumação Mínima")*50%)-(SUMIFS(BD_Eventos_Novo!$J:$J,BD_Eventos_Novo!$AB:$AB,DRE!Q$4,BD_Eventos_Novo!$G:$G,"Comanda Aberta / Couvert Antecipado")*50%)-(SUMIFS(BD_Eventos_Novo!$K:$K,BD_Eventos_Novo!$AB:$AB,DRE!Q$4,BD_Eventos_Novo!$G:$G,"Comanda Aberta / Couvert Antecipado")*50%)+SUMIFS(Aut_Ajustes_Manuais!$G:$G,Aut_Ajustes_Manuais!$I:$I,DRE!Q$4,Aut_Ajustes_Manuais!$F:$F,"Bebida") -> 175366.7 | T10: 196200.7 | U10: 202414.66 | V10: =SUMIFS(Aut_Faturamento_Zig!$F:$F,Aut_Faturamento_Zig!$E:$E,"Bebidas",Aut_Faturamento_Zig!$D:$D,DRE!T$4)-SUMIFS(Aut_Promocoes_Utilizadas!$G:$G,Aut_Promocoes_Utilizadas!$J:$J,DRE!T$4,Aut_Promocoes_Utilizadas!$H:$H,"B",Aut_Promocoes_Utilizadas!$I:$I,"Eventos")-SUMIFS(Aut_Descontos!$J:$J,Aut_Descontos!$L:$L,DRE!T$4)-(SUMIFS(BD_Eventos_Novo!$J:$J,BD_Eventos_Novo!$AB:$AB,DRE!T$4,BD_Eventos_Novo!$G:$G,"Consumação Mínima")*50%)-(SUMIFS(BD_Eventos_Novo!$K:$K,BD_Eventos_Novo!$AB:$AB,DRE!T$4,BD_Eventos_Novo!$G:$G,"Consumação Mínima")*50%)-(SUMIFS(BD_Eventos_Novo!$J:$J,BD_Eventos_Novo!$AB:$AB,DRE!T$4,BD_Eventos_Novo!$G:$G,"Comanda Aberta / Couvert Antecipado")*50%)-(SUMIFS(BD_Eventos_Novo!$K:$K,BD_Eventos_Novo!$AB:$AB,DRE!T$4,BD_Eventos_Novo!$G:$G,"Comanda Aberta / Couvert Antecipado")*50%)+SUMIFS(Aut_Ajustes_Manuais!$G:$G,Aut_Ajustes_Manuais!$I:$I,DRE!T$4,Aut_Ajustes_Manuais!$F:$F,"Bebida") -> 170771.1 | W10: 150109.1 | X10: 180459.04 | Y10: =SUMIFS(Aut_Faturamento_Zig!$F:$F,Aut_Faturamento_Zig!$E:$E,"Bebidas",Aut_Faturamento_Zig!$D:$D,DRE!W$4)-SUMIFS(Aut_Promocoes_Utilizadas!$G:$G,Aut_Promocoes_Utilizadas!$J:$J,DRE!W$4,Aut_Promocoes_Utilizadas!$H:$H,"B",Aut_Promocoes_Utilizadas!$I:$I,"Eventos")-SUMIFS(Aut_Descontos!$J:$J,Aut_Descontos!$L:$L,DRE!W$4)-(SUMIFS(BD_Eventos_Novo!$J:$J,BD_Eventos_Novo!$AB:$AB,DRE!W$4,BD_Eventos_Novo!$G:$G,"Consumação Mínima")*50%)-(SUMIFS(BD_Eventos_Novo!$K:$K,BD_Eventos_Novo!$AB:$AB,DRE!W$4,BD_Eventos_Novo!$G:$G,"Consumação Mínima")*50%)-(SUMIFS(BD_Eventos_Novo!$J:$J,BD_Eventos_Novo!$AB:$AB,DRE!W$4,BD_Eventos_Novo!$G:$G,"Comanda Aberta / Couvert Antecipado")*50%)-(SUMIFS(BD_Eventos_Novo!$K:$K,BD_Eventos_Novo!$AB:$AB,DRE!W$4,BD_Eventos_Novo!$G:$G,"Comanda Aberta / Couvert Antecipado")*50%)+SUMIFS(Aut_Ajustes_Manuais!$G:$G,Aut_Ajustes_Manuais!$I:$I,DRE!W$4,Aut_Ajustes_Manuais!$F:$F,"Bebida") -> 166426.7 | Z10: 152662.1 | AA10: 178747.84 | AB10: =SUMIFS(Aut_Faturamento_Zig!$F:$F,Aut_Faturamento_Zig!$E:$E,"Bebidas",Aut_Faturamento_Zig!$D:$D,DRE!Z$4)-SUMIFS(Aut_Promocoes_Utilizadas!$G:$G,Aut_Promocoes_Utilizadas!$J:$J,DRE!Z$4,Aut_Promocoes_Utilizadas!$H:$H,"B",Aut_Promocoes_Utilizadas!$I:$I,"Eventos")-SUMIFS(Aut_Descontos!$J:$J,Aut_Descontos!$L:$L,DRE!Z$4)-(SUMIFS(BD_Eventos_Novo!$J:$J,BD_Eventos_Novo!$AB:$AB,DRE!Z$4,BD_Eventos_Novo!$G:$G,"Consumação Mínima")*50%)-(SUMIFS(BD_Eventos_Novo!$K:$K,BD_Eventos_Novo!$AB:$AB,DRE!Z$4,BD_Eventos_Novo!$G:$G,"Consumação Mínima")*50%)-(SUMIFS(BD_Eventos_Novo!$J:$J,BD_Eventos_Novo!$AB:$AB,DRE!Z$4,BD_Eventos_Novo!$G:$G,"Comanda Aberta / Couvert Antecipado")*50%)-(SUMIFS(BD_Eventos_Novo!$K:$K,BD_Eventos_Novo!$AB:$AB,DRE!Z$4,BD_Eventos_Novo!$G:$G,"Comanda Aberta / Couvert Antecipado")*50%)+SUMIFS(Aut_Ajustes_Manuais!$G:$G,Aut_Ajustes_Manuais!$I:$I,DRE!Z$4,Aut_Ajustes_Manuais!$F:$F,"Bebida") -> 36787.4 | AC10: 194325.2 | AD10: 192906.39 | AE10: =SUMIFS(Aut_Faturamento_Zig!$F:$F,Aut_Faturamento_Zig!$E:$E,"Bebidas",Aut_Faturamento_Zig!$D:$D,DRE!AC$4)-SUMIFS(Aut_Promocoes_Utilizadas!$G:$G,Aut_Promocoes_Utilizadas!$J:$J,DRE!AC$4,Aut_Promocoes_Utilizadas!$H:$H,"B",Aut_Promocoes_Utilizadas!$I:$I,"Eventos")-SUMIFS(Aut_Descontos!$J:$J,Aut_Descontos!$L:$L,DRE!AC$4)-(SUMIFS(BD_Eventos_Novo!$J:$J,BD_Eventos_Novo!$AB:$AB,DRE!AC$4,BD_Eventos_Novo!$G:$G,"Consumação Mínima")*50%)-(SUMIFS(BD_Eventos_Novo!$K:$K,BD_Eventos_Novo!$AB:$AB,DRE!AC$4,BD_Eventos_Novo!$G:$G,"Consumação Mínima")*50%)-(SUMIFS(BD_Eventos_Novo!$J:$J,BD_Eventos_Novo!$AB:$AB,DRE!AC$4,BD_Eventos_Novo!$G:$G,"Comanda Aberta / Couvert Antecipado")*50%)-(SUMIFS(BD_Eventos_Novo!$K:$K,BD_Eventos_Novo!$AB:$AB,DRE!AC$4,BD_Eventos_Novo!$G:$G,"Comanda Aberta / Couvert Antecipado")*50%)+SUMIFS(Aut_Ajustes_Manuais!$G:$G,Aut_Ajustes_Manuais!$I:$I,DRE!AC$4,Aut_Ajustes_Manuais!$F:$F,"Bebida") -> 0 | AF10: 159277.5 | AG10: 168090.24 | AH10: =SUMIFS(Aut_Faturamento_Zig!$F:$F,Aut_Faturamento_Zig!$E:$E,"Bebidas",Aut_Faturamento_Zig!$D:$D,DRE!AF$4)-SUMIFS(Aut_Promocoes_Utilizadas!$G:$G,Aut_Promocoes_Utilizadas!$J:$J,DRE!AF$4,Aut_Promocoes_Utilizadas!$H:$H,"B",Aut_Promocoes_Utilizadas!$I:$I,"Eventos")-SUMIFS(Aut_Descontos!$J:$J,Aut_Descontos!$L:$L,DRE!AF$4)-(SUMIFS(BD_Eventos_Novo!$J:$J,BD_Eventos_Novo!$AB:$AB,DRE!AF$4,BD_Eventos_Novo!$G:$G,"Consumação Mínima")*50%)-(SUMIFS(BD_Eventos_Novo!$K:$K,BD_Eventos_Novo!$AB:$AB,DRE!AF$4,BD_Eventos_Novo!$G:$G,"Consumação Mínima")*50%)-(SUMIFS(BD_Eventos_Novo!$J:$J,BD_Eventos_Novo!$AB:$AB,DRE!AF$4,BD_Eventos_Novo!$G:$G,"Comanda Aberta / Couvert Antecipado")*50%)-(SUMIFS(BD_Eventos_Novo!$K:$K,BD_Eventos_Novo!$AB:$AB,DRE!AF$4,BD_Eventos_Novo!$G:$G,"Comanda Aberta / Couvert Antecipado")*50%)+SUMIFS(Aut_Ajustes_Manuais!$G:$G,Aut_Ajustes_Manuais!$I:$I,DRE!AF$4,Aut_Ajustes_Manuais!$F:$F,"Bebida") -> 0 | AI10: 165615.5 | AJ10: 169150.54 | AK10: =SUMIFS(Aut_Faturamento_Zig!$F:$F,Aut_Faturamento_Zig!$E:$E,"Bebidas",Aut_Faturamento_Zig!$D:$D,DRE!AI$4)-SUMIFS(Aut_Promocoes_Utilizadas!$G:$G,Aut_Promocoes_Utilizadas!$J:$J,DRE!AI$4,Aut_Promocoes_Utilizadas!$H:$H,"B",Aut_Promocoes_Utilizadas!$I:$I,"Eventos")-SUMIFS(Aut_Descontos!$J:$J,Aut_Descontos!$L:$L,DRE!AI$4)-(SUMIFS(BD_Eventos_Novo!$J:$J,BD_Eventos_Novo!$AB:$AB,DRE!AI$4,BD_Eventos_Novo!$G:$G,"Consumação Mínima")*50%)-(SUMIFS(BD_Eventos_Novo!$K:$K,BD_Eventos_Novo!$AB:$AB,DRE!AI$4,BD_Eventos_Novo!$G:$G,"Consumação Mínima")*50%)-(SUMIFS(BD_Eventos_Novo!$J:$J,BD_Eventos_Novo!$AB:$AB,DRE!AI$4,BD_Eventos_Novo!$G:$G,"Comanda Aberta / Couvert Antecipado")*50%)-(SUMIFS(BD_Eventos_Novo!$K:$K,BD_Eventos_Novo!$AB:$AB,DRE!AI$4,BD_Eventos_Novo!$G:$G,"Comanda Aberta / Couvert Antecipado")*50%)+SUMIFS(Aut_Ajustes_Manuais!$G:$G,Aut_Ajustes_Manuais!$I:$I,DRE!AI$4,Aut_Ajustes_Manuais!$F:$F,"Bebida") -> 0 | AL10: 212155.5 | AM10: 196298 | AN10: =SUMIFS(Aut_Faturamento_Zig!$F:$F,Aut_Faturamento_Zig!$E:$E,"Bebidas",Aut_Faturamento_Zig!$D:$D,DRE!AL$4)-SUMIFS(Aut_Promocoes_Utilizadas!$G:$G,Aut_Promocoes_Utilizadas!$J:$J,DRE!AL$4,Aut_Promocoes_Utilizadas!$H:$H,"B",Aut_Promocoes_Utilizadas!$I:$I,"Eventos")-SUMIFS(Aut_Descontos!$J:$J,Aut_Descontos!$L:$L,DRE!AL$4)-(SUMIFS(BD_Eventos_Novo!$J:$J,BD_Eventos_Novo!$AB:$AB,DRE!AL$4,BD_Eventos_Novo!$G:$G,"Consumação Mínima")*50%)-(SUMIFS(BD_Eventos_Novo!$K:$K,BD_Eventos_Novo!$AB:$AB,DRE!AL$4,BD_Eventos_Novo!$G:$G,"Consumação Mínima")*50%)-(SUMIFS(BD_Eventos_Novo!$J:$J,BD_Eventos_Novo!$AB:$AB,DRE!AL$4,BD_Eventos_Novo!$G:$G,"Comanda Aberta / Couvert Antecipado")*50%)-(SUMIFS(BD_Eventos_Novo!$K:$K,BD_Eventos_Novo!$AB:$AB,DRE!AL$4,BD_Eventos_Novo!$G:$G,"Comanda Aberta / Couvert Antecipado")*50%)+SUMIFS(Aut_Ajustes_Manuais!$G:$G,Aut_Ajustes_Manuais!$I:$I,DRE!AL$4,Aut_Ajustes_Manuais!$F:$F,"Bebida") -> 0 | AO10: 238922.8 | AP10: 177671.95 | AQ10: =SUMIFS(Aut_Faturamento_Zig!$F:$F,Aut_Faturamento_Zig!$E:$E,"Bebidas",Aut_Faturamento_Zig!$D:$D,DRE!AO$4)-SUMIFS(Aut_Promocoes_Utilizadas!$G:$G,Aut_Promocoes_Utilizadas!$J:$J,DRE!AO$4,Aut_Promocoes_Utilizadas!$H:$H,"B",Aut_Promocoes_Utilizadas!$I:$I,"Eventos")-SUMIFS(Aut_Descontos!$J:$J,Aut_Descontos!$L:$L,DRE!AO$4)-(SUMIFS(BD_Eventos_Novo!$J:$J,BD_Eventos_Novo!$AB:$AB,DRE!AO$4,BD_Eventos_Novo!$G:$G,"Consumação Mínima")*50%)-(SUMIFS(BD_Eventos_Novo!$K:$K,BD_Eventos_Novo!$AB:$AB,DRE!AO$4,BD_Eventos_Novo!$G:$G,"Consumação Mínima")*50%)-(SUMIFS(BD_Eventos_Novo!$J:$J,BD_Eventos_Novo!$AB:$AB,DRE!AO$4,BD_Eventos_Novo!$G:$G,"Comanda Aberta / Couvert Antecipado")*50%)-(SUMIFS(BD_Eventos_Novo!$K:$K,BD_Eventos_Novo!$AB:$AB,DRE!AO$4,BD_Eventos_Novo!$G:$G,"Comanda Aberta / Couvert Antecipado")*50%)+SUMIFS(Aut_Ajustes_Manuais!$G:$G,Aut_Ajustes_Manuais!$I:$I,DRE!AO$4,Aut_Ajustes_Manuais!$F:$F,"Bebida") -> 0 | AR10: =SUMIFS($H10:$AO10,$H$5:$AO$5,"<"&MONTH(TODAY()),$H$6:$AO$6,"REAL 25") -> 924625.5 | AS10: =SUMIFS($I10:$AP10,$I$5:$AP$5,"<"&MONTH(TODAY()),$I$6:$AP$6,"ORÇADO ") -> 931414.55 | AT10: =SUMIFS($J10:$AQ10,$J$5:$AQ$5,"<"&MONTH(TODAY()),$J$6:$AQ$6,"REAL 26") -> 1003146 | AU10: =SUM(H10,K10,N10,Q10,T10,W10,Z10,AC10,AF10,AI10,AL10,AO10) -> 2047584.1 | AV10: =SUM(I10,L10,O10,R10,U10,X10,AA10,AD10,AG10,AJ10,AM10,AP10) -> 2014279.5 | AW10: =SUM(J10,M10,P10,S10,V10,Y10,AB10,AE10,AH10,AK10,AN10,AQ10) -> 1039933.4 | AX10: =SUM(H10,K10,N10) -> 433351.9 | AY10: =SUM(I10,L10,O10) -> 424467.11 | AZ10: =SUM(J10,M10,P10) -> 490581.5 | BA10: =SUM(Q10,T10,W10) -> 491273.6 | BB10: =SUM(R10,U10,X10) -> 506947.45 | BC10: =SUM(S10,V10,Y10) -> 512564.5 | BD10: =SUM(Z10,AC10,AF10) -> 506264.8 | BE10: =SUM(AA10,AD10,AG10) -> 539744.47 | BF10: =SUM(AB10,AE10,AH10) -> 36787.4 | BG10: =SUM(AI10,AL10,AO10) -> 616693.8 | BH10: =SUM(AJ10,AM10,AP10) -> 543120.49 | BI10: =SUM(AK10,AN10,AQ10) -> 0 | BK10: =SUM(I10,L10,O10,R10,U10,X10,AA10,AD10,AG10,AJ10,AM10,AP10) -> 2014279.5 | BL10: =BK10-AV10 -> 0 | BM10: =SUM(J10,M10,P10,S10,V10) -> 836719.3 | BN10: =BM10-AT10 -> -166426.7
A11: Artístico (couvert/shows) | C11: Estim. Mensal | D11: Preencher base de Faturamento A&B&C | H11: 0 | I11: 46784.293 | J11: =SUMIFS(Aut_Faturamento_Zig!$F:$F,Aut_Faturamento_Zig!$E:$E,"Couvert",Aut_Faturamento_Zig!$D:$D,DRE!H$4)+SUMIFS(Aut_Ajustes_Manuais!$G:$G,Aut_Ajustes_Manuais!$I:$I,DRE!H$4,Aut_Ajustes_Manuais!$F:$F,"Artístico (couvert/shows)") -> 2490 | K11: 0 | L11: 44388.103 | M11: =SUMIFS(Aut_Faturamento_Zig!$F:$F,Aut_Faturamento_Zig!$E:$E,"Couvert",Aut_Faturamento_Zig!$D:$D,DRE!K$4)+SUMIFS(Aut_Ajustes_Manuais!$G:$G,Aut_Ajustes_Manuais!$I:$I,DRE!K$4,Aut_Ajustes_Manuais!$F:$F,"Artístico (couvert/shows)") -> 1365 | N11: 900 | O11: 35610.354 | P11: =SUMIFS(Aut_Faturamento_Zig!$F:$F,Aut_Faturamento_Zig!$E:$E,"Couvert",Aut_Faturamento_Zig!$D:$D,DRE!N$4)+SUMIFS(Aut_Ajustes_Manuais!$G:$G,Aut_Ajustes_Manuais!$I:$I,DRE!N$4,Aut_Ajustes_Manuais!$F:$F,"Artístico (couvert/shows)") -> 1995 | Q11: 1215 | R11: 37059.197 | S11: =SUMIFS(Aut_Faturamento_Zig!$F:$F,Aut_Faturamento_Zig!$E:$E,"Couvert",Aut_Faturamento_Zig!$D:$D,DRE!Q$4)+SUMIFS(Aut_Ajustes_Manuais!$G:$G,Aut_Ajustes_Manuais!$I:$I,DRE!Q$4,Aut_Ajustes_Manuais!$F:$F,"Artístico (couvert/shows)") -> 1290 | T11: 1620 | U11: 60458.601 | V11: =SUMIFS(Aut_Faturamento_Zig!$F:$F,Aut_Faturamento_Zig!$E:$E,"Couvert",Aut_Faturamento_Zig!$D:$D,DRE!T$4)+SUMIFS(Aut_Ajustes_Manuais!$G:$G,Aut_Ajustes_Manuais!$I:$I,DRE!T$4,Aut_Ajustes_Manuais!$F:$F,"Artístico (couvert/shows)") -> 2655 | W11: 225 | X11: 53900.746 | Y11: =SUMIFS(Aut_Faturamento_Zig!$F:$F,Aut_Faturamento_Zig!$E:$E,"Couvert",Aut_Faturamento_Zig!$D:$D,DRE!W$4)+SUMIFS(Aut_Ajustes_Manuais!$G:$G,Aut_Ajustes_Manuais!$I:$I,DRE!W$4,Aut_Ajustes_Manuais!$F:$F,"Artístico (couvert/shows)") -> 1440 | Z11: 0 | AA11: 53389.631 | AB11: =SUMIFS(Aut_Faturamento_Zig!$F:$F,Aut_Faturamento_Zig!$E:$E,"Couvert",Aut_Faturamento_Zig!$D:$D,DRE!Z$4)+SUMIFS(Aut_Ajustes_Manuais!$G:$G,Aut_Ajustes_Manuais!$I:$I,DRE!Z$4,Aut_Ajustes_Manuais!$F:$F,"Artístico (couvert/shows)") -> 480 | AC11: 1890 | AD11: 57618.606 | AE11: =SUMIFS(Aut_Faturamento_Zig!$F:$F,Aut_Faturamento_Zig!$E:$E,"Couvert",Aut_Faturamento_Zig!$D:$D,DRE!AC$4)+SUMIFS(Aut_Ajustes_Manuais!$G:$G,Aut_Ajustes_Manuais!$I:$I,DRE!AC$4,Aut_Ajustes_Manuais!$F:$F,"Artístico (couvert/shows)") -> 0 | AF11: 1815 | AG11: 50206.346 | AH11: =SUMIFS(Aut_Faturamento_Zig!$F:$F,Aut_Faturamento_Zig!$E:$E,"Couvert",Aut_Faturamento_Zig!$D:$D,DRE!AF$4)+SUMIFS(Aut_Ajustes_Manuais!$G:$G,Aut_Ajustes_Manuais!$I:$I,DRE!AF$4,Aut_Ajustes_Manuais!$F:$F,"Artístico (couvert/shows)") -> 0 | AI11: 2055 | AJ11: 50523.046 | AK11: =SUMIFS(Aut_Faturamento_Zig!$F:$F,Aut_Faturamento_Zig!$E:$E,"Couvert",Aut_Faturamento_Zig!$D:$D,DRE!AI$4)+SUMIFS(Aut_Ajustes_Manuais!$G:$G,Aut_Ajustes_Manuais!$I:$I,DRE!AI$4,Aut_Ajustes_Manuais!$F:$F,"Artístico (couvert/shows)") -> 0 | AL11: 2400 | AM11: 58631.633 | AN11: =SUMIFS(Aut_Faturamento_Zig!$F:$F,Aut_Faturamento_Zig!$E:$E,"Couvert",Aut_Faturamento_Zig!$D:$D,DRE!AL$4)+SUMIFS(Aut_Ajustes_Manuais!$G:$G,Aut_Ajustes_Manuais!$I:$I,DRE!AL$4,Aut_Ajustes_Manuais!$F:$F,"Artístico (couvert/shows)") -> 0 | AO11: 1245 | AP11: 53068.278 | AQ11: =SUMIFS(Aut_Faturamento_Zig!$F:$F,Aut_Faturamento_Zig!$E:$E,"Couvert",Aut_Faturamento_Zig!$D:$D,DRE!AO$4)+SUMIFS(Aut_Ajustes_Manuais!$G:$G,Aut_Ajustes_Manuais!$I:$I,DRE!AO$4,Aut_Ajustes_Manuais!$F:$F,"Artístico (couvert/shows)") -> 0 | AR11: =SUMIFS($H11:$AO11,$H$5:$AO$5,"<"&MONTH(TODAY()),$H$6:$AO$6,"REAL 25") -> 3960 | AS11: =SUMIFS($I11:$AP11,$I$5:$AP$5,"<"&MONTH(TODAY()),$I$6:$AP$6,"ORÇADO ") -> 278201.29 | AT11: =SUMIFS($J11:$AQ11,$J$5:$AQ$5,"<"&MONTH(TODAY()),$J$6:$AQ$6,"REAL 26") -> 11235 | AU11: =SUM(H11,K11,N11,Q11,T11,W11,Z11,AC11,AF11,AI11,AL11,AO11) -> 13365 | AV11: =SUM(I11,L11,O11,R11,U11,X11,AA11,AD11,AG11,AJ11,AM11,AP11) -> 601638.83 | AW11: =SUM(J11,M11,P11,S11,V11,Y11,AB11,AE11,AH11,AK11,AN11,AQ11) -> 11715 | AX11: =SUM(H11,K11,N11) -> 900 | AY11: =SUM(I11,L11,O11) -> 126782.75 | AZ11: =SUM(J11,M11,P11) -> 5850 | BA11: =SUM(Q11,T11,W11) -> 3060 | BB11: =SUM(R11,U11,X11) -> 151418.54 | BC11: =SUM(S11,V11,Y11) -> 5385 | BD11: =SUM(Z11,AC11,AF11) -> 3705 | BE11: =SUM(AA11,AD11,AG11) -> 161214.58 | BF11: =SUM(AB11,AE11,AH11) -> 480 | BG11: =SUM(AI11,AL11,AO11) -> 5700 | BH11: =SUM(AJ11,AM11,AP11) -> 162222.96 | BI11: =SUM(AK11,AN11,AQ11) -> 0 | BK11: =SUM(I11,L11,O11,R11,U11,X11,AA11,AD11,AG11,AJ11,AM11,AP11) -> 601638.83 | BL11: =BK11-AV11 -> 0 | BM11: =SUM(J11,M11,P11,S11,V11) -> 9795 | BN11: =BM11-AT11 -> -1440
A12: Gifts | C12: Estim. Mensal | D12: Vendas Lojinha | H12: 1780 | I12: 1958.189 | J12: =SUMIFS(Aut_Faturamento_Zig!$F:$F,Aut_Faturamento_Zig!$E:$E,"Gifts",Aut_Faturamento_Zig!$D:$D,DRE!H$4)+SUMIFS(Aut_Ajustes_Manuais!$G:$G,Aut_Ajustes_Manuais!$I:$I,DRE!H$4,Aut_Ajustes_Manuais!$F:$F,"Gifts") -> 4042 | K12: 1725 | L12: 1857.8948 | M12: =SUMIFS(Aut_Faturamento_Zig!$F:$F,Aut_Faturamento_Zig!$E:$E,"Gifts",Aut_Faturamento_Zig!$D:$D,DRE!K$4)+SUMIFS(Aut_Ajustes_Manuais!$G:$G,Aut_Ajustes_Manuais!$I:$I,DRE!K$4,Aut_Ajustes_Manuais!$F:$F,"Gifts") -> 2212 | N12: 1544 | O12: 1490.496 | P12: =SUMIFS(Aut_Faturamento_Zig!$F:$F,Aut_Faturamento_Zig!$E:$E,"Gifts",Aut_Faturamento_Zig!$D:$D,DRE!N$4)+SUMIFS(Aut_Ajustes_Manuais!$G:$G,Aut_Ajustes_Manuais!$I:$I,DRE!N$4,Aut_Ajustes_Manuais!$F:$F,"Gifts") -> 3551 | Q12: 1607 | R12: 1551.1383 | S12: =SUMIFS(Aut_Faturamento_Zig!$F:$F,Aut_Faturamento_Zig!$E:$E,"Gifts",Aut_Faturamento_Zig!$D:$D,DRE!Q$4)+SUMIFS(Aut_Ajustes_Manuais!$G:$G,Aut_Ajustes_Manuais!$I:$I,DRE!Q$4,Aut_Ajustes_Manuais!$F:$F,"Gifts") -> 1721 | T12: 2472 | U12: 2530.5366 | V12: =SUMIFS(Aut_Faturamento_Zig!$F:$F,Aut_Faturamento_Zig!$E:$E,"Gifts",Aut_Faturamento_Zig!$D:$D,DRE!T$4)+SUMIFS(Aut_Ajustes_Manuais!$G:$G,Aut_Ajustes_Manuais!$I:$I,DRE!T$4,Aut_Ajustes_Manuais!$F:$F,"Gifts") -> 1350 | W12: 1478 | X12: 2256.053 | Y12: =SUMIFS(Aut_Faturamento_Zig!$F:$F,Aut_Faturamento_Zig!$E:$E,"Gifts",Aut_Faturamento_Zig!$D:$D,DRE!W$4)+SUMIFS(Aut_Ajustes_Manuais!$G:$G,Aut_Ajustes_Manuais!$I:$I,DRE!W$4,Aut_Ajustes_Manuais!$F:$F,"Gifts") -> 937 | Z12: 1644 | AA12: 2234.66 | AB12: =SUMIFS(Aut_Faturamento_Zig!$F:$F,Aut_Faturamento_Zig!$E:$E,"Gifts",Aut_Faturamento_Zig!$D:$D,DRE!Z$4)+SUMIFS(Aut_Ajustes_Manuais!$G:$G,Aut_Ajustes_Manuais!$I:$I,DRE!Z$4,Aut_Ajustes_Manuais!$F:$F,"Gifts") -> 48 | AC12: 1691 | AD12: 2411.6666 | AE12: =SUMIFS(Aut_Faturamento_Zig!$F:$F,Aut_Faturamento_Zig!$E:$E,"Gifts",Aut_Faturamento_Zig!$D:$D,DRE!AC$4)+SUMIFS(Aut_Ajustes_Manuais!$G:$G,Aut_Ajustes_Manuais!$I:$I,DRE!AC$4,Aut_Ajustes_Manuais!$F:$F,"Gifts") -> 0 | AF12: 1649 | AG12: 2101.4214 | AH12: =SUMIFS(Aut_Faturamento_Zig!$F:$F,Aut_Faturamento_Zig!$E:$E,"Gifts",Aut_Faturamento_Zig!$D:$D,DRE!AF$4)+SUMIFS(Aut_Ajustes_Manuais!$G:$G,Aut_Ajustes_Manuais!$I:$I,DRE!AF$4,Aut_Ajustes_Manuais!$F:$F,"Gifts") -> 0 | AI12: 1802 | AJ12: 2114.6771 | AK12: =SUMIFS(Aut_Faturamento_Zig!$F:$F,Aut_Faturamento_Zig!$E:$E,"Gifts",Aut_Faturamento_Zig!$D:$D,DRE!AI$4)+SUMIFS(Aut_Ajustes_Manuais!$G:$G,Aut_Ajustes_Manuais!$I:$I,DRE!AI$4,Aut_Ajustes_Manuais!$F:$F,"Gifts") -> 0 | AL12: 4696 | AM12: 2454.0676 | AN12: =SUMIFS(Aut_Faturamento_Zig!$F:$F,Aut_Faturamento_Zig!$E:$E,"Gifts",Aut_Faturamento_Zig!$D:$D,DRE!AL$4)+SUMIFS(Aut_Ajustes_Manuais!$G:$G,Aut_Ajustes_Manuais!$I:$I,DRE!AL$4,Aut_Ajustes_Manuais!$F:$F,"Gifts") -> 0 | AO12: 5340 | AP12: 2221.2095 | AQ12: =SUMIFS(Aut_Faturamento_Zig!$F:$F,Aut_Faturamento_Zig!$E:$E,"Gifts",Aut_Faturamento_Zig!$D:$D,DRE!AO$4)+SUMIFS(Aut_Ajustes_Manuais!$G:$G,Aut_Ajustes_Manuais!$I:$I,DRE!AO$4,Aut_Ajustes_Manuais!$F:$F,"Gifts") -> 0 | AR12: =SUMIFS($H12:$AO12,$H$5:$AO$5,"<"&MONTH(TODAY()),$H$6:$AO$6,"REAL 25") -> 10606 | AS12: =SUMIFS($I12:$AP12,$I$5:$AP$5,"<"&MONTH(TODAY()),$I$6:$AP$6,"ORÇADO ") -> 11644.308 | AT12: =SUMIFS($J12:$AQ12,$J$5:$AQ$5,"<"&MONTH(TODAY()),$J$6:$AQ$6,"REAL 26") -> 13813 | AU12: =SUM(H12,K12,N12,Q12,T12,W12,Z12,AC12,AF12,AI12,AL12,AO12) -> 27428 | AV12: =SUM(I12,L12,O12,R12,U12,X12,AA12,AD12,AG12,AJ12,AM12,AP12) -> 25182.01 | AW12: =SUM(J12,M12,P12,S12,V12,Y12,AB12,AE12,AH12,AK12,AN12,AQ12) -> 13861 | AX12: =SUM(H12,K12,N12) -> 5049 | AY12: =SUM(I12,L12,O12) -> 5306.5798 | AZ12: =SUM(J12,M12,P12) -> 9805 | BA12: =SUM(Q12,T12,W12) -> 5557 | BB12: =SUM(R12,U12,X12) -> 6337.728 | BC12: =SUM(S12,V12,Y12) -> 4008 | BD12: =SUM(Z12,AC12,AF12) -> 4984 | BE12: =SUM(AA12,AD12,AG12) -> 6747.748 | BF12: =SUM(AB12,AE12,AH12) -> 48 | BG12: =SUM(AI12,AL12,AO12) -> 11838 | BH12: =SUM(AJ12,AM12,AP12) -> 6789.9542 | BI12: =SUM(AK12,AN12,AQ12) -> 0 | BK12: =SUM(I12,L12,O12,R12,U12,X12,AA12,AD12,AG12,AJ12,AM12,AP12) -> 25182.01 | BL12: =BK12-AV12 -> 0 | BM12: =SUM(J12,M12,P12,S12,V12) -> 12876 | BN12: =BM12-AT12 -> -937
A13: Serviço | C13: Estim. Mensal | D13: Gorjeta Fórmula | E13: 13% sobre A&B&C | H13: 38256.59 | I13: 38286.93 | J13: =SUMIFS(Aut_Faturamento_Zig!$F:$F,Aut_Faturamento_Zig!$E:$E,"Serviço",Aut_Faturamento_Zig!$D:$D,DRE!H$4)+SUMIFS(Aut_Ajustes_Manuais!$G:$G,Aut_Ajustes_Manuais!$I:$I,DRE!H$4,Aut_Ajustes_Manuais!$F:$F,"Serviço") -> 43508.15 | K13: 34751.18 | L13: 36325.956 | M13: =SUMIFS(Aut_Faturamento_Zig!$F:$F,Aut_Faturamento_Zig!$E:$E,"Serviço",Aut_Faturamento_Zig!$D:$D,DRE!K$4)+SUMIFS(Aut_Ajustes_Manuais!$G:$G,Aut_Ajustes_Manuais!$I:$I,DRE!K$4,Aut_Ajustes_Manuais!$F:$F,"Serviço") -> 35399.38 | N13: 34535.35 | O13: 29142.497 | P13: =SUMIFS(Aut_Faturamento_Zig!$F:$F,Aut_Faturamento_Zig!$E:$E,"Serviço",Aut_Faturamento_Zig!$D:$D,DRE!N$4)+SUMIFS(Aut_Ajustes_Manuais!$G:$G,Aut_Ajustes_Manuais!$I:$I,DRE!N$4,Aut_Ajustes_Manuais!$F:$F,"Serviço") -> 37123.69 | Q13: 36941.19 | R13: 30328.189 | S13: =SUMIFS(Aut_Faturamento_Zig!$F:$F,Aut_Faturamento_Zig!$E:$E,"Serviço",Aut_Faturamento_Zig!$D:$D,DRE!Q$4)+SUMIFS(Aut_Ajustes_Manuais!$G:$G,Aut_Ajustes_Manuais!$I:$I,DRE!Q$4,Aut_Ajustes_Manuais!$F:$F,"Serviço") -> 40637.15 | T13: 48405.33 | U13: 49477.594 | V13: =SUMIFS(Aut_Faturamento_Zig!$F:$F,Aut_Faturamento_Zig!$E:$E,"Serviço",Aut_Faturamento_Zig!$D:$D,DRE!T$4)+SUMIFS(Aut_Ajustes_Manuais!$G:$G,Aut_Ajustes_Manuais!$I:$I,DRE!T$4,Aut_Ajustes_Manuais!$F:$F,"Serviço") -> 41612.77 | W13: 36988.57 | X13: 44110.832 | Y13: =SUMIFS(Aut_Faturamento_Zig!$F:$F,Aut_Faturamento_Zig!$E:$E,"Serviço",Aut_Faturamento_Zig!$D:$D,DRE!W$4)+SUMIFS(Aut_Ajustes_Manuais!$G:$G,Aut_Ajustes_Manuais!$I:$I,DRE!W$4,Aut_Ajustes_Manuais!$F:$F,"Serviço") -> 40068.77 | Z13: 39419.73 | AA13: 43692.55 | AB13: =SUMIFS(Aut_Faturamento_Zig!$F:$F,Aut_Faturamento_Zig!$E:$E,"Serviço",Aut_Faturamento_Zig!$D:$D,DRE!Z$4)+SUMIFS(Aut_Ajustes_Manuais!$G:$G,Aut_Ajustes_Manuais!$I:$I,DRE!Z$4,Aut_Ajustes_Manuais!$F:$F,"Serviço") -> 8709.55 | AC13: 46429.36 | AD13: 47153.423 | AE13: =SUMIFS(Aut_Faturamento_Zig!$F:$F,Aut_Faturamento_Zig!$E:$E,"Serviço",Aut_Faturamento_Zig!$D:$D,DRE!AC$4)+SUMIFS(Aut_Ajustes_Manuais!$G:$G,Aut_Ajustes_Manuais!$I:$I,DRE!AC$4,Aut_Ajustes_Manuais!$F:$F,"Serviço") -> 0 | AF13: 38996.34 | AG13: 41087.441 | AH13: =SUMIFS(Aut_Faturamento_Zig!$F:$F,Aut_Faturamento_Zig!$E:$E,"Serviço",Aut_Faturamento_Zig!$D:$D,DRE!AF$4)+SUMIFS(Aut_Ajustes_Manuais!$G:$G,Aut_Ajustes_Manuais!$I:$I,DRE!AF$4,Aut_Ajustes_Manuais!$F:$F,"Serviço") -> 0 | AI13: 40943.88 | AJ13: 41346.619 | AK13: =SUMIFS(Aut_Faturamento_Zig!$F:$F,Aut_Faturamento_Zig!$E:$E,"Serviço",Aut_Faturamento_Zig!$D:$D,DRE!AI$4)+SUMIFS(Aut_Ajustes_Manuais!$G:$G,Aut_Ajustes_Manuais!$I:$I,DRE!AI$4,Aut_Ajustes_Manuais!$F:$F,"Serviço") -> 0 | AL13: 47415.6 | AM13: 47982.455 | AN13: =SUMIFS(Aut_Faturamento_Zig!$F:$F,Aut_Faturamento_Zig!$E:$E,"Serviço",Aut_Faturamento_Zig!$D:$D,DRE!AL$4)+SUMIFS(Aut_Ajustes_Manuais!$G:$G,Aut_Ajustes_Manuais!$I:$I,DRE!AL$4,Aut_Ajustes_Manuais!$F:$F,"Serviço") -> 0 | AO13: 52286.04 | AP13: 43429.564 | AQ13: =SUMIFS(Aut_Faturamento_Zig!$F:$F,Aut_Faturamento_Zig!$E:$E,"Serviço",Aut_Faturamento_Zig!$D:$D,DRE!AO$4)+SUMIFS(Aut_Ajustes_Manuais!$G:$G,Aut_Ajustes_Manuais!$I:$I,DRE!AO$4,Aut_Ajustes_Manuais!$F:$F,"Serviço") -> 0 | AR13: =SUMIFS($H13:$AO13,$H$5:$AO$5,"<"&MONTH(TODAY()),$H$6:$AO$6,"REAL 25") -> 229878.21 | AS13: =SUMIFS($I13:$AP13,$I$5:$AP$5,"<"&MONTH(TODAY()),$I$6:$AP$6,"ORÇADO ") -> 227672 | AT13: =SUMIFS($J13:$AQ13,$J$5:$AQ$5,"<"&MONTH(TODAY()),$J$6:$AQ$6,"REAL 26") -> 238349.91 | AU13: =SUM(H13,K13,N13,Q13,T13,W13,Z13,AC13,AF13,AI13,AL13,AO13) -> 495369.16 | AV13: =SUM(I13,L13,O13,R13,U13,X13,AA13,AD13,AG13,AJ13,AM13,AP13) -> 492364.05 | AW13: =SUM(J13,M13,P13,S13,V13,Y13,AB13,AE13,AH13,AK13,AN13,AQ13) -> 247059.46 | AX13: =SUM(H13,K13,N13) -> 107543.12 | AY13: =SUM(I13,L13,O13) -> 103755.38 | AZ13: =SUM(J13,M13,P13) -> 116031.22 | BA13: =SUM(Q13,T13,W13) -> 122335.09 | BB13: =SUM(R13,U13,X13) -> 123916.61 | BC13: =SUM(S13,V13,Y13) -> 122318.69 | BD13: =SUM(Z13,AC13,AF13) -> 124845.43 | BE13: =SUM(AA13,AD13,AG13) -> 131933.41 | BF13: =SUM(AB13,AE13,AH13) -> 8709.55 | BG13: =SUM(AI13,AL13,AO13) -> 140645.52 | BH13: =SUM(AJ13,AM13,AP13) -> 132758.64 | BI13: =SUM(AK13,AN13,AQ13) -> 0 | BK13: =SUM(I13,L13,O13,R13,U13,X13,AA13,AD13,AG13,AJ13,AM13,AP13) -> 492364.05 | BL13: =BK13-AV13 -> 0 | BM13: =SUM(J13,M13,P13,S13,V13) -> 198281.14 | BN13: =BM13-AT13 -> -40068.77
A14: Eventos A&B | C14: Estim. Mensal | D14: Preencher base de Eventos | H14: 0 | I14: 8395.8695 | J14: =SUMIFS(BD_Eventos_Novo!$J:$J,BD_Eventos_Novo!$AB:$AB,DRE!H$4)+SUMIFS(BD_Eventos_Novo!$K:$K,BD_Eventos_Novo!$AB:$AB,DRE!H$4)+SUMIFS(Aut_Ajustes_Manuais!$G:$G,Aut_Ajustes_Manuais!$I:$I,DRE!H$4,Aut_Ajustes_Manuais!$F:$F,"Eventos A&B") -> 0 | K14: 0 | L14: 7965.8512 | M14: =SUMIFS(BD_Eventos_Novo!$J:$J,BD_Eventos_Novo!$AB:$AB,DRE!K$4)+SUMIFS(BD_Eventos_Novo!$K:$K,BD_Eventos_Novo!$AB:$AB,DRE!K$4)+SUMIFS(Aut_Ajustes_Manuais!$G:$G,Aut_Ajustes_Manuais!$I:$I,DRE!K$4,Aut_Ajustes_Manuais!$F:$F,"Eventos A&B") -> 0 | N14: 0 | O14: 6390.6039 | P14: =SUMIFS(BD_Eventos_Novo!$J:$J,BD_Eventos_Novo!$AB:$AB,DRE!N$4)+SUMIFS(BD_Eventos_Novo!$K:$K,BD_Eventos_Novo!$AB:$AB,DRE!N$4)+SUMIFS(Aut_Ajustes_Manuais!$G:$G,Aut_Ajustes_Manuais!$I:$I,DRE!N$4,Aut_Ajustes_Manuais!$F:$F,"Eventos A&B") -> 0 | Q14: 0 | R14: 6650.612 | S14: =SUMIFS(BD_Eventos_Novo!$J:$J,BD_Eventos_Novo!$AB:$AB,DRE!Q$4)+SUMIFS(BD_Eventos_Novo!$K:$K,BD_Eventos_Novo!$AB:$AB,DRE!Q$4)+SUMIFS(Aut_Ajustes_Manuais!$G:$G,Aut_Ajustes_Manuais!$I:$I,DRE!Q$4,Aut_Ajustes_Manuais!$F:$F,"Eventos A&B") -> 0 | T14: 0 | U14: 10849.849 | V14: =SUMIFS(BD_Eventos_Novo!$J:$J,BD_Eventos_Novo!$AB:$AB,DRE!T$4)+SUMIFS(BD_Eventos_Novo!$K:$K,BD_Eventos_Novo!$AB:$AB,DRE!T$4)+SUMIFS(Aut_Ajustes_Manuais!$G:$G,Aut_Ajustes_Manuais!$I:$I,DRE!T$4,Aut_Ajustes_Manuais!$F:$F,"Eventos A&B") -> 0 | W14: 0 | X14: 9672.9821 | Y14: =SUMIFS(BD_Eventos_Novo!$J:$J,BD_Eventos_Novo!$AB:$AB,DRE!W$4)+SUMIFS(BD_Eventos_Novo!$K:$K,BD_Eventos_Novo!$AB:$AB,DRE!W$4)+SUMIFS(Aut_Ajustes_Manuais!$G:$G,Aut_Ajustes_Manuais!$I:$I,DRE!W$4,Aut_Ajustes_Manuais!$F:$F,"Eventos A&B") -> 0 | Z14: 0 | AA14: 9581.2578 | AB14: =SUMIFS(BD_Eventos_Novo!$J:$J,BD_Eventos_Novo!$AB:$AB,DRE!Z$4)+SUMIFS(BD_Eventos_Novo!$K:$K,BD_Eventos_Novo!$AB:$AB,DRE!Z$4)+SUMIFS(Aut_Ajustes_Manuais!$G:$G,Aut_Ajustes_Manuais!$I:$I,DRE!Z$4,Aut_Ajustes_Manuais!$F:$F,"Eventos A&B") -> 0 | AC14: 0 | AD14: 10340.186 | AE14: =SUMIFS(BD_Eventos_Novo!$J:$J,BD_Eventos_Novo!$AB:$AB,DRE!AC$4)+SUMIFS(BD_Eventos_Novo!$K:$K,BD_Eventos_Novo!$AB:$AB,DRE!AC$4)+SUMIFS(Aut_Ajustes_Manuais!$G:$G,Aut_Ajustes_Manuais!$I:$I,DRE!AC$4,Aut_Ajustes_Manuais!$F:$F,"Eventos A&B") -> 0 | AF14: 0 | AG14: 9009.9883 | AH14: =SUMIFS(BD_Eventos_Novo!$J:$J,BD_Eventos_Novo!$AB:$AB,DRE!AF$4)+SUMIFS(BD_Eventos_Novo!$K:$K,BD_Eventos_Novo!$AB:$AB,DRE!AF$4)+SUMIFS(Aut_Ajustes_Manuais!$G:$G,Aut_Ajustes_Manuais!$I:$I,DRE!AF$4,Aut_Ajustes_Manuais!$F:$F,"Eventos A&B") -> 0 | AI14: 0 | AJ14: 9066.8229 | AK14: =SUMIFS(BD_Eventos_Novo!$J:$J,BD_Eventos_Novo!$AB:$AB,DRE!AI$4)+SUMIFS(BD_Eventos_Novo!$K:$K,BD_Eventos_Novo!$AB:$AB,DRE!AI$4)+SUMIFS(Aut_Ajustes_Manuais!$G:$G,Aut_Ajustes_Manuais!$I:$I,DRE!AI$4,Aut_Ajustes_Manuais!$F:$F,"Eventos A&B") -> 0 | AL14: 6400 | AM14: 10521.983 | AN14: =SUMIFS(BD_Eventos_Novo!$J:$J,BD_Eventos_Novo!$AB:$AB,DRE!AL$4)+SUMIFS(BD_Eventos_Novo!$K:$K,BD_Eventos_Novo!$AB:$AB,DRE!AL$4)+SUMIFS(Aut_Ajustes_Manuais!$G:$G,Aut_Ajustes_Manuais!$I:$I,DRE!AL$4,Aut_Ajustes_Manuais!$F:$F,"Eventos A&B") -> 0 | AO14: 10500 | AP14: 9523.5882 | AQ14: =SUMIFS(BD_Eventos_Novo!$J:$J,BD_Eventos_Novo!$AB:$AB,DRE!AO$4)+SUMIFS(BD_Eventos_Novo!$K:$K,BD_Eventos_Novo!$AB:$AB,DRE!AO$4)+SUMIFS(Aut_Ajustes_Manuais!$G:$G,Aut_Ajustes_Manuais!$I:$I,DRE!AO$4,Aut_Ajustes_Manuais!$F:$F,"Eventos A&B") -> 0 | AR14: =SUMIFS($H14:$AO14,$H$5:$AO$5,"<"&MONTH(TODAY()),$H$6:$AO$6,"REAL 25") -> 0 | AS14: =SUMIFS($I14:$AP14,$I$5:$AP$5,"<"&MONTH(TODAY()),$I$6:$AP$6,"ORÇADO ") -> 49925.768 | AT14: =SUMIFS($J14:$AQ14,$J$5:$AQ$5,"<"&MONTH(TODAY()),$J$6:$AQ$6,"REAL 26") -> 0 | AU14: =SUM(H14,K14,N14,Q14,T14,W14,Z14,AC14,AF14,AI14,AL14,AO14) -> 16900 | AV14: =SUM(I14,L14,O14,R14,U14,X14,AA14,AD14,AG14,AJ14,AM14,AP14) -> 107969.59 | AW14: =SUM(J14,M14,P14,S14,V14,Y14,AB14,AE14,AH14,AK14,AN14,AQ14) -> 0 | AX14: =SUM(H14,K14,N14) -> 0 | AY14: =SUM(I14,L14,O14) -> 22752.325 | AZ14: =SUM(J14,M14,P14) -> 0 | BA14: =SUM(Q14,T14,W14) -> 0 | BB14: =SUM(R14,U14,X14) -> 27173.443 | BC14: =SUM(S14,V14,Y14) -> 0 | BD14: =SUM(Z14,AC14,AF14) -> 0 | BE14: =SUM(AA14,AD14,AG14) -> 28931.432 | BF14: =SUM(AB14,AE14,AH14) -> 0 | BG14: =SUM(AI14,AL14,AO14) -> 16900 | BH14: =SUM(AJ14,AM14,AP14) -> 29112.394 | BI14: =SUM(AK14,AN14,AQ14) -> 0 | BK14: =SUM(I14,L14,O14,R14,U14,X14,AA14,AD14,AG14,AJ14,AM14,AP14) -> 107969.59 | BL14: =BK14-AV14 -> 0 | BM14: =SUM(J14,M14,P14,S14,V14) -> 0 | BN14: =BM14-AT14 -> 0
A15: Eventos Couvert | C15: Estim. Mensal | D15: Preencher base de Eventos | H15: 0 | I15: 1185.5929 | J15: =SUMIFS(BD_Eventos_Novo!$M:$M,BD_Eventos_Novo!$AB:$AB,DRE!H$4)+SUMIFS(BD_Eventos_Novo!$N:$N,BD_Eventos_Novo!$AB:$AB,DRE!H$4)+SUMIFS(BD_Eventos_Novo!$O:$O,BD_Eventos_Novo!$AB:$AB,DRE!H$4)+SUMIFS(Aut_Ajustes_Manuais!$G:$G,Aut_Ajustes_Manuais!$I:$I,DRE!H$4,Aut_Ajustes_Manuais!$F:$F,"Eventos Couvert") -> 0 | K15: 0 | L15: 1124.8694 | M15: =SUMIFS(BD_Eventos_Novo!$M:$M,BD_Eventos_Novo!$AB:$AB,DRE!K$4)+SUMIFS(BD_Eventos_Novo!$N:$N,BD_Eventos_Novo!$AB:$AB,DRE!K$4)+SUMIFS(BD_Eventos_Novo!$O:$O,BD_Eventos_Novo!$AB:$AB,DRE!K$4)+SUMIFS(Aut_Ajustes_Manuais!$G:$G,Aut_Ajustes_Manuais!$I:$I,DRE!K$4,Aut_Ajustes_Manuais!$F:$F,"Eventos Couvert") -> 0 | N15: 0 | O15: 902.42645 | P15: =SUMIFS(BD_Eventos_Novo!$M:$M,BD_Eventos_Novo!$AB:$AB,DRE!N$4)+SUMIFS(BD_Eventos_Novo!$N:$N,BD_Eventos_Novo!$AB:$AB,DRE!N$4)+SUMIFS(BD_Eventos_Novo!$O:$O,BD_Eventos_Novo!$AB:$AB,DRE!N$4)+SUMIFS(Aut_Ajustes_Manuais!$G:$G,Aut_Ajustes_Manuais!$I:$I,DRE!N$4,Aut_Ajustes_Manuais!$F:$F,"Eventos Couvert") -> 0 | Q15: 0 | R15: 939.14257 | S15: =SUMIFS(BD_Eventos_Novo!$M:$M,BD_Eventos_Novo!$AB:$AB,DRE!Q$4)+SUMIFS(BD_Eventos_Novo!$N:$N,BD_Eventos_Novo!$AB:$AB,DRE!Q$4)+SUMIFS(BD_Eventos_Novo!$O:$O,BD_Eventos_Novo!$AB:$AB,DRE!Q$4)+SUMIFS(Aut_Ajustes_Manuais!$G:$G,Aut_Ajustes_Manuais!$I:$I,DRE!Q$4,Aut_Ajustes_Manuais!$F:$F,"Eventos Couvert") -> 0 | T15: 0 | U15: 1532.123 | V15: =SUMIFS(BD_Eventos_Novo!$M:$M,BD_Eventos_Novo!$AB:$AB,DRE!T$4)+SUMIFS(BD_Eventos_Novo!$N:$N,BD_Eventos_Novo!$AB:$AB,DRE!T$4)+SUMIFS(BD_Eventos_Novo!$O:$O,BD_Eventos_Novo!$AB:$AB,DRE!T$4)+SUMIFS(Aut_Ajustes_Manuais!$G:$G,Aut_Ajustes_Manuais!$I:$I,DRE!T$4,Aut_Ajustes_Manuais!$F:$F,"Eventos Couvert") -> 0 | W15: 0 | X15: 1365.9358 | Y15: =SUMIFS(BD_Eventos_Novo!$M:$M,BD_Eventos_Novo!$AB:$AB,DRE!W$4)+SUMIFS(BD_Eventos_Novo!$N:$N,BD_Eventos_Novo!$AB:$AB,DRE!W$4)+SUMIFS(BD_Eventos_Novo!$O:$O,BD_Eventos_Novo!$AB:$AB,DRE!W$4)+SUMIFS(Aut_Ajustes_Manuais!$G:$G,Aut_Ajustes_Manuais!$I:$I,DRE!W$4,Aut_Ajustes_Manuais!$F:$F,"Eventos Couvert") -> 0 | Z15: 0 | AA15: 1352.9833 | AB15: =SUMIFS(BD_Eventos_Novo!$M:$M,BD_Eventos_Novo!$AB:$AB,DRE!Z$4)+SUMIFS(BD_Eventos_Novo!$N:$N,BD_Eventos_Novo!$AB:$AB,DRE!Z$4)+SUMIFS(BD_Eventos_Novo!$O:$O,BD_Eventos_Novo!$AB:$AB,DRE!Z$4)+SUMIFS(Aut_Ajustes_Manuais!$G:$G,Aut_Ajustes_Manuais!$I:$I,DRE!Z$4,Aut_Ajustes_Manuais!$F:$F,"Eventos Couvert") -> 0 | AC15: 0 | AD15: 1460.1527 | AE15: =SUMIFS(BD_Eventos_Novo!$M:$M,BD_Eventos_Novo!$AB:$AB,DRE!AC$4)+SUMIFS(BD_Eventos_Novo!$N:$N,BD_Eventos_Novo!$AB:$AB,DRE!AC$4)+SUMIFS(BD_Eventos_Novo!$O:$O,BD_Eventos_Novo!$AB:$AB,DRE!AC$4)+SUMIFS(Aut_Ajustes_Manuais!$G:$G,Aut_Ajustes_Manuais!$I:$I,DRE!AC$4,Aut_Ajustes_Manuais!$F:$F,"Eventos Couvert") -> 0 | AF15: 0 | AG15: 1272.3135 | AH15: =SUMIFS(BD_Eventos_Novo!$M:$M,BD_Eventos_Novo!$AB:$AB,DRE!AF$4)+SUMIFS(BD_Eventos_Novo!$N:$N,BD_Eventos_Novo!$AB:$AB,DRE!AF$4)+SUMIFS(BD_Eventos_Novo!$O:$O,BD_Eventos_Novo!$AB:$AB,DRE!AF$4)+SUMIFS(Aut_Ajustes_Manuais!$G:$G,Aut_Ajustes_Manuais!$I:$I,DRE!AF$4,Aut_Ajustes_Manuais!$F:$F,"Eventos Couvert") -> 0 | AI15: 0 | AJ15: 1280.3392 | AK15: =SUMIFS(BD_Eventos_Novo!$M:$M,BD_Eventos_Novo!$AB:$AB,DRE!AI$4)+SUMIFS(BD_Eventos_Novo!$N:$N,BD_Eventos_Novo!$AB:$AB,DRE!AI$4)+SUMIFS(BD_Eventos_Novo!$O:$O,BD_Eventos_Novo!$AB:$AB,DRE!AI$4)+SUMIFS(Aut_Ajustes_Manuais!$G:$G,Aut_Ajustes_Manuais!$I:$I,DRE!AI$4,Aut_Ajustes_Manuais!$F:$F,"Eventos Couvert") -> 0 | AL15: 0 | AM15: 1485.8245 | AN15: =SUMIFS(BD_Eventos_Novo!$M:$M,BD_Eventos_Novo!$AB:$AB,DRE!AL$4)+SUMIFS(BD_Eventos_Novo!$N:$N,BD_Eventos_Novo!$AB:$AB,DRE!AL$4)+SUMIFS(BD_Eventos_Novo!$O:$O,BD_Eventos_Novo!$AB:$AB,DRE!AL$4)+SUMIFS(Aut_Ajustes_Manuais!$G:$G,Aut_Ajustes_Manuais!$I:$I,DRE!AL$4,Aut_Ajustes_Manuais!$F:$F,"Eventos Couvert") -> 0 | AO15: 0 | AP15: 1344.8397 | AQ15: =SUMIFS(BD_Eventos_Novo!$M:$M,BD_Eventos_Novo!$AB:$AB,DRE!AO$4)+SUMIFS(BD_Eventos_Novo!$N:$N,BD_Eventos_Novo!$AB:$AB,DRE!AO$4)+SUMIFS(BD_Eventos_Novo!$O:$O,BD_Eventos_Novo!$AB:$AB,DRE!AO$4)+SUMIFS(Aut_Ajustes_Manuais!$G:$G,Aut_Ajustes_Manuais!$I:$I,DRE!AO$4,Aut_Ajustes_Manuais!$F:$F,"Eventos Couvert") -> 0 | AR15: =SUMIFS($H15:$AO15,$H$5:$AO$5,"<"&MONTH(TODAY()),$H$6:$AO$6,"REAL 25") -> 0 | AS15: =SUMIFS($I15:$AP15,$I$5:$AP$5,"<"&MONTH(TODAY()),$I$6:$AP$6,"ORÇADO ") -> 7050.0901 | AT15: =SUMIFS($J15:$AQ15,$J$5:$AQ$5,"<"&MONTH(TODAY()),$J$6:$AQ$6,"REAL 26") -> 0 | AU15: =SUM(H15,K15,N15,Q15,T15,W15,Z15,AC15,AF15,AI15,AL15,AO15) -> 0 | AV15: =SUM(I15,L15,O15,R15,U15,X15,AA15,AD15,AG15,AJ15,AM15,AP15) -> 15246.543 | AW15: =SUM(J15,M15,P15,S15,V15,Y15,AB15,AE15,AH15,AK15,AN15,AQ15) -> 0 | AX15: =SUM(H15,K15,N15) -> 0 | AY15: =SUM(I15,L15,O15) -> 3212.8888 | AZ15: =SUM(J15,M15,P15) -> 0 | BA15: =SUM(Q15,T15,W15) -> 0 | BB15: =SUM(R15,U15,X15) -> 3837.2014 | BC15: =SUM(S15,V15,Y15) -> 0 | BD15: =SUM(Z15,AC15,AF15) -> 0 | BE15: =SUM(AA15,AD15,AG15) -> 4085.4495 | BF15: =SUM(AB15,AE15,AH15) -> 0 | BG15: =SUM(AI15,AL15,AO15) -> 0 | BH15: =SUM(AJ15,AM15,AP15) -> 4111.0034 | BI15: =SUM(AK15,AN15,AQ15) -> 0 | BK15: =SUM(I15,L15,O15,R15,U15,X15,AA15,AD15,AG15,AJ15,AM15,AP15) -> 15246.543 | BL15: =BK15-AV15 -> 0 | BM15: =SUM(J15,M15,P15,S15,V15) -> 0 | BN15: =BM15-AT15 -> 0
A16: Eventos Locações | C16: Estim. Mensal | D16: Preencher base de Eventos | H16: 0 | I16: 417.56366 | J16: =SUMIFS(BD_Eventos_Novo!$L:$L,BD_Eventos_Novo!$AB:$AB,DRE!H$4)+SUMIFS(BD_Eventos_Novo!$P:$P,BD_Eventos_Novo!$AB:$AB,DRE!H$4)+SUMIFS(BD_Eventos_Novo!$Q:$Q,BD_Eventos_Novo!$AB:$AB,DRE!H$4)+SUMIFS(BD_Eventos_Novo!$R:$R,BD_Eventos_Novo!$AB:$AB,DRE!H$4)+SUMIFS(BD_Eventos_Novo!$S:$S,BD_Eventos_Novo!$AB:$AB,DRE!H$4)+SUMIFS(BD_Eventos_Novo!$T:$T,BD_Eventos_Novo!$AB:$AB,DRE!H$4)+SUMIFS(BD_Eventos_Novo!$U:$U,BD_Eventos_Novo!$AB:$AB,DRE!H$4)+SUMIFS(BD_Eventos_Novo!$V:$V,BD_Eventos_Novo!$AB:$AB,DRE!H$4)+SUMIFS(BD_Eventos_Novo!$W:$W,BD_Eventos_Novo!$AB:$AB,DRE!H$4)+SUMIFS(BD_Eventos_Novo!$X:$X,BD_Eventos_Novo!$AB:$AB,DRE!H$4)+SUMIFS(Aut_Ajustes_Manuais!$G:$G,Aut_Ajustes_Manuais!$I:$I,DRE!H$4,Aut_Ajustes_Manuais!$F:$F,"Eventos Locações") -> 0 | K16: 0 | L16: 396.17695 | M16: =SUMIFS(BD_Eventos_Novo!$L:$L,BD_Eventos_Novo!$AB:$AB,DRE!K$4)+SUMIFS(BD_Eventos_Novo!$P:$P,BD_Eventos_Novo!$AB:$AB,DRE!K$4)+SUMIFS(BD_Eventos_Novo!$Q:$Q,BD_Eventos_Novo!$AB:$AB,DRE!K$4)+SUMIFS(BD_Eventos_Novo!$R:$R,BD_Eventos_Novo!$AB:$AB,DRE!K$4)+SUMIFS(BD_Eventos_Novo!$S:$S,BD_Eventos_Novo!$AB:$AB,DRE!K$4)+SUMIFS(BD_Eventos_Novo!$T:$T,BD_Eventos_Novo!$AB:$AB,DRE!K$4)+SUMIFS(BD_Eventos_Novo!$U:$U,BD_Eventos_Novo!$AB:$AB,DRE!K$4)+SUMIFS(BD_Eventos_Novo!$V:$V,BD_Eventos_Novo!$AB:$AB,DRE!K$4)+SUMIFS(BD_Eventos_Novo!$W:$W,BD_Eventos_Novo!$AB:$AB,DRE!K$4)+SUMIFS(BD_Eventos_Novo!$X:$X,BD_Eventos_Novo!$AB:$AB,DRE!K$4)+SUMIFS(Aut_Ajustes_Manuais!$G:$G,Aut_Ajustes_Manuais!$I:$I,DRE!K$4,Aut_Ajustes_Manuais!$F:$F,"Eventos Locações") -> 0 | N16: 0 | O16: 317.83295 | P16: =SUMIFS(BD_Eventos_Novo!$L:$L,BD_Eventos_Novo!$AB:$AB,DRE!N$4)+SUMIFS(BD_Eventos_Novo!$P:$P,BD_Eventos_Novo!$AB:$AB,DRE!N$4)+SUMIFS(BD_Eventos_Novo!$Q:$Q,BD_Eventos_Novo!$AB:$AB,DRE!N$4)+SUMIFS(BD_Eventos_Novo!$R:$R,BD_Eventos_Novo!$AB:$AB,DRE!N$4)+SUMIFS(BD_Eventos_Novo!$S:$S,BD_Eventos_Novo!$AB:$AB,DRE!N$4)+SUMIFS(BD_Eventos_Novo!$T:$T,BD_Eventos_Novo!$AB:$AB,DRE!N$4)+SUMIFS(BD_Eventos_Novo!$U:$U,BD_Eventos_Novo!$AB:$AB,DRE!N$4)+SUMIFS(BD_Eventos_Novo!$V:$V,BD_Eventos_Novo!$AB:$AB,DRE!N$4)+SUMIFS(BD_Eventos_Novo!$W:$W,BD_Eventos_Novo!$AB:$AB,DRE!N$4)+SUMIFS(BD_Eventos_Novo!$X:$X,BD_Eventos_Novo!$AB:$AB,DRE!N$4)+SUMIFS(Aut_Ajustes_Manuais!$G:$G,Aut_Ajustes_Manuais!$I:$I,DRE!N$4,Aut_Ajustes_Manuais!$F:$F,"Eventos Locações") -> 0 | Q16: 0 | R16: 330.7643 | S16: =SUMIFS(BD_Eventos_Novo!$L:$L,BD_Eventos_Novo!$AB:$AB,DRE!Q$4)+SUMIFS(BD_Eventos_Novo!$P:$P,BD_Eventos_Novo!$AB:$AB,DRE!Q$4)+SUMIFS(BD_Eventos_Novo!$Q:$Q,BD_Eventos_Novo!$AB:$AB,DRE!Q$4)+SUMIFS(BD_Eventos_Novo!$R:$R,BD_Eventos_Novo!$AB:$AB,DRE!Q$4)+SUMIFS(BD_Eventos_Novo!$S:$S,BD_Eventos_Novo!$AB:$AB,DRE!Q$4)+SUMIFS(BD_Eventos_Novo!$T:$T,BD_Eventos_Novo!$AB:$AB,DRE!Q$4)+SUMIFS(BD_Eventos_Novo!$U:$U,BD_Eventos_Novo!$AB:$AB,DRE!Q$4)+SUMIFS(BD_Eventos_Novo!$V:$V,BD_Eventos_Novo!$AB:$AB,DRE!Q$4)+SUMIFS(BD_Eventos_Novo!$W:$W,BD_Eventos_Novo!$AB:$AB,DRE!Q$4)+SUMIFS(BD_Eventos_Novo!$X:$X,BD_Eventos_Novo!$AB:$AB,DRE!Q$4)+SUMIFS(Aut_Ajustes_Manuais!$G:$G,Aut_Ajustes_Manuais!$I:$I,DRE!Q$4,Aut_Ajustes_Manuais!$F:$F,"Eventos Locações") -> 0 | T16: 0 | U16: 539.61091 | V16: =SUMIFS(BD_Eventos_Novo!$L:$L,BD_Eventos_Novo!$AB:$AB,DRE!T$4)+SUMIFS(BD_Eventos_Novo!$P:$P,BD_Eventos_Novo!$AB:$AB,DRE!T$4)+SUMIFS(BD_Eventos_Novo!$Q:$Q,BD_Eventos_Novo!$AB:$AB,DRE!T$4)+SUMIFS(BD_Eventos_Novo!$R:$R,BD_Eventos_Novo!$AB:$AB,DRE!T$4)+SUMIFS(BD_Eventos_Novo!$S:$S,BD_Eventos_Novo!$AB:$AB,DRE!T$4)+SUMIFS(BD_Eventos_Novo!$T:$T,BD_Eventos_Novo!$AB:$AB,DRE!T$4)+SUMIFS(BD_Eventos_Novo!$U:$U,BD_Eventos_Novo!$AB:$AB,DRE!T$4)+SUMIFS(BD_Eventos_Novo!$V:$V,BD_Eventos_Novo!$AB:$AB,DRE!T$4)+SUMIFS(BD_Eventos_Novo!$W:$W,BD_Eventos_Novo!$AB:$AB,DRE!T$4)+SUMIFS(BD_Eventos_Novo!$X:$X,BD_Eventos_Novo!$AB:$AB,DRE!T$4)+SUMIFS(Aut_Ajustes_Manuais!$G:$G,Aut_Ajustes_Manuais!$I:$I,DRE!T$4,Aut_Ajustes_Manuais!$F:$F,"Eventos Locações") -> 0 | W16: 0 | X16: 481.08011 | Y16: =SUMIFS(BD_Eventos_Novo!$L:$L,BD_Eventos_Novo!$AB:$AB,DRE!W$4)+SUMIFS(BD_Eventos_Novo!$P:$P,BD_Eventos_Novo!$AB:$AB,DRE!W$4)+SUMIFS(BD_Eventos_Novo!$Q:$Q,BD_Eventos_Novo!$AB:$AB,DRE!W$4)+SUMIFS(BD_Eventos_Novo!$R:$R,BD_Eventos_Novo!$AB:$AB,DRE!W$4)+SUMIFS(BD_Eventos_Novo!$S:$S,BD_Eventos_Novo!$AB:$AB,DRE!W$4)+SUMIFS(BD_Eventos_Novo!$T:$T,BD_Eventos_Novo!$AB:$AB,DRE!W$4)+SUMIFS(BD_Eventos_Novo!$U:$U,BD_Eventos_Novo!$AB:$AB,DRE!W$4)+SUMIFS(BD_Eventos_Novo!$V:$V,BD_Eventos_Novo!$AB:$AB,DRE!W$4)+SUMIFS(BD_Eventos_Novo!$W:$W,BD_Eventos_Novo!$AB:$AB,DRE!W$4)+SUMIFS(BD_Eventos_Novo!$X:$X,BD_Eventos_Novo!$AB:$AB,DRE!W$4)+SUMIFS(Aut_Ajustes_Manuais!$G:$G,Aut_Ajustes_Manuais!$I:$I,DRE!W$4,Aut_Ajustes_Manuais!$F:$F,"Eventos Locações") -> 0 | Z16: 0 | AA16: 476.51825 | AB16: =SUMIFS(BD_Eventos_Novo!$L:$L,BD_Eventos_Novo!$AB:$AB,DRE!Z$4)+SUMIFS(BD_Eventos_Novo!$P:$P,BD_Eventos_Novo!$AB:$AB,DRE!Z$4)+SUMIFS(BD_Eventos_Novo!$Q:$Q,BD_Eventos_Novo!$AB:$AB,DRE!Z$4)+SUMIFS(BD_Eventos_Novo!$R:$R,BD_Eventos_Novo!$AB:$AB,DRE!Z$4)+SUMIFS(BD_Eventos_Novo!$S:$S,BD_Eventos_Novo!$AB:$AB,DRE!Z$4)+SUMIFS(BD_Eventos_Novo!$T:$T,BD_Eventos_Novo!$AB:$AB,DRE!Z$4)+SUMIFS(BD_Eventos_Novo!$U:$U,BD_Eventos_Novo!$AB:$AB,DRE!Z$4)+SUMIFS(BD_Eventos_Novo!$V:$V,BD_Eventos_Novo!$AB:$AB,DRE!Z$4)+SUMIFS(BD_Eventos_Novo!$W:$W,BD_Eventos_Novo!$AB:$AB,DRE!Z$4)+SUMIFS(BD_Eventos_Novo!$X:$X,BD_Eventos_Novo!$AB:$AB,DRE!Z$4)+SUMIFS(Aut_Ajustes_Manuais!$G:$G,Aut_Ajustes_Manuais!$I:$I,DRE!Z$4,Aut_Ajustes_Manuais!$F:$F,"Eventos Locações") -> 0 | AC16: 0 | AD16: 514.26311 | AE16: =SUMIFS(BD_Eventos_Novo!$L:$L,BD_Eventos_Novo!$AB:$AB,DRE!AC$4)+SUMIFS(BD_Eventos_Novo!$P:$P,BD_Eventos_Novo!$AB:$AB,DRE!AC$4)+SUMIFS(BD_Eventos_Novo!$Q:$Q,BD_Eventos_Novo!$AB:$AB,DRE!AC$4)+SUMIFS(BD_Eventos_Novo!$R:$R,BD_Eventos_Novo!$AB:$AB,DRE!AC$4)+SUMIFS(BD_Eventos_Novo!$S:$S,BD_Eventos_Novo!$AB:$AB,DRE!AC$4)+SUMIFS(BD_Eventos_Novo!$T:$T,BD_Eventos_Novo!$AB:$AB,DRE!AC$4)+SUMIFS(BD_Eventos_Novo!$U:$U,BD_Eventos_Novo!$AB:$AB,DRE!AC$4)+SUMIFS(BD_Eventos_Novo!$V:$V,BD_Eventos_Novo!$AB:$AB,DRE!AC$4)+SUMIFS(BD_Eventos_Novo!$W:$W,BD_Eventos_Novo!$AB:$AB,DRE!AC$4)+SUMIFS(BD_Eventos_Novo!$X:$X,BD_Eventos_Novo!$AB:$AB,DRE!AC$4)+SUMIFS(Aut_Ajustes_Manuais!$G:$G,Aut_Ajustes_Manuais!$I:$I,DRE!AC$4,Aut_Ajustes_Manuais!$F:$F,"Eventos Locações") -> 0 | AF16: 0 | AG16: 448.1065 | AH16: =SUMIFS(BD_Eventos_Novo!$L:$L,BD_Eventos_Novo!$AB:$AB,DRE!AF$4)+SUMIFS(BD_Eventos_Novo!$P:$P,BD_Eventos_Novo!$AB:$AB,DRE!AF$4)+SUMIFS(BD_Eventos_Novo!$Q:$Q,BD_Eventos_Novo!$AB:$AB,DRE!AF$4)+SUMIFS(BD_Eventos_Novo!$R:$R,BD_Eventos_Novo!$AB:$AB,DRE!AF$4)+SUMIFS(BD_Eventos_Novo!$S:$S,BD_Eventos_Novo!$AB:$AB,DRE!AF$4)+SUMIFS(BD_Eventos_Novo!$T:$T,BD_Eventos_Novo!$AB:$AB,DRE!AF$4)+SUMIFS(BD_Eventos_Novo!$U:$U,BD_Eventos_Novo!$AB:$AB,DRE!AF$4)+SUMIFS(BD_Eventos_Novo!$V:$V,BD_Eventos_Novo!$AB:$AB,DRE!AF$4)+SUMIFS(BD_Eventos_Novo!$W:$W,BD_Eventos_Novo!$AB:$AB,DRE!AF$4)+SUMIFS(BD_Eventos_Novo!$X:$X,BD_Eventos_Novo!$AB:$AB,DRE!AF$4)+SUMIFS(Aut_Ajustes_Manuais!$G:$G,Aut_Ajustes_Manuais!$I:$I,DRE!AF$4,Aut_Ajustes_Manuais!$F:$F,"Eventos Locações") -> 0 | AI16: 0 | AJ16: 450.93313 | AK16: =SUMIFS(BD_Eventos_Novo!$L:$L,BD_Eventos_Novo!$AB:$AB,DRE!AI$4)+SUMIFS(BD_Eventos_Novo!$P:$P,BD_Eventos_Novo!$AB:$AB,DRE!AI$4)+SUMIFS(BD_Eventos_Novo!$Q:$Q,BD_Eventos_Novo!$AB:$AB,DRE!AI$4)+SUMIFS(BD_Eventos_Novo!$R:$R,BD_Eventos_Novo!$AB:$AB,DRE!AI$4)+SUMIFS(BD_Eventos_Novo!$S:$S,BD_Eventos_Novo!$AB:$AB,DRE!AI$4)+SUMIFS(BD_Eventos_Novo!$T:$T,BD_Eventos_Novo!$AB:$AB,DRE!AI$4)+SUMIFS(BD_Eventos_Novo!$U:$U,BD_Eventos_Novo!$AB:$AB,DRE!AI$4)+SUMIFS(BD_Eventos_Novo!$V:$V,BD_Eventos_Novo!$AB:$AB,DRE!AI$4)+SUMIFS(BD_Eventos_Novo!$W:$W,BD_Eventos_Novo!$AB:$AB,DRE!AI$4)+SUMIFS(BD_Eventos_Novo!$X:$X,BD_Eventos_Novo!$AB:$AB,DRE!AI$4)+SUMIFS(Aut_Ajustes_Manuais!$G:$G,Aut_Ajustes_Manuais!$I:$I,DRE!AI$4,Aut_Ajustes_Manuais!$F:$F,"Eventos Locações") -> 0 | AL16: 0 | AM16: 523.30468 | AN16: =SUMIFS(BD_Eventos_Novo!$L:$L,BD_Eventos_Novo!$AB:$AB,DRE!AL$4)+SUMIFS(BD_Eventos_Novo!$P:$P,BD_Eventos_Novo!$AB:$AB,DRE!AL$4)+SUMIFS(BD_Eventos_Novo!$Q:$Q,BD_Eventos_Novo!$AB:$AB,DRE!AL$4)+SUMIFS(BD_Eventos_Novo!$R:$R,BD_Eventos_Novo!$AB:$AB,DRE!AL$4)+SUMIFS(BD_Eventos_Novo!$S:$S,BD_Eventos_Novo!$AB:$AB,DRE!AL$4)+SUMIFS(BD_Eventos_Novo!$T:$T,BD_Eventos_Novo!$AB:$AB,DRE!AL$4)+SUMIFS(BD_Eventos_Novo!$U:$U,BD_Eventos_Novo!$AB:$AB,DRE!AL$4)+SUMIFS(BD_Eventos_Novo!$V:$V,BD_Eventos_Novo!$AB:$AB,DRE!AL$4)+SUMIFS(BD_Eventos_Novo!$W:$W,BD_Eventos_Novo!$AB:$AB,DRE!AL$4)+SUMIFS(BD_Eventos_Novo!$X:$X,BD_Eventos_Novo!$AB:$AB,DRE!AL$4)+SUMIFS(Aut_Ajustes_Manuais!$G:$G,Aut_Ajustes_Manuais!$I:$I,DRE!AL$4,Aut_Ajustes_Manuais!$F:$F,"Eventos Locações") -> 0 | AO16: 0 | AP16: 473.65009 | AQ16: =SUMIFS(BD_Eventos_Novo!$L:$L,BD_Eventos_Novo!$AB:$AB,DRE!AO$4)+SUMIFS(BD_Eventos_Novo!$P:$P,BD_Eventos_Novo!$AB:$AB,DRE!AO$4)+SUMIFS(BD_Eventos_Novo!$Q:$Q,BD_Eventos_Novo!$AB:$AB,DRE!AO$4)+SUMIFS(BD_Eventos_Novo!$R:$R,BD_Eventos_Novo!$AB:$AB,DRE!AO$4)+SUMIFS(BD_Eventos_Novo!$S:$S,BD_Eventos_Novo!$AB:$AB,DRE!AO$4)+SUMIFS(BD_Eventos_Novo!$T:$T,BD_Eventos_Novo!$AB:$AB,DRE!AO$4)+SUMIFS(BD_Eventos_Novo!$U:$U,BD_Eventos_Novo!$AB:$AB,DRE!AO$4)+SUMIFS(BD_Eventos_Novo!$V:$V,BD_Eventos_Novo!$AB:$AB,DRE!AO$4)+SUMIFS(BD_Eventos_Novo!$W:$W,BD_Eventos_Novo!$AB:$AB,DRE!AO$4)+SUMIFS(BD_Eventos_Novo!$X:$X,BD_Eventos_Novo!$AB:$AB,DRE!AO$4)+SUMIFS(Aut_Ajustes_Manuais!$G:$G,Aut_Ajustes_Manuais!$I:$I,DRE!AO$4,Aut_Ajustes_Manuais!$F:$F,"Eventos Locações") -> 0 | AR16: =SUMIFS($H16:$AO16,$H$5:$AO$5,"<"&MONTH(TODAY()),$H$6:$AO$6,"REAL 25") -> 0 | AS16: =SUMIFS($I16:$AP16,$I$5:$AP$5,"<"&MONTH(TODAY()),$I$6:$AP$6,"ORÇADO ") -> 2483.0289 | AT16: =SUMIFS($J16:$AQ16,$J$5:$AQ$5,"<"&MONTH(TODAY()),$J$6:$AQ$6,"REAL 26") -> 0 | AU16: =SUM(H16,K16,N16,Q16,T16,W16,Z16,AC16,AF16,AI16,AL16,AO16) -> 0 | AV16: =SUM(I16,L16,O16,R16,U16,X16,AA16,AD16,AG16,AJ16,AM16,AP16) -> 5369.8046 | AW16: =SUM(J16,M16,P16,S16,V16,Y16,AB16,AE16,AH16,AK16,AN16,AQ16) -> 0 | AX16: =SUM(H16,K16,N16) -> 0 | AY16: =SUM(I16,L16,O16) -> 1131.5736 | AZ16: =SUM(J16,M16,P16) -> 0 | BA16: =SUM(Q16,T16,W16) -> 0 | BB16: =SUM(R16,U16,X16) -> 1351.4553 | BC16: =SUM(S16,V16,Y16) -> 0 | BD16: =SUM(Z16,AC16,AF16) -> 0 | BE16: =SUM(AA16,AD16,AG16) -> 1438.8879 | BF16: =SUM(AB16,AE16,AH16) -> 0 | BG16: =SUM(AI16,AL16,AO16) -> 0 | BH16: =SUM(AJ16,AM16,AP16) -> 1447.8879 | BI16: =SUM(AK16,AN16,AQ16) -> 0 | BK16: =SUM(I16,L16,O16,R16,U16,X16,AA16,AD16,AG16,AJ16,AM16,AP16) -> 5369.8046 | BL16: =BK16-AV16 -> 0 | BM16: =SUM(J16,M16,P16,S16,V16) -> 0 | BN16: =BM16-AT16 -> 0
A17: Eventos Rebate Fornecedores | C17: Estim. Mensal | D17: Comissão sobre venda dos fornecedores homologados | I17: 307.13903 | J17: 0 | L17: 291.40803 | M17: 0 | O17: 233.78208 | P17: 0 | R17: 243.29374 | S17: 0 | U17: 396.9109 | V17: 0 | X17: 353.85856 | Y17: 0 | AA17: 350.50309 | AB17: 0 | AD17: 378.26632 | AE17: 0 | AF17: 0 | AG17: 329.60481 | AH17: 0 | AI17: 0 | AJ17: 331.68395 | AK17: 0 | AL17: 0 | AM17: 384.91685 | AN17: 0 | AO17: 0 | AP17: 348.39341 | AQ17: 0 | AR17: =SUMIFS($H17:$AO17,$H$5:$AO$5,"<"&MONTH(TODAY()),$H$6:$AO$6,"REAL 25") -> 0 | AS17: =SUMIFS($I17:$AP17,$I$5:$AP$5,"<"&MONTH(TODAY()),$I$6:$AP$6,"ORÇADO ") -> 1826.3923 | AT17: =SUMIFS($J17:$AQ17,$J$5:$AQ$5,"<"&MONTH(TODAY()),$J$6:$AQ$6,"REAL 26") -> 0 | AU17: =SUM(H17,K17,N17,Q17,T17,W17,Z17,AC17,AF17,AI17,AL17,AO17) -> 0 | AV17: =SUM(I17,L17,O17,R17,U17,X17,AA17,AD17,AG17,AJ17,AM17,AP17) -> 3949.7607 | AW17: =SUM(J17,M17,P17,S17,V17,Y17,AB17,AE17,AH17,AK17,AN17,AQ17) -> 0 | AX17: =SUM(H17,K17,N17) -> 0 | AY17: =SUM(I17,L17,O17) -> 832.32913 | AZ17: =SUM(J17,M17,P17) -> 0 | BA17: =SUM(Q17,T17,W17) -> 0 | BB17: =SUM(R17,U17,X17) -> 994.06319 | BC17: =SUM(S17,V17,Y17) -> 0 | BD17: =SUM(Z17,AC17,AF17) -> 0 | BE17: =SUM(AA17,AD17,AG17) -> 1058.3742 | BF17: =SUM(AB17,AE17,AH17) -> 0 | BG17: =SUM(AI17,AL17,AO17) -> 0 | BH17: =SUM(AJ17,AM17,AP17) -> 1064.9942 | BI17: =SUM(AK17,AN17,AQ17) -> 0 | BK17: =SUM(I17,L17,O17,R17,U17,X17,AA17,AD17,AG17,AJ17,AM17,AP17) -> 3949.7607 | BL17: =BK17-AV17 -> 0 | BM17: =SUM(J17,M17,P17,S17,V17) -> 0 | BN17: =BM17-AT17 -> 0
A18: Delivery | C18: Estim. Mensal | D18: Preencher base de Delivery | H18: 1110 | I18: 1324.0792 | J18: =SUMIFS(Aut_Faturamento_Zig_Delivery!$F:$F,Aut_Faturamento_Zig_Delivery!$D:$D,DRE!H4)+SUMIFS(Aut_Ajustes_Manuais!$G:$G,Aut_Ajustes_Manuais!$I:$I,DRE!H$4,Aut_Ajustes_Manuais!$F:$F,"Delivery") -> 1011.85 | K18: 760 | L18: 1256.2627 | M18: =SUMIFS(Aut_Faturamento_Zig_Delivery!$F:$F,Aut_Faturamento_Zig_Delivery!$D:$D,DRE!K4)+SUMIFS(Aut_Ajustes_Manuais!$G:$G,Aut_Ajustes_Manuais!$I:$I,DRE!K$4,Aut_Ajustes_Manuais!$F:$F,"Delivery") -> 1864.68 | N18: 2606 | O18: 1007.8367 | P18: =SUMIFS(Aut_Faturamento_Zig_Delivery!$F:$F,Aut_Faturamento_Zig_Delivery!$D:$D,DRE!N4)+SUMIFS(Aut_Ajustes_Manuais!$G:$G,Aut_Ajustes_Manuais!$I:$I,DRE!N$4,Aut_Ajustes_Manuais!$F:$F,"Delivery") -> 4114.04 | Q18: 732 | R18: 1048.8415 | S18: =SUMIFS(Aut_Faturamento_Zig_Delivery!$F:$F,Aut_Faturamento_Zig_Delivery!$D:$D,DRE!Q4)+SUMIFS(Aut_Ajustes_Manuais!$G:$G,Aut_Ajustes_Manuais!$I:$I,DRE!Q$4,Aut_Ajustes_Manuais!$F:$F,"Delivery") -> 2829.96 | T18: 1684 | U18: 1711.0865 | V18: =SUMIFS(Aut_Faturamento_Zig_Delivery!$F:$F,Aut_Faturamento_Zig_Delivery!$D:$D,DRE!T4)+SUMIFS(Aut_Ajustes_Manuais!$G:$G,Aut_Ajustes_Manuais!$I:$I,DRE!T$4,Aut_Ajustes_Manuais!$F:$F,"Delivery") -> 1246.67 | W18: 1132 | X18: 1525.4875 | Y18: =SUMIFS(Aut_Faturamento_Zig_Delivery!$F:$F,Aut_Faturamento_Zig_Delivery!$D:$D,DRE!W4)+SUMIFS(Aut_Ajustes_Manuais!$G:$G,Aut_Ajustes_Manuais!$I:$I,DRE!W$4,Aut_Ajustes_Manuais!$F:$F,"Delivery") -> 1009.37 | Z18: 1708 | AA18: 1511.022 | AB18: =SUMIFS(Aut_Faturamento_Zig_Delivery!$F:$F,Aut_Faturamento_Zig_Delivery!$D:$D,DRE!Z4)+SUMIFS(Aut_Ajustes_Manuais!$G:$G,Aut_Ajustes_Manuais!$I:$I,DRE!Z$4,Aut_Ajustes_Manuais!$F:$F,"Delivery") -> 427.93 | AC18: 1115 | AD18: 1630.7096 | AE18: =SUMIFS(Aut_Faturamento_Zig_Delivery!$F:$F,Aut_Faturamento_Zig_Delivery!$D:$D,DRE!AC4)+SUMIFS(Aut_Ajustes_Manuais!$G:$G,Aut_Ajustes_Manuais!$I:$I,DRE!AC$4,Aut_Ajustes_Manuais!$F:$F,"Delivery") -> 0 | AF18: 792 | AG18: 1420.9294 | AH18: =SUMIFS(Aut_Faturamento_Zig_Delivery!$F:$F,Aut_Faturamento_Zig_Delivery!$D:$D,DRE!AF4)+SUMIFS(Aut_Ajustes_Manuais!$G:$G,Aut_Ajustes_Manuais!$I:$I,DRE!AF$4,Aut_Ajustes_Manuais!$F:$F,"Delivery") -> 0 | AI18: 696.88 | AJ18: 1429.8925 | AK18: =SUMIFS(Aut_Faturamento_Zig_Delivery!$F:$F,Aut_Faturamento_Zig_Delivery!$D:$D,DRE!AI4)+SUMIFS(Aut_Ajustes_Manuais!$G:$G,Aut_Ajustes_Manuais!$I:$I,DRE!AI$4,Aut_Ajustes_Manuais!$F:$F,"Delivery") -> 0 | AL18: 1476.82 | AM18: 1659.3801 | AN18: =SUMIFS(Aut_Faturamento_Zig_Delivery!$F:$F,Aut_Faturamento_Zig_Delivery!$D:$D,DRE!AL4)+SUMIFS(Aut_Ajustes_Manuais!$G:$G,Aut_Ajustes_Manuais!$I:$I,DRE!AL$4,Aut_Ajustes_Manuais!$F:$F,"Delivery") -> 0 | AO18: 872.88 | AP18: 1501.9272 | AQ18: =SUMIFS(Aut_Faturamento_Zig_Delivery!$F:$F,Aut_Faturamento_Zig_Delivery!$D:$D,DRE!AO4)+SUMIFS(Aut_Ajustes_Manuais!$G:$G,Aut_Ajustes_Manuais!$I:$I,DRE!AO$4,Aut_Ajustes_Manuais!$F:$F,"Delivery") -> 0 | AR18: =SUMIFS($H18:$AO18,$H$5:$AO$5,"<"&MONTH(TODAY()),$H$6:$AO$6,"REAL 25") -> 8024 | AS18: =SUMIFS($I18:$AP18,$I$5:$AP$5,"<"&MONTH(TODAY()),$I$6:$AP$6,"ORÇADO ") -> 7873.5942 | AT18: =SUMIFS($J18:$AQ18,$J$5:$AQ$5,"<"&MONTH(TODAY()),$J$6:$AQ$6,"REAL 26") -> 12076.57 | AU18: =SUM(H18,K18,N18,Q18,T18,W18,Z18,AC18,AF18,AI18,AL18,AO18) -> 14685.58 | AV18: =SUM(I18,L18,O18,R18,U18,X18,AA18,AD18,AG18,AJ18,AM18,AP18) -> 17027.455 | AW18: =SUM(J18,M18,P18,S18,V18,Y18,AB18,AE18,AH18,AK18,AN18,AQ18) -> 12504.5 | AX18: =SUM(H18,K18,N18) -> 4476 | AY18: =SUM(I18,L18,O18) -> 3588.1786 | AZ18: =SUM(J18,M18,P18) -> 6990.57 | BA18: =SUM(Q18,T18,W18) -> 3548 | BB18: =SUM(R18,U18,X18) -> 4285.4156 | BC18: =SUM(S18,V18,Y18) -> 5086 | BD18: =SUM(Z18,AC18,AF18) -> 3615 | BE18: =SUM(AA18,AD18,AG18) -> 4562.661 | BF18: =SUM(AB18,AE18,AH18) -> 427.93 | BG18: =SUM(AI18,AL18,AO18) -> 3046.58 | BH18: =SUM(AJ18,AM18,AP18) -> 4591.1998 | BI18: =SUM(AK18,AN18,AQ18) -> 0 | BK18: =SUM(I18,L18,O18,R18,U18,X18,AA18,AD18,AG18,AJ18,AM18,AP18) -> 17027.455 | BL18: =BK18-AV18 -> 0 | BM18: =SUM(J18,M18,P18,S18,V18) -> 11067.2 | BN18: =BM18-AT18 -> -1009.37
A19: Outras Receitas | C19: Estim. Mensal | D19: Coleta de Oleo e etc | H19: 121.5 | I19: 208.77495 | J19: =SUMIFS(Aut_Receitas_Extraord!$L:$L,Aut_Receitas_Extraord!$U:$U,DRE!H4,Aut_Receitas_Extraord!$D:$D,"Coleta de Óleo")+SUMIFS(Aut_Ajustes_Manuais!$G:$G,Aut_Ajustes_Manuais!$I:$I,DRE!H$4,Aut_Ajustes_Manuais!$F:$F,"Outras Receitas") -> 189 | K19: 135 | L19: 198.08195 | M19: =SUMIFS(Aut_Receitas_Extraord!$L:$L,Aut_Receitas_Extraord!$U:$U,DRE!K4,Aut_Receitas_Extraord!$D:$D,"Coleta de Óleo")+SUMIFS(Aut_Ajustes_Manuais!$G:$G,Aut_Ajustes_Manuais!$I:$I,DRE!K$4,Aut_Ajustes_Manuais!$F:$F,"Outras Receitas") -> 297 | N19: 135 | O19: 158.91124 | P19: =SUMIFS(Aut_Receitas_Extraord!$L:$L,Aut_Receitas_Extraord!$U:$U,DRE!N4,Aut_Receitas_Extraord!$D:$D,"Coleta de Óleo")+SUMIFS(Aut_Ajustes_Manuais!$G:$G,Aut_Ajustes_Manuais!$I:$I,DRE!N$4,Aut_Ajustes_Manuais!$F:$F,"Outras Receitas") -> 270 | Q19: 81 | R19: 165.3767 | S19: =SUMIFS(Aut_Receitas_Extraord!$L:$L,Aut_Receitas_Extraord!$U:$U,DRE!Q4,Aut_Receitas_Extraord!$D:$D,"Coleta de Óleo")+SUMIFS(Aut_Ajustes_Manuais!$G:$G,Aut_Ajustes_Manuais!$I:$I,DRE!Q$4,Aut_Ajustes_Manuais!$F:$F,"Outras Receitas") -> 216 | T19: 0 | U19: 269.79657 | V19: =SUMIFS(Aut_Receitas_Extraord!$L:$L,Aut_Receitas_Extraord!$U:$U,DRE!T4,Aut_Receitas_Extraord!$D:$D,"Coleta de Óleo")+SUMIFS(Aut_Ajustes_Manuais!$G:$G,Aut_Ajustes_Manuais!$I:$I,DRE!T$4,Aut_Ajustes_Manuais!$F:$F,"Outras Receitas") -> 270 | W19: 81 | X19: 240.53213 | Y19: =SUMIFS(Aut_Receitas_Extraord!$L:$L,Aut_Receitas_Extraord!$U:$U,DRE!W4,Aut_Receitas_Extraord!$D:$D,"Coleta de Óleo")+SUMIFS(Aut_Ajustes_Manuais!$G:$G,Aut_Ajustes_Manuais!$I:$I,DRE!W$4,Aut_Ajustes_Manuais!$F:$F,"Outras Receitas") -> 0 | Z19: 0 | AA19: 238.25128 | AB19: =SUMIFS(Aut_Receitas_Extraord!$L:$L,Aut_Receitas_Extraord!$U:$U,DRE!Z4,Aut_Receitas_Extraord!$D:$D,"Coleta de Óleo")+SUMIFS(Aut_Ajustes_Manuais!$G:$G,Aut_Ajustes_Manuais!$I:$I,DRE!Z$4,Aut_Ajustes_Manuais!$F:$F,"Outras Receitas") -> 0 | AC19: 135 | AD19: 257.12308 | AE19: =SUMIFS(Aut_Receitas_Extraord!$L:$L,Aut_Receitas_Extraord!$U:$U,DRE!AC4,Aut_Receitas_Extraord!$D:$D,"Coleta de Óleo")+SUMIFS(Aut_Ajustes_Manuais!$G:$G,Aut_Ajustes_Manuais!$I:$I,DRE!AC$4,Aut_Ajustes_Manuais!$F:$F,"Outras Receitas") -> 0 | AF19: 351 | AG19: 224.04587 | AH19: =SUMIFS(Aut_Receitas_Extraord!$L:$L,Aut_Receitas_Extraord!$U:$U,DRE!AF4,Aut_Receitas_Extraord!$D:$D,"Coleta de Óleo")+SUMIFS(Aut_Ajustes_Manuais!$G:$G,Aut_Ajustes_Manuais!$I:$I,DRE!AF$4,Aut_Ajustes_Manuais!$F:$F,"Outras Receitas") -> 0 | AI19: 189 | AJ19: 225.45914 | AK19: =SUMIFS(Aut_Receitas_Extraord!$L:$L,Aut_Receitas_Extraord!$U:$U,DRE!AI4,Aut_Receitas_Extraord!$D:$D,"Coleta de Óleo")+SUMIFS(Aut_Ajustes_Manuais!$G:$G,Aut_Ajustes_Manuais!$I:$I,DRE!AI$4,Aut_Ajustes_Manuais!$F:$F,"Outras Receitas") -> 0 | AL19: 310.5 | AM19: 261.64372 | AN19: =SUMIFS(Aut_Receitas_Extraord!$L:$L,Aut_Receitas_Extraord!$U:$U,DRE!AL4,Aut_Receitas_Extraord!$D:$D,"Coleta de Óleo")+SUMIFS(Aut_Ajustes_Manuais!$G:$G,Aut_Ajustes_Manuais!$I:$I,DRE!AL$4,Aut_Ajustes_Manuais!$F:$F,"Outras Receitas") -> 0 | AO19: 297 | AP19: 236.81724 | AQ19: =SUMIFS(Aut_Receitas_Extraord!$L:$L,Aut_Receitas_Extraord!$U:$U,DRE!AO4,Aut_Receitas_Extraord!$D:$D,"Coleta de Óleo")+SUMIFS(Aut_Ajustes_Manuais!$G:$G,Aut_Ajustes_Manuais!$I:$I,DRE!AO$4,Aut_Ajustes_Manuais!$F:$F,"Outras Receitas") -> 0 | AR19: =SUMIFS($H19:$AO19,$H$5:$AO$5,"<"&MONTH(TODAY()),$H$6:$AO$6,"REAL 25") -> 553.5 | AS19: =SUMIFS($I19:$AP19,$I$5:$AP$5,"<"&MONTH(TODAY()),$I$6:$AP$6,"ORÇADO ") -> 1241.4735 | AT19: =SUMIFS($J19:$AQ19,$J$5:$AQ$5,"<"&MONTH(TODAY()),$J$6:$AQ$6,"REAL 26") -> 1242 | AU19: =SUM(H19,K19,N19,Q19,T19,W19,Z19,AC19,AF19,AI19,AL19,AO19) -> 1836 | AV19: =SUM(I19,L19,O19,R19,U19,X19,AA19,AD19,AG19,AJ19,AM19,AP19) -> 2684.8139 | AW19: =SUM(J19,M19,P19,S19,V19,Y19,AB19,AE19,AH19,AK19,AN19,AQ19) -> 1242 | AX19: =SUM(H19,K19,N19) -> 391.5 | AY19: =SUM(I19,L19,O19) -> 565.76814 | AZ19: =SUM(J19,M19,P19) -> 756 | BA19: =SUM(Q19,T19,W19) -> 162 | BB19: =SUM(R19,U19,X19) -> 675.70539 | BC19: =SUM(S19,V19,Y19) -> 486 | BD19: =SUM(Z19,AC19,AF19) -> 486 | BE19: =SUM(AA19,AD19,AG19) -> 719.42023 | BF19: =SUM(AB19,AE19,AH19) -> 0 | BG19: =SUM(AI19,AL19,AO19) -> 796.5 | BH19: =SUM(AJ19,AM19,AP19) -> 723.9201 | BI19: =SUM(AK19,AN19,AQ19) -> 0 | BK19: =SUM(I19,L19,O19,R19,U19,X19,AA19,AD19,AG19,AJ19,AM19,AP19) -> 2684.8139 | BL19: =BK19-AV19 -> 0 | BM19: =SUM(J19,M19,P19,S19,V19) -> 1242 | BN19: =BM19-AT19 -> 0
A20: Eventos | H20: 0 | I20: =SUM(I14:I17) -> 10306.165 | J20: =SUM(J14:J17)+SUMIFS(Aut_Ajustes_Manuais!$G:$G,Aut_Ajustes_Manuais!$I:$I,DRE!H$4,Aut_Ajustes_Manuais!$F:$F,"Eventos") -> 0 | K20: 0 | L20: =SUM(L14:L17) -> 9778.3056 | M20: =SUM(M14:M17)+SUMIFS(Aut_Ajustes_Manuais!$G:$G,Aut_Ajustes_Manuais!$I:$I,DRE!K$4,Aut_Ajustes_Manuais!$F:$F,"Eventos") -> 0 | N20: 0 | O20: =SUM(O14:O17) -> 7844.6454 | P20: =SUM(P14:P17)+SUMIFS(Aut_Ajustes_Manuais!$G:$G,Aut_Ajustes_Manuais!$I:$I,DRE!N$4,Aut_Ajustes_Manuais!$F:$F,"Eventos") -> 0 | Q20: 0 | R20: =SUM(R14:R17) -> 8163.8126 | S20: =SUM(S14:S17)+SUMIFS(Aut_Ajustes_Manuais!$G:$G,Aut_Ajustes_Manuais!$I:$I,DRE!Q$4,Aut_Ajustes_Manuais!$F:$F,"Eventos") -> 0 | T20: 0 | U20: =SUM(U14:U17) -> 13318.494 | V20: =SUM(V14:V17)+SUMIFS(Aut_Ajustes_Manuais!$G:$G,Aut_Ajustes_Manuais!$I:$I,DRE!T$4,Aut_Ajustes_Manuais!$F:$F,"Eventos") -> 0 | W20: 0 | X20: =SUM(X14:X17) -> 11873.857 | Y20: =SUM(Y14:Y17)+SUMIFS(Aut_Ajustes_Manuais!$G:$G,Aut_Ajustes_Manuais!$I:$I,DRE!W$4,Aut_Ajustes_Manuais!$F:$F,"Eventos") -> 0 | Z20: 0 | AA20: =SUM(AA14:AA17) -> 11761.262 | AB20: =SUM(AB14:AB17)+SUMIFS(Aut_Ajustes_Manuais!$G:$G,Aut_Ajustes_Manuais!$I:$I,DRE!Z$4,Aut_Ajustes_Manuais!$F:$F,"Eventos") -> 0 | AC20: 0 | AD20: =SUM(AD14:AD17) -> 12692.868 | AE20: =SUM(AE14:AE17)+SUMIFS(Aut_Ajustes_Manuais!$G:$G,Aut_Ajustes_Manuais!$I:$I,DRE!AC$4,Aut_Ajustes_Manuais!$F:$F,"Eventos") -> 0 | AF20: 0 | AG20: =SUM(AG14:AG17) -> 11060.013 | AH20: =SUM(AH14:AH17)+SUMIFS(Aut_Ajustes_Manuais!$G:$G,Aut_Ajustes_Manuais!$I:$I,DRE!AF$4,Aut_Ajustes_Manuais!$F:$F,"Eventos") -> 0 | AI20: 0 | AJ20: =SUM(AJ14:AJ17) -> 11129.779 | AK20: =SUM(AK14:AK17)+SUMIFS(Aut_Ajustes_Manuais!$G:$G,Aut_Ajustes_Manuais!$I:$I,DRE!AI$4,Aut_Ajustes_Manuais!$F:$F,"Eventos") -> 0 | AL20: 6400 | AM20: =SUM(AM14:AM17) -> 12916.029 | AN20: =SUM(AN14:AN17)+SUMIFS(Aut_Ajustes_Manuais!$G:$G,Aut_Ajustes_Manuais!$I:$I,DRE!AL$4,Aut_Ajustes_Manuais!$F:$F,"Eventos") -> 0 | AO20: 10500 | AP20: =SUM(AP14:AP17) -> 11690.471 | AQ20: =SUM(AQ14:AQ17)+SUMIFS(Aut_Ajustes_Manuais!$G:$G,Aut_Ajustes_Manuais!$I:$I,DRE!AO$4,Aut_Ajustes_Manuais!$F:$F,"Eventos") -> 0 | AR20: =SUMIFS($H20:$AO20,$H$5:$AO$5,"<"&MONTH(TODAY()),$H$6:$AO$6,"REAL 25") -> 0 | AS20: =SUMIFS($I20:$AP20,$I$5:$AP$5,"<"&MONTH(TODAY()),$I$6:$AP$6,"ORÇADO ") -> 61285.279 | AT20: =SUMIFS($J20:$AQ20,$J$5:$AQ$5,"<"&MONTH(TODAY()),$J$6:$AQ$6,"REAL 26") -> 0 | AU20: =SUM(AU14:AU17) -> 16900 | AV20: =SUM(AV14:AV17) -> 132535.7 | AW20: =SUM(AW14:AW17) -> 0 | AX20: =SUM(AX14:AX17) -> 0 | AY20: =SUM(AY14:AY17) -> 27929.116 | AZ20: =SUM(AZ14:AZ17) -> 0 | BA20: =SUM(BA14:BA17) -> 0 | BB20: =SUM(BB14:BB17) -> 33356.163 | ... BI20: =SUM(BI14:BI17) -> 0 | BK20: =SUM(I20,L20,O20,R20,U20,X20,AA20,AD20,AG20,AJ20,AM20,AP20) -> 132535.7 | BL20: =BK20-AV20 -> 0 | BM20: =SUM(J20,M20,P20,S20,V20) -> 0 | BN20: =BM20-AT20 -> 0
A21: (-) Desconto sobre Venda | C21: Premissas | D21: Valores | E21: % Incid | H21: -7802.6492 | I21: -8744.0165 | J21: =SUM(J22:J24)+SUMIFS(Aut_Ajustes_Manuais!$G:$G,Aut_Ajustes_Manuais!$I:$I,DRE!H$4,Aut_Ajustes_Manuais!$F:$F,"(-) Desconto sobre Venda") -> -6330.32 | K21: -8252.2993 | L21: -8296.1669 | M21: =SUM(M22:M24)+SUMIFS(Aut_Ajustes_Manuais!$G:$G,Aut_Ajustes_Manuais!$I:$I,DRE!K$4,Aut_Ajustes_Manuais!$F:$F,"(-) Desconto sobre Venda") -> -4512.98 | N21: -7476.0648 | O21: -6655.5996 | P21: =SUM(P22:P24)+SUMIFS(Aut_Ajustes_Manuais!$G:$G,Aut_Ajustes_Manuais!$I:$I,DRE!N$4,Aut_Ajustes_Manuais!$F:$F,"(-) Desconto sobre Venda") -> -6090.01 | Q21: -10030.552 | R21: -6926.3893 | S21: =SUM(S22:S24)+SUMIFS(Aut_Ajustes_Manuais!$G:$G,Aut_Ajustes_Manuais!$I:$I,DRE!Q$4,Aut_Ajustes_Manuais!$F:$F,"(-) Desconto sobre Venda") -> -6636.31 | T21: -13829.944 | U21: -11299.754 | V21: =SUM(V22:V24)+SUMIFS(Aut_Ajustes_Manuais!$G:$G,Aut_Ajustes_Manuais!$I:$I,DRE!T$4,Aut_Ajustes_Manuais!$F:$F,"(-) Desconto sobre Venda") -> -6887.96 | W21: -6334.2872 | X21: -10074.086 | Y21: =SUM(Y22:Y24)+SUMIFS(Aut_Ajustes_Manuais!$G:$G,Aut_Ajustes_Manuais!$I:$I,DRE!W$4,Aut_Ajustes_Manuais!$F:$F,"(-) Desconto sobre Venda") -> -8216.28 | Z21: -9220.3861 | AA21: -9978.5586 | AB21: =SUM(AB22:AB24)+SUMIFS(Aut_Ajustes_Manuais!$G:$G,Aut_Ajustes_Manuais!$I:$I,DRE!Z$4,Aut_Ajustes_Manuais!$F:$F,"(-) Desconto sobre Venda") -> 0 | AC21: -7795.7615 | AD21: -10768.957 | AE21: =SUM(AE22:AE24)+SUMIFS(Aut_Ajustes_Manuais!$G:$G,Aut_Ajustes_Manuais!$I:$I,DRE!AC$4,Aut_Ajustes_Manuais!$F:$F,"(-) Desconto sobre Venda") -> 0 | AF21: -8195.6043 | AG21: -9383.6006 | AH21: =SUM(AH22:AH24)+SUMIFS(Aut_Ajustes_Manuais!$G:$G,Aut_Ajustes_Manuais!$I:$I,DRE!AF$4,Aut_Ajustes_Manuais!$F:$F,"(-) Desconto sobre Venda") -> 0 | AI21: -8447.8828 | AJ21: -9442.7919 | AK21: =SUM(AK22:AK24)+SUMIFS(Aut_Ajustes_Manuais!$G:$G,Aut_Ajustes_Manuais!$I:$I,DRE!AI$4,Aut_Ajustes_Manuais!$F:$F,"(-) Desconto sobre Venda") -> 0 | AL21: -8113.5816 | AM21: -10958.292 | AN21: =SUM(AN22:AN24)+SUMIFS(Aut_Ajustes_Manuais!$G:$G,Aut_Ajustes_Manuais!$I:$I,DRE!AL$4,Aut_Ajustes_Manuais!$F:$F,"(-) Desconto sobre Venda") -> 0 | AO21: -7497.4917 | AP21: -9918.4977 | AQ21: =SUM(AQ22:AQ24)+SUMIFS(Aut_Ajustes_Manuais!$G:$G,Aut_Ajustes_Manuais!$I:$I,DRE!AO$4,Aut_Ajustes_Manuais!$F:$F,"(-) Desconto sobre Venda") -> 0 | AR21: =SUM(AR22:AR24) -> -53725.797 | AS21: =SUM(AS22:AS24) -> -51996.013 | AT21: =SUM(AT22:AT24) -> -38673.86 | AU21: =SUM(AU22:AU24) -> -102996.51 | AV21: =SUM(AV22:AV24) -> -112446.71 | AW21: =SUM(AW22:AW24) -> -38673.86 | AX21: =SUM(AX22:AX24) -> -23531.013 | AY21: =SUM(AY22:AY24) -> -23695.783 | ... BI21: =SUM(BI22:BI24) -> 0 | BK21: =SUM(I21,L21,O21,R21,U21,X21,AA21,AD21,AG21,AJ21,AM21,AP21) -> -112446.71 | BL21: =BK21-AV21 -> 0 | BM21: =SUM(J21,M21,P21,S21,V21) -> -30457.58 | BN21: =BM21-AT21 -> 8216.28
A22: Descontos - Operação | C22: Estim. Mensal | D22: Alimentação OP/ Correção de Problemas | E22: 0.025 | H22: -3966.8 | I22: -5274.1687 | J22: =-SUMIFS(Aut_Descontos!$F:$F,Aut_Descontos!$L:$L,DRE!H$4,Aut_Descontos!$K:$K,DRE!$A22)+SUMIFS(Aut_Ajustes_Manuais!$G:$G,Aut_Ajustes_Manuais!$I:$I,DRE!H$4,Aut_Ajustes_Manuais!$F:$F,"Descontos - Operação") -> -607.87 | K22: -4838.19 | L22: -5004.0372 | M22: =-SUMIFS(Aut_Descontos!$F:$F,Aut_Descontos!$L:$L,DRE!K$4,Aut_Descontos!$K:$K,DRE!$A22)+SUMIFS(Aut_Ajustes_Manuais!$G:$G,Aut_Ajustes_Manuais!$I:$I,DRE!K$4,Aut_Ajustes_Manuais!$F:$F,"Descontos - Operação") -> -821.15 | N22: -3305.4147 | O22: -4014.4887 | P22: =-SUMIFS(Aut_Descontos!$F:$F,Aut_Descontos!$L:$L,DRE!N$4,Aut_Descontos!$K:$K,DRE!$A22)+SUMIFS(Aut_Ajustes_Manuais!$G:$G,Aut_Ajustes_Manuais!$I:$I,DRE!N$4,Aut_Ajustes_Manuais!$F:$F,"Descontos - Operação") -> -1207.84 | Q22: -6198.203 | R22: -4177.8221 | S22: =-SUMIFS(Aut_Descontos!$F:$F,Aut_Descontos!$L:$L,DRE!Q$4,Aut_Descontos!$K:$K,DRE!$A22)+SUMIFS(Aut_Ajustes_Manuais!$G:$G,Aut_Ajustes_Manuais!$I:$I,DRE!Q$4,Aut_Ajustes_Manuais!$F:$F,"Descontos - Operação") -> -902.6 | T22: -7587.1162 | U22: -6815.7247 | V22: =-SUMIFS(Aut_Descontos!$F:$F,Aut_Descontos!$L:$L,DRE!T$4,Aut_Descontos!$K:$K,DRE!$A22)+SUMIFS(Aut_Ajustes_Manuais!$G:$G,Aut_Ajustes_Manuais!$I:$I,DRE!T$4,Aut_Ajustes_Manuais!$F:$F,"Descontos - Operação") -> -1316.49 | W22: -730.3 | X22: -6076.4331 | Y22: =-SUMIFS(Aut_Descontos!$F:$F,Aut_Descontos!$L:$L,DRE!W$4,Aut_Descontos!$K:$K,DRE!$A22)+SUMIFS(Aut_Ajustes_Manuais!$G:$G,Aut_Ajustes_Manuais!$I:$I,DRE!W$4,Aut_Ajustes_Manuais!$F:$F,"Descontos - Operação") -> -1011.57 | Z22: -780.88 | AA22: -6018.8132 | AB22: =-SUMIFS(Aut_Descontos!$F:$F,Aut_Descontos!$L:$L,DRE!Z$4,Aut_Descontos!$K:$K,DRE!$A22)+SUMIFS(Aut_Ajustes_Manuais!$G:$G,Aut_Ajustes_Manuais!$I:$I,DRE!Z$4,Aut_Ajustes_Manuais!$F:$F,"Descontos - Operação") -> 0 | AC22: -1498.619 | AD22: -6495.5614 | AE22: =-SUMIFS(Aut_Descontos!$F:$F,Aut_Descontos!$L:$L,DRE!AC$4,Aut_Descontos!$K:$K,DRE!$A22)+SUMIFS(Aut_Ajustes_Manuais!$G:$G,Aut_Ajustes_Manuais!$I:$I,DRE!AC$4,Aut_Ajustes_Manuais!$F:$F,"Descontos - Operação") -> 0 | AF22: -1559.32 | AG22: -5659.9496 | AH22: =-SUMIFS(Aut_Descontos!$F:$F,Aut_Descontos!$L:$L,DRE!AF$4,Aut_Descontos!$K:$K,DRE!$A22)+SUMIFS(Aut_Ajustes_Manuais!$G:$G,Aut_Ajustes_Manuais!$I:$I,DRE!AF$4,Aut_Ajustes_Manuais!$F:$F,"Descontos - Operação") -> 0 | AI22: -1400.83 | AJ22: -5695.6523 | AK22: =-SUMIFS(Aut_Descontos!$F:$F,Aut_Descontos!$L:$L,DRE!AI$4,Aut_Descontos!$K:$K,DRE!$A22)+SUMIFS(Aut_Ajustes_Manuais!$G:$G,Aut_Ajustes_Manuais!$I:$I,DRE!AI$4,Aut_Ajustes_Manuais!$F:$F,"Descontos - Operação") -> 0 | AL22: -1520.28 | AM22: -6609.7637 | AN22: =-SUMIFS(Aut_Descontos!$F:$F,Aut_Descontos!$L:$L,DRE!AL$4,Aut_Descontos!$K:$K,DRE!$A22)+SUMIFS(Aut_Ajustes_Manuais!$G:$G,Aut_Ajustes_Manuais!$I:$I,DRE!AL$4,Aut_Ajustes_Manuais!$F:$F,"Descontos - Operação") -> 0 | AO22: -1511.11 | AP22: -5982.5859 | AQ22: =-SUMIFS(Aut_Descontos!$F:$F,Aut_Descontos!$L:$L,DRE!AO$4,Aut_Descontos!$K:$K,DRE!$A22)+SUMIFS(Aut_Ajustes_Manuais!$G:$G,Aut_Ajustes_Manuais!$I:$I,DRE!AO$4,Aut_Ajustes_Manuais!$F:$F,"Descontos - Operação") -> 0 | AR22: =SUMIFS($H22:$AO22,$H$5:$AO$5,"<"&MONTH(TODAY()),$H$6:$AO$6,"REAL 25") -> -26626.024 | AS22: =SUMIFS($I22:$AP22,$I$5:$AP$5,"<"&MONTH(TODAY()),$I$6:$AP$6,"ORÇADO ") -> -31362.674 | AT22: =SUMIFS($J22:$AQ22,$J$5:$AQ$5,"<"&MONTH(TODAY()),$J$6:$AQ$6,"REAL 26") -> -5867.52 | AU22: =SUM(H22,K22,N22,Q22,T22,W22,Z22,AC22,AF22,AI22,AL22,AO22) -> -34897.063 | AV22: =SUM(I22,L22,O22,R22,U22,X22,AA22,AD22,AG22,AJ22,AM22,AP22) -> -67825 | AW22: =SUM(J22,M22,P22,S22,V22,Y22,AB22,AE22,AH22,AK22,AN22,AQ22) -> -5867.52 | AX22: =SUM(H22,K22,N22) -> -12110.405 | AY22: =SUM(I22,L22,O22) -> -14292.695 | AZ22: =SUM(J22,M22,P22) -> -2636.86 | BA22: =SUM(Q22,T22,W22) -> -14515.619 | BB22: =SUM(R22,U22,X22) -> -17069.98 | BC22: =SUM(S22,V22,Y22) -> -3230.66 | BD22: =SUM(Z22,AC22,AF22) -> -3838.819 | BE22: =SUM(AA22,AD22,AG22) -> -18174.324 | BF22: =SUM(AB22,AE22,AH22) -> 0 | BG22: =SUM(AI22,AL22,AO22) -> -4432.22 | BH22: =SUM(AJ22,AM22,AP22) -> -18288.002 | BI22: =SUM(AK22,AN22,AQ22) -> 0 | BK22: =SUM(I22,L22,O22,R22,U22,X22,AA22,AD22,AG22,AJ22,AM22,AP22) -> -67825 | BL22: =BK22-AV22 -> 0 | BM22: =SUM(J22,M22,P22,S22,V22) -> -4855.95 | BN22: =BM22-AT22 -> 1011.57
A23: Desconto - Alimentação Escritório | C23: Estim. Mensal | D23: Cartão FB / Alimentação Escritório | E23: 0.0198 | H23: -3750.8319 | I23: -2775.8783 | J23: =-SUMIFS(Aut_Descontos!$F:$F,Aut_Descontos!$L:$L,DRE!H$4,Aut_Descontos!$K:$K,DRE!$A23)+SUMIFS(Aut_Ajustes_Manuais!$G:$G,Aut_Ajustes_Manuais!$I:$I,DRE!H$4,Aut_Ajustes_Manuais!$F:$F,"Desconto - Alimentação Escritório") -> -4312.22 | K23: -3259.32 | L23: -2633.7038 | M23: =-SUMIFS(Aut_Descontos!$F:$F,Aut_Descontos!$L:$L,DRE!K$4,Aut_Descontos!$K:$K,DRE!$A23)+SUMIFS(Aut_Ajustes_Manuais!$G:$G,Aut_Ajustes_Manuais!$I:$I,DRE!K$4,Aut_Ajustes_Manuais!$F:$F,"Desconto - Alimentação Escritório") -> -2781.01 | N23: -3083.46 | O23: -2112.8888 | P23: =-SUMIFS(Aut_Descontos!$F:$F,Aut_Descontos!$L:$L,DRE!N$4,Aut_Descontos!$K:$K,DRE!$A23)+SUMIFS(Aut_Ajustes_Manuais!$G:$G,Aut_Ajustes_Manuais!$I:$I,DRE!N$4,Aut_Ajustes_Manuais!$F:$F,"Desconto - Alimentação Escritório") -> -3861.54 | Q23: -2971.83 | R23: -2198.8537 | S23: =-SUMIFS(Aut_Descontos!$F:$F,Aut_Descontos!$L:$L,DRE!Q$4,Aut_Descontos!$K:$K,DRE!$A23)+SUMIFS(Aut_Ajustes_Manuais!$G:$G,Aut_Ajustes_Manuais!$I:$I,DRE!Q$4,Aut_Ajustes_Manuais!$F:$F,"Desconto - Alimentação Escritório") -> -4994.17 | T23: -5810.3427 | U23: -3587.2235 | V23: =-SUMIFS(Aut_Descontos!$F:$F,Aut_Descontos!$L:$L,DRE!T$4,Aut_Descontos!$K:$K,DRE!$A23)+SUMIFS(Aut_Ajustes_Manuais!$G:$G,Aut_Ajustes_Manuais!$I:$I,DRE!T$4,Aut_Ajustes_Manuais!$F:$F,"Desconto - Alimentação Escritório") -> -4690.57 | W23: -3248.4641 | X23: -3198.1227 | Y23: =-SUMIFS(Aut_Descontos!$F:$F,Aut_Descontos!$L:$L,DRE!W$4,Aut_Descontos!$K:$K,DRE!$A23)+SUMIFS(Aut_Ajustes_Manuais!$G:$G,Aut_Ajustes_Manuais!$I:$I,DRE!W$4,Aut_Ajustes_Manuais!$F:$F,"Desconto - Alimentação Escritório") -> -6379.69 | Z23: -4971.5722 | AA23: -3167.7964 | AB23: =-SUMIFS(Aut_Descontos!$F:$F,Aut_Descontos!$L:$L,DRE!Z$4,Aut_Descontos!$K:$K,DRE!$A23)+SUMIFS(Aut_Ajustes_Manuais!$G:$G,Aut_Ajustes_Manuais!$I:$I,DRE!Z$4,Aut_Ajustes_Manuais!$F:$F,"Desconto - Alimentação Escritório") -> 0 | AC23: -4260.36 | AD23: -3418.7165 | AE23: =-SUMIFS(Aut_Descontos!$F:$F,Aut_Descontos!$L:$L,DRE!AC$4,Aut_Descontos!$K:$K,DRE!$A23)+SUMIFS(Aut_Ajustes_Manuais!$G:$G,Aut_Ajustes_Manuais!$I:$I,DRE!AC$4,Aut_Ajustes_Manuais!$F:$F,"Desconto - Alimentação Escritório") -> 0 | AF23: -4638.39 | AG23: -2978.9208 | AH23: =-SUMIFS(Aut_Descontos!$F:$F,Aut_Descontos!$L:$L,DRE!AF$4,Aut_Descontos!$K:$K,DRE!$A23)+SUMIFS(Aut_Ajustes_Manuais!$G:$G,Aut_Ajustes_Manuais!$I:$I,DRE!AF$4,Aut_Ajustes_Manuais!$F:$F,"Desconto - Alimentação Escritório") -> 0 | AI23: -3627.96 | AJ23: -2997.7117 | AK23: =-SUMIFS(Aut_Descontos!$F:$F,Aut_Descontos!$L:$L,DRE!AI$4,Aut_Descontos!$K:$K,DRE!$A23)+SUMIFS(Aut_Ajustes_Manuais!$G:$G,Aut_Ajustes_Manuais!$I:$I,DRE!AI$4,Aut_Ajustes_Manuais!$F:$F,"Desconto - Alimentação Escritório") -> 0 | AL23: -4190.7 | AM23: -3478.823 | AN23: =-SUMIFS(Aut_Descontos!$F:$F,Aut_Descontos!$L:$L,DRE!AL$4,Aut_Descontos!$K:$K,DRE!$A23)+SUMIFS(Aut_Ajustes_Manuais!$G:$G,Aut_Ajustes_Manuais!$I:$I,DRE!AL$4,Aut_Ajustes_Manuais!$F:$F,"Desconto - Alimentação Escritório") -> 0 | AO23: -4136.97 | AP23: -3148.7294 | AQ23: =-SUMIFS(Aut_Descontos!$F:$F,Aut_Descontos!$L:$L,DRE!AO$4,Aut_Descontos!$K:$K,DRE!$A23)+SUMIFS(Aut_Ajustes_Manuais!$G:$G,Aut_Ajustes_Manuais!$I:$I,DRE!AO$4,Aut_Ajustes_Manuais!$F:$F,"Desconto - Alimentação Escritório") -> 0 | AR23: =SUMIFS($H23:$AO23,$H$5:$AO$5,"<"&MONTH(TODAY()),$H$6:$AO$6,"REAL 25") -> -22124.249 | AS23: =SUMIFS($I23:$AP23,$I$5:$AP$5,"<"&MONTH(TODAY()),$I$6:$AP$6,"ORÇADO ") -> -16506.671 | AT23: =SUMIFS($J23:$AQ23,$J$5:$AQ$5,"<"&MONTH(TODAY()),$J$6:$AQ$6,"REAL 26") -> -27019.2 | AU23: =SUM(H23,K23,N23,Q23,T23,W23,Z23,AC23,AF23,AI23,AL23,AO23) -> -47950.201 | AV23: =SUM(I23,L23,O23,R23,U23,X23,AA23,AD23,AG23,AJ23,AM23,AP23) -> -35697.369 | AW23: =SUM(J23,M23,P23,S23,V23,Y23,AB23,AE23,AH23,AK23,AN23,AQ23) -> -27019.2 | AX23: =SUM(H23,K23,N23) -> -10093.612 | AY23: =SUM(I23,L23,O23) -> -7522.4708 | AZ23: =SUM(J23,M23,P23) -> -10954.77 | BA23: =SUM(Q23,T23,W23) -> -12030.637 | BB23: =SUM(R23,U23,X23) -> -8984.1999 | BC23: =SUM(S23,V23,Y23) -> -16064.43 | BD23: =SUM(Z23,AC23,AF23) -> -13870.322 | BE23: =SUM(AA23,AD23,AG23) -> -9565.4337 | BF23: =SUM(AB23,AE23,AH23) -> 0 | BG23: =SUM(AI23,AL23,AO23) -> -11955.63 | BH23: =SUM(AJ23,AM23,AP23) -> -9625.2641 | BI23: =SUM(AK23,AN23,AQ23) -> 0 | BK23: =SUM(I23,L23,O23,R23,U23,X23,AA23,AD23,AG23,AJ23,AM23,AP23) -> -35697.369 | BL23: =BK23-AV23 -> 0 | BM23: =SUM(J23,M23,P23,S23,V23) -> -20639.51 | BN23: =BM23-AT23 -> 6379.69
A24: Descontos - Marketing | C24: Estim. Mensal | D24: Permutas e Ações Gerais | E24: 0.0025 | H24: -85.017352 | I24: -693.96957 | J24: =-SUMIFS(Aut_Descontos!$F:$F,Aut_Descontos!$L:$L,DRE!H$4,Aut_Descontos!$K:$K,DRE!$A24)+SUMIFS(Aut_Ajustes_Manuais!$G:$G,Aut_Ajustes_Manuais!$I:$I,DRE!H$4,Aut_Ajustes_Manuais!$F:$F,"Descontos - Marketing") -> -1410.23 | K24: -154.78931 | L24: -658.42594 | M24: =-SUMIFS(Aut_Descontos!$F:$F,Aut_Descontos!$L:$L,DRE!K$4,Aut_Descontos!$K:$K,DRE!$A24)+SUMIFS(Aut_Ajustes_Manuais!$G:$G,Aut_Ajustes_Manuais!$I:$I,DRE!K$4,Aut_Ajustes_Manuais!$F:$F,"Descontos - Marketing") -> -910.82 | N24: -1087.1902 | O24: -528.22219 | P24: =-SUMIFS(Aut_Descontos!$F:$F,Aut_Descontos!$L:$L,DRE!N$4,Aut_Descontos!$K:$K,DRE!$A24)+SUMIFS(Aut_Ajustes_Manuais!$G:$G,Aut_Ajustes_Manuais!$I:$I,DRE!N$4,Aut_Ajustes_Manuais!$F:$F,"Descontos - Marketing") -> -1020.63 | Q24: -860.51946 | R24: -549.71344 | S24: =-SUMIFS(Aut_Descontos!$F:$F,Aut_Descontos!$L:$L,DRE!Q$4,Aut_Descontos!$K:$K,DRE!$A24)+SUMIFS(Aut_Ajustes_Manuais!$G:$G,Aut_Ajustes_Manuais!$I:$I,DRE!Q$4,Aut_Ajustes_Manuais!$F:$F,"Descontos - Marketing") -> -739.54 | T24: -432.48519 | U24: -896.80588 | V24: =-SUMIFS(Aut_Descontos!$F:$F,Aut_Descontos!$L:$L,DRE!T$4,Aut_Descontos!$K:$K,DRE!$A24)+SUMIFS(Aut_Ajustes_Manuais!$G:$G,Aut_Ajustes_Manuais!$I:$I,DRE!T$4,Aut_Ajustes_Manuais!$F:$F,"Descontos - Marketing") -> -880.9 | W24: -2355.5231 | X24: -799.53067 | Y24: =-SUMIFS(Aut_Descontos!$F:$F,Aut_Descontos!$L:$L,DRE!W$4,Aut_Descontos!$K:$K,DRE!$A24)+SUMIFS(Aut_Ajustes_Manuais!$G:$G,Aut_Ajustes_Manuais!$I:$I,DRE!W$4,Aut_Ajustes_Manuais!$F:$F,"Descontos - Marketing") -> -825.02 | Z24: -3467.9339 | AA24: -791.9491 | AB24: =-SUMIFS(Aut_Descontos!$F:$F,Aut_Descontos!$L:$L,DRE!Z$4,Aut_Descontos!$K:$K,DRE!$A24)+SUMIFS(Aut_Ajustes_Manuais!$G:$G,Aut_Ajustes_Manuais!$I:$I,DRE!Z$4,Aut_Ajustes_Manuais!$F:$F,"Descontos - Marketing") -> 0 | AC24: -2036.7825 | AD24: -854.67913 | AE24: =-SUMIFS(Aut_Descontos!$F:$F,Aut_Descontos!$L:$L,DRE!AC$4,Aut_Descontos!$K:$K,DRE!$A24)+SUMIFS(Aut_Ajustes_Manuais!$G:$G,Aut_Ajustes_Manuais!$I:$I,DRE!AC$4,Aut_Ajustes_Manuais!$F:$F,"Descontos - Marketing") -> 0 | AF24: -1997.8943 | AG24: -744.73021 | AH24: =-SUMIFS(Aut_Descontos!$F:$F,Aut_Descontos!$L:$L,DRE!AF$4,Aut_Descontos!$K:$K,DRE!$A24)+SUMIFS(Aut_Ajustes_Manuais!$G:$G,Aut_Ajustes_Manuais!$I:$I,DRE!AF$4,Aut_Ajustes_Manuais!$F:$F,"Descontos - Marketing") -> 0 | AI24: -3419.0928 | AJ24: -749.42793 | AK24: =-SUMIFS(Aut_Descontos!$F:$F,Aut_Descontos!$L:$L,DRE!AI$4,Aut_Descontos!$K:$K,DRE!$A24)+SUMIFS(Aut_Ajustes_Manuais!$G:$G,Aut_Ajustes_Manuais!$I:$I,DRE!AI$4,Aut_Ajustes_Manuais!$F:$F,"Descontos - Marketing") -> 0 | AL24: -2402.6016 | AM24: -869.70575 | AN24: =-SUMIFS(Aut_Descontos!$F:$F,Aut_Descontos!$L:$L,DRE!AL$4,Aut_Descontos!$K:$K,DRE!$A24)+SUMIFS(Aut_Ajustes_Manuais!$G:$G,Aut_Ajustes_Manuais!$I:$I,DRE!AL$4,Aut_Ajustes_Manuais!$F:$F,"Descontos - Marketing") -> 0 | AO24: -1849.4117 | AP24: -787.18235 | AQ24: =-SUMIFS(Aut_Descontos!$F:$F,Aut_Descontos!$L:$L,DRE!AO$4,Aut_Descontos!$K:$K,DRE!$A24)+SUMIFS(Aut_Ajustes_Manuais!$G:$G,Aut_Ajustes_Manuais!$I:$I,DRE!AO$4,Aut_Ajustes_Manuais!$F:$F,"Descontos - Marketing") -> 0 | AR24: =SUMIFS($H24:$AO24,$H$5:$AO$5,"<"&MONTH(TODAY()),$H$6:$AO$6,"REAL 25") -> -4975.5246 | AS24: =SUMIFS($I24:$AP24,$I$5:$AP$5,"<"&MONTH(TODAY()),$I$6:$AP$6,"ORÇADO ") -> -4126.6677 | AT24: =SUMIFS($J24:$AQ24,$J$5:$AQ$5,"<"&MONTH(TODAY()),$J$6:$AQ$6,"REAL 26") -> -5787.14 | AU24: =SUM(H24,K24,N24,Q24,T24,W24,Z24,AC24,AF24,AI24,AL24,AO24) -> -20149.241 | AV24: =SUM(I24,L24,O24,R24,U24,X24,AA24,AD24,AG24,AJ24,AM24,AP24) -> -8924.3422 | AW24: =SUM(J24,M24,P24,S24,V24,Y24,AB24,AE24,AH24,AK24,AN24,AQ24) -> -5787.14 | AX24: =SUM(H24,K24,N24) -> -1326.9968 | AY24: =SUM(I24,L24,O24) -> -1880.6177 | AZ24: =SUM(J24,M24,P24) -> -3341.68 | BA24: =SUM(Q24,T24,W24) -> -3648.5278 | BB24: =SUM(R24,U24,X24) -> -2246.05 | BC24: =SUM(S24,V24,Y24) -> -2445.46 | BD24: =SUM(Z24,AC24,AF24) -> -7502.6107 | BE24: =SUM(AA24,AD24,AG24) -> -2391.3584 | BF24: =SUM(AB24,AE24,AH24) -> 0 | BG24: =SUM(AI24,AL24,AO24) -> -7671.1061 | BH24: =SUM(AJ24,AM24,AP24) -> -2406.316 | BI24: =SUM(AK24,AN24,AQ24) -> 0 | BK24: =SUM(I24,L24,O24,R24,U24,X24,AA24,AD24,AG24,AJ24,AM24,AP24) -> -8924.3422 | BL24: =BK24-AV24 -> 0 | BM24: =SUM(J24,M24,P24,S24,V24) -> -4962.12 | BN24: =BM24-AT24 -> 825.02
A25: % sobre Receita Bruta | H25: -0.022918447 | I25: -0.023348629 | J25: =IFERROR(J21/J8,0)+SUMIFS(Aut_Ajustes_Manuais!$G:$G,Aut_Ajustes_Manuais!$I:$I,DRE!H$4,Aut_Ajustes_Manuais!$F:$F,"% sobre Receita Bruta") -> -0.0163836 | K25: -0.026708944 | L25: -0.023348629 | M25: =IFERROR(M21/M8,0)+SUMIFS(Aut_Ajustes_Manuais!$G:$G,Aut_Ajustes_Manuais!$I:$I,DRE!K$4,Aut_Ajustes_Manuais!$F:$F,"% sobre Receita Bruta") -> -0.014236137 | N25: -0.024128764 | O25: -0.023348629 | P25: =IFERROR(P21/P8,0)+SUMIFS(Aut_Ajustes_Manuais!$G:$G,Aut_Ajustes_Manuais!$I:$I,DRE!N$4,Aut_Ajustes_Manuais!$F:$F,"% sobre Receita Bruta") -> -0.018050388 | Q25: -0.030431394 | R25: -0.023348629 | S25: =IFERROR(S21/S8,0)+SUMIFS(Aut_Ajustes_Manuais!$G:$G,Aut_Ajustes_Manuais!$I:$I,DRE!Q$4,Aut_Ajustes_Manuais!$F:$F,"% sobre Receita Bruta") -> -0.01795982 | T25: -0.031720191 | U25: -0.023348629 | V25: =IFERROR(V21/V8,0)+SUMIFS(Aut_Ajustes_Manuais!$G:$G,Aut_Ajustes_Manuais!$I:$I,DRE!T$4,Aut_Ajustes_Manuais!$F:$F,"% sobre Receita Bruta") -> -0.01847574 | W25: -0.019085204 | X25: -0.023348629 | Y25: =IFERROR(Y21/Y8,0)+SUMIFS(Aut_Ajustes_Manuais!$G:$G,Aut_Ajustes_Manuais!$I:$I,DRE!W$4,Aut_Ajustes_Manuais!$F:$F,"% sobre Receita Bruta") -> -0.022854925 | Z25: -0.025889516 | AA25: -0.023348629 | AB25: =IFERROR(AB21/AB8,0)+SUMIFS(Aut_Ajustes_Manuais!$G:$G,Aut_Ajustes_Manuais!$I:$I,DRE!Z$4,Aut_Ajustes_Manuais!$F:$F,"% sobre Receita Bruta") -> 0 | AC25: -0.018761574 | AD25: -0.023348629 | AE25: =IFERROR(AE21/AE8,0)+SUMIFS(Aut_Ajustes_Manuais!$G:$G,Aut_Ajustes_Manuais!$I:$I,DRE!AC$4,Aut_Ajustes_Manuais!$F:$F,"% sobre Receita Bruta") -> 0 | AF25: -0.023247578 | AG25: -0.023348629 | AH25: =IFERROR(AH21/AH8,0)+SUMIFS(Aut_Ajustes_Manuais!$G:$G,Aut_Ajustes_Manuais!$I:$I,DRE!AF$4,Aut_Ajustes_Manuais!$F:$F,"% sobre Receita Bruta") -> 0 | AI25: -0.023277999 | AJ25: -0.023348629 | AK25: =IFERROR(AK21/AK8,0)+SUMIFS(Aut_Ajustes_Manuais!$G:$G,Aut_Ajustes_Manuais!$I:$I,DRE!AI$4,Aut_Ajustes_Manuais!$F:$F,"% sobre Receita Bruta") -> 0 | AL25: -0.018889291 | AM25: -0.023348629 | AN25: =IFERROR(AN21/AN8,0)+SUMIFS(Aut_Ajustes_Manuais!$G:$G,Aut_Ajustes_Manuais!$I:$I,DRE!AL$4,Aut_Ajustes_Manuais!$F:$F,"% sobre Receita Bruta") -> 0 | AO25: -0.015612208 | AP25: -0.023348629 | AQ25: =IFERROR(AQ21/AQ8,0)+SUMIFS(Aut_Ajustes_Manuais!$G:$G,Aut_Ajustes_Manuais!$I:$I,DRE!AO$4,Aut_Ajustes_Manuais!$F:$F,"% sobre Receita Bruta") -> 0 | AR25: =IFERROR(AR21/AR8,0) -> -0.026121444 | AS25: =IFERROR(AS21/AS8,0) -> -0.023348629 | AT25: =IFERROR(AT21/AT8,0) -> -0.018049996 | AU25: =IFERROR(AU21/AU8,0) -> -0.023126336 | AV25: =IFERROR(AV21/AV8,0) -> -0.023348629 | AW25: =IFERROR(AW21/AW8,0) -> -0.01741174 | AX25: =IFERROR(AX21/AX8,0) -> -0.024530266 | AY25: =IFERROR(AY21/AY8,0) -> -0.023348629 | ... BI25: =IFERROR(BI21/BI8,0) -> 0 | BK25: =SUM(I25,L25,O25,R25,U25,X25,AA25,AD25,AG25,AJ25,AM25,AP25) -> -0.28018355 | BL25: =BK25-AV25 -> -0.25683492 | BM25: =SUM(J25,M25,P25,S25,V25) -> -0.085105685 | BN25: =BM25-AT25 -> -0.067055689
BK26: =SUM(I26,L26,O26,R26,U26,X26,AA26,AD26,AG26,AJ26,AM26,AP26) -> 0 | BL26: =BK26-AV26 -> 0 | BM26: =SUM(J26,M26,P26,S26,V26) -> 0 | BN26: =BM26-AT26 -> 0
A27: (-) Impostos sobre Venda | C27: Premissas | D27: Valores | E27: % Incid | H27: -12141.73 | I27: -11972.595 | J27: =SUM(J28:J30)+SUMIFS(Aut_Ajustes_Manuais!$G:$G,Aut_Ajustes_Manuais!$I:$I,DRE!H$4,Aut_Ajustes_Manuais!$F:$F,"(-) Impostos sobre Venda") -> -12710.079 | K27: -10976.246 | L27: -11359.385 | M27: =SUM(M28:M30)+SUMIFS(Aut_Ajustes_Manuais!$G:$G,Aut_Ajustes_Manuais!$I:$I,DRE!K$4,Aut_Ajustes_Manuais!$F:$F,"(-) Impostos sobre Venda") -> -10378.502 | N27: -11036.296 | O27: -9113.0659 | P27: =SUM(P28:P30)+SUMIFS(Aut_Ajustes_Manuais!$G:$G,Aut_Ajustes_Manuais!$I:$I,DRE!N$4,Aut_Ajustes_Manuais!$F:$F,"(-) Impostos sobre Venda") -> -11127.395 | Q27: -11664.722 | R27: -9483.8401 | S27: =SUM(S28:S30)+SUMIFS(Aut_Ajustes_Manuais!$G:$G,Aut_Ajustes_Manuais!$I:$I,DRE!Q$4,Aut_Ajustes_Manuais!$F:$F,"(-) Impostos sobre Venda") -> -12081.978 | T27: -15409.139 | U27: -15471.995 | V27: =SUM(V28:V30)+SUMIFS(Aut_Ajustes_Manuais!$G:$G,Aut_Ajustes_Manuais!$I:$I,DRE!T$4,Aut_Ajustes_Manuais!$F:$F,"(-) Impostos sobre Venda") -> -12146.382 | W27: -11882.972 | X27: -13793.77 | Y27: =SUM(Y28:Y30)+SUMIFS(Aut_Ajustes_Manuais!$G:$G,Aut_Ajustes_Manuais!$I:$I,DRE!W$4,Aut_Ajustes_Manuais!$F:$F,"(-) Impostos sobre Venda") -> -11705.986 | Z27: -12662.698 | AA27: -13662.971 | AB27: =SUM(AB28:AB30)+SUMIFS(Aut_Ajustes_Manuais!$G:$G,Aut_Ajustes_Manuais!$I:$I,DRE!Z$4,Aut_Ajustes_Manuais!$F:$F,"(-) Impostos sobre Venda") -> -5240.6556 | AC27: -14881.842 | AD27: -14745.21 | AE27: =SUM(AE28:AE30)+SUMIFS(Aut_Ajustes_Manuais!$G:$G,Aut_Ajustes_Manuais!$I:$I,DRE!AC$4,Aut_Ajustes_Manuais!$F:$F,"(-) Impostos sobre Venda") -> 0 | AF27: -12568.419 | AG27: -12848.335 | AH27: =SUM(AH28:AH30)+SUMIFS(Aut_Ajustes_Manuais!$G:$G,Aut_Ajustes_Manuais!$I:$I,DRE!AF$4,Aut_Ajustes_Manuais!$F:$F,"(-) Impostos sobre Venda") -> 0 | AI27: -12937.968 | AJ27: -12929.381 | AK27: =SUM(AK28:AK30)+SUMIFS(Aut_Ajustes_Manuais!$G:$G,Aut_Ajustes_Manuais!$I:$I,DRE!AI$4,Aut_Ajustes_Manuais!$F:$F,"(-) Impostos sobre Venda") -> 0 | AL27: -15148.224 | AM27: -15004.454 | AN27: =SUM(AN28:AN30)+SUMIFS(Aut_Ajustes_Manuais!$G:$G,Aut_Ajustes_Manuais!$I:$I,DRE!AL$4,Aut_Ajustes_Manuais!$F:$F,"(-) Impostos sobre Venda") -> 0 | AO27: -16871.582 | AP27: -13580.733 | AQ27: =SUM(AQ28:AQ30)+SUMIFS(Aut_Ajustes_Manuais!$G:$G,Aut_Ajustes_Manuais!$I:$I,DRE!AO$4,Aut_Ajustes_Manuais!$F:$F,"(-) Impostos sobre Venda") -> 0 | AR27: =SUM(AR28:AR30) -> -73111.106 | AS27: =SUM(AS28:AS30) -> -71194.651 | AT27: =SUM(AT28:AT30) -> -70150.32 | AU27: =SUM(AU28:AU30) -> -158181.84 | AV27: =SUM(AV28:AV30) -> -153965.74 | AW27: =SUM(AW28:AW30) -> -75390.976 | AX27: =SUM(AX28:AX30) -> -34154.273 | AY27: =SUM(AY28:AY30) -> -32445.046 | ... BI27: =SUM(BI28:BI30) -> 0 | BK27: =SUM(I27,L27,O27,R27,U27,X27,AA27,AD27,AG27,AJ27,AM27,AP27) -> -153965.74 | BL27: =BK27-AV27 -> 0 | BM27: =SUM(J27,M27,P27,S27,V27) -> -58444.335 | BN27: =BM27-AT27 -> 11705.986
A28: PIS / COFINS | C28: Base Fiscal | E28: 0.0365 | H28: -12141.73 | I28: -11779.171 | J28: =-Fiscal!D21-Fiscal!D22+SUMIFS(Aut_Ajustes_Manuais!$G:$G,Aut_Ajustes_Manuais!$I:$I,DRE!H$4,Aut_Ajustes_Manuais!$F:$F,"PIS / COFINS") -> -12507.979 | K28: -10976.246 | L28: -11175.867 | M28: =-Fiscal!E21-Fiscal!E22+SUMIFS(Aut_Ajustes_Manuais!$G:$G,Aut_Ajustes_Manuais!$I:$I,DRE!K$4,Aut_Ajustes_Manuais!$F:$F,"PIS / COFINS") -> -10267.902 | N28: -11036.296 | O28: -8965.8391 | P28: =-Fiscal!F21-Fiscal!F22+SUMIFS(Aut_Ajustes_Manuais!$G:$G,Aut_Ajustes_Manuais!$I:$I,DRE!N$4,Aut_Ajustes_Manuais!$F:$F,"PIS / COFINS") -> -10949.845 | Q28: -11664.722 | R28: -9330.6231 | S28: =-Fiscal!H21-Fiscal!H22+SUMIFS(Aut_Ajustes_Manuais!$G:$G,Aut_Ajustes_Manuais!$I:$I,DRE!Q$4,Aut_Ajustes_Manuais!$F:$F,"PIS / COFINS") -> -11995.928 | T28: -15409.139 | U28: -15222.036 | V28: =-Fiscal!I21-Fiscal!I22+SUMIFS(Aut_Ajustes_Manuais!$G:$G,Aut_Ajustes_Manuais!$I:$I,DRE!T$4,Aut_Ajustes_Manuais!$F:$F,"PIS / COFINS") -> -12078.882 | W28: -11882.972 | X28: -13570.924 | Y28: =-Fiscal!J21-Fiscal!J22+SUMIFS(Aut_Ajustes_Manuais!$G:$G,Aut_Ajustes_Manuais!$I:$I,DRE!W$4,Aut_Ajustes_Manuais!$F:$F,"PIS / COFINS") -> -11659.136 | Z28: -12662.698 | AA28: -13442.237 | AB28: =-Fiscal!L21-Fiscal!L22+SUMIFS(Aut_Ajustes_Manuais!$G:$G,Aut_Ajustes_Manuais!$I:$I,DRE!Z$4,Aut_Ajustes_Manuais!$F:$F,"PIS / COFINS") -> -2446.9424 | AC28: -14881.842 | AD28: -14506.993 | AE28: =-Fiscal!M21-Fiscal!M22+SUMIFS(Aut_Ajustes_Manuais!$G:$G,Aut_Ajustes_Manuais!$I:$I,DRE!AC$4,Aut_Ajustes_Manuais!$F:$F,"PIS / COFINS") -> 0 | AF28: -12568.419 | AG28: -12640.762 | AH28: =-Fiscal!N21-Fiscal!N22+SUMIFS(Aut_Ajustes_Manuais!$G:$G,Aut_Ajustes_Manuais!$I:$I,DRE!AF$4,Aut_Ajustes_Manuais!$F:$F,"PIS / COFINS") -> 0 | AI28: -12937.968 | AJ28: -12720.5 | AK28: =-Fiscal!P21-Fiscal!P22+SUMIFS(Aut_Ajustes_Manuais!$G:$G,Aut_Ajustes_Manuais!$I:$I,DRE!AI$4,Aut_Ajustes_Manuais!$F:$F,"PIS / COFINS") -> 0 | AL28: -15148.224 | AM28: -14762.049 | AN28: =-Fiscal!Q21-Fiscal!Q22+SUMIFS(Aut_Ajustes_Manuais!$G:$G,Aut_Ajustes_Manuais!$I:$I,DRE!AL$4,Aut_Ajustes_Manuais!$F:$F,"PIS / COFINS") -> 0 | AO28: -16871.582 | AP28: -13361.329 | AQ28: =-Fiscal!R21-Fiscal!R22+SUMIFS(Aut_Ajustes_Manuais!$G:$G,Aut_Ajustes_Manuais!$I:$I,DRE!AO$4,Aut_Ajustes_Manuais!$F:$F,"PIS / COFINS") -> 0 | AR28: =SUMIFS($H28:$AO28,$H$5:$AO$5,"<"&MONTH(TODAY()),$H$6:$AO$6,"REAL 25") -> -73111.106 | AS28: =SUMIFS($I28:$AP28,$I$5:$AP$5,"<"&MONTH(TODAY()),$I$6:$AP$6,"ORÇADO ") -> -70044.46 | AT28: =SUMIFS($J28:$AQ28,$J$5:$AQ$5,"<"&MONTH(TODAY()),$J$6:$AQ$6,"REAL 26") -> -69459.67 | AU28: =SUM(H28,K28,N28,Q28,T28,W28,Z28,AC28,AF28,AI28,AL28,AO28) -> -158181.84 | AV28: =SUM(I28,L28,O28,R28,U28,X28,AA28,AD28,AG28,AJ28,AM28,AP28) -> -151478.33 | AW28: =SUM(J28,M28,P28,S28,V28,Y28,AB28,AE28,AH28,AK28,AN28,AQ28) -> -71906.613 | AX28: =SUM(H28,K28,N28) -> -34154.273 | AY28: =SUM(I28,L28,O28) -> -31920.877 | AZ28: =SUM(J28,M28,P28) -> -33725.725 | BA28: =SUM(Q28,T28,W28) -> -38956.833 | BB28: =SUM(R28,U28,X28) -> -38123.583 | BC28: =SUM(S28,V28,Y28) -> -35733.945 | BD28: =SUM(Z28,AC28,AF28) -> -40112.959 | BE28: =SUM(AA28,AD28,AG28) -> -40589.992 | BF28: =SUM(AB28,AE28,AH28) -> -2446.9424 | BG28: =SUM(AI28,AL28,AO28) -> -44957.774 | BH28: =SUM(AJ28,AM28,AP28) -> -40843.877 | BI28: =SUM(AK28,AN28,AQ28) -> 0 | BK28: =SUM(I28,L28,O28,R28,U28,X28,AA28,AD28,AG28,AJ28,AM28,AP28) -> -151478.33 | BL28: =BK28-AV28 -> 0 | BM28: =SUM(J28,M28,P28,S28,V28) -> -57800.535 | BN28: =BM28-AT28 -> 11659.136
A29: ICMS | C29: Base Fiscal | E29: 0.04 | H29: 0 | I29: 0 | J29: =-Fiscal!D23+SUMIFS(Aut_Ajustes_Manuais!$G:$G,Aut_Ajustes_Manuais!$I:$I,DRE!H$4,Aut_Ajustes_Manuais!$F:$F,"ICMS") -> 0 | K29: 0 | L29: 0 | M29: =-Fiscal!E23+SUMIFS(Aut_Ajustes_Manuais!$G:$G,Aut_Ajustes_Manuais!$I:$I,DRE!K$4,Aut_Ajustes_Manuais!$F:$F,"ICMS") -> 0 | N29: 0 | O29: 0 | P29: =-Fiscal!F23+SUMIFS(Aut_Ajustes_Manuais!$G:$G,Aut_Ajustes_Manuais!$I:$I,DRE!N$4,Aut_Ajustes_Manuais!$F:$F,"ICMS") -> 0 | Q29: 0 | R29: 0 | S29: =-Fiscal!H23+SUMIFS(Aut_Ajustes_Manuais!$G:$G,Aut_Ajustes_Manuais!$I:$I,DRE!Q$4,Aut_Ajustes_Manuais!$F:$F,"ICMS") -> 0 | T29: 0 | U29: 0 | V29: =-Fiscal!I23+SUMIFS(Aut_Ajustes_Manuais!$G:$G,Aut_Ajustes_Manuais!$I:$I,DRE!T$4,Aut_Ajustes_Manuais!$F:$F,"ICMS") -> 0 | W29: 0 | X29: 0 | Y29: =-Fiscal!J23+SUMIFS(Aut_Ajustes_Manuais!$G:$G,Aut_Ajustes_Manuais!$I:$I,DRE!W$4,Aut_Ajustes_Manuais!$F:$F,"ICMS") -> 0 | Z29: 0 | AA29: 0 | AB29: =-Fiscal!L23+SUMIFS(Aut_Ajustes_Manuais!$G:$G,Aut_Ajustes_Manuais!$I:$I,DRE!Z$4,Aut_Ajustes_Manuais!$F:$F,"ICMS") -> -2791.3132 | AC29: 0 | AD29: 0 | AE29: =-Fiscal!M23+SUMIFS(Aut_Ajustes_Manuais!$G:$G,Aut_Ajustes_Manuais!$I:$I,DRE!AC$4,Aut_Ajustes_Manuais!$F:$F,"ICMS") -> 0 | AF29: 0 | AG29: 0 | AH29: =-Fiscal!N23+SUMIFS(Aut_Ajustes_Manuais!$G:$G,Aut_Ajustes_Manuais!$I:$I,DRE!AF$4,Aut_Ajustes_Manuais!$F:$F,"ICMS") -> 0 | AI29: 0 | AJ29: 0 | AK29: =-Fiscal!P23+SUMIFS(Aut_Ajustes_Manuais!$G:$G,Aut_Ajustes_Manuais!$I:$I,DRE!AI$4,Aut_Ajustes_Manuais!$F:$F,"ICMS") -> 0 | AL29: 0 | AM29: 0 | AN29: =-Fiscal!Q23+SUMIFS(Aut_Ajustes_Manuais!$G:$G,Aut_Ajustes_Manuais!$I:$I,DRE!AL$4,Aut_Ajustes_Manuais!$F:$F,"ICMS") -> 0 | AO29: 0 | AP29: 0 | AQ29: =-Fiscal!R23+SUMIFS(Aut_Ajustes_Manuais!$G:$G,Aut_Ajustes_Manuais!$I:$I,DRE!AO$4,Aut_Ajustes_Manuais!$F:$F,"ICMS") -> 0 | AR29: =SUMIFS($H29:$AO29,$H$5:$AO$5,"<"&MONTH(TODAY()),$H$6:$AO$6,"REAL 25") -> 0 | AS29: =SUMIFS($I29:$AP29,$I$5:$AP$5,"<"&MONTH(TODAY()),$I$6:$AP$6,"ORÇADO ") -> 0 | AT29: =SUMIFS($J29:$AQ29,$J$5:$AQ$5,"<"&MONTH(TODAY()),$J$6:$AQ$6,"REAL 26") -> 0 | AU29: =SUM(H29,K29,N29,Q29,T29,W29,Z29,AC29,AF29,AI29,AL29,AO29) -> 0 | AV29: =SUM(I29,L29,O29,R29,U29,X29,AA29,AD29,AG29,AJ29,AM29,AP29) -> 0 | AW29: =SUM(J29,M29,P29,S29,V29,Y29,AB29,AE29,AH29,AK29,AN29,AQ29) -> -2791.3132 | AX29: =SUM(H29,K29,N29) -> 0 | AY29: =SUM(I29,L29,O29) -> 0 | AZ29: =SUM(J29,M29,P29) -> 0 | BA29: =SUM(Q29,T29,W29) -> 0 | BB29: =SUM(R29,U29,X29) -> 0 | BC29: =SUM(S29,V29,Y29) -> 0 | BD29: =SUM(Z29,AC29,AF29) -> 0 | BE29: =SUM(AA29,AD29,AG29) -> 0 | BF29: =SUM(AB29,AE29,AH29) -> -2791.3132 | BG29: =SUM(AI29,AL29,AO29) -> 0 | BH29: =SUM(AJ29,AM29,AP29) -> 0 | BI29: =SUM(AK29,AN29,AQ29) -> 0 | BK29: =SUM(I29,L29,O29,R29,U29,X29,AA29,AD29,AG29,AJ29,AM29,AP29) -> 0 | BL29: =BK29-AV29 -> 0 | BM29: =SUM(J29,M29,P29,S29,V29) -> 0 | BN29: =BM29-AT29 -> 0
A30: ISS | C30: Base Fiscal | E30: 0.05 | H30: 0 | I30: -193.42423 | J30: =-Fiscal!D20+SUMIFS(Aut_Ajustes_Manuais!$G:$G,Aut_Ajustes_Manuais!$I:$I,DRE!H$4,Aut_Ajustes_Manuais!$F:$F,"ISS") -> -202.1 | K30: 0 | L30: -183.51746 | M30: =-Fiscal!E20+SUMIFS(Aut_Ajustes_Manuais!$G:$G,Aut_Ajustes_Manuais!$I:$I,DRE!K$4,Aut_Ajustes_Manuais!$F:$F,"ISS") -> -110.6 | N30: 0 | O30: -147.22688 | P30: =-Fiscal!F20+SUMIFS(Aut_Ajustes_Manuais!$G:$G,Aut_Ajustes_Manuais!$I:$I,DRE!N$4,Aut_Ajustes_Manuais!$F:$F,"ISS") -> -177.55 | Q30: 0 | R30: -153.21695 | S30: =-Fiscal!H20+SUMIFS(Aut_Ajustes_Manuais!$G:$G,Aut_Ajustes_Manuais!$I:$I,DRE!Q$4,Aut_Ajustes_Manuais!$F:$F,"ISS") -> -86.05 | T30: 0 | U30: -249.95907 | V30: =-Fiscal!I20+SUMIFS(Aut_Ajustes_Manuais!$G:$G,Aut_Ajustes_Manuais!$I:$I,DRE!T$4,Aut_Ajustes_Manuais!$F:$F,"ISS") -> -67.5 | W30: 0 | X30: -222.84638 | Y30: =-Fiscal!J20+SUMIFS(Aut_Ajustes_Manuais!$G:$G,Aut_Ajustes_Manuais!$I:$I,DRE!W$4,Aut_Ajustes_Manuais!$F:$F,"ISS") -> -46.85 | Z30: 0 | AA30: -220.73323 | AB30: =-Fiscal!L20+SUMIFS(Aut_Ajustes_Manuais!$G:$G,Aut_Ajustes_Manuais!$I:$I,DRE!Z$4,Aut_Ajustes_Manuais!$F:$F,"ISS") -> -2.4 | AC30: 0 | AD30: -238.21744 | AE30: =-Fiscal!M20+SUMIFS(Aut_Ajustes_Manuais!$G:$G,Aut_Ajustes_Manuais!$I:$I,DRE!AC$4,Aut_Ajustes_Manuais!$F:$F,"ISS") -> 0 | AF30: 0 | AG30: -207.57231 | AH30: =-Fiscal!N20+SUMIFS(Aut_Ajustes_Manuais!$G:$G,Aut_Ajustes_Manuais!$I:$I,DRE!AF$4,Aut_Ajustes_Manuais!$F:$F,"ISS") -> 0 | AI30: 0 | AJ30: -208.88167 | AK30: =-Fiscal!P20+SUMIFS(Aut_Ajustes_Manuais!$G:$G,Aut_Ajustes_Manuais!$I:$I,DRE!AI$4,Aut_Ajustes_Manuais!$F:$F,"ISS") -> 0 | AL30: 0 | AM30: -242.40568 | AN30: =-Fiscal!Q20+SUMIFS(Aut_Ajustes_Manuais!$G:$G,Aut_Ajustes_Manuais!$I:$I,DRE!AL$4,Aut_Ajustes_Manuais!$F:$F,"ISS") -> 0 | AO30: 0 | AP30: -219.40464 | AQ30: =-Fiscal!R20+SUMIFS(Aut_Ajustes_Manuais!$G:$G,Aut_Ajustes_Manuais!$I:$I,DRE!AO$4,Aut_Ajustes_Manuais!$F:$F,"ISS") -> 0 | AR30: =SUMIFS($H30:$AO30,$H$5:$AO$5,"<"&MONTH(TODAY()),$H$6:$AO$6,"REAL 25") -> 0 | AS30: =SUMIFS($I30:$AP30,$I$5:$AP$5,"<"&MONTH(TODAY()),$I$6:$AP$6,"ORÇADO ") -> -1150.191 | AT30: =SUMIFS($J30:$AQ30,$J$5:$AQ$5,"<"&MONTH(TODAY()),$J$6:$AQ$6,"REAL 26") -> -690.65 | AU30: =SUM(H30,K30,N30,Q30,T30,W30,Z30,AC30,AF30,AI30,AL30,AO30) -> 0 | AV30: =SUM(I30,L30,O30,R30,U30,X30,AA30,AD30,AG30,AJ30,AM30,AP30) -> -2487.4059 | AW30: =SUM(J30,M30,P30,S30,V30,Y30,AB30,AE30,AH30,AK30,AN30,AQ30) -> -693.05 | AX30: =SUM(H30,K30,N30) -> 0 | AY30: =SUM(I30,L30,O30) -> -524.16856 | AZ30: =SUM(J30,M30,P30) -> -490.25 | BA30: =SUM(Q30,T30,W30) -> 0 | BB30: =SUM(R30,U30,X30) -> -626.02239 | BC30: =SUM(S30,V30,Y30) -> -200.4 | BD30: =SUM(Z30,AC30,AF30) -> 0 | BE30: =SUM(AA30,AD30,AG30) -> -666.52298 | BF30: =SUM(AB30,AE30,AH30) -> -2.4 | BG30: =SUM(AI30,AL30,AO30) -> 0 | BH30: =SUM(AJ30,AM30,AP30) -> -670.69198 | BI30: =SUM(AK30,AN30,AQ30) -> 0 | BK30: =SUM(I30,L30,O30,R30,U30,X30,AA30,AD30,AG30,AJ30,AM30,AP30) -> -2487.4059 | BL30: =BK30-AV30 -> 0 | BM30: =SUM(J30,M30,P30,S30,V30) -> -643.8 | BN30: =BM30-AT30 -> 46.85
BK31: =SUM(I31,L31,O31,R31,U31,X31,AA31,AD31,AG31,AJ31,AM31,AP31) -> 0 | BL31: =BK31-AV31 -> 0 | BM31: =SUM(J31,M31,P31,S31,V31) -> 0 | BN31: =BM31-AT31 -> 0
A32: RECEITA LÍQUIDA | H32: 320508.41 | I32: 353781.46 | J32: =SUM(J27,J21,J8)+SUMIFS(Aut_Ajustes_Manuais!$G:$G,Aut_Ajustes_Manuais!$I:$I,DRE!H$4,Aut_Ajustes_Manuais!$F:$F,"RECEITA LÍQUIDA") -> 367341.1 | K32: 289742.83 | L32: 335661.54 | M32: =SUM(M27,M21,M8)+SUMIFS(Aut_Ajustes_Manuais!$G:$G,Aut_Ajustes_Manuais!$I:$I,DRE!K$4,Aut_Ajustes_Manuais!$F:$F,"RECEITA LÍQUIDA") -> 302117.28 | N32: 291327.99 | O32: 269284.46 | P32: =SUM(P27,P21,P8)+SUMIFS(Aut_Ajustes_Manuais!$G:$G,Aut_Ajustes_Manuais!$I:$I,DRE!N$4,Aut_Ajustes_Manuais!$F:$F,"RECEITA LÍQUIDA") -> 320172.03 | Q32: 307916.72 | R32: 280240.56 | S32: =SUM(S27,S21,S8)+SUMIFS(Aut_Ajustes_Manuais!$G:$G,Aut_Ajustes_Manuais!$I:$I,DRE!Q$4,Aut_Ajustes_Manuais!$F:$F,"RECEITA LÍQUIDA") -> 350790.42 | T32: 406759.05 | U32: 457186.18 | V32: =SUM(V27,V21,V8)+SUMIFS(Aut_Ajustes_Manuais!$G:$G,Aut_Ajustes_Manuais!$I:$I,DRE!T$4,Aut_Ajustes_Manuais!$F:$F,"RECEITA LÍQUIDA") -> 353776.7 | W32: 313677.91 | X32: 407595.86 | Y32: =SUM(Y27,Y21,Y8)+SUMIFS(Aut_Ajustes_Manuais!$G:$G,Aut_Ajustes_Manuais!$I:$I,DRE!W$4,Aut_Ajustes_Manuais!$F:$F,"RECEITA LÍQUIDA") -> 339574.87 | Z32: 334260.55 | AA32: 403730.83 | AB32: =SUM(AB27,AB21,AB8)+SUMIFS(Aut_Ajustes_Manuais!$G:$G,Aut_Ajustes_Manuais!$I:$I,DRE!Z$4,Aut_Ajustes_Manuais!$F:$F,"RECEITA LÍQUIDA") -> 73299.724 | AC32: 392839.86 | AD32: 435710.21 | AE32: =SUM(AE27,AE21,AE8)+SUMIFS(Aut_Ajustes_Manuais!$G:$G,Aut_Ajustes_Manuais!$I:$I,DRE!AC$4,Aut_Ajustes_Manuais!$F:$F,"RECEITA LÍQUIDA") -> 0 | AF32: 331771.82 | AG32: 379658.92 | AH32: =SUM(AH27,AH21,AH8)+SUMIFS(Aut_Ajustes_Manuais!$G:$G,Aut_Ajustes_Manuais!$I:$I,DRE!AF$4,Aut_Ajustes_Manuais!$F:$F,"RECEITA LÍQUIDA") -> 0 | AI32: 341526.91 | AJ32: 382053.79 | AK32: =SUM(AK27,AK21,AK8)+SUMIFS(Aut_Ajustes_Manuais!$G:$G,Aut_Ajustes_Manuais!$I:$I,DRE!AI$4,Aut_Ajustes_Manuais!$F:$F,"RECEITA LÍQUIDA") -> 0 | AL32: 406271.61 | AM32: 443370.69 | AN32: =SUM(AN27,AN21,AN8)+SUMIFS(Aut_Ajustes_Manuais!$G:$G,Aut_Ajustes_Manuais!$I:$I,DRE!AL$4,Aut_Ajustes_Manuais!$F:$F,"RECEITA LÍQUIDA") -> 0 | AO32: 455863.55 | AP32: 401300.77 | AQ32: =SUM(AQ27,AQ21,AQ8)+SUMIFS(Aut_Ajustes_Manuais!$G:$G,Aut_Ajustes_Manuais!$I:$I,DRE!AO$4,Aut_Ajustes_Manuais!$F:$F,"RECEITA LÍQUIDA") -> 0 | AR32: =SUM(AR27,AR21,AR8) -> 1929932.9 | AS32: =SUM(AS27,AS21,AS8) -> 2103750.1 | AT32: =SUM(AT27,AT21,AT8) -> 2033772.4 | AU32: =SUM(AU27,AU21,AU8) -> 4192467.2 | AV32: =SUM(AV27,AV21,AV8) -> 4549575.3 | AW32: =SUM(AW27,AW21,AW8) -> 2107072.1 | AX32: =SUM(AX27,AX21,AX8) -> 901579.23 | AY32: =SUM(AY27,AY21,AY8) -> 958727.45 | ... BI32: =SUM(BI27,BI21,BI8) -> 0 | BK32: =SUM(I32,L32,O32,R32,U32,X32,AA32,AD32,AG32,AJ32,AM32,AP32) -> 4549575.3 | BL32: =BK32-AV32 -> 0 | BM32: =SUM(J32,M32,P32,S32,V32) -> 1694197.5 | BN32: =BM32-AT32 -> -339574.87
BK33: =SUM(I33,L33,O33,R33,U33,X33,AA33,AD33,AG33,AJ33,AM33,AP33) -> 0 | BL33: =BK33-AV33 -> 0 | BM33: =SUM(J33,M33,P33,S33,V33) -> 0 | BN33: =BM33-AT33 -> 0
A34: (-) Custo Mercadoria Vendida | C34: Premissas | D34: Valores | E34: % Incid | H34: -99269.03 | I34: -82469.455 | J34: =SUM(J35:J38)+SUMIFS(Aut_Ajustes_Manuais!$G:$G,Aut_Ajustes_Manuais!$I:$I,DRE!H$4,Aut_Ajustes_Manuais!$F:$F,"(-) Custo Mercadoria Vendida") -> -105582.25 | K34: -94476.45 | L34: -78245.548 | M34: =SUM(M35:M38)+SUMIFS(Aut_Ajustes_Manuais!$G:$G,Aut_Ajustes_Manuais!$I:$I,DRE!K$4,Aut_Ajustes_Manuais!$F:$F,"(-) Custo Mercadoria Vendida") -> -93321.26 | N34: -95474.21 | O34: -62772.488 | P34: =SUM(P35:P38)+SUMIFS(Aut_Ajustes_Manuais!$G:$G,Aut_Ajustes_Manuais!$I:$I,DRE!N$4,Aut_Ajustes_Manuais!$F:$F,"(-) Custo Mercadoria Vendida") -> -97620.45 | Q34: -108092.99 | R34: -65326.449 | S34: =SUM(S35:S38)+SUMIFS(Aut_Ajustes_Manuais!$G:$G,Aut_Ajustes_Manuais!$I:$I,DRE!Q$4,Aut_Ajustes_Manuais!$F:$F,"(-) Custo Mercadoria Vendida") -> -107837.37 | T34: -121985 | U34: -106573.97 | V34: =SUM(V35:V38)+SUMIFS(Aut_Ajustes_Manuais!$G:$G,Aut_Ajustes_Manuais!$I:$I,DRE!T$4,Aut_Ajustes_Manuais!$F:$F,"(-) Custo Mercadoria Vendida") -> -105839.64 | W34: -93973.74 | X34: -95014.05 | Y34: =SUM(Y35:Y38)+SUMIFS(Aut_Ajustes_Manuais!$G:$G,Aut_Ajustes_Manuais!$I:$I,DRE!W$4,Aut_Ajustes_Manuais!$F:$F,"(-) Custo Mercadoria Vendida") -> -160190.16 | Z34: -98399.43 | AA34: -94113.077 | AB34: =SUM(AB35:AB38)+SUMIFS(Aut_Ajustes_Manuais!$G:$G,Aut_Ajustes_Manuais!$I:$I,DRE!Z$4,Aut_Ajustes_Manuais!$F:$F,"(-) Custo Mercadoria Vendida") -> -8464.86 | AC34: -108560.51 | AD34: -101567.74 | AE34: =SUM(AE35:AE38)+SUMIFS(Aut_Ajustes_Manuais!$G:$G,Aut_Ajustes_Manuais!$I:$I,DRE!AC$4,Aut_Ajustes_Manuais!$F:$F,"(-) Custo Mercadoria Vendida") -> 0 | AF34: -95630.18 | AG34: -88501.712 | AH34: =SUM(AH35:AH38)+SUMIFS(Aut_Ajustes_Manuais!$G:$G,Aut_Ajustes_Manuais!$I:$I,DRE!AF$4,Aut_Ajustes_Manuais!$F:$F,"(-) Custo Mercadoria Vendida") -> 0 | AI34: -83729.66 | AJ34: -89059.977 | AK34: =SUM(AK35:AK38)+SUMIFS(Aut_Ajustes_Manuais!$G:$G,Aut_Ajustes_Manuais!$I:$I,DRE!AI$4,Aut_Ajustes_Manuais!$F:$F,"(-) Custo Mercadoria Vendida") -> 0 | AL34: -116109.37 | AM34: -103353.47 | AN34: =SUM(AN35:AN38)+SUMIFS(Aut_Ajustes_Manuais!$G:$G,Aut_Ajustes_Manuais!$I:$I,DRE!AL$4,Aut_Ajustes_Manuais!$F:$F,"(-) Custo Mercadoria Vendida") -> 0 | AO34: -143296.87 | AP34: -93546.61 | AQ34: =SUM(AQ35:AQ38)+SUMIFS(Aut_Ajustes_Manuais!$G:$G,Aut_Ajustes_Manuais!$I:$I,DRE!AO$4,Aut_Ajustes_Manuais!$F:$F,"(-) Custo Mercadoria Vendida") -> 0 | AR34: =SUM(AR35:AR38) -> -613271.42 | AS34: =SUM(AS35:AS38) -> -490401.96 | AT34: =SUM(AT35:AT38) -> -670391.13 | AU34: =SUM(AU35:AU38) -> -1258997.4 | AV34: =SUM(AV35:AV38) -> -1060544.5 | AW34: =SUM(AW35:AW38) -> -678855.99 | AX34: =SUM(AX35:AX38) -> -289219.69 | AY34: =SUM(AY35:AY38) -> -223487.49 | ... BI34: =SUM(BI35:BI38) -> 0 | BK34: =SUM(I34,L34,O34,R34,U34,X34,AA34,AD34,AG34,AJ34,AM34,AP34) -> -1060544.5 | BL34: =BK34-AV34 -> 0 | BM34: =SUM(J34,M34,P34,S34,V34) -> -510200.97 | BN34: =BM34-AT34 -> 160190.16
A35: Alimentação D | C35: Estim. Mensal | E35: 0.33 | H35: -59332.25 | I35: -46337.883 | J35: =-CMV_Manual!D22+SUMIFS(Aut_Ajustes_Manuais!$G:$G,Aut_Ajustes_Manuais!$I:$I,DRE!H$4,Aut_Ajustes_Manuais!$F:$F,"Insumos - Alimentos") -> -61819.51 | K35: -53056.5 | L35: -43964.556 | M35: =-CMV_Manual!E22+SUMIFS(Aut_Ajustes_Manuais!$G:$G,Aut_Ajustes_Manuais!$I:$I,DRE!K$4,Aut_Ajustes_Manuais!$F:$F,"Insumos - Alimentos") -> -51975.11 | N35: -55707.23 | O35: -35270.564 | P35: =-CMV_Manual!F22+SUMIFS(Aut_Ajustes_Manuais!$G:$G,Aut_Ajustes_Manuais!$I:$I,DRE!N$4,Aut_Ajustes_Manuais!$F:$F,"Insumos - Alimentos") -> -61100.35 | Q35: -68385.91 | R35: -36705.582 | S35: =-CMV_Manual!G22+SUMIFS(Aut_Ajustes_Manuais!$G:$G,Aut_Ajustes_Manuais!$I:$I,DRE!Q$4,Aut_Ajustes_Manuais!$F:$F,"Insumos - Alimentos") -> -59317.3 | T35: -72787.5 | U35: -59881.712 | V35: =-CMV_Manual!H22+SUMIFS(Aut_Ajustes_Manuais!$G:$G,Aut_Ajustes_Manuais!$I:$I,DRE!T$4,Aut_Ajustes_Manuais!$F:$F,"Insumos - Alimentos") -> -64729.36 | W35: -58960.82 | X35: -53386.431 | Y35: =-CMV_Manual!I22+SUMIFS(Aut_Ajustes_Manuais!$G:$G,Aut_Ajustes_Manuais!$I:$I,DRE!W$4,Aut_Ajustes_Manuais!$F:$F,"Insumos - Alimentos") -> -94880.31 | Z35: -61129.26 | AA35: -52880.193 | AB35: =-CMV_Manual!J22+SUMIFS(Aut_Ajustes_Manuais!$G:$G,Aut_Ajustes_Manuais!$I:$I,DRE!Z$4,Aut_Ajustes_Manuais!$F:$F,"Insumos - Alimentos") -> -7755.22 | AC35: -61209.97 | AD35: -57068.815 | AE35: =-CMV_Manual!K22+SUMIFS(Aut_Ajustes_Manuais!$G:$G,Aut_Ajustes_Manuais!$I:$I,DRE!AC$4,Aut_Ajustes_Manuais!$F:$F,"Insumos - Alimentos") -> 0 | AF35: -60765.24 | AG35: -49727.283 | AH35: =-CMV_Manual!L22+SUMIFS(Aut_Ajustes_Manuais!$G:$G,Aut_Ajustes_Manuais!$I:$I,DRE!AF$4,Aut_Ajustes_Manuais!$F:$F,"Insumos - Alimentos") -> 0 | AI35: -46723.38 | AJ35: -50040.96 | AK35: =-CMV_Manual!M22+SUMIFS(Aut_Ajustes_Manuais!$G:$G,Aut_Ajustes_Manuais!$I:$I,DRE!AI$4,Aut_Ajustes_Manuais!$F:$F,"Insumos - Alimentos") -> 0 | AL35: -70295.3 | AM35: -58072.176 | AN35: =-CMV_Manual!N22+SUMIFS(Aut_Ajustes_Manuais!$G:$G,Aut_Ajustes_Manuais!$I:$I,DRE!AL$4,Aut_Ajustes_Manuais!$F:$F,"Insumos - Alimentos") -> 0 | AO35: -73432.61 | AP35: -52561.907 | AQ35: =-CMV_Manual!O22+SUMIFS(Aut_Ajustes_Manuais!$G:$G,Aut_Ajustes_Manuais!$I:$I,DRE!AO$4,Aut_Ajustes_Manuais!$F:$F,"Insumos - Alimentos") -> 0 | AR35: =SUMIFS($H35:$AO35,$H$5:$AO$5,"<"&MONTH(TODAY()),$H$6:$AO$6,"REAL 25") -> -368230.21 | AS35: =SUMIFS($I35:$AP35,$I$5:$AP$5,"<"&MONTH(TODAY()),$I$6:$AP$6,"ORÇADO ") -> -275546.73 | AT35: =SUMIFS($J35:$AQ35,$J$5:$AQ$5,"<"&MONTH(TODAY()),$J$6:$AQ$6,"REAL 26") -> -393821.94 | AU35: =SUM(H35,K35,N35,Q35,T35,W35,Z35,AC35,AF35,AI35,AL35,AO35) -> -741785.97 | AV35: =SUM(I35,L35,O35,R35,U35,X35,AA35,AD35,AG35,AJ35,AM35,AP35) -> -595898.06 | AW35: =SUM(J35,M35,P35,S35,V35,Y35,AB35,AE35,AH35,AK35,AN35,AQ35) -> -401577.16 | AX35: =SUM(H35,K35,N35) -> -168095.98 | AY35: =SUM(I35,L35,O35) -> -125573 | AZ35: =SUM(J35,M35,P35) -> -174894.97 | BA35: =SUM(Q35,T35,W35) -> -200134.23 | BB35: =SUM(R35,U35,X35) -> -149973.72 | BC35: =SUM(S35,V35,Y35) -> -218926.97 | BD35: =SUM(Z35,AC35,AF35) -> -183104.47 | BE35: =SUM(AA35,AD35,AG35) -> -159676.29 | BF35: =SUM(AB35,AE35,AH35) -> -7755.22 | BG35: =SUM(AI35,AL35,AO35) -> -190451.29 | BH35: =SUM(AJ35,AM35,AP35) -> -160675.04 | BI35: =SUM(AK35,AN35,AQ35) -> 0 | BK35: =SUM(I35,L35,O35,R35,U35,X35,AA35,AD35,AG35,AJ35,AM35,AP35) -> -595898.06 | BL35: =BK35-AV35 -> 0 | BM35: =SUM(J35,M35,P35,S35,V35) -> -298941.63 | BN35: =BM35-AT35 -> 94880.31
A36: Bebida D | C36: Estim. Mensal | E36: 0.18 | H36: -39936.78 | I36: -36025.647 | J36: =-CMV_Manual!D23+SUMIFS(Aut_Ajustes_Manuais!$G:$G,Aut_Ajustes_Manuais!$I:$I,DRE!H$4,Aut_Ajustes_Manuais!$F:$F,"Insumos - Bebidas") -> -43762.74 | K36: -41419.95 | L36: -34180.491 | M36: =-CMV_Manual!E23+SUMIFS(Aut_Ajustes_Manuais!$G:$G,Aut_Ajustes_Manuais!$I:$I,DRE!K$4,Aut_Ajustes_Manuais!$F:$F,"Insumos - Bebidas") -> -39388.25 | N36: -39766.98 | O36: -27421.298 | P36: =-CMV_Manual!F23+SUMIFS(Aut_Ajustes_Manuais!$G:$G,Aut_Ajustes_Manuais!$I:$I,DRE!N$4,Aut_Ajustes_Manuais!$F:$F,"Insumos - Bebidas") -> -35910.11 | Q36: -39707.08 | R36: -28536.96 | S36: =-CMV_Manual!G23+SUMIFS(Aut_Ajustes_Manuais!$G:$G,Aut_Ajustes_Manuais!$I:$I,DRE!Q$4,Aut_Ajustes_Manuais!$F:$F,"Insumos - Bebidas") -> -48520.07 | T36: -49197.5 | U36: -46555.373 | V36: =-CMV_Manual!H23+SUMIFS(Aut_Ajustes_Manuais!$G:$G,Aut_Ajustes_Manuais!$I:$I,DRE!T$4,Aut_Ajustes_Manuais!$F:$F,"Insumos - Bebidas") -> -41110.28 | W36: -35012.92 | X36: -41505.58 | Y36: =-CMV_Manual!I23+SUMIFS(Aut_Ajustes_Manuais!$G:$G,Aut_Ajustes_Manuais!$I:$I,DRE!W$4,Aut_Ajustes_Manuais!$F:$F,"Insumos - Bebidas") -> -65309.85 | Z36: -37270.17 | AA36: -41112.002 | AB36: =-CMV_Manual!J23+SUMIFS(Aut_Ajustes_Manuais!$G:$G,Aut_Ajustes_Manuais!$I:$I,DRE!Z$4,Aut_Ajustes_Manuais!$F:$F,"Insumos - Bebidas") -> -709.64 | AC36: -47350.54 | AD36: -44368.47 | AE36: =-CMV_Manual!K23+SUMIFS(Aut_Ajustes_Manuais!$G:$G,Aut_Ajustes_Manuais!$I:$I,DRE!AC$4,Aut_Ajustes_Manuais!$F:$F,"Insumos - Bebidas") -> 0 | AF36: -34864.94 | AG36: -38660.755 | AH36: =-CMV_Manual!L23+SUMIFS(Aut_Ajustes_Manuais!$G:$G,Aut_Ajustes_Manuais!$I:$I,DRE!AF$4,Aut_Ajustes_Manuais!$F:$F,"Insumos - Bebidas") -> 0 | AI36: -37006.28 | AJ36: -38904.625 | AK36: =-CMV_Manual!M23+SUMIFS(Aut_Ajustes_Manuais!$G:$G,Aut_Ajustes_Manuais!$I:$I,DRE!AI$4,Aut_Ajustes_Manuais!$F:$F,"Insumos - Bebidas") -> 0 | AL36: -45814.07 | AM36: -45148.539 | AN36: =-CMV_Manual!N23+SUMIFS(Aut_Ajustes_Manuais!$G:$G,Aut_Ajustes_Manuais!$I:$I,DRE!AL$4,Aut_Ajustes_Manuais!$F:$F,"Insumos - Bebidas") -> 0 | AO36: -69864.26 | AP36: -40864.549 | AQ36: =-CMV_Manual!O23+SUMIFS(Aut_Ajustes_Manuais!$G:$G,Aut_Ajustes_Manuais!$I:$I,DRE!AO$4,Aut_Ajustes_Manuais!$F:$F,"Insumos - Bebidas") -> 0 | AR36: =SUMIFS($H36:$AO36,$H$5:$AO$5,"<"&MONTH(TODAY()),$H$6:$AO$6,"REAL 25") -> -245041.21 | AS36: =SUMIFS($I36:$AP36,$I$5:$AP$5,"<"&MONTH(TODAY()),$I$6:$AP$6,"ORÇADO ") -> -214225.35 | AT36: =SUMIFS($J36:$AQ36,$J$5:$AQ$5,"<"&MONTH(TODAY()),$J$6:$AQ$6,"REAL 26") -> -274001.3 | AU36: =SUM(H36,K36,N36,Q36,T36,W36,Z36,AC36,AF36,AI36,AL36,AO36) -> -517211.47 | AV36: =SUM(I36,L36,O36,R36,U36,X36,AA36,AD36,AG36,AJ36,AM36,AP36) -> -463284.29 | AW36: =SUM(J36,M36,P36,S36,V36,Y36,AB36,AE36,AH36,AK36,AN36,AQ36) -> -274710.94 | AX36: =SUM(H36,K36,N36) -> -121123.71 | AY36: =SUM(I36,L36,O36) -> -97627.435 | AZ36: =SUM(J36,M36,P36) -> -119061.1 | BA36: =SUM(Q36,T36,W36) -> -123917.5 | BB36: =SUM(R36,U36,X36) -> -116597.91 | BC36: =SUM(S36,V36,Y36) -> -154940.2 | BD36: =SUM(Z36,AC36,AF36) -> -119485.65 | BE36: =SUM(AA36,AD36,AG36) -> -124141.23 | BF36: =SUM(AB36,AE36,AH36) -> -709.64 | BG36: =SUM(AI36,AL36,AO36) -> -152684.61 | BH36: =SUM(AJ36,AM36,AP36) -> -124917.71 | BI36: =SUM(AK36,AN36,AQ36) -> 0 | BK36: =SUM(I36,L36,O36,R36,U36,X36,AA36,AD36,AG36,AJ36,AM36,AP36) -> -463284.29 | BL36: =BK36-AV36 -> 0 | BM36: =SUM(J36,M36,P36,S36,V36) -> -208691.45 | BN36: =BM36-AT36 -> 65309.85
A37: Embalagens | C37: Estim. Mensal | H37: 0 | I37: -105.92633 | J37: =SUMIFS(Aut_BlueMe_Sem_Pedido!$J:$J,Aut_BlueMe_Sem_Pedido!$Q:$Q,DRE!H$4,Aut_BlueMe_Sem_Pedido!$H:$H,DRE!$A37)+SUMIFS(Aut_Ajustes_Manuais!$G:$G,Aut_Ajustes_Manuais!$I:$I,DRE!H$4,Aut_Ajustes_Manuais!$F:$F,"Insumos - Embalagens") -> 0 | K37: 0 | L37: -100.50102 | M37: =SUMIFS(Aut_BlueMe_Sem_Pedido!$J:$J,Aut_BlueMe_Sem_Pedido!$Q:$Q,DRE!K$4,Aut_BlueMe_Sem_Pedido!$H:$H,DRE!$A37)+SUMIFS(Aut_Ajustes_Manuais!$G:$G,Aut_Ajustes_Manuais!$I:$I,DRE!K$4,Aut_Ajustes_Manuais!$F:$F,"Insumos - Embalagens") -> -1957.9 | N37: 0 | O37: -80.626936 | P37: =SUMIFS(Aut_BlueMe_Sem_Pedido!$J:$J,Aut_BlueMe_Sem_Pedido!$Q:$Q,DRE!N$4,Aut_BlueMe_Sem_Pedido!$H:$H,DRE!$A37)+SUMIFS(Aut_Ajustes_Manuais!$G:$G,Aut_Ajustes_Manuais!$I:$I,DRE!N$4,Aut_Ajustes_Manuais!$F:$F,"Insumos - Embalagens") -> -609.99 | Q37: 0 | R37: -83.907323 | S37: =SUMIFS(Aut_BlueMe_Sem_Pedido!$J:$J,Aut_BlueMe_Sem_Pedido!$Q:$Q,DRE!Q$4,Aut_BlueMe_Sem_Pedido!$H:$H,DRE!$A37)+SUMIFS(Aut_Ajustes_Manuais!$G:$G,Aut_Ajustes_Manuais!$I:$I,DRE!Q$4,Aut_Ajustes_Manuais!$F:$F,"Insumos - Embalagens") -> 0 | T37: 0 | U37: -136.88692 | V37: =SUMIFS(Aut_BlueMe_Sem_Pedido!$J:$J,Aut_BlueMe_Sem_Pedido!$Q:$Q,DRE!T$4,Aut_BlueMe_Sem_Pedido!$H:$H,DRE!$A37)+SUMIFS(Aut_Ajustes_Manuais!$G:$G,Aut_Ajustes_Manuais!$I:$I,DRE!T$4,Aut_Ajustes_Manuais!$F:$F,"Insumos - Embalagens") -> 0 | W37: 0 | X37: -122.039 | Y37: =SUMIFS(Aut_BlueMe_Sem_Pedido!$J:$J,Aut_BlueMe_Sem_Pedido!$Q:$Q,DRE!W$4,Aut_BlueMe_Sem_Pedido!$H:$H,DRE!$A37)+SUMIFS(Aut_Ajustes_Manuais!$G:$G,Aut_Ajustes_Manuais!$I:$I,DRE!W$4,Aut_Ajustes_Manuais!$F:$F,"Insumos - Embalagens") -> 0 | Z37: 0 | AA37: -120.88176 | AB37: =SUMIFS(Aut_BlueMe_Sem_Pedido!$J:$J,Aut_BlueMe_Sem_Pedido!$Q:$Q,DRE!Z$4,Aut_BlueMe_Sem_Pedido!$H:$H,DRE!$A37)+SUMIFS(Aut_Ajustes_Manuais!$G:$G,Aut_Ajustes_Manuais!$I:$I,DRE!Z$4,Aut_Ajustes_Manuais!$F:$F,"Insumos - Embalagens") -> 0 | AC37: 0 | AD37: -130.45677 | AE37: =SUMIFS(Aut_BlueMe_Sem_Pedido!$J:$J,Aut_BlueMe_Sem_Pedido!$Q:$Q,DRE!AC$4,Aut_BlueMe_Sem_Pedido!$H:$H,DRE!$A37)+SUMIFS(Aut_Ajustes_Manuais!$G:$G,Aut_Ajustes_Manuais!$I:$I,DRE!AC$4,Aut_Ajustes_Manuais!$F:$F,"Insumos - Embalagens") -> 0 | AF37: 0 | AG37: -113.67435 | AH37: =SUMIFS(Aut_BlueMe_Sem_Pedido!$J:$J,Aut_BlueMe_Sem_Pedido!$Q:$Q,DRE!AF$4,Aut_BlueMe_Sem_Pedido!$H:$H,DRE!$A37)+SUMIFS(Aut_Ajustes_Manuais!$G:$G,Aut_Ajustes_Manuais!$I:$I,DRE!AF$4,Aut_Ajustes_Manuais!$F:$F,"Insumos - Embalagens") -> 0 | AI37: 0 | AJ37: -114.3914 | AK37: =SUMIFS(Aut_BlueMe_Sem_Pedido!$J:$J,Aut_BlueMe_Sem_Pedido!$Q:$Q,DRE!AI$4,Aut_BlueMe_Sem_Pedido!$H:$H,DRE!$A37)+SUMIFS(Aut_Ajustes_Manuais!$G:$G,Aut_Ajustes_Manuais!$I:$I,DRE!AI$4,Aut_Ajustes_Manuais!$F:$F,"Insumos - Embalagens") -> 0 | AL37: 0 | AM37: -132.75041 | AN37: =SUMIFS(Aut_BlueMe_Sem_Pedido!$J:$J,Aut_BlueMe_Sem_Pedido!$Q:$Q,DRE!AL$4,Aut_BlueMe_Sem_Pedido!$H:$H,DRE!$A37)+SUMIFS(Aut_Ajustes_Manuais!$G:$G,Aut_Ajustes_Manuais!$I:$I,DRE!AL$4,Aut_Ajustes_Manuais!$F:$F,"Insumos - Embalagens") -> 0 | AO37: 0 | AP37: -120.15417 | AQ37: =SUMIFS(Aut_BlueMe_Sem_Pedido!$J:$J,Aut_BlueMe_Sem_Pedido!$Q:$Q,DRE!AO$4,Aut_BlueMe_Sem_Pedido!$H:$H,DRE!$A37)+SUMIFS(Aut_Ajustes_Manuais!$G:$G,Aut_Ajustes_Manuais!$I:$I,DRE!AO$4,Aut_Ajustes_Manuais!$F:$F,"Insumos - Embalagens") -> 0 | AR37: =SUMIFS($H37:$AO37,$H$5:$AO$5,"<"&MONTH(TODAY()),$H$6:$AO$6,"REAL 25") -> 0 | AS37: =SUMIFS($I37:$AP37,$I$5:$AP$5,"<"&MONTH(TODAY()),$I$6:$AP$6,"ORÇADO ") -> -629.88753 | AT37: =SUMIFS($J37:$AQ37,$J$5:$AQ$5,"<"&MONTH(TODAY()),$J$6:$AQ$6,"REAL 26") -> -2567.89 | AU37: =SUM(H37,K37,N37,Q37,T37,W37,Z37,AC37,AF37,AI37,AL37,AO37) -> 0 | AV37: =SUM(I37,L37,O37,R37,U37,X37,AA37,AD37,AG37,AJ37,AM37,AP37) -> -1362.1964 | AW37: =SUM(J37,M37,P37,S37,V37,Y37,AB37,AE37,AH37,AK37,AN37,AQ37) -> -2567.89 | AX37: =SUM(H37,K37,N37) -> 0 | AY37: =SUM(I37,L37,O37) -> -287.05429 | AZ37: =SUM(J37,M37,P37) -> -2567.89 | BA37: =SUM(Q37,T37,W37) -> 0 | BB37: =SUM(R37,U37,X37) -> -342.83325 | BC37: =SUM(S37,V37,Y37) -> 0 | BD37: =SUM(Z37,AC37,AF37) -> 0 | BE37: =SUM(AA37,AD37,AG37) -> -365.01288 | BF37: =SUM(AB37,AE37,AH37) -> 0 | BG37: =SUM(AI37,AL37,AO37) -> 0 | BH37: =SUM(AJ37,AM37,AP37) -> -367.29598 | BI37: =SUM(AK37,AN37,AQ37) -> 0 | BK37: =SUM(I37,L37,O37,R37,U37,X37,AA37,AD37,AG37,AJ37,AM37,AP37) -> -1362.1964 | BL37: =BK37-AV37 -> 0 | BM37: =SUM(J37,M37,P37,S37,V37) -> -2567.89 | BN37: =BM37-AT37 -> 0
A38: Eventos A&B | C38: Estim. Mensal | H38: 0 | K38: 0 | N38: 0 | Q38: 0 | T38: 0 | W38: 0 | Z38: 0 | AC38: 0 | AF38: 0 | AI38: 0 | AL38: 0 | AO38: 0 | AR38: =SUMIFS($H38:$AO38,$H$5:$AO$5,"<"&MONTH(TODAY()),$H$6:$AO$6,"REAL 25") -> 0 | AS38: =SUMIFS($I38:$AP38,$I$5:$AP$5,"<"&MONTH(TODAY()),$I$6:$AP$6,"ORÇADO ") -> 0 | AT38: =SUMIFS($J38:$AQ38,$J$5:$AQ$5,"<"&MONTH(TODAY()),$J$6:$AQ$6,"REAL 26") -> 0 | AV38: =SUM(I38,L38,O38,R38,U38,X38,AA38,AD38,AG38,AJ38,AM38,AP38) -> 0 | AW38: =SUM(J38,M38,P38,S38,V38,Y38,AB38,AE38,AH38,AK38,AN38,AQ38) -> 0 | AX38: =SUM(H38,K38,N38) -> 0 | AY38: =SUM(I38,L38,O38) -> 0 | AZ38: =SUM(J38,M38,P38) -> 0 | BA38: =SUM(Q38,T38,W38) -> 0 | BB38: =SUM(R38,U38,X38) -> 0 | BC38: =SUM(S38,V38,Y38) -> 0 | BD38: =SUM(Z38,AC38,AF38) -> 0 | BE38: =SUM(AA38,AD38,AG38) -> 0 | BF38: =SUM(AB38,AE38,AH38) -> 0 | BG38: =SUM(AI38,AL38,AO38) -> 0 | BH38: =SUM(AJ38,AM38,AP38) -> 0 | BI38: =SUM(AK38,AN38,AQ38) -> 0 | BK38: =SUM(I38,L38,O38,R38,U38,X38,AA38,AD38,AG38,AJ38,AM38,AP38) -> 0 | BL38: =BK38-AV38 -> 0 | BM38: =SUM(J38,M38,P38,S38,V38) -> 0 | BN38: =BM38-AT38 -> 0
A39: % sobre Receita Bruta | H39: -0.33057203 | I39: -0.289012 | J39: =IFERROR(J34/(J9+J10+J14+J18),0)+SUMIFS(Aut_Ajustes_Manuais!$G:$G,Aut_Ajustes_Manuais!$I:$I,DRE!H$4,Aut_Ajustes_Manuais!$F:$F,"% sobre Receita Bruta") -> -0.31409047 | K39: -0.34688053 | L39: -0.289012 | M39: =IFERROR(M34/(M9+M10+M14+M18),0)+SUMIFS(Aut_Ajustes_Manuais!$G:$G,Aut_Ajustes_Manuais!$I:$I,DRE!K$4,Aut_Ajustes_Manuais!$F:$F,"% sobre Receita Bruta") -> -0.33600782 | N39: -0.35007374 | O39: -0.289012 | P39: =IFERROR(P34/(P9+P10+P14+P18),0)+SUMIFS(Aut_Ajustes_Manuais!$G:$G,Aut_Ajustes_Manuais!$I:$I,DRE!N$4,Aut_Ajustes_Manuais!$F:$F,"% sobre Receita Bruta") -> -0.33153519 | Q39: -0.37303313 | R39: -0.289012 | S39: =IFERROR(S34/(S9+S10+S14+S18),0)+SUMIFS(Aut_Ajustes_Manuais!$G:$G,Aut_Ajustes_Manuais!$I:$I,DRE!Q$4,Aut_Ajustes_Manuais!$F:$F,"% sobre Receita Bruta") -> -0.33115053 | T39: -0.31808278 | U39: -0.289012 | V39: =IFERROR(V34/(V9+V10+V14+V18),0)+SUMIFS(Aut_Ajustes_Manuais!$G:$G,Aut_Ajustes_Manuais!$I:$I,DRE!T$4,Aut_Ajustes_Manuais!$F:$F,"% sobre Receita Bruta") -> -0.32374459 | W39: -0.32059534 | X39: -0.289012 | Y39: =IFERROR(Y34/(Y9+Y10+Y14+Y18),0)+SUMIFS(Aut_Ajustes_Manuais!$G:$G,Aut_Ajustes_Manuais!$I:$I,DRE!W$4,Aut_Ajustes_Manuais!$F:$F,"% sobre Receita Bruta") -> -0.50524986 | Z39: -0.31229993 | AA39: -0.289012 | AB39: =IFERROR(AB34/(AB9+AB10+AB14+AB18),0)+SUMIFS(Aut_Ajustes_Manuais!$G:$G,Aut_Ajustes_Manuais!$I:$I,DRE!Z$4,Aut_Ajustes_Manuais!$F:$F,"% sobre Receita Bruta") -> -0.12214306 | AC39: -0.29712315 | AD39: -0.289012 | AE39: =IFERROR(AE34/(AE9+AE10+AE14+AE18),0)+SUMIFS(Aut_Ajustes_Manuais!$G:$G,Aut_Ajustes_Manuais!$I:$I,DRE!AC$4,Aut_Ajustes_Manuais!$F:$F,"% sobre Receita Bruta") -> 0 | AF39: -0.30875885 | AG39: -0.289012 | AH39: =IFERROR(AH34/(AH9+AH10+AH14+AH18),0)+SUMIFS(Aut_Ajustes_Manuais!$G:$G,Aut_Ajustes_Manuais!$I:$I,DRE!AF$4,Aut_Ajustes_Manuais!$F:$F,"% sobre Receita Bruta") -> 0 | AI39: -0.26336469 | AJ39: -0.289012 | AK39: =IFERROR(AK34/(AK9+AK10+AK14+AK18),0)+SUMIFS(Aut_Ajustes_Manuais!$G:$G,Aut_Ajustes_Manuais!$I:$I,DRE!AI$4,Aut_Ajustes_Manuais!$F:$F,"% sobre Receita Bruta") -> 0 | AL39: -0.30986352 | AM39: -0.289012 | AN39: =IFERROR(AN34/(AN9+AN10+AN14+AN18),0)+SUMIFS(Aut_Ajustes_Manuais!$G:$G,Aut_Ajustes_Manuais!$I:$I,DRE!AL$4,Aut_Ajustes_Manuais!$F:$F,"% sobre Receita Bruta") -> 0 | AO39: -0.34032041 | AP39: -0.289012 | AQ39: =IFERROR(AQ34/(AQ9+AQ10+AQ14+AQ18),0)+SUMIFS(Aut_Ajustes_Manuais!$G:$G,Aut_Ajustes_Manuais!$I:$I,DRE!AO$4,Aut_Ajustes_Manuais!$F:$F,"% sobre Receita Bruta") -> 0 | AR39: =IFERROR(AR34/(AR9+AR10+AR14+AR18),0) -> -0.33849258 | AS39: =IFERROR(AS34/(AS9+AS10+AS14+AS18),0) -> -0.289012 | AT39: =IFERROR(AT34/(AT9+AT10+AT14+AT18),0) -> -0.35697902 | AU39: =IFERROR(AU34/(AU9+AU10+AU14+AU18),0) -> -0.32152983 | AV39: =IFERROR(AV34/(AV9+AV10+AV14+AV18),0) -> -0.289012 | AW39: =IFERROR(AW34/(AW9+AW10+AW14+AW18),0) -> -0.34862122 | AX39: =IFERROR(AX34/(AX9+AX10+AX14+AX18),0) -> -0.34211761 | AY39: =IFERROR(AY34/(AY9+AY10+AY14+AY18),0) -> -0.289012 | ... BI39: =IFERROR(BI34/(BI9+BI10+BI14+BI18),0) -> 0 | BK39: =SUM(I39,L39,O39,R39,U39,X39,AA39,AD39,AG39,AJ39,AM39,AP39) -> -3.468144 | BL39: =BK39-AV39 -> -3.179132 | BM39: =SUM(J39,M39,P39,S39,V39) -> -1.6365286 | BN39: =BM39-AT39 -> -1.2795496
A40: % sobre Receita Líquida | H40: -0.30972364 | I40: -0.23310847 | J40: =IFERROR(J34/J32,0)+SUMIFS(Aut_Ajustes_Manuais!$G:$G,Aut_Ajustes_Manuais!$I:$I,DRE!H$4,Aut_Ajustes_Manuais!$F:$F,"% sobre Receita Líquida") -> -0.28742291 | K40: -0.32607001 | L40: -0.23310847 | M40: =IFERROR(M34/M32,0)+SUMIFS(Aut_Ajustes_Manuais!$G:$G,Aut_Ajustes_Manuais!$I:$I,DRE!K$4,Aut_Ajustes_Manuais!$F:$F,"% sobre Receita Líquida") -> -0.30889084 | N40: -0.32772069 | O40: -0.23310847 | P40: =IFERROR(P34/P32,0)+SUMIFS(Aut_Ajustes_Manuais!$G:$G,Aut_Ajustes_Manuais!$I:$I,DRE!N$4,Aut_Ajustes_Manuais!$F:$F,"% sobre Receita Líquida") -> -0.3049 | Q40: -0.35104619 | R40: -0.23310847 | S40: =IFERROR(S34/S32,0)+SUMIFS(Aut_Ajustes_Manuais!$G:$G,Aut_Ajustes_Manuais!$I:$I,DRE!Q$4,Aut_Ajustes_Manuais!$F:$F,"% sobre Receita Líquida") -> -0.30741253 | T40: -0.29989499 | U40: -0.23310847 | V40: =IFERROR(V34/V32,0)+SUMIFS(Aut_Ajustes_Manuais!$G:$G,Aut_Ajustes_Manuais!$I:$I,DRE!T$4,Aut_Ajustes_Manuais!$F:$F,"% sobre Receita Líquida") -> -0.29917075 | W40: -0.29958673 | X40: -0.23310847 | Y40: =IFERROR(Y34/Y32,0)+SUMIFS(Aut_Ajustes_Manuais!$G:$G,Aut_Ajustes_Manuais!$I:$I,DRE!W$4,Aut_Ajustes_Manuais!$F:$F,"% sobre Receita Líquida") -> -0.47173738 | Z40: -0.29437943 | AA40: -0.23310847 | AB40: =IFERROR(AB34/AB32,0)+SUMIFS(Aut_Ajustes_Manuais!$G:$G,Aut_Ajustes_Manuais!$I:$I,DRE!Z$4,Aut_Ajustes_Manuais!$F:$F,"% sobre Receita Líquida") -> -0.11548284 | AC40: -0.276348 | AD40: -0.23310847 | AE40: =IFERROR(AE34/AE32,0)+SUMIFS(Aut_Ajustes_Manuais!$G:$G,Aut_Ajustes_Manuais!$I:$I,DRE!AC$4,Aut_Ajustes_Manuais!$F:$F,"% sobre Receita Líquida") -> 0 | AF40: -0.28824082 | AG40: -0.23310847 | AH40: =IFERROR(AH34/AH32,0)+SUMIFS(Aut_Ajustes_Manuais!$G:$G,Aut_Ajustes_Manuais!$I:$I,DRE!AF$4,Aut_Ajustes_Manuais!$F:$F,"% sobre Receita Líquida") -> 0 | AI40: -0.2451627 | AJ40: -0.23310847 | AK40: =IFERROR(AK34/AK32,0)+SUMIFS(Aut_Ajustes_Manuais!$G:$G,Aut_Ajustes_Manuais!$I:$I,DRE!AI$4,Aut_Ajustes_Manuais!$F:$F,"% sobre Receita Líquida") -> 0 | AL40: -0.28579247 | AM40: -0.23310847 | AN40: =IFERROR(AN34/AN32,0)+SUMIFS(Aut_Ajustes_Manuais!$G:$G,Aut_Ajustes_Manuais!$I:$I,DRE!AL$4,Aut_Ajustes_Manuais!$F:$F,"% sobre Receita Líquida") -> 0 | AO40: -0.31434159 | AP40: -0.23310847 | AQ40: =IFERROR(AQ34/AQ32,0)+SUMIFS(Aut_Ajustes_Manuais!$G:$G,Aut_Ajustes_Manuais!$I:$I,DRE!AO$4,Aut_Ajustes_Manuais!$F:$F,"% sobre Receita Líquida") -> 0 | AR40: =IFERROR(AR34/AR32,0) -> -0.31776826 | AS40: =IFERROR(AS34/AS32,0) -> -0.23310847 | AT40: =IFERROR(AT34/AT32,0) -> -0.32962938 | AU40: =IFERROR(AU34/AU32,0) -> -0.30029989 | AV40: =IFERROR(AV34/AV32,0) -> -0.23310847 | AW40: =IFERROR(AW34/AW32,0) -> -0.32217976 | AX40: =IFERROR(AX34/AX32,0) -> -0.32079232 | AY40: =IFERROR(AY34/AY32,0) -> -0.23310847 | ... BI40: =IFERROR(BI34/BI32,0) -> 0 | BK40: =SUM(I40,L40,O40,R40,U40,X40,AA40,AD40,AG40,AJ40,AM40,AP40) -> -2.7973017 | BL40: =BK40-AV40 -> -2.5641932 | BM40: =SUM(J40,M40,P40,S40,V40) -> -1.507797 | BN40: =BM40-AT40 -> -1.1781677
BK41: =SUM(I41,L41,O41,R41,U41,X41,AA41,AD41,AG41,AJ41,AM41,AP41) -> 0 | BL41: =BK41-AV41 -> 0 | BM41: =SUM(J41,M41,P41,S41,V41) -> 0 | BN41: =BM41-AT41 -> 0
A42: (-) Custos Artístico Geral | C42: Premissas | D42: Valores | E42: % Incid | H42: -1400 | I42: =SUM(I43,I49) -> -8400 | J42: =SUM(J43,J49)+SUMIFS(Aut_Ajustes_Manuais!$G:$G,Aut_Ajustes_Manuais!$I:$I,DRE!H$4,Aut_Ajustes_Manuais!$F:$F,"(-) Custos Artístico Geral") -> -5600 | K42: -1400 | L42: =SUM(L43,L49) -> -7000 | M42: =SUM(M43,M49)+SUMIFS(Aut_Ajustes_Manuais!$G:$G,Aut_Ajustes_Manuais!$I:$I,DRE!K$4,Aut_Ajustes_Manuais!$F:$F,"(-) Custos Artístico Geral") -> -7000 | N42: -4793.9853 | O42: =SUM(O43,O49) -> -7000 | P42: =SUM(P43,P49)+SUMIFS(Aut_Ajustes_Manuais!$G:$G,Aut_Ajustes_Manuais!$I:$I,DRE!N$4,Aut_Ajustes_Manuais!$F:$F,"(-) Custos Artístico Geral") -> -4200 | Q42: -3700.607 | R42: =SUM(R43,R49) -> -7000 | S42: =SUM(S43,S49)+SUMIFS(Aut_Ajustes_Manuais!$G:$G,Aut_Ajustes_Manuais!$I:$I,DRE!Q$4,Aut_Ajustes_Manuais!$F:$F,"(-) Custos Artístico Geral") -> -7000 | T42: -6198.1338 | U42: =SUM(U43,U49) -> -8400 | V42: =SUM(V43,V49)+SUMIFS(Aut_Ajustes_Manuais!$G:$G,Aut_Ajustes_Manuais!$I:$I,DRE!T$4,Aut_Ajustes_Manuais!$F:$F,"(-) Custos Artístico Geral") -> -8400 | W42: -3600 | X42: =SUM(X43,X49) -> -7000 | Y42: =SUM(Y43,Y49)+SUMIFS(Aut_Ajustes_Manuais!$G:$G,Aut_Ajustes_Manuais!$I:$I,DRE!W$4,Aut_Ajustes_Manuais!$F:$F,"(-) Custos Artístico Geral") -> -7300 | Z42: -3600 | AA42: =SUM(AA43,AA49) -> -7000 | AB42: =SUM(AB43,AB49)+SUMIFS(Aut_Ajustes_Manuais!$G:$G,Aut_Ajustes_Manuais!$I:$I,DRE!Z$4,Aut_Ajustes_Manuais!$F:$F,"(-) Custos Artístico Geral") -> -2800 | AC42: -7211.261 | AD42: =SUM(AD43,AD49) -> -8400 | AE42: =SUM(AE43,AE49)+SUMIFS(Aut_Ajustes_Manuais!$G:$G,Aut_Ajustes_Manuais!$I:$I,DRE!AC$4,Aut_Ajustes_Manuais!$F:$F,"(-) Custos Artístico Geral") -> 0 | AF42: -3800 | AG42: =SUM(AG43,AG49) -> -7000 | AH42: =SUM(AH43,AH49)+SUMIFS(Aut_Ajustes_Manuais!$G:$G,Aut_Ajustes_Manuais!$I:$I,DRE!AF$4,Aut_Ajustes_Manuais!$F:$F,"(-) Custos Artístico Geral") -> 0 | AI42: -1400 | AJ42: =SUM(AJ43,AJ49) -> -8400 | AK42: =SUM(AK43,AK49)+SUMIFS(Aut_Ajustes_Manuais!$G:$G,Aut_Ajustes_Manuais!$I:$I,DRE!AI$4,Aut_Ajustes_Manuais!$F:$F,"(-) Custos Artístico Geral") -> 0 | AL42: -13400 | AM42: =SUM(AM43,AM49) -> -7000 | AN42: =SUM(AN43,AN49)+SUMIFS(Aut_Ajustes_Manuais!$G:$G,Aut_Ajustes_Manuais!$I:$I,DRE!AL$4,Aut_Ajustes_Manuais!$F:$F,"(-) Custos Artístico Geral") -> 0 | AO42: -9800 | AP42: =SUM(AP43,AP49) -> -7000 | AQ42: =SUM(AQ43,AQ49)+SUMIFS(Aut_Ajustes_Manuais!$G:$G,Aut_Ajustes_Manuais!$I:$I,DRE!AO$4,Aut_Ajustes_Manuais!$F:$F,"(-) Custos Artístico Geral") -> 0 | AR42: =SUM(AR43,AR49) -> -21092.726 | AS42: =SUM(AS43,AS49) -> -44800 | AT42: =SUM(AT43,AT49) -> -39500 | AU42: =SUM(AU43,AU49) -> -60303.987 | AV42: =SUM(AV43,AV49) -> -89600 | AW42: =SUM(AW43,AW49) -> -42300 | AX42: =SUM(AX43,AX49) -> -7593.9853 | AY42: =SUM(AY43,AY49) -> -22400 | ... BI42: =SUM(BI43,BI49) -> 0 | BK42: =SUM(I42,L42,O42,R42,U42,X42,AA42,AD42,AG42,AJ42,AM42,AP42) -> -89600 | BL42: =BK42-AV42 -> 0 | BM42: =SUM(J42,M42,P42,S42,V42) -> -32200 | BN42: =BM42-AT42 -> 7300
A43: Custos Artístico | H43: -1400 | I43: -8400 | J43: =SUM(J44:J48)+SUMIFS(Aut_Ajustes_Manuais!$G:$G,Aut_Ajustes_Manuais!$I:$I,DRE!H$4,Aut_Ajustes_Manuais!$F:$F,"Custos Artístico") -> -5600 | K43: -1400 | L43: -7000 | M43: =SUM(M44:M48)+SUMIFS(Aut_Ajustes_Manuais!$G:$G,Aut_Ajustes_Manuais!$I:$I,DRE!K$4,Aut_Ajustes_Manuais!$F:$F,"Custos Artístico") -> -7000 | N43: -4793.9853 | O43: -7000 | P43: =SUM(P44:P48)+SUMIFS(Aut_Ajustes_Manuais!$G:$G,Aut_Ajustes_Manuais!$I:$I,DRE!N$4,Aut_Ajustes_Manuais!$F:$F,"Custos Artístico") -> -4200 | Q43: -3700.607 | R43: -7000 | S43: =SUM(S44:S48)+SUMIFS(Aut_Ajustes_Manuais!$G:$G,Aut_Ajustes_Manuais!$I:$I,DRE!Q$4,Aut_Ajustes_Manuais!$F:$F,"Custos Artístico") -> -7000 | T43: -6198.1338 | U43: -8400 | V43: =SUM(V44:V48)+SUMIFS(Aut_Ajustes_Manuais!$G:$G,Aut_Ajustes_Manuais!$I:$I,DRE!T$4,Aut_Ajustes_Manuais!$F:$F,"Custos Artístico") -> -8400 | W43: -3600 | X43: -7000 | Y43: =SUM(Y44:Y48)+SUMIFS(Aut_Ajustes_Manuais!$G:$G,Aut_Ajustes_Manuais!$I:$I,DRE!W$4,Aut_Ajustes_Manuais!$F:$F,"Custos Artístico") -> -7300 | Z43: -3600 | AA43: -7000 | AB43: =SUM(AB44:AB48)+SUMIFS(Aut_Ajustes_Manuais!$G:$G,Aut_Ajustes_Manuais!$I:$I,DRE!Z$4,Aut_Ajustes_Manuais!$F:$F,"Custos Artístico") -> -2800 | AC43: -7211.261 | AD43: -8400 | AE43: =SUM(AE44:AE48)+SUMIFS(Aut_Ajustes_Manuais!$G:$G,Aut_Ajustes_Manuais!$I:$I,DRE!AC$4,Aut_Ajustes_Manuais!$F:$F,"Custos Artístico") -> 0 | AF43: -3800 | AG43: -7000 | AH43: =SUM(AH44:AH48)+SUMIFS(Aut_Ajustes_Manuais!$G:$G,Aut_Ajustes_Manuais!$I:$I,DRE!AF$4,Aut_Ajustes_Manuais!$F:$F,"Custos Artístico") -> 0 | AI43: -1400 | AJ43: -8400 | AK43: =SUM(AK44:AK48)+SUMIFS(Aut_Ajustes_Manuais!$G:$G,Aut_Ajustes_Manuais!$I:$I,DRE!AI$4,Aut_Ajustes_Manuais!$F:$F,"Custos Artístico") -> 0 | AL43: -13400 | AM43: -7000 | AN43: =SUM(AN44:AN48)+SUMIFS(Aut_Ajustes_Manuais!$G:$G,Aut_Ajustes_Manuais!$I:$I,DRE!AL$4,Aut_Ajustes_Manuais!$F:$F,"Custos Artístico") -> 0 | AO43: -9800 | AP43: -7000 | AQ43: =SUM(AQ44:AQ48)+SUMIFS(Aut_Ajustes_Manuais!$G:$G,Aut_Ajustes_Manuais!$I:$I,DRE!AO$4,Aut_Ajustes_Manuais!$F:$F,"Custos Artístico") -> 0 | AR43: =SUMIFS($H43:$AO43,$H$5:$AO$5,"<"&MONTH(TODAY()),$H$6:$AO$6,"REAL 25") -> -21092.726 | AS43: =SUMIFS($I43:$AP43,$I$5:$AP$5,"<"&MONTH(TODAY()),$I$6:$AP$6,"ORÇADO ") -> -44800 | AT43: =SUMIFS($J43:$AQ43,$J$5:$AQ$5,"<"&MONTH(TODAY()),$J$6:$AQ$6,"REAL 26") -> -39500 | AU43: =SUM(AU44:AU48) -> -60303.987 | AV43: =SUM(AV44:AV48) -> -89600 | AW43: =SUM(AW44:AW48) -> -42300 | AX43: =SUM(AX44:AX48) -> -7593.9853 | AY43: =SUM(AY44:AY48) -> -22400 | AZ43: =SUM(AZ44:AZ48) -> -16800 | BA43: =SUM(BA44:BA48) -> -13498.741 | BB43: =SUM(BB44:BB48) -> -22400 | ... BI43: =SUM(BI44:BI48) -> 0 | BK43: =SUM(I43,L43,O43,R43,U43,X43,AA43,AD43,AG43,AJ43,AM43,AP43) -> -89600 | BL43: =BK43-AV43 -> 0 | BM43: =SUM(J43,M43,P43,S43,V43) -> -32200 | BN43: =BM43-AT43 -> 7300
A44: Cachê de Músicos e Artistas | C44: Estim. Mensal | E44: 0.0067 | H44: -1400 | I44: -7000 | J44: =SUMIFS(Aut_BlueMe_Sem_Pedido!$J:$J,Aut_BlueMe_Sem_Pedido!$Q:$Q,DRE!H$4,Aut_BlueMe_Sem_Pedido!$H:$H,DRE!$A44)+SUMIFS(Aut_Ajustes_Manuais!$G:$G,Aut_Ajustes_Manuais!$I:$I,DRE!H$4,Aut_Ajustes_Manuais!$F:$F,"Cachê de Músicos e Artistas") -> -5600 | K44: -1400 | L44: -5600 | M44: =SUMIFS(Aut_BlueMe_Sem_Pedido!$J:$J,Aut_BlueMe_Sem_Pedido!$Q:$Q,DRE!K$4,Aut_BlueMe_Sem_Pedido!$H:$H,DRE!$A44)+SUMIFS(Aut_Ajustes_Manuais!$G:$G,Aut_Ajustes_Manuais!$I:$I,DRE!K$4,Aut_Ajustes_Manuais!$F:$F,"Cachê de Músicos e Artistas") -> -7000 | N44: -4650 | O44: -5600 | P44: =SUMIFS(Aut_BlueMe_Sem_Pedido!$J:$J,Aut_BlueMe_Sem_Pedido!$Q:$Q,DRE!N$4,Aut_BlueMe_Sem_Pedido!$H:$H,DRE!$A44)+SUMIFS(Aut_Ajustes_Manuais!$G:$G,Aut_Ajustes_Manuais!$I:$I,DRE!N$4,Aut_Ajustes_Manuais!$F:$F,"Cachê de Músicos e Artistas") -> -4200 | Q44: -3600 | R44: -5600 | S44: =SUMIFS(Aut_BlueMe_Sem_Pedido!$J:$J,Aut_BlueMe_Sem_Pedido!$Q:$Q,DRE!Q$4,Aut_BlueMe_Sem_Pedido!$H:$H,DRE!$A44)+SUMIFS(Aut_Ajustes_Manuais!$G:$G,Aut_Ajustes_Manuais!$I:$I,DRE!Q$4,Aut_Ajustes_Manuais!$F:$F,"Cachê de Músicos e Artistas") -> -7000 | T44: -6000 | U44: -7000 | V44: =SUMIFS(Aut_BlueMe_Sem_Pedido!$J:$J,Aut_BlueMe_Sem_Pedido!$Q:$Q,DRE!T$4,Aut_BlueMe_Sem_Pedido!$H:$H,DRE!$A44)+SUMIFS(Aut_Ajustes_Manuais!$G:$G,Aut_Ajustes_Manuais!$I:$I,DRE!T$4,Aut_Ajustes_Manuais!$F:$F,"Cachê de Músicos e Artistas") -> -8400 | W44: -3600 | X44: -5600 | Y44: =SUMIFS(Aut_BlueMe_Sem_Pedido!$J:$J,Aut_BlueMe_Sem_Pedido!$Q:$Q,DRE!W$4,Aut_BlueMe_Sem_Pedido!$H:$H,DRE!$A44)+SUMIFS(Aut_Ajustes_Manuais!$G:$G,Aut_Ajustes_Manuais!$I:$I,DRE!W$4,Aut_Ajustes_Manuais!$F:$F,"Cachê de Músicos e Artistas") -> -7300 | Z44: -3600 | AA44: -5600 | AB44: =SUMIFS(Aut_BlueMe_Sem_Pedido!$J:$J,Aut_BlueMe_Sem_Pedido!$Q:$Q,DRE!Z$4,Aut_BlueMe_Sem_Pedido!$H:$H,DRE!$A44)+SUMIFS(Aut_Ajustes_Manuais!$G:$G,Aut_Ajustes_Manuais!$I:$I,DRE!Z$4,Aut_Ajustes_Manuais!$F:$F,"Cachê de Músicos e Artistas") -> -2800 | AC44: -7200 | AD44: -7000 | AE44: =SUMIFS(Aut_BlueMe_Sem_Pedido!$J:$J,Aut_BlueMe_Sem_Pedido!$Q:$Q,DRE!AC$4,Aut_BlueMe_Sem_Pedido!$H:$H,DRE!$A44)+SUMIFS(Aut_Ajustes_Manuais!$G:$G,Aut_Ajustes_Manuais!$I:$I,DRE!AC$4,Aut_Ajustes_Manuais!$F:$F,"Cachê de Músicos e Artistas") -> 0 | AF44: -3800 | AG44: -5600 | AH44: =SUMIFS(Aut_BlueMe_Sem_Pedido!$J:$J,Aut_BlueMe_Sem_Pedido!$Q:$Q,DRE!AF$4,Aut_BlueMe_Sem_Pedido!$H:$H,DRE!$A44)+SUMIFS(Aut_Ajustes_Manuais!$G:$G,Aut_Ajustes_Manuais!$I:$I,DRE!AF$4,Aut_Ajustes_Manuais!$F:$F,"Cachê de Músicos e Artistas") -> 0 | AI44: -1400 | AJ44: -7000 | AK44: =SUMIFS(Aut_BlueMe_Sem_Pedido!$J:$J,Aut_BlueMe_Sem_Pedido!$Q:$Q,DRE!AI$4,Aut_BlueMe_Sem_Pedido!$H:$H,DRE!$A44)+SUMIFS(Aut_Ajustes_Manuais!$G:$G,Aut_Ajustes_Manuais!$I:$I,DRE!AI$4,Aut_Ajustes_Manuais!$F:$F,"Cachê de Músicos e Artistas") -> 0 | AL44: -13400 | AM44: -5600 | AN44: =SUMIFS(Aut_BlueMe_Sem_Pedido!$J:$J,Aut_BlueMe_Sem_Pedido!$Q:$Q,DRE!AL$4,Aut_BlueMe_Sem_Pedido!$H:$H,DRE!$A44)+SUMIFS(Aut_Ajustes_Manuais!$G:$G,Aut_Ajustes_Manuais!$I:$I,DRE!AL$4,Aut_Ajustes_Manuais!$F:$F,"Cachê de Músicos e Artistas") -> 0 | AO44: -9800 | AP44: -5600 | AQ44: =SUMIFS(Aut_BlueMe_Sem_Pedido!$J:$J,Aut_BlueMe_Sem_Pedido!$Q:$Q,DRE!AO$4,Aut_BlueMe_Sem_Pedido!$H:$H,DRE!$A44)+SUMIFS(Aut_Ajustes_Manuais!$G:$G,Aut_Ajustes_Manuais!$I:$I,DRE!AO$4,Aut_Ajustes_Manuais!$F:$F,"Cachê de Músicos e Artistas") -> 0 | AR44: =SUMIFS($H44:$AO44,$H$5:$AO$5,"<"&MONTH(TODAY()),$H$6:$AO$6,"REAL 25") -> -20650 | AS44: =SUMIFS($I44:$AP44,$I$5:$AP$5,"<"&MONTH(TODAY()),$I$6:$AP$6,"ORÇADO ") -> -36400 | AT44: =SUMIFS($J44:$AQ44,$J$5:$AQ$5,"<"&MONTH(TODAY()),$J$6:$AQ$6,"REAL 26") -> -39500 | AU44: =SUM(H44,K44,N44,Q44,T44,W44,Z44,AC44,AF44,AI44,AL44,AO44) -> -59850 | AV44: =SUM(I44,L44,O44,R44,U44,X44,AA44,AD44,AG44,AJ44,AM44,AP44) -> -72800 | AW44: =SUM(J44,M44,P44,S44,V44,Y44,AB44,AE44,AH44,AK44,AN44,AQ44) -> -42300 | AX44: =SUM(H44,K44,N44) -> -7450 | AY44: =SUM(I44,L44,O44) -> -18200 | AZ44: =SUM(J44,M44,P44) -> -16800 | BA44: =SUM(Q44,T44,W44) -> -13200 | BB44: =SUM(R44,U44,X44) -> -18200 | BC44: =SUM(S44,V44,Y44) -> -22700 | BD44: =SUM(Z44,AC44,AF44) -> -14600 | BE44: =SUM(AA44,AD44,AG44) -> -18200 | BF44: =SUM(AB44,AE44,AH44) -> -2800 | BG44: =SUM(AI44,AL44,AO44) -> -24600 | BH44: =SUM(AJ44,AM44,AP44) -> -18200 | BI44: =SUM(AK44,AN44,AQ44) -> 0 | BK44: =SUM(I44,L44,O44,R44,U44,X44,AA44,AD44,AG44,AJ44,AM44,AP44) -> -72800 | BL44: =BK44-AV44 -> 0 | BM44: =SUM(J44,M44,P44,S44,V44) -> -32200 | BN44: =BM44-AT44 -> 7300
A45: Alimentação e Transporte | C45: Estim. Mensal | E45: 0.0067 | H45: 0 | I45: -1400 | J45: =SUMIFS(Aut_BlueMe_Sem_Pedido!$J:$J,Aut_BlueMe_Sem_Pedido!$Q:$Q,DRE!H$4,Aut_BlueMe_Sem_Pedido!$H:$H,DRE!$A45)-SUMIFS(Aut_Descontos!$G:$G,Aut_Descontos!$H:$H,DRE!$A45,Aut_Descontos!$L:$L,DRE!H$4)+SUMIFS(Aut_Ajustes_Manuais!$G:$G,Aut_Ajustes_Manuais!$I:$I,DRE!H$4,Aut_Ajustes_Manuais!$F:$F,"Alimentação e Transporte") -> 0 | K45: 0 | L45: -1400 | M45: =SUMIFS(Aut_BlueMe_Sem_Pedido!$J:$J,Aut_BlueMe_Sem_Pedido!$Q:$Q,DRE!K$4,Aut_BlueMe_Sem_Pedido!$H:$H,DRE!$A45)-SUMIFS(Aut_Descontos!$G:$G,Aut_Descontos!$H:$H,DRE!$A45,Aut_Descontos!$L:$L,DRE!K$4)+SUMIFS(Aut_Ajustes_Manuais!$G:$G,Aut_Ajustes_Manuais!$I:$I,DRE!K$4,Aut_Ajustes_Manuais!$F:$F,"Alimentação e Transporte") -> 0 | N45: -143.98533 | O45: -1400 | P45: =SUMIFS(Aut_BlueMe_Sem_Pedido!$J:$J,Aut_BlueMe_Sem_Pedido!$Q:$Q,DRE!N$4,Aut_BlueMe_Sem_Pedido!$H:$H,DRE!$A45)-SUMIFS(Aut_Descontos!$G:$G,Aut_Descontos!$H:$H,DRE!$A45,Aut_Descontos!$L:$L,DRE!N$4)+SUMIFS(Aut_Ajustes_Manuais!$G:$G,Aut_Ajustes_Manuais!$I:$I,DRE!N$4,Aut_Ajustes_Manuais!$F:$F,"Alimentação e Transporte") -> 0 | Q45: -100.60704 | R45: -1400 | S45: =SUMIFS(Aut_BlueMe_Sem_Pedido!$J:$J,Aut_BlueMe_Sem_Pedido!$Q:$Q,DRE!Q$4,Aut_BlueMe_Sem_Pedido!$H:$H,DRE!$A45)-SUMIFS(Aut_Descontos!$G:$G,Aut_Descontos!$H:$H,DRE!$A45,Aut_Descontos!$L:$L,DRE!Q$4)+SUMIFS(Aut_Ajustes_Manuais!$G:$G,Aut_Ajustes_Manuais!$I:$I,DRE!Q$4,Aut_Ajustes_Manuais!$F:$F,"Alimentação e Transporte") -> 0 | T45: -198.13376 | U45: -1400 | V45: =SUMIFS(Aut_BlueMe_Sem_Pedido!$J:$J,Aut_BlueMe_Sem_Pedido!$Q:$Q,DRE!T$4,Aut_BlueMe_Sem_Pedido!$H:$H,DRE!$A45)-SUMIFS(Aut_Descontos!$G:$G,Aut_Descontos!$H:$H,DRE!$A45,Aut_Descontos!$L:$L,DRE!T$4)+SUMIFS(Aut_Ajustes_Manuais!$G:$G,Aut_Ajustes_Manuais!$I:$I,DRE!T$4,Aut_Ajustes_Manuais!$F:$F,"Alimentação e Transporte") -> 0 | W45: 0 | X45: -1400 | Y45: =SUMIFS(Aut_BlueMe_Sem_Pedido!$J:$J,Aut_BlueMe_Sem_Pedido!$Q:$Q,DRE!W$4,Aut_BlueMe_Sem_Pedido!$H:$H,DRE!$A45)-SUMIFS(Aut_Descontos!$G:$G,Aut_Descontos!$H:$H,DRE!$A45,Aut_Descontos!$L:$L,DRE!W$4)+SUMIFS(Aut_Ajustes_Manuais!$G:$G,Aut_Ajustes_Manuais!$I:$I,DRE!W$4,Aut_Ajustes_Manuais!$F:$F,"Alimentação e Transporte") -> 0 | Z45: 0 | AA45: -1400 | AB45: =SUMIFS(Aut_BlueMe_Sem_Pedido!$J:$J,Aut_BlueMe_Sem_Pedido!$Q:$Q,DRE!Z$4,Aut_BlueMe_Sem_Pedido!$H:$H,DRE!$A45)-SUMIFS(Aut_Descontos!$G:$G,Aut_Descontos!$H:$H,DRE!$A45,Aut_Descontos!$L:$L,DRE!Z$4)+SUMIFS(Aut_Ajustes_Manuais!$G:$G,Aut_Ajustes_Manuais!$I:$I,DRE!Z$4,Aut_Ajustes_Manuais!$F:$F,"Alimentação e Transporte") -> 0 | AC45: -11.260967 | AD45: -1400 | AE45: =SUMIFS(Aut_BlueMe_Sem_Pedido!$J:$J,Aut_BlueMe_Sem_Pedido!$Q:$Q,DRE!AC$4,Aut_BlueMe_Sem_Pedido!$H:$H,DRE!$A45)-SUMIFS(Aut_Descontos!$G:$G,Aut_Descontos!$H:$H,DRE!$A45,Aut_Descontos!$L:$L,DRE!AC$4)+SUMIFS(Aut_Ajustes_Manuais!$G:$G,Aut_Ajustes_Manuais!$I:$I,DRE!AC$4,Aut_Ajustes_Manuais!$F:$F,"Alimentação e Transporte") -> 0 | AF45: 0 | AG45: -1400 | AH45: =SUMIFS(Aut_BlueMe_Sem_Pedido!$J:$J,Aut_BlueMe_Sem_Pedido!$Q:$Q,DRE!AF$4,Aut_BlueMe_Sem_Pedido!$H:$H,DRE!$A45)-SUMIFS(Aut_Descontos!$G:$G,Aut_Descontos!$H:$H,DRE!$A45,Aut_Descontos!$L:$L,DRE!AF$4)+SUMIFS(Aut_Ajustes_Manuais!$G:$G,Aut_Ajustes_Manuais!$I:$I,DRE!AF$4,Aut_Ajustes_Manuais!$F:$F,"Alimentação e Transporte") -> 0 | AI45: 0 | AJ45: -1400 | AK45: =SUMIFS(Aut_BlueMe_Sem_Pedido!$J:$J,Aut_BlueMe_Sem_Pedido!$Q:$Q,DRE!AI$4,Aut_BlueMe_Sem_Pedido!$H:$H,DRE!$A45)-SUMIFS(Aut_Descontos!$G:$G,Aut_Descontos!$H:$H,DRE!$A45,Aut_Descontos!$L:$L,DRE!AI$4)+SUMIFS(Aut_Ajustes_Manuais!$G:$G,Aut_Ajustes_Manuais!$I:$I,DRE!AI$4,Aut_Ajustes_Manuais!$F:$F,"Alimentação e Transporte") -> 0 | AL45: 0 | AM45: -1400 | AN45: =SUMIFS(Aut_BlueMe_Sem_Pedido!$J:$J,Aut_BlueMe_Sem_Pedido!$Q:$Q,DRE!AL$4,Aut_BlueMe_Sem_Pedido!$H:$H,DRE!$A45)-SUMIFS(Aut_Descontos!$G:$G,Aut_Descontos!$H:$H,DRE!$A45,Aut_Descontos!$L:$L,DRE!AL$4)+SUMIFS(Aut_Ajustes_Manuais!$G:$G,Aut_Ajustes_Manuais!$I:$I,DRE!AL$4,Aut_Ajustes_Manuais!$F:$F,"Alimentação e Transporte") -> 0 | AO45: 0 | AP45: -1400 | AQ45: =SUMIFS(Aut_BlueMe_Sem_Pedido!$J:$J,Aut_BlueMe_Sem_Pedido!$Q:$Q,DRE!AO$4,Aut_BlueMe_Sem_Pedido!$H:$H,DRE!$A45)-SUMIFS(Aut_Descontos!$G:$G,Aut_Descontos!$H:$H,DRE!$A45,Aut_Descontos!$L:$L,DRE!AO$4)+SUMIFS(Aut_Ajustes_Manuais!$G:$G,Aut_Ajustes_Manuais!$I:$I,DRE!AO$4,Aut_Ajustes_Manuais!$F:$F,"Alimentação e Transporte") -> 0 | AR45: =SUMIFS($H45:$AO45,$H$5:$AO$5,"<"&MONTH(TODAY()),$H$6:$AO$6,"REAL 25") -> -442.72613 | AS45: =SUMIFS($I45:$AP45,$I$5:$AP$5,"<"&MONTH(TODAY()),$I$6:$AP$6,"ORÇADO ") -> -8400 | AT45: =SUMIFS($J45:$AQ45,$J$5:$AQ$5,"<"&MONTH(TODAY()),$J$6:$AQ$6,"REAL 26") -> 0 | AU45: =SUM(H45,K45,N45,Q45,T45,W45,Z45,AC45,AF45,AI45,AL45,AO45) -> -453.98709 | AV45: =SUM(I45,L45,O45,R45,U45,X45,AA45,AD45,AG45,AJ45,AM45,AP45) -> -16800 | AW45: =SUM(J45,M45,P45,S45,V45,Y45,AB45,AE45,AH45,AK45,AN45,AQ45) -> 0 | AX45: =SUM(H45,K45,N45) -> -143.98533 | AY45: =SUM(I45,L45,O45) -> -4200 | AZ45: =SUM(J45,M45,P45) -> 0 | BA45: =SUM(Q45,T45,W45) -> -298.7408 | BB45: =SUM(R45,U45,X45) -> -4200 | BC45: =SUM(S45,V45,Y45) -> 0 | BD45: =SUM(Z45,AC45,AF45) -> -11.260967 | BE45: =SUM(AA45,AD45,AG45) -> -4200 | BF45: =SUM(AB45,AE45,AH45) -> 0 | BG45: =SUM(AI45,AL45,AO45) -> 0 | BH45: =SUM(AJ45,AM45,AP45) -> -4200 | BI45: =SUM(AK45,AN45,AQ45) -> 0 | BK45: =SUM(I45,L45,O45,R45,U45,X45,AA45,AD45,AG45,AJ45,AM45,AP45) -> -16800 | BL45: =BK45-AV45 -> 0 | BM45: =SUM(J45,M45,P45,S45,V45) -> 0 | BN45: =BM45-AT45 -> 0
A46: Viagens e Estadias | C46: Estim. Mensal | H46: 0 | I46: 0 | J46: =SUMIFS(Aut_BlueMe_Sem_Pedido!$J:$J,Aut_BlueMe_Sem_Pedido!$Q:$Q,DRE!H$4,Aut_BlueMe_Sem_Pedido!$H:$H,DRE!$A46)+SUMIFS(Aut_Ajustes_Manuais!$G:$G,Aut_Ajustes_Manuais!$I:$I,DRE!H$4,Aut_Ajustes_Manuais!$F:$F,"Viagens e Estadias") -> 0 | K46: 0 | L46: 0 | M46: =SUMIFS(Aut_BlueMe_Sem_Pedido!$J:$J,Aut_BlueMe_Sem_Pedido!$Q:$Q,DRE!K$4,Aut_BlueMe_Sem_Pedido!$H:$H,DRE!$A46)+SUMIFS(Aut_Ajustes_Manuais!$G:$G,Aut_Ajustes_Manuais!$I:$I,DRE!K$4,Aut_Ajustes_Manuais!$F:$F,"Viagens e Estadias") -> 0 | N46: 0 | O46: 0 | P46: =SUMIFS(Aut_BlueMe_Sem_Pedido!$J:$J,Aut_BlueMe_Sem_Pedido!$Q:$Q,DRE!N$4,Aut_BlueMe_Sem_Pedido!$H:$H,DRE!$A46)+SUMIFS(Aut_Ajustes_Manuais!$G:$G,Aut_Ajustes_Manuais!$I:$I,DRE!N$4,Aut_Ajustes_Manuais!$F:$F,"Viagens e Estadias") -> 0 | Q46: 0 | R46: 0 | S46: =SUMIFS(Aut_BlueMe_Sem_Pedido!$J:$J,Aut_BlueMe_Sem_Pedido!$Q:$Q,DRE!Q$4,Aut_BlueMe_Sem_Pedido!$H:$H,DRE!$A46)+SUMIFS(Aut_Ajustes_Manuais!$G:$G,Aut_Ajustes_Manuais!$I:$I,DRE!Q$4,Aut_Ajustes_Manuais!$F:$F,"Viagens e Estadias") -> 0 | T46: 0 | U46: 0 | V46: =SUMIFS(Aut_BlueMe_Sem_Pedido!$J:$J,Aut_BlueMe_Sem_Pedido!$Q:$Q,DRE!T$4,Aut_BlueMe_Sem_Pedido!$H:$H,DRE!$A46)+SUMIFS(Aut_Ajustes_Manuais!$G:$G,Aut_Ajustes_Manuais!$I:$I,DRE!T$4,Aut_Ajustes_Manuais!$F:$F,"Viagens e Estadias") -> 0 | W46: 0 | X46: 0 | Y46: =SUMIFS(Aut_BlueMe_Sem_Pedido!$J:$J,Aut_BlueMe_Sem_Pedido!$Q:$Q,DRE!W$4,Aut_BlueMe_Sem_Pedido!$H:$H,DRE!$A46)+SUMIFS(Aut_Ajustes_Manuais!$G:$G,Aut_Ajustes_Manuais!$I:$I,DRE!W$4,Aut_Ajustes_Manuais!$F:$F,"Viagens e Estadias") -> 0 | Z46: 0 | AA46: 0 | AB46: =SUMIFS(Aut_BlueMe_Sem_Pedido!$J:$J,Aut_BlueMe_Sem_Pedido!$Q:$Q,DRE!Z$4,Aut_BlueMe_Sem_Pedido!$H:$H,DRE!$A46)+SUMIFS(Aut_Ajustes_Manuais!$G:$G,Aut_Ajustes_Manuais!$I:$I,DRE!Z$4,Aut_Ajustes_Manuais!$F:$F,"Viagens e Estadias") -> 0 | AC46: 0 | AD46: 0 | AE46: =SUMIFS(Aut_BlueMe_Sem_Pedido!$J:$J,Aut_BlueMe_Sem_Pedido!$Q:$Q,DRE!AC$4,Aut_BlueMe_Sem_Pedido!$H:$H,DRE!$A46)+SUMIFS(Aut_Ajustes_Manuais!$G:$G,Aut_Ajustes_Manuais!$I:$I,DRE!AC$4,Aut_Ajustes_Manuais!$F:$F,"Viagens e Estadias") -> 0 | AF46: 0 | AG46: 0 | AH46: =SUMIFS(Aut_BlueMe_Sem_Pedido!$J:$J,Aut_BlueMe_Sem_Pedido!$Q:$Q,DRE!AF$4,Aut_BlueMe_Sem_Pedido!$H:$H,DRE!$A46)+SUMIFS(Aut_Ajustes_Manuais!$G:$G,Aut_Ajustes_Manuais!$I:$I,DRE!AF$4,Aut_Ajustes_Manuais!$F:$F,"Viagens e Estadias") -> 0 | AI46: 0 | AJ46: 0 | AK46: =SUMIFS(Aut_BlueMe_Sem_Pedido!$J:$J,Aut_BlueMe_Sem_Pedido!$Q:$Q,DRE!AI$4,Aut_BlueMe_Sem_Pedido!$H:$H,DRE!$A46)+SUMIFS(Aut_Ajustes_Manuais!$G:$G,Aut_Ajustes_Manuais!$I:$I,DRE!AI$4,Aut_Ajustes_Manuais!$F:$F,"Viagens e Estadias") -> 0 | AL46: 0 | AM46: 0 | AN46: =SUMIFS(Aut_BlueMe_Sem_Pedido!$J:$J,Aut_BlueMe_Sem_Pedido!$Q:$Q,DRE!AL$4,Aut_BlueMe_Sem_Pedido!$H:$H,DRE!$A46)+SUMIFS(Aut_Ajustes_Manuais!$G:$G,Aut_Ajustes_Manuais!$I:$I,DRE!AL$4,Aut_Ajustes_Manuais!$F:$F,"Viagens e Estadias") -> 0 | AO46: 0 | AP46: 0 | AQ46: =SUMIFS(Aut_BlueMe_Sem_Pedido!$J:$J,Aut_BlueMe_Sem_Pedido!$Q:$Q,DRE!AO$4,Aut_BlueMe_Sem_Pedido!$H:$H,DRE!$A46)+SUMIFS(Aut_Ajustes_Manuais!$G:$G,Aut_Ajustes_Manuais!$I:$I,DRE!AO$4,Aut_Ajustes_Manuais!$F:$F,"Viagens e Estadias") -> 0 | AR46: =SUMIFS($H46:$AO46,$H$5:$AO$5,"<"&MONTH(TODAY()),$H$6:$AO$6,"REAL 25") -> 0 | AS46: =SUMIFS($I46:$AP46,$I$5:$AP$5,"<"&MONTH(TODAY()),$I$6:$AP$6,"ORÇADO ") -> 0 | AT46: =SUMIFS($J46:$AQ46,$J$5:$AQ$5,"<"&MONTH(TODAY()),$J$6:$AQ$6,"REAL 26") -> 0 | AU46: =SUM(H46,K46,N46,Q46,T46,W46,Z46,AC46,AF46,AI46,AL46,AO46) -> 0 | AV46: =SUM(I46,L46,O46,R46,U46,X46,AA46,AD46,AG46,AJ46,AM46,AP46) -> 0 | AW46: =SUM(J46,M46,P46,S46,V46,Y46,AB46,AE46,AH46,AK46,AN46,AQ46) -> 0 | AX46: =SUM(H46,K46,N46) -> 0 | AY46: =SUM(I46,L46,O46) -> 0 | AZ46: =SUM(J46,M46,P46) -> 0 | BA46: =SUM(Q46,T46,W46) -> 0 | BB46: =SUM(R46,U46,X46) -> 0 | BC46: =SUM(S46,V46,Y46) -> 0 | BD46: =SUM(Z46,AC46,AF46) -> 0 | BE46: =SUM(AA46,AD46,AG46) -> 0 | BF46: =SUM(AB46,AE46,AH46) -> 0 | BG46: =SUM(AI46,AL46,AO46) -> 0 | BH46: =SUM(AJ46,AM46,AP46) -> 0 | BI46: =SUM(AK46,AN46,AQ46) -> 0 | BK46: =SUM(I46,L46,O46,R46,U46,X46,AA46,AD46,AG46,AJ46,AM46,AP46) -> 0 | BL46: =BK46-AV46 -> 0 | BM46: =SUM(J46,M46,P46,S46,V46) -> 0 | BN46: =BM46-AT46 -> 0
A47: Taxas e Licenças - Artístico | C47: Contr/Prov - ECAD Valor Mensal | H47: 0 | I47: 0 | J47: =SUMIFS(Aut_BlueMe_Sem_Pedido!$J:$J,Aut_BlueMe_Sem_Pedido!$Q:$Q,DRE!H$4,Aut_BlueMe_Sem_Pedido!$H:$H,DRE!$A47)+SUMIFS(Aut_Ajustes_Manuais!$G:$G,Aut_Ajustes_Manuais!$I:$I,DRE!H$4,Aut_Ajustes_Manuais!$F:$F,"Taxas e Licenças - Artístico") -> 0 | K47: 0 | L47: 0 | M47: =SUMIFS(Aut_BlueMe_Sem_Pedido!$J:$J,Aut_BlueMe_Sem_Pedido!$Q:$Q,DRE!K$4,Aut_BlueMe_Sem_Pedido!$H:$H,DRE!$A47)+SUMIFS(Aut_Ajustes_Manuais!$G:$G,Aut_Ajustes_Manuais!$I:$I,DRE!K$4,Aut_Ajustes_Manuais!$F:$F,"Taxas e Licenças - Artístico") -> 0 | N47: 0 | O47: 0 | P47: =SUMIFS(Aut_BlueMe_Sem_Pedido!$J:$J,Aut_BlueMe_Sem_Pedido!$Q:$Q,DRE!N$4,Aut_BlueMe_Sem_Pedido!$H:$H,DRE!$A47)+SUMIFS(Aut_Ajustes_Manuais!$G:$G,Aut_Ajustes_Manuais!$I:$I,DRE!N$4,Aut_Ajustes_Manuais!$F:$F,"Taxas e Licenças - Artístico") -> 0 | Q47: 0 | R47: 0 | S47: =SUMIFS(Aut_BlueMe_Sem_Pedido!$J:$J,Aut_BlueMe_Sem_Pedido!$Q:$Q,DRE!Q$4,Aut_BlueMe_Sem_Pedido!$H:$H,DRE!$A47)+SUMIFS(Aut_Ajustes_Manuais!$G:$G,Aut_Ajustes_Manuais!$I:$I,DRE!Q$4,Aut_Ajustes_Manuais!$F:$F,"Taxas e Licenças - Artístico") -> 0 | T47: 0 | U47: 0 | V47: =SUMIFS(Aut_BlueMe_Sem_Pedido!$J:$J,Aut_BlueMe_Sem_Pedido!$Q:$Q,DRE!T$4,Aut_BlueMe_Sem_Pedido!$H:$H,DRE!$A47)+SUMIFS(Aut_Ajustes_Manuais!$G:$G,Aut_Ajustes_Manuais!$I:$I,DRE!T$4,Aut_Ajustes_Manuais!$F:$F,"Taxas e Licenças - Artístico") -> 0 | W47: 0 | X47: 0 | Y47: =SUMIFS(Aut_BlueMe_Sem_Pedido!$J:$J,Aut_BlueMe_Sem_Pedido!$Q:$Q,DRE!W$4,Aut_BlueMe_Sem_Pedido!$H:$H,DRE!$A47)+SUMIFS(Aut_Ajustes_Manuais!$G:$G,Aut_Ajustes_Manuais!$I:$I,DRE!W$4,Aut_Ajustes_Manuais!$F:$F,"Taxas e Licenças - Artístico") -> 0 | Z47: 0 | AA47: 0 | AB47: =SUMIFS(Aut_BlueMe_Sem_Pedido!$J:$J,Aut_BlueMe_Sem_Pedido!$Q:$Q,DRE!Z$4,Aut_BlueMe_Sem_Pedido!$H:$H,DRE!$A47)+SUMIFS(Aut_Ajustes_Manuais!$G:$G,Aut_Ajustes_Manuais!$I:$I,DRE!Z$4,Aut_Ajustes_Manuais!$F:$F,"Taxas e Licenças - Artístico") -> 0 | AC47: 0 | AD47: 0 | AE47: =SUMIFS(Aut_BlueMe_Sem_Pedido!$J:$J,Aut_BlueMe_Sem_Pedido!$Q:$Q,DRE!AC$4,Aut_BlueMe_Sem_Pedido!$H:$H,DRE!$A47)+SUMIFS(Aut_Ajustes_Manuais!$G:$G,Aut_Ajustes_Manuais!$I:$I,DRE!AC$4,Aut_Ajustes_Manuais!$F:$F,"Taxas e Licenças - Artístico") -> 0 | AF47: 0 | AG47: 0 | AH47: =SUMIFS(Aut_BlueMe_Sem_Pedido!$J:$J,Aut_BlueMe_Sem_Pedido!$Q:$Q,DRE!AF$4,Aut_BlueMe_Sem_Pedido!$H:$H,DRE!$A47)+SUMIFS(Aut_Ajustes_Manuais!$G:$G,Aut_Ajustes_Manuais!$I:$I,DRE!AF$4,Aut_Ajustes_Manuais!$F:$F,"Taxas e Licenças - Artístico") -> 0 | AI47: 0 | AJ47: 0 | AK47: =SUMIFS(Aut_BlueMe_Sem_Pedido!$J:$J,Aut_BlueMe_Sem_Pedido!$Q:$Q,DRE!AI$4,Aut_BlueMe_Sem_Pedido!$H:$H,DRE!$A47)+SUMIFS(Aut_Ajustes_Manuais!$G:$G,Aut_Ajustes_Manuais!$I:$I,DRE!AI$4,Aut_Ajustes_Manuais!$F:$F,"Taxas e Licenças - Artístico") -> 0 | AL47: 0 | AM47: 0 | AN47: =SUMIFS(Aut_BlueMe_Sem_Pedido!$J:$J,Aut_BlueMe_Sem_Pedido!$Q:$Q,DRE!AL$4,Aut_BlueMe_Sem_Pedido!$H:$H,DRE!$A47)+SUMIFS(Aut_Ajustes_Manuais!$G:$G,Aut_Ajustes_Manuais!$I:$I,DRE!AL$4,Aut_Ajustes_Manuais!$F:$F,"Taxas e Licenças - Artístico") -> 0 | AO47: 0 | AP47: 0 | AQ47: =SUMIFS(Aut_BlueMe_Sem_Pedido!$J:$J,Aut_BlueMe_Sem_Pedido!$Q:$Q,DRE!AO$4,Aut_BlueMe_Sem_Pedido!$H:$H,DRE!$A47)+SUMIFS(Aut_Ajustes_Manuais!$G:$G,Aut_Ajustes_Manuais!$I:$I,DRE!AO$4,Aut_Ajustes_Manuais!$F:$F,"Taxas e Licenças - Artístico") -> 0 | AR47: =SUMIFS($H47:$AO47,$H$5:$AO$5,"<"&MONTH(TODAY()),$H$6:$AO$6,"REAL 25") -> 0 | AS47: =SUMIFS($I47:$AP47,$I$5:$AP$5,"<"&MONTH(TODAY()),$I$6:$AP$6,"ORÇADO ") -> 0 | AT47: =SUMIFS($J47:$AQ47,$J$5:$AQ$5,"<"&MONTH(TODAY()),$J$6:$AQ$6,"REAL 26") -> 0 | AU47: =SUM(H47,K47,N47,Q47,T47,W47,Z47,AC47,AF47,AI47,AL47,AO47) -> 0 | AV47: =SUM(I47,L47,O47,R47,U47,X47,AA47,AD47,AG47,AJ47,AM47,AP47) -> 0 | AW47: =SUM(J47,M47,P47,S47,V47,Y47,AB47,AE47,AH47,AK47,AN47,AQ47) -> 0 | AX47: =SUM(H47,K47,N47) -> 0 | AY47: =SUM(I47,L47,O47) -> 0 | AZ47: =SUM(J47,M47,P47) -> 0 | BA47: =SUM(Q47,T47,W47) -> 0 | BB47: =SUM(R47,U47,X47) -> 0 | BC47: =SUM(S47,V47,Y47) -> 0 | BD47: =SUM(Z47,AC47,AF47) -> 0 | BE47: =SUM(AA47,AD47,AG47) -> 0 | BF47: =SUM(AB47,AE47,AH47) -> 0 | BG47: =SUM(AI47,AL47,AO47) -> 0 | BH47: =SUM(AJ47,AM47,AP47) -> 0 | BI47: =SUM(AK47,AN47,AQ47) -> 0 | BK47: =SUM(I47,L47,O47,R47,U47,X47,AA47,AD47,AG47,AJ47,AM47,AP47) -> 0 | BL47: =BK47-AV47 -> 0 | BM47: =SUM(J47,M47,P47,S47,V47) -> 0 | BN47: =BM47-AT47 -> 0
A48: MDO Terceirizada - Artístico | H48: 0 | J48: =SUMIFS(Aut_BlueMe_Sem_Pedido!$J:$J,Aut_BlueMe_Sem_Pedido!$Q:$Q,DRE!H$4,Aut_BlueMe_Sem_Pedido!$H:$H,DRE!$A48)+SUMIFS(Aut_Ajustes_Manuais!$G:$G,Aut_Ajustes_Manuais!$I:$I,DRE!H$4,Aut_Ajustes_Manuais!$F:$F,"MDO Terceirizada - Artístico") -> 0 | K48: 0 | M48: =SUMIFS(Aut_BlueMe_Sem_Pedido!$J:$J,Aut_BlueMe_Sem_Pedido!$Q:$Q,DRE!K$4,Aut_BlueMe_Sem_Pedido!$H:$H,DRE!$A48)+SUMIFS(Aut_Ajustes_Manuais!$G:$G,Aut_Ajustes_Manuais!$I:$I,DRE!K$4,Aut_Ajustes_Manuais!$F:$F,"MDO Terceirizada - Artístico") -> 0 | N48: 0 | P48: =SUMIFS(Aut_BlueMe_Sem_Pedido!$J:$J,Aut_BlueMe_Sem_Pedido!$Q:$Q,DRE!N$4,Aut_BlueMe_Sem_Pedido!$H:$H,DRE!$A48)+SUMIFS(Aut_Ajustes_Manuais!$G:$G,Aut_Ajustes_Manuais!$I:$I,DRE!N$4,Aut_Ajustes_Manuais!$F:$F,"MDO Terceirizada - Artístico") -> 0 | Q48: 0 | S48: =SUMIFS(Aut_BlueMe_Sem_Pedido!$J:$J,Aut_BlueMe_Sem_Pedido!$Q:$Q,DRE!Q$4,Aut_BlueMe_Sem_Pedido!$H:$H,DRE!$A48)+SUMIFS(Aut_Ajustes_Manuais!$G:$G,Aut_Ajustes_Manuais!$I:$I,DRE!Q$4,Aut_Ajustes_Manuais!$F:$F,"MDO Terceirizada - Artístico") -> 0 | T48: 0 | V48: =SUMIFS(Aut_BlueMe_Sem_Pedido!$J:$J,Aut_BlueMe_Sem_Pedido!$Q:$Q,DRE!T$4,Aut_BlueMe_Sem_Pedido!$H:$H,DRE!$A48)+SUMIFS(Aut_Ajustes_Manuais!$G:$G,Aut_Ajustes_Manuais!$I:$I,DRE!T$4,Aut_Ajustes_Manuais!$F:$F,"MDO Terceirizada - Artístico") -> 0 | W48: 0 | Y48: =SUMIFS(Aut_BlueMe_Sem_Pedido!$J:$J,Aut_BlueMe_Sem_Pedido!$Q:$Q,DRE!W$4,Aut_BlueMe_Sem_Pedido!$H:$H,DRE!$A48)+SUMIFS(Aut_Ajustes_Manuais!$G:$G,Aut_Ajustes_Manuais!$I:$I,DRE!W$4,Aut_Ajustes_Manuais!$F:$F,"MDO Terceirizada - Artístico") -> 0 | Z48: 0 | AB48: =SUMIFS(Aut_BlueMe_Sem_Pedido!$J:$J,Aut_BlueMe_Sem_Pedido!$Q:$Q,DRE!Z$4,Aut_BlueMe_Sem_Pedido!$H:$H,DRE!$A48)+SUMIFS(Aut_Ajustes_Manuais!$G:$G,Aut_Ajustes_Manuais!$I:$I,DRE!Z$4,Aut_Ajustes_Manuais!$F:$F,"MDO Terceirizada - Artístico") -> 0 | AC48: 0 | AE48: =SUMIFS(Aut_BlueMe_Sem_Pedido!$J:$J,Aut_BlueMe_Sem_Pedido!$Q:$Q,DRE!AC$4,Aut_BlueMe_Sem_Pedido!$H:$H,DRE!$A48)+SUMIFS(Aut_Ajustes_Manuais!$G:$G,Aut_Ajustes_Manuais!$I:$I,DRE!AC$4,Aut_Ajustes_Manuais!$F:$F,"MDO Terceirizada - Artístico") -> 0 | AF48: 0 | AH48: =SUMIFS(Aut_BlueMe_Sem_Pedido!$J:$J,Aut_BlueMe_Sem_Pedido!$Q:$Q,DRE!AF$4,Aut_BlueMe_Sem_Pedido!$H:$H,DRE!$A48)+SUMIFS(Aut_Ajustes_Manuais!$G:$G,Aut_Ajustes_Manuais!$I:$I,DRE!AF$4,Aut_Ajustes_Manuais!$F:$F,"MDO Terceirizada - Artístico") -> 0 | AI48: 0 | AK48: =SUMIFS(Aut_BlueMe_Sem_Pedido!$J:$J,Aut_BlueMe_Sem_Pedido!$Q:$Q,DRE!AI$4,Aut_BlueMe_Sem_Pedido!$H:$H,DRE!$A48)+SUMIFS(Aut_Ajustes_Manuais!$G:$G,Aut_Ajustes_Manuais!$I:$I,DRE!AI$4,Aut_Ajustes_Manuais!$F:$F,"MDO Terceirizada - Artístico") -> 0 | AL48: 0 | AN48: =SUMIFS(Aut_BlueMe_Sem_Pedido!$J:$J,Aut_BlueMe_Sem_Pedido!$Q:$Q,DRE!AL$4,Aut_BlueMe_Sem_Pedido!$H:$H,DRE!$A48)+SUMIFS(Aut_Ajustes_Manuais!$G:$G,Aut_Ajustes_Manuais!$I:$I,DRE!AL$4,Aut_Ajustes_Manuais!$F:$F,"MDO Terceirizada - Artístico") -> 0 | AO48: 0 | AQ48: =SUMIFS(Aut_BlueMe_Sem_Pedido!$J:$J,Aut_BlueMe_Sem_Pedido!$Q:$Q,DRE!AO$4,Aut_BlueMe_Sem_Pedido!$H:$H,DRE!$A48)+SUMIFS(Aut_Ajustes_Manuais!$G:$G,Aut_Ajustes_Manuais!$I:$I,DRE!AO$4,Aut_Ajustes_Manuais!$F:$F,"MDO Terceirizada - Artístico") -> 0 | AR48: =SUMIFS($H48:$AO48,$H$5:$AO$5,"<"&MONTH(TODAY()),$H$6:$AO$6,"REAL 25") -> 0 | AS48: =SUMIFS($I48:$AP48,$I$5:$AP$5,"<"&MONTH(TODAY()),$I$6:$AP$6,"ORÇADO ") -> 0 | AT48: =SUMIFS($J48:$AQ48,$J$5:$AQ$5,"<"&MONTH(TODAY()),$J$6:$AQ$6,"REAL 26") -> 0 | AU48: =SUM(H48,K48,N48,Q48,T48,W48,Z48,AC48,AF48,AI48,AL48,AO48) -> 0 | AV48: =SUM(I48,L48,O48,R48,U48,X48,AA48,AD48,AG48,AJ48,AM48,AP48) -> 0 | AW48: =SUM(J48,M48,P48,S48,V48,Y48,AB48,AE48,AH48,AK48,AN48,AQ48) -> 0 | AX48: =SUM(H48,K48,N48) -> 0 | AY48: =SUM(I48,L48,O48) -> 0 | AZ48: =SUM(J48,M48,P48) -> 0 | BA48: =SUM(Q48,T48,W48) -> 0 | BB48: =SUM(R48,U48,X48) -> 0 | BC48: =SUM(S48,V48,Y48) -> 0 | BD48: =SUM(Z48,AC48,AF48) -> 0 | BE48: =SUM(AA48,AD48,AG48) -> 0 | BF48: =SUM(AB48,AE48,AH48) -> 0 | BG48: =SUM(AI48,AL48,AO48) -> 0 | BH48: =SUM(AJ48,AM48,AP48) -> 0 | BI48: =SUM(AK48,AN48,AQ48) -> 0 | BK48: =SUM(I48,L48,O48,R48,U48,X48,AA48,AD48,AG48,AJ48,AM48,AP48) -> 0 | BL48: =BK48-AV48 -> 0 | BM48: =SUM(J48,M48,P48,S48,V48) -> 0 | BN48: =BM48-AT48 -> 0
A49: Custos Ténico de Som | H49: 0 | I49: 0 | J49: =SUM(J50:J52)+SUMIFS(Aut_Ajustes_Manuais!$G:$G,Aut_Ajustes_Manuais!$I:$I,DRE!H$4,Aut_Ajustes_Manuais!$F:$F,"Custos Ténico de Som") -> 0 | K49: 0 | L49: 0 | M49: =SUM(M50:M52)+SUMIFS(Aut_Ajustes_Manuais!$G:$G,Aut_Ajustes_Manuais!$I:$I,DRE!K$4,Aut_Ajustes_Manuais!$F:$F,"Custos Ténico de Som") -> 0 | N49: 0 | O49: 0 | P49: =SUM(P50:P52)+SUMIFS(Aut_Ajustes_Manuais!$G:$G,Aut_Ajustes_Manuais!$I:$I,DRE!N$4,Aut_Ajustes_Manuais!$F:$F,"Custos Ténico de Som") -> 0 | Q49: 0 | R49: 0 | S49: =SUM(S50:S52)+SUMIFS(Aut_Ajustes_Manuais!$G:$G,Aut_Ajustes_Manuais!$I:$I,DRE!Q$4,Aut_Ajustes_Manuais!$F:$F,"Custos Ténico de Som") -> 0 | T49: 0 | U49: 0 | V49: =SUM(V50:V52)+SUMIFS(Aut_Ajustes_Manuais!$G:$G,Aut_Ajustes_Manuais!$I:$I,DRE!T$4,Aut_Ajustes_Manuais!$F:$F,"Custos Ténico de Som") -> 0 | W49: 0 | X49: 0 | Y49: =SUM(Y50:Y52)+SUMIFS(Aut_Ajustes_Manuais!$G:$G,Aut_Ajustes_Manuais!$I:$I,DRE!W$4,Aut_Ajustes_Manuais!$F:$F,"Custos Ténico de Som") -> 0 | Z49: 0 | AA49: 0 | AB49: =SUM(AB50:AB52)+SUMIFS(Aut_Ajustes_Manuais!$G:$G,Aut_Ajustes_Manuais!$I:$I,DRE!Z$4,Aut_Ajustes_Manuais!$F:$F,"Custos Ténico de Som") -> 0 | AC49: 0 | AD49: 0 | AE49: =SUM(AE50:AE52)+SUMIFS(Aut_Ajustes_Manuais!$G:$G,Aut_Ajustes_Manuais!$I:$I,DRE!AC$4,Aut_Ajustes_Manuais!$F:$F,"Custos Ténico de Som") -> 0 | AF49: 0 | AG49: 0 | AH49: =SUM(AH50:AH52)+SUMIFS(Aut_Ajustes_Manuais!$G:$G,Aut_Ajustes_Manuais!$I:$I,DRE!AF$4,Aut_Ajustes_Manuais!$F:$F,"Custos Ténico de Som") -> 0 | AI49: 0 | AJ49: 0 | AK49: =SUM(AK50:AK52)+SUMIFS(Aut_Ajustes_Manuais!$G:$G,Aut_Ajustes_Manuais!$I:$I,DRE!AI$4,Aut_Ajustes_Manuais!$F:$F,"Custos Ténico de Som") -> 0 | AL49: 0 | AM49: 0 | AN49: =SUM(AN50:AN52)+SUMIFS(Aut_Ajustes_Manuais!$G:$G,Aut_Ajustes_Manuais!$I:$I,DRE!AL$4,Aut_Ajustes_Manuais!$F:$F,"Custos Ténico de Som") -> 0 | AO49: 0 | AP49: 0 | AQ49: =SUM(AQ50:AQ52)+SUMIFS(Aut_Ajustes_Manuais!$G:$G,Aut_Ajustes_Manuais!$I:$I,DRE!AO$4,Aut_Ajustes_Manuais!$F:$F,"Custos Ténico de Som") -> 0 | AR49: =SUMIFS($H49:$AO49,$H$5:$AO$5,"<"&MONTH(TODAY()),$H$6:$AO$6,"REAL 25") -> 0 | AS49: =SUMIFS($I49:$AP49,$I$5:$AP$5,"<"&MONTH(TODAY()),$I$6:$AP$6,"ORÇADO ") -> 0 | AT49: =SUMIFS($J49:$AQ49,$J$5:$AQ$5,"<"&MONTH(TODAY()),$J$6:$AQ$6,"REAL 26") -> 0 | AU49: =SUM(AU50:AU52) -> 0 | AV49: =SUM(AV50:AV52) -> 0 | AW49: =SUM(AW50:AW52) -> 0 | AX49: =SUM(AX50:AX52) -> 0 | AY49: =SUM(AY50:AY52) -> 0 | AZ49: =SUM(AZ50:AZ52) -> 0 | BA49: =SUM(BA50:BA52) -> 0 | BB49: =SUM(BB50:BB52) -> 0 | ... BI49: =SUM(BI50:BI52) -> 0 | BK49: =SUM(I49,L49,O49,R49,U49,X49,AA49,AD49,AG49,AJ49,AM49,AP49) -> 0 | BL49: =BK49-AV49 -> 0 | BM49: =SUM(J49,M49,P49,S49,V49) -> 0 | BN49: =BM49-AT49 -> 0
A50: Técnico de Som / Luz | C50: Contr/Prov | H50: 0 | I50: 0 | J50: =SUMIFS(Aut_BlueMe_Sem_Pedido!$J:$J,Aut_BlueMe_Sem_Pedido!$Q:$Q,DRE!H$4,Aut_BlueMe_Sem_Pedido!$H:$H,DRE!$A50)+SUMIFS(Aut_Ajustes_Manuais!$G:$G,Aut_Ajustes_Manuais!$I:$I,DRE!H$4,Aut_Ajustes_Manuais!$F:$F,"Técnico de Som / Luz") -> 0 | K50: 0 | L50: 0 | M50: =SUMIFS(Aut_BlueMe_Sem_Pedido!$J:$J,Aut_BlueMe_Sem_Pedido!$Q:$Q,DRE!K$4,Aut_BlueMe_Sem_Pedido!$H:$H,DRE!$A50)+SUMIFS(Aut_Ajustes_Manuais!$G:$G,Aut_Ajustes_Manuais!$I:$I,DRE!K$4,Aut_Ajustes_Manuais!$F:$F,"Técnico de Som / Luz") -> 0 | N50: 0 | O50: 0 | P50: =SUMIFS(Aut_BlueMe_Sem_Pedido!$J:$J,Aut_BlueMe_Sem_Pedido!$Q:$Q,DRE!N$4,Aut_BlueMe_Sem_Pedido!$H:$H,DRE!$A50)+SUMIFS(Aut_Ajustes_Manuais!$G:$G,Aut_Ajustes_Manuais!$I:$I,DRE!N$4,Aut_Ajustes_Manuais!$F:$F,"Técnico de Som / Luz") -> 0 | Q50: 0 | R50: 0 | S50: =SUMIFS(Aut_BlueMe_Sem_Pedido!$J:$J,Aut_BlueMe_Sem_Pedido!$Q:$Q,DRE!Q$4,Aut_BlueMe_Sem_Pedido!$H:$H,DRE!$A50)+SUMIFS(Aut_Ajustes_Manuais!$G:$G,Aut_Ajustes_Manuais!$I:$I,DRE!Q$4,Aut_Ajustes_Manuais!$F:$F,"Técnico de Som / Luz") -> 0 | T50: 0 | U50: 0 | V50: =SUMIFS(Aut_BlueMe_Sem_Pedido!$J:$J,Aut_BlueMe_Sem_Pedido!$Q:$Q,DRE!T$4,Aut_BlueMe_Sem_Pedido!$H:$H,DRE!$A50)+SUMIFS(Aut_Ajustes_Manuais!$G:$G,Aut_Ajustes_Manuais!$I:$I,DRE!T$4,Aut_Ajustes_Manuais!$F:$F,"Técnico de Som / Luz") -> 0 | W50: 0 | X50: 0 | Y50: =SUMIFS(Aut_BlueMe_Sem_Pedido!$J:$J,Aut_BlueMe_Sem_Pedido!$Q:$Q,DRE!W$4,Aut_BlueMe_Sem_Pedido!$H:$H,DRE!$A50)+SUMIFS(Aut_Ajustes_Manuais!$G:$G,Aut_Ajustes_Manuais!$I:$I,DRE!W$4,Aut_Ajustes_Manuais!$F:$F,"Técnico de Som / Luz") -> 0 | Z50: 0 | AA50: 0 | AB50: =SUMIFS(Aut_BlueMe_Sem_Pedido!$J:$J,Aut_BlueMe_Sem_Pedido!$Q:$Q,DRE!Z$4,Aut_BlueMe_Sem_Pedido!$H:$H,DRE!$A50)+SUMIFS(Aut_Ajustes_Manuais!$G:$G,Aut_Ajustes_Manuais!$I:$I,DRE!Z$4,Aut_Ajustes_Manuais!$F:$F,"Técnico de Som / Luz") -> 0 | AC50: 0 | AD50: 0 | AE50: =SUMIFS(Aut_BlueMe_Sem_Pedido!$J:$J,Aut_BlueMe_Sem_Pedido!$Q:$Q,DRE!AC$4,Aut_BlueMe_Sem_Pedido!$H:$H,DRE!$A50)+SUMIFS(Aut_Ajustes_Manuais!$G:$G,Aut_Ajustes_Manuais!$I:$I,DRE!AC$4,Aut_Ajustes_Manuais!$F:$F,"Técnico de Som / Luz") -> 0 | AF50: 0 | AG50: 0 | AH50: =SUMIFS(Aut_BlueMe_Sem_Pedido!$J:$J,Aut_BlueMe_Sem_Pedido!$Q:$Q,DRE!AF$4,Aut_BlueMe_Sem_Pedido!$H:$H,DRE!$A50)+SUMIFS(Aut_Ajustes_Manuais!$G:$G,Aut_Ajustes_Manuais!$I:$I,DRE!AF$4,Aut_Ajustes_Manuais!$F:$F,"Técnico de Som / Luz") -> 0 | AI50: 0 | AJ50: 0 | AK50: =SUMIFS(Aut_BlueMe_Sem_Pedido!$J:$J,Aut_BlueMe_Sem_Pedido!$Q:$Q,DRE!AI$4,Aut_BlueMe_Sem_Pedido!$H:$H,DRE!$A50)+SUMIFS(Aut_Ajustes_Manuais!$G:$G,Aut_Ajustes_Manuais!$I:$I,DRE!AI$4,Aut_Ajustes_Manuais!$F:$F,"Técnico de Som / Luz") -> 0 | AL50: 0 | AM50: 0 | AN50: =SUMIFS(Aut_BlueMe_Sem_Pedido!$J:$J,Aut_BlueMe_Sem_Pedido!$Q:$Q,DRE!AL$4,Aut_BlueMe_Sem_Pedido!$H:$H,DRE!$A50)+SUMIFS(Aut_Ajustes_Manuais!$G:$G,Aut_Ajustes_Manuais!$I:$I,DRE!AL$4,Aut_Ajustes_Manuais!$F:$F,"Técnico de Som / Luz") -> 0 | AO50: 0 | AP50: 0 | AQ50: =SUMIFS(Aut_BlueMe_Sem_Pedido!$J:$J,Aut_BlueMe_Sem_Pedido!$Q:$Q,DRE!AO$4,Aut_BlueMe_Sem_Pedido!$H:$H,DRE!$A50)+SUMIFS(Aut_Ajustes_Manuais!$G:$G,Aut_Ajustes_Manuais!$I:$I,DRE!AO$4,Aut_Ajustes_Manuais!$F:$F,"Técnico de Som / Luz") -> 0 | AR50: =SUMIFS($H50:$AO50,$H$5:$AO$5,"<"&MONTH(TODAY()),$H$6:$AO$6,"REAL 25") -> 0 | AS50: =SUMIFS($I50:$AP50,$I$5:$AP$5,"<"&MONTH(TODAY()),$I$6:$AP$6,"ORÇADO ") -> 0 | AT50: =SUMIFS($J50:$AQ50,$J$5:$AQ$5,"<"&MONTH(TODAY()),$J$6:$AQ$6,"REAL 26") -> 0 | AU50: =SUM(H50,K50,N50,Q50,T50,W50,Z50,AC50,AF50,AI50,AL50,AO50) -> 0 | AV50: =SUM(I50,L50,O50,R50,U50,X50,AA50,AD50,AG50,AJ50,AM50,AP50) -> 0 | AW50: =SUM(J50,M50,P50,S50,V50,Y50,AB50,AE50,AH50,AK50,AN50,AQ50) -> 0 | AX50: =SUM(H50,K50,N50) -> 0 | AY50: =SUM(I50,L50,O50) -> 0 | AZ50: =SUM(J50,M50,P50) -> 0 | BA50: =SUM(Q50,T50,W50) -> 0 | BB50: =SUM(R50,U50,X50) -> 0 | BC50: =SUM(S50,V50,Y50) -> 0 | BD50: =SUM(Z50,AC50,AF50) -> 0 | BE50: =SUM(AA50,AD50,AG50) -> 0 | BF50: =SUM(AB50,AE50,AH50) -> 0 | BG50: =SUM(AI50,AL50,AO50) -> 0 | BH50: =SUM(AJ50,AM50,AP50) -> 0 | BI50: =SUM(AK50,AN50,AQ50) -> 0 | BK50: =SUM(I50,L50,O50,R50,U50,X50,AA50,AD50,AG50,AJ50,AM50,AP50) -> 0 | BL50: =BK50-AV50 -> 0 | BM50: =SUM(J50,M50,P50,S50,V50) -> 0 | BN50: =BM50-AT50 -> 0
A51: Locação de Equipamentos Fixo | C51: Contr/Prov | H51: 0 | I51: 0 | J51: =SUMIFS(Aut_BlueMe_Sem_Pedido!$J:$J,Aut_BlueMe_Sem_Pedido!$Q:$Q,DRE!H$4,Aut_BlueMe_Sem_Pedido!$H:$H,DRE!$A51)+SUMIFS(Aut_Ajustes_Manuais!$G:$G,Aut_Ajustes_Manuais!$I:$I,DRE!H$4,Aut_Ajustes_Manuais!$F:$F,"Locação de Equipamentos Fixo") -> 0 | K51: 0 | L51: 0 | M51: =SUMIFS(Aut_BlueMe_Sem_Pedido!$J:$J,Aut_BlueMe_Sem_Pedido!$Q:$Q,DRE!K$4,Aut_BlueMe_Sem_Pedido!$H:$H,DRE!$A51)+SUMIFS(Aut_Ajustes_Manuais!$G:$G,Aut_Ajustes_Manuais!$I:$I,DRE!K$4,Aut_Ajustes_Manuais!$F:$F,"Locação de Equipamentos Fixo") -> 0 | N51: 0 | O51: 0 | P51: =SUMIFS(Aut_BlueMe_Sem_Pedido!$J:$J,Aut_BlueMe_Sem_Pedido!$Q:$Q,DRE!N$4,Aut_BlueMe_Sem_Pedido!$H:$H,DRE!$A51)+SUMIFS(Aut_Ajustes_Manuais!$G:$G,Aut_Ajustes_Manuais!$I:$I,DRE!N$4,Aut_Ajustes_Manuais!$F:$F,"Locação de Equipamentos Fixo") -> 0 | Q51: 0 | R51: 0 | S51: =SUMIFS(Aut_BlueMe_Sem_Pedido!$J:$J,Aut_BlueMe_Sem_Pedido!$Q:$Q,DRE!Q$4,Aut_BlueMe_Sem_Pedido!$H:$H,DRE!$A51)+SUMIFS(Aut_Ajustes_Manuais!$G:$G,Aut_Ajustes_Manuais!$I:$I,DRE!Q$4,Aut_Ajustes_Manuais!$F:$F,"Locação de Equipamentos Fixo") -> 0 | T51: 0 | U51: 0 | V51: =SUMIFS(Aut_BlueMe_Sem_Pedido!$J:$J,Aut_BlueMe_Sem_Pedido!$Q:$Q,DRE!T$4,Aut_BlueMe_Sem_Pedido!$H:$H,DRE!$A51)+SUMIFS(Aut_Ajustes_Manuais!$G:$G,Aut_Ajustes_Manuais!$I:$I,DRE!T$4,Aut_Ajustes_Manuais!$F:$F,"Locação de Equipamentos Fixo") -> 0 | W51: 0 | X51: 0 | Y51: =SUMIFS(Aut_BlueMe_Sem_Pedido!$J:$J,Aut_BlueMe_Sem_Pedido!$Q:$Q,DRE!W$4,Aut_BlueMe_Sem_Pedido!$H:$H,DRE!$A51)+SUMIFS(Aut_Ajustes_Manuais!$G:$G,Aut_Ajustes_Manuais!$I:$I,DRE!W$4,Aut_Ajustes_Manuais!$F:$F,"Locação de Equipamentos Fixo") -> 0 | Z51: 0 | AA51: 0 | AB51: =SUMIFS(Aut_BlueMe_Sem_Pedido!$J:$J,Aut_BlueMe_Sem_Pedido!$Q:$Q,DRE!Z$4,Aut_BlueMe_Sem_Pedido!$H:$H,DRE!$A51)+SUMIFS(Aut_Ajustes_Manuais!$G:$G,Aut_Ajustes_Manuais!$I:$I,DRE!Z$4,Aut_Ajustes_Manuais!$F:$F,"Locação de Equipamentos Fixo") -> 0 | AC51: 0 | AD51: 0 | AE51: =SUMIFS(Aut_BlueMe_Sem_Pedido!$J:$J,Aut_BlueMe_Sem_Pedido!$Q:$Q,DRE!AC$4,Aut_BlueMe_Sem_Pedido!$H:$H,DRE!$A51)+SUMIFS(Aut_Ajustes_Manuais!$G:$G,Aut_Ajustes_Manuais!$I:$I,DRE!AC$4,Aut_Ajustes_Manuais!$F:$F,"Locação de Equipamentos Fixo") -> 0 | AF51: 0 | AG51: 0 | AH51: =SUMIFS(Aut_BlueMe_Sem_Pedido!$J:$J,Aut_BlueMe_Sem_Pedido!$Q:$Q,DRE!AF$4,Aut_BlueMe_Sem_Pedido!$H:$H,DRE!$A51)+SUMIFS(Aut_Ajustes_Manuais!$G:$G,Aut_Ajustes_Manuais!$I:$I,DRE!AF$4,Aut_Ajustes_Manuais!$F:$F,"Locação de Equipamentos Fixo") -> 0 | AI51: 0 | AJ51: 0 | AK51: =SUMIFS(Aut_BlueMe_Sem_Pedido!$J:$J,Aut_BlueMe_Sem_Pedido!$Q:$Q,DRE!AI$4,Aut_BlueMe_Sem_Pedido!$H:$H,DRE!$A51)+SUMIFS(Aut_Ajustes_Manuais!$G:$G,Aut_Ajustes_Manuais!$I:$I,DRE!AI$4,Aut_Ajustes_Manuais!$F:$F,"Locação de Equipamentos Fixo") -> 0 | AL51: 0 | AM51: 0 | AN51: =SUMIFS(Aut_BlueMe_Sem_Pedido!$J:$J,Aut_BlueMe_Sem_Pedido!$Q:$Q,DRE!AL$4,Aut_BlueMe_Sem_Pedido!$H:$H,DRE!$A51)+SUMIFS(Aut_Ajustes_Manuais!$G:$G,Aut_Ajustes_Manuais!$I:$I,DRE!AL$4,Aut_Ajustes_Manuais!$F:$F,"Locação de Equipamentos Fixo") -> 0 | AO51: 0 | AP51: 0 | AQ51: =SUMIFS(Aut_BlueMe_Sem_Pedido!$J:$J,Aut_BlueMe_Sem_Pedido!$Q:$Q,DRE!AO$4,Aut_BlueMe_Sem_Pedido!$H:$H,DRE!$A51)+SUMIFS(Aut_Ajustes_Manuais!$G:$G,Aut_Ajustes_Manuais!$I:$I,DRE!AO$4,Aut_Ajustes_Manuais!$F:$F,"Locação de Equipamentos Fixo") -> 0 | AR51: =SUMIFS($H51:$AO51,$H$5:$AO$5,"<"&MONTH(TODAY()),$H$6:$AO$6,"REAL 25") -> 0 | AS51: =SUMIFS($I51:$AP51,$I$5:$AP$5,"<"&MONTH(TODAY()),$I$6:$AP$6,"ORÇADO ") -> 0 | AT51: =SUMIFS($J51:$AQ51,$J$5:$AQ$5,"<"&MONTH(TODAY()),$J$6:$AQ$6,"REAL 26") -> 0 | AU51: =SUM(H51,K51,N51,Q51,T51,W51,Z51,AC51,AF51,AI51,AL51,AO51) -> 0 | AV51: =SUM(I51,L51,O51,R51,U51,X51,AA51,AD51,AG51,AJ51,AM51,AP51) -> 0 | AW51: =SUM(J51,M51,P51,S51,V51,Y51,AB51,AE51,AH51,AK51,AN51,AQ51) -> 0 | AX51: =SUM(H51,K51,N51) -> 0 | AY51: =SUM(I51,L51,O51) -> 0 | AZ51: =SUM(J51,M51,P51) -> 0 | BA51: =SUM(Q51,T51,W51) -> 0 | BB51: =SUM(R51,U51,X51) -> 0 | BC51: =SUM(S51,V51,Y51) -> 0 | BD51: =SUM(Z51,AC51,AF51) -> 0 | BE51: =SUM(AA51,AD51,AG51) -> 0 | BF51: =SUM(AB51,AE51,AH51) -> 0 | BG51: =SUM(AI51,AL51,AO51) -> 0 | BH51: =SUM(AJ51,AM51,AP51) -> 0 | BI51: =SUM(AK51,AN51,AQ51) -> 0 | BK51: =SUM(I51,L51,O51,R51,U51,X51,AA51,AD51,AG51,AJ51,AM51,AP51) -> 0 | BL51: =BK51-AV51 -> 0 | BM51: =SUM(J51,M51,P51,S51,V51) -> 0 | BN51: =BM51-AT51 -> 0
A52: Locação de Equipamentos Variável | C52: Estim. Mensal | E52: 0 | H52: 0 | I52: 0 | J52: =SUMIFS(Aut_BlueMe_Sem_Pedido!$J:$J,Aut_BlueMe_Sem_Pedido!$Q:$Q,DRE!H$4,Aut_BlueMe_Sem_Pedido!$H:$H,DRE!$A52)+SUMIFS(Aut_Ajustes_Manuais!$G:$G,Aut_Ajustes_Manuais!$I:$I,DRE!H$4,Aut_Ajustes_Manuais!$F:$F,"Locação de Equipamentos Variável") -> 0 | K52: 0 | L52: 0 | M52: =SUMIFS(Aut_BlueMe_Sem_Pedido!$J:$J,Aut_BlueMe_Sem_Pedido!$Q:$Q,DRE!K$4,Aut_BlueMe_Sem_Pedido!$H:$H,DRE!$A52)+SUMIFS(Aut_Ajustes_Manuais!$G:$G,Aut_Ajustes_Manuais!$I:$I,DRE!K$4,Aut_Ajustes_Manuais!$F:$F,"Locação de Equipamentos Variável") -> 0 | N52: 0 | O52: 0 | P52: =SUMIFS(Aut_BlueMe_Sem_Pedido!$J:$J,Aut_BlueMe_Sem_Pedido!$Q:$Q,DRE!N$4,Aut_BlueMe_Sem_Pedido!$H:$H,DRE!$A52)+SUMIFS(Aut_Ajustes_Manuais!$G:$G,Aut_Ajustes_Manuais!$I:$I,DRE!N$4,Aut_Ajustes_Manuais!$F:$F,"Locação de Equipamentos Variável") -> 0 | Q52: 0 | R52: 0 | S52: =SUMIFS(Aut_BlueMe_Sem_Pedido!$J:$J,Aut_BlueMe_Sem_Pedido!$Q:$Q,DRE!Q$4,Aut_BlueMe_Sem_Pedido!$H:$H,DRE!$A52)+SUMIFS(Aut_Ajustes_Manuais!$G:$G,Aut_Ajustes_Manuais!$I:$I,DRE!Q$4,Aut_Ajustes_Manuais!$F:$F,"Locação de Equipamentos Variável") -> 0 | T52: 0 | U52: 0 | V52: =SUMIFS(Aut_BlueMe_Sem_Pedido!$J:$J,Aut_BlueMe_Sem_Pedido!$Q:$Q,DRE!T$4,Aut_BlueMe_Sem_Pedido!$H:$H,DRE!$A52)+SUMIFS(Aut_Ajustes_Manuais!$G:$G,Aut_Ajustes_Manuais!$I:$I,DRE!T$4,Aut_Ajustes_Manuais!$F:$F,"Locação de Equipamentos Variável") -> 0 | W52: 0 | X52: 0 | Y52: =SUMIFS(Aut_BlueMe_Sem_Pedido!$J:$J,Aut_BlueMe_Sem_Pedido!$Q:$Q,DRE!W$4,Aut_BlueMe_Sem_Pedido!$H:$H,DRE!$A52)+SUMIFS(Aut_Ajustes_Manuais!$G:$G,Aut_Ajustes_Manuais!$I:$I,DRE!W$4,Aut_Ajustes_Manuais!$F:$F,"Locação de Equipamentos Variável") -> 0 | Z52: 0 | AA52: 0 | AB52: =SUMIFS(Aut_BlueMe_Sem_Pedido!$J:$J,Aut_BlueMe_Sem_Pedido!$Q:$Q,DRE!Z$4,Aut_BlueMe_Sem_Pedido!$H:$H,DRE!$A52)+SUMIFS(Aut_Ajustes_Manuais!$G:$G,Aut_Ajustes_Manuais!$I:$I,DRE!Z$4,Aut_Ajustes_Manuais!$F:$F,"Locação de Equipamentos Variável") -> 0 | AC52: 0 | AD52: 0 | AE52: =SUMIFS(Aut_BlueMe_Sem_Pedido!$J:$J,Aut_BlueMe_Sem_Pedido!$Q:$Q,DRE!AC$4,Aut_BlueMe_Sem_Pedido!$H:$H,DRE!$A52)+SUMIFS(Aut_Ajustes_Manuais!$G:$G,Aut_Ajustes_Manuais!$I:$I,DRE!AC$4,Aut_Ajustes_Manuais!$F:$F,"Locação de Equipamentos Variável") -> 0 | AF52: 0 | AG52: 0 | AH52: =SUMIFS(Aut_BlueMe_Sem_Pedido!$J:$J,Aut_BlueMe_Sem_Pedido!$Q:$Q,DRE!AF$4,Aut_BlueMe_Sem_Pedido!$H:$H,DRE!$A52)+SUMIFS(Aut_Ajustes_Manuais!$G:$G,Aut_Ajustes_Manuais!$I:$I,DRE!AF$4,Aut_Ajustes_Manuais!$F:$F,"Locação de Equipamentos Variável") -> 0 | AI52: 0 | AJ52: 0 | AK52: =SUMIFS(Aut_BlueMe_Sem_Pedido!$J:$J,Aut_BlueMe_Sem_Pedido!$Q:$Q,DRE!AI$4,Aut_BlueMe_Sem_Pedido!$H:$H,DRE!$A52)+SUMIFS(Aut_Ajustes_Manuais!$G:$G,Aut_Ajustes_Manuais!$I:$I,DRE!AI$4,Aut_Ajustes_Manuais!$F:$F,"Locação de Equipamentos Variável") -> 0 | AL52: 0 | AM52: 0 | AN52: =SUMIFS(Aut_BlueMe_Sem_Pedido!$J:$J,Aut_BlueMe_Sem_Pedido!$Q:$Q,DRE!AL$4,Aut_BlueMe_Sem_Pedido!$H:$H,DRE!$A52)+SUMIFS(Aut_Ajustes_Manuais!$G:$G,Aut_Ajustes_Manuais!$I:$I,DRE!AL$4,Aut_Ajustes_Manuais!$F:$F,"Locação de Equipamentos Variável") -> 0 | AO52: 0 | AP52: 0 | AQ52: =SUMIFS(Aut_BlueMe_Sem_Pedido!$J:$J,Aut_BlueMe_Sem_Pedido!$Q:$Q,DRE!AO$4,Aut_BlueMe_Sem_Pedido!$H:$H,DRE!$A52)+SUMIFS(Aut_Ajustes_Manuais!$G:$G,Aut_Ajustes_Manuais!$I:$I,DRE!AO$4,Aut_Ajustes_Manuais!$F:$F,"Locação de Equipamentos Variável") -> 0 | AR52: =SUMIFS($H52:$AO52,$H$5:$AO$5,"<"&MONTH(TODAY()),$H$6:$AO$6,"REAL 25") -> 0 | AS52: =SUMIFS($I52:$AP52,$I$5:$AP$5,"<"&MONTH(TODAY()),$I$6:$AP$6,"ORÇADO ") -> 0 | AT52: =SUMIFS($J52:$AQ52,$J$5:$AQ$5,"<"&MONTH(TODAY()),$J$6:$AQ$6,"REAL 26") -> 0 | AU52: =SUM(H52,K52,N52,Q52,T52,W52,Z52,AC52,AF52,AI52,AL52,AO52) -> 0 | AV52: =SUM(I52,L52,O52,R52,U52,X52,AA52,AD52,AG52,AJ52,AM52,AP52) -> 0 | AW52: =SUM(J52,M52,P52,S52,V52,Y52,AB52,AE52,AH52,AK52,AN52,AQ52) -> 0 | AX52: =SUM(H52,K52,N52) -> 0 | AY52: =SUM(I52,L52,O52) -> 0 | AZ52: =SUM(J52,M52,P52) -> 0 | BA52: =SUM(Q52,T52,W52) -> 0 | BB52: =SUM(R52,U52,X52) -> 0 | BC52: =SUM(S52,V52,Y52) -> 0 | BD52: =SUM(Z52,AC52,AF52) -> 0 | BE52: =SUM(AA52,AD52,AG52) -> 0 | BF52: =SUM(AB52,AE52,AH52) -> 0 | BG52: =SUM(AI52,AL52,AO52) -> 0 | BH52: =SUM(AJ52,AM52,AP52) -> 0 | BI52: =SUM(AK52,AN52,AQ52) -> 0 | BK52: =SUM(I52,L52,O52,R52,U52,X52,AA52,AD52,AG52,AJ52,AM52,AP52) -> 0 | BL52: =BK52-AV52 -> 0 | BM52: =SUM(J52,M52,P52,S52,V52) -> 0 | BN52: =BM52-AT52 -> 0
A53: % sobre Receita Artístico | H53: 0 | I53: -0.17954744 | J53: =IFERROR(J42/J11,0)+SUMIFS(Aut_Ajustes_Manuais!$G:$G,Aut_Ajustes_Manuais!$I:$I,DRE!H$4,Aut_Ajustes_Manuais!$F:$F,"% sobre Receita Artístico") -> -2.248996 | K53: 0 | L53: -0.15769991 | M53: =IFERROR(M42/M11,0)+SUMIFS(Aut_Ajustes_Manuais!$G:$G,Aut_Ajustes_Manuais!$I:$I,DRE!K$4,Aut_Ajustes_Manuais!$F:$F,"% sobre Receita Artístico") -> -5.1282051 | N53: -5.3266504 | O53: -0.19657204 | P53: =IFERROR(P42/P11,0)+SUMIFS(Aut_Ajustes_Manuais!$G:$G,Aut_Ajustes_Manuais!$I:$I,DRE!N$4,Aut_Ajustes_Manuais!$F:$F,"% sobre Receita Artístico") -> -2.1052632 | Q53: -3.0457671 | R53: -0.18888699 | S53: =IFERROR(S42/S11,0)+SUMIFS(Aut_Ajustes_Manuais!$G:$G,Aut_Ajustes_Manuais!$I:$I,DRE!Q$4,Aut_Ajustes_Manuais!$F:$F,"% sobre Receita Artístico") -> -5.4263566 | T53: -3.8260085 | U53: -0.13893805 | V53: =IFERROR(V42/V11,0)+SUMIFS(Aut_Ajustes_Manuais!$G:$G,Aut_Ajustes_Manuais!$I:$I,DRE!T$4,Aut_Ajustes_Manuais!$F:$F,"% sobre Receita Artístico") -> -3.1638418 | W53: -16 | X53: -0.12986833 | Y53: =IFERROR(Y42/Y11,0)+SUMIFS(Aut_Ajustes_Manuais!$G:$G,Aut_Ajustes_Manuais!$I:$I,DRE!W$4,Aut_Ajustes_Manuais!$F:$F,"% sobre Receita Artístico") -> -5.0694444 | Z53: 0 | AA53: -0.1311116 | AB53: =IFERROR(AB42/AB11,0)+SUMIFS(Aut_Ajustes_Manuais!$G:$G,Aut_Ajustes_Manuais!$I:$I,DRE!Z$4,Aut_Ajustes_Manuais!$F:$F,"% sobre Receita Artístico") -> -5.8333333 | AC53: -3.815482 | AD53: -0.14578624 | AE53: =IFERROR(AE42/AE11,0)+SUMIFS(Aut_Ajustes_Manuais!$G:$G,Aut_Ajustes_Manuais!$I:$I,DRE!AC$4,Aut_Ajustes_Manuais!$F:$F,"% sobre Receita Artístico") -> 0 | AF53: -2.0936639 | AG53: -0.13942461 | AH53: =IFERROR(AH42/AH11,0)+SUMIFS(Aut_Ajustes_Manuais!$G:$G,Aut_Ajustes_Manuais!$I:$I,DRE!AF$4,Aut_Ajustes_Manuais!$F:$F,"% sobre Receita Artístico") -> 0 | AI53: -0.68126521 | AJ53: -0.16626076 | AK53: =IFERROR(AK42/AK11,0)+SUMIFS(Aut_Ajustes_Manuais!$G:$G,Aut_Ajustes_Manuais!$I:$I,DRE!AI$4,Aut_Ajustes_Manuais!$F:$F,"% sobre Receita Artístico") -> 0 | AL53: -5.5833333 | AM53: -0.11938948 | AN53: =IFERROR(AN42/AN11,0)+SUMIFS(Aut_Ajustes_Manuais!$G:$G,Aut_Ajustes_Manuais!$I:$I,DRE!AL$4,Aut_Ajustes_Manuais!$F:$F,"% sobre Receita Artístico") -> 0 | AO53: -7.8714859 | AP53: -0.13190554 | AQ53: =IFERROR(AQ42/AQ11,0)+SUMIFS(Aut_Ajustes_Manuais!$G:$G,Aut_Ajustes_Manuais!$I:$I,DRE!AO$4,Aut_Ajustes_Manuais!$F:$F,"% sobre Receita Artístico") -> 0 | AR53: =IFERROR(AR42/AR11,0) -> -5.326446 | AS53: =IFERROR(AS42/AS11,0) -> -0.16103448 | AT53: =IFERROR(AT42/AT11,0) -> -3.5157988 | AU53: =IFERROR(AU42/AU11,0) -> -4.5120828 | AV53: =IFERROR(AV42/AV11,0) -> -0.14892656 | AW53: =IFERROR(AW42/AW11,0) -> -3.6107554 | AX53: =IFERROR(AX42/AX11,0) -> -8.4377615 | AY53: =IFERROR(AY42/AY11,0) -> -0.17668019 | ... BI53: =IFERROR(BI42/BI11,0) -> 0 | BK53: =SUM(I53,L53,O53,R53,U53,X53,AA53,AD53,AG53,AJ53,AM53,AP53) -> -1.825391 | BL53: =BK53-AV53 -> -1.6764644 | BM53: =SUM(J53,M53,P53,S53,V53) -> -18.072663 | BN53: =BM53-AT53 -> -14.556864
A54: % sobre Receita Bruta | H54: -0.0041121707 | I54: -0.022430022 | J54: =IFERROR(J42/J8,0)+SUMIFS(Aut_Ajustes_Manuais!$G:$G,Aut_Ajustes_Manuais!$I:$I,DRE!H$4,Aut_Ajustes_Manuais!$F:$F,"% sobre Receita Bruta") -> -0.014493448 | K54: -0.004531164 | L54: -0.019700713 | M54: =IFERROR(M42/M8,0)+SUMIFS(Aut_Ajustes_Manuais!$G:$G,Aut_Ajustes_Manuais!$I:$I,DRE!K$4,Aut_Ajustes_Manuais!$F:$F,"% sobre Receita Bruta") -> -0.022081409 | N54: -0.015472437 | O54: -0.024556826 | P54: =IFERROR(P42/P8,0)+SUMIFS(Aut_Ajustes_Manuais!$G:$G,Aut_Ajustes_Manuais!$I:$I,DRE!N$4,Aut_Ajustes_Manuais!$F:$F,"% sobre Receita Bruta") -> -0.012448523 | Q54: -0.011227161 | R54: -0.023596768 | S54: =IFERROR(S42/S8,0)+SUMIFS(Aut_Ajustes_Manuais!$G:$G,Aut_Ajustes_Manuais!$I:$I,DRE!Q$4,Aut_Ajustes_Manuais!$F:$F,"% sobre Receita Bruta") -> -0.018944073 | T54: -0.014215964 | U54: -0.017356881 | V54: =IFERROR(V42/V8,0)+SUMIFS(Aut_Ajustes_Manuais!$G:$G,Aut_Ajustes_Manuais!$I:$I,DRE!T$4,Aut_Ajustes_Manuais!$F:$F,"% sobre Receita Bruta") -> -0.022531522 | W54: -0.010846798 | X54: -0.016223844 | Y54: =IFERROR(Y42/Y8,0)+SUMIFS(Aut_Ajustes_Manuais!$G:$G,Aut_Ajustes_Manuais!$I:$I,DRE!W$4,Aut_Ajustes_Manuais!$F:$F,"% sobre Receita Bruta") -> -0.020306142 | Z54: -0.010108281 | AA54: -0.01637916 | AB54: =IFERROR(AB42/AB8,0)+SUMIFS(Aut_Ajustes_Manuais!$G:$G,Aut_Ajustes_Manuais!$I:$I,DRE!Z$4,Aut_Ajustes_Manuais!$F:$F,"% sobre Receita Bruta") -> -0.035650451 | AC54: -0.017354893 | AD54: -0.018212394 | AE54: =IFERROR(AE42/AE8,0)+SUMIFS(Aut_Ajustes_Manuais!$G:$G,Aut_Ajustes_Manuais!$I:$I,DRE!AC$4,Aut_Ajustes_Manuais!$F:$F,"% sobre Receita Bruta") -> 0 | AF54: -0.010779046 | AG54: -0.017417664 | AH54: =IFERROR(AH42/AH8,0)+SUMIFS(Aut_Ajustes_Manuais!$G:$G,Aut_Ajustes_Manuais!$I:$I,DRE!AF$4,Aut_Ajustes_Manuais!$F:$F,"% sobre Receita Bruta") -> 0 | AI54: -0.0038576764 | AJ54: -0.02077018 | AK54: =IFERROR(AK42/AK8,0)+SUMIFS(Aut_Ajustes_Manuais!$G:$G,Aut_Ajustes_Manuais!$I:$I,DRE!AI$4,Aut_Ajustes_Manuais!$F:$F,"% sobre Receita Bruta") -> 0 | AL54: -0.031196641 | AM54: -0.014914769 | AN54: =IFERROR(AN42/AN8,0)+SUMIFS(Aut_Ajustes_Manuais!$G:$G,Aut_Ajustes_Manuais!$I:$I,DRE!AL$4,Aut_Ajustes_Manuais!$F:$F,"% sobre Receita Bruta") -> 0 | AO54: -0.020406777 | AP54: -0.016478343 | AQ54: =IFERROR(AQ42/AQ8,0)+SUMIFS(Aut_Ajustes_Manuais!$G:$G,Aut_Ajustes_Manuais!$I:$I,DRE!AO$4,Aut_Ajustes_Manuais!$F:$F,"% sobre Receita Bruta") -> 0 | AR54: =IFERROR(AR42/AR8,0) -> -0.010255268 | AS54: =IFERROR(AS42/AS8,0) -> -0.020117285 | AT54: =IFERROR(AT42/AT8,0) -> -0.018435575 | AU54: =IFERROR(AU42/AU8,0) -> -0.013540365 | AV54: =IFERROR(AV42/AV8,0) -> -0.018604699 | AW54: =IFERROR(AW42/AW8,0) -> -0.019044301 | AX54: =IFERROR(AX42/AX8,0) -> -0.0079164664 | AY54: =IFERROR(AY42/AY8,0) -> -0.02207183 | ... BI54: =IFERROR(BI42/BI8,0) -> 0 | BK54: =SUM(I54,L54,O54,R54,U54,X54,AA54,AD54,AG54,AJ54,AM54,AP54) -> -0.22803756 | BL54: =BK54-AV54 -> -0.20943287 | BM54: =SUM(J54,M54,P54,S54,V54) -> -0.090498974 | BN54: =BM54-AT54 -> -0.072063399
BK55: =SUM(I55,L55,O55,R55,U55,X55,AA55,AD55,AG55,AJ55,AM55,AP55) -> 0 | BL55: =BK55-AV55 -> 0 | BM55: =SUM(J55,M55,P55,S55,V55) -> 0 | BN55: =BM55-AT55 -> 0
A56: (-) Custos Eventos | C56: Premissas | D56: Valores | E56: % Incid | H56: -490.5 | I56: =SUM(I57,I60,I65,I73,I77,I82) -> -2371.0219 | J56: =SUM(J57,J60,J65,J73,J77,J82)+SUMIFS(Aut_Ajustes_Manuais!$G:$G,Aut_Ajustes_Manuais!$I:$I,DRE!H$4,Aut_Ajustes_Manuais!$F:$F,"(-) Custos Eventos") -> -600 | K56: -400 | L56: =SUM(L57,L60,L65,L73,L77,L82) -> -2352.019 | M56: =SUM(M57,M60,M65,M73,M77,M82)+SUMIFS(Aut_Ajustes_Manuais!$G:$G,Aut_Ajustes_Manuais!$I:$I,DRE!K$4,Aut_Ajustes_Manuais!$F:$F,"(-) Custos Eventos") -> -600 | N56: -400 | O56: =SUM(O57,O60,O65,O73,O77,O82) -> -2282.4072 | P56: =SUM(P57,P60,P65,P73,P77,P82)+SUMIFS(Aut_Ajustes_Manuais!$G:$G,Aut_Ajustes_Manuais!$I:$I,DRE!N$4,Aut_Ajustes_Manuais!$F:$F,"(-) Custos Eventos") -> -600 | Q56: -400 | R56: =SUM(R57,R60,R65,R73,R77,R82) -> -2293.8973 | S56: =SUM(S57,S60,S65,S73,S77,S82)+SUMIFS(Aut_Ajustes_Manuais!$G:$G,Aut_Ajustes_Manuais!$I:$I,DRE!Q$4,Aut_Ajustes_Manuais!$F:$F,"(-) Custos Eventos") -> -600 | T56: -400 | U56: =SUM(U57,U60,U65,U73,U77,U82) -> -2479.4658 | V56: =SUM(V57,V60,V65,V73,V77,V82)+SUMIFS(Aut_Ajustes_Manuais!$G:$G,Aut_Ajustes_Manuais!$I:$I,DRE!T$4,Aut_Ajustes_Manuais!$F:$F,"(-) Custos Eventos") -> -600 | W56: 0 | X56: =SUM(X57,X60,X65,X73,X77,X82) -> -2427.4588 | Y56: =SUM(Y57,Y60,Y65,Y73,Y77,Y82)+SUMIFS(Aut_Ajustes_Manuais!$G:$G,Aut_Ajustes_Manuais!$I:$I,DRE!W$4,Aut_Ajustes_Manuais!$F:$F,"(-) Custos Eventos") -> -4337.45 | Z56: -600 | AA56: =SUM(AA57,AA60,AA65,AA73,AA77,AA82) -> -2423.4054 | AB56: =SUM(AB57,AB60,AB65,AB73,AB77,AB82)+SUMIFS(Aut_Ajustes_Manuais!$G:$G,Aut_Ajustes_Manuais!$I:$I,DRE!Z$4,Aut_Ajustes_Manuais!$F:$F,"(-) Custos Eventos") -> -600 | AC56: -600 | AD56: =SUM(AD57,AD60,AD65,AD73,AD77,AD82) -> -2456.9433 | AE56: =SUM(AE57,AE60,AE65,AE73,AE77,AE82)+SUMIFS(Aut_Ajustes_Manuais!$G:$G,Aut_Ajustes_Manuais!$I:$I,DRE!AC$4,Aut_Ajustes_Manuais!$F:$F,"(-) Custos Eventos") -> -600 | AF56: -600 | AG56: =SUM(AG57,AG60,AG65,AG73,AG77,AG82) -> -2398.1605 | AH56: =SUM(AH57,AH60,AH65,AH73,AH77,AH82)+SUMIFS(Aut_Ajustes_Manuais!$G:$G,Aut_Ajustes_Manuais!$I:$I,DRE!AF$4,Aut_Ajustes_Manuais!$F:$F,"(-) Custos Eventos") -> -600 | AI56: -600 | AJ56: =SUM(AJ57,AJ60,AJ65,AJ73,AJ77,AJ82) -> -2400.6721 | AK56: =SUM(AK57,AK60,AK65,AK73,AK77,AK82)+SUMIFS(Aut_Ajustes_Manuais!$G:$G,Aut_Ajustes_Manuais!$I:$I,DRE!AI$4,Aut_Ajustes_Manuais!$F:$F,"(-) Custos Eventos") -> -600 | AL56: -7893.5 | AM56: =SUM(AM57,AM60,AM65,AM73,AM77,AM82) -> -2464.977 | AN56: =SUM(AN57,AN60,AN65,AN73,AN77,AN82)+SUMIFS(Aut_Ajustes_Manuais!$G:$G,Aut_Ajustes_Manuais!$I:$I,DRE!AL$4,Aut_Ajustes_Manuais!$F:$F,"(-) Custos Eventos") -> -600 | AO56: -1192 | AP56: =SUM(AP57,AP60,AP65,AP73,AP77,AP82) -> -2420.857 | AQ56: =SUM(AQ57,AQ60,AQ65,AQ73,AQ77,AQ82)+SUMIFS(Aut_Ajustes_Manuais!$G:$G,Aut_Ajustes_Manuais!$I:$I,DRE!AO$4,Aut_Ajustes_Manuais!$F:$F,"(-) Custos Eventos") -> -600 | AR56: =SUM(AR57,AR60,AR65,AR73,AR77,AR82) -> -2090.5 | AS56: =SUM(AS57,AS60,AS65,AS73,AS77,AS82) -> -14206.27 | AT56: =SUM(AT57,AT60,AT65,AT73,AT77,AT82) -> -7337.45 | AU56: =SUM(AU57,AU60,AU65,AU73,AU77,AU82) -> -13576 | AV56: =SUM(AV57,AV60,AV65,AV73,AV77,AV82) -> -28771.285 | AW56: =SUM(AW57,AW60,AW65,AW73,AW77,AW82) -> -10937.45 | AX56: =SUM(AX57,AX60,AX65,AX73,AX77,AX82) -> -1290.5 | AY56: =SUM(AY57,AY60,AY65,AY73,AY77,AY82) -> -7005.4482 | ... BI56: =SUM(BI57,BI60,BI65,BI73,BI77,BI82) -> -1800 | BK56: =SUM(I56,L56,O56,R56,U56,X56,AA56,AD56,AG56,AJ56,AM56,AP56) -> -28771.285 | BL56: =BK56-AV56 -> 0 | BM56: =SUM(J56,M56,P56,S56,V56) -> -3000 | BN56: =BM56-AT56 -> 4337.45
A57: MDO | H57: -490.5 | I57: -2154.5925 | J57: =SUM(J58:J59)+SUMIFS(Aut_Ajustes_Manuais!$G:$G,Aut_Ajustes_Manuais!$I:$I,DRE!H$4,Aut_Ajustes_Manuais!$F:$F,"MDO") -> -600 | K57: -400 | L57: -2146.6746 | M57: =SUM(M58:M59)+SUMIFS(Aut_Ajustes_Manuais!$G:$G,Aut_Ajustes_Manuais!$I:$I,DRE!K$4,Aut_Ajustes_Manuais!$F:$F,"MDO") -> -600 | N57: -400 | O57: -2117.6697 | P57: =SUM(P58:P59)+SUMIFS(Aut_Ajustes_Manuais!$G:$G,Aut_Ajustes_Manuais!$I:$I,DRE!N$4,Aut_Ajustes_Manuais!$F:$F,"MDO") -> -600 | Q57: -400 | R57: -2122.4572 | S57: =SUM(S58:S59)+SUMIFS(Aut_Ajustes_Manuais!$G:$G,Aut_Ajustes_Manuais!$I:$I,DRE!Q$4,Aut_Ajustes_Manuais!$F:$F,"MDO") -> -600 | T57: -400 | U57: -2199.7774 | V57: =SUM(V58:V59)+SUMIFS(Aut_Ajustes_Manuais!$G:$G,Aut_Ajustes_Manuais!$I:$I,DRE!T$4,Aut_Ajustes_Manuais!$F:$F,"MDO") -> -600 | W57: 0 | X57: -2178.1078 | Y57: =SUM(Y58:Y59)+SUMIFS(Aut_Ajustes_Manuais!$G:$G,Aut_Ajustes_Manuais!$I:$I,DRE!W$4,Aut_Ajustes_Manuais!$F:$F,"MDO") -> -600 | Z57: -600 | AA57: -2176.4189 | AB57: =SUM(AB58:AB59)+SUMIFS(Aut_Ajustes_Manuais!$G:$G,Aut_Ajustes_Manuais!$I:$I,DRE!Z$4,Aut_Ajustes_Manuais!$F:$F,"MDO") -> -600 | AC57: -600 | AD57: -2190.393 | AE57: =SUM(AE58:AE59)+SUMIFS(Aut_Ajustes_Manuais!$G:$G,Aut_Ajustes_Manuais!$I:$I,DRE!AC$4,Aut_Ajustes_Manuais!$F:$F,"MDO") -> -600 | AF57: -600 | AG57: -2165.9002 | AH57: =SUM(AH58:AH59)+SUMIFS(Aut_Ajustes_Manuais!$G:$G,Aut_Ajustes_Manuais!$I:$I,DRE!AF$4,Aut_Ajustes_Manuais!$F:$F,"MDO") -> -600 | AI57: -600 | AJ57: -2166.9467 | AK57: =SUM(AK58:AK59)+SUMIFS(Aut_Ajustes_Manuais!$G:$G,Aut_Ajustes_Manuais!$I:$I,DRE!AI$4,Aut_Ajustes_Manuais!$F:$F,"MDO") -> -600 | AL57: -600 | AM57: -2193.7404 | AN57: =SUM(AN58:AN59)+SUMIFS(Aut_Ajustes_Manuais!$G:$G,Aut_Ajustes_Manuais!$I:$I,DRE!AL$4,Aut_Ajustes_Manuais!$F:$F,"MDO") -> -600 | AO57: -664 | AP57: -2175.3571 | AQ57: =SUM(AQ58:AQ59)+SUMIFS(Aut_Ajustes_Manuais!$G:$G,Aut_Ajustes_Manuais!$I:$I,DRE!AO$4,Aut_Ajustes_Manuais!$F:$F,"MDO") -> -600 | AR57: =SUMIFS($H57:$AO57,$H$5:$AO$5,"<"&MONTH(TODAY()),$H$6:$AO$6,"REAL 25") -> -2090.5 | AS57: =SUMIFS($I57:$AP57,$I$5:$AP$5,"<"&MONTH(TODAY()),$I$6:$AP$6,"ORÇADO ") -> -12919.279 | AT57: =SUMIFS($J57:$AQ57,$J$5:$AQ$5,"<"&MONTH(TODAY()),$J$6:$AQ$6,"REAL 26") -> -3600 | AU57: =SUM(AU58:AU59) -> -5754.5 | AV57: =SUM(AV58:AV59) -> -25988.036 | AW57: =SUM(AW58:AW59) -> -7200 | AX57: =SUM(AX58:AX59) -> -1290.5 | AY57: =SUM(AY58:AY59) -> -6418.9367 | AZ57: =SUM(AZ58:AZ59) -> -1800 | BA57: =SUM(BA58:BA59) -> -800 | BB57: =SUM(BB58:BB59) -> -6500.3424 | ... BI57: =SUM(BI58:BI59) -> -1800 | BK57: =SUM(I57,L57,O57,R57,U57,X57,AA57,AD57,AG57,AJ57,AM57,AP57) -> -25988.036 | BL57: =BK57-AV57 -> 0 | BM57: =SUM(J57,M57,P57,S57,V57) -> -3000 | BN57: =BM57-AT57 -> 600
A58: MDO Terceirizada - Eventos | C58: Equipe de Eventos | H58: -400 | I58: -2000 | J58: =SUMIFS(Aut_BlueMe_Sem_Pedido!$J:$J,Aut_BlueMe_Sem_Pedido!$H:$H,$A58,Aut_BlueMe_Sem_Pedido!$Q:$Q,DRE!H$4)+SUMIFS(Aut_BlueMe_Sem_Pedido!$J:$J,Aut_BlueMe_Sem_Pedido!$H:$H,"MDO PJ Fixo",Aut_BlueMe_Sem_Pedido!$Q:$Q,DRE!H$4,Aut_BlueMe_Sem_Pedido!$N:$N,$A58)+SUMIFS(Aut_Ajustes_Manuais!$G:$G,Aut_Ajustes_Manuais!$I:$I,DRE!H$4,Aut_Ajustes_Manuais!$F:$F,"MDO Terceirizada - Eventos") -> -600 | K58: -400 | L58: -2000 | M58: =SUMIFS(Aut_BlueMe_Sem_Pedido!$J:$J,Aut_BlueMe_Sem_Pedido!$H:$H,$A58,Aut_BlueMe_Sem_Pedido!$Q:$Q,DRE!K$4)+SUMIFS(Aut_BlueMe_Sem_Pedido!$J:$J,Aut_BlueMe_Sem_Pedido!$H:$H,"MDO PJ Fixo",Aut_BlueMe_Sem_Pedido!$Q:$Q,DRE!K$4,Aut_BlueMe_Sem_Pedido!$N:$N,$A58)+SUMIFS(Aut_Ajustes_Manuais!$G:$G,Aut_Ajustes_Manuais!$I:$I,DRE!K$4,Aut_Ajustes_Manuais!$F:$F,"MDO Terceirizada - Eventos") -> -600 | N58: -400 | O58: -2000 | P58: =SUMIFS(Aut_BlueMe_Sem_Pedido!$J:$J,Aut_BlueMe_Sem_Pedido!$H:$H,$A58,Aut_BlueMe_Sem_Pedido!$Q:$Q,DRE!N$4)+SUMIFS(Aut_BlueMe_Sem_Pedido!$J:$J,Aut_BlueMe_Sem_Pedido!$H:$H,"MDO PJ Fixo",Aut_BlueMe_Sem_Pedido!$Q:$Q,DRE!N$4,Aut_BlueMe_Sem_Pedido!$N:$N,$A58)+SUMIFS(Aut_Ajustes_Manuais!$G:$G,Aut_Ajustes_Manuais!$I:$I,DRE!N$4,Aut_Ajustes_Manuais!$F:$F,"MDO Terceirizada - Eventos") -> -600 | Q58: -400 | R58: -2000 | S58: =SUMIFS(Aut_BlueMe_Sem_Pedido!$J:$J,Aut_BlueMe_Sem_Pedido!$H:$H,$A58,Aut_BlueMe_Sem_Pedido!$Q:$Q,DRE!Q$4)+SUMIFS(Aut_BlueMe_Sem_Pedido!$J:$J,Aut_BlueMe_Sem_Pedido!$H:$H,"MDO PJ Fixo",Aut_BlueMe_Sem_Pedido!$Q:$Q,DRE!Q$4,Aut_BlueMe_Sem_Pedido!$N:$N,$A58)+SUMIFS(Aut_Ajustes_Manuais!$G:$G,Aut_Ajustes_Manuais!$I:$I,DRE!Q$4,Aut_Ajustes_Manuais!$F:$F,"MDO Terceirizada - Eventos") -> -600 | T58: -400 | U58: -2000 | V58: =SUMIFS(Aut_BlueMe_Sem_Pedido!$J:$J,Aut_BlueMe_Sem_Pedido!$H:$H,$A58,Aut_BlueMe_Sem_Pedido!$Q:$Q,DRE!T$4)+SUMIFS(Aut_BlueMe_Sem_Pedido!$J:$J,Aut_BlueMe_Sem_Pedido!$H:$H,"MDO PJ Fixo",Aut_BlueMe_Sem_Pedido!$Q:$Q,DRE!T$4,Aut_BlueMe_Sem_Pedido!$N:$N,$A58)+SUMIFS(Aut_Ajustes_Manuais!$G:$G,Aut_Ajustes_Manuais!$I:$I,DRE!T$4,Aut_Ajustes_Manuais!$F:$F,"MDO Terceirizada - Eventos") -> -600 | W58: 0 | X58: -2000 | Y58: =SUMIFS(Aut_BlueMe_Sem_Pedido!$J:$J,Aut_BlueMe_Sem_Pedido!$H:$H,$A58,Aut_BlueMe_Sem_Pedido!$Q:$Q,DRE!W$4)+SUMIFS(Aut_BlueMe_Sem_Pedido!$J:$J,Aut_BlueMe_Sem_Pedido!$H:$H,"MDO PJ Fixo",Aut_BlueMe_Sem_Pedido!$Q:$Q,DRE!W$4,Aut_BlueMe_Sem_Pedido!$N:$N,$A58)+SUMIFS(Aut_Ajustes_Manuais!$G:$G,Aut_Ajustes_Manuais!$I:$I,DRE!W$4,Aut_Ajustes_Manuais!$F:$F,"MDO Terceirizada - Eventos") -> -600 | Z58: -600 | AA58: -2000 | AB58: =SUMIFS(Aut_BlueMe_Sem_Pedido!$J:$J,Aut_BlueMe_Sem_Pedido!$H:$H,$A58,Aut_BlueMe_Sem_Pedido!$Q:$Q,DRE!Z$4)+SUMIFS(Aut_BlueMe_Sem_Pedido!$J:$J,Aut_BlueMe_Sem_Pedido!$H:$H,"MDO PJ Fixo",Aut_BlueMe_Sem_Pedido!$Q:$Q,DRE!Z$4,Aut_BlueMe_Sem_Pedido!$N:$N,$A58)+SUMIFS(Aut_Ajustes_Manuais!$G:$G,Aut_Ajustes_Manuais!$I:$I,DRE!Z$4,Aut_Ajustes_Manuais!$F:$F,"MDO Terceirizada - Eventos") -> -600 | AC58: -600 | AD58: -2000 | AE58: =SUMIFS(Aut_BlueMe_Sem_Pedido!$J:$J,Aut_BlueMe_Sem_Pedido!$H:$H,$A58,Aut_BlueMe_Sem_Pedido!$Q:$Q,DRE!AC$4)+SUMIFS(Aut_BlueMe_Sem_Pedido!$J:$J,Aut_BlueMe_Sem_Pedido!$H:$H,"MDO PJ Fixo",Aut_BlueMe_Sem_Pedido!$Q:$Q,DRE!AC$4,Aut_BlueMe_Sem_Pedido!$N:$N,$A58)+SUMIFS(Aut_Ajustes_Manuais!$G:$G,Aut_Ajustes_Manuais!$I:$I,DRE!AC$4,Aut_Ajustes_Manuais!$F:$F,"MDO Terceirizada - Eventos") -> -600 | AF58: -600 | AG58: -2000 | AH58: =SUMIFS(Aut_BlueMe_Sem_Pedido!$J:$J,Aut_BlueMe_Sem_Pedido!$H:$H,$A58,Aut_BlueMe_Sem_Pedido!$Q:$Q,DRE!AF$4)+SUMIFS(Aut_BlueMe_Sem_Pedido!$J:$J,Aut_BlueMe_Sem_Pedido!$H:$H,"MDO PJ Fixo",Aut_BlueMe_Sem_Pedido!$Q:$Q,DRE!AF$4,Aut_BlueMe_Sem_Pedido!$N:$N,$A58)+SUMIFS(Aut_Ajustes_Manuais!$G:$G,Aut_Ajustes_Manuais!$I:$I,DRE!AF$4,Aut_Ajustes_Manuais!$F:$F,"MDO Terceirizada - Eventos") -> -600 | AI58: -600 | AJ58: -2000 | AK58: =SUMIFS(Aut_BlueMe_Sem_Pedido!$J:$J,Aut_BlueMe_Sem_Pedido!$H:$H,$A58,Aut_BlueMe_Sem_Pedido!$Q:$Q,DRE!AI$4)+SUMIFS(Aut_BlueMe_Sem_Pedido!$J:$J,Aut_BlueMe_Sem_Pedido!$H:$H,"MDO PJ Fixo",Aut_BlueMe_Sem_Pedido!$Q:$Q,DRE!AI$4,Aut_BlueMe_Sem_Pedido!$N:$N,$A58)+SUMIFS(Aut_Ajustes_Manuais!$G:$G,Aut_Ajustes_Manuais!$I:$I,DRE!AI$4,Aut_Ajustes_Manuais!$F:$F,"MDO Terceirizada - Eventos") -> -600 | AL58: -600 | AM58: -2000 | AN58: =SUMIFS(Aut_BlueMe_Sem_Pedido!$J:$J,Aut_BlueMe_Sem_Pedido!$H:$H,$A58,Aut_BlueMe_Sem_Pedido!$Q:$Q,DRE!AL$4)+SUMIFS(Aut_BlueMe_Sem_Pedido!$J:$J,Aut_BlueMe_Sem_Pedido!$H:$H,"MDO PJ Fixo",Aut_BlueMe_Sem_Pedido!$Q:$Q,DRE!AL$4,Aut_BlueMe_Sem_Pedido!$N:$N,$A58)+SUMIFS(Aut_Ajustes_Manuais!$G:$G,Aut_Ajustes_Manuais!$I:$I,DRE!AL$4,Aut_Ajustes_Manuais!$F:$F,"MDO Terceirizada - Eventos") -> -600 | AO58: -600 | AP58: -2000 | AQ58: =SUMIFS(Aut_BlueMe_Sem_Pedido!$J:$J,Aut_BlueMe_Sem_Pedido!$H:$H,$A58,Aut_BlueMe_Sem_Pedido!$Q:$Q,DRE!AO$4)+SUMIFS(Aut_BlueMe_Sem_Pedido!$J:$J,Aut_BlueMe_Sem_Pedido!$H:$H,"MDO PJ Fixo",Aut_BlueMe_Sem_Pedido!$Q:$Q,DRE!AO$4,Aut_BlueMe_Sem_Pedido!$N:$N,$A58)+SUMIFS(Aut_Ajustes_Manuais!$G:$G,Aut_Ajustes_Manuais!$I:$I,DRE!AO$4,Aut_Ajustes_Manuais!$F:$F,"MDO Terceirizada - Eventos") -> -600 | AR58: =SUMIFS($H58:$AO58,$H$5:$AO$5,"<"&MONTH(TODAY()),$H$6:$AO$6,"REAL 25") -> -2000 | AS58: =SUMIFS($I58:$AP58,$I$5:$AP$5,"<"&MONTH(TODAY()),$I$6:$AP$6,"ORÇADO ") -> -12000 | AT58: =SUMIFS($J58:$AQ58,$J$5:$AQ$5,"<"&MONTH(TODAY()),$J$6:$AQ$6,"REAL 26") -> -3600 | AU58: =SUM(H58,K58,N58,Q58,T58,W58,Z58,AC58,AF58,AI58,AL58,AO58) -> -5600 | AV58: =SUM(I58,L58,O58,R58,U58,X58,AA58,AD58,AG58,AJ58,AM58,AP58) -> -24000 | AW58: =SUM(J58,M58,P58,S58,V58,Y58,AB58,AE58,AH58,AK58,AN58,AQ58) -> -7200 | AX58: =SUM(H58,K58,N58) -> -1200 | AY58: =SUM(I58,L58,O58) -> -6000 | AZ58: =SUM(J58,M58,P58) -> -1800 | BA58: =SUM(Q58,T58,W58) -> -800 | BB58: =SUM(R58,U58,X58) -> -6000 | BC58: =SUM(S58,V58,Y58) -> -1800 | BD58: =SUM(Z58,AC58,AF58) -> -1800 | BE58: =SUM(AA58,AD58,AG58) -> -6000 | BF58: =SUM(AB58,AE58,AH58) -> -1800 | BG58: =SUM(AI58,AL58,AO58) -> -1800 | BH58: =SUM(AJ58,AM58,AP58) -> -6000 | BI58: =SUM(AK58,AN58,AQ58) -> -1800 | BK58: =SUM(I58,L58,O58,R58,U58,X58,AA58,AD58,AG58,AJ58,AM58,AP58) -> -24000 | BL58: =BK58-AV58 -> 0 | BM58: =SUM(J58,M58,P58,S58,V58) -> -3000 | BN58: =BM58-AT58 -> 600
A59: Comissões de Vendas - Eventos | D59: % sobre o Faturamento de Eventos | E59: -0.02 | H59: -90.5 | I59: -154.59248 | J59: =SUMIFS(Aut_BlueMe_Sem_Pedido!$J:$J,Aut_BlueMe_Sem_Pedido!$Q:$Q,DRE!H$4,Aut_BlueMe_Sem_Pedido!$H:$H,DRE!$A59)+SUMIFS(Aut_Ajustes_Manuais!$G:$G,Aut_Ajustes_Manuais!$I:$I,DRE!H$4,Aut_Ajustes_Manuais!$F:$F,"Comissões de Vendas - Eventos") -> 0 | K59: 0 | L59: -146.67458 | M59: =SUMIFS(Aut_BlueMe_Sem_Pedido!$J:$J,Aut_BlueMe_Sem_Pedido!$Q:$Q,DRE!K$4,Aut_BlueMe_Sem_Pedido!$H:$H,DRE!$A59)+SUMIFS(Aut_Ajustes_Manuais!$G:$G,Aut_Ajustes_Manuais!$I:$I,DRE!K$4,Aut_Ajustes_Manuais!$F:$F,"Comissões de Vendas - Eventos") -> 0 | N59: 0 | O59: -117.66968 | P59: =SUMIFS(Aut_BlueMe_Sem_Pedido!$J:$J,Aut_BlueMe_Sem_Pedido!$Q:$Q,DRE!N$4,Aut_BlueMe_Sem_Pedido!$H:$H,DRE!$A59)+SUMIFS(Aut_Ajustes_Manuais!$G:$G,Aut_Ajustes_Manuais!$I:$I,DRE!N$4,Aut_Ajustes_Manuais!$F:$F,"Comissões de Vendas - Eventos") -> 0 | Q59: 0 | R59: -122.45719 | S59: =SUMIFS(Aut_BlueMe_Sem_Pedido!$J:$J,Aut_BlueMe_Sem_Pedido!$Q:$Q,DRE!Q$4,Aut_BlueMe_Sem_Pedido!$H:$H,DRE!$A59)+SUMIFS(Aut_Ajustes_Manuais!$G:$G,Aut_Ajustes_Manuais!$I:$I,DRE!Q$4,Aut_Ajustes_Manuais!$F:$F,"Comissões de Vendas - Eventos") -> 0 | T59: 0 | U59: -199.77741 | V59: =SUMIFS(Aut_BlueMe_Sem_Pedido!$J:$J,Aut_BlueMe_Sem_Pedido!$Q:$Q,DRE!T$4,Aut_BlueMe_Sem_Pedido!$H:$H,DRE!$A59)+SUMIFS(Aut_Ajustes_Manuais!$G:$G,Aut_Ajustes_Manuais!$I:$I,DRE!T$4,Aut_Ajustes_Manuais!$F:$F,"Comissões de Vendas - Eventos") -> 0 | W59: 0 | X59: -178.10785 | Y59: =SUMIFS(Aut_BlueMe_Sem_Pedido!$J:$J,Aut_BlueMe_Sem_Pedido!$Q:$Q,DRE!W$4,Aut_BlueMe_Sem_Pedido!$H:$H,DRE!$A59)+SUMIFS(Aut_Ajustes_Manuais!$G:$G,Aut_Ajustes_Manuais!$I:$I,DRE!W$4,Aut_Ajustes_Manuais!$F:$F,"Comissões de Vendas - Eventos") -> 0 | Z59: 0 | AA59: -176.41894 | AB59: =SUMIFS(Aut_BlueMe_Sem_Pedido!$J:$J,Aut_BlueMe_Sem_Pedido!$Q:$Q,DRE!Z$4,Aut_BlueMe_Sem_Pedido!$H:$H,DRE!$A59)+SUMIFS(Aut_Ajustes_Manuais!$G:$G,Aut_Ajustes_Manuais!$I:$I,DRE!Z$4,Aut_Ajustes_Manuais!$F:$F,"Comissões de Vendas - Eventos") -> 0 | AC59: 0 | AD59: -190.39302 | AE59: =SUMIFS(Aut_BlueMe_Sem_Pedido!$J:$J,Aut_BlueMe_Sem_Pedido!$Q:$Q,DRE!AC$4,Aut_BlueMe_Sem_Pedido!$H:$H,DRE!$A59)+SUMIFS(Aut_Ajustes_Manuais!$G:$G,Aut_Ajustes_Manuais!$I:$I,DRE!AC$4,Aut_Ajustes_Manuais!$F:$F,"Comissões de Vendas - Eventos") -> 0 | AF59: 0 | AG59: -165.9002 | AH59: =SUMIFS(Aut_BlueMe_Sem_Pedido!$J:$J,Aut_BlueMe_Sem_Pedido!$Q:$Q,DRE!AF$4,Aut_BlueMe_Sem_Pedido!$H:$H,DRE!$A59)+SUMIFS(Aut_Ajustes_Manuais!$G:$G,Aut_Ajustes_Manuais!$I:$I,DRE!AF$4,Aut_Ajustes_Manuais!$F:$F,"Comissões de Vendas - Eventos") -> 0 | AI59: 0 | AJ59: -166.94669 | AK59: =SUMIFS(Aut_BlueMe_Sem_Pedido!$J:$J,Aut_BlueMe_Sem_Pedido!$Q:$Q,DRE!AI$4,Aut_BlueMe_Sem_Pedido!$H:$H,DRE!$A59)+SUMIFS(Aut_Ajustes_Manuais!$G:$G,Aut_Ajustes_Manuais!$I:$I,DRE!AI$4,Aut_Ajustes_Manuais!$F:$F,"Comissões de Vendas - Eventos") -> 0 | AL59: 0 | AM59: -193.74044 | AN59: =SUMIFS(Aut_BlueMe_Sem_Pedido!$J:$J,Aut_BlueMe_Sem_Pedido!$Q:$Q,DRE!AL$4,Aut_BlueMe_Sem_Pedido!$H:$H,DRE!$A59)+SUMIFS(Aut_Ajustes_Manuais!$G:$G,Aut_Ajustes_Manuais!$I:$I,DRE!AL$4,Aut_Ajustes_Manuais!$F:$F,"Comissões de Vendas - Eventos") -> 0 | AO59: -64 | AP59: -175.35707 | AQ59: =SUMIFS(Aut_BlueMe_Sem_Pedido!$J:$J,Aut_BlueMe_Sem_Pedido!$Q:$Q,DRE!AO$4,Aut_BlueMe_Sem_Pedido!$H:$H,DRE!$A59)+SUMIFS(Aut_Ajustes_Manuais!$G:$G,Aut_Ajustes_Manuais!$I:$I,DRE!AO$4,Aut_Ajustes_Manuais!$F:$F,"Comissões de Vendas - Eventos") -> 0 | AR59: =SUMIFS($H59:$AO59,$H$5:$AO$5,"<"&MONTH(TODAY()),$H$6:$AO$6,"REAL 25") -> -90.5 | AS59: =SUMIFS($I59:$AP59,$I$5:$AP$5,"<"&MONTH(TODAY()),$I$6:$AP$6,"ORÇADO ") -> -919.27919 | AT59: =SUMIFS($J59:$AQ59,$J$5:$AQ$5,"<"&MONTH(TODAY()),$J$6:$AQ$6,"REAL 26") -> 0 | AU59: =SUM(H59,K59,N59,Q59,T59,W59,Z59,AC59,AF59,AI59,AL59,AO59) -> -154.5 | AV59: =SUM(I59,L59,O59,R59,U59,X59,AA59,AD59,AG59,AJ59,AM59,AP59) -> -1988.0355 | AW59: =SUM(J59,M59,P59,S59,V59,Y59,AB59,AE59,AH59,AK59,AN59,AQ59) -> 0 | AX59: =SUM(H59,K59,N59) -> -90.5 | AY59: =SUM(I59,L59,O59) -> -418.93674 | AZ59: =SUM(J59,M59,P59) -> 0 | BA59: =SUM(Q59,T59,W59) -> 0 | BB59: =SUM(R59,U59,X59) -> -500.34245 | BC59: =SUM(S59,V59,Y59) -> 0 | BD59: =SUM(Z59,AC59,AF59) -> 0 | BE59: =SUM(AA59,AD59,AG59) -> -532.71216 | BF59: =SUM(AB59,AE59,AH59) -> 0 | BG59: =SUM(AI59,AL59,AO59) -> -64 | BH59: =SUM(AJ59,AM59,AP59) -> -536.04419 | BI59: =SUM(AK59,AN59,AQ59) -> 0 | BK59: =SUM(I59,L59,O59,R59,U59,X59,AA59,AD59,AG59,AJ59,AM59,AP59) -> -1988.0355 | BL59: =BK59-AV59 -> 0 | BM59: =SUM(J59,M59,P59,S59,V59) -> 0 | BN59: =BM59-AT59 -> 0
